Workbook

Sheet Intro
E15: YY ASSURANCE COMPANY LIMITED
E16: Group Life Insurance Business
E17: LRC Analysis
G20: Start Date | H20: 44197
G21: Valuation Date | H21: 45657

Sheet GWP
C3: Summary of Gross Written Premium
C4: Class of Business | D4: 2021 | E4: 2022 | F4: 2023 | G4: 2024
C5: Group Life | D5: 3330769.2 | E5: 3697153.8 | F5: 4251726.9 | G5: 4330000
C6: Group Credit | D6: 4038461.5 | E6: 4482692.3 | F6: 5155096.2 | G6: 5250000
C7: Group Last Expense | D7: 3738461.5 | E7: 4149692.3 | F7: 4772146.2 | G7: 4860000
C8: Total | D8: =SUM(D5:D7) -> 11107692 | E8: =SUM(E5:E7) -> 12329538 | F8: =SUM(F5:F7) -> 14178969 | G8: =SUM(G5:G7) -> 14440000

Sheet Premium Receivables
C3: Summary of Premium Receivables
C4: Class of Business | D4: 2021 | E4: 2022 | F4: 2023 | G4: 2024
C5: Group Life | D5: 666153.85 | E5: 739430.77 | F5: 850345.38 | G5: 866000
C6: Group Credit | D6: 807692.31 | E6: 896538.46 | F6: 1031019.2 | G6: 1050000
C7: Group Last Expense | D7: 747692.31 | E7: 829938.46 | F7: 954429.23 | G7: 972000
C8: Total | D8: =SUM(D5:D7) -> 2221538.5 | E8: =SUM(E5:E7) -> 2465907.7 | F8: =SUM(F5:F7) -> 2835793.8 | G8: =SUM(G5:G7) -> 2888000

Sheet DAC
C3: Summary of Deferred Acquisition Costs
C4: Class of Business | D4: 2021 | E4: 2022 | F4: 2023 | G4: 2024
C5: Group Life | D5: 166538.46 | E5: 184857.69 | F5: 212586.35 | G5: 216500
C6: Group Credit | D6: 201923.08 | E6: 224134.62 | F6: 257754.81 | G6: 262500
C7: Group Last Expense | D7: 186923.08 | E7: 207484.62 | F7: 238607.31 | G7: 243000
C8: Total | D8: =SUM(D5:D7) -> 555384.62 | E8: =SUM(E5:E7) -> 616476.92 | F8: =SUM(F5:F7) -> 708948.46 | G8: =SUM(G5:G7) -> 722000

Sheet UPR
C3: Summary of Unearned Premium Reserve
C4: Class of Business | D4: 2021 | E4: 2022 | F4: 2023 | G4: 2024
C5: Group Life | D5: 1110256.4 | E5: 1232384.6 | F5: 1417242.3 | G5: 1443333.3
C6: Group Credit | D6: 1346153.8 | E6: 1494230.8 | F6: 1718365.4 | G6: 1750000
C7: Group Last Expense | D7: 1246153.8 | E7: 1383230.8 | F7: 1590715.4 | G7: 1620000
C8: Total | D8: =SUM(D5:D7) -> 3702564.1 | E8: =SUM(E5:E7) -> 4109846.2 | F8: =SUM(F5:F7) -> 4726323.1 | G8: =SUM(G5:G7) -> 4813333.3

Sheet LRC
B5: YY Assurance Company Limited Summary of LRC as at 31 December 2021
B6: Class | C6: UPR | D6: DAC | E6: Premium Receivables as at 31 Dec 2021 | F6: Closing LRC
B7: Group Life | C7: =UPR!D5 -> 1110256.4 | D7: =DAC!D5 -> 166538.46 | E7: ='Premium Receivables'!D5 -> 666153.85 | F7: =C7-D7-E7 -> 277564.1
B8: Group Credit | C8: =UPR!D6 -> 1346153.8 | D8: =DAC!D6 -> 201923.08 | E8: ='Premium Receivables'!D6 -> 807692.31 | F8: =C8-D8-E8 -> 336538.46
B9: Group Last Expense | C9: =UPR!D7 -> 1246153.8 | D9: =DAC!D7 -> 186923.08 | E9: ='Premium Receivables'!D7 -> 747692.31 | F9: =C9-D9-E9 -> 311538.46
B10: Grand Total | C10: =SUM(C7:C8) -> 2456410.3 | D10: =SUM(D7:D8) -> 368461.54 | E10: =SUM(E7:E8) -> 1473846.2 | F10: =SUM(F7:F8) -> 614102.56
B14: YY Assurance Company Limited Summary of LRC as at 31 December 2022
B15: Class | C15: Opening LRC | D15: GWP 2022 | E15: Premium Receivables as at 31 Dec 2021 | F15: Premium Receivables as at 31 Dec 2022 | G15: Premium Received for the year | H15: Earned Premium for the year | I15: Change in DAC | J15: Closing LRC
B16: Group Life | C16: =F7 -> 277564.1 | D16: =GWP!E5 -> 3697153.8 | E16: =E7 -> 666153.85 | F16: ='Premium Receivables'!E5 -> 739430.77 | G16: =D16+E16-F16 -> 3623876.9 | H16: =GWP!E5-(UPR!E5-UPR!D5) -> 3575025.6 | I16: =DAC!E5-DAC!D5 -> 18319.231 | J16: =C16+G16-H16-I16 -> 308096.15
B17: Group Credit | C17: =F8 -> 336538.46 | D17: =GWP!E6 -> 4482692.3 | E17: =E8 -> 807692.31 | F17: ='Premium Receivables'!E6 -> 896538.46 | G17: =D17+E17-F17 -> 4393846.2 | H17: =GWP!E6-(UPR!E6-UPR!D6) -> 4334615.4 | I17: =DAC!E6-DAC!D6 -> 22211.538 | J17: =C17+G17-H17-I17 -> 373557.69
B18: Group Last Expense | C18: =F9 -> 311538.46 | D18: =GWP!E7 -> 4149692.3 | E18: =E9 -> 747692.31 | F18: ='Premium Receivables'!E7 -> 829938.46 | G18: =D18+E18-F18 -> 4067446.2 | H18: =GWP!E7-(UPR!E7-UPR!D7) -> 4012615.4 | I18: =DAC!E7-DAC!D7 -> 20561.538 | J18: =C18+G18-H18-I18 -> 345807.69
B19: Grand Total | C19: =SUM(C16:C17) -> 614102.56 | D19: =SUM(D16:D18) -> 12329538 | E19: =SUM(E16:E18) -> 2221538.5 | F19: =SUM(F16:F18) -> 2465907.7 | G19: =SUM(G16:G17) -> 8017723.1 | H19: =SUM(H16:H17) -> 7909641 | I19: =SUM(I16:I17) -> 40530.769 | J19: =SUM(J16:J17) -> 681653.85
B22: YY Assurance Company Limited Summary of LRC as at 31 December 2023
B23: Class | C23: Opening LRC | D23: GWP 2023 | E23: Premium Receivables as at 31 Dec 2022 | F23: Premium Receivables as at 31 Dec 2023 | G23: Premium Received for the year | H23: Earned Premium for the year | I23: Change in DAC | J23: Closing LRC
B24: Group Life | C24: =J16 -> 308096.15 | D24: =GWP!F5 -> 4251726.9 | E24: =F16 -> 739430.77 | F24: ='Premium Receivables'!F5 -> 850345.38 | G24: =D24+E24-F24 -> 4140812.3 | H24: =GWP!F5-(UPR!F5-UPR!E5) -> 4066869.2 | I24: =DAC!F5-DAC!E5 -> 27728.654 | J24: =C24+G24-H24-I24 -> 354310.58
B25: Group Credit | C25: =J17 -> 373557.69 | D25: =GWP!F6 -> 5155096.2 | E25: =F17 -> 896538.46 | F25: ='Premium Receivables'!F6 -> 1031019.2 | G25: =D25+E25-F25 -> 5020615.4 | H25: =GWP!F6-(UPR!F6-UPR!E6) -> 4930961.5 | I25: =DAC!F6-DAC!E6 -> 33620.192 | J25: =C25+G25-H25-I25 -> 429591.35
B26: Group Last Expense | C26: =J18 -> 345807.69 | D26: =GWP!F7 -> 4772146.2 | E26: =F18 -> 829938.46 | F26: ='Premium Receivables'!F7 -> 954429.23 | G26: =D26+E26-F26 -> 4647655.4 | H26: =GWP!F7-(UPR!F7-UPR!E7) -> 4564661.5 | I26: =DAC!F7-DAC!E7 -> 31122.692 | J26: =C26+G26-H26-I26 -> 397678.85
B27: Grand Total | C27: =SUM(C24:C25) -> 681653.85 | D27: =SUM(D24:D26) -> 14178969 | E27: =SUM(E24:E26) -> 2465907.7 | F27: =SUM(F24:F26) -> 2835793.8 | G27: =SUM(G24:G25) -> 9161427.7 | H27: =SUM(H24:H25) -> 8997830.8 | I27: =SUM(I24:I25) -> 61348.846 | J27: =SUM(J24:J25) -> 783901.92
B30: YY Assurance Company Limited Summary of LRC as at 31 December 2024
B31: Class | C31: Opening LRC | D31: GWP 2024 | E31: Premium Receivables as at 31 Dec 2023 | F31: Premium Receivables as at 31 Dec 2024 | G31: Premium Received for the year | H31: Earned Premium for the year | I31: Change in DAC | J31: Closing LRC
B32: Group Life | C32: =J24 -> 354310.58 | D32: =GWP!G5 -> 4330000 | E32: =F24 -> 850345.38 | F32: ='Premium Receivables'!G5 -> 866000 | G32: =D32+E32-F32 -> 4314345.4 | H32: =GWP!G5-(UPR!G5-UPR!F5) -> 4303909 | I32: =DAC!G5-DAC!F5 -> 3913.6538 | J32: =C32+G32-H32-I32 -> 360833.33
B33: Group Credit | C33: =J25 -> 429591.35 | D33: =GWP!G6 -> 5250000 | E33: =F25 -> 1031019.2 | F33: ='Premium Receivables'!G6 -> 1050000 | G33: =D33+E33-F33 -> 5231019.2 | H33: =GWP!G6-(UPR!G6-UPR!F6) -> 5218365.4 | I33: =DAC!G6-DAC!F6 -> 4745.1923 | J33: =C33+G33-H33-I33 -> 437500
B34: Group Last Expense | C34: =J26 -> 397678.85 | D34: =GWP!G7 -> 4860000 | E34: =F26 -> 954429.23 | F34: ='Premium Receivables'!G7 -> 972000 | G34: =D34+E34-F34 -> 4842429.2 | H34: =GWP!G7-(UPR!G7-UPR!F7) -> 4830715.4 | I34: =DAC!G7-DAC!F7 -> 4392.6923 | J34: =C34+G34-H34-I34 -> 405000
B35: Grand Total | C35: =SUM(C32:C33) -> 783901.92 | D35: =SUM(D32:D34) -> 14440000 | E35: =SUM(E32:E34) -> 2835793.8 | F35: =SUM(F32:F34) -> 2888000 | G35: =SUM(G32:G33) -> 9545364.6 | H35: =SUM(H32:H33) -> 9522274.4 | I35: =SUM(I32:I33) -> 8658.8462 | J35: =SUM(J32:J33) -> 798333.33
B39: Use Net figures/ retention rates to compute Net LRC
