Workbook

Sheet Intro
C11: Company Logo
C17: KAFS Training LTD Limited
D19: Discounting Model for Claim Liabilities
D22: Start Date | E22: 43101
D23: Valuation Date | E23: 45657
B29: Updates
B30: NSE Yield Curve
B31: Added ROI
B32: Updated the Piad DF's from Incurred to Paid to Reported to Paid
B45: Class Codes
C47: Quarterly | E47: Annually
B48: Business Class | C48: Qrt Adjusted Triangles | D48: Qrt Actual Triangles | E48: Ann Adjusted Triangles | F48: Ann Actual Triangles
B49: Aviation | C49: AVI_ADJ_QRT_TRI | D49: AVI_ACT_QRT_TRI | E49: AVI_ADJ_ANN_TRI | F49: AVI_ACT_ANN_TRI
B50: Engineering | C50: ENG_ADJ_QRT_TRI | D50: ENG_ACT_QRT_TRI | E50: ENG_ADJ_ANN_TRI | F50: ENG_ACT_ANN_TRI
B51: Fire Domestic | C51: FD_ADJ_QRT_TRI | D51: FD_ACT_QRT_TRI | E51: FD_ADJ_ANN_TRI | F51: FD_ACT_ANN_TRI
B52: Fire Industrial | C52: FI_ADJ_QRT_TRI | D52: FI_ACT_QRT_TRI | E52: FI_ADJ_ANN_TRI | F52: FI_ACT_ANN_TRI
B53: Liability | C53: LIA_ADJ_QRT_TRI | D53: LIA_ACT_QRT_TRI | E53: LIA_ADJ_ANN_TRI | F53: LIA_ACT_ANN_TRI
B54: Marine | C54: MAR_ADJ_QRT_TRI | D54: MAR_ACT_QRT_TRI | E54: MAR_ADJ_ANN_TRI | F54: MAR_ACT_ANN_TRI
B55: Miscellaneous | C55: MISC_ADJ_QRT_TRI | D55: MISC_ACT_QRT_TRI | E55: MISC_ADJ_ANN_TRI | F55: MISC_ACT_ANN_TRI
B56: Motor Commercial | C56: MC_ADJ_QRT_TRI | D56: MC_ACT_QRT_TRI | E56: MC_ADJ_ANN_TRI | F56: MC_ACT_ANN_TRI
B57: Motor Commercial-PSV | C57: MCPSV_ADJ_QRT_TRI | D57: MCPSV_ACT_QRT_TRI | E57: MCPSV_ADJ_ANN_TRI | F57: MCPSV_ACT_ANN_TRI
B58: Motor Private | C58: MP_ADJ_QRT_TRI | D58: MP_ACT_QRT_TRI | E58: MP_ADJ_ANN_TRI | F58: MP_ACT_ANN_TRI
B59: Personal Accident | C59: PA_ADJ_QRT_TRI | D59: PA_ACT_QRT_TRI | E59: PA_ADJ_ANN_TRI | F59: PA_ACT_ANN_TRI
... B61: Workmen’s Compensation | C61: WIBA_ADJ_QRT_TRI | D61: WIBA_ACT_QRT_TRI | E61: WIBA_ADJ_ANN_TRI | F61: WIBA_ACT_ANN_TRI
B66: Row Labels | C66: Average of Reporting Delay | D66: Days
B67: Engineering | D67: =C67*30*3 -> 0
B68: Fire Domestic | D68: =C68*30*3 -> 0
B69: Fire Industrial | D69: =C69*30*3 -> 0
B70: Liability | D70: =C70*30*3 -> 0
B71: Marine | D71: =C71*30*3 -> 0
B72: Miscellaneous | D72: =C72*30*3 -> 0
B73: Motor Commercial | D73: =C73*30*3 -> 0
B74: Motor Commercial-PSV | D74: =C74*30*3 -> 0
B75: Motor Private | D75: =C75*30*3 -> 0
B76: Personal Accident | D76: =C76*30*3 -> 0
B77: Theft | D77: =C77*30*3 -> 0
B78: Workmen’s Compensation | D78: =C78*30*3 -> 0
B79: Grand Total | D79: =C79*30*3 -> 0

Sheet IBNR
G5: Aviation | H5: Engineering | I5: Fire Domestic | J5: Fire Industrial | K5: Liability | L5: Marine | M5: Miscellaneous | N5: Motor Commercial | O5: Motor Commercial PSV | P5: Motor Private | Q5: Personal Accident | R5: Theft | S5: Workmen's Compensation
F6: Loss_Yr_Loss_Qtr | G6: AVI | H6: ENG | I6: FD | J6: FI | K6: LIA | L6: MAR | M6: MISC | N6: MC | O6: MCPSV | P6: MP | Q6: PA | R6: THEFT | S6: WIBA
F7: 2018Q1 | G7: 0 | H7: 3.3892386e-09 | I7: 0 | J7: 2.2178352e-08 | K7: 2.3702478e-10 | L7: 0 | M7: 0 | N7: 2923638.1 | O7: 2.2466999e-08 | P7: 1259942.2 | Q7: 0 | R7: 0 | S7: 51598.825
F8: 2018Q2 | G8: 0 | H8: 2.2090339e-09 | I8: 0 | J8: 5.6009666e-08 | K8: 4.4442147e-11 | L8: 0 | M8: 0 | N8: 386940.44 | O8: 2.7714427e-08 | P8: 245718.16 | Q8: 0 | R8: 0 | S8: 70075.861
F9: 2018Q3 | G9: 0 | H9: 0 | I9: 0 | J9: 2.2178352e-08 | K9: 1.8961983e-09 | L9: 0 | M9: 0 | N9: 598722.67 | O9: 2.2466999e-08 | P9: 255542.62 | Q9: 0 | R9: 0 | S9: 82925.158
F10: 2018Q4 | G10: 0 | H10: 0 | I10: 0 | J10: 2.2178352e-08 | K10: 8.8884293e-11 | L10: 0 | M10: 0 | N10: 632053.26 | O10: 2.2698269e-08 | P10: 395362.61 | Q10: 0 | R10: 0 | S10: 53920.584
F11: 2019Q1 | G11: 0 | H11: 0 | I11: 0 | J11: 9.1195113e-09 | K11: 1.7776859e-10 | L11: 0 | M11: 0 | N11: 697884.44 | O11: 1.8867315e-08 | P11: 487827.46 | Q11: 0 | R11: 0 | S11: 27944.836
F12: 2019Q2 | G12: 0 | H12: 0 | I12: 0 | J12: 7.9457054e-09 | K12: 0 | L12: 0 | M12: 0 | N12: 865008.49 | O12: 1.3246513e-08 | P12: 487827.46 | Q12: 0 | R12: 0 | S12: 53813.701
F13: 2019Q3 | G13: 0 | H13: 0 | I13: 0 | J13: 7.9457054e-09 | K13: 4.7404956e-10 | L13: 0 | M13: 0 | N13: 781153.91 | O13: 1.3847656e-08 | P13: 574168.67 | Q13: 0 | R13: 0 | S13: 30929.959
F14: 2019Q4 | G14: 0 | H14: 0 | I14: 0 | J14: 1.7601958e-08 | K14: 0 | L14: 0 | M14: 0 | N14: 923633.21 | O14: 1.3246513e-08 | P14: 549089.68 | Q14: 0 | R14: 0 | S14: 93355.124
F15: 2020Q1 | G15: 0 | H15: 0 | I15: 0 | J15: 1.3349376e-08 | K15: 1.8517561e-12 | L15: 0 | M15: 0 | N15: 471105.12 | O15: 3.2082793e-09 | P15: 395148.04 | Q15: 0 | R15: 0 | S15: 89699.414
F16: 2020Q2 | G16: 0 | H16: 0 | I16: 0 | J16: 2.3635352e-08 | K16: 3095.1111 | L16: 0 | M16: 0 | N16: 572102.62 | O16: 1.7072903e-09 | P16: 355926.18 | Q16: 0 | R16: 0 | S16: 15676.928
F17: 2020Q3 | G17: 0 | H17: 0 | I17: 0 | J17: 1.3349376e-08 | K17: 21521.836 | L17: 0 | M17: 0 | N17: 675800.57 | O17: 1.7072903e-09 | P17: 394360.92 | Q17: 0 | R17: 0 | S17: 99783.655
F18: 2020Q4 | G18: 0 | H18: 0 | I18: 0 | J18: 1.3349376e-08 | K18: 14265.297 | L18: 0 | M18: 0 | N18: 790340.4 | O18: 1.7072903e-09 | P18: 403710.43 | Q18: 9420.3877 | R18: 0 | S18: 50388.302
... F34: 2024Q4 | G34: 0 | H34: 2374900.1 | I34: 137825.8 | J34: 649496.7 | K34: 1286705.4 | L34: 3315151.7 | M34: 0 | N34: 7751299.6 | O34: 351210.15 | P34: 8314477.3 | Q34: 487096.83 | R34: 1994941.1 | S34: 6119893.7
H35: =SUM(H7:H34) -> 7700615.5 | I35: =SUM(I7:I34) -> 1157549.9 | J35: =SUM(J7:J34) -> 1313156.5 | K35: =SUM(K7:K34) -> 5117447.9 | L35: =SUM(L7:L34) -> 13257199 | M35: =SUM(M7:M34) -> 8180170.2 | N35: =SUM(N7:N34) -> 50252154 | O35: =SUM(O7:O34) -> 1432701.8 | ... S35: =SUM(S7:S34) -> 44641183 | T35: =SUM(H35:S35) -> 1.8820111e+08

Sheet OCR
D2: Aviation | E2: Engineering | F2: Fire Domestic | G2: Fire Industrial | H2: Liability | I2: Marine | J2: Miscellaneous | K2: Motor Commercial | L2: Motor Commercial PSV | M2: Motor Private | N2: Personal Accident | O2: Theft | P2: Workmen's Compensation
C3: Loss_Yr_Loss_Qtr | D3: AVI | E3: ENG | F3: FD | G3: FI | H3: LIA | I3: MAR | J3: MISC | K3: MC | L3: MC PSV | M3: MP | N3: PA | O3: THEFT | P3: WIBA
C4: 2018Q1 | D4: 0 | E4: 600600 | F4: 0 | G4: 2200000 | H4: 6461708 | I4: 4331547 | J4: 78925 | K4: 1.0501682e+08 | L4: 2702337 | M4: 36493848 | N4: 31812 | O4: 1834652.6 | P4: 62052653
C5: 2018Q2 | D5: 0 | E5: 172496.5 | F5: 0 | G5: 0 | H5: 165000 | I5: 337790.2 | J5: 0 | K5: 2104645.4 | L5: 2047769.9 | M5: 2046627 | N5: 0 | O5: 3432110 | P5: 3747554.8
C6: 2018Q3 | D6: 0 | E6: 0 | F6: 112200 | G6: 0 | H6: 110000 | I6: 22292.6 | J6: 0 | K6: 6424642.4 | L6: 935001.1 | M6: 6207851.1 | N6: 0 | O6: 15740175 | P6: 600845.3
C7: 2018Q4 | D7: 0 | E7: 0 | F7: 0 | G7: 0 | H7: 0 | I7: 0 | J7: 0 | K7: 7346598.6 | L7: 538637 | M7: 2929203.2 | N7: 0 | O7: 3007779.5 | P7: 550000
C8: 2019Q1 | D8: 0 | E8: 0 | F8: 0 | G8: 0 | H8: 220000 | I8: 4005169.3 | J8: 0 | K8: 9158690.2 | L8: 1583901 | M8: 6774208.1 | N8: 0 | O8: 2338839.8 | P8: 2989404
C9: 2019Q2 | D9: 0 | E9: 0 | F9: 0 | G9: 1650000 | H9: 0 | I9: 0 | J9: 0 | K9: 4590228.5 | L9: 895207.5 | M9: 7712479.5 | N9: 0 | O9: 198000 | P9: 1138500
C10: 2019Q3 | D10: 0 | E10: 0 | F10: 0 | G10: 0 | H10: 0 | I10: 0 | J10: 0 | K10: 5612289.1 | L10: 689129.1 | M10: 12526027 | N10: 0 | O10: 3543569.7 | P10: 1100000
C11: 2019Q4 | D11: 0 | E11: 1142603 | F11: 0 | G11: 0 | H11: 1760000 | I11: 0 | J11: 0 | K11: 13467370 | L11: 1354788.6 | M11: 9869184.6 | N11: 0 | O11: 767069.6 | P11: 2181841.2
C12: 2020Q1 | D12: 0 | E12: 10386638 | F12: 0 | G12: 0 | H12: 0 | I12: 0 | J12: 0 | K12: 7069901.3 | L12: 1272920 | M12: 11134955 | N12: 0 | O12: 499959.9 | P12: 1045000
C13: 2020Q2 | D13: 0 | E13: 0 | F13: 0 | G13: 0 | H13: 0 | I13: 0 | J13: 0 | K13: 6121767.3 | L13: 0 | M13: 6259267.3 | N13: 0 | O13: 550000 | P13: 1231593
C14: 2020Q3 | D14: 0 | E14: 0 | F14: 0 | G14: 110000 | H14: 220000 | I14: 0 | J14: 1100000 | K14: 9763216.1 | L14: 0 | M14: 9731482.2 | N14: 0 | O14: 4426440.7 | P14: 2109599.8
C15: 2020Q4 | D15: 0 | E15: 2553160.5 | F15: 0 | G15: 0 | H15: 874500 | I15: 0 | J15: 0 | K15: 9403182.8 | L15: 0 | M15: 16286755 | N15: 0 | O15: 86427 | P15: 1766880.5
... C31: 2024Q4 | D31: 0 | E31: 9109304.6 | F31: 637407.1 | G31: 1100000 | H31: 14190000 | I31: 14429500 | J31: 99000 | K31: 74134234 | L31: 5280000 | M31: 1.5023753e+08 | N31: 0 | O31: 11430392 | P31: 8250002.2
C32: Grand Total | D32: =SUM(D4:D31) -> 0 | E32: =SUM(E4:E31) -> 1.1501912e+08 | F32: =SUM(F4:F31) -> 50306108 | G32: =SUM(G4:G31) -> 1.3338408e+08 | H32: =SUM(H4:H31) -> 1.4532053e+08 | I32: =SUM(I4:I31) -> 1.5486418e+08 | J32: =SUM(J4:J31) -> 17023875 | K32: =SUM(K4:K31) -> 7.0241946e+08 | ... P32: =SUM(P4:P31) -> 2.7436158e+08 | Q32: =SUM(D32:P32) -> 2.6513434e+09
Q35: =Q32+IBNR!T35 -> 2.8395445e+09

Sheet NSE_Yield_Curve
B8: NSE Yield Curve as at 31 December 2024
B10: t | C10: FY 24 | D10: H1 24 | E10: FY 23 | F10: FY_24 | G10: Revised NSE | W10: t | X10: 2017 | Y10: =X10+1 -> 2018 | Z10: =Y10+1 -> 2019 | AA10: =Z10+1 -> 2020 | AB10: Q1 2021 | AC10: Q2 2021 | AD10: Q3 2021 | AE10: Q4 2021 | AF10: Q1 2022
B11: 0.25 | C11: 0 | D11: 0.159771 | E11: 0.159829 | F11: 0.098946 | G11: 0 | W11: 0.25 | X11: 8.08 | Y11: 7.34 | Z11: 7.2 | AB11: 7.087 | AC11: 6.86 | AD11: 6.896 | AE11: 7.271 | AF11: 7.302
B12: 0.5 | C12: 0 | D12: 0.167636 | E12: 0.159667 | F12: 0.100216 | G12: 0 | W12: 0.5 | X12: 10.649 | Y12: 9 | Z12: 8.15 | AB12: 7.89 | AC12: 7.317 | AD12: 7.282 | AE12: 8.095 | AF12: 8.164
B13: 1 | C13: 0 | D13: 0.167911 | E13: 0.161 | F13: 0.114095 | G13: 0 | W13: 1 | X13: 11.151 | Y13: 9.952 | Z13: 9.815 | AA13: 8.35 | AB13: 9.259 | AC13: 7.729 | AD13: 7.89 | AE13: 9.367 | AF13: 9.752
B14: 2 | C14: =F14 -> 0.122994 | D14: 0.172423 | E14: 0.179195 | F14: 0.122994 | G14: =$F14-($F$11-ROI!$F$7) -> 0.144048 | W14: 2 | X14: 12.0551 | Y14: 10.5849 | Z14: 10.5933 | AA14: 9.32 | AB14: 9.95 | AC14: 9.426 | AD14: 9.473 | AE14: 10.0533 | AF14: 11.0414
B15: 3 | C15: =F15 -> 0.134438 | D15: 0.174892 | E15: 0.179619 | F15: 0.134438 | G15: =$F15-($F$11-ROI!$F$7) -> 0.155492 | W15: 3 | X15: 12.2375 | Y15: 11.2844 | Z15: 10.8812 | AA15: 10 | AB15: 10.2917 | AC15: 10.263 | AD15: 9.9682 | AE15: 10.6982 | AF15: 11.3193
B16: 4 | C16: =F16 -> 0.141645 | D16: 0.178073 | E16: 0.178735 | F16: 0.141645 | G16: =$F16-($F$11-ROI!$F$7) -> 0.162699 | W16: 4 | X16: 12.4264 | Y16: 11.5 | Z16: 11.2 | AA16: 10.25 | AB16: 10.5379 | AC16: 10.5403 | AD16: 10.5322 | AE16: 11.0029 | AF16: 11.674
B17: 5 | C17: =F17 -> 0.141419 | D17: 0.156512 | E17: 0.174514 | F17: 0.141419 | G17: =$F17-($F$11-ROI!$F$7) -> 0.162473 | W17: 5 | X17: 12.4874 | Y17: 11.55 | Z17: 11.492 | AA17: 10.51 | AB17: 10.9502 | AC17: 11.1231 | AD17: 10.9116 | AE17: 11.4162 | AF17: 11.9775
B18: 6 | C18: =F18 -> 0.138666 | D18: 0.152556 | E18: 0.16787 | F18: 0.138666 | G18: =$F18-($F$11-ROI!$F$7) -> 0.15972 | W18: 6 | X18: 12.6211 | Y18: 11.8808 | Z18: 11.5445 | AA18: 10.83 | AB18: 11.2256 | AC18: 11.449 | AD18: 11.5418 | AE18: 11.8017 | AF18: 12.2489
B19: 7 | C19: =F19 -> 0.135966 | D19: 0.151092 | E19: 0.163212 | F19: 0.135966 | G19: =$F19-($F$11-ROI!$F$7) -> 0.15702 | W19: 7 | X19: 12.6965 | Y19: 12 | Z19: 11.5716 | AA19: 11.35 | AB19: 11.81 | AC19: 11.8542 | AD19: 11.9049 | AE19: 12.1544 | AF19: 12.4526
B20: 8 | C20: =F20 -> 0.13466 | D20: 0.149966 | E20: 0.159731 | F20: 0.13466 | G20: =$F20-($F$11-ROI!$F$7) -> 0.155714 | W20: 8 | X20: 12.7126 | Y20: 12.1514 | Z20: 11.6413 | AA20: 11.66 | AB20: 12.1893 | AC20: 11.979 | AD20: 12.2721 | AE20: 12.3647 | AF20: 12.6363
B21: 9 | C21: =F21 -> 0.136109 | D21: 0.150023 | E21: 0.157301 | F21: 0.136109 | G21: =$F21-($F$11-ROI!$F$7) -> 0.157163 | W21: 9 | X21: 12.725 | Y21: 12.3681 | Z21: 11.8277 | AA21: 11.75 | AB21: 12.2764 | AC21: 12.1395 | AD21: 12.2846 | AE21: 12.4304 | AF21: 12.7941
B22: 10 | C22: =F22 -> 0.136012 | D22: 0.149767 | E22: 0.157043 | F22: 0.136012 | G22: =$F22-($F$11-ROI!$F$7) -> 0.157066 | W22: 10 | X22: 13.0957 | Y22: 12.5 | Z22: 12.2375 | AA22: 11.88 | AB22: 12.3512 | AC22: 12.2628 | AD22: 12.3265 | AE22: 12.4866 | AF22: 12.876
B23: 11 | C23: =F23 -> 0.135381 | D23: 0.149604 | E23: 0.157121 | F23: 0.135381 | G23: =$F23-($F$11-ROI!$F$7) -> 0.156435 | W23: 11 | X23: 13.1094 | Y23: 12.5253 | Z23: 12.3526 | AA23: 12.01 | AB23: 12.4412 | AC23: 12.4379 | AD23: 12.4 | AE23: 12.5641 | AF23: 13.0044
B24: 12 | C24: =F24 -> 0.134754 | D24: 0.149447 | E24: 0.157185 | F24: 0.134754 | G24: =$F24-($F$11-ROI!$F$7) -> 0.155808 | W24: 12 | X24: 13.1233 | Y24: 12.5445 | Z24: 12.4423 | AA24: 12.13 | AB24: 12.6088 | AC24: 12.5346 | AD24: 12.5591 | AE24: 12.7037 | AF24: 13.2814
B25: 13 | C25: =F25 -> 0.13413 | D25: 0.149352 | E25: 0.15724 | F25: 0.13413 | G25: =$F25-($F$11-ROI!$F$7) -> 0.155184 | W25: 13 | X25: 13.1341 | Y25: 12.55 | Z25: 12.4651 | AA25: 12.43 | AB25: 12.6671 | AC25: 12.6973 | AD25: 12.7642 | AE25: 12.7914 | AF25: 13.5087
... B34: 22 | C34: =F34 -> 0.153607 | D34: 0.155039 | E34: 0.160135 | F34: 0.153607 | G34: =$F34-($F$11-ROI!$F$7) -> 0.174661 | W34: 22 | X34: 13.4089 | Y34: 12.85 | Z34: 13.052 | AA34: 13.27 | AB34: 13.3432 | AC34: 13.306 | AD34: 13.4036 | AE34: 13.5989 | AF34: 13.844
B35: 23 | D35: 0.158795 | E35: 0.160641 | W35: 23 | X35: 13.4499 | Y35: 12.925 | Z35: 13.1042 | AA35: 13.29 | AB35: 13.3493 | AC35: 13.4188 | AD35: 13.4304 | AE35: 13.6246 | AF35: 13.8615
B36: 24 | E36: 0.161019 | W36: 24 | Y36: 12.9374 | Z36: 13.125 | AC36: 13.4752 | AD36: 13.4731 | AE36: 13.6437 | AF36: 13.8732
B37: 25 | W37: 25 | Y37: 13 | AC37: 13.5316 | AD37: 13.5017 | AE37: 13.6513
C41: =AVERAGE(C13:C37)/100 -> 0.0013264932

Sheet ROI
D4: Total Assets
F7: 0.12

Sheet Spot_Rates
A4: t | B4: FY 24
C6: Duration (Years) | D6: Lower Bound (Duration) | E6: Upper Bound (Duration) | F6: Lower Bound (Spot Rate) | G6: Upper Bound (Spot Rate) | H6: Spot Rate (NACA)
C7: 0 | D7: =IF($C7<=MIN(NSE_Yield_Curve!$B$11:$B$37),0,INDEX(NSE_Yield_Curve!B:B,MATCH($C7,NSE_Yield_Curve!B:B,1))) -> 0 | E7: =IF(C7<=MIN(NSE_Yield_Curve!$B$11:$B$37),MIN(NSE_Yield_Curve!$B$11:$B$37),IF(C7>=MAX(NSE_Yield_Curve!$B$11:$B$37),MAX(NSE_Yield_Curve!$B$11:$B$37),INDEX(NSE_Yield_Curve!B:B,MATCH($C7,NSE_Yield_Curve!B:B,1)+1))) -> 0.25 | F7: =INDEX(NSE_Yield_Curve!$B$11:$C$37,MATCH(IF(D7<=MIN(NSE_Yield_Curve!$B:$B),MIN(NSE_Yield_Curve!$B:$B),D7),NSE_Yield_Curve!$B$11:$B$37,0),MATCH($B$4,NSE_Yield_Curve!$B$10:$C$10,0)) -> 0 | G7: =INDEX(NSE_Yield_Curve!$B$11:$C$37,MATCH(IF(E7<=MIN(NSE_Yield_Curve!B:B),MIN(NSE_Yield_Curve!B:B),E7),NSE_Yield_Curve!$B$11:$B$37,0),MATCH($B$4,NSE_Yield_Curve!$B$10:$C$10,0)) -> 0 | H7: =IF(E7=D7,G7,F7+(G7-F7)*(C7-D7)/(E7-D7)) -> 0
C8: 0.08 | D8: =IF($C8<=MIN(NSE_Yield_Curve!$B$11:$B$37),0,INDEX(NSE_Yield_Curve!B:B,MATCH($C8,NSE_Yield_Curve!B:B,1))) -> 0 | E8: =IF(C8<=MIN(NSE_Yield_Curve!$B$11:$B$37),MIN(NSE_Yield_Curve!$B$11:$B$37),IF(C8>=MAX(NSE_Yield_Curve!$B$11:$B$37),MAX(NSE_Yield_Curve!$B$11:$B$37),INDEX(NSE_Yield_Curve!B:B,MATCH($C8,NSE_Yield_Curve!B:B,1)+1))) -> 0.25 | F8: =INDEX(NSE_Yield_Curve!$B$11:$C$37,MATCH(IF(D8<=MIN(NSE_Yield_Curve!$B:$B),MIN(NSE_Yield_Curve!$B:$B),D8),NSE_Yield_Curve!$B$11:$B$37,0),MATCH($B$4,NSE_Yield_Curve!$B$10:$C$10,0)) -> 0 | G8: =INDEX(NSE_Yield_Curve!$B$11:$C$37,MATCH(IF(E8<=MIN(NSE_Yield_Curve!B:B),MIN(NSE_Yield_Curve!B:B),E8),NSE_Yield_Curve!$B$11:$B$37,0),MATCH($B$4,NSE_Yield_Curve!$B$10:$C$10,0)) -> 0 | H8: =IF(E8=D8,G8,F8+(G8-F8)*(C8-D8)/(E8-D8)) -> 0
C9: 0.17 | D9: =IF($C9<=MIN(NSE_Yield_Curve!$B$11:$B$37),0,INDEX(NSE_Yield_Curve!B:B,MATCH($C9,NSE_Yield_Curve!B:B,1))) -> 0 | E9: =IF(C9<=MIN(NSE_Yield_Curve!$B$11:$B$37),MIN(NSE_Yield_Curve!$B$11:$B$37),IF(C9>=MAX(NSE_Yield_Curve!$B$11:$B$37),MAX(NSE_Yield_Curve!$B$11:$B$37),INDEX(NSE_Yield_Curve!B:B,MATCH($C9,NSE_Yield_Curve!B:B,1)+1))) -> 0.25 | F9: =INDEX(NSE_Yield_Curve!$B$11:$C$37,MATCH(IF(D9<=MIN(NSE_Yield_Curve!$B:$B),MIN(NSE_Yield_Curve!$B:$B),D9),NSE_Yield_Curve!$B$11:$B$37,0),MATCH($B$4,NSE_Yield_Curve!$B$10:$C$10,0)) -> 0 | G9: =INDEX(NSE_Yield_Curve!$B$11:$C$37,MATCH(IF(E9<=MIN(NSE_Yield_Curve!B:B),MIN(NSE_Yield_Curve!B:B),E9),NSE_Yield_Curve!$B$11:$B$37,0),MATCH($B$4,NSE_Yield_Curve!$B$10:$C$10,0)) -> 0 | H9: =IF(E9=D9,G9,F9+(G9-F9)*(C9-D9)/(E9-D9)) -> 0
C10: 0.25 | D10: =IF($C10<=MIN(NSE_Yield_Curve!$B$11:$B$37),0,INDEX(NSE_Yield_Curve!B:B,MATCH($C10,NSE_Yield_Curve!B:B,1))) -> 0 | E10: =IF(C10<=MIN(NSE_Yield_Curve!$B$11:$B$37),MIN(NSE_Yield_Curve!$B$11:$B$37),IF(C10>=MAX(NSE_Yield_Curve!$B$11:$B$37),MAX(NSE_Yield_Curve!$B$11:$B$37),INDEX(NSE_Yield_Curve!B:B,MATCH($C10,NSE_Yield_Curve!B:B,1)+1))) -> 0.25 | F10: =INDEX(NSE_Yield_Curve!$B$11:$C$37,MATCH(IF(D10<=MIN(NSE_Yield_Curve!$B:$B),MIN(NSE_Yield_Curve!$B:$B),D10),NSE_Yield_Curve!$B$11:$B$37,0),MATCH($B$4,NSE_Yield_Curve!$B$10:$C$10,0)) -> 0 | G10: =INDEX(NSE_Yield_Curve!$B$11:$C$37,MATCH(IF(E10<=MIN(NSE_Yield_Curve!B:B),MIN(NSE_Yield_Curve!B:B),E10),NSE_Yield_Curve!$B$11:$B$37,0),MATCH($B$4,NSE_Yield_Curve!$B$10:$C$10,0)) -> 0 | H10: =IF(E10=D10,G10,F10+(G10-F10)*(C10-D10)/(E10-D10)) -> 0
C11: 0.33 | D11: =IF($C11<=MIN(NSE_Yield_Curve!$B$11:$B$37),0,INDEX(NSE_Yield_Curve!B:B,MATCH($C11,NSE_Yield_Curve!B:B,1))) -> 0.25 | E11: =IF(C11<=MIN(NSE_Yield_Curve!$B$11:$B$37),MIN(NSE_Yield_Curve!$B$11:$B$37),IF(C11>=MAX(NSE_Yield_Curve!$B$11:$B$37),MAX(NSE_Yield_Curve!$B$11:$B$37),INDEX(NSE_Yield_Curve!B:B,MATCH($C11,NSE_Yield_Curve!B:B,1)+1))) -> 0.5 | F11: =INDEX(NSE_Yield_Curve!$B$11:$C$37,MATCH(IF(D11<=MIN(NSE_Yield_Curve!$B:$B),MIN(NSE_Yield_Curve!$B:$B),D11),NSE_Yield_Curve!$B$11:$B$37,0),MATCH($B$4,NSE_Yield_Curve!$B$10:$C$10,0)) -> 0 | G11: =INDEX(NSE_Yield_Curve!$B$11:$C$37,MATCH(IF(E11<=MIN(NSE_Yield_Curve!B:B),MIN(NSE_Yield_Curve!B:B),E11),NSE_Yield_Curve!$B$11:$B$37,0),MATCH($B$4,NSE_Yield_Curve!$B$10:$C$10,0)) -> 0 | H11: =IF(E11=D11,G11,F11+(G11-F11)*(C11-D11)/(E11-D11)) -> 0
C12: 0.42 | D12: =IF($C12<=MIN(NSE_Yield_Curve!$B$11:$B$37),0,INDEX(NSE_Yield_Curve!B:B,MATCH($C12,NSE_Yield_Curve!B:B,1))) -> 0.25 | E12: =IF(C12<=MIN(NSE_Yield_Curve!$B$11:$B$37),MIN(NSE_Yield_Curve!$B$11:$B$37),IF(C12>=MAX(NSE_Yield_Curve!$B$11:$B$37),MAX(NSE_Yield_Curve!$B$11:$B$37),INDEX(NSE_Yield_Curve!B:B,MATCH($C12,NSE_Yield_Curve!B:B,1)+1))) -> 0.5 | F12: =INDEX(NSE_Yield_Curve!$B$11:$C$37,MATCH(IF(D12<=MIN(NSE_Yield_Curve!$B:$B),MIN(NSE_Yield_Curve!$B:$B),D12),NSE_Yield_Curve!$B$11:$B$37,0),MATCH($B$4,NSE_Yield_Curve!$B$10:$C$10,0)) -> 0 | G12: =INDEX(NSE_Yield_Curve!$B$11:$C$37,MATCH(IF(E12<=MIN(NSE_Yield_Curve!B:B),MIN(NSE_Yield_Curve!B:B),E12),NSE_Yield_Curve!$B$11:$B$37,0),MATCH($B$4,NSE_Yield_Curve!$B$10:$C$10,0)) -> 0 | H12: =IF(E12=D12,G12,F12+(G12-F12)*(C12-D12)/(E12-D12)) -> 0
C13: 0.5 | D13: =IF($C13<=MIN(NSE_Yield_Curve!$B$11:$B$37),0,INDEX(NSE_Yield_Curve!B:B,MATCH($C13,NSE_Yield_Curve!B:B,1))) -> 0.5 | E13: =IF(C13<=MIN(NSE_Yield_Curve!$B$11:$B$37),MIN(NSE_Yield_Curve!$B$11:$B$37),IF(C13>=MAX(NSE_Yield_Curve!$B$11:$B$37),MAX(NSE_Yield_Curve!$B$11:$B$37),INDEX(NSE_Yield_Curve!B:B,MATCH($C13,NSE_Yield_Curve!B:B,1)+1))) -> 1 | F13: =INDEX(NSE_Yield_Curve!$B$11:$C$37,MATCH(IF(D13<=MIN(NSE_Yield_Curve!$B:$B),MIN(NSE_Yield_Curve!$B:$B),D13),NSE_Yield_Curve!$B$11:$B$37,0),MATCH($B$4,NSE_Yield_Curve!$B$10:$C$10,0)) -> 0 | G13: =INDEX(NSE_Yield_Curve!$B$11:$C$37,MATCH(IF(E13<=MIN(NSE_Yield_Curve!B:B),MIN(NSE_Yield_Curve!B:B),E13),NSE_Yield_Curve!$B$11:$B$37,0),MATCH($B$4,NSE_Yield_Curve!$B$10:$C$10,0)) -> 0 | H13: =IF(E13=D13,G13,F13+(G13-F13)*(C13-D13)/(E13-D13)) -> 0
C14: 0.58 | D14: =IF($C14<=MIN(NSE_Yield_Curve!$B$11:$B$37),0,INDEX(NSE_Yield_Curve!B:B,MATCH($C14,NSE_Yield_Curve!B:B,1))) -> 0.5 | E14: =IF(C14<=MIN(NSE_Yield_Curve!$B$11:$B$37),MIN(NSE_Yield_Curve!$B$11:$B$37),IF(C14>=MAX(NSE_Yield_Curve!$B$11:$B$37),MAX(NSE_Yield_Curve!$B$11:$B$37),INDEX(NSE_Yield_Curve!B:B,MATCH($C14,NSE_Yield_Curve!B:B,1)+1))) -> 1 | F14: =INDEX(NSE_Yield_Curve!$B$11:$C$37,MATCH(IF(D14<=MIN(NSE_Yield_Curve!$B:$B),MIN(NSE_Yield_Curve!$B:$B),D14),NSE_Yield_Curve!$B$11:$B$37,0),MATCH($B$4,NSE_Yield_Curve!$B$10:$C$10,0)) -> 0 | G14: =INDEX(NSE_Yield_Curve!$B$11:$C$37,MATCH(IF(E14<=MIN(NSE_Yield_Curve!B:B),MIN(NSE_Yield_Curve!B:B),E14),NSE_Yield_Curve!$B$11:$B$37,0),MATCH($B$4,NSE_Yield_Curve!$B$10:$C$10,0)) -> 0 | H14: =IF(E14=D14,G14,F14+(G14-F14)*(C14-D14)/(E14-D14)) -> 0
C15: 0.67 | D15: =IF($C15<=MIN(NSE_Yield_Curve!$B$11:$B$37),0,INDEX(NSE_Yield_Curve!B:B,MATCH($C15,NSE_Yield_Curve!B:B,1))) -> 0.5 | E15: =IF(C15<=MIN(NSE_Yield_Curve!$B$11:$B$37),MIN(NSE_Yield_Curve!$B$11:$B$37),IF(C15>=MAX(NSE_Yield_Curve!$B$11:$B$37),MAX(NSE_Yield_Curve!$B$11:$B$37),INDEX(NSE_Yield_Curve!B:B,MATCH($C15,NSE_Yield_Curve!B:B,1)+1))) -> 1 | F15: =INDEX(NSE_Yield_Curve!$B$11:$C$37,MATCH(IF(D15<=MIN(NSE_Yield_Curve!$B:$B),MIN(NSE_Yield_Curve!$B:$B),D15),NSE_Yield_Curve!$B$11:$B$37,0),MATCH($B$4,NSE_Yield_Curve!$B$10:$C$10,0)) -> 0 | G15: =INDEX(NSE_Yield_Curve!$B$11:$C$37,MATCH(IF(E15<=MIN(NSE_Yield_Curve!B:B),MIN(NSE_Yield_Curve!B:B),E15),NSE_Yield_Curve!$B$11:$B$37,0),MATCH($B$4,NSE_Yield_Curve!$B$10:$C$10,0)) -> 0 | H15: =IF(E15=D15,G15,F15+(G15-F15)*(C15-D15)/(E15-D15)) -> 0
C16: 0.75 | D16: =IF($C16<=MIN(NSE_Yield_Curve!$B$11:$B$37),0,INDEX(NSE_Yield_Curve!B:B,MATCH($C16,NSE_Yield_Curve!B:B,1))) -> 0.5 | E16: =IF(C16<=MIN(NSE_Yield_Curve!$B$11:$B$37),MIN(NSE_Yield_Curve!$B$11:$B$37),IF(C16>=MAX(NSE_Yield_Curve!$B$11:$B$37),MAX(NSE_Yield_Curve!$B$11:$B$37),INDEX(NSE_Yield_Curve!B:B,MATCH($C16,NSE_Yield_Curve!B:B,1)+1))) -> 1 | F16: =INDEX(NSE_Yield_Curve!$B$11:$C$37,MATCH(IF(D16<=MIN(NSE_Yield_Curve!$B:$B),MIN(NSE_Yield_Curve!$B:$B),D16),NSE_Yield_Curve!$B$11:$B$37,0),MATCH($B$4,NSE_Yield_Curve!$B$10:$C$10,0)) -> 0 | G16: =INDEX(NSE_Yield_Curve!$B$11:$C$37,MATCH(IF(E16<=MIN(NSE_Yield_Curve!B:B),MIN(NSE_Yield_Curve!B:B),E16),NSE_Yield_Curve!$B$11:$B$37,0),MATCH($B$4,NSE_Yield_Curve!$B$10:$C$10,0)) -> 0 | H16: =IF(E16=D16,G16,F16+(G16-F16)*(C16-D16)/(E16-D16)) -> 0
C17: 0.83 | D17: =IF($C17<=MIN(NSE_Yield_Curve!$B$11:$B$37),0,INDEX(NSE_Yield_Curve!B:B,MATCH($C17,NSE_Yield_Curve!B:B,1))) -> 0.5 | E17: =IF(C17<=MIN(NSE_Yield_Curve!$B$11:$B$37),MIN(NSE_Yield_Curve!$B$11:$B$37),IF(C17>=MAX(NSE_Yield_Curve!$B$11:$B$37),MAX(NSE_Yield_Curve!$B$11:$B$37),INDEX(NSE_Yield_Curve!B:B,MATCH($C17,NSE_Yield_Curve!B:B,1)+1))) -> 1 | F17: =INDEX(NSE_Yield_Curve!$B$11:$C$37,MATCH(IF(D17<=MIN(NSE_Yield_Curve!$B:$B),MIN(NSE_Yield_Curve!$B:$B),D17),NSE_Yield_Curve!$B$11:$B$37,0),MATCH($B$4,NSE_Yield_Curve!$B$10:$C$10,0)) -> 0 | G17: =INDEX(NSE_Yield_Curve!$B$11:$C$37,MATCH(IF(E17<=MIN(NSE_Yield_Curve!B:B),MIN(NSE_Yield_Curve!B:B),E17),NSE_Yield_Curve!$B$11:$B$37,0),MATCH($B$4,NSE_Yield_Curve!$B$10:$C$10,0)) -> 0 | H17: =IF(E17=D17,G17,F17+(G17-F17)*(C17-D17)/(E17-D17)) -> 0
C18: 0.92 | D18: =IF($C18<=MIN(NSE_Yield_Curve!$B$11:$B$37),0,INDEX(NSE_Yield_Curve!B:B,MATCH($C18,NSE_Yield_Curve!B:B,1))) -> 0.5 | E18: =IF(C18<=MIN(NSE_Yield_Curve!$B$11:$B$37),MIN(NSE_Yield_Curve!$B$11:$B$37),IF(C18>=MAX(NSE_Yield_Curve!$B$11:$B$37),MAX(NSE_Yield_Curve!$B$11:$B$37),INDEX(NSE_Yield_Curve!B:B,MATCH($C18,NSE_Yield_Curve!B:B,1)+1))) -> 1 | F18: =INDEX(NSE_Yield_Curve!$B$11:$C$37,MATCH(IF(D18<=MIN(NSE_Yield_Curve!$B:$B),MIN(NSE_Yield_Curve!$B:$B),D18),NSE_Yield_Curve!$B$11:$B$37,0),MATCH($B$4,NSE_Yield_Curve!$B$10:$C$10,0)) -> 0 | G18: =INDEX(NSE_Yield_Curve!$B$11:$C$37,MATCH(IF(E18<=MIN(NSE_Yield_Curve!B:B),MIN(NSE_Yield_Curve!B:B),E18),NSE_Yield_Curve!$B$11:$B$37,0),MATCH($B$4,NSE_Yield_Curve!$B$10:$C$10,0)) -> 0 | H18: =IF(E18=D18,G18,F18+(G18-F18)*(C18-D18)/(E18-D18)) -> 0
... C307: 25 | D307: =IF($C307<=MIN(NSE_Yield_Curve!$B$11:$B$37),0,INDEX(NSE_Yield_Curve!B:B,MATCH($C307,NSE_Yield_Curve!B:B,1))) -> 25 | E307: =IF(C307<=MIN(NSE_Yield_Curve!$B$11:$B$37),MIN(NSE_Yield_Curve!$B$11:$B$37),IF(C307>=MAX(NSE_Yield_Curve!$B$11:$B$37),MAX(NSE_Yield_Curve!$B$11:$B$37),INDEX(NSE_Yield_Curve!B:B,MATCH($C307,NSE_Yield_Curve!B:B,1)+1))) -> 25 | F307: =INDEX(NSE_Yield_Curve!$B$11:$C$37,MATCH(IF(D307<=MIN(NSE_Yield_Curve!$B:$B),MIN(NSE_Yield_Curve!$B:$B),D307),NSE_Yield_Curve!$B$11:$B$37,0),MATCH($B$4,NSE_Yield_Curve!$B$10:$C$10,0)) -> 0 | G307: =INDEX(NSE_Yield_Curve!$B$11:$C$37,MATCH(IF(E307<=MIN(NSE_Yield_Curve!B:B),MIN(NSE_Yield_Curve!B:B),E307),NSE_Yield_Curve!$B$11:$B$37,0),MATCH($B$4,NSE_Yield_Curve!$B$10:$C$10,0)) -> 0 | H307: =IF(E307=D307,G307,F307+(G307-F307)*(C307-D307)/(E307-D307)) -> 0
C308: =C307+1/12 -> 25.083333 | D308: =IF($C308<=MIN(NSE_Yield_Curve!$B$11:$B$37),0,INDEX(NSE_Yield_Curve!B:B,MATCH($C308,NSE_Yield_Curve!B:B,1))) -> 25 | E308: =IF(C308<=MIN(NSE_Yield_Curve!$B$11:$B$37),MIN(NSE_Yield_Curve!$B$11:$B$37),IF(C308>=MAX(NSE_Yield_Curve!$B$11:$B$37),MAX(NSE_Yield_Curve!$B$11:$B$37),INDEX(NSE_Yield_Curve!B:B,MATCH($C308,NSE_Yield_Curve!B:B,1)+1))) -> 25 | F308: =INDEX(NSE_Yield_Curve!$B$11:$C$37,MATCH(IF(D308<=MIN(NSE_Yield_Curve!$B:$B),MIN(NSE_Yield_Curve!$B:$B),D308),NSE_Yield_Curve!$B$11:$B$37,0),MATCH($B$4,NSE_Yield_Curve!$B$10:$C$10,0)) -> 0 | G308: =INDEX(NSE_Yield_Curve!$B$11:$C$37,MATCH(IF(E308<=MIN(NSE_Yield_Curve!B:B),MIN(NSE_Yield_Curve!B:B),E308),NSE_Yield_Curve!$B$11:$B$37,0),MATCH($B$4,NSE_Yield_Curve!$B$10:$C$10,0)) -> 0 | H308: =IF(E308=D308,G308,F308+(G308-F308)*(C308-D308)/(E308-D308)) -> 0
C309: =C308+1/12 -> 25.166667 | D309: =IF($C309<=MIN(NSE_Yield_Curve!$B$11:$B$37),0,INDEX(NSE_Yield_Curve!B:B,MATCH($C309,NSE_Yield_Curve!B:B,1))) -> 25 | E309: =IF(C309<=MIN(NSE_Yield_Curve!$B$11:$B$37),MIN(NSE_Yield_Curve!$B$11:$B$37),IF(C309>=MAX(NSE_Yield_Curve!$B$11:$B$37),MAX(NSE_Yield_Curve!$B$11:$B$37),INDEX(NSE_Yield_Curve!B:B,MATCH($C309,NSE_Yield_Curve!B:B,1)+1))) -> 25 | F309: =INDEX(NSE_Yield_Curve!$B$11:$C$37,MATCH(IF(D309<=MIN(NSE_Yield_Curve!$B:$B),MIN(NSE_Yield_Curve!$B:$B),D309),NSE_Yield_Curve!$B$11:$B$37,0),MATCH($B$4,NSE_Yield_Curve!$B$10:$C$10,0)) -> 0 | G309: =INDEX(NSE_Yield_Curve!$B$11:$C$37,MATCH(IF(E309<=MIN(NSE_Yield_Curve!B:B),MIN(NSE_Yield_Curve!B:B),E309),NSE_Yield_Curve!$B$11:$B$37,0),MATCH($B$4,NSE_Yield_Curve!$B$10:$C$10,0)) -> 0 | H309: =IF(E309=D309,G309,F309+(G309-F309)*(C309-D309)/(E309-D309)) -> 0
C310: =C309+1/12 -> 25.25 | D310: =IF($C310<=MIN(NSE_Yield_Curve!$B$11:$B$37),0,INDEX(NSE_Yield_Curve!B:B,MATCH($C310,NSE_Yield_Curve!B:B,1))) -> 25 | E310: =IF(C310<=MIN(NSE_Yield_Curve!$B$11:$B$37),MIN(NSE_Yield_Curve!$B$11:$B$37),IF(C310>=MAX(NSE_Yield_Curve!$B$11:$B$37),MAX(NSE_Yield_Curve!$B$11:$B$37),INDEX(NSE_Yield_Curve!B:B,MATCH($C310,NSE_Yield_Curve!B:B,1)+1))) -> 25 | F310: =INDEX(NSE_Yield_Curve!$B$11:$C$37,MATCH(IF(D310<=MIN(NSE_Yield_Curve!$B:$B),MIN(NSE_Yield_Curve!$B:$B),D310),NSE_Yield_Curve!$B$11:$B$37,0),MATCH($B$4,NSE_Yield_Curve!$B$10:$C$10,0)) -> 0 | G310: =INDEX(NSE_Yield_Curve!$B$11:$C$37,MATCH(IF(E310<=MIN(NSE_Yield_Curve!B:B),MIN(NSE_Yield_Curve!B:B),E310),NSE_Yield_Curve!$B$11:$B$37,0),MATCH($B$4,NSE_Yield_Curve!$B$10:$C$10,0)) -> 0 | H310: =IF(E310=D310,G310,F310+(G310-F310)*(C310-D310)/(E310-D310)) -> 0
C311: =C310+1/12 -> 25.333333 | D311: =IF($C311<=MIN(NSE_Yield_Curve!$B$11:$B$37),0,INDEX(NSE_Yield_Curve!B:B,MATCH($C311,NSE_Yield_Curve!B:B,1))) -> 25 | E311: =IF(C311<=MIN(NSE_Yield_Curve!$B$11:$B$37),MIN(NSE_Yield_Curve!$B$11:$B$37),IF(C311>=MAX(NSE_Yield_Curve!$B$11:$B$37),MAX(NSE_Yield_Curve!$B$11:$B$37),INDEX(NSE_Yield_Curve!B:B,MATCH($C311,NSE_Yield_Curve!B:B,1)+1))) -> 25 | F311: =INDEX(NSE_Yield_Curve!$B$11:$C$37,MATCH(IF(D311<=MIN(NSE_Yield_Curve!$B:$B),MIN(NSE_Yield_Curve!$B:$B),D311),NSE_Yield_Curve!$B$11:$B$37,0),MATCH($B$4,NSE_Yield_Curve!$B$10:$C$10,0)) -> 0 | G311: =INDEX(NSE_Yield_Curve!$B$11:$C$37,MATCH(IF(E311<=MIN(NSE_Yield_Curve!B:B),MIN(NSE_Yield_Curve!B:B),E311),NSE_Yield_Curve!$B$11:$B$37,0),MATCH($B$4,NSE_Yield_Curve!$B$10:$C$10,0)) -> 0 | H311: =IF(E311=D311,G311,F311+(G311-F311)*(C311-D311)/(E311-D311)) -> 0
C312: =C311+1/12 -> 25.416667 | D312: =IF($C312<=MIN(NSE_Yield_Curve!$B$11:$B$37),0,INDEX(NSE_Yield_Curve!B:B,MATCH($C312,NSE_Yield_Curve!B:B,1))) -> 25 | E312: =IF(C312<=MIN(NSE_Yield_Curve!$B$11:$B$37),MIN(NSE_Yield_Curve!$B$11:$B$37),IF(C312>=MAX(NSE_Yield_Curve!$B$11:$B$37),MAX(NSE_Yield_Curve!$B$11:$B$37),INDEX(NSE_Yield_Curve!B:B,MATCH($C312,NSE_Yield_Curve!B:B,1)+1))) -> 25 | F312: =INDEX(NSE_Yield_Curve!$B$11:$C$37,MATCH(IF(D312<=MIN(NSE_Yield_Curve!$B:$B),MIN(NSE_Yield_Curve!$B:$B),D312),NSE_Yield_Curve!$B$11:$B$37,0),MATCH($B$4,NSE_Yield_Curve!$B$10:$C$10,0)) -> 0 | G312: =INDEX(NSE_Yield_Curve!$B$11:$C$37,MATCH(IF(E312<=MIN(NSE_Yield_Curve!B:B),MIN(NSE_Yield_Curve!B:B),E312),NSE_Yield_Curve!$B$11:$B$37,0),MATCH($B$4,NSE_Yield_Curve!$B$10:$C$10,0)) -> 0 | H312: =IF(E312=D312,G312,F312+(G312-F312)*(C312-D312)/(E312-D312)) -> 0
C313: =C312+1/12 -> 25.5 | D313: =IF($C313<=MIN(NSE_Yield_Curve!$B$11:$B$37),0,INDEX(NSE_Yield_Curve!B:B,MATCH($C313,NSE_Yield_Curve!B:B,1))) -> 25 | E313: =IF(C313<=MIN(NSE_Yield_Curve!$B$11:$B$37),MIN(NSE_Yield_Curve!$B$11:$B$37),IF(C313>=MAX(NSE_Yield_Curve!$B$11:$B$37),MAX(NSE_Yield_Curve!$B$11:$B$37),INDEX(NSE_Yield_Curve!B:B,MATCH($C313,NSE_Yield_Curve!B:B,1)+1))) -> 25 | F313: =INDEX(NSE_Yield_Curve!$B$11:$C$37,MATCH(IF(D313<=MIN(NSE_Yield_Curve!$B:$B),MIN(NSE_Yield_Curve!$B:$B),D313),NSE_Yield_Curve!$B$11:$B$37,0),MATCH($B$4,NSE_Yield_Curve!$B$10:$C$10,0)) -> 0 | G313: =INDEX(NSE_Yield_Curve!$B$11:$C$37,MATCH(IF(E313<=MIN(NSE_Yield_Curve!B:B),MIN(NSE_Yield_Curve!B:B),E313),NSE_Yield_Curve!$B$11:$B$37,0),MATCH($B$4,NSE_Yield_Curve!$B$10:$C$10,0)) -> 0 | H313: =IF(E313=D313,G313,F313+(G313-F313)*(C313-D313)/(E313-D313)) -> 0
C314: =C313+1/12 -> 25.583333 | D314: =IF($C314<=MIN(NSE_Yield_Curve!$B$11:$B$37),0,INDEX(NSE_Yield_Curve!B:B,MATCH($C314,NSE_Yield_Curve!B:B,1))) -> 25 | E314: =IF(C314<=MIN(NSE_Yield_Curve!$B$11:$B$37),MIN(NSE_Yield_Curve!$B$11:$B$37),IF(C314>=MAX(NSE_Yield_Curve!$B$11:$B$37),MAX(NSE_Yield_Curve!$B$11:$B$37),INDEX(NSE_Yield_Curve!B:B,MATCH($C314,NSE_Yield_Curve!B:B,1)+1))) -> 25 | F314: =INDEX(NSE_Yield_Curve!$B$11:$C$37,MATCH(IF(D314<=MIN(NSE_Yield_Curve!$B:$B),MIN(NSE_Yield_Curve!$B:$B),D314),NSE_Yield_Curve!$B$11:$B$37,0),MATCH($B$4,NSE_Yield_Curve!$B$10:$C$10,0)) -> 0 | G314: =INDEX(NSE_Yield_Curve!$B$11:$C$37,MATCH(IF(E314<=MIN(NSE_Yield_Curve!B:B),MIN(NSE_Yield_Curve!B:B),E314),NSE_Yield_Curve!$B$11:$B$37,0),MATCH($B$4,NSE_Yield_Curve!$B$10:$C$10,0)) -> 0 | H314: =IF(E314=D314,G314,F314+(G314-F314)*(C314-D314)/(E314-D314)) -> 0
C315: =C314+1/12 -> 25.666667 | D315: =IF($C315<=MIN(NSE_Yield_Curve!$B$11:$B$37),0,INDEX(NSE_Yield_Curve!B:B,MATCH($C315,NSE_Yield_Curve!B:B,1))) -> 25 | E315: =IF(C315<=MIN(NSE_Yield_Curve!$B$11:$B$37),MIN(NSE_Yield_Curve!$B$11:$B$37),IF(C315>=MAX(NSE_Yield_Curve!$B$11:$B$37),MAX(NSE_Yield_Curve!$B$11:$B$37),INDEX(NSE_Yield_Curve!B:B,MATCH($C315,NSE_Yield_Curve!B:B,1)+1))) -> 25 | F315: =INDEX(NSE_Yield_Curve!$B$11:$C$37,MATCH(IF(D315<=MIN(NSE_Yield_Curve!$B:$B),MIN(NSE_Yield_Curve!$B:$B),D315),NSE_Yield_Curve!$B$11:$B$37,0),MATCH($B$4,NSE_Yield_Curve!$B$10:$C$10,0)) -> 0 | G315: =INDEX(NSE_Yield_Curve!$B$11:$C$37,MATCH(IF(E315<=MIN(NSE_Yield_Curve!B:B),MIN(NSE_Yield_Curve!B:B),E315),NSE_Yield_Curve!$B$11:$B$37,0),MATCH($B$4,NSE_Yield_Curve!$B$10:$C$10,0)) -> 0 | H315: =IF(E315=D315,G315,F315+(G315-F315)*(C315-D315)/(E315-D315)) -> 0
C316: =C315+1/12 -> 25.75 | D316: =IF($C316<=MIN(NSE_Yield_Curve!$B$11:$B$37),0,INDEX(NSE_Yield_Curve!B:B,MATCH($C316,NSE_Yield_Curve!B:B,1))) -> 25 | E316: =IF(C316<=MIN(NSE_Yield_Curve!$B$11:$B$37),MIN(NSE_Yield_Curve!$B$11:$B$37),IF(C316>=MAX(NSE_Yield_Curve!$B$11:$B$37),MAX(NSE_Yield_Curve!$B$11:$B$37),INDEX(NSE_Yield_Curve!B:B,MATCH($C316,NSE_Yield_Curve!B:B,1)+1))) -> 25 | F316: =INDEX(NSE_Yield_Curve!$B$11:$C$37,MATCH(IF(D316<=MIN(NSE_Yield_Curve!$B:$B),MIN(NSE_Yield_Curve!$B:$B),D316),NSE_Yield_Curve!$B$11:$B$37,0),MATCH($B$4,NSE_Yield_Curve!$B$10:$C$10,0)) -> 0 | G316: =INDEX(NSE_Yield_Curve!$B$11:$C$37,MATCH(IF(E316<=MIN(NSE_Yield_Curve!B:B),MIN(NSE_Yield_Curve!B:B),E316),NSE_Yield_Curve!$B$11:$B$37,0),MATCH($B$4,NSE_Yield_Curve!$B$10:$C$10,0)) -> 0 | H316: =IF(E316=D316,G316,F316+(G316-F316)*(C316-D316)/(E316-D316)) -> 0
C317: =C316+1/12 -> 25.833333 | D317: =IF($C317<=MIN(NSE_Yield_Curve!$B$11:$B$37),0,INDEX(NSE_Yield_Curve!B:B,MATCH($C317,NSE_Yield_Curve!B:B,1))) -> 25 | E317: =IF(C317<=MIN(NSE_Yield_Curve!$B$11:$B$37),MIN(NSE_Yield_Curve!$B$11:$B$37),IF(C317>=MAX(NSE_Yield_Curve!$B$11:$B$37),MAX(NSE_Yield_Curve!$B$11:$B$37),INDEX(NSE_Yield_Curve!B:B,MATCH($C317,NSE_Yield_Curve!B:B,1)+1))) -> 25 | F317: =INDEX(NSE_Yield_Curve!$B$11:$C$37,MATCH(IF(D317<=MIN(NSE_Yield_Curve!$B:$B),MIN(NSE_Yield_Curve!$B:$B),D317),NSE_Yield_Curve!$B$11:$B$37,0),MATCH($B$4,NSE_Yield_Curve!$B$10:$C$10,0)) -> 0 | G317: =INDEX(NSE_Yield_Curve!$B$11:$C$37,MATCH(IF(E317<=MIN(NSE_Yield_Curve!B:B),MIN(NSE_Yield_Curve!B:B),E317),NSE_Yield_Curve!$B$11:$B$37,0),MATCH($B$4,NSE_Yield_Curve!$B$10:$C$10,0)) -> 0 | H317: =IF(E317=D317,G317,F317+(G317-F317)*(C317-D317)/(E317-D317)) -> 0
C318: =C317+1/12 -> 25.916667 | D318: =IF($C318<=MIN(NSE_Yield_Curve!$B$11:$B$37),0,INDEX(NSE_Yield_Curve!B:B,MATCH($C318,NSE_Yield_Curve!B:B,1))) -> 25 | E318: =IF(C318<=MIN(NSE_Yield_Curve!$B$11:$B$37),MIN(NSE_Yield_Curve!$B$11:$B$37),IF(C318>=MAX(NSE_Yield_Curve!$B$11:$B$37),MAX(NSE_Yield_Curve!$B$11:$B$37),INDEX(NSE_Yield_Curve!B:B,MATCH($C318,NSE_Yield_Curve!B:B,1)+1))) -> 25 | F318: =INDEX(NSE_Yield_Curve!$B$11:$C$37,MATCH(IF(D318<=MIN(NSE_Yield_Curve!$B:$B),MIN(NSE_Yield_Curve!$B:$B),D318),NSE_Yield_Curve!$B$11:$B$37,0),MATCH($B$4,NSE_Yield_Curve!$B$10:$C$10,0)) -> 0 | G318: =INDEX(NSE_Yield_Curve!$B$11:$C$37,MATCH(IF(E318<=MIN(NSE_Yield_Curve!B:B),MIN(NSE_Yield_Curve!B:B),E318),NSE_Yield_Curve!$B$11:$B$37,0),MATCH($B$4,NSE_Yield_Curve!$B$10:$C$10,0)) -> 0 | H318: =IF(E318=D318,G318,F318+(G318-F318)*(C318-D318)/(E318-D318)) -> 0
C319: =C318+1/12 -> 26 | D319: =IF($C319<=MIN(NSE_Yield_Curve!$B$11:$B$37),0,INDEX(NSE_Yield_Curve!B:B,MATCH($C319,NSE_Yield_Curve!B:B,1))) -> 25 | E319: =IF(C319<=MIN(NSE_Yield_Curve!$B$11:$B$37),MIN(NSE_Yield_Curve!$B$11:$B$37),IF(C319>=MAX(NSE_Yield_Curve!$B$11:$B$37),MAX(NSE_Yield_Curve!$B$11:$B$37),INDEX(NSE_Yield_Curve!B:B,MATCH($C319,NSE_Yield_Curve!B:B,1)+1))) -> 25 | F319: =INDEX(NSE_Yield_Curve!$B$11:$C$37,MATCH(IF(D319<=MIN(NSE_Yield_Curve!$B:$B),MIN(NSE_Yield_Curve!$B:$B),D319),NSE_Yield_Curve!$B$11:$B$37,0),MATCH($B$4,NSE_Yield_Curve!$B$10:$C$10,0)) -> 0 | G319: =INDEX(NSE_Yield_Curve!$B$11:$C$37,MATCH(IF(E319<=MIN(NSE_Yield_Curve!B:B),MIN(NSE_Yield_Curve!B:B),E319),NSE_Yield_Curve!$B$11:$B$37,0),MATCH($B$4,NSE_Yield_Curve!$B$10:$C$10,0)) -> 0 | H319: =IF(E319=D319,G319,F319+(G319-F319)*(C319-D319)/(E319-D319)) -> 0
... C367: =C366+1/12 -> 30 | D367: =IF($C367<=MIN(NSE_Yield_Curve!$B$11:$B$37),0,INDEX(NSE_Yield_Curve!B:B,MATCH($C367,NSE_Yield_Curve!B:B,1))) -> 25 | E367: =IF(C367<=MIN(NSE_Yield_Curve!$B$11:$B$37),MIN(NSE_Yield_Curve!$B$11:$B$37),IF(C367>=MAX(NSE_Yield_Curve!$B$11:$B$37),MAX(NSE_Yield_Curve!$B$11:$B$37),INDEX(NSE_Yield_Curve!B:B,MATCH($C367,NSE_Yield_Curve!B:B,1)+1))) -> 25 | F367: =INDEX(NSE_Yield_Curve!$B$11:$C$37,MATCH(IF(D367<=MIN(NSE_Yield_Curve!$B:$B),MIN(NSE_Yield_Curve!$B:$B),D367),NSE_Yield_Curve!$B$11:$B$37,0),MATCH($B$4,NSE_Yield_Curve!$B$10:$C$10,0)) -> 0 | G367: =INDEX(NSE_Yield_Curve!$B$11:$C$37,MATCH(IF(E367<=MIN(NSE_Yield_Curve!B:B),MIN(NSE_Yield_Curve!B:B),E367),NSE_Yield_Curve!$B$11:$B$37,0),MATCH($B$4,NSE_Yield_Curve!$B$10:$C$10,0)) -> 0 | H367: =IF(E367=D367,G367,F367+(G367-F367)*(C367-D367)/(E367-D367)) -> 0

Sheet Paid_DFs
G3: Reported to Paid DFs
G5: Aviation | H5: Engineering | I5: Fire Domestic | J5: Fire Industrial | K5: Liability | L5: Marine | M5: Miscellaneous | N5: Motor Commercial | O5: Motor Commercial PSV | P5: Motor Private | Q5: Personal Accident | R5: Theft | S5: Workmen's Compensation
F6: INCREMENTAL DEVELOPMENT FACTORS | G6: AVI | H6: ENG | I6: FD | J6: FI | K6: LIA | L6: MAR | M6: MISC | N6: MC | O6: MCPSV | P6: MP | Q6: PA | R6: THEFT | S6: WIBA
E7: 2018Q1 | F7: =F8+1 -> 27 | H7: 1 | I7: 1 | J7: 1 | K7: 1 | L7: 1 | M7: 1 | N7: 1 | O7: 1 | P7: 1 | Q7: 1 | R7: 1 | S7: 1
E8: 2018Q2 | F8: =F9+1 -> 26 | H8: 1 | I8: 1 | J8: 1 | K8: 1 | L8: 1 | M8: 1 | N8: 1.0003308 | O8: 1 | P8: 1 | Q8: 1 | R8: 1 | S8: 1.0018217
E9: 2018Q3 | F9: =F10+1 -> 25 | H9: 1 | I9: 1 | J9: 1 | K9: 1 | L9: 1 | M9: 1 | N9: 1.0012834 | O9: 1 | P9: 1 | Q9: 1 | R9: 1 | S9: 1
E10: 2018Q4 | F10: =F11+1 -> 24 | H10: 1 | I10: 1 | J10: 1 | K10: 1 | L10: 1 | M10: 1 | N10: 1.000796 | O10: 1 | P10: 1.0008949 | Q10: 1 | R10: 1 | S10: 1
E11: 2019Q1 | F11: =F12+1 -> 23 | H11: 1 | I11: 1 | J11: 1 | K11: 1 | L11: 1 | M11: 1 | N11: 1.0004637 | O11: 1 | P11: 1 | Q11: 1 | R11: 1 | S11: 1
E12: 2019Q2 | F12: =F13+1 -> 22 | H12: 1 | I12: 1 | J12: 1 | K12: 1 | L12: 1 | M12: 1 | N12: 1.0002221 | O12: 1 | P12: 1 | Q12: 1 | R12: 1 | S12: 1
E13: 2019Q3 | F13: =F14+1 -> 21 | H13: 1 | I13: 1 | J13: 1 | K13: 1 | L13: 1 | M13: 1 | N13: 1.0000211 | O13: 1 | P13: 1 | Q13: 1 | R13: 1 | S13: 1.0000925
E14: 2019Q4 | F14: =F15+1 -> 20 | H14: 1 | I14: 1 | J14: 1 | K14: 1 | L14: 1 | M14: 1 | N14: 1.0000184 | O14: 1 | P14: 1 | Q14: 1 | R14: 1 | S14: 1.0003908
E15: 2020Q1 | F15: =F16+1 -> 19 | H15: 1 | I15: 1 | J15: 1 | K15: 1 | L15: 1 | M15: 1 | N15: 1.000007 | O15: 1 | P15: 1 | Q15: 1 | R15: 1 | S15: 1.0006327
E16: 2020Q2 | F16: =F17+1 -> 18 | H16: 1 | I16: 1 | J16: 1 | K16: 1 | L16: 1 | M16: 1 | N16: 1.0007687 | O16: 1 | P16: 1 | Q16: 1 | R16: 1 | S16: 1.0001138
E17: 2020Q3 | F17: =F18+1 -> 17 | H17: 1 | I17: 1 | J17: 1 | K17: 1.0081988 | L17: 1 | M17: 1 | N17: 1 | O17: 1 | P17: 1.0001817 | Q17: 1 | R17: 1 | S17: 1.0002865
E18: 2020Q4 | F18: =F19+1 -> 16 | H18: 1 | I18: 1 | J18: 1 | K18: 1 | L18: 1 | M18: 1 | N18: 1.0007335 | O18: 1 | P18: 1 | Q18: 1.0005188 | R18: 1 | S18: 1.0011235
... E33: 2024Q3 | F33: =F34+1 -> 1 | H33: 1.0056291 | I33: 1.0241707 | J33: 1.0033145 | K33: 1.005781 | L33: 1.0492059 | M33: 1.2919189 | N33: 1.0118416 | O33: 1.0032901 | P33: 1.0037946 | Q33: 1.0150013 | R33: 1.0272386 | S33: 1.0677743
E34: 2024Q4 | F34: 0 | H34: 1.0517447 | I34: 1.0341014 | J34: 1.0286034 | K34: 1.0606112 | L34: 1.0730024 | M34: 1.2119761 | N34: 1.032624 | O34: 1.0107306 | P34: 1.0137997 | Q34: 1.1465719 | R34: 1.0815449 | S34: 1.1740733

Sheet ENG
J3: 2025 | K3: 2025 | L3: 2025 | M3: 2025 | N3: =J3+1 -> 2026 | O3: =K3+1 -> 2026 | P3: =L3+1 -> 2026 | Q3: =M3+1 -> 2026 | R3: =N3+1 -> 2027 | S3: =O3+1 -> 2027 | T3: =P3+1 -> 2027 | U3: =Q3+1 -> 2027 | ... AK3: =AG3+1 -> 2031
J4: Q1 | K4: Q2 | L4: Q3 | M4: Q4 | N4: Q1 | O4: Q2 | P4: Q3 | Q4: Q4 | R4: Q1 | S4: Q2 | T4: Q3 | U4: Q4 | V4: Q1 | W4: Q2 | X4: Q3 | Y4: Q4 | Z4: Q1 | AA4: Q2 | AB4: Q3 | AC4: Q4 | AD4: Q1 | AE4: Q2 | AF4: Q3 | AG4: Q4 | AH4: Q1 | AI4: Q2 | AJ4: Q3 | AK4: Q4
J5: =J4&"-"&J3 -> Q1-2025 | K5: =K4&"-"&K3 -> Q2-2025 | L5: =L4&"-"&L3 -> Q3-2025 | M5: =M4&"-"&M3 -> Q4-2025 | N5: =N4&"-"&N3 -> Q1-2026 | O5: =O4&"-"&O3 -> Q2-2026 | P5: =P4&"-"&P3 -> Q3-2026 | Q5: =Q4&"-"&Q3 -> Q4-2026 | ... AK5: =AK4&"-"&AK3 -> Q4-2031
H6: Payments in | J6: 3 | K6: =J6+3 -> 6 | L6: =K6+3 -> 9 | M6: =L6+3 -> 12 | N6: =M6+3 -> 15 | O6: =N6+3 -> 18 | P6: =O6+3 -> 21 | Q6: =P6+3 -> 24 | R6: =Q6+3 -> 27 | ... AK6: =AJ6+3 -> 84
K7: =K10-J10 -> 0.26 | L7: =L10-K10 -> 0.24 | M7: =M10-L10 -> 0.26 | N7: =N10-M10 -> 0.24 | O7: =O10-N10 -> 0.26 | P7: =P10-O10 -> 0.24 | Q7: =Q10-P10 -> 0.26 | R7: =R10-Q10 -> 0.24 | ... AK7: =AK10-AJ10 -> 0.26
B8: Engineering | K8: =SUM(J10:K10) -> 0.5 | L8: =SUM(K10:L10) -> 1 | M8: =SUM(L10:M10) -> 1.5 | N8: =SUM(M10:N10) -> 2 | O8: =SUM(N10:O10) -> 2.5 | P8: =SUM(O10:P10) -> 3 | Q8: =SUM(P10:Q10) -> 3.5 | R8: =SUM(Q10:R10) -> 4 | ... AK8: =SUM(AJ10:AK10) -> 13.5
J9: Time (in years)
B10: Origin | C10: Age | D10: Paid DF's | E10: Cumulative Development Factors | F10: Incremental Payments | G10: Cumulative Payments | H10: Expected Unpaid % | I10: Check | J10: 0.12 | K10: 0.38 | L10: 0.62 | M10: 0.88 | N10: 1.12 | O10: 1.38 | P10: 1.62 | Q10: 1.88 | R10: 2.12 | S10: 2.38 | T10: 2.62 | U10: 2.88 | V10: 3.12 | W10: 3.38 | X10: 3.62 | Y10: 3.88 | Z10: 4.12 | AA10: 4.38 | AB10: 4.62 | AC10: 4.88 | AD10: 5.12 | AE10: 5.38 | AF10: 5.62 | AG10: 5.88 | AH10: 6.12 | AI10: 6.38 | AJ10: 6.62 | AK10: 6.88
B11: =IBNR!F7 -> 2018Q1 | C11: =C12+3 -> 84 | D11: =_xlfn.XLOOKUP($B$8,Paid_DFs!$G$5:$S$5,Paid_DFs!$G7:$S7) -> 1 | E11: =PRODUCT($D$11:$D11) -> 1 | F11: =G11-G12 -> 0 | G11: =1/E11 -> 1 | H11: =1-G11 -> 0 | I11: =SUM(J11:AK11) -> 1 | J11: =IF($H11=0%,100%,IFERROR(VLOOKUP($C11+J$6,$C$11:$AK$38,4,FALSE)/$H11,0)) -> 1 | K11: =IFERROR(VLOOKUP($C11+K$6,$C$11:$AK$38,4,FALSE)/$H11,0) -> 0 | L11: =IFERROR(VLOOKUP($C11+L$6,$C$11:$AK$38,4,FALSE)/$H11,0) -> 0 | M11: =IFERROR(VLOOKUP($C11+M$6,$C$11:$AK$38,4,FALSE)/$H11,0) -> 0 | N11: =IFERROR(VLOOKUP($C11+N$6,$C$11:$AK$38,4,FALSE)/$H11,0) -> 0 | O11: =IFERROR(VLOOKUP($C11+O$6,$C$11:$AK$38,4,FALSE)/$H11,0) -> 0 | P11: =IFERROR(VLOOKUP($C11+P$6,$C$11:$AK$38,4,FALSE)/$H11,0) -> 0 | Q11: =IFERROR(VLOOKUP($C11+Q$6,$C$11:$AK$38,4,FALSE)/$H11,0) -> 0 | R11: =IFERROR(VLOOKUP($C11+R$6,$C$11:$AK$38,4,FALSE)/$H11,0) -> 0 | ... AK11: =IFERROR(VLOOKUP($C11+AK$6,$C$11:$AK$38,4,FALSE)/$H11,0) -> 0
B12: =IBNR!F8 -> 2018Q2 | C12: =C13+3 -> 81 | D12: =_xlfn.XLOOKUP($B$8,Paid_DFs!$G$5:$S$5,Paid_DFs!$G8:$S8) -> 1 | E12: =PRODUCT($D$11:$D12) -> 1 | F12: =G12-G13 -> 0 | G12: =1/E12 -> 1 | H12: =1-G12 -> 0 | I12: =SUM(J12:AK12) -> 1 | J12: =IF($H12=0%,100%,IFERROR(VLOOKUP($C12+J$6,$C$11:$AK$38,4,FALSE)/$H12,0)) -> 1 | K12: =IFERROR(VLOOKUP($C12+K$6,$C$11:$AK$38,4,FALSE)/$H12,0) -> 0 | L12: =IFERROR(VLOOKUP($C12+L$6,$C$11:$AK$38,4,FALSE)/$H12,0) -> 0 | M12: =IFERROR(VLOOKUP($C12+M$6,$C$11:$AK$38,4,FALSE)/$H12,0) -> 0 | N12: =IFERROR(VLOOKUP($C12+N$6,$C$11:$AK$38,4,FALSE)/$H12,0) -> 0 | O12: =IFERROR(VLOOKUP($C12+O$6,$C$11:$AK$38,4,FALSE)/$H12,0) -> 0 | P12: =IFERROR(VLOOKUP($C12+P$6,$C$11:$AK$38,4,FALSE)/$H12,0) -> 0 | Q12: =IFERROR(VLOOKUP($C12+Q$6,$C$11:$AK$38,4,FALSE)/$H12,0) -> 0 | R12: =IFERROR(VLOOKUP($C12+R$6,$C$11:$AK$38,4,FALSE)/$H12,0) -> 0 | ... AK12: =IFERROR(VLOOKUP($C12+AK$6,$C$11:$AK$38,4,FALSE)/$H12,0) -> 0
B13: =IBNR!F9 -> 2018Q3 | C13: =C14+3 -> 78 | D13: =_xlfn.XLOOKUP($B$8,Paid_DFs!$G$5:$S$5,Paid_DFs!$G9:$S9) -> 1 | E13: =PRODUCT($D$11:$D13) -> 1 | F13: =G13-G14 -> 0 | G13: =1/E13 -> 1 | H13: =1-G13 -> 0 | I13: =SUM(J13:AK13) -> 1 | J13: =IF($H13=0%,100%,IFERROR(VLOOKUP($C13+J$6,$C$11:$AK$38,4,FALSE)/$H13,0)) -> 1 | K13: =IFERROR(VLOOKUP($C13+K$6,$C$11:$AK$38,4,FALSE)/$H13,0) -> 0 | L13: =IFERROR(VLOOKUP($C13+L$6,$C$11:$AK$38,4,FALSE)/$H13,0) -> 0 | M13: =IFERROR(VLOOKUP($C13+M$6,$C$11:$AK$38,4,FALSE)/$H13,0) -> 0 | N13: =IFERROR(VLOOKUP($C13+N$6,$C$11:$AK$38,4,FALSE)/$H13,0) -> 0 | O13: =IFERROR(VLOOKUP($C13+O$6,$C$11:$AK$38,4,FALSE)/$H13,0) -> 0 | P13: =IFERROR(VLOOKUP($C13+P$6,$C$11:$AK$38,4,FALSE)/$H13,0) -> 0 | Q13: =IFERROR(VLOOKUP($C13+Q$6,$C$11:$AK$38,4,FALSE)/$H13,0) -> 0 | R13: =IFERROR(VLOOKUP($C13+R$6,$C$11:$AK$38,4,FALSE)/$H13,0) -> 0 | ... AK13: =IFERROR(VLOOKUP($C13+AK$6,$C$11:$AK$38,4,FALSE)/$H13,0) -> 0
B14: =IBNR!F10 -> 2018Q4 | C14: =C15+3 -> 75 | D14: =_xlfn.XLOOKUP($B$8,Paid_DFs!$G$5:$S$5,Paid_DFs!$G10:$S10) -> 1 | E14: =PRODUCT($D$11:$D14) -> 1 | F14: =G14-G15 -> 0 | G14: =1/E14 -> 1 | H14: =1-G14 -> 0 | I14: =SUM(J14:AK14) -> 1 | J14: =IF($H14=0%,100%,IFERROR(VLOOKUP($C14+J$6,$C$11:$AK$38,4,FALSE)/$H14,0)) -> 1 | K14: =IFERROR(VLOOKUP($C14+K$6,$C$11:$AK$38,4,FALSE)/$H14,0) -> 0 | L14: =IFERROR(VLOOKUP($C14+L$6,$C$11:$AK$38,4,FALSE)/$H14,0) -> 0 | M14: =IFERROR(VLOOKUP($C14+M$6,$C$11:$AK$38,4,FALSE)/$H14,0) -> 0 | N14: =IFERROR(VLOOKUP($C14+N$6,$C$11:$AK$38,4,FALSE)/$H14,0) -> 0 | O14: =IFERROR(VLOOKUP($C14+O$6,$C$11:$AK$38,4,FALSE)/$H14,0) -> 0 | P14: =IFERROR(VLOOKUP($C14+P$6,$C$11:$AK$38,4,FALSE)/$H14,0) -> 0 | Q14: =IFERROR(VLOOKUP($C14+Q$6,$C$11:$AK$38,4,FALSE)/$H14,0) -> 0 | R14: =IFERROR(VLOOKUP($C14+R$6,$C$11:$AK$38,4,FALSE)/$H14,0) -> 0 | ... AK14: =IFERROR(VLOOKUP($C14+AK$6,$C$11:$AK$38,4,FALSE)/$H14,0) -> 0
B15: =IBNR!F11 -> 2019Q1 | C15: =C16+3 -> 72 | D15: =_xlfn.XLOOKUP($B$8,Paid_DFs!$G$5:$S$5,Paid_DFs!$G11:$S11) -> 1 | E15: =PRODUCT($D$11:$D15) -> 1 | F15: =G15-G16 -> 0 | G15: =1/E15 -> 1 | H15: =1-G15 -> 0 | I15: =SUM(J15:AK15) -> 1 | J15: =IF($H15=0%,100%,IFERROR(VLOOKUP($C15+J$6,$C$11:$AK$38,4,FALSE)/$H15,0)) -> 1 | K15: =IFERROR(VLOOKUP($C15+K$6,$C$11:$AK$38,4,FALSE)/$H15,0) -> 0 | L15: =IFERROR(VLOOKUP($C15+L$6,$C$11:$AK$38,4,FALSE)/$H15,0) -> 0 | M15: =IFERROR(VLOOKUP($C15+M$6,$C$11:$AK$38,4,FALSE)/$H15,0) -> 0 | N15: =IFERROR(VLOOKUP($C15+N$6,$C$11:$AK$38,4,FALSE)/$H15,0) -> 0 | O15: =IFERROR(VLOOKUP($C15+O$6,$C$11:$AK$38,4,FALSE)/$H15,0) -> 0 | P15: =IFERROR(VLOOKUP($C15+P$6,$C$11:$AK$38,4,FALSE)/$H15,0) -> 0 | Q15: =IFERROR(VLOOKUP($C15+Q$6,$C$11:$AK$38,4,FALSE)/$H15,0) -> 0 | R15: =IFERROR(VLOOKUP($C15+R$6,$C$11:$AK$38,4,FALSE)/$H15,0) -> 0 | ... AK15: =IFERROR(VLOOKUP($C15+AK$6,$C$11:$AK$38,4,FALSE)/$H15,0) -> 0
B16: =IBNR!F12 -> 2019Q2 | C16: =C17+3 -> 69 | D16: =_xlfn.XLOOKUP($B$8,Paid_DFs!$G$5:$S$5,Paid_DFs!$G12:$S12) -> 1 | E16: =PRODUCT($D$11:$D16) -> 1 | F16: =G16-G17 -> 0 | G16: =1/E16 -> 1 | H16: =1-G16 -> 0 | I16: =SUM(J16:AK16) -> 1 | J16: =IF($H16=0%,100%,IFERROR(VLOOKUP($C16+J$6,$C$11:$AK$38,4,FALSE)/$H16,0)) -> 1 | K16: =IFERROR(VLOOKUP($C16+K$6,$C$11:$AK$38,4,FALSE)/$H16,0) -> 0 | L16: =IFERROR(VLOOKUP($C16+L$6,$C$11:$AK$38,4,FALSE)/$H16,0) -> 0 | M16: =IFERROR(VLOOKUP($C16+M$6,$C$11:$AK$38,4,FALSE)/$H16,0) -> 0 | N16: =IFERROR(VLOOKUP($C16+N$6,$C$11:$AK$38,4,FALSE)/$H16,0) -> 0 | O16: =IFERROR(VLOOKUP($C16+O$6,$C$11:$AK$38,4,FALSE)/$H16,0) -> 0 | P16: =IFERROR(VLOOKUP($C16+P$6,$C$11:$AK$38,4,FALSE)/$H16,0) -> 0 | Q16: =IFERROR(VLOOKUP($C16+Q$6,$C$11:$AK$38,4,FALSE)/$H16,0) -> 0 | R16: =IFERROR(VLOOKUP($C16+R$6,$C$11:$AK$38,4,FALSE)/$H16,0) -> 0 | ... AK16: =IFERROR(VLOOKUP($C16+AK$6,$C$11:$AK$38,4,FALSE)/$H16,0) -> 0
B17: =IBNR!F13 -> 2019Q3 | C17: =C18+3 -> 66 | D17: =_xlfn.XLOOKUP($B$8,Paid_DFs!$G$5:$S$5,Paid_DFs!$G13:$S13) -> 1 | E17: =PRODUCT($D$11:$D17) -> 1 | F17: =G17-G18 -> 0 | G17: =1/E17 -> 1 | H17: =1-G17 -> 0 | I17: =SUM(J17:AK17) -> 1 | J17: =IF($H17=0%,100%,IFERROR(VLOOKUP($C17+J$6,$C$11:$AK$38,4,FALSE)/$H17,0)) -> 1 | K17: =IFERROR(VLOOKUP($C17+K$6,$C$11:$AK$38,4,FALSE)/$H17,0) -> 0 | L17: =IFERROR(VLOOKUP($C17+L$6,$C$11:$AK$38,4,FALSE)/$H17,0) -> 0 | M17: =IFERROR(VLOOKUP($C17+M$6,$C$11:$AK$38,4,FALSE)/$H17,0) -> 0 | N17: =IFERROR(VLOOKUP($C17+N$6,$C$11:$AK$38,4,FALSE)/$H17,0) -> 0 | O17: =IFERROR(VLOOKUP($C17+O$6,$C$11:$AK$38,4,FALSE)/$H17,0) -> 0 | P17: =IFERROR(VLOOKUP($C17+P$6,$C$11:$AK$38,4,FALSE)/$H17,0) -> 0 | Q17: =IFERROR(VLOOKUP($C17+Q$6,$C$11:$AK$38,4,FALSE)/$H17,0) -> 0 | R17: =IFERROR(VLOOKUP($C17+R$6,$C$11:$AK$38,4,FALSE)/$H17,0) -> 0 | ... AK17: =IFERROR(VLOOKUP($C17+AK$6,$C$11:$AK$38,4,FALSE)/$H17,0) -> 0
B18: =IBNR!F14 -> 2019Q4 | C18: =C19+3 -> 63 | D18: =_xlfn.XLOOKUP($B$8,Paid_DFs!$G$5:$S$5,Paid_DFs!$G14:$S14) -> 1 | E18: =PRODUCT($D$11:$D18) -> 1 | F18: =G18-G19 -> 0 | G18: =1/E18 -> 1 | H18: =1-G18 -> 0 | I18: =SUM(J18:AK18) -> 1 | J18: =IF($H18=0%,100%,IFERROR(VLOOKUP($C18+J$6,$C$11:$AK$38,4,FALSE)/$H18,0)) -> 1 | K18: =IFERROR(VLOOKUP($C18+K$6,$C$11:$AK$38,4,FALSE)/$H18,0) -> 0 | L18: =IFERROR(VLOOKUP($C18+L$6,$C$11:$AK$38,4,FALSE)/$H18,0) -> 0 | M18: =IFERROR(VLOOKUP($C18+M$6,$C$11:$AK$38,4,FALSE)/$H18,0) -> 0 | N18: =IFERROR(VLOOKUP($C18+N$6,$C$11:$AK$38,4,FALSE)/$H18,0) -> 0 | O18: =IFERROR(VLOOKUP($C18+O$6,$C$11:$AK$38,4,FALSE)/$H18,0) -> 0 | P18: =IFERROR(VLOOKUP($C18+P$6,$C$11:$AK$38,4,FALSE)/$H18,0) -> 0 | Q18: =IFERROR(VLOOKUP($C18+Q$6,$C$11:$AK$38,4,FALSE)/$H18,0) -> 0 | R18: =IFERROR(VLOOKUP($C18+R$6,$C$11:$AK$38,4,FALSE)/$H18,0) -> 0 | ... AK18: =IFERROR(VLOOKUP($C18+AK$6,$C$11:$AK$38,4,FALSE)/$H18,0) -> 0
B19: =IBNR!F15 -> 2020Q1 | C19: =C20+3 -> 60 | D19: =_xlfn.XLOOKUP($B$8,Paid_DFs!$G$5:$S$5,Paid_DFs!$G15:$S15) -> 1 | E19: =PRODUCT($D$11:$D19) -> 1 | F19: =G19-G20 -> 0 | G19: =1/E19 -> 1 | H19: =1-G19 -> 0 | I19: =SUM(J19:AK19) -> 1 | J19: =IF($H19=0%,100%,IFERROR(VLOOKUP($C19+J$6,$C$11:$AK$38,4,FALSE)/$H19,0)) -> 1 | K19: =IFERROR(VLOOKUP($C19+K$6,$C$11:$AK$38,4,FALSE)/$H19,0) -> 0 | L19: =IFERROR(VLOOKUP($C19+L$6,$C$11:$AK$38,4,FALSE)/$H19,0) -> 0 | M19: =IFERROR(VLOOKUP($C19+M$6,$C$11:$AK$38,4,FALSE)/$H19,0) -> 0 | N19: =IFERROR(VLOOKUP($C19+N$6,$C$11:$AK$38,4,FALSE)/$H19,0) -> 0 | O19: =IFERROR(VLOOKUP($C19+O$6,$C$11:$AK$38,4,FALSE)/$H19,0) -> 0 | P19: =IFERROR(VLOOKUP($C19+P$6,$C$11:$AK$38,4,FALSE)/$H19,0) -> 0 | Q19: =IFERROR(VLOOKUP($C19+Q$6,$C$11:$AK$38,4,FALSE)/$H19,0) -> 0 | R19: =IFERROR(VLOOKUP($C19+R$6,$C$11:$AK$38,4,FALSE)/$H19,0) -> 0 | ... AK19: =IFERROR(VLOOKUP($C19+AK$6,$C$11:$AK$38,4,FALSE)/$H19,0) -> 0
B20: =IBNR!F16 -> 2020Q2 | C20: =C21+3 -> 57 | D20: =_xlfn.XLOOKUP($B$8,Paid_DFs!$G$5:$S$5,Paid_DFs!$G16:$S16) -> 1 | E20: =PRODUCT($D$11:$D20) -> 1 | F20: =G20-G21 -> 0 | G20: =1/E20 -> 1 | H20: =1-G20 -> 0 | I20: =SUM(J20:AK20) -> 1 | J20: =IF($H20=0%,100%,IFERROR(VLOOKUP($C20+J$6,$C$11:$AK$38,4,FALSE)/$H20,0)) -> 1 | K20: =IFERROR(VLOOKUP($C20+K$6,$C$11:$AK$38,4,FALSE)/$H20,0) -> 0 | L20: =IFERROR(VLOOKUP($C20+L$6,$C$11:$AK$38,4,FALSE)/$H20,0) -> 0 | M20: =IFERROR(VLOOKUP($C20+M$6,$C$11:$AK$38,4,FALSE)/$H20,0) -> 0 | N20: =IFERROR(VLOOKUP($C20+N$6,$C$11:$AK$38,4,FALSE)/$H20,0) -> 0 | O20: =IFERROR(VLOOKUP($C20+O$6,$C$11:$AK$38,4,FALSE)/$H20,0) -> 0 | P20: =IFERROR(VLOOKUP($C20+P$6,$C$11:$AK$38,4,FALSE)/$H20,0) -> 0 | Q20: =IFERROR(VLOOKUP($C20+Q$6,$C$11:$AK$38,4,FALSE)/$H20,0) -> 0 | R20: =IFERROR(VLOOKUP($C20+R$6,$C$11:$AK$38,4,FALSE)/$H20,0) -> 0 | ... AK20: =IFERROR(VLOOKUP($C20+AK$6,$C$11:$AK$38,4,FALSE)/$H20,0) -> 0
B21: =IBNR!F17 -> 2020Q3 | C21: =C22+3 -> 54 | D21: =_xlfn.XLOOKUP($B$8,Paid_DFs!$G$5:$S$5,Paid_DFs!$G17:$S17) -> 1 | E21: =PRODUCT($D$11:$D21) -> 1 | F21: =G21-G22 -> 0 | G21: =1/E21 -> 1 | H21: =1-G21 -> 0 | I21: =SUM(J21:AK21) -> 1 | J21: =IF($H21=0%,100%,IFERROR(VLOOKUP($C21+J$6,$C$11:$AK$38,4,FALSE)/$H21,0)) -> 1 | K21: =IFERROR(VLOOKUP($C21+K$6,$C$11:$AK$38,4,FALSE)/$H21,0) -> 0 | L21: =IFERROR(VLOOKUP($C21+L$6,$C$11:$AK$38,4,FALSE)/$H21,0) -> 0 | M21: =IFERROR(VLOOKUP($C21+M$6,$C$11:$AK$38,4,FALSE)/$H21,0) -> 0 | N21: =IFERROR(VLOOKUP($C21+N$6,$C$11:$AK$38,4,FALSE)/$H21,0) -> 0 | O21: =IFERROR(VLOOKUP($C21+O$6,$C$11:$AK$38,4,FALSE)/$H21,0) -> 0 | P21: =IFERROR(VLOOKUP($C21+P$6,$C$11:$AK$38,4,FALSE)/$H21,0) -> 0 | Q21: =IFERROR(VLOOKUP($C21+Q$6,$C$11:$AK$38,4,FALSE)/$H21,0) -> 0 | R21: =IFERROR(VLOOKUP($C21+R$6,$C$11:$AK$38,4,FALSE)/$H21,0) -> 0 | ... AK21: =IFERROR(VLOOKUP($C21+AK$6,$C$11:$AK$38,4,FALSE)/$H21,0) -> 0
B22: =IBNR!F18 -> 2020Q4 | C22: =C23+3 -> 51 | D22: =_xlfn.XLOOKUP($B$8,Paid_DFs!$G$5:$S$5,Paid_DFs!$G18:$S18) -> 1 | E22: =PRODUCT($D$11:$D22) -> 1 | F22: =G22-G23 -> 0 | G22: =1/E22 -> 1 | H22: =1-G22 -> 0 | I22: =SUM(J22:AK22) -> 1 | J22: =IF($H22=0%,100%,IFERROR(VLOOKUP($C22+J$6,$C$11:$AK$38,4,FALSE)/$H22,0)) -> 1 | K22: =IFERROR(VLOOKUP($C22+K$6,$C$11:$AK$38,4,FALSE)/$H22,0) -> 0 | L22: =IFERROR(VLOOKUP($C22+L$6,$C$11:$AK$38,4,FALSE)/$H22,0) -> 0 | M22: =IFERROR(VLOOKUP($C22+M$6,$C$11:$AK$38,4,FALSE)/$H22,0) -> 0 | N22: =IFERROR(VLOOKUP($C22+N$6,$C$11:$AK$38,4,FALSE)/$H22,0) -> 0 | O22: =IFERROR(VLOOKUP($C22+O$6,$C$11:$AK$38,4,FALSE)/$H22,0) -> 0 | P22: =IFERROR(VLOOKUP($C22+P$6,$C$11:$AK$38,4,FALSE)/$H22,0) -> 0 | Q22: =IFERROR(VLOOKUP($C22+Q$6,$C$11:$AK$38,4,FALSE)/$H22,0) -> 0 | R22: =IFERROR(VLOOKUP($C22+R$6,$C$11:$AK$38,4,FALSE)/$H22,0) -> 0 | ... AK22: =IFERROR(VLOOKUP($C22+AK$6,$C$11:$AK$38,4,FALSE)/$H22,0) -> 0
... B30: =IBNR!F26 -> 2022Q4 | C30: =C31+3 -> 27 | D30: =_xlfn.XLOOKUP($B$8,Paid_DFs!$G$5:$S$5,Paid_DFs!$G26:$S26) -> 1 | E30: =PRODUCT($D$11:$D30) -> 1.0056648 | F30: =G30-G31 -> 0 | G30: =1/E30 -> 0.99436715 | H30: =1-G30 -> 0.005632855 | I30: =SUM(J30:AK30) -> 1 | J30: =IF($H30=0%,100%,IFERROR(VLOOKUP($C30+J$6,$C$11:$AK$38,4,FALSE)/$H30,0)) -> 0 | K30: =IFERROR(VLOOKUP($C30+K$6,$C$11:$AK$38,4,FALSE)/$H30,0) -> 0 | L30: =IFERROR(VLOOKUP($C30+L$6,$C$11:$AK$38,4,FALSE)/$H30,0) -> 1 | M30: =IFERROR(VLOOKUP($C30+M$6,$C$11:$AK$38,4,FALSE)/$H30,0) -> 0 | N30: =IFERROR(VLOOKUP($C30+N$6,$C$11:$AK$38,4,FALSE)/$H30,0) -> 0 | O30: =IFERROR(VLOOKUP($C30+O$6,$C$11:$AK$38,4,FALSE)/$H30,0) -> 0 | P30: =IFERROR(VLOOKUP($C30+P$6,$C$11:$AK$38,4,FALSE)/$H30,0) -> 0 | Q30: =IFERROR(VLOOKUP($C30+Q$6,$C$11:$AK$38,4,FALSE)/$H30,0) -> 0 | R30: =IFERROR(VLOOKUP($C30+R$6,$C$11:$AK$38,4,FALSE)/$H30,0) -> 0 | ... AK30: =IFERROR(VLOOKUP($C30+AK$6,$C$11:$AK$38,4,FALSE)/$H30,0) -> 0
B31: 2023Q1 | C31: =C32+3 -> 24 | D31: =_xlfn.XLOOKUP($B$8,Paid_DFs!$G$5:$S$5,Paid_DFs!$G27:$S27) -> 1 | E31: =PRODUCT($D$11:$D31) -> 1.0056648 | F31: =G31-G32 -> 0.0014888952 | G31: =1/E31 -> 0.99436715 | H31: =1-G31 -> 0.005632855 | I31: =SUM(J31:AK31) -> 1 | J31: =IF($H31=0%,100%,IFERROR(VLOOKUP($C31+J$6,$C$11:$AK$38,4,FALSE)/$H31,0)) -> 0 | K31: =IFERROR(VLOOKUP($C31+K$6,$C$11:$AK$38,4,FALSE)/$H31,0) -> 0 | L31: =IFERROR(VLOOKUP($C31+L$6,$C$11:$AK$38,4,FALSE)/$H31,0) -> 0 | M31: =IFERROR(VLOOKUP($C31+M$6,$C$11:$AK$38,4,FALSE)/$H31,0) -> 1 | N31: =IFERROR(VLOOKUP($C31+N$6,$C$11:$AK$38,4,FALSE)/$H31,0) -> 0 | O31: =IFERROR(VLOOKUP($C31+O$6,$C$11:$AK$38,4,FALSE)/$H31,0) -> 0 | P31: =IFERROR(VLOOKUP($C31+P$6,$C$11:$AK$38,4,FALSE)/$H31,0) -> 0 | Q31: =IFERROR(VLOOKUP($C31+Q$6,$C$11:$AK$38,4,FALSE)/$H31,0) -> 0 | R31: =IFERROR(VLOOKUP($C31+R$6,$C$11:$AK$38,4,FALSE)/$H31,0) -> 0 | ... AK31: =IFERROR(VLOOKUP($C31+AK$6,$C$11:$AK$38,4,FALSE)/$H31,0) -> 0
B32: 2023Q2 | C32: =C33+3 -> 21 | D32: =_xlfn.XLOOKUP($B$8,Paid_DFs!$G$5:$S$5,Paid_DFs!$G28:$S28) -> 1.0014996 | E32: =PRODUCT($D$11:$D32) -> 1.0071728 | F32: =G32-G33 -> 0.05130935 | G32: =1/E32 -> 0.99287825 | H32: =1-G32 -> 0.0071217502 | I32: =SUM(J32:AK32) -> 1 | J32: =IF($H32=0%,100%,IFERROR(VLOOKUP($C32+J$6,$C$11:$AK$38,4,FALSE)/$H32,0)) -> 0.2090631 | K32: =IFERROR(VLOOKUP($C32+K$6,$C$11:$AK$38,4,FALSE)/$H32,0) -> 0 | L32: =IFERROR(VLOOKUP($C32+L$6,$C$11:$AK$38,4,FALSE)/$H32,0) -> 0 | M32: =IFERROR(VLOOKUP($C32+M$6,$C$11:$AK$38,4,FALSE)/$H32,0) -> 0 | N32: =IFERROR(VLOOKUP($C32+N$6,$C$11:$AK$38,4,FALSE)/$H32,0) -> 0.7909369 | O32: =IFERROR(VLOOKUP($C32+O$6,$C$11:$AK$38,4,FALSE)/$H32,0) -> 0 | P32: =IFERROR(VLOOKUP($C32+P$6,$C$11:$AK$38,4,FALSE)/$H32,0) -> 0 | Q32: =IFERROR(VLOOKUP($C32+Q$6,$C$11:$AK$38,4,FALSE)/$H32,0) -> 0 | R32: =IFERROR(VLOOKUP($C32+R$6,$C$11:$AK$38,4,FALSE)/$H32,0) -> 0 | ... AK32: =IFERROR(VLOOKUP($C32+AK$6,$C$11:$AK$38,4,FALSE)/$H32,0) -> 0
B33: 2023Q3 | C33: =C34+3 -> 18 | D33: =_xlfn.XLOOKUP($B$8,Paid_DFs!$G$5:$S$5,Paid_DFs!$G29:$S29) -> 1.0544935 | E33: =PRODUCT($D$11:$D33) -> 1.0620572 | F33: =G33-G34 -> 0.0099123259 | G33: =1/E33 -> 0.9415689 | H33: =1-G33 -> 0.0584311 | I33: =SUM(J33:AK33) -> 1 | J33: =IF($H33=0%,100%,IFERROR(VLOOKUP($C33+J$6,$C$11:$AK$38,4,FALSE)/$H33,0)) -> 0.87811713 | K33: =IFERROR(VLOOKUP($C33+K$6,$C$11:$AK$38,4,FALSE)/$H33,0) -> 0.025481211 | L33: =IFERROR(VLOOKUP($C33+L$6,$C$11:$AK$38,4,FALSE)/$H33,0) -> 0 | M33: =IFERROR(VLOOKUP($C33+M$6,$C$11:$AK$38,4,FALSE)/$H33,0) -> 0 | N33: =IFERROR(VLOOKUP($C33+N$6,$C$11:$AK$38,4,FALSE)/$H33,0) -> 0 | O33: =IFERROR(VLOOKUP($C33+O$6,$C$11:$AK$38,4,FALSE)/$H33,0) -> 0.096401658 | P33: =IFERROR(VLOOKUP($C33+P$6,$C$11:$AK$38,4,FALSE)/$H33,0) -> 0 | Q33: =IFERROR(VLOOKUP($C33+Q$6,$C$11:$AK$38,4,FALSE)/$H33,0) -> 0 | R33: =IFERROR(VLOOKUP($C33+R$6,$C$11:$AK$38,4,FALSE)/$H33,0) -> 0 | ... AK33: =IFERROR(VLOOKUP($C33+AK$6,$C$11:$AK$38,4,FALSE)/$H33,0) -> 0
B34: 2023Q4 | C34: =C35+3 -> 15 | D34: =_xlfn.XLOOKUP($B$8,Paid_DFs!$G$5:$S$5,Paid_DFs!$G30:$S30) -> 1.0106395 | E34: =PRODUCT($D$11:$D34) -> 1.0733569 | F34: =G34-G35 -> 0.0097221601 | G34: =1/E34 -> 0.93165657 | H34: =1-G34 -> 0.068343426 | I34: =SUM(J34:AK34) -> 1 | J34: =IF($H34=0%,100%,IFERROR(VLOOKUP($C34+J$6,$C$11:$AK$38,4,FALSE)/$H34,0)) -> 0.14503701 | K34: =IFERROR(VLOOKUP($C34+K$6,$C$11:$AK$38,4,FALSE)/$H34,0) -> 0.75075765 | L34: =IFERROR(VLOOKUP($C34+L$6,$C$11:$AK$38,4,FALSE)/$H34,0) -> 0.021785492 | M34: =IFERROR(VLOOKUP($C34+M$6,$C$11:$AK$38,4,FALSE)/$H34,0) -> 0 | N34: =IFERROR(VLOOKUP($C34+N$6,$C$11:$AK$38,4,FALSE)/$H34,0) -> 0 | O34: =IFERROR(VLOOKUP($C34+O$6,$C$11:$AK$38,4,FALSE)/$H34,0) -> 0 | P34: =IFERROR(VLOOKUP($C34+P$6,$C$11:$AK$38,4,FALSE)/$H34,0) -> 0.082419851 | Q34: =IFERROR(VLOOKUP($C34+Q$6,$C$11:$AK$38,4,FALSE)/$H34,0) -> 0 | R34: =IFERROR(VLOOKUP($C34+R$6,$C$11:$AK$38,4,FALSE)/$H34,0) -> 0 | ... AK34: =IFERROR(VLOOKUP($C34+AK$6,$C$11:$AK$38,4,FALSE)/$H34,0) -> 0
B35: 2024Q1 | C35: =C36+3 -> 12 | D35: =_xlfn.XLOOKUP($B$8,Paid_DFs!$G$5:$S$5,Paid_DFs!$G31:$S31) -> 1.0105454 | E35: =PRODUCT($D$11:$D35) -> 1.0846759 | F35: =G35-G36 -> 0.0062616973 | G35: =1/E35 -> 0.92193441 | H35: =1-G35 -> 0.078065586 | I35: =SUM(J35:AK35) -> 1 | J35: =IF($H35=0%,100%,IFERROR(VLOOKUP($C35+J$6,$C$11:$AK$38,4,FALSE)/$H35,0)) -> 0.12453836 | K35: =IFERROR(VLOOKUP($C35+K$6,$C$11:$AK$38,4,FALSE)/$H35,0) -> 0.12697434 | L35: =IFERROR(VLOOKUP($C35+L$6,$C$11:$AK$38,4,FALSE)/$H35,0) -> 0.65725952 | M35: =IFERROR(VLOOKUP($C35+M$6,$C$11:$AK$38,4,FALSE)/$H35,0) -> 0.019072363 | N35: =IFERROR(VLOOKUP($C35+N$6,$C$11:$AK$38,4,FALSE)/$H35,0) -> 0 | O35: =IFERROR(VLOOKUP($C35+O$6,$C$11:$AK$38,4,FALSE)/$H35,0) -> 0 | P35: =IFERROR(VLOOKUP($C35+P$6,$C$11:$AK$38,4,FALSE)/$H35,0) -> 0 | Q35: =IFERROR(VLOOKUP($C35+Q$6,$C$11:$AK$38,4,FALSE)/$H35,0) -> 0.072155417 | R35: =IFERROR(VLOOKUP($C35+R$6,$C$11:$AK$38,4,FALSE)/$H35,0) -> 0 | ... AK35: =IFERROR(VLOOKUP($C35+AK$6,$C$11:$AK$38,4,FALSE)/$H35,0) -> 0
B36: 2024Q2 | C36: =C37+3 -> 9 | D36: =_xlfn.XLOOKUP($B$8,Paid_DFs!$G$5:$S$5,Paid_DFs!$G32:$S32) -> 1.0068384 | E36: =PRODUCT($D$11:$D36) -> 1.0920933 | F36: =G36-G37 -> 0.0051255403 | G36: =1/E36 -> 0.91567272 | H36: =1-G36 -> 0.084327284 | I36: =SUM(J36:AK36) -> 1 | J36: =IF($H36=0%,100%,IFERROR(VLOOKUP($C36+J$6,$C$11:$AK$38,4,FALSE)/$H36,0)) -> 0.074254702 | K36: =IFERROR(VLOOKUP($C36+K$6,$C$11:$AK$38,4,FALSE)/$H36,0) -> 0.1152908 | L36: =IFERROR(VLOOKUP($C36+L$6,$C$11:$AK$38,4,FALSE)/$H36,0) -> 0.11754589 | M36: =IFERROR(VLOOKUP($C36+M$6,$C$11:$AK$38,4,FALSE)/$H36,0) -> 0.60845491 | N36: =IFERROR(VLOOKUP($C36+N$6,$C$11:$AK$38,4,FALSE)/$H36,0) -> 0.01765615 | O36: =IFERROR(VLOOKUP($C36+O$6,$C$11:$AK$38,4,FALSE)/$H36,0) -> 0 | P36: =IFERROR(VLOOKUP($C36+P$6,$C$11:$AK$38,4,FALSE)/$H36,0) -> 0 | Q36: =IFERROR(VLOOKUP($C36+Q$6,$C$11:$AK$38,4,FALSE)/$H36,0) -> 0 | R36: =IFERROR(VLOOKUP($C36+R$6,$C$11:$AK$38,4,FALSE)/$H36,0) -> 0.066797538 | ... AK36: =IFERROR(VLOOKUP($C36+AK$6,$C$11:$AK$38,4,FALSE)/$H36,0) -> 0
B37: 2024Q3 | C37: =C38+3 -> 6 | D37: =_xlfn.XLOOKUP($B$8,Paid_DFs!$G$5:$S$5,Paid_DFs!$G33:$S33) -> 1.0056291 | E37: =PRODUCT($D$11:$D37) -> 1.0982407 | F37: =G37-G38 -> 0.04479796 | G37: =1/E37 -> 0.91054718 | H37: =1-G37 -> 0.089452824 | I37: =SUM(J37:AK37) -> 1 | J37: =IF($H37=0%,100%,IFERROR(VLOOKUP($C37+J$6,$C$11:$AK$38,4,FALSE)/$H37,0)) -> 0.057298809 | K37: =IFERROR(VLOOKUP($C37+K$6,$C$11:$AK$38,4,FALSE)/$H37,0) -> 0.069999996 | L37: =IFERROR(VLOOKUP($C37+L$6,$C$11:$AK$38,4,FALSE)/$H37,0) -> 0.10868478 | M37: =IFERROR(VLOOKUP($C37+M$6,$C$11:$AK$38,4,FALSE)/$H37,0) -> 0.11081065 | N37: =IFERROR(VLOOKUP($C37+N$6,$C$11:$AK$38,4,FALSE)/$H37,0) -> 0.57359117 | O37: =IFERROR(VLOOKUP($C37+O$6,$C$11:$AK$38,4,FALSE)/$H37,0) -> 0.016644474 | P37: =IFERROR(VLOOKUP($C37+P$6,$C$11:$AK$38,4,FALSE)/$H37,0) -> 0 | Q37: =IFERROR(VLOOKUP($C37+Q$6,$C$11:$AK$38,4,FALSE)/$H37,0) -> 0 | R37: =IFERROR(VLOOKUP($C37+R$6,$C$11:$AK$38,4,FALSE)/$H37,0) -> 0 | ... AK37: =IFERROR(VLOOKUP($C37+AK$6,$C$11:$AK$38,4,FALSE)/$H37,0) -> 0
B38: 2024Q4 | C38: =C39+3 -> 3 | D38: =_xlfn.XLOOKUP($B$8,Paid_DFs!$G$5:$S$5,Paid_DFs!$G34:$S34) -> 1.0517447 | E38: =PRODUCT($D$11:$D38) -> 1.1550689 | F38: =G38-G39 -> 0.86574922 | G38: =1/E38 -> 0.86574922 | H38: =1-G38 -> 0.13425078 | I38: =SUM(J38:AK38) -> 1 | J38: =IF($H38=0%,100%,IFERROR(VLOOKUP($C38+J$6,$C$11:$AK$38,4,FALSE)/$H38,0)) -> 0.33368863 | K38: =IFERROR(VLOOKUP($C38+K$6,$C$11:$AK$38,4,FALSE)/$H38,0) -> 0.038178848 | L38: =IFERROR(VLOOKUP($C38+L$6,$C$11:$AK$38,4,FALSE)/$H38,0) -> 0.046641793 | M38: =IFERROR(VLOOKUP($C38+M$6,$C$11:$AK$38,4,FALSE)/$H38,0) -> 0.072417902 | N38: =IFERROR(VLOOKUP($C38+N$6,$C$11:$AK$38,4,FALSE)/$H38,0) -> 0.073834399 | O38: =IFERROR(VLOOKUP($C38+O$6,$C$11:$AK$38,4,FALSE)/$H38,0) -> 0.38219032 | P38: =IFERROR(VLOOKUP($C38+P$6,$C$11:$AK$38,4,FALSE)/$H38,0) -> 0.011090402 | Q38: =IFERROR(VLOOKUP($C38+Q$6,$C$11:$AK$38,4,FALSE)/$H38,0) -> 0 | R38: =IFERROR(VLOOKUP($C38+R$6,$C$11:$AK$38,4,FALSE)/$H38,0) -> 0 | ... AK38: =IFERROR(VLOOKUP($C38+AK$6,$C$11:$AK$38,4,FALSE)/$H38,0) -> 0
B39: Total | H39: =SUM(H11:H38) -> 0.54252418 | J39: =SUM(J11:J38) -> 19.821998 | K39: =SUM(K11:K38) -> 2.1266828 | L39: =SUM(L11:L38) -> 1.9519175 | M39: =SUM(M11:M38) -> 1.8107558 | N39: =SUM(N11:N38) -> 1.4560186 | O39: =SUM(O11:O38) -> 0.49523645 | P39: =SUM(P11:P38) -> 0.093510253 | Q39: =SUM(Q11:Q38) -> 0.072155417 | ... AK39: =SUM(AK11:AK38) -> 0
I41: =1-I38 -> 0 | K41: =F33/H38 -> 0.073834399
I42: 0.019525856
B45: =B8 -> Engineering
J46: Time (in years)
E47: Origin | F47: OCR | G47: IBNR | H47: Claims Provision | I47: Check | J47: =J10 -> 0.12 | K47: =K10 -> 0.38 | L47: =L10 -> 0.62 | M47: =M10 -> 0.88 | N47: =N10 -> 1.12 | O47: =O10 -> 1.38 | P47: =P10 -> 1.62 | Q47: =Q10 -> 1.88 | ... AD47: =AD10 -> 5.12 | AE47: 5.38 | AF47: 5.62 | AG47: 5.88 | AH47: 6.12 | AI47: 6.38 | AJ47: 6.62 | AK47: 6.88
E48: =B11 -> 2018Q1 | F48: =_xlfn.XLOOKUP($B$8,OCR!$D$2:$P$2,OCR!$D4:$P4) -> 600600 | G48: =_xlfn.XLOOKUP($B$8,IBNR!$G$5:$S$5,IBNR!$G7:$S7) -> 3.3892386e-09 | H48: =SUM(F48:G48) -> 600600 | I48: =SUM(J48:AK48) -> 600600 | J48: =$H48*J11 -> 600600 | K48: =$H48*K11 -> 0 | L48: =$H48*L11 -> 0 | M48: =$H48*M11 -> 0 | N48: =$H48*N11 -> 0 | O48: =$H48*O11 -> 0 | P48: =$H48*P11 -> 0 | Q48: =$H48*Q11 -> 0 | ... AK48: =$H48*AK11 -> 0
E49: =B12 -> 2018Q2 | F49: =_xlfn.XLOOKUP($B$8,OCR!$D$2:$P$2,OCR!$D5:$P5) -> 172496.5 | G49: =_xlfn.XLOOKUP($B$8,IBNR!$G$5:$S$5,IBNR!$G8:$S8) -> 2.2090339e-09 | H49: =SUM(F49:G49) -> 172496.5 | I49: =SUM(J49:AK49) -> 172496.5 | J49: =$H49*J12 -> 172496.5 | K49: =$H49*K12 -> 0 | L49: =$H49*L12 -> 0 | M49: =$H49*M12 -> 0 | N49: =$H49*N12 -> 0 | O49: =$H49*O12 -> 0 | P49: =$H49*P12 -> 0 | Q49: =$H49*Q12 -> 0 | ... AK49: =$H49*AK12 -> 0
E50: =B13 -> 2018Q3 | F50: =_xlfn.XLOOKUP($B$8,OCR!$D$2:$P$2,OCR!$D6:$P6) -> 0 | G50: =_xlfn.XLOOKUP($B$8,IBNR!$G$5:$S$5,IBNR!$G9:$S9) -> 0 | H50: =SUM(F50:G50) -> 0 | I50: =SUM(J50:AK50) -> 0 | J50: =$H50*J13 -> 0 | K50: =$H50*K13 -> 0 | L50: =$H50*L13 -> 0 | M50: =$H50*M13 -> 0 | N50: =$H50*N13 -> 0 | O50: =$H50*O13 -> 0 | P50: =$H50*P13 -> 0 | Q50: =$H50*Q13 -> 0 | ... AK50: =$H50*AK13 -> 0
E51: =B14 -> 2018Q4 | F51: =_xlfn.XLOOKUP($B$8,OCR!$D$2:$P$2,OCR!$D7:$P7) -> 0 | G51: =_xlfn.XLOOKUP($B$8,IBNR!$G$5:$S$5,IBNR!$G10:$S10) -> 0 | H51: =SUM(F51:G51) -> 0 | I51: =SUM(J51:AK51) -> 0 | J51: =$H51*J14 -> 0 | K51: =$H51*K14 -> 0 | L51: =$H51*L14 -> 0 | M51: =$H51*M14 -> 0 | N51: =$H51*N14 -> 0 | O51: =$H51*O14 -> 0 | P51: =$H51*P14 -> 0 | Q51: =$H51*Q14 -> 0 | ... AK51: =$H51*AK14 -> 0
E52: =B15 -> 2019Q1 | F52: =_xlfn.XLOOKUP($B$8,OCR!$D$2:$P$2,OCR!$D8:$P8) -> 0 | G52: =_xlfn.XLOOKUP($B$8,IBNR!$G$5:$S$5,IBNR!$G11:$S11) -> 0 | H52: =SUM(F52:G52) -> 0 | I52: =SUM(J52:AK52) -> 0 | J52: =$H52*J15 -> 0 | K52: =$H52*K15 -> 0 | L52: =$H52*L15 -> 0 | M52: =$H52*M15 -> 0 | N52: =$H52*N15 -> 0 | O52: =$H52*O15 -> 0 | P52: =$H52*P15 -> 0 | Q52: =$H52*Q15 -> 0 | ... AK52: =$H52*AK15 -> 0
E53: =B16 -> 2019Q2 | F53: =_xlfn.XLOOKUP($B$8,OCR!$D$2:$P$2,OCR!$D9:$P9) -> 0 | G53: =_xlfn.XLOOKUP($B$8,IBNR!$G$5:$S$5,IBNR!$G12:$S12) -> 0 | H53: =SUM(F53:G53) -> 0 | I53: =SUM(J53:AK53) -> 0 | J53: =$H53*J16 -> 0 | K53: =$H53*K16 -> 0 | L53: =$H53*L16 -> 0 | M53: =$H53*M16 -> 0 | N53: =$H53*N16 -> 0 | O53: =$H53*O16 -> 0 | P53: =$H53*P16 -> 0 | Q53: =$H53*Q16 -> 0 | ... AK53: =$H53*AK16 -> 0
E54: =B17 -> 2019Q3 | F54: =_xlfn.XLOOKUP($B$8,OCR!$D$2:$P$2,OCR!$D10:$P10) -> 0 | G54: =_xlfn.XLOOKUP($B$8,IBNR!$G$5:$S$5,IBNR!$G13:$S13) -> 0 | H54: =SUM(F54:G54) -> 0 | I54: =SUM(J54:AK54) -> 0 | J54: =$H54*J17 -> 0 | K54: =$H54*K17 -> 0 | L54: =$H54*L17 -> 0 | M54: =$H54*M17 -> 0 | N54: =$H54*N17 -> 0 | O54: =$H54*O17 -> 0 | P54: =$H54*P17 -> 0 | Q54: =$H54*Q17 -> 0 | ... AK54: =$H54*AK17 -> 0
E55: =B18 -> 2019Q4 | F55: =_xlfn.XLOOKUP($B$8,OCR!$D$2:$P$2,OCR!$D11:$P11) -> 1142603 | G55: =_xlfn.XLOOKUP($B$8,IBNR!$G$5:$S$5,IBNR!$G14:$S14) -> 0 | H55: =SUM(F55:G55) -> 1142603 | I55: =SUM(J55:AK55) -> 1142603 | J55: =$H55*J18 -> 1142603 | K55: =$H55*K18 -> 0 | L55: =$H55*L18 -> 0 | M55: =$H55*M18 -> 0 | N55: =$H55*N18 -> 0 | O55: =$H55*O18 -> 0 | P55: =$H55*P18 -> 0 | Q55: =$H55*Q18 -> 0 | ... AK55: =$H55*AK18 -> 0
E56: =B19 -> 2020Q1 | F56: =_xlfn.XLOOKUP($B$8,OCR!$D$2:$P$2,OCR!$D12:$P12) -> 10386638 | G56: =_xlfn.XLOOKUP($B$8,IBNR!$G$5:$S$5,IBNR!$G15:$S15) -> 0 | H56: =SUM(F56:G56) -> 10386638 | I56: =SUM(J56:AK56) -> 10386638 | J56: =$H56*J19 -> 10386638 | K56: =$H56*K19 -> 0 | L56: =$H56*L19 -> 0 | M56: =$H56*M19 -> 0 | N56: =$H56*N19 -> 0 | O56: =$H56*O19 -> 0 | P56: =$H56*P19 -> 0 | Q56: =$H56*Q19 -> 0 | ... AK56: =$H56*AK19 -> 0
E57: =B20 -> 2020Q2 | F57: =_xlfn.XLOOKUP($B$8,OCR!$D$2:$P$2,OCR!$D13:$P13) -> 0 | G57: =_xlfn.XLOOKUP($B$8,IBNR!$G$5:$S$5,IBNR!$G16:$S16) -> 0 | H57: =SUM(F57:G57) -> 0 | I57: =SUM(J57:AK57) -> 0 | J57: =$H57*J20 -> 0 | K57: =$H57*K20 -> 0 | L57: =$H57*L20 -> 0 | M57: =$H57*M20 -> 0 | N57: =$H57*N20 -> 0 | O57: =$H57*O20 -> 0 | P57: =$H57*P20 -> 0 | Q57: =$H57*Q20 -> 0 | ... AK57: =$H57*AK20 -> 0
E58: =B21 -> 2020Q3 | F58: =_xlfn.XLOOKUP($B$8,OCR!$D$2:$P$2,OCR!$D14:$P14) -> 0 | G58: =_xlfn.XLOOKUP($B$8,IBNR!$G$5:$S$5,IBNR!$G17:$S17) -> 0 | H58: =SUM(F58:G58) -> 0 | I58: =SUM(J58:AK58) -> 0 | J58: =$H58*J21 -> 0 | K58: =$H58*K21 -> 0 | L58: =$H58*L21 -> 0 | M58: =$H58*M21 -> 0 | N58: =$H58*N21 -> 0 | O58: =$H58*O21 -> 0 | P58: =$H58*P21 -> 0 | Q58: =$H58*Q21 -> 0 | ... AK58: =$H58*AK21 -> 0
E59: =B22 -> 2020Q4 | F59: =_xlfn.XLOOKUP($B$8,OCR!$D$2:$P$2,OCR!$D15:$P15) -> 2553160.5 | G59: =_xlfn.XLOOKUP($B$8,IBNR!$G$5:$S$5,IBNR!$G18:$S18) -> 0 | H59: =SUM(F59:G59) -> 2553160.5 | I59: =SUM(J59:AK59) -> 2553160.5 | J59: =$H59*J22 -> 2553160.5 | K59: =$H59*K22 -> 0 | L59: =$H59*L22 -> 0 | M59: =$H59*M22 -> 0 | N59: =$H59*N22 -> 0 | O59: =$H59*O22 -> 0 | P59: =$H59*P22 -> 0 | Q59: =$H59*Q22 -> 0 | ... AK59: =$H59*AK22 -> 0
... E67: =B30 -> 2022Q4 | F67: =_xlfn.XLOOKUP($B$8,OCR!$D$2:$P$2,OCR!$D23:$P23) -> 2903551.2 | G67: =_xlfn.XLOOKUP($B$8,IBNR!$G$5:$S$5,IBNR!$G26:$S26) -> 47866.024 | H67: =SUM(F67:G67) -> 2951417.2 | I67: =SUM(J67:AK67) -> 2951417.2 | J67: =$H67*J30 -> 0 | K67: =$H67*K30 -> 0 | L67: =$H67*L30 -> 2951417.2 | M67: =$H67*M30 -> 0 | N67: =$H67*N30 -> 0 | O67: =$H67*O30 -> 0 | P67: =$H67*P30 -> 0 | Q67: =$H67*Q30 -> 0 | ... AK67: =$H67*AK30 -> 0
E68: 2023Q1 | F68: =_xlfn.XLOOKUP($B$8,OCR!$D$2:$P$2,OCR!$D24:$P24) -> 2326500 | G68: =_xlfn.XLOOKUP($B$8,IBNR!$G$5:$S$5,IBNR!$G27:$S27) -> 46190.455 | H68: =SUM(F68:G68) -> 2372690.5 | I68: =SUM(J68:AK68) -> 2372690.5 | J68: =$H68*J31 -> 0 | K68: =$H68*K31 -> 0 | L68: =$H68*L31 -> 0 | M68: =$H68*M31 -> 2372690.5 | N68: =$H68*N31 -> 0 | O68: =$H68*O31 -> 0 | P68: =$H68*P31 -> 0 | Q68: =$H68*Q31 -> 0 | ... AK68: =$H68*AK31 -> 0
E69: 2023Q2 | F69: =_xlfn.XLOOKUP($B$8,OCR!$D$2:$P$2,OCR!$D25:$P25) -> 3300000 | G69: =_xlfn.XLOOKUP($B$8,IBNR!$G$5:$S$5,IBNR!$G28:$S28) -> 80888.111 | H69: =SUM(F69:G69) -> 3380888.1 | I69: =SUM(J69:AK69) -> 3380888.1 | J69: =$H69*J32 -> 706818.96 | K69: =$H69*K32 -> 0 | L69: =$H69*L32 -> 0 | M69: =$H69*M32 -> 0 | N69: =$H69*N32 -> 2674069.1 | O69: =$H69*O32 -> 0 | P69: =$H69*P32 -> 0 | Q69: =$H69*Q32 -> 0 | ... AK69: =$H69*AK32 -> 0
E70: 2023Q3 | F70: =_xlfn.XLOOKUP($B$8,OCR!$D$2:$P$2,OCR!$D26:$P26) -> 110000 | G70: =_xlfn.XLOOKUP($B$8,IBNR!$G$5:$S$5,IBNR!$G29:$S29) -> 356090.9 | H70: =SUM(F70:G70) -> 466090.9 | I70: =SUM(J70:AK70) -> 466090.9 | J70: =$H70*J33 -> 409282.4 | K70: =$H70*K33 -> 11876.56 | L70: =$H70*L33 -> 0 | M70: =$H70*M33 -> 0 | N70: =$H70*N33 -> 0 | O70: =$H70*O33 -> 44931.935 | P70: =$H70*P33 -> 0 | Q70: =$H70*Q33 -> 0 | ... AK70: =$H70*AK33 -> 0
E71: 2023Q4 | F71: =_xlfn.XLOOKUP($B$8,OCR!$D$2:$P$2,OCR!$D27:$P27) -> 0 | G71: =_xlfn.XLOOKUP($B$8,IBNR!$G$5:$S$5,IBNR!$G30:$S30) -> 293299.38 | H71: =SUM(F71:G71) -> 293299.38 | I71: =SUM(J71:AK71) -> 293299.38 | J71: =$H71*J34 -> 42539.264 | K71: =$H71*K34 -> 220196.75 | L71: =$H71*L34 -> 6389.6715 | M71: =$H71*M34 -> 0 | N71: =$H71*N34 -> 0 | O71: =$H71*O34 -> 0 | P71: =$H71*P34 -> 24173.691 | Q71: =$H71*Q34 -> 0 | ... AK71: =$H71*AK34 -> 0
E72: 2024Q1 | F72: =_xlfn.XLOOKUP($B$8,OCR!$D$2:$P$2,OCR!$D28:$P28) -> 1540000 | G72: =_xlfn.XLOOKUP($B$8,IBNR!$G$5:$S$5,IBNR!$G31:$S31) -> 1356654.8 | H72: =SUM(F72:G72) -> 2896654.8 | I72: =SUM(J72:AK72) -> 2896654.8 | J72: =$H72*J35 -> 360744.64 | K72: =$H72*K35 -> 367800.82 | L72: =$H72*L35 -> 1903854 | M72: =$H72*M35 -> 55246.052 | N72: =$H72*N35 -> 0 | O72: =$H72*O35 -> 0 | P72: =$H72*P35 -> 0 | Q72: =$H72*Q35 -> 209009.34 | ... AK72: =$H72*AK35 -> 0
E73: 2024Q2 | F73: =_xlfn.XLOOKUP($B$8,OCR!$D$2:$P$2,OCR!$D29:$P29) -> 36408319 | G73: =_xlfn.XLOOKUP($B$8,IBNR!$G$5:$S$5,IBNR!$G32:$S32) -> 1469955.8 | H73: =SUM(F73:G73) -> 37878275 | I73: =SUM(J73:AK73) -> 37878275 | J73: =$H73*J36 -> 2812640 | K73: =$H73*K36 -> 4367016.7 | L73: =$H73*L36 -> 4452435.7 | M73: =$H73*M36 -> 23047223 | N73: =$H73*N36 -> 668784.52 | O73: =$H73*O36 -> 0 | P73: =$H73*P36 -> 0 | Q73: =$H73*Q36 -> 0 | ... AK73: =$H73*AK36 -> 0
E74: 2024Q3 | F74: =_xlfn.XLOOKUP($B$8,OCR!$D$2:$P$2,OCR!$D30:$P30) -> 5500000 | G74: =_xlfn.XLOOKUP($B$8,IBNR!$G$5:$S$5,IBNR!$G33:$S33) -> 1562894.5 | H74: =SUM(F74:G74) -> 7062894.5 | I74: =SUM(J74:AK74) -> 7062894.5 | J74: =$H74*J37 -> 404695.44 | K74: =$H74*K37 -> 494402.58 | L74: =$H74*L37 -> 767629.1 | M74: =$H74*M37 -> 782643.95 | N74: =$H74*N37 -> 4051213.9 | O74: =$H74*O37 -> 117558.16 | P74: =$H74*P37 -> 0 | Q74: =$H74*Q37 -> 0 | ... AK74: =$H74*AK37 -> 0
E75: 2024Q4 | F75: =_xlfn.XLOOKUP($B$8,OCR!$D$2:$P$2,OCR!$D31:$P31) -> 9109304.6 | G75: =_xlfn.XLOOKUP($B$8,IBNR!$G$5:$S$5,IBNR!$G34:$S34) -> 2374900.1 | H75: =SUM(F75:G75) -> 11484205 | I75: =SUM(J75:AK75) -> 11484205 | J75: =$H75*J38 -> 3832148.6 | K75: =$H75*K38 -> 438453.71 | L75: =$H75*L38 -> 535643.9 | M75: =$H75*M38 -> 831662.01 | N75: =$H75*N38 -> 847929.35 | O75: =$H75*O38 -> 4389151.9 | P75: =$H75*P38 -> 127364.45 | Q75: =$H75*Q38 -> 0 | ... AK75: =$H75*AK38 -> 0
E76: =B39 -> Total | F76: =SUM(F48:F75) -> 1.1501912e+08 | G76: =SUM(G48:G75) -> 7700615.5 | H76: =SUM(F76:G76) -> 1.2271974e+08 | I76: =SUM(J76:AK76) -> 1.2271974e+08 | J76: =SUM(J48:J75) -> 54906401 | K76: =SUM(K48:K75) -> 13495538 | L76: =SUM(L48:L75) -> 10617370 | M76: =SUM(M48:M75) -> 27089465 | N76: =SUM(N48:N75) -> 8241996.9 | O76: =SUM(O48:O75) -> 4551642 | P76: =SUM(P48:P75) -> 151538.14 | Q76: =SUM(Q48:Q75) -> 209009.34 | ... AK76: =SUM(AK48:AK75) -> 0
I77: =ROUNDDOWN(I76,0)=ROUNDDOWN(H76,0) -> TRUE
L80: ‹

Sheet FD
J3: 2025 | K3: 2025 | L3: 2025 | M3: 2025 | N3: =J3+1 -> 2026 | O3: =K3+1 -> 2026 | P3: =L3+1 -> 2026 | Q3: =M3+1 -> 2026 | R3: =N3+1 -> 2027 | S3: =O3+1 -> 2027 | T3: =P3+1 -> 2027 | U3: =Q3+1 -> 2027 | ... AK3: =AG3+1 -> 2031
J4: Q1 | K4: Q2 | L4: Q3 | M4: Q4 | N4: Q1 | O4: Q2 | P4: Q3 | Q4: Q4 | R4: Q1 | S4: Q2 | T4: Q3 | U4: Q4 | V4: Q1 | W4: Q2 | X4: Q3 | Y4: Q4 | Z4: Q1 | AA4: Q2 | AB4: Q3 | AC4: Q4 | AD4: Q1 | AE4: Q2 | AF4: Q3 | AG4: Q4 | AH4: Q1 | AI4: Q2 | AJ4: Q3 | AK4: Q4
J5: =J4&"-"&J3 -> Q1-2025 | K5: =K4&"-"&K3 -> Q2-2025 | L5: =L4&"-"&L3 -> Q3-2025 | M5: =M4&"-"&M3 -> Q4-2025 | N5: =N4&"-"&N3 -> Q1-2026 | O5: =O4&"-"&O3 -> Q2-2026 | P5: =P4&"-"&P3 -> Q3-2026 | Q5: =Q4&"-"&Q3 -> Q4-2026 | ... AK5: =AK4&"-"&AK3 -> Q4-2031
H6: Payments in | J6: 3 | K6: =J6+3 -> 6 | L6: =K6+3 -> 9 | M6: =L6+3 -> 12 | N6: =M6+3 -> 15 | O6: =N6+3 -> 18 | P6: =O6+3 -> 21 | Q6: =P6+3 -> 24 | R6: =Q6+3 -> 27 | ... AK6: =AJ6+3 -> 84
K7: =K10-J10 -> 0.26 | L7: =L10-K10 -> 0.24 | M7: =M10-L10 -> 0.26 | N7: =N10-M10 -> 0.24 | O7: =O10-N10 -> 0.26 | P7: =P10-O10 -> 0.24 | Q7: =Q10-P10 -> 0.26 | R7: =R10-Q10 -> 0.24 | ... AK7: =AK10-AJ10 -> 0.26
B8: Fire Domestic | K8: =SUM(J10:K10) -> 0.5 | L8: =SUM(K10:L10) -> 1 | M8: =SUM(L10:M10) -> 1.5 | N8: =SUM(M10:N10) -> 2 | O8: =SUM(N10:O10) -> 2.5 | P8: =SUM(O10:P10) -> 3 | Q8: =SUM(P10:Q10) -> 3.5 | R8: =SUM(Q10:R10) -> 4 | ... AK8: =SUM(AJ10:AK10) -> 13.5
J9: Time (in years)
B10: Origin | C10: Age | D10: Paid DF's | E10: Cumulative Development Factors | F10: Incremental Payments | G10: Cumulative Payments | H10: Expected Unpaid % | I10: Check | J10: 0.12 | K10: 0.38 | L10: 0.62 | M10: 0.88 | N10: 1.12 | O10: 1.38 | P10: 1.62 | Q10: 1.88 | R10: 2.12 | S10: 2.38 | T10: 2.62 | U10: 2.88 | V10: 3.12 | W10: 3.38 | X10: 3.62 | Y10: 3.88 | Z10: 4.12 | AA10: 4.38 | AB10: 4.62 | AC10: 4.88 | AD10: 5.12 | AE10: 5.38 | AF10: 5.62 | AG10: 5.88 | AH10: 6.12 | AI10: 6.38 | AJ10: 6.62 | AK10: 6.88
B11: =IBNR!F7 -> 2018Q1 | C11: =C12+3 -> 84 | D11: =_xlfn.XLOOKUP($B$8,Paid_DFs!$G$5:$S$5,Paid_DFs!$G7:$S7) -> 1 | E11: =PRODUCT($D$11:$D11) -> 1 | F11: =G11-G12 -> 0 | G11: =1/E11 -> 1 | H11: =1-G11 -> 0 | I11: =SUM(J11:AK11) -> 1 | J11: =IF($H11=0%,100%,IFERROR(VLOOKUP($C11+J$6,$C$11:$AK$38,4,FALSE)/$H11,0)) -> 1 | K11: =IFERROR(VLOOKUP($C11+K$6,$C$11:$AK$38,4,FALSE)/$H11,0) -> 0 | L11: =IFERROR(VLOOKUP($C11+L$6,$C$11:$AK$38,4,FALSE)/$H11,0) -> 0 | M11: =IFERROR(VLOOKUP($C11+M$6,$C$11:$AK$38,4,FALSE)/$H11,0) -> 0 | N11: =IFERROR(VLOOKUP($C11+N$6,$C$11:$AK$38,4,FALSE)/$H11,0) -> 0 | O11: =IFERROR(VLOOKUP($C11+O$6,$C$11:$AK$38,4,FALSE)/$H11,0) -> 0 | P11: =IFERROR(VLOOKUP($C11+P$6,$C$11:$AK$38,4,FALSE)/$H11,0) -> 0 | Q11: =IFERROR(VLOOKUP($C11+Q$6,$C$11:$AK$38,4,FALSE)/$H11,0) -> 0 | R11: =IFERROR(VLOOKUP($C11+R$6,$C$11:$AK$38,4,FALSE)/$H11,0) -> 0 | ... AK11: =IFERROR(VLOOKUP($C11+AK$6,$C$11:$AK$38,4,FALSE)/$H11,0) -> 0
B12: =IBNR!F8 -> 2018Q2 | C12: =C13+3 -> 81 | D12: =_xlfn.XLOOKUP($B$8,Paid_DFs!$G$5:$S$5,Paid_DFs!$G8:$S8) -> 1 | E12: =PRODUCT($D$11:$D12) -> 1 | F12: =G12-G13 -> 0 | G12: =1/E12 -> 1 | H12: =1-G12 -> 0 | I12: =SUM(J12:AK12) -> 1 | J12: =IF($H12=0%,100%,IFERROR(VLOOKUP($C12+J$6,$C$11:$AK$38,4,FALSE)/$H12,0)) -> 1 | K12: =IFERROR(VLOOKUP($C12+K$6,$C$11:$AK$38,4,FALSE)/$H12,0) -> 0 | L12: =IFERROR(VLOOKUP($C12+L$6,$C$11:$AK$38,4,FALSE)/$H12,0) -> 0 | M12: =IFERROR(VLOOKUP($C12+M$6,$C$11:$AK$38,4,FALSE)/$H12,0) -> 0 | N12: =IFERROR(VLOOKUP($C12+N$6,$C$11:$AK$38,4,FALSE)/$H12,0) -> 0 | O12: =IFERROR(VLOOKUP($C12+O$6,$C$11:$AK$38,4,FALSE)/$H12,0) -> 0 | P12: =IFERROR(VLOOKUP($C12+P$6,$C$11:$AK$38,4,FALSE)/$H12,0) -> 0 | Q12: =IFERROR(VLOOKUP($C12+Q$6,$C$11:$AK$38,4,FALSE)/$H12,0) -> 0 | R12: =IFERROR(VLOOKUP($C12+R$6,$C$11:$AK$38,4,FALSE)/$H12,0) -> 0 | ... AK12: =IFERROR(VLOOKUP($C12+AK$6,$C$11:$AK$38,4,FALSE)/$H12,0) -> 0
B13: =IBNR!F9 -> 2018Q3 | C13: =C14+3 -> 78 | D13: =_xlfn.XLOOKUP($B$8,Paid_DFs!$G$5:$S$5,Paid_DFs!$G9:$S9) -> 1 | E13: =PRODUCT($D$11:$D13) -> 1 | F13: =G13-G14 -> 0 | G13: =1/E13 -> 1 | H13: =1-G13 -> 0 | I13: =SUM(J13:AK13) -> 1 | J13: =IF($H13=0%,100%,IFERROR(VLOOKUP($C13+J$6,$C$11:$AK$38,4,FALSE)/$H13,0)) -> 1 | K13: =IFERROR(VLOOKUP($C13+K$6,$C$11:$AK$38,4,FALSE)/$H13,0) -> 0 | L13: =IFERROR(VLOOKUP($C13+L$6,$C$11:$AK$38,4,FALSE)/$H13,0) -> 0 | M13: =IFERROR(VLOOKUP($C13+M$6,$C$11:$AK$38,4,FALSE)/$H13,0) -> 0 | N13: =IFERROR(VLOOKUP($C13+N$6,$C$11:$AK$38,4,FALSE)/$H13,0) -> 0 | O13: =IFERROR(VLOOKUP($C13+O$6,$C$11:$AK$38,4,FALSE)/$H13,0) -> 0 | P13: =IFERROR(VLOOKUP($C13+P$6,$C$11:$AK$38,4,FALSE)/$H13,0) -> 0 | Q13: =IFERROR(VLOOKUP($C13+Q$6,$C$11:$AK$38,4,FALSE)/$H13,0) -> 0 | R13: =IFERROR(VLOOKUP($C13+R$6,$C$11:$AK$38,4,FALSE)/$H13,0) -> 0 | ... AK13: =IFERROR(VLOOKUP($C13+AK$6,$C$11:$AK$38,4,FALSE)/$H13,0) -> 0
B14: =IBNR!F10 -> 2018Q4 | C14: =C15+3 -> 75 | D14: =_xlfn.XLOOKUP($B$8,Paid_DFs!$G$5:$S$5,Paid_DFs!$G10:$S10) -> 1 | E14: =PRODUCT($D$11:$D14) -> 1 | F14: =G14-G15 -> 0 | G14: =1/E14 -> 1 | H14: =1-G14 -> 0 | I14: =SUM(J14:AK14) -> 1 | J14: =IF($H14=0%,100%,IFERROR(VLOOKUP($C14+J$6,$C$11:$AK$38,4,FALSE)/$H14,0)) -> 1 | K14: =IFERROR(VLOOKUP($C14+K$6,$C$11:$AK$38,4,FALSE)/$H14,0) -> 0 | L14: =IFERROR(VLOOKUP($C14+L$6,$C$11:$AK$38,4,FALSE)/$H14,0) -> 0 | M14: =IFERROR(VLOOKUP($C14+M$6,$C$11:$AK$38,4,FALSE)/$H14,0) -> 0 | N14: =IFERROR(VLOOKUP($C14+N$6,$C$11:$AK$38,4,FALSE)/$H14,0) -> 0 | O14: =IFERROR(VLOOKUP($C14+O$6,$C$11:$AK$38,4,FALSE)/$H14,0) -> 0 | P14: =IFERROR(VLOOKUP($C14+P$6,$C$11:$AK$38,4,FALSE)/$H14,0) -> 0 | Q14: =IFERROR(VLOOKUP($C14+Q$6,$C$11:$AK$38,4,FALSE)/$H14,0) -> 0 | R14: =IFERROR(VLOOKUP($C14+R$6,$C$11:$AK$38,4,FALSE)/$H14,0) -> 0 | ... AK14: =IFERROR(VLOOKUP($C14+AK$6,$C$11:$AK$38,4,FALSE)/$H14,0) -> 0
B15: =IBNR!F11 -> 2019Q1 | C15: =C16+3 -> 72 | D15: =_xlfn.XLOOKUP($B$8,Paid_DFs!$G$5:$S$5,Paid_DFs!$G11:$S11) -> 1 | E15: =PRODUCT($D$11:$D15) -> 1 | F15: =G15-G16 -> 0 | G15: =1/E15 -> 1 | H15: =1-G15 -> 0 | I15: =SUM(J15:AK15) -> 1 | J15: =IF($H15=0%,100%,IFERROR(VLOOKUP($C15+J$6,$C$11:$AK$38,4,FALSE)/$H15,0)) -> 1 | K15: =IFERROR(VLOOKUP($C15+K$6,$C$11:$AK$38,4,FALSE)/$H15,0) -> 0 | L15: =IFERROR(VLOOKUP($C15+L$6,$C$11:$AK$38,4,FALSE)/$H15,0) -> 0 | M15: =IFERROR(VLOOKUP($C15+M$6,$C$11:$AK$38,4,FALSE)/$H15,0) -> 0 | N15: =IFERROR(VLOOKUP($C15+N$6,$C$11:$AK$38,4,FALSE)/$H15,0) -> 0 | O15: =IFERROR(VLOOKUP($C15+O$6,$C$11:$AK$38,4,FALSE)/$H15,0) -> 0 | P15: =IFERROR(VLOOKUP($C15+P$6,$C$11:$AK$38,4,FALSE)/$H15,0) -> 0 | Q15: =IFERROR(VLOOKUP($C15+Q$6,$C$11:$AK$38,4,FALSE)/$H15,0) -> 0 | R15: =IFERROR(VLOOKUP($C15+R$6,$C$11:$AK$38,4,FALSE)/$H15,0) -> 0 | ... AK15: =IFERROR(VLOOKUP($C15+AK$6,$C$11:$AK$38,4,FALSE)/$H15,0) -> 0
B16: =IBNR!F12 -> 2019Q2 | C16: =C17+3 -> 69 | D16: =_xlfn.XLOOKUP($B$8,Paid_DFs!$G$5:$S$5,Paid_DFs!$G12:$S12) -> 1 | E16: =PRODUCT($D$11:$D16) -> 1 | F16: =G16-G17 -> 0 | G16: =1/E16 -> 1 | H16: =1-G16 -> 0 | I16: =SUM(J16:AK16) -> 1 | J16: =IF($H16=0%,100%,IFERROR(VLOOKUP($C16+J$6,$C$11:$AK$38,4,FALSE)/$H16,0)) -> 1 | K16: =IFERROR(VLOOKUP($C16+K$6,$C$11:$AK$38,4,FALSE)/$H16,0) -> 0 | L16: =IFERROR(VLOOKUP($C16+L$6,$C$11:$AK$38,4,FALSE)/$H16,0) -> 0 | M16: =IFERROR(VLOOKUP($C16+M$6,$C$11:$AK$38,4,FALSE)/$H16,0) -> 0 | N16: =IFERROR(VLOOKUP($C16+N$6,$C$11:$AK$38,4,FALSE)/$H16,0) -> 0 | O16: =IFERROR(VLOOKUP($C16+O$6,$C$11:$AK$38,4,FALSE)/$H16,0) -> 0 | P16: =IFERROR(VLOOKUP($C16+P$6,$C$11:$AK$38,4,FALSE)/$H16,0) -> 0 | Q16: =IFERROR(VLOOKUP($C16+Q$6,$C$11:$AK$38,4,FALSE)/$H16,0) -> 0 | R16: =IFERROR(VLOOKUP($C16+R$6,$C$11:$AK$38,4,FALSE)/$H16,0) -> 0 | ... AK16: =IFERROR(VLOOKUP($C16+AK$6,$C$11:$AK$38,4,FALSE)/$H16,0) -> 0
B17: =IBNR!F13 -> 2019Q3 | C17: =C18+3 -> 66 | D17: =_xlfn.XLOOKUP($B$8,Paid_DFs!$G$5:$S$5,Paid_DFs!$G13:$S13) -> 1 | E17: =PRODUCT($D$11:$D17) -> 1 | F17: =G17-G18 -> 0 | G17: =1/E17 -> 1 | H17: =1-G17 -> 0 | I17: =SUM(J17:AK17) -> 1 | J17: =IF($H17=0%,100%,IFERROR(VLOOKUP($C17+J$6,$C$11:$AK$38,4,FALSE)/$H17,0)) -> 1 | K17: =IFERROR(VLOOKUP($C17+K$6,$C$11:$AK$38,4,FALSE)/$H17,0) -> 0 | L17: =IFERROR(VLOOKUP($C17+L$6,$C$11:$AK$38,4,FALSE)/$H17,0) -> 0 | M17: =IFERROR(VLOOKUP($C17+M$6,$C$11:$AK$38,4,FALSE)/$H17,0) -> 0 | N17: =IFERROR(VLOOKUP($C17+N$6,$C$11:$AK$38,4,FALSE)/$H17,0) -> 0 | O17: =IFERROR(VLOOKUP($C17+O$6,$C$11:$AK$38,4,FALSE)/$H17,0) -> 0 | P17: =IFERROR(VLOOKUP($C17+P$6,$C$11:$AK$38,4,FALSE)/$H17,0) -> 0 | Q17: =IFERROR(VLOOKUP($C17+Q$6,$C$11:$AK$38,4,FALSE)/$H17,0) -> 0 | R17: =IFERROR(VLOOKUP($C17+R$6,$C$11:$AK$38,4,FALSE)/$H17,0) -> 0 | ... AK17: =IFERROR(VLOOKUP($C17+AK$6,$C$11:$AK$38,4,FALSE)/$H17,0) -> 0
B18: =IBNR!F14 -> 2019Q4 | C18: =C19+3 -> 63 | D18: =_xlfn.XLOOKUP($B$8,Paid_DFs!$G$5:$S$5,Paid_DFs!$G14:$S14) -> 1 | E18: =PRODUCT($D$11:$D18) -> 1 | F18: =G18-G19 -> 0 | G18: =1/E18 -> 1 | H18: =1-G18 -> 0 | I18: =SUM(J18:AK18) -> 1 | J18: =IF($H18=0%,100%,IFERROR(VLOOKUP($C18+J$6,$C$11:$AK$38,4,FALSE)/$H18,0)) -> 1 | K18: =IFERROR(VLOOKUP($C18+K$6,$C$11:$AK$38,4,FALSE)/$H18,0) -> 0 | L18: =IFERROR(VLOOKUP($C18+L$6,$C$11:$AK$38,4,FALSE)/$H18,0) -> 0 | M18: =IFERROR(VLOOKUP($C18+M$6,$C$11:$AK$38,4,FALSE)/$H18,0) -> 0 | N18: =IFERROR(VLOOKUP($C18+N$6,$C$11:$AK$38,4,FALSE)/$H18,0) -> 0 | O18: =IFERROR(VLOOKUP($C18+O$6,$C$11:$AK$38,4,FALSE)/$H18,0) -> 0 | P18: =IFERROR(VLOOKUP($C18+P$6,$C$11:$AK$38,4,FALSE)/$H18,0) -> 0 | Q18: =IFERROR(VLOOKUP($C18+Q$6,$C$11:$AK$38,4,FALSE)/$H18,0) -> 0 | R18: =IFERROR(VLOOKUP($C18+R$6,$C$11:$AK$38,4,FALSE)/$H18,0) -> 0 | ... AK18: =IFERROR(VLOOKUP($C18+AK$6,$C$11:$AK$38,4,FALSE)/$H18,0) -> 0
B19: =IBNR!F15 -> 2020Q1 | C19: =C20+3 -> 60 | D19: =_xlfn.XLOOKUP($B$8,Paid_DFs!$G$5:$S$5,Paid_DFs!$G15:$S15) -> 1 | E19: =PRODUCT($D$11:$D19) -> 1 | F19: =G19-G20 -> 0 | G19: =1/E19 -> 1 | H19: =1-G19 -> 0 | I19: =SUM(J19:AK19) -> 1 | J19: =IF($H19=0%,100%,IFERROR(VLOOKUP($C19+J$6,$C$11:$AK$38,4,FALSE)/$H19,0)) -> 1 | K19: =IFERROR(VLOOKUP($C19+K$6,$C$11:$AK$38,4,FALSE)/$H19,0) -> 0 | L19: =IFERROR(VLOOKUP($C19+L$6,$C$11:$AK$38,4,FALSE)/$H19,0) -> 0 | M19: =IFERROR(VLOOKUP($C19+M$6,$C$11:$AK$38,4,FALSE)/$H19,0) -> 0 | N19: =IFERROR(VLOOKUP($C19+N$6,$C$11:$AK$38,4,FALSE)/$H19,0) -> 0 | O19: =IFERROR(VLOOKUP($C19+O$6,$C$11:$AK$38,4,FALSE)/$H19,0) -> 0 | P19: =IFERROR(VLOOKUP($C19+P$6,$C$11:$AK$38,4,FALSE)/$H19,0) -> 0 | Q19: =IFERROR(VLOOKUP($C19+Q$6,$C$11:$AK$38,4,FALSE)/$H19,0) -> 0 | R19: =IFERROR(VLOOKUP($C19+R$6,$C$11:$AK$38,4,FALSE)/$H19,0) -> 0 | ... AK19: =IFERROR(VLOOKUP($C19+AK$6,$C$11:$AK$38,4,FALSE)/$H19,0) -> 0
B20: =IBNR!F16 -> 2020Q2 | C20: =C21+3 -> 57 | D20: =_xlfn.XLOOKUP($B$8,Paid_DFs!$G$5:$S$5,Paid_DFs!$G16:$S16) -> 1 | E20: =PRODUCT($D$11:$D20) -> 1 | F20: =G20-G21 -> 0 | G20: =1/E20 -> 1 | H20: =1-G20 -> 0 | I20: =SUM(J20:AK20) -> 1 | J20: =IF($H20=0%,100%,IFERROR(VLOOKUP($C20+J$6,$C$11:$AK$38,4,FALSE)/$H20,0)) -> 1 | K20: =IFERROR(VLOOKUP($C20+K$6,$C$11:$AK$38,4,FALSE)/$H20,0) -> 0 | L20: =IFERROR(VLOOKUP($C20+L$6,$C$11:$AK$38,4,FALSE)/$H20,0) -> 0 | M20: =IFERROR(VLOOKUP($C20+M$6,$C$11:$AK$38,4,FALSE)/$H20,0) -> 0 | N20: =IFERROR(VLOOKUP($C20+N$6,$C$11:$AK$38,4,FALSE)/$H20,0) -> 0 | O20: =IFERROR(VLOOKUP($C20+O$6,$C$11:$AK$38,4,FALSE)/$H20,0) -> 0 | P20: =IFERROR(VLOOKUP($C20+P$6,$C$11:$AK$38,4,FALSE)/$H20,0) -> 0 | Q20: =IFERROR(VLOOKUP($C20+Q$6,$C$11:$AK$38,4,FALSE)/$H20,0) -> 0 | R20: =IFERROR(VLOOKUP($C20+R$6,$C$11:$AK$38,4,FALSE)/$H20,0) -> 0 | ... AK20: =IFERROR(VLOOKUP($C20+AK$6,$C$11:$AK$38,4,FALSE)/$H20,0) -> 0
B21: =IBNR!F17 -> 2020Q3 | C21: =C22+3 -> 54 | D21: =_xlfn.XLOOKUP($B$8,Paid_DFs!$G$5:$S$5,Paid_DFs!$G17:$S17) -> 1 | E21: =PRODUCT($D$11:$D21) -> 1 | F21: =G21-G22 -> 0 | G21: =1/E21 -> 1 | H21: =1-G21 -> 0 | I21: =SUM(J21:AK21) -> 1 | J21: =IF($H21=0%,100%,IFERROR(VLOOKUP($C21+J$6,$C$11:$AK$38,4,FALSE)/$H21,0)) -> 1 | K21: =IFERROR(VLOOKUP($C21+K$6,$C$11:$AK$38,4,FALSE)/$H21,0) -> 0 | L21: =IFERROR(VLOOKUP($C21+L$6,$C$11:$AK$38,4,FALSE)/$H21,0) -> 0 | M21: =IFERROR(VLOOKUP($C21+M$6,$C$11:$AK$38,4,FALSE)/$H21,0) -> 0 | N21: =IFERROR(VLOOKUP($C21+N$6,$C$11:$AK$38,4,FALSE)/$H21,0) -> 0 | O21: =IFERROR(VLOOKUP($C21+O$6,$C$11:$AK$38,4,FALSE)/$H21,0) -> 0 | P21: =IFERROR(VLOOKUP($C21+P$6,$C$11:$AK$38,4,FALSE)/$H21,0) -> 0 | Q21: =IFERROR(VLOOKUP($C21+Q$6,$C$11:$AK$38,4,FALSE)/$H21,0) -> 0 | R21: =IFERROR(VLOOKUP($C21+R$6,$C$11:$AK$38,4,FALSE)/$H21,0) -> 0 | ... AK21: =IFERROR(VLOOKUP($C21+AK$6,$C$11:$AK$38,4,FALSE)/$H21,0) -> 0
B22: =IBNR!F18 -> 2020Q4 | C22: =C23+3 -> 51 | D22: =_xlfn.XLOOKUP($B$8,Paid_DFs!$G$5:$S$5,Paid_DFs!$G18:$S18) -> 1 | E22: =PRODUCT($D$11:$D22) -> 1 | F22: =G22-G23 -> 0 | G22: =1/E22 -> 1 | H22: =1-G22 -> 0 | I22: =SUM(J22:AK22) -> 1 | J22: =IF($H22=0%,100%,IFERROR(VLOOKUP($C22+J$6,$C$11:$AK$38,4,FALSE)/$H22,0)) -> 1 | K22: =IFERROR(VLOOKUP($C22+K$6,$C$11:$AK$38,4,FALSE)/$H22,0) -> 0 | L22: =IFERROR(VLOOKUP($C22+L$6,$C$11:$AK$38,4,FALSE)/$H22,0) -> 0 | M22: =IFERROR(VLOOKUP($C22+M$6,$C$11:$AK$38,4,FALSE)/$H22,0) -> 0 | N22: =IFERROR(VLOOKUP($C22+N$6,$C$11:$AK$38,4,FALSE)/$H22,0) -> 0 | O22: =IFERROR(VLOOKUP($C22+O$6,$C$11:$AK$38,4,FALSE)/$H22,0) -> 0 | P22: =IFERROR(VLOOKUP($C22+P$6,$C$11:$AK$38,4,FALSE)/$H22,0) -> 0 | Q22: =IFERROR(VLOOKUP($C22+Q$6,$C$11:$AK$38,4,FALSE)/$H22,0) -> 0 | R22: =IFERROR(VLOOKUP($C22+R$6,$C$11:$AK$38,4,FALSE)/$H22,0) -> 0 | ... AK22: =IFERROR(VLOOKUP($C22+AK$6,$C$11:$AK$38,4,FALSE)/$H22,0) -> 0
... B30: =IBNR!F26 -> 2022Q4 | C30: =C31+3 -> 27 | D30: =_xlfn.XLOOKUP($B$8,Paid_DFs!$G$5:$S$5,Paid_DFs!$G26:$S26) -> 1 | E30: =PRODUCT($D$11:$D30) -> 1 | F30: =G30-G31 -> 0.04711903 | G30: =1/E30 -> 1 | H30: =1-G30 -> 0 | I30: =SUM(J30:AK30) -> 1 | J30: =IF($H30=0%,100%,IFERROR(VLOOKUP($C30+J$6,$C$11:$AK$38,4,FALSE)/$H30,0)) -> 1 | K30: =IFERROR(VLOOKUP($C30+K$6,$C$11:$AK$38,4,FALSE)/$H30,0) -> 0 | L30: =IFERROR(VLOOKUP($C30+L$6,$C$11:$AK$38,4,FALSE)/$H30,0) -> 0 | M30: =IFERROR(VLOOKUP($C30+M$6,$C$11:$AK$38,4,FALSE)/$H30,0) -> 0 | N30: =IFERROR(VLOOKUP($C30+N$6,$C$11:$AK$38,4,FALSE)/$H30,0) -> 0 | O30: =IFERROR(VLOOKUP($C30+O$6,$C$11:$AK$38,4,FALSE)/$H30,0) -> 0 | P30: =IFERROR(VLOOKUP($C30+P$6,$C$11:$AK$38,4,FALSE)/$H30,0) -> 0 | Q30: =IFERROR(VLOOKUP($C30+Q$6,$C$11:$AK$38,4,FALSE)/$H30,0) -> 0 | R30: =IFERROR(VLOOKUP($C30+R$6,$C$11:$AK$38,4,FALSE)/$H30,0) -> 0 | ... AK30: =IFERROR(VLOOKUP($C30+AK$6,$C$11:$AK$38,4,FALSE)/$H30,0) -> 0
B31: 2023Q1 | C31: =C32+3 -> 24 | D31: =_xlfn.XLOOKUP($B$8,Paid_DFs!$G$5:$S$5,Paid_DFs!$G27:$S27) -> 1.049449 | E31: =PRODUCT($D$11:$D31) -> 1.049449 | F31: =G31-G32 -> 0 | G31: =1/E31 -> 0.95288097 | H31: =1-G31 -> 0.04711903 | I31: =SUM(J31:AK31) -> 1 | J31: =IF($H31=0%,100%,IFERROR(VLOOKUP($C31+J$6,$C$11:$AK$38,4,FALSE)/$H31,0)) -> 1 | K31: =IFERROR(VLOOKUP($C31+K$6,$C$11:$AK$38,4,FALSE)/$H31,0) -> 0 | L31: =IFERROR(VLOOKUP($C31+L$6,$C$11:$AK$38,4,FALSE)/$H31,0) -> 0 | M31: =IFERROR(VLOOKUP($C31+M$6,$C$11:$AK$38,4,FALSE)/$H31,0) -> 0 | N31: =IFERROR(VLOOKUP($C31+N$6,$C$11:$AK$38,4,FALSE)/$H31,0) -> 0 | O31: =IFERROR(VLOOKUP($C31+O$6,$C$11:$AK$38,4,FALSE)/$H31,0) -> 0 | P31: =IFERROR(VLOOKUP($C31+P$6,$C$11:$AK$38,4,FALSE)/$H31,0) -> 0 | Q31: =IFERROR(VLOOKUP($C31+Q$6,$C$11:$AK$38,4,FALSE)/$H31,0) -> 0 | R31: =IFERROR(VLOOKUP($C31+R$6,$C$11:$AK$38,4,FALSE)/$H31,0) -> 0 | ... AK31: =IFERROR(VLOOKUP($C31+AK$6,$C$11:$AK$38,4,FALSE)/$H31,0) -> 0
B32: 2023Q2 | C32: =C33+3 -> 21 | D32: =_xlfn.XLOOKUP($B$8,Paid_DFs!$G$5:$S$5,Paid_DFs!$G28:$S28) -> 1 | E32: =PRODUCT($D$11:$D32) -> 1.049449 | F32: =G32-G33 -> 0 | G32: =1/E32 -> 0.95288097 | H32: =1-G32 -> 0.04711903 | I32: =SUM(J32:AK32) -> 1 | J32: =IF($H32=0%,100%,IFERROR(VLOOKUP($C32+J$6,$C$11:$AK$38,4,FALSE)/$H32,0)) -> 0 | K32: =IFERROR(VLOOKUP($C32+K$6,$C$11:$AK$38,4,FALSE)/$H32,0) -> 1 | L32: =IFERROR(VLOOKUP($C32+L$6,$C$11:$AK$38,4,FALSE)/$H32,0) -> 0 | M32: =IFERROR(VLOOKUP($C32+M$6,$C$11:$AK$38,4,FALSE)/$H32,0) -> 0 | N32: =IFERROR(VLOOKUP($C32+N$6,$C$11:$AK$38,4,FALSE)/$H32,0) -> 0 | O32: =IFERROR(VLOOKUP($C32+O$6,$C$11:$AK$38,4,FALSE)/$H32,0) -> 0 | P32: =IFERROR(VLOOKUP($C32+P$6,$C$11:$AK$38,4,FALSE)/$H32,0) -> 0 | Q32: =IFERROR(VLOOKUP($C32+Q$6,$C$11:$AK$38,4,FALSE)/$H32,0) -> 0 | R32: =IFERROR(VLOOKUP($C32+R$6,$C$11:$AK$38,4,FALSE)/$H32,0) -> 0 | ... AK32: =IFERROR(VLOOKUP($C32+AK$6,$C$11:$AK$38,4,FALSE)/$H32,0) -> 0
B33: 2023Q3 | C33: =C34+3 -> 18 | D33: =_xlfn.XLOOKUP($B$8,Paid_DFs!$G$5:$S$5,Paid_DFs!$G29:$S29) -> 1 | E33: =PRODUCT($D$11:$D33) -> 1.049449 | F33: =G33-G34 -> 0.00072382885 | G33: =1/E33 -> 0.95288097 | H33: =1-G33 -> 0.04711903 | I33: =SUM(J33:AK33) -> 1 | J33: =IF($H33=0%,100%,IFERROR(VLOOKUP($C33+J$6,$C$11:$AK$38,4,FALSE)/$H33,0)) -> 0 | K33: =IFERROR(VLOOKUP($C33+K$6,$C$11:$AK$38,4,FALSE)/$H33,0) -> 0 | L33: =IFERROR(VLOOKUP($C33+L$6,$C$11:$AK$38,4,FALSE)/$H33,0) -> 1 | M33: =IFERROR(VLOOKUP($C33+M$6,$C$11:$AK$38,4,FALSE)/$H33,0) -> 0 | N33: =IFERROR(VLOOKUP($C33+N$6,$C$11:$AK$38,4,FALSE)/$H33,0) -> 0 | O33: =IFERROR(VLOOKUP($C33+O$6,$C$11:$AK$38,4,FALSE)/$H33,0) -> 0 | P33: =IFERROR(VLOOKUP($C33+P$6,$C$11:$AK$38,4,FALSE)/$H33,0) -> 0 | Q33: =IFERROR(VLOOKUP($C33+Q$6,$C$11:$AK$38,4,FALSE)/$H33,0) -> 0 | R33: =IFERROR(VLOOKUP($C33+R$6,$C$11:$AK$38,4,FALSE)/$H33,0) -> 0 | ... AK33: =IFERROR(VLOOKUP($C33+AK$6,$C$11:$AK$38,4,FALSE)/$H33,0) -> 0
B34: 2023Q4 | C34: =C35+3 -> 15 | D34: =_xlfn.XLOOKUP($B$8,Paid_DFs!$G$5:$S$5,Paid_DFs!$G30:$S30) -> 1.0007602 | E34: =PRODUCT($D$11:$D34) -> 1.0502468 | F34: =G34-G35 -> 0.00022280334 | G34: =1/E34 -> 0.95215714 | H34: =1-G34 -> 0.047842859 | I34: =SUM(J34:AK34) -> 1 | J34: =IF($H34=0%,100%,IFERROR(VLOOKUP($C34+J$6,$C$11:$AK$38,4,FALSE)/$H34,0)) -> 0.015129297 | K34: =IFERROR(VLOOKUP($C34+K$6,$C$11:$AK$38,4,FALSE)/$H34,0) -> 0 | L34: =IFERROR(VLOOKUP($C34+L$6,$C$11:$AK$38,4,FALSE)/$H34,0) -> 0 | M34: =IFERROR(VLOOKUP($C34+M$6,$C$11:$AK$38,4,FALSE)/$H34,0) -> 0.9848707 | N34: =IFERROR(VLOOKUP($C34+N$6,$C$11:$AK$38,4,FALSE)/$H34,0) -> 0 | O34: =IFERROR(VLOOKUP($C34+O$6,$C$11:$AK$38,4,FALSE)/$H34,0) -> 0 | P34: =IFERROR(VLOOKUP($C34+P$6,$C$11:$AK$38,4,FALSE)/$H34,0) -> 0 | Q34: =IFERROR(VLOOKUP($C34+Q$6,$C$11:$AK$38,4,FALSE)/$H34,0) -> 0 | R34: =IFERROR(VLOOKUP($C34+R$6,$C$11:$AK$38,4,FALSE)/$H34,0) -> 0 | ... AK34: =IFERROR(VLOOKUP($C34+AK$6,$C$11:$AK$38,4,FALSE)/$H34,0) -> 0
B35: 2024Q1 | C35: =C36+3 -> 12 | D35: =_xlfn.XLOOKUP($B$8,Paid_DFs!$G$5:$S$5,Paid_DFs!$G31:$S31) -> 1.0002341 | E35: =PRODUCT($D$11:$D35) -> 1.0504926 | F35: =G35-G36 -> 0.00041714473 | G35: =1/E35 -> 0.95193434 | H35: =1-G35 -> 0.048065663 | I35: =SUM(J35:AK35) -> 1 | J35: =IF($H35=0%,100%,IFERROR(VLOOKUP($C35+J$6,$C$11:$AK$38,4,FALSE)/$H35,0)) -> 0.0046353951 | K35: =IFERROR(VLOOKUP($C35+K$6,$C$11:$AK$38,4,FALSE)/$H35,0) -> 0.015059167 | L35: =IFERROR(VLOOKUP($C35+L$6,$C$11:$AK$38,4,FALSE)/$H35,0) -> 0 | M35: =IFERROR(VLOOKUP($C35+M$6,$C$11:$AK$38,4,FALSE)/$H35,0) -> 0 | N35: =IFERROR(VLOOKUP($C35+N$6,$C$11:$AK$38,4,FALSE)/$H35,0) -> 0.98030544 | O35: =IFERROR(VLOOKUP($C35+O$6,$C$11:$AK$38,4,FALSE)/$H35,0) -> 0 | P35: =IFERROR(VLOOKUP($C35+P$6,$C$11:$AK$38,4,FALSE)/$H35,0) -> 0 | Q35: =IFERROR(VLOOKUP($C35+Q$6,$C$11:$AK$38,4,FALSE)/$H35,0) -> 0 | R35: =IFERROR(VLOOKUP($C35+R$6,$C$11:$AK$38,4,FALSE)/$H35,0) -> 0 | ... AK35: =IFERROR(VLOOKUP($C35+AK$6,$C$11:$AK$38,4,FALSE)/$H35,0) -> 0
B36: 2024Q2 | C36: =C37+3 -> 9 | D36: =_xlfn.XLOOKUP($B$8,Paid_DFs!$G$5:$S$5,Paid_DFs!$G32:$S32) -> 1.0004384 | E36: =PRODUCT($D$11:$D36) -> 1.0509532 | F36: =G36-G37 -> 0.022456071 | G36: =1/E36 -> 0.95151719 | H36: =1-G36 -> 0.048482807 | I36: =SUM(J36:AK36) -> 1 | J36: =IF($H36=0%,100%,IFERROR(VLOOKUP($C36+J$6,$C$11:$AK$38,4,FALSE)/$H36,0)) -> 0.0086039723 | K36: =IFERROR(VLOOKUP($C36+K$6,$C$11:$AK$38,4,FALSE)/$H36,0) -> 0.0045955123 | L36: =IFERROR(VLOOKUP($C36+L$6,$C$11:$AK$38,4,FALSE)/$H36,0) -> 0.014929598 | M36: =IFERROR(VLOOKUP($C36+M$6,$C$11:$AK$38,4,FALSE)/$H36,0) -> 0 | N36: =IFERROR(VLOOKUP($C36+N$6,$C$11:$AK$38,4,FALSE)/$H36,0) -> 0 | O36: =IFERROR(VLOOKUP($C36+O$6,$C$11:$AK$38,4,FALSE)/$H36,0) -> 0.97187092 | P36: =IFERROR(VLOOKUP($C36+P$6,$C$11:$AK$38,4,FALSE)/$H36,0) -> 0 | Q36: =IFERROR(VLOOKUP($C36+Q$6,$C$11:$AK$38,4,FALSE)/$H36,0) -> 0 | R36: =IFERROR(VLOOKUP($C36+R$6,$C$11:$AK$38,4,FALSE)/$H36,0) -> 0 | ... AK36: =IFERROR(VLOOKUP($C36+AK$6,$C$11:$AK$38,4,FALSE)/$H36,0) -> 0
B37: 2024Q3 | C37: =C38+3 -> 6 | D37: =_xlfn.XLOOKUP($B$8,Paid_DFs!$G$5:$S$5,Paid_DFs!$G33:$S33) -> 1.0241707 | E37: =PRODUCT($D$11:$D37) -> 1.0763554 | F37: =G37-G38 -> 0.030637532 | G37: =1/E37 -> 0.92906112 | H37: =1-G37 -> 0.070938879 | I37: =SUM(J37:AK37) -> 1 | J37: =IF($H37=0%,100%,IFERROR(VLOOKUP($C37+J$6,$C$11:$AK$38,4,FALSE)/$H37,0)) -> 0.3165552 | K37: =IFERROR(VLOOKUP($C37+K$6,$C$11:$AK$38,4,FALSE)/$H37,0) -> 0.0058803401 | L37: =IFERROR(VLOOKUP($C37+L$6,$C$11:$AK$38,4,FALSE)/$H37,0) -> 0.0031407789 | M37: =IFERROR(VLOOKUP($C37+M$6,$C$11:$AK$38,4,FALSE)/$H37,0) -> 0.010203556 | N37: =IFERROR(VLOOKUP($C37+N$6,$C$11:$AK$38,4,FALSE)/$H37,0) -> 0 | O37: =IFERROR(VLOOKUP($C37+O$6,$C$11:$AK$38,4,FALSE)/$H37,0) -> 0 | P37: =IFERROR(VLOOKUP($C37+P$6,$C$11:$AK$38,4,FALSE)/$H37,0) -> 0.66422012 | Q37: =IFERROR(VLOOKUP($C37+Q$6,$C$11:$AK$38,4,FALSE)/$H37,0) -> 0 | R37: =IFERROR(VLOOKUP($C37+R$6,$C$11:$AK$38,4,FALSE)/$H37,0) -> 0 | ... AK37: =IFERROR(VLOOKUP($C37+AK$6,$C$11:$AK$38,4,FALSE)/$H37,0) -> 0
B38: 2024Q4 | C38: =C39+3 -> 3 | D38: =_xlfn.XLOOKUP($B$8,Paid_DFs!$G$5:$S$5,Paid_DFs!$G34:$S34) -> 1.0341014 | E38: =PRODUCT($D$11:$D38) -> 1.1130607 | F38: =G38-G39 -> 0.89842359 | G38: =1/E38 -> 0.89842359 | H38: =1-G38 -> 0.10157641 | I38: =SUM(J38:AK38) -> 1 | J38: =IF($H38=0%,100%,IFERROR(VLOOKUP($C38+J$6,$C$11:$AK$38,4,FALSE)/$H38,0)) -> 0.30162054 | K38: =IFERROR(VLOOKUP($C38+K$6,$C$11:$AK$38,4,FALSE)/$H38,0) -> 0.22107565 | L38: =IFERROR(VLOOKUP($C38+L$6,$C$11:$AK$38,4,FALSE)/$H38,0) -> 0.0041067087 | M38: =IFERROR(VLOOKUP($C38+M$6,$C$11:$AK$38,4,FALSE)/$H38,0) -> 0.0021934555 | N38: =IFERROR(VLOOKUP($C38+N$6,$C$11:$AK$38,4,FALSE)/$H38,0) -> 0.0071259541 | O38: =IFERROR(VLOOKUP($C38+O$6,$C$11:$AK$38,4,FALSE)/$H38,0) -> 0 | P38: =IFERROR(VLOOKUP($C38+P$6,$C$11:$AK$38,4,FALSE)/$H38,0) -> 0 | Q38: =IFERROR(VLOOKUP($C38+Q$6,$C$11:$AK$38,4,FALSE)/$H38,0) -> 0.46387769 | R38: =IFERROR(VLOOKUP($C38+R$6,$C$11:$AK$38,4,FALSE)/$H38,0) -> 0 | ... AK38: =IFERROR(VLOOKUP($C38+AK$6,$C$11:$AK$38,4,FALSE)/$H38,0) -> 0
B39: Total | H39: =SUM(H11:H38) -> 0.45826371 | J39: =SUM(J11:J38) -> 21.646544 | K39: =SUM(K11:K38) -> 1.2466107 | L39: =SUM(L11:L38) -> 1.0221771 | M39: =SUM(M11:M38) -> 0.99726771 | N39: =SUM(N11:N38) -> 0.98743139 | O39: =SUM(O11:O38) -> 0.97187092 | P39: =SUM(P11:P38) -> 0.66422012 | Q39: =SUM(Q11:Q38) -> 0.46387769 | ... AK39: =SUM(AK11:AK38) -> 0
I41: =1-I38 -> 0 | K41: =F33/H38 -> 0.0071259541
H42: =H39-H40 -> 0.45826371
B45: =B8 -> Fire Domestic
J46: Time (in years)
E47: Origin | F47: OCR | G47: IBNR | H47: Claims Provision | I47: Check | J47: =J10 -> 0.12 | K47: =K10 -> 0.38 | L47: =L10 -> 0.62 | M47: =M10 -> 0.88 | N47: =N10 -> 1.12 | O47: =O10 -> 1.38 | P47: =P10 -> 1.62 | Q47: =Q10 -> 1.88 | ... AD47: =AD10 -> 5.12 | AE47: 5.38 | AF47: 5.62 | AG47: 5.88 | AH47: 6.12 | AI47: 6.38 | AJ47: 6.62 | AK47: 6.88
E48: =B11 -> 2018Q1 | F48: =_xlfn.XLOOKUP($B$8,OCR!$D$2:$P$2,OCR!$D4:$P4) -> 0 | G48: =_xlfn.XLOOKUP($B$8,IBNR!$G$5:$S$5,IBNR!$G7:$S7) -> 0 | H48: =SUM(F48:G48) -> 0 | I48: =SUM(J48:AK48) -> 0 | J48: =$H48*J11 -> 0 | K48: =$H48*K11 -> 0 | L48: =$H48*L11 -> 0 | M48: =$H48*M11 -> 0 | N48: =$H48*N11 -> 0 | O48: =$H48*O11 -> 0 | P48: =$H48*P11 -> 0 | Q48: =$H48*Q11 -> 0 | ... AK48: =$H48*AK11 -> 0
E49: =B12 -> 2018Q2 | F49: =_xlfn.XLOOKUP($B$8,OCR!$D$2:$P$2,OCR!$D5:$P5) -> 0 | G49: =_xlfn.XLOOKUP($B$8,IBNR!$G$5:$S$5,IBNR!$G8:$S8) -> 0 | H49: =SUM(F49:G49) -> 0 | I49: =SUM(J49:AK49) -> 0 | J49: =$H49*J12 -> 0 | K49: =$H49*K12 -> 0 | L49: =$H49*L12 -> 0 | M49: =$H49*M12 -> 0 | N49: =$H49*N12 -> 0 | O49: =$H49*O12 -> 0 | P49: =$H49*P12 -> 0 | Q49: =$H49*Q12 -> 0 | ... AK49: =$H49*AK12 -> 0
E50: =B13 -> 2018Q3 | F50: =_xlfn.XLOOKUP($B$8,OCR!$D$2:$P$2,OCR!$D6:$P6) -> 112200 | G50: =_xlfn.XLOOKUP($B$8,IBNR!$G$5:$S$5,IBNR!$G9:$S9) -> 0 | H50: =SUM(F50:G50) -> 112200 | I50: =SUM(J50:AK50) -> 112200 | J50: =$H50*J13 -> 112200 | K50: =$H50*K13 -> 0 | L50: =$H50*L13 -> 0 | M50: =$H50*M13 -> 0 | N50: =$H50*N13 -> 0 | O50: =$H50*O13 -> 0 | P50: =$H50*P13 -> 0 | Q50: =$H50*Q13 -> 0 | ... AK50: =$H50*AK13 -> 0
E51: =B14 -> 2018Q4 | F51: =_xlfn.XLOOKUP($B$8,OCR!$D$2:$P$2,OCR!$D7:$P7) -> 0 | G51: =_xlfn.XLOOKUP($B$8,IBNR!$G$5:$S$5,IBNR!$G10:$S10) -> 0 | H51: =SUM(F51:G51) -> 0 | I51: =SUM(J51:AK51) -> 0 | J51: =$H51*J14 -> 0 | K51: =$H51*K14 -> 0 | L51: =$H51*L14 -> 0 | M51: =$H51*M14 -> 0 | N51: =$H51*N14 -> 0 | O51: =$H51*O14 -> 0 | P51: =$H51*P14 -> 0 | Q51: =$H51*Q14 -> 0 | ... AK51: =$H51*AK14 -> 0
E52: =B15 -> 2019Q1 | F52: =_xlfn.XLOOKUP($B$8,OCR!$D$2:$P$2,OCR!$D8:$P8) -> 0 | G52: =_xlfn.XLOOKUP($B$8,IBNR!$G$5:$S$5,IBNR!$G11:$S11) -> 0 | H52: =SUM(F52:G52) -> 0 | I52: =SUM(J52:AK52) -> 0 | J52: =$H52*J15 -> 0 | K52: =$H52*K15 -> 0 | L52: =$H52*L15 -> 0 | M52: =$H52*M15 -> 0 | N52: =$H52*N15 -> 0 | O52: =$H52*O15 -> 0 | P52: =$H52*P15 -> 0 | Q52: =$H52*Q15 -> 0 | ... AK52: =$H52*AK15 -> 0
E53: =B16 -> 2019Q2 | F53: =_xlfn.XLOOKUP($B$8,OCR!$D$2:$P$2,OCR!$D9:$P9) -> 0 | G53: =_xlfn.XLOOKUP($B$8,IBNR!$G$5:$S$5,IBNR!$G12:$S12) -> 0 | H53: =SUM(F53:G53) -> 0 | I53: =SUM(J53:AK53) -> 0 | J53: =$H53*J16 -> 0 | K53: =$H53*K16 -> 0 | L53: =$H53*L16 -> 0 | M53: =$H53*M16 -> 0 | N53: =$H53*N16 -> 0 | O53: =$H53*O16 -> 0 | P53: =$H53*P16 -> 0 | Q53: =$H53*Q16 -> 0 | ... AK53: =$H53*AK16 -> 0
E54: =B17 -> 2019Q3 | F54: =_xlfn.XLOOKUP($B$8,OCR!$D$2:$P$2,OCR!$D10:$P10) -> 0 | G54: =_xlfn.XLOOKUP($B$8,IBNR!$G$5:$S$5,IBNR!$G13:$S13) -> 0 | H54: =SUM(F54:G54) -> 0 | I54: =SUM(J54:AK54) -> 0 | J54: =$H54*J17 -> 0 | K54: =$H54*K17 -> 0 | L54: =$H54*L17 -> 0 | M54: =$H54*M17 -> 0 | N54: =$H54*N17 -> 0 | O54: =$H54*O17 -> 0 | P54: =$H54*P17 -> 0 | Q54: =$H54*Q17 -> 0 | ... AK54: =$H54*AK17 -> 0
E55: =B18 -> 2019Q4 | F55: =_xlfn.XLOOKUP($B$8,OCR!$D$2:$P$2,OCR!$D11:$P11) -> 0 | G55: =_xlfn.XLOOKUP($B$8,IBNR!$G$5:$S$5,IBNR!$G14:$S14) -> 0 | H55: =SUM(F55:G55) -> 0 | I55: =SUM(J55:AK55) -> 0 | J55: =$H55*J18 -> 0 | K55: =$H55*K18 -> 0 | L55: =$H55*L18 -> 0 | M55: =$H55*M18 -> 0 | N55: =$H55*N18 -> 0 | O55: =$H55*O18 -> 0 | P55: =$H55*P18 -> 0 | Q55: =$H55*Q18 -> 0 | ... AK55: =$H55*AK18 -> 0
E56: =B19 -> 2020Q1 | F56: =_xlfn.XLOOKUP($B$8,OCR!$D$2:$P$2,OCR!$D12:$P12) -> 0 | G56: =_xlfn.XLOOKUP($B$8,IBNR!$G$5:$S$5,IBNR!$G15:$S15) -> 0 | H56: =SUM(F56:G56) -> 0 | I56: =SUM(J56:AK56) -> 0 | J56: =$H56*J19 -> 0 | K56: =$H56*K19 -> 0 | L56: =$H56*L19 -> 0 | M56: =$H56*M19 -> 0 | N56: =$H56*N19 -> 0 | O56: =$H56*O19 -> 0 | P56: =$H56*P19 -> 0 | Q56: =$H56*Q19 -> 0 | ... AK56: =$H56*AK19 -> 0
E57: =B20 -> 2020Q2 | F57: =_xlfn.XLOOKUP($B$8,OCR!$D$2:$P$2,OCR!$D13:$P13) -> 0 | G57: =_xlfn.XLOOKUP($B$8,IBNR!$G$5:$S$5,IBNR!$G16:$S16) -> 0 | H57: =SUM(F57:G57) -> 0 | I57: =SUM(J57:AK57) -> 0 | J57: =$H57*J20 -> 0 | K57: =$H57*K20 -> 0 | L57: =$H57*L20 -> 0 | M57: =$H57*M20 -> 0 | N57: =$H57*N20 -> 0 | O57: =$H57*O20 -> 0 | P57: =$H57*P20 -> 0 | Q57: =$H57*Q20 -> 0 | ... AK57: =$H57*AK20 -> 0
E58: =B21 -> 2020Q3 | F58: =_xlfn.XLOOKUP($B$8,OCR!$D$2:$P$2,OCR!$D14:$P14) -> 0 | G58: =_xlfn.XLOOKUP($B$8,IBNR!$G$5:$S$5,IBNR!$G17:$S17) -> 0 | H58: =SUM(F58:G58) -> 0 | I58: =SUM(J58:AK58) -> 0 | J58: =$H58*J21 -> 0 | K58: =$H58*K21 -> 0 | L58: =$H58*L21 -> 0 | M58: =$H58*M21 -> 0 | N58: =$H58*N21 -> 0 | O58: =$H58*O21 -> 0 | P58: =$H58*P21 -> 0 | Q58: =$H58*Q21 -> 0 | ... AK58: =$H58*AK21 -> 0
E59: =B22 -> 2020Q4 | F59: =_xlfn.XLOOKUP($B$8,OCR!$D$2:$P$2,OCR!$D15:$P15) -> 0 | G59: =_xlfn.XLOOKUP($B$8,IBNR!$G$5:$S$5,IBNR!$G18:$S18) -> 0 | H59: =SUM(F59:G59) -> 0 | I59: =SUM(J59:AK59) -> 0 | J59: =$H59*J22 -> 0 | K59: =$H59*K22 -> 0 | L59: =$H59*L22 -> 0 | M59: =$H59*M22 -> 0 | N59: =$H59*N22 -> 0 | O59: =$H59*O22 -> 0 | P59: =$H59*P22 -> 0 | Q59: =$H59*Q22 -> 0 | ... AK59: =$H59*AK22 -> 0
... E67: =B30 -> 2022Q4 | F67: =_xlfn.XLOOKUP($B$8,OCR!$D$2:$P$2,OCR!$D23:$P23) -> 187000 | G67: =_xlfn.XLOOKUP($B$8,IBNR!$G$5:$S$5,IBNR!$G26:$S26) -> 0 | H67: =SUM(F67:G67) -> 187000 | I67: =SUM(J67:AK67) -> 187000 | J67: =$H67*J30 -> 187000 | K67: =$H67*K30 -> 0 | L67: =$H67*L30 -> 0 | M67: =$H67*M30 -> 0 | N67: =$H67*N30 -> 0 | O67: =$H67*O30 -> 0 | P67: =$H67*P30 -> 0 | Q67: =$H67*Q30 -> 0 | ... AK67: =$H67*AK30 -> 0
E68: 2023Q1 | F68: =_xlfn.XLOOKUP($B$8,OCR!$D$2:$P$2,OCR!$D24:$P24) -> 0 | G68: =_xlfn.XLOOKUP($B$8,IBNR!$G$5:$S$5,IBNR!$G27:$S27) -> 196076.35 | H68: =SUM(F68:G68) -> 196076.35 | I68: =SUM(J68:AK68) -> 196076.35 | J68: =$H68*J31 -> 196076.35 | K68: =$H68*K31 -> 0 | L68: =$H68*L31 -> 0 | M68: =$H68*M31 -> 0 | N68: =$H68*N31 -> 0 | O68: =$H68*O31 -> 0 | P68: =$H68*P31 -> 0 | Q68: =$H68*Q31 -> 0 | ... AK68: =$H68*AK31 -> 0
E69: 2023Q2 | F69: =_xlfn.XLOOKUP($B$8,OCR!$D$2:$P$2,OCR!$D25:$P25) -> 44000 | G69: =_xlfn.XLOOKUP($B$8,IBNR!$G$5:$S$5,IBNR!$G28:$S28) -> 49901.486 | H69: =SUM(F69:G69) -> 93901.486 | I69: =SUM(J69:AK69) -> 93901.486 | J69: =$H69*J32 -> 0 | K69: =$H69*K32 -> 93901.486 | L69: =$H69*L32 -> 0 | M69: =$H69*M32 -> 0 | N69: =$H69*N32 -> 0 | O69: =$H69*O32 -> 0 | P69: =$H69*P32 -> 0 | Q69: =$H69*Q32 -> 0 | ... AK69: =$H69*AK32 -> 0
E70: 2023Q3 | F70: =_xlfn.XLOOKUP($B$8,OCR!$D$2:$P$2,OCR!$D26:$P26) -> 55000 | G70: =_xlfn.XLOOKUP($B$8,IBNR!$G$5:$S$5,IBNR!$G29:$S29) -> 28539.39 | H70: =SUM(F70:G70) -> 83539.39 | I70: =SUM(J70:AK70) -> 83539.39 | J70: =$H70*J33 -> 0 | K70: =$H70*K33 -> 0 | L70: =$H70*L33 -> 83539.39 | M70: =$H70*M33 -> 0 | N70: =$H70*N33 -> 0 | O70: =$H70*O33 -> 0 | P70: =$H70*P33 -> 0 | Q70: =$H70*Q33 -> 0 | ... AK70: =$H70*AK33 -> 0
E71: 2023Q4 | F71: =_xlfn.XLOOKUP($B$8,OCR!$D$2:$P$2,OCR!$D27:$P27) -> 1004405.6 | G71: =_xlfn.XLOOKUP($B$8,IBNR!$G$5:$S$5,IBNR!$G30:$S30) -> 151687.8 | H71: =SUM(F71:G71) -> 1156093.4 | I71: =SUM(J71:AK71) -> 1156093.4 | J71: =$H71*J34 -> 17490.881 | K71: =$H71*K34 -> 0 | L71: =$H71*L34 -> 0 | M71: =$H71*M34 -> 1138602.5 | N71: =$H71*N34 -> 0 | O71: =$H71*O34 -> 0 | P71: =$H71*P34 -> 0 | Q71: =$H71*Q34 -> 0 | ... AK71: =$H71*AK34 -> 0
E72: 2024Q1 | F72: =_xlfn.XLOOKUP($B$8,OCR!$D$2:$P$2,OCR!$D28:$P28) -> 0 | G72: =_xlfn.XLOOKUP($B$8,IBNR!$G$5:$S$5,IBNR!$G31:$S31) -> 5866.7968 | H72: =SUM(F72:G72) -> 5866.7968 | I72: =SUM(J72:AK72) -> 5866.7968 | J72: =$H72*J35 -> 27.194921 | K72: =$H72*K35 -> 88.349074 | L72: =$H72*L35 -> 0 | M72: =$H72*M35 -> 0 | N72: =$H72*N35 -> 5751.2528 | O72: =$H72*O35 -> 0 | P72: =$H72*P35 -> 0 | Q72: =$H72*Q35 -> 0 | ... AK72: =$H72*AK35 -> 0
E73: 2024Q2 | F73: =_xlfn.XLOOKUP($B$8,OCR!$D$2:$P$2,OCR!$D29:$P29) -> 47835335 | G73: =_xlfn.XLOOKUP($B$8,IBNR!$G$5:$S$5,IBNR!$G32:$S32) -> 447740.77 | H73: =SUM(F73:G73) -> 48283076 | I73: =SUM(J73:AK73) -> 48283076 | J73: =$H73*J36 -> 415426.24 | K73: =$H73*K36 -> 221885.47 | L73: =$H73*L36 -> 720846.93 | M73: =$H73*M36 -> 0 | N73: =$H73*N36 -> 0 | O73: =$H73*O36 -> 46924917 | P73: =$H73*P36 -> 0 | Q73: =$H73*Q36 -> 0 | ... AK73: =$H73*AK36 -> 0
E74: 2024Q3 | F74: =_xlfn.XLOOKUP($B$8,OCR!$D$2:$P$2,OCR!$D30:$P30) -> 227810 | G74: =_xlfn.XLOOKUP($B$8,IBNR!$G$5:$S$5,IBNR!$G33:$S33) -> 139911.54 | H74: =SUM(F74:G74) -> 367721.54 | I74: =SUM(J74:AK74) -> 367721.54 | J74: =$H74*J37 -> 116404.17 | K74: =$H74*K37 -> 2162.3277 | L74: =$H74*L37 -> 1154.9321 | M74: =$H74*M37 -> 3752.0674 | N74: =$H74*N37 -> 0 | O74: =$H74*O37 -> 0 | P74: =$H74*P37 -> 244248.04 | Q74: =$H74*Q37 -> 0 | ... AK74: =$H74*AK37 -> 0
E75: 2024Q4 | F75: =_xlfn.XLOOKUP($B$8,OCR!$D$2:$P$2,OCR!$D31:$P31) -> 637407.1 | G75: =_xlfn.XLOOKUP($B$8,IBNR!$G$5:$S$5,IBNR!$G34:$S34) -> 137825.8 | H75: =SUM(F75:G75) -> 775232.9 | I75: =SUM(J75:AK75) -> 775232.9 | J75: =$H75*J38 -> 233826.17 | K75: =$H75*K38 -> 171385.12 | L75: =$H75*L38 -> 3183.6557 | M75: =$H75*M38 -> 1700.4389 | N75: =$H75*N38 -> 5524.2741 | O75: =$H75*O38 -> 0 | P75: =$H75*P38 -> 0 | Q75: =$H75*Q38 -> 359613.24 | ... AK75: =$H75*AK38 -> 0
E76: =B39 -> Total | F76: =SUM(F48:F75) -> 50306108 | G76: =SUM(G48:G75) -> 1157549.9 | H76: =SUM(F76:G76) -> 51463657 | I76: =SUM(J76:AK76) -> 51463657 | J76: =SUM(J48:J75) -> 1481401 | K76: =SUM(K48:K75) -> 489422.75 | L76: =SUM(L48:L75) -> 808724.91 | M76: =SUM(M48:M75) -> 1144055 | N76: =SUM(N48:N75) -> 11275.527 | O76: =SUM(O48:O75) -> 46924917 | P76: =SUM(P48:P75) -> 244248.04 | Q76: =SUM(Q48:Q75) -> 359613.24 | ... AK76: =SUM(AK48:AK75) -> 0
I77: =ROUNDDOWN(I76,0)=ROUNDDOWN(H76,0) -> TRUE
I79: =I76-H76 -> 0

Sheet FI
J3: 2025 | K3: 2025 | L3: 2025 | M3: 2025 | N3: =J3+1 -> 2026 | O3: =K3+1 -> 2026 | P3: =L3+1 -> 2026 | Q3: =M3+1 -> 2026 | R3: =N3+1 -> 2027 | S3: =O3+1 -> 2027 | T3: =P3+1 -> 2027 | U3: =Q3+1 -> 2027 | ... AK3: =AG3+1 -> 2031
J4: Q1 | K4: Q2 | L4: Q3 | M4: Q4 | N4: Q1 | O4: Q2 | P4: Q3 | Q4: Q4 | R4: Q1 | S4: Q2 | T4: Q3 | U4: Q4 | V4: Q1 | W4: Q2 | X4: Q3 | Y4: Q4 | Z4: Q1 | AA4: Q2 | AB4: Q3 | AC4: Q4 | AD4: Q1 | AE4: Q2 | AF4: Q3 | AG4: Q4 | AH4: Q1 | AI4: Q2 | AJ4: Q3 | AK4: Q4
J5: =J4&"-"&J3 -> Q1-2025 | K5: =K4&"-"&K3 -> Q2-2025 | L5: =L4&"-"&L3 -> Q3-2025 | M5: =M4&"-"&M3 -> Q4-2025 | N5: =N4&"-"&N3 -> Q1-2026 | O5: =O4&"-"&O3 -> Q2-2026 | P5: =P4&"-"&P3 -> Q3-2026 | Q5: =Q4&"-"&Q3 -> Q4-2026 | ... AK5: =AK4&"-"&AK3 -> Q4-2031
H6: Payments in | J6: 3 | K6: =J6+3 -> 6 | L6: =K6+3 -> 9 | M6: =L6+3 -> 12 | N6: =M6+3 -> 15 | O6: =N6+3 -> 18 | P6: =O6+3 -> 21 | Q6: =P6+3 -> 24 | R6: =Q6+3 -> 27 | ... AK6: =AJ6+3 -> 84
K7: =K10-J10 -> 0.26 | L7: =L10-K10 -> 0.24 | M7: =M10-L10 -> 0.26 | N7: =N10-M10 -> 0.24 | O7: =O10-N10 -> 0.26 | P7: =P10-O10 -> 0.24 | Q7: =Q10-P10 -> 0.26 | R7: =R10-Q10 -> 0.24 | ... AK7: =AK10-AJ10 -> 0.26
B8: Fire Industrial | K8: =SUM(J10:K10) -> 0.5 | L8: =SUM(K10:L10) -> 1 | M8: =SUM(L10:M10) -> 1.5 | N8: =SUM(M10:N10) -> 2 | O8: =SUM(N10:O10) -> 2.5 | P8: =SUM(O10:P10) -> 3 | Q8: =SUM(P10:Q10) -> 3.5 | R8: =SUM(Q10:R10) -> 4 | ... AK8: =SUM(AJ10:AK10) -> 13.5
J9: Time (in years)
B10: Origin | C10: Age | D10: Paid DF's | E10: Cumulative Development Factors | F10: Incremental Payments | G10: Cumulative Payments | H10: Expected Unpaid % | I10: Check | J10: 0.12 | K10: 0.38 | L10: 0.62 | M10: 0.88 | N10: 1.12 | O10: 1.38 | P10: 1.62 | Q10: 1.88 | R10: 2.12 | S10: 2.38 | T10: 2.62 | U10: 2.88 | V10: 3.12 | W10: 3.38 | X10: 3.62 | Y10: 3.88 | Z10: 4.12 | AA10: 4.38 | AB10: 4.62 | AC10: 4.88 | AD10: 5.12 | AE10: 5.38 | AF10: 5.62 | AG10: 5.88 | AH10: 6.12 | AI10: 6.38 | AJ10: 6.62 | AK10: 6.88
B11: =IBNR!F7 -> 2018Q1 | C11: =C12+3 -> 84 | D11: =_xlfn.XLOOKUP($B$8,Paid_DFs!$G$5:$S$5,Paid_DFs!$G7:$S7) -> 1 | E11: =PRODUCT($D$11:$D11) -> 1 | F11: =G11-G12 -> 0 | G11: =1/E11 -> 1 | H11: =1-G11 -> 0 | I11: =SUM(J11:AK11) -> 1 | J11: =IF($H11=0%,100%,IFERROR(VLOOKUP($C11+J$6,$C$11:$AK$38,4,FALSE)/$H11,0)) -> 1 | K11: =IFERROR(VLOOKUP($C11+K$6,$C$11:$AK$38,4,FALSE)/$H11,0) -> 0 | L11: =IFERROR(VLOOKUP($C11+L$6,$C$11:$AK$38,4,FALSE)/$H11,0) -> 0 | M11: =IFERROR(VLOOKUP($C11+M$6,$C$11:$AK$38,4,FALSE)/$H11,0) -> 0 | N11: =IFERROR(VLOOKUP($C11+N$6,$C$11:$AK$38,4,FALSE)/$H11,0) -> 0 | O11: =IFERROR(VLOOKUP($C11+O$6,$C$11:$AK$38,4,FALSE)/$H11,0) -> 0 | P11: =IFERROR(VLOOKUP($C11+P$6,$C$11:$AK$38,4,FALSE)/$H11,0) -> 0 | Q11: =IFERROR(VLOOKUP($C11+Q$6,$C$11:$AK$38,4,FALSE)/$H11,0) -> 0 | R11: =IFERROR(VLOOKUP($C11+R$6,$C$11:$AK$38,4,FALSE)/$H11,0) -> 0 | ... AK11: =IFERROR(VLOOKUP($C11+AK$6,$C$11:$AK$38,4,FALSE)/$H11,0) -> 0
B12: =IBNR!F8 -> 2018Q2 | C12: =C13+3 -> 81 | D12: =_xlfn.XLOOKUP($B$8,Paid_DFs!$G$5:$S$5,Paid_DFs!$G8:$S8) -> 1 | E12: =PRODUCT($D$11:$D12) -> 1 | F12: =G12-G13 -> 0 | G12: =1/E12 -> 1 | H12: =1-G12 -> 0 | I12: =SUM(J12:AK12) -> 1 | J12: =IF($H12=0%,100%,IFERROR(VLOOKUP($C12+J$6,$C$11:$AK$38,4,FALSE)/$H12,0)) -> 1 | K12: =IFERROR(VLOOKUP($C12+K$6,$C$11:$AK$38,4,FALSE)/$H12,0) -> 0 | L12: =IFERROR(VLOOKUP($C12+L$6,$C$11:$AK$38,4,FALSE)/$H12,0) -> 0 | M12: =IFERROR(VLOOKUP($C12+M$6,$C$11:$AK$38,4,FALSE)/$H12,0) -> 0 | N12: =IFERROR(VLOOKUP($C12+N$6,$C$11:$AK$38,4,FALSE)/$H12,0) -> 0 | O12: =IFERROR(VLOOKUP($C12+O$6,$C$11:$AK$38,4,FALSE)/$H12,0) -> 0 | P12: =IFERROR(VLOOKUP($C12+P$6,$C$11:$AK$38,4,FALSE)/$H12,0) -> 0 | Q12: =IFERROR(VLOOKUP($C12+Q$6,$C$11:$AK$38,4,FALSE)/$H12,0) -> 0 | R12: =IFERROR(VLOOKUP($C12+R$6,$C$11:$AK$38,4,FALSE)/$H12,0) -> 0 | ... AK12: =IFERROR(VLOOKUP($C12+AK$6,$C$11:$AK$38,4,FALSE)/$H12,0) -> 0
B13: =IBNR!F9 -> 2018Q3 | C13: =C14+3 -> 78 | D13: =_xlfn.XLOOKUP($B$8,Paid_DFs!$G$5:$S$5,Paid_DFs!$G9:$S9) -> 1 | E13: =PRODUCT($D$11:$D13) -> 1 | F13: =G13-G14 -> 0 | G13: =1/E13 -> 1 | H13: =1-G13 -> 0 | I13: =SUM(J13:AK13) -> 1 | J13: =IF($H13=0%,100%,IFERROR(VLOOKUP($C13+J$6,$C$11:$AK$38,4,FALSE)/$H13,0)) -> 1 | K13: =IFERROR(VLOOKUP($C13+K$6,$C$11:$AK$38,4,FALSE)/$H13,0) -> 0 | L13: =IFERROR(VLOOKUP($C13+L$6,$C$11:$AK$38,4,FALSE)/$H13,0) -> 0 | M13: =IFERROR(VLOOKUP($C13+M$6,$C$11:$AK$38,4,FALSE)/$H13,0) -> 0 | N13: =IFERROR(VLOOKUP($C13+N$6,$C$11:$AK$38,4,FALSE)/$H13,0) -> 0 | O13: =IFERROR(VLOOKUP($C13+O$6,$C$11:$AK$38,4,FALSE)/$H13,0) -> 0 | P13: =IFERROR(VLOOKUP($C13+P$6,$C$11:$AK$38,4,FALSE)/$H13,0) -> 0 | Q13: =IFERROR(VLOOKUP($C13+Q$6,$C$11:$AK$38,4,FALSE)/$H13,0) -> 0 | R13: =IFERROR(VLOOKUP($C13+R$6,$C$11:$AK$38,4,FALSE)/$H13,0) -> 0 | ... AK13: =IFERROR(VLOOKUP($C13+AK$6,$C$11:$AK$38,4,FALSE)/$H13,0) -> 0
B14: =IBNR!F10 -> 2018Q4 | C14: =C15+3 -> 75 | D14: =_xlfn.XLOOKUP($B$8,Paid_DFs!$G$5:$S$5,Paid_DFs!$G10:$S10) -> 1 | E14: =PRODUCT($D$11:$D14) -> 1 | F14: =G14-G15 -> 0 | G14: =1/E14 -> 1 | H14: =1-G14 -> 0 | I14: =SUM(J14:AK14) -> 1 | J14: =IF($H14=0%,100%,IFERROR(VLOOKUP($C14+J$6,$C$11:$AK$38,4,FALSE)/$H14,0)) -> 1 | K14: =IFERROR(VLOOKUP($C14+K$6,$C$11:$AK$38,4,FALSE)/$H14,0) -> 0 | L14: =IFERROR(VLOOKUP($C14+L$6,$C$11:$AK$38,4,FALSE)/$H14,0) -> 0 | M14: =IFERROR(VLOOKUP($C14+M$6,$C$11:$AK$38,4,FALSE)/$H14,0) -> 0 | N14: =IFERROR(VLOOKUP($C14+N$6,$C$11:$AK$38,4,FALSE)/$H14,0) -> 0 | O14: =IFERROR(VLOOKUP($C14+O$6,$C$11:$AK$38,4,FALSE)/$H14,0) -> 0 | P14: =IFERROR(VLOOKUP($C14+P$6,$C$11:$AK$38,4,FALSE)/$H14,0) -> 0 | Q14: =IFERROR(VLOOKUP($C14+Q$6,$C$11:$AK$38,4,FALSE)/$H14,0) -> 0 | R14: =IFERROR(VLOOKUP($C14+R$6,$C$11:$AK$38,4,FALSE)/$H14,0) -> 0 | ... AK14: =IFERROR(VLOOKUP($C14+AK$6,$C$11:$AK$38,4,FALSE)/$H14,0) -> 0
B15: =IBNR!F11 -> 2019Q1 | C15: =C16+3 -> 72 | D15: =_xlfn.XLOOKUP($B$8,Paid_DFs!$G$5:$S$5,Paid_DFs!$G11:$S11) -> 1 | E15: =PRODUCT($D$11:$D15) -> 1 | F15: =G15-G16 -> 0 | G15: =1/E15 -> 1 | H15: =1-G15 -> 0 | I15: =SUM(J15:AK15) -> 1 | J15: =IF($H15=0%,100%,IFERROR(VLOOKUP($C15+J$6,$C$11:$AK$38,4,FALSE)/$H15,0)) -> 1 | K15: =IFERROR(VLOOKUP($C15+K$6,$C$11:$AK$38,4,FALSE)/$H15,0) -> 0 | L15: =IFERROR(VLOOKUP($C15+L$6,$C$11:$AK$38,4,FALSE)/$H15,0) -> 0 | M15: =IFERROR(VLOOKUP($C15+M$6,$C$11:$AK$38,4,FALSE)/$H15,0) -> 0 | N15: =IFERROR(VLOOKUP($C15+N$6,$C$11:$AK$38,4,FALSE)/$H15,0) -> 0 | O15: =IFERROR(VLOOKUP($C15+O$6,$C$11:$AK$38,4,FALSE)/$H15,0) -> 0 | P15: =IFERROR(VLOOKUP($C15+P$6,$C$11:$AK$38,4,FALSE)/$H15,0) -> 0 | Q15: =IFERROR(VLOOKUP($C15+Q$6,$C$11:$AK$38,4,FALSE)/$H15,0) -> 0 | R15: =IFERROR(VLOOKUP($C15+R$6,$C$11:$AK$38,4,FALSE)/$H15,0) -> 0 | ... AK15: =IFERROR(VLOOKUP($C15+AK$6,$C$11:$AK$38,4,FALSE)/$H15,0) -> 0
B16: =IBNR!F12 -> 2019Q2 | C16: =C17+3 -> 69 | D16: =_xlfn.XLOOKUP($B$8,Paid_DFs!$G$5:$S$5,Paid_DFs!$G12:$S12) -> 1 | E16: =PRODUCT($D$11:$D16) -> 1 | F16: =G16-G17 -> 0 | G16: =1/E16 -> 1 | H16: =1-G16 -> 0 | I16: =SUM(J16:AK16) -> 1 | J16: =IF($H16=0%,100%,IFERROR(VLOOKUP($C16+J$6,$C$11:$AK$38,4,FALSE)/$H16,0)) -> 1 | K16: =IFERROR(VLOOKUP($C16+K$6,$C$11:$AK$38,4,FALSE)/$H16,0) -> 0 | L16: =IFERROR(VLOOKUP($C16+L$6,$C$11:$AK$38,4,FALSE)/$H16,0) -> 0 | M16: =IFERROR(VLOOKUP($C16+M$6,$C$11:$AK$38,4,FALSE)/$H16,0) -> 0 | N16: =IFERROR(VLOOKUP($C16+N$6,$C$11:$AK$38,4,FALSE)/$H16,0) -> 0 | O16: =IFERROR(VLOOKUP($C16+O$6,$C$11:$AK$38,4,FALSE)/$H16,0) -> 0 | P16: =IFERROR(VLOOKUP($C16+P$6,$C$11:$AK$38,4,FALSE)/$H16,0) -> 0 | Q16: =IFERROR(VLOOKUP($C16+Q$6,$C$11:$AK$38,4,FALSE)/$H16,0) -> 0 | R16: =IFERROR(VLOOKUP($C16+R$6,$C$11:$AK$38,4,FALSE)/$H16,0) -> 0 | ... AK16: =IFERROR(VLOOKUP($C16+AK$6,$C$11:$AK$38,4,FALSE)/$H16,0) -> 0
B17: =IBNR!F13 -> 2019Q3 | C17: =C18+3 -> 66 | D17: =_xlfn.XLOOKUP($B$8,Paid_DFs!$G$5:$S$5,Paid_DFs!$G13:$S13) -> 1 | E17: =PRODUCT($D$11:$D17) -> 1 | F17: =G17-G18 -> 0 | G17: =1/E17 -> 1 | H17: =1-G17 -> 0 | I17: =SUM(J17:AK17) -> 1 | J17: =IF($H17=0%,100%,IFERROR(VLOOKUP($C17+J$6,$C$11:$AK$38,4,FALSE)/$H17,0)) -> 1 | K17: =IFERROR(VLOOKUP($C17+K$6,$C$11:$AK$38,4,FALSE)/$H17,0) -> 0 | L17: =IFERROR(VLOOKUP($C17+L$6,$C$11:$AK$38,4,FALSE)/$H17,0) -> 0 | M17: =IFERROR(VLOOKUP($C17+M$6,$C$11:$AK$38,4,FALSE)/$H17,0) -> 0 | N17: =IFERROR(VLOOKUP($C17+N$6,$C$11:$AK$38,4,FALSE)/$H17,0) -> 0 | O17: =IFERROR(VLOOKUP($C17+O$6,$C$11:$AK$38,4,FALSE)/$H17,0) -> 0 | P17: =IFERROR(VLOOKUP($C17+P$6,$C$11:$AK$38,4,FALSE)/$H17,0) -> 0 | Q17: =IFERROR(VLOOKUP($C17+Q$6,$C$11:$AK$38,4,FALSE)/$H17,0) -> 0 | R17: =IFERROR(VLOOKUP($C17+R$6,$C$11:$AK$38,4,FALSE)/$H17,0) -> 0 | ... AK17: =IFERROR(VLOOKUP($C17+AK$6,$C$11:$AK$38,4,FALSE)/$H17,0) -> 0
B18: =IBNR!F14 -> 2019Q4 | C18: =C19+3 -> 63 | D18: =_xlfn.XLOOKUP($B$8,Paid_DFs!$G$5:$S$5,Paid_DFs!$G14:$S14) -> 1 | E18: =PRODUCT($D$11:$D18) -> 1 | F18: =G18-G19 -> 0 | G18: =1/E18 -> 1 | H18: =1-G18 -> 0 | I18: =SUM(J18:AK18) -> 1 | J18: =IF($H18=0%,100%,IFERROR(VLOOKUP($C18+J$6,$C$11:$AK$38,4,FALSE)/$H18,0)) -> 1 | K18: =IFERROR(VLOOKUP($C18+K$6,$C$11:$AK$38,4,FALSE)/$H18,0) -> 0 | L18: =IFERROR(VLOOKUP($C18+L$6,$C$11:$AK$38,4,FALSE)/$H18,0) -> 0 | M18: =IFERROR(VLOOKUP($C18+M$6,$C$11:$AK$38,4,FALSE)/$H18,0) -> 0 | N18: =IFERROR(VLOOKUP($C18+N$6,$C$11:$AK$38,4,FALSE)/$H18,0) -> 0 | O18: =IFERROR(VLOOKUP($C18+O$6,$C$11:$AK$38,4,FALSE)/$H18,0) -> 0 | P18: =IFERROR(VLOOKUP($C18+P$6,$C$11:$AK$38,4,FALSE)/$H18,0) -> 0 | Q18: =IFERROR(VLOOKUP($C18+Q$6,$C$11:$AK$38,4,FALSE)/$H18,0) -> 0 | R18: =IFERROR(VLOOKUP($C18+R$6,$C$11:$AK$38,4,FALSE)/$H18,0) -> 0 | ... AK18: =IFERROR(VLOOKUP($C18+AK$6,$C$11:$AK$38,4,FALSE)/$H18,0) -> 0
B19: =IBNR!F15 -> 2020Q1 | C19: =C20+3 -> 60 | D19: =_xlfn.XLOOKUP($B$8,Paid_DFs!$G$5:$S$5,Paid_DFs!$G15:$S15) -> 1 | E19: =PRODUCT($D$11:$D19) -> 1 | F19: =G19-G20 -> 0 | G19: =1/E19 -> 1 | H19: =1-G19 -> 0 | I19: =SUM(J19:AK19) -> 1 | J19: =IF($H19=0%,100%,IFERROR(VLOOKUP($C19+J$6,$C$11:$AK$38,4,FALSE)/$H19,0)) -> 1 | K19: =IFERROR(VLOOKUP($C19+K$6,$C$11:$AK$38,4,FALSE)/$H19,0) -> 0 | L19: =IFERROR(VLOOKUP($C19+L$6,$C$11:$AK$38,4,FALSE)/$H19,0) -> 0 | M19: =IFERROR(VLOOKUP($C19+M$6,$C$11:$AK$38,4,FALSE)/$H19,0) -> 0 | N19: =IFERROR(VLOOKUP($C19+N$6,$C$11:$AK$38,4,FALSE)/$H19,0) -> 0 | O19: =IFERROR(VLOOKUP($C19+O$6,$C$11:$AK$38,4,FALSE)/$H19,0) -> 0 | P19: =IFERROR(VLOOKUP($C19+P$6,$C$11:$AK$38,4,FALSE)/$H19,0) -> 0 | Q19: =IFERROR(VLOOKUP($C19+Q$6,$C$11:$AK$38,4,FALSE)/$H19,0) -> 0 | R19: =IFERROR(VLOOKUP($C19+R$6,$C$11:$AK$38,4,FALSE)/$H19,0) -> 0 | ... AK19: =IFERROR(VLOOKUP($C19+AK$6,$C$11:$AK$38,4,FALSE)/$H19,0) -> 0
B20: =IBNR!F16 -> 2020Q2 | C20: =C21+3 -> 57 | D20: =_xlfn.XLOOKUP($B$8,Paid_DFs!$G$5:$S$5,Paid_DFs!$G16:$S16) -> 1 | E20: =PRODUCT($D$11:$D20) -> 1 | F20: =G20-G21 -> 0 | G20: =1/E20 -> 1 | H20: =1-G20 -> 0 | I20: =SUM(J20:AK20) -> 1 | J20: =IF($H20=0%,100%,IFERROR(VLOOKUP($C20+J$6,$C$11:$AK$38,4,FALSE)/$H20,0)) -> 1 | K20: =IFERROR(VLOOKUP($C20+K$6,$C$11:$AK$38,4,FALSE)/$H20,0) -> 0 | L20: =IFERROR(VLOOKUP($C20+L$6,$C$11:$AK$38,4,FALSE)/$H20,0) -> 0 | M20: =IFERROR(VLOOKUP($C20+M$6,$C$11:$AK$38,4,FALSE)/$H20,0) -> 0 | N20: =IFERROR(VLOOKUP($C20+N$6,$C$11:$AK$38,4,FALSE)/$H20,0) -> 0 | O20: =IFERROR(VLOOKUP($C20+O$6,$C$11:$AK$38,4,FALSE)/$H20,0) -> 0 | P20: =IFERROR(VLOOKUP($C20+P$6,$C$11:$AK$38,4,FALSE)/$H20,0) -> 0 | Q20: =IFERROR(VLOOKUP($C20+Q$6,$C$11:$AK$38,4,FALSE)/$H20,0) -> 0 | R20: =IFERROR(VLOOKUP($C20+R$6,$C$11:$AK$38,4,FALSE)/$H20,0) -> 0 | ... AK20: =IFERROR(VLOOKUP($C20+AK$6,$C$11:$AK$38,4,FALSE)/$H20,0) -> 0
B21: =IBNR!F17 -> 2020Q3 | C21: =C22+3 -> 54 | D21: =_xlfn.XLOOKUP($B$8,Paid_DFs!$G$5:$S$5,Paid_DFs!$G17:$S17) -> 1 | E21: =PRODUCT($D$11:$D21) -> 1 | F21: =G21-G22 -> 0 | G21: =1/E21 -> 1 | H21: =1-G21 -> 0 | I21: =SUM(J21:AK21) -> 1 | J21: =IF($H21=0%,100%,IFERROR(VLOOKUP($C21+J$6,$C$11:$AK$38,4,FALSE)/$H21,0)) -> 1 | K21: =IFERROR(VLOOKUP($C21+K$6,$C$11:$AK$38,4,FALSE)/$H21,0) -> 0 | L21: =IFERROR(VLOOKUP($C21+L$6,$C$11:$AK$38,4,FALSE)/$H21,0) -> 0 | M21: =IFERROR(VLOOKUP($C21+M$6,$C$11:$AK$38,4,FALSE)/$H21,0) -> 0 | N21: =IFERROR(VLOOKUP($C21+N$6,$C$11:$AK$38,4,FALSE)/$H21,0) -> 0 | O21: =IFERROR(VLOOKUP($C21+O$6,$C$11:$AK$38,4,FALSE)/$H21,0) -> 0 | P21: =IFERROR(VLOOKUP($C21+P$6,$C$11:$AK$38,4,FALSE)/$H21,0) -> 0 | Q21: =IFERROR(VLOOKUP($C21+Q$6,$C$11:$AK$38,4,FALSE)/$H21,0) -> 0 | R21: =IFERROR(VLOOKUP($C21+R$6,$C$11:$AK$38,4,FALSE)/$H21,0) -> 0 | ... AK21: =IFERROR(VLOOKUP($C21+AK$6,$C$11:$AK$38,4,FALSE)/$H21,0) -> 0
B22: =IBNR!F18 -> 2020Q4 | C22: =C23+3 -> 51 | D22: =_xlfn.XLOOKUP($B$8,Paid_DFs!$G$5:$S$5,Paid_DFs!$G18:$S18) -> 1 | E22: =PRODUCT($D$11:$D22) -> 1 | F22: =G22-G23 -> 0 | G22: =1/E22 -> 1 | H22: =1-G22 -> 0 | I22: =SUM(J22:AK22) -> 1 | J22: =IF($H22=0%,100%,IFERROR(VLOOKUP($C22+J$6,$C$11:$AK$38,4,FALSE)/$H22,0)) -> 1 | K22: =IFERROR(VLOOKUP($C22+K$6,$C$11:$AK$38,4,FALSE)/$H22,0) -> 0 | L22: =IFERROR(VLOOKUP($C22+L$6,$C$11:$AK$38,4,FALSE)/$H22,0) -> 0 | M22: =IFERROR(VLOOKUP($C22+M$6,$C$11:$AK$38,4,FALSE)/$H22,0) -> 0 | N22: =IFERROR(VLOOKUP($C22+N$6,$C$11:$AK$38,4,FALSE)/$H22,0) -> 0 | O22: =IFERROR(VLOOKUP($C22+O$6,$C$11:$AK$38,4,FALSE)/$H22,0) -> 0 | P22: =IFERROR(VLOOKUP($C22+P$6,$C$11:$AK$38,4,FALSE)/$H22,0) -> 0 | Q22: =IFERROR(VLOOKUP($C22+Q$6,$C$11:$AK$38,4,FALSE)/$H22,0) -> 0 | R22: =IFERROR(VLOOKUP($C22+R$6,$C$11:$AK$38,4,FALSE)/$H22,0) -> 0 | ... AK22: =IFERROR(VLOOKUP($C22+AK$6,$C$11:$AK$38,4,FALSE)/$H22,0) -> 0
... B30: =IBNR!F26 -> 2022Q4 | C30: =C31+3 -> 27 | D30: =_xlfn.XLOOKUP($B$8,Paid_DFs!$G$5:$S$5,Paid_DFs!$G26:$S26) -> 1 | E30: =PRODUCT($D$11:$D30) -> 1 | F30: =G30-G31 -> 1.7073477e-05 | G30: =1/E30 -> 1 | H30: =1-G30 -> 0 | I30: =SUM(J30:AK30) -> 1 | J30: =IF($H30=0%,100%,IFERROR(VLOOKUP($C30+J$6,$C$11:$AK$38,4,FALSE)/$H30,0)) -> 1 | K30: =IFERROR(VLOOKUP($C30+K$6,$C$11:$AK$38,4,FALSE)/$H30,0) -> 0 | L30: =IFERROR(VLOOKUP($C30+L$6,$C$11:$AK$38,4,FALSE)/$H30,0) -> 0 | M30: =IFERROR(VLOOKUP($C30+M$6,$C$11:$AK$38,4,FALSE)/$H30,0) -> 0 | N30: =IFERROR(VLOOKUP($C30+N$6,$C$11:$AK$38,4,FALSE)/$H30,0) -> 0 | O30: =IFERROR(VLOOKUP($C30+O$6,$C$11:$AK$38,4,FALSE)/$H30,0) -> 0 | P30: =IFERROR(VLOOKUP($C30+P$6,$C$11:$AK$38,4,FALSE)/$H30,0) -> 0 | Q30: =IFERROR(VLOOKUP($C30+Q$6,$C$11:$AK$38,4,FALSE)/$H30,0) -> 0 | R30: =IFERROR(VLOOKUP($C30+R$6,$C$11:$AK$38,4,FALSE)/$H30,0) -> 0 | ... AK30: =IFERROR(VLOOKUP($C30+AK$6,$C$11:$AK$38,4,FALSE)/$H30,0) -> 0
B31: 2023Q1 | C31: =C32+3 -> 24 | D31: =_xlfn.XLOOKUP($B$8,Paid_DFs!$G$5:$S$5,Paid_DFs!$G27:$S27) -> 1.0000171 | E31: =PRODUCT($D$11:$D31) -> 1.0000171 | F31: =G31-G32 -> 1.109567e-05 | G31: =1/E31 -> 0.99998293 | H31: =1-G31 -> 1.7073477e-05 | I31: =SUM(J31:AK31) -> 1 | J31: =IF($H31=0%,100%,IFERROR(VLOOKUP($C31+J$6,$C$11:$AK$38,4,FALSE)/$H31,0)) -> 1 | K31: =IFERROR(VLOOKUP($C31+K$6,$C$11:$AK$38,4,FALSE)/$H31,0) -> 0 | L31: =IFERROR(VLOOKUP($C31+L$6,$C$11:$AK$38,4,FALSE)/$H31,0) -> 0 | M31: =IFERROR(VLOOKUP($C31+M$6,$C$11:$AK$38,4,FALSE)/$H31,0) -> 0 | N31: =IFERROR(VLOOKUP($C31+N$6,$C$11:$AK$38,4,FALSE)/$H31,0) -> 0 | O31: =IFERROR(VLOOKUP($C31+O$6,$C$11:$AK$38,4,FALSE)/$H31,0) -> 0 | P31: =IFERROR(VLOOKUP($C31+P$6,$C$11:$AK$38,4,FALSE)/$H31,0) -> 0 | Q31: =IFERROR(VLOOKUP($C31+Q$6,$C$11:$AK$38,4,FALSE)/$H31,0) -> 0 | R31: =IFERROR(VLOOKUP($C31+R$6,$C$11:$AK$38,4,FALSE)/$H31,0) -> 0 | ... AK31: =IFERROR(VLOOKUP($C31+AK$6,$C$11:$AK$38,4,FALSE)/$H31,0) -> 0
B32: 2023Q2 | C32: =C33+3 -> 21 | D32: =_xlfn.XLOOKUP($B$8,Paid_DFs!$G$5:$S$5,Paid_DFs!$G28:$S28) -> 1.0000111 | E32: =PRODUCT($D$11:$D32) -> 1.0000282 | F32: =G32-G33 -> 3.6010679e-05 | G32: =1/E32 -> 0.99997183 | H32: =1-G32 -> 2.8169147e-05 | I32: =SUM(J32:AK32) -> 1 | J32: =IF($H32=0%,100%,IFERROR(VLOOKUP($C32+J$6,$C$11:$AK$38,4,FALSE)/$H32,0)) -> 0.39389444 | K32: =IFERROR(VLOOKUP($C32+K$6,$C$11:$AK$38,4,FALSE)/$H32,0) -> 0.60610556 | L32: =IFERROR(VLOOKUP($C32+L$6,$C$11:$AK$38,4,FALSE)/$H32,0) -> 0 | M32: =IFERROR(VLOOKUP($C32+M$6,$C$11:$AK$38,4,FALSE)/$H32,0) -> 0 | N32: =IFERROR(VLOOKUP($C32+N$6,$C$11:$AK$38,4,FALSE)/$H32,0) -> 0 | O32: =IFERROR(VLOOKUP($C32+O$6,$C$11:$AK$38,4,FALSE)/$H32,0) -> 0 | P32: =IFERROR(VLOOKUP($C32+P$6,$C$11:$AK$38,4,FALSE)/$H32,0) -> 0 | Q32: =IFERROR(VLOOKUP($C32+Q$6,$C$11:$AK$38,4,FALSE)/$H32,0) -> 0 | R32: =IFERROR(VLOOKUP($C32+R$6,$C$11:$AK$38,4,FALSE)/$H32,0) -> 0 | ... AK32: =IFERROR(VLOOKUP($C32+AK$6,$C$11:$AK$38,4,FALSE)/$H32,0) -> 0
B33: 2023Q3 | C33: =C34+3 -> 18 | D33: =_xlfn.XLOOKUP($B$8,Paid_DFs!$G$5:$S$5,Paid_DFs!$G29:$S29) -> 1.000036 | E33: =PRODUCT($D$11:$D33) -> 1.0000642 | F33: =G33-G34 -> 0.00074028362 | G33: =1/E33 -> 0.99993582 | H33: =1-G33 -> 6.4179826e-05 | I33: =SUM(J33:AK33) -> 1 | J33: =IF($H33=0%,100%,IFERROR(VLOOKUP($C33+J$6,$C$11:$AK$38,4,FALSE)/$H33,0)) -> 0.56109032 | K33: =IFERROR(VLOOKUP($C33+K$6,$C$11:$AK$38,4,FALSE)/$H33,0) -> 0.17288408 | L33: =IFERROR(VLOOKUP($C33+L$6,$C$11:$AK$38,4,FALSE)/$H33,0) -> 0.2660256 | M33: =IFERROR(VLOOKUP($C33+M$6,$C$11:$AK$38,4,FALSE)/$H33,0) -> 0 | N33: =IFERROR(VLOOKUP($C33+N$6,$C$11:$AK$38,4,FALSE)/$H33,0) -> 0 | O33: =IFERROR(VLOOKUP($C33+O$6,$C$11:$AK$38,4,FALSE)/$H33,0) -> 0 | P33: =IFERROR(VLOOKUP($C33+P$6,$C$11:$AK$38,4,FALSE)/$H33,0) -> 0 | Q33: =IFERROR(VLOOKUP($C33+Q$6,$C$11:$AK$38,4,FALSE)/$H33,0) -> 0 | R33: =IFERROR(VLOOKUP($C33+R$6,$C$11:$AK$38,4,FALSE)/$H33,0) -> 0 | ... AK33: =IFERROR(VLOOKUP($C33+AK$6,$C$11:$AK$38,4,FALSE)/$H33,0) -> 0
B34: 2023Q4 | C34: =C35+3 -> 15 | D34: =_xlfn.XLOOKUP($B$8,Paid_DFs!$G$5:$S$5,Paid_DFs!$G30:$S30) -> 1.0007409 | E34: =PRODUCT($D$11:$D34) -> 1.0008051 | F34: =G34-G35 -> 0.002132283 | G34: =1/E34 -> 0.99919554 | H34: =1-G34 -> 0.00080446345 | I34: =SUM(J34:AK34) -> 1 | J34: =IF($H34=0%,100%,IFERROR(VLOOKUP($C34+J$6,$C$11:$AK$38,4,FALSE)/$H34,0)) -> 0.92022033 | K34: =IFERROR(VLOOKUP($C34+K$6,$C$11:$AK$38,4,FALSE)/$H34,0) -> 0.044763599 | L34: =IFERROR(VLOOKUP($C34+L$6,$C$11:$AK$38,4,FALSE)/$H34,0) -> 0.013792634 | M34: =IFERROR(VLOOKUP($C34+M$6,$C$11:$AK$38,4,FALSE)/$H34,0) -> 0.021223434 | N34: =IFERROR(VLOOKUP($C34+N$6,$C$11:$AK$38,4,FALSE)/$H34,0) -> 0 | O34: =IFERROR(VLOOKUP($C34+O$6,$C$11:$AK$38,4,FALSE)/$H34,0) -> 0 | P34: =IFERROR(VLOOKUP($C34+P$6,$C$11:$AK$38,4,FALSE)/$H34,0) -> 0 | Q34: =IFERROR(VLOOKUP($C34+Q$6,$C$11:$AK$38,4,FALSE)/$H34,0) -> 0 | R34: =IFERROR(VLOOKUP($C34+R$6,$C$11:$AK$38,4,FALSE)/$H34,0) -> 0 | ... AK34: =IFERROR(VLOOKUP($C34+AK$6,$C$11:$AK$38,4,FALSE)/$H34,0) -> 0
B35: 2024Q1 | C35: =C36+3 -> 12 | D35: =_xlfn.XLOOKUP($B$8,Paid_DFs!$G$5:$S$5,Paid_DFs!$G31:$S31) -> 1.0021386 | E35: =PRODUCT($D$11:$D35) -> 1.0029454 | F35: =G35-G36 -> 0.0007774372 | G35: =1/E35 -> 0.99706325 | H35: =1-G35 -> 0.0029367465 | I35: =SUM(J35:AK35) -> 1 | J35: =IF($H35=0%,100%,IFERROR(VLOOKUP($C35+J$6,$C$11:$AK$38,4,FALSE)/$H35,0)) -> 0.72606983 | K35: =IFERROR(VLOOKUP($C35+K$6,$C$11:$AK$38,4,FALSE)/$H35,0) -> 0.25207611 | L35: =IFERROR(VLOOKUP($C35+L$6,$C$11:$AK$38,4,FALSE)/$H35,0) -> 0.0122621 | M35: =IFERROR(VLOOKUP($C35+M$6,$C$11:$AK$38,4,FALSE)/$H35,0) -> 0.0037782187 | N35: =IFERROR(VLOOKUP($C35+N$6,$C$11:$AK$38,4,FALSE)/$H35,0) -> 0.0058137388 | O35: =IFERROR(VLOOKUP($C35+O$6,$C$11:$AK$38,4,FALSE)/$H35,0) -> 0 | P35: =IFERROR(VLOOKUP($C35+P$6,$C$11:$AK$38,4,FALSE)/$H35,0) -> 0 | Q35: =IFERROR(VLOOKUP($C35+Q$6,$C$11:$AK$38,4,FALSE)/$H35,0) -> 0 | R35: =IFERROR(VLOOKUP($C35+R$6,$C$11:$AK$38,4,FALSE)/$H35,0) -> 0 | ... AK35: =IFERROR(VLOOKUP($C35+AK$6,$C$11:$AK$38,4,FALSE)/$H35,0) -> 0
B36: 2024Q2 | C36: =C37+3 -> 9 | D36: =_xlfn.XLOOKUP($B$8,Paid_DFs!$G$5:$S$5,Paid_DFs!$G32:$S32) -> 1.0007803 | E36: =PRODUCT($D$11:$D36) -> 1.003728 | F36: =G36-G37 -> 0.00329132 | G36: =1/E36 -> 0.99628582 | H36: =1-G36 -> 0.0037141837 | I36: =SUM(J36:AK36) -> 1 | J36: =IF($H36=0%,100%,IFERROR(VLOOKUP($C36+J$6,$C$11:$AK$38,4,FALSE)/$H36,0)) -> 0.20931577 | K36: =IFERROR(VLOOKUP($C36+K$6,$C$11:$AK$38,4,FALSE)/$H36,0) -> 0.57409197 | L36: =IFERROR(VLOOKUP($C36+L$6,$C$11:$AK$38,4,FALSE)/$H36,0) -> 0.19931261 | M36: =IFERROR(VLOOKUP($C36+M$6,$C$11:$AK$38,4,FALSE)/$H36,0) -> 0.0096954492 | N36: =IFERROR(VLOOKUP($C36+N$6,$C$11:$AK$38,4,FALSE)/$H36,0) -> 0.0029873779 | O36: =IFERROR(VLOOKUP($C36+O$6,$C$11:$AK$38,4,FALSE)/$H36,0) -> 0.0045968316 | P36: =IFERROR(VLOOKUP($C36+P$6,$C$11:$AK$38,4,FALSE)/$H36,0) -> 0 | Q36: =IFERROR(VLOOKUP($C36+Q$6,$C$11:$AK$38,4,FALSE)/$H36,0) -> 0 | R36: =IFERROR(VLOOKUP($C36+R$6,$C$11:$AK$38,4,FALSE)/$H36,0) -> 0 | ... AK36: =IFERROR(VLOOKUP($C36+AK$6,$C$11:$AK$38,4,FALSE)/$H36,0) -> 0
B37: 2024Q3 | C37: =C38+3 -> 6 | D37: =_xlfn.XLOOKUP($B$8,Paid_DFs!$G$5:$S$5,Paid_DFs!$G33:$S33) -> 1.0033145 | E37: =PRODUCT($D$11:$D37) -> 1.0070549 | F37: =G37-G38 -> 0.027613201 | G37: =1/E37 -> 0.9929945 | H37: =1-G37 -> 0.0070055037 | I37: =SUM(J37:AK37) -> 1 | J37: =IF($H37=0%,100%,IFERROR(VLOOKUP($C37+J$6,$C$11:$AK$38,4,FALSE)/$H37,0)) -> 0.46981918 | K37: =IFERROR(VLOOKUP($C37+K$6,$C$11:$AK$38,4,FALSE)/$H37,0) -> 0.1109752 | L37: =IFERROR(VLOOKUP($C37+L$6,$C$11:$AK$38,4,FALSE)/$H37,0) -> 0.30437255 | M37: =IFERROR(VLOOKUP($C37+M$6,$C$11:$AK$38,4,FALSE)/$H37,0) -> 0.10567172 | N37: =IFERROR(VLOOKUP($C37+N$6,$C$11:$AK$38,4,FALSE)/$H37,0) -> 0.0051403412 | O37: =IFERROR(VLOOKUP($C37+O$6,$C$11:$AK$38,4,FALSE)/$H37,0) -> 0.0015838505 | P37: =IFERROR(VLOOKUP($C37+P$6,$C$11:$AK$38,4,FALSE)/$H37,0) -> 0.0024371519 | Q37: =IFERROR(VLOOKUP($C37+Q$6,$C$11:$AK$38,4,FALSE)/$H37,0) -> 0 | R37: =IFERROR(VLOOKUP($C37+R$6,$C$11:$AK$38,4,FALSE)/$H37,0) -> 0 | ... AK37: =IFERROR(VLOOKUP($C37+AK$6,$C$11:$AK$38,4,FALSE)/$H37,0) -> 0
B38: 2024Q4 | C38: =C39+3 -> 3 | D38: =_xlfn.XLOOKUP($B$8,Paid_DFs!$G$5:$S$5,Paid_DFs!$G34:$S34) -> 1.0286034 | E38: =PRODUCT($D$11:$D38) -> 1.0358601 | F38: =G38-G39 -> 0.96538129 | G38: =1/E38 -> 0.96538129 | H38: =1-G38 -> 0.034618705 | I38: =SUM(J38:AK38) -> 1 | J38: =IF($H38=0%,100%,IFERROR(VLOOKUP($C38+J$6,$C$11:$AK$38,4,FALSE)/$H38,0)) -> 0.79763819 | K38: =IFERROR(VLOOKUP($C38+K$6,$C$11:$AK$38,4,FALSE)/$H38,0) -> 0.095073458 | L38: =IFERROR(VLOOKUP($C38+L$6,$C$11:$AK$38,4,FALSE)/$H38,0) -> 0.022457143 | M38: =IFERROR(VLOOKUP($C38+M$6,$C$11:$AK$38,4,FALSE)/$H38,0) -> 0.061593378 | N38: =IFERROR(VLOOKUP($C38+N$6,$C$11:$AK$38,4,FALSE)/$H38,0) -> 0.02138392 | O38: =IFERROR(VLOOKUP($C38+O$6,$C$11:$AK$38,4,FALSE)/$H38,0) -> 0.0010402087 | P38: =IFERROR(VLOOKUP($C38+P$6,$C$11:$AK$38,4,FALSE)/$H38,0) -> 0.00032051084 | Q38: =IFERROR(VLOOKUP($C38+Q$6,$C$11:$AK$38,4,FALSE)/$H38,0) -> 0.00049318646 | R38: =IFERROR(VLOOKUP($C38+R$6,$C$11:$AK$38,4,FALSE)/$H38,0) -> 0 | ... AK38: =IFERROR(VLOOKUP($C38+AK$6,$C$11:$AK$38,4,FALSE)/$H38,0) -> 0
B39: Total | H39: =SUM(H11:H38) -> 0.049189025 | J39: =SUM(J11:J38) -> 25.078048 | K39: =SUM(K11:K38) -> 1.85597 | L39: =SUM(L11:L38) -> 0.81822263 | M39: =SUM(M11:M38) -> 0.2019622 | N39: =SUM(N11:N38) -> 0.035325378 | O39: =SUM(O11:O38) -> 0.0072208908 | P39: =SUM(P11:P38) -> 0.0027576628 | Q39: =SUM(Q11:Q38) -> 0.00049318646 | ... AK39: =SUM(AK11:AK38) -> 0
I41: =1-I38 -> 0 | K41: =F33/H38 -> 0.02138392
H42: =H39-H40 -> 0.049189025 | I42: 2.6982819e-05 | J42: 0
I43: 2.4244783e-05
B45: =B8 -> Fire Industrial
J46: Time (in years)
E47: Origin | F47: OCR | G47: IBNR | H47: Claims Provision | I47: Check | J47: =J10 -> 0.12 | K47: =K10 -> 0.38 | L47: =L10 -> 0.62 | M47: =M10 -> 0.88 | N47: =N10 -> 1.12 | O47: =O10 -> 1.38 | P47: =P10 -> 1.62 | Q47: =Q10 -> 1.88 | ... AD47: =AD10 -> 5.12 | AE47: 5.38 | AF47: 5.62 | AG47: 5.88 | AH47: 6.12 | AI47: 6.38 | AJ47: 6.62 | AK47: 6.88
E48: =B11 -> 2018Q1 | F48: =_xlfn.XLOOKUP($B$8,OCR!$D$2:$P$2,OCR!$D4:$P4) -> 2200000 | G48: =_xlfn.XLOOKUP($B$8,IBNR!$G$5:$S$5,IBNR!$G7:$S7) -> 2.2178352e-08 | H48: =SUM(F48:G48) -> 2200000 | I48: =SUM(J48:AK48) -> 2200000 | J48: =$H48*J11 -> 2200000 | K48: =$H48*K11 -> 0 | L48: =$H48*L11 -> 0 | M48: =$H48*M11 -> 0 | N48: =$H48*N11 -> 0 | O48: =$H48*O11 -> 0 | P48: =$H48*P11 -> 0 | Q48: =$H48*Q11 -> 0 | ... AK48: =$H48*AK11 -> 0
E49: =B12 -> 2018Q2 | F49: =_xlfn.XLOOKUP($B$8,OCR!$D$2:$P$2,OCR!$D5:$P5) -> 0 | G49: =_xlfn.XLOOKUP($B$8,IBNR!$G$5:$S$5,IBNR!$G8:$S8) -> 5.6009666e-08 | H49: =SUM(F49:G49) -> 5.6009666e-08 | I49: =SUM(J49:AK49) -> 5.6009666e-08 | J49: =$H49*J12 -> 5.6009666e-08 | K49: =$H49*K12 -> 0 | L49: =$H49*L12 -> 0 | M49: =$H49*M12 -> 0 | N49: =$H49*N12 -> 0 | O49: =$H49*O12 -> 0 | P49: =$H49*P12 -> 0 | Q49: =$H49*Q12 -> 0 | ... AK49: =$H49*AK12 -> 0
E50: =B13 -> 2018Q3 | F50: =_xlfn.XLOOKUP($B$8,OCR!$D$2:$P$2,OCR!$D6:$P6) -> 0 | G50: =_xlfn.XLOOKUP($B$8,IBNR!$G$5:$S$5,IBNR!$G9:$S9) -> 2.2178352e-08 | H50: =SUM(F50:G50) -> 2.2178352e-08 | I50: =SUM(J50:AK50) -> 2.2178352e-08 | J50: =$H50*J13 -> 2.2178352e-08 | K50: =$H50*K13 -> 0 | L50: =$H50*L13 -> 0 | M50: =$H50*M13 -> 0 | N50: =$H50*N13 -> 0 | O50: =$H50*O13 -> 0 | P50: =$H50*P13 -> 0 | Q50: =$H50*Q13 -> 0 | ... AK50: =$H50*AK13 -> 0
E51: =B14 -> 2018Q4 | F51: =_xlfn.XLOOKUP($B$8,OCR!$D$2:$P$2,OCR!$D7:$P7) -> 0 | G51: =_xlfn.XLOOKUP($B$8,IBNR!$G$5:$S$5,IBNR!$G10:$S10) -> 2.2178352e-08 | H51: =SUM(F51:G51) -> 2.2178352e-08 | I51: =SUM(J51:AK51) -> 2.2178352e-08 | J51: =$H51*J14 -> 2.2178352e-08 | K51: =$H51*K14 -> 0 | L51: =$H51*L14 -> 0 | M51: =$H51*M14 -> 0 | N51: =$H51*N14 -> 0 | O51: =$H51*O14 -> 0 | P51: =$H51*P14 -> 0 | Q51: =$H51*Q14 -> 0 | ... AK51: =$H51*AK14 -> 0
E52: =B15 -> 2019Q1 | F52: =_xlfn.XLOOKUP($B$8,OCR!$D$2:$P$2,OCR!$D8:$P8) -> 0 | G52: =_xlfn.XLOOKUP($B$8,IBNR!$G$5:$S$5,IBNR!$G11:$S11) -> 9.1195113e-09 | H52: =SUM(F52:G52) -> 9.1195113e-09 | I52: =SUM(J52:AK52) -> 9.1195113e-09 | J52: =$H52*J15 -> 9.1195113e-09 | K52: =$H52*K15 -> 0 | L52: =$H52*L15 -> 0 | M52: =$H52*M15 -> 0 | N52: =$H52*N15 -> 0 | O52: =$H52*O15 -> 0 | P52: =$H52*P15 -> 0 | Q52: =$H52*Q15 -> 0 | ... AK52: =$H52*AK15 -> 0
E53: =B16 -> 2019Q2 | F53: =_xlfn.XLOOKUP($B$8,OCR!$D$2:$P$2,OCR!$D9:$P9) -> 1650000 | G53: =_xlfn.XLOOKUP($B$8,IBNR!$G$5:$S$5,IBNR!$G12:$S12) -> 7.9457054e-09 | H53: =SUM(F53:G53) -> 1650000 | I53: =SUM(J53:AK53) -> 1650000 | J53: =$H53*J16 -> 1650000 | K53: =$H53*K16 -> 0 | L53: =$H53*L16 -> 0 | M53: =$H53*M16 -> 0 | N53: =$H53*N16 -> 0 | O53: =$H53*O16 -> 0 | P53: =$H53*P16 -> 0 | Q53: =$H53*Q16 -> 0 | ... AK53: =$H53*AK16 -> 0
E54: =B17 -> 2019Q3 | F54: =_xlfn.XLOOKUP($B$8,OCR!$D$2:$P$2,OCR!$D10:$P10) -> 0 | G54: =_xlfn.XLOOKUP($B$8,IBNR!$G$5:$S$5,IBNR!$G13:$S13) -> 7.9457054e-09 | H54: =SUM(F54:G54) -> 7.9457054e-09 | I54: =SUM(J54:AK54) -> 7.9457054e-09 | J54: =$H54*J17 -> 7.9457054e-09 | K54: =$H54*K17 -> 0 | L54: =$H54*L17 -> 0 | M54: =$H54*M17 -> 0 | N54: =$H54*N17 -> 0 | O54: =$H54*O17 -> 0 | P54: =$H54*P17 -> 0 | Q54: =$H54*Q17 -> 0 | ... AK54: =$H54*AK17 -> 0
E55: =B18 -> 2019Q4 | F55: =_xlfn.XLOOKUP($B$8,OCR!$D$2:$P$2,OCR!$D11:$P11) -> 0 | G55: =_xlfn.XLOOKUP($B$8,IBNR!$G$5:$S$5,IBNR!$G14:$S14) -> 1.7601958e-08 | H55: =SUM(F55:G55) -> 1.7601958e-08 | I55: =SUM(J55:AK55) -> 1.7601958e-08 | J55: =$H55*J18 -> 1.7601958e-08 | K55: =$H55*K18 -> 0 | L55: =$H55*L18 -> 0 | M55: =$H55*M18 -> 0 | N55: =$H55*N18 -> 0 | O55: =$H55*O18 -> 0 | P55: =$H55*P18 -> 0 | Q55: =$H55*Q18 -> 0 | ... AK55: =$H55*AK18 -> 0
E56: =B19 -> 2020Q1 | F56: =_xlfn.XLOOKUP($B$8,OCR!$D$2:$P$2,OCR!$D12:$P12) -> 0 | G56: =_xlfn.XLOOKUP($B$8,IBNR!$G$5:$S$5,IBNR!$G15:$S15) -> 1.3349376e-08 | H56: =SUM(F56:G56) -> 1.3349376e-08 | I56: =SUM(J56:AK56) -> 1.3349376e-08 | J56: =$H56*J19 -> 1.3349376e-08 | K56: =$H56*K19 -> 0 | L56: =$H56*L19 -> 0 | M56: =$H56*M19 -> 0 | N56: =$H56*N19 -> 0 | O56: =$H56*O19 -> 0 | P56: =$H56*P19 -> 0 | Q56: =$H56*Q19 -> 0 | ... AK56: =$H56*AK19 -> 0
E57: =B20 -> 2020Q2 | F57: =_xlfn.XLOOKUP($B$8,OCR!$D$2:$P$2,OCR!$D13:$P13) -> 0 | G57: =_xlfn.XLOOKUP($B$8,IBNR!$G$5:$S$5,IBNR!$G16:$S16) -> 2.3635352e-08 | H57: =SUM(F57:G57) -> 2.3635352e-08 | I57: =SUM(J57:AK57) -> 2.3635352e-08 | J57: =$H57*J20 -> 2.3635352e-08 | K57: =$H57*K20 -> 0 | L57: =$H57*L20 -> 0 | M57: =$H57*M20 -> 0 | N57: =$H57*N20 -> 0 | O57: =$H57*O20 -> 0 | P57: =$H57*P20 -> 0 | Q57: =$H57*Q20 -> 0 | ... AK57: =$H57*AK20 -> 0
E58: =B21 -> 2020Q3 | F58: =_xlfn.XLOOKUP($B$8,OCR!$D$2:$P$2,OCR!$D14:$P14) -> 110000 | G58: =_xlfn.XLOOKUP($B$8,IBNR!$G$5:$S$5,IBNR!$G17:$S17) -> 1.3349376e-08 | H58: =SUM(F58:G58) -> 110000 | I58: =SUM(J58:AK58) -> 110000 | J58: =$H58*J21 -> 110000 | K58: =$H58*K21 -> 0 | L58: =$H58*L21 -> 0 | M58: =$H58*M21 -> 0 | N58: =$H58*N21 -> 0 | O58: =$H58*O21 -> 0 | P58: =$H58*P21 -> 0 | Q58: =$H58*Q21 -> 0 | ... AK58: =$H58*AK21 -> 0
E59: =B22 -> 2020Q4 | F59: =_xlfn.XLOOKUP($B$8,OCR!$D$2:$P$2,OCR!$D15:$P15) -> 0 | G59: =_xlfn.XLOOKUP($B$8,IBNR!$G$5:$S$5,IBNR!$G18:$S18) -> 1.3349376e-08 | H59: =SUM(F59:G59) -> 1.3349376e-08 | I59: =SUM(J59:AK59) -> 1.3349376e-08 | J59: =$H59*J22 -> 1.3349376e-08 | K59: =$H59*K22 -> 0 | L59: =$H59*L22 -> 0 | M59: =$H59*M22 -> 0 | N59: =$H59*N22 -> 0 | O59: =$H59*O22 -> 0 | P59: =$H59*P22 -> 0 | Q59: =$H59*Q22 -> 0 | ... AK59: =$H59*AK22 -> 0
... E67: =B30 -> 2022Q4 | F67: =_xlfn.XLOOKUP($B$8,OCR!$D$2:$P$2,OCR!$D23:$P23) -> 165000 | G67: =_xlfn.XLOOKUP($B$8,IBNR!$G$5:$S$5,IBNR!$G26:$S26) -> 6.0435968e-09 | H67: =SUM(F67:G67) -> 165000 | I67: =SUM(J67:AK67) -> 165000 | J67: =$H67*J30 -> 165000 | K67: =$H67*K30 -> 0 | L67: =$H67*L30 -> 0 | M67: =$H67*M30 -> 0 | N67: =$H67*N30 -> 0 | O67: =$H67*O30 -> 0 | P67: =$H67*P30 -> 0 | Q67: =$H67*Q30 -> 0 | ... AK67: =$H67*AK30 -> 0
E68: 2023Q1 | F68: =_xlfn.XLOOKUP($B$8,OCR!$D$2:$P$2,OCR!$D24:$P24) -> 0 | G68: =_xlfn.XLOOKUP($B$8,IBNR!$G$5:$S$5,IBNR!$G27:$S27) -> 150.95074 | H68: =SUM(F68:G68) -> 150.95074 | I68: =SUM(J68:AK68) -> 150.95074 | J68: =$H68*J31 -> 150.95074 | K68: =$H68*K31 -> 0 | L68: =$H68*L31 -> 0 | M68: =$H68*M31 -> 0 | N68: =$H68*N31 -> 0 | O68: =$H68*O31 -> 0 | P68: =$H68*P31 -> 0 | Q68: =$H68*Q31 -> 0 | ... AK68: =$H68*AK31 -> 0
E69: 2023Q2 | F69: =_xlfn.XLOOKUP($B$8,OCR!$D$2:$P$2,OCR!$D25:$P25) -> 2005560.7 | G69: =_xlfn.XLOOKUP($B$8,IBNR!$G$5:$S$5,IBNR!$G28:$S28) -> 249.0354 | H69: =SUM(F69:G69) -> 2005809.7 | I69: =SUM(J69:AK69) -> 2005809.7 | J69: =$H69*J32 -> 790077.29 | K69: =$H69*K32 -> 1215732.4 | L69: =$H69*L32 -> 0 | M69: =$H69*M32 -> 0 | N69: =$H69*N32 -> 0 | O69: =$H69*O32 -> 0 | P69: =$H69*P32 -> 0 | Q69: =$H69*Q32 -> 0 | ... AK69: =$H69*AK32 -> 0
E70: 2023Q3 | F70: =_xlfn.XLOOKUP($B$8,OCR!$D$2:$P$2,OCR!$D26:$P26) -> 495000 | G70: =_xlfn.XLOOKUP($B$8,IBNR!$G$5:$S$5,IBNR!$G29:$S29) -> 567.30325 | H70: =SUM(F70:G70) -> 495567.3 | I70: =SUM(J70:AK70) -> 495567.3 | J70: =$H70*J33 -> 278058.02 | K70: =$H70*K33 -> 85675.698 | L70: =$H70*L33 -> 131833.59 | M70: =$H70*M33 -> 0 | N70: =$H70*N33 -> 0 | O70: =$H70*O33 -> 0 | P70: =$H70*P33 -> 0 | Q70: =$H70*Q33 -> 0 | ... AK70: =$H70*AK33 -> 0
E71: 2023Q4 | F71: =_xlfn.XLOOKUP($B$8,OCR!$D$2:$P$2,OCR!$D27:$P27) -> 80151.5 | G71: =_xlfn.XLOOKUP($B$8,IBNR!$G$5:$S$5,IBNR!$G30:$S30) -> 7109.506 | H71: =SUM(F71:G71) -> 87261.006 | I71: =SUM(J71:AK71) -> 87261.006 | J71: =$H71*J34 -> 80299.352 | K71: =$H71*K34 -> 3906.1167 | L71: =$H71*L34 -> 1203.5592 | M71: =$H71*M34 -> 1851.9782 | N71: =$H71*N34 -> 0 | O71: =$H71*O34 -> 0 | P71: =$H71*P34 -> 0 | Q71: =$H71*Q34 -> 0 | ... AK71: =$H71*AK34 -> 0
E72: 2024Q1 | F72: =_xlfn.XLOOKUP($B$8,OCR!$D$2:$P$2,OCR!$D28:$P28) -> 110000 | G72: =_xlfn.XLOOKUP($B$8,IBNR!$G$5:$S$5,IBNR!$G31:$S31) -> 54919.384 | H72: =SUM(F72:G72) -> 164919.38 | I72: =SUM(J72:AK72) -> 164919.38 | J72: =$H72*J35 -> 119742.99 | K72: =$H72*K35 -> 41572.237 | L72: =$H72*L35 -> 2022.258 | M72: =$H72*M35 -> 623.10149 | N72: =$H72*N35 -> 958.79821 | O72: =$H72*O35 -> 0 | P72: =$H72*P35 -> 0 | Q72: =$H72*Q35 -> 0 | ... AK72: =$H72*AK35 -> 0
E73: 2024Q2 | F73: =_xlfn.XLOOKUP($B$8,OCR!$D$2:$P$2,OCR!$D29:$P29) -> 85311228 | G73: =_xlfn.XLOOKUP($B$8,IBNR!$G$5:$S$5,IBNR!$G32:$S32) -> 469429.1 | H73: =SUM(F73:G73) -> 85780657 | I73: =SUM(J73:AK73) -> 85780657 | J73: =$H73*J36 -> 17955244 | K73: =$H73*K36 -> 49245986 | L73: =$H73*L36 -> 17097166 | M73: =$H73*M36 -> 831682.01 | N73: =$H73*N36 -> 256259.24 | O73: =$H73*O36 -> 394319.23 | P73: =$H73*P36 -> 0 | Q73: =$H73*Q36 -> 0 | ... AK73: =$H73*AK36 -> 0
E74: 2024Q3 | F74: =_xlfn.XLOOKUP($B$8,OCR!$D$2:$P$2,OCR!$D30:$P30) -> 1650000 | G74: =_xlfn.XLOOKUP($B$8,IBNR!$G$5:$S$5,IBNR!$G33:$S33) -> 131234.57 | H74: =SUM(F74:G74) -> 1781234.6 | I74: =SUM(J74:AK74) -> 1781234.6 | J74: =$H74*J37 -> 836858.17 | K74: =$H74*K37 -> 197672.87 | L74: =$H74*L37 -> 542158.9 | M74: =$H74*M37 -> 188226.12 | N74: =$H74*N37 -> 9156.1534 | O74: =$H74*O37 -> 2821.2092 | P74: =$H74*P37 -> 4341.1392 | Q74: =$H74*Q37 -> 0 | ... AK74: =$H74*AK37 -> 0
E75: 2024Q4 | F75: =_xlfn.XLOOKUP($B$8,OCR!$D$2:$P$2,OCR!$D31:$P31) -> 1100000 | G75: =_xlfn.XLOOKUP($B$8,IBNR!$G$5:$S$5,IBNR!$G34:$S34) -> 649496.7 | H75: =SUM(F75:G75) -> 1749496.7 | I75: =SUM(J75:AK75) -> 1749496.7 | J75: =$H75*J38 -> 1395465.4 | K75: =$H75*K38 -> 166330.7 | L75: =$H75*L38 -> 39288.697 | M75: =$H75*M38 -> 107757.41 | N75: =$H75*N38 -> 37411.097 | O75: =$H75*O38 -> 1819.8417 | P75: =$H75*P38 -> 560.73266 | Q75: =$H75*Q38 -> 862.82809 | ... AK75: =$H75*AK38 -> 0
E76: =B39 -> Total | F76: =SUM(F48:F75) -> 1.3338408e+08 | G76: =SUM(G48:G75) -> 1313156.5 | H76: =SUM(F76:G76) -> 1.3469723e+08 | I76: =SUM(J76:AK76) -> 1.3469723e+08 | J76: =SUM(J48:J75) -> 64088033 | K76: =SUM(K48:K75) -> 50956876 | L76: =SUM(L48:L75) -> 17813673 | M76: =SUM(M48:M75) -> 1130140.6 | N76: =SUM(N48:N75) -> 303785.29 | O76: =SUM(O48:O75) -> 398960.29 | P76: =SUM(P48:P75) -> 4901.8719 | Q76: =SUM(Q48:Q75) -> 862.82809 | ... AK76: =SUM(AK48:AK75) -> 0
I77: =ROUNDDOWN(I76,0)=ROUNDDOWN(H76,0) -> TRUE
I79: =H76-I76 -> 0

Sheet LIA
J3: 2025 | K3: 2025 | L3: 2025 | M3: 2025 | N3: =J3+1 -> 2026 | O3: =K3+1 -> 2026 | P3: =L3+1 -> 2026 | Q3: =M3+1 -> 2026 | R3: =N3+1 -> 2027 | S3: =O3+1 -> 2027 | T3: =P3+1 -> 2027 | U3: =Q3+1 -> 2027 | ... AK3: =AG3+1 -> 2031
J4: Q1 | K4: Q2 | L4: Q3 | M4: Q4 | N4: Q1 | O4: Q2 | P4: Q3 | Q4: Q4 | R4: Q1 | S4: Q2 | T4: Q3 | U4: Q4 | V4: Q1 | W4: Q2 | X4: Q3 | Y4: Q4 | Z4: Q1 | AA4: Q2 | AB4: Q3 | AC4: Q4 | AD4: Q1 | AE4: Q2 | AF4: Q3 | AG4: Q4 | AH4: Q1 | AI4: Q2 | AJ4: Q3 | AK4: Q4
J5: =J4&"-"&J3 -> Q1-2025 | K5: =K4&"-"&K3 -> Q2-2025 | L5: =L4&"-"&L3 -> Q3-2025 | M5: =M4&"-"&M3 -> Q4-2025 | N5: =N4&"-"&N3 -> Q1-2026 | O5: =O4&"-"&O3 -> Q2-2026 | P5: =P4&"-"&P3 -> Q3-2026 | Q5: =Q4&"-"&Q3 -> Q4-2026 | ... AK5: =AK4&"-"&AK3 -> Q4-2031
H6: Payments in | J6: 3 | K6: =J6+3 -> 6 | L6: =K6+3 -> 9 | M6: =L6+3 -> 12 | N6: =M6+3 -> 15 | O6: =N6+3 -> 18 | P6: =O6+3 -> 21 | Q6: =P6+3 -> 24 | R6: =Q6+3 -> 27 | ... AK6: =AJ6+3 -> 84
K7: =K10-J10 -> 0.26 | L7: =L10-K10 -> 0.24 | M7: =M10-L10 -> 0.26 | N7: =N10-M10 -> 0.24 | O7: =O10-N10 -> 0.26 | P7: =P10-O10 -> 0.24 | Q7: =Q10-P10 -> 0.26 | R7: =R10-Q10 -> 0.24 | ... AK7: =AK10-AJ10 -> 0.26
B8: Liability | K8: =SUM(J10:K10) -> 0.5 | L8: =SUM(K10:L10) -> 1 | M8: =SUM(L10:M10) -> 1.5 | N8: =SUM(M10:N10) -> 2 | O8: =SUM(N10:O10) -> 2.5 | P8: =SUM(O10:P10) -> 3 | Q8: =SUM(P10:Q10) -> 3.5 | R8: =SUM(Q10:R10) -> 4 | ... AK8: =SUM(AJ10:AK10) -> 13.5
J9: Time (in years)
B10: Origin | C10: Age | D10: Paid DF's | E10: Cumulative Development Factors | F10: Incremental Payments | G10: Cumulative Payments | H10: Expected Unpaid % | I10: Check | J10: 0.12 | K10: 0.38 | L10: 0.62 | M10: 0.88 | N10: 1.12 | O10: 1.38 | P10: 1.62 | Q10: 1.88 | R10: 2.12 | S10: 2.38 | T10: 2.62 | U10: 2.88 | V10: 3.12 | W10: 3.38 | X10: 3.62 | Y10: 3.88 | Z10: 4.12 | AA10: 4.38 | AB10: 4.62 | AC10: 4.88 | AD10: 5.12 | AE10: 5.38 | AF10: 5.62 | AG10: 5.88 | AH10: 6.12 | AI10: 6.38 | AJ10: 6.62 | AK10: 6.88
B11: =IBNR!F7 -> 2018Q1 | C11: =C12+3 -> 84 | D11: =_xlfn.XLOOKUP($B$8,Paid_DFs!$G$5:$S$5,Paid_DFs!$G7:$S7) -> 1 | E11: =PRODUCT($D$11:$D11) -> 1 | F11: =G11-G12 -> 0 | G11: =1/E11 -> 1 | H11: =1-G11 -> 0 | I11: =SUM(J11:AK11) -> 1 | J11: =IF($H11=0%,100%,IFERROR(VLOOKUP($C11+J$6,$C$11:$AK$38,4,FALSE)/$H11,0)) -> 1 | K11: =IFERROR(VLOOKUP($C11+K$6,$C$11:$AK$38,4,FALSE)/$H11,0) -> 0 | L11: =IFERROR(VLOOKUP($C11+L$6,$C$11:$AK$38,4,FALSE)/$H11,0) -> 0 | M11: =IFERROR(VLOOKUP($C11+M$6,$C$11:$AK$38,4,FALSE)/$H11,0) -> 0 | N11: =IFERROR(VLOOKUP($C11+N$6,$C$11:$AK$38,4,FALSE)/$H11,0) -> 0 | O11: =IFERROR(VLOOKUP($C11+O$6,$C$11:$AK$38,4,FALSE)/$H11,0) -> 0 | P11: =IFERROR(VLOOKUP($C11+P$6,$C$11:$AK$38,4,FALSE)/$H11,0) -> 0 | Q11: =IFERROR(VLOOKUP($C11+Q$6,$C$11:$AK$38,4,FALSE)/$H11,0) -> 0 | R11: =IFERROR(VLOOKUP($C11+R$6,$C$11:$AK$38,4,FALSE)/$H11,0) -> 0 | ... AK11: =IFERROR(VLOOKUP($C11+AK$6,$C$11:$AK$38,4,FALSE)/$H11,0) -> 0
B12: =IBNR!F8 -> 2018Q2 | C12: =C13+3 -> 81 | D12: =_xlfn.XLOOKUP($B$8,Paid_DFs!$G$5:$S$5,Paid_DFs!$G8:$S8) -> 1 | E12: =PRODUCT($D$11:$D12) -> 1 | F12: =G12-G13 -> 0 | G12: =1/E12 -> 1 | H12: =1-G12 -> 0 | I12: =SUM(J12:AK12) -> 1 | J12: =IF($H12=0%,100%,IFERROR(VLOOKUP($C12+J$6,$C$11:$AK$38,4,FALSE)/$H12,0)) -> 1 | K12: =IFERROR(VLOOKUP($C12+K$6,$C$11:$AK$38,4,FALSE)/$H12,0) -> 0 | L12: =IFERROR(VLOOKUP($C12+L$6,$C$11:$AK$38,4,FALSE)/$H12,0) -> 0 | M12: =IFERROR(VLOOKUP($C12+M$6,$C$11:$AK$38,4,FALSE)/$H12,0) -> 0 | N12: =IFERROR(VLOOKUP($C12+N$6,$C$11:$AK$38,4,FALSE)/$H12,0) -> 0 | O12: =IFERROR(VLOOKUP($C12+O$6,$C$11:$AK$38,4,FALSE)/$H12,0) -> 0 | P12: =IFERROR(VLOOKUP($C12+P$6,$C$11:$AK$38,4,FALSE)/$H12,0) -> 0 | Q12: =IFERROR(VLOOKUP($C12+Q$6,$C$11:$AK$38,4,FALSE)/$H12,0) -> 0 | R12: =IFERROR(VLOOKUP($C12+R$6,$C$11:$AK$38,4,FALSE)/$H12,0) -> 0 | ... AK12: =IFERROR(VLOOKUP($C12+AK$6,$C$11:$AK$38,4,FALSE)/$H12,0) -> 0
B13: =IBNR!F9 -> 2018Q3 | C13: =C14+3 -> 78 | D13: =_xlfn.XLOOKUP($B$8,Paid_DFs!$G$5:$S$5,Paid_DFs!$G9:$S9) -> 1 | E13: =PRODUCT($D$11:$D13) -> 1 | F13: =G13-G14 -> 0 | G13: =1/E13 -> 1 | H13: =1-G13 -> 0 | I13: =SUM(J13:AK13) -> 1 | J13: =IF($H13=0%,100%,IFERROR(VLOOKUP($C13+J$6,$C$11:$AK$38,4,FALSE)/$H13,0)) -> 1 | K13: =IFERROR(VLOOKUP($C13+K$6,$C$11:$AK$38,4,FALSE)/$H13,0) -> 0 | L13: =IFERROR(VLOOKUP($C13+L$6,$C$11:$AK$38,4,FALSE)/$H13,0) -> 0 | M13: =IFERROR(VLOOKUP($C13+M$6,$C$11:$AK$38,4,FALSE)/$H13,0) -> 0 | N13: =IFERROR(VLOOKUP($C13+N$6,$C$11:$AK$38,4,FALSE)/$H13,0) -> 0 | O13: =IFERROR(VLOOKUP($C13+O$6,$C$11:$AK$38,4,FALSE)/$H13,0) -> 0 | P13: =IFERROR(VLOOKUP($C13+P$6,$C$11:$AK$38,4,FALSE)/$H13,0) -> 0 | Q13: =IFERROR(VLOOKUP($C13+Q$6,$C$11:$AK$38,4,FALSE)/$H13,0) -> 0 | R13: =IFERROR(VLOOKUP($C13+R$6,$C$11:$AK$38,4,FALSE)/$H13,0) -> 0 | ... AK13: =IFERROR(VLOOKUP($C13+AK$6,$C$11:$AK$38,4,FALSE)/$H13,0) -> 0
B14: =IBNR!F10 -> 2018Q4 | C14: =C15+3 -> 75 | D14: =_xlfn.XLOOKUP($B$8,Paid_DFs!$G$5:$S$5,Paid_DFs!$G10:$S10) -> 1 | E14: =PRODUCT($D$11:$D14) -> 1 | F14: =G14-G15 -> 0 | G14: =1/E14 -> 1 | H14: =1-G14 -> 0 | I14: =SUM(J14:AK14) -> 1 | J14: =IF($H14=0%,100%,IFERROR(VLOOKUP($C14+J$6,$C$11:$AK$38,4,FALSE)/$H14,0)) -> 1 | K14: =IFERROR(VLOOKUP($C14+K$6,$C$11:$AK$38,4,FALSE)/$H14,0) -> 0 | L14: =IFERROR(VLOOKUP($C14+L$6,$C$11:$AK$38,4,FALSE)/$H14,0) -> 0 | M14: =IFERROR(VLOOKUP($C14+M$6,$C$11:$AK$38,4,FALSE)/$H14,0) -> 0 | N14: =IFERROR(VLOOKUP($C14+N$6,$C$11:$AK$38,4,FALSE)/$H14,0) -> 0 | O14: =IFERROR(VLOOKUP($C14+O$6,$C$11:$AK$38,4,FALSE)/$H14,0) -> 0 | P14: =IFERROR(VLOOKUP($C14+P$6,$C$11:$AK$38,4,FALSE)/$H14,0) -> 0 | Q14: =IFERROR(VLOOKUP($C14+Q$6,$C$11:$AK$38,4,FALSE)/$H14,0) -> 0 | R14: =IFERROR(VLOOKUP($C14+R$6,$C$11:$AK$38,4,FALSE)/$H14,0) -> 0 | ... AK14: =IFERROR(VLOOKUP($C14+AK$6,$C$11:$AK$38,4,FALSE)/$H14,0) -> 0
B15: =IBNR!F11 -> 2019Q1 | C15: =C16+3 -> 72 | D15: =_xlfn.XLOOKUP($B$8,Paid_DFs!$G$5:$S$5,Paid_DFs!$G11:$S11) -> 1 | E15: =PRODUCT($D$11:$D15) -> 1 | F15: =G15-G16 -> 0 | G15: =1/E15 -> 1 | H15: =1-G15 -> 0 | I15: =SUM(J15:AK15) -> 1 | J15: =IF($H15=0%,100%,IFERROR(VLOOKUP($C15+J$6,$C$11:$AK$38,4,FALSE)/$H15,0)) -> 1 | K15: =IFERROR(VLOOKUP($C15+K$6,$C$11:$AK$38,4,FALSE)/$H15,0) -> 0 | L15: =IFERROR(VLOOKUP($C15+L$6,$C$11:$AK$38,4,FALSE)/$H15,0) -> 0 | M15: =IFERROR(VLOOKUP($C15+M$6,$C$11:$AK$38,4,FALSE)/$H15,0) -> 0 | N15: =IFERROR(VLOOKUP($C15+N$6,$C$11:$AK$38,4,FALSE)/$H15,0) -> 0 | O15: =IFERROR(VLOOKUP($C15+O$6,$C$11:$AK$38,4,FALSE)/$H15,0) -> 0 | P15: =IFERROR(VLOOKUP($C15+P$6,$C$11:$AK$38,4,FALSE)/$H15,0) -> 0 | Q15: =IFERROR(VLOOKUP($C15+Q$6,$C$11:$AK$38,4,FALSE)/$H15,0) -> 0 | R15: =IFERROR(VLOOKUP($C15+R$6,$C$11:$AK$38,4,FALSE)/$H15,0) -> 0 | ... AK15: =IFERROR(VLOOKUP($C15+AK$6,$C$11:$AK$38,4,FALSE)/$H15,0) -> 0
B16: =IBNR!F12 -> 2019Q2 | C16: =C17+3 -> 69 | D16: =_xlfn.XLOOKUP($B$8,Paid_DFs!$G$5:$S$5,Paid_DFs!$G12:$S12) -> 1 | E16: =PRODUCT($D$11:$D16) -> 1 | F16: =G16-G17 -> 0 | G16: =1/E16 -> 1 | H16: =1-G16 -> 0 | I16: =SUM(J16:AK16) -> 1 | J16: =IF($H16=0%,100%,IFERROR(VLOOKUP($C16+J$6,$C$11:$AK$38,4,FALSE)/$H16,0)) -> 1 | K16: =IFERROR(VLOOKUP($C16+K$6,$C$11:$AK$38,4,FALSE)/$H16,0) -> 0 | L16: =IFERROR(VLOOKUP($C16+L$6,$C$11:$AK$38,4,FALSE)/$H16,0) -> 0 | M16: =IFERROR(VLOOKUP($C16+M$6,$C$11:$AK$38,4,FALSE)/$H16,0) -> 0 | N16: =IFERROR(VLOOKUP($C16+N$6,$C$11:$AK$38,4,FALSE)/$H16,0) -> 0 | O16: =IFERROR(VLOOKUP($C16+O$6,$C$11:$AK$38,4,FALSE)/$H16,0) -> 0 | P16: =IFERROR(VLOOKUP($C16+P$6,$C$11:$AK$38,4,FALSE)/$H16,0) -> 0 | Q16: =IFERROR(VLOOKUP($C16+Q$6,$C$11:$AK$38,4,FALSE)/$H16,0) -> 0 | R16: =IFERROR(VLOOKUP($C16+R$6,$C$11:$AK$38,4,FALSE)/$H16,0) -> 0 | ... AK16: =IFERROR(VLOOKUP($C16+AK$6,$C$11:$AK$38,4,FALSE)/$H16,0) -> 0
B17: =IBNR!F13 -> 2019Q3 | C17: =C18+3 -> 66 | D17: =_xlfn.XLOOKUP($B$8,Paid_DFs!$G$5:$S$5,Paid_DFs!$G13:$S13) -> 1 | E17: =PRODUCT($D$11:$D17) -> 1 | F17: =G17-G18 -> 0 | G17: =1/E17 -> 1 | H17: =1-G17 -> 0 | I17: =SUM(J17:AK17) -> 1 | J17: =IF($H17=0%,100%,IFERROR(VLOOKUP($C17+J$6,$C$11:$AK$38,4,FALSE)/$H17,0)) -> 1 | K17: =IFERROR(VLOOKUP($C17+K$6,$C$11:$AK$38,4,FALSE)/$H17,0) -> 0 | L17: =IFERROR(VLOOKUP($C17+L$6,$C$11:$AK$38,4,FALSE)/$H17,0) -> 0 | M17: =IFERROR(VLOOKUP($C17+M$6,$C$11:$AK$38,4,FALSE)/$H17,0) -> 0 | N17: =IFERROR(VLOOKUP($C17+N$6,$C$11:$AK$38,4,FALSE)/$H17,0) -> 0 | O17: =IFERROR(VLOOKUP($C17+O$6,$C$11:$AK$38,4,FALSE)/$H17,0) -> 0 | P17: =IFERROR(VLOOKUP($C17+P$6,$C$11:$AK$38,4,FALSE)/$H17,0) -> 0 | Q17: =IFERROR(VLOOKUP($C17+Q$6,$C$11:$AK$38,4,FALSE)/$H17,0) -> 0 | R17: =IFERROR(VLOOKUP($C17+R$6,$C$11:$AK$38,4,FALSE)/$H17,0) -> 0 | ... AK17: =IFERROR(VLOOKUP($C17+AK$6,$C$11:$AK$38,4,FALSE)/$H17,0) -> 0
B18: =IBNR!F14 -> 2019Q4 | C18: =C19+3 -> 63 | D18: =_xlfn.XLOOKUP($B$8,Paid_DFs!$G$5:$S$5,Paid_DFs!$G14:$S14) -> 1 | E18: =PRODUCT($D$11:$D18) -> 1 | F18: =G18-G19 -> 0 | G18: =1/E18 -> 1 | H18: =1-G18 -> 0 | I18: =SUM(J18:AK18) -> 1 | J18: =IF($H18=0%,100%,IFERROR(VLOOKUP($C18+J$6,$C$11:$AK$38,4,FALSE)/$H18,0)) -> 1 | K18: =IFERROR(VLOOKUP($C18+K$6,$C$11:$AK$38,4,FALSE)/$H18,0) -> 0 | L18: =IFERROR(VLOOKUP($C18+L$6,$C$11:$AK$38,4,FALSE)/$H18,0) -> 0 | M18: =IFERROR(VLOOKUP($C18+M$6,$C$11:$AK$38,4,FALSE)/$H18,0) -> 0 | N18: =IFERROR(VLOOKUP($C18+N$6,$C$11:$AK$38,4,FALSE)/$H18,0) -> 0 | O18: =IFERROR(VLOOKUP($C18+O$6,$C$11:$AK$38,4,FALSE)/$H18,0) -> 0 | P18: =IFERROR(VLOOKUP($C18+P$6,$C$11:$AK$38,4,FALSE)/$H18,0) -> 0 | Q18: =IFERROR(VLOOKUP($C18+Q$6,$C$11:$AK$38,4,FALSE)/$H18,0) -> 0 | R18: =IFERROR(VLOOKUP($C18+R$6,$C$11:$AK$38,4,FALSE)/$H18,0) -> 0 | ... AK18: =IFERROR(VLOOKUP($C18+AK$6,$C$11:$AK$38,4,FALSE)/$H18,0) -> 0
B19: =IBNR!F15 -> 2020Q1 | C19: =C20+3 -> 60 | D19: =_xlfn.XLOOKUP($B$8,Paid_DFs!$G$5:$S$5,Paid_DFs!$G15:$S15) -> 1 | E19: =PRODUCT($D$11:$D19) -> 1 | F19: =G19-G20 -> 0 | G19: =1/E19 -> 1 | H19: =1-G19 -> 0 | I19: =SUM(J19:AK19) -> 1 | J19: =IF($H19=0%,100%,IFERROR(VLOOKUP($C19+J$6,$C$11:$AK$38,4,FALSE)/$H19,0)) -> 1 | K19: =IFERROR(VLOOKUP($C19+K$6,$C$11:$AK$38,4,FALSE)/$H19,0) -> 0 | L19: =IFERROR(VLOOKUP($C19+L$6,$C$11:$AK$38,4,FALSE)/$H19,0) -> 0 | M19: =IFERROR(VLOOKUP($C19+M$6,$C$11:$AK$38,4,FALSE)/$H19,0) -> 0 | N19: =IFERROR(VLOOKUP($C19+N$6,$C$11:$AK$38,4,FALSE)/$H19,0) -> 0 | O19: =IFERROR(VLOOKUP($C19+O$6,$C$11:$AK$38,4,FALSE)/$H19,0) -> 0 | P19: =IFERROR(VLOOKUP($C19+P$6,$C$11:$AK$38,4,FALSE)/$H19,0) -> 0 | Q19: =IFERROR(VLOOKUP($C19+Q$6,$C$11:$AK$38,4,FALSE)/$H19,0) -> 0 | R19: =IFERROR(VLOOKUP($C19+R$6,$C$11:$AK$38,4,FALSE)/$H19,0) -> 0 | ... AK19: =IFERROR(VLOOKUP($C19+AK$6,$C$11:$AK$38,4,FALSE)/$H19,0) -> 0
B20: =IBNR!F16 -> 2020Q2 | C20: =C21+3 -> 57 | D20: =_xlfn.XLOOKUP($B$8,Paid_DFs!$G$5:$S$5,Paid_DFs!$G16:$S16) -> 1 | E20: =PRODUCT($D$11:$D20) -> 1 | F20: =G20-G21 -> 0.0081321315 | G20: =1/E20 -> 1 | H20: =1-G20 -> 0 | I20: =SUM(J20:AK20) -> 1 | J20: =IF($H20=0%,100%,IFERROR(VLOOKUP($C20+J$6,$C$11:$AK$38,4,FALSE)/$H20,0)) -> 1 | K20: =IFERROR(VLOOKUP($C20+K$6,$C$11:$AK$38,4,FALSE)/$H20,0) -> 0 | L20: =IFERROR(VLOOKUP($C20+L$6,$C$11:$AK$38,4,FALSE)/$H20,0) -> 0 | M20: =IFERROR(VLOOKUP($C20+M$6,$C$11:$AK$38,4,FALSE)/$H20,0) -> 0 | N20: =IFERROR(VLOOKUP($C20+N$6,$C$11:$AK$38,4,FALSE)/$H20,0) -> 0 | O20: =IFERROR(VLOOKUP($C20+O$6,$C$11:$AK$38,4,FALSE)/$H20,0) -> 0 | P20: =IFERROR(VLOOKUP($C20+P$6,$C$11:$AK$38,4,FALSE)/$H20,0) -> 0 | Q20: =IFERROR(VLOOKUP($C20+Q$6,$C$11:$AK$38,4,FALSE)/$H20,0) -> 0 | R20: =IFERROR(VLOOKUP($C20+R$6,$C$11:$AK$38,4,FALSE)/$H20,0) -> 0 | ... AK20: =IFERROR(VLOOKUP($C20+AK$6,$C$11:$AK$38,4,FALSE)/$H20,0) -> 0
B21: =IBNR!F17 -> 2020Q3 | C21: =C22+3 -> 54 | D21: =_xlfn.XLOOKUP($B$8,Paid_DFs!$G$5:$S$5,Paid_DFs!$G17:$S17) -> 1.0081988 | E21: =PRODUCT($D$11:$D21) -> 1.0081988 | F21: =G21-G22 -> 0 | G21: =1/E21 -> 0.99186787 | H21: =1-G21 -> 0.0081321315 | I21: =SUM(J21:AK21) -> 1 | J21: =IF($H21=0%,100%,IFERROR(VLOOKUP($C21+J$6,$C$11:$AK$38,4,FALSE)/$H21,0)) -> 1 | K21: =IFERROR(VLOOKUP($C21+K$6,$C$11:$AK$38,4,FALSE)/$H21,0) -> 0 | L21: =IFERROR(VLOOKUP($C21+L$6,$C$11:$AK$38,4,FALSE)/$H21,0) -> 0 | M21: =IFERROR(VLOOKUP($C21+M$6,$C$11:$AK$38,4,FALSE)/$H21,0) -> 0 | N21: =IFERROR(VLOOKUP($C21+N$6,$C$11:$AK$38,4,FALSE)/$H21,0) -> 0 | O21: =IFERROR(VLOOKUP($C21+O$6,$C$11:$AK$38,4,FALSE)/$H21,0) -> 0 | P21: =IFERROR(VLOOKUP($C21+P$6,$C$11:$AK$38,4,FALSE)/$H21,0) -> 0 | Q21: =IFERROR(VLOOKUP($C21+Q$6,$C$11:$AK$38,4,FALSE)/$H21,0) -> 0 | R21: =IFERROR(VLOOKUP($C21+R$6,$C$11:$AK$38,4,FALSE)/$H21,0) -> 0 | ... AK21: =IFERROR(VLOOKUP($C21+AK$6,$C$11:$AK$38,4,FALSE)/$H21,0) -> 0
B22: =IBNR!F18 -> 2020Q4 | C22: =C23+3 -> 51 | D22: =_xlfn.XLOOKUP($B$8,Paid_DFs!$G$5:$S$5,Paid_DFs!$G18:$S18) -> 1 | E22: =PRODUCT($D$11:$D22) -> 1.0081988 | F22: =G22-G23 -> 0 | G22: =1/E22 -> 0.99186787 | H22: =1-G22 -> 0.0081321315 | I22: =SUM(J22:AK22) -> 1 | J22: =IF($H22=0%,100%,IFERROR(VLOOKUP($C22+J$6,$C$11:$AK$38,4,FALSE)/$H22,0)) -> 0 | K22: =IFERROR(VLOOKUP($C22+K$6,$C$11:$AK$38,4,FALSE)/$H22,0) -> 1 | L22: =IFERROR(VLOOKUP($C22+L$6,$C$11:$AK$38,4,FALSE)/$H22,0) -> 0 | M22: =IFERROR(VLOOKUP($C22+M$6,$C$11:$AK$38,4,FALSE)/$H22,0) -> 0 | N22: =IFERROR(VLOOKUP($C22+N$6,$C$11:$AK$38,4,FALSE)/$H22,0) -> 0 | O22: =IFERROR(VLOOKUP($C22+O$6,$C$11:$AK$38,4,FALSE)/$H22,0) -> 0 | P22: =IFERROR(VLOOKUP($C22+P$6,$C$11:$AK$38,4,FALSE)/$H22,0) -> 0 | Q22: =IFERROR(VLOOKUP($C22+Q$6,$C$11:$AK$38,4,FALSE)/$H22,0) -> 0 | R22: =IFERROR(VLOOKUP($C22+R$6,$C$11:$AK$38,4,FALSE)/$H22,0) -> 0 | ... AK22: =IFERROR(VLOOKUP($C22+AK$6,$C$11:$AK$38,4,FALSE)/$H22,0) -> 0
... B30: =IBNR!F26 -> 2022Q4 | C30: =C31+3 -> 27 | D30: =_xlfn.XLOOKUP($B$8,Paid_DFs!$G$5:$S$5,Paid_DFs!$G26:$S26) -> 1 | E30: =PRODUCT($D$11:$D30) -> 1.0081988 | F30: =G30-G31 -> 0.0061234928 | G30: =1/E30 -> 0.99186787 | H30: =1-G30 -> 0.0081321315 | I30: =SUM(J30:AK30) -> 1 | J30: =IF($H30=0%,100%,IFERROR(VLOOKUP($C30+J$6,$C$11:$AK$38,4,FALSE)/$H30,0)) -> 0 | K30: =IFERROR(VLOOKUP($C30+K$6,$C$11:$AK$38,4,FALSE)/$H30,0) -> 0 | L30: =IFERROR(VLOOKUP($C30+L$6,$C$11:$AK$38,4,FALSE)/$H30,0) -> 0 | M30: =IFERROR(VLOOKUP($C30+M$6,$C$11:$AK$38,4,FALSE)/$H30,0) -> 0 | N30: =IFERROR(VLOOKUP($C30+N$6,$C$11:$AK$38,4,FALSE)/$H30,0) -> 0 | O30: =IFERROR(VLOOKUP($C30+O$6,$C$11:$AK$38,4,FALSE)/$H30,0) -> 0 | P30: =IFERROR(VLOOKUP($C30+P$6,$C$11:$AK$38,4,FALSE)/$H30,0) -> 0 | Q30: =IFERROR(VLOOKUP($C30+Q$6,$C$11:$AK$38,4,FALSE)/$H30,0) -> 0 | R30: =IFERROR(VLOOKUP($C30+R$6,$C$11:$AK$38,4,FALSE)/$H30,0) -> 0 | ... AK30: =IFERROR(VLOOKUP($C30+AK$6,$C$11:$AK$38,4,FALSE)/$H30,0) -> 0
B31: 2023Q1 | C31: =C32+3 -> 24 | D31: =_xlfn.XLOOKUP($B$8,Paid_DFs!$G$5:$S$5,Paid_DFs!$G27:$S27) -> 1.006212 | E31: =PRODUCT($D$11:$D31) -> 1.0144618 | F31: =G31-G32 -> 0 | G31: =1/E31 -> 0.98574438 | H31: =1-G31 -> 0.014255624 | I31: =SUM(J31:AK31) -> 1 | J31: =IF($H31=0%,100%,IFERROR(VLOOKUP($C31+J$6,$C$11:$AK$38,4,FALSE)/$H31,0)) -> 0.42954925 | K31: =IFERROR(VLOOKUP($C31+K$6,$C$11:$AK$38,4,FALSE)/$H31,0) -> 0 | L31: =IFERROR(VLOOKUP($C31+L$6,$C$11:$AK$38,4,FALSE)/$H31,0) -> 0 | M31: =IFERROR(VLOOKUP($C31+M$6,$C$11:$AK$38,4,FALSE)/$H31,0) -> 0 | N31: =IFERROR(VLOOKUP($C31+N$6,$C$11:$AK$38,4,FALSE)/$H31,0) -> 0 | O31: =IFERROR(VLOOKUP($C31+O$6,$C$11:$AK$38,4,FALSE)/$H31,0) -> 0 | P31: =IFERROR(VLOOKUP($C31+P$6,$C$11:$AK$38,4,FALSE)/$H31,0) -> 0 | Q31: =IFERROR(VLOOKUP($C31+Q$6,$C$11:$AK$38,4,FALSE)/$H31,0) -> 0 | R31: =IFERROR(VLOOKUP($C31+R$6,$C$11:$AK$38,4,FALSE)/$H31,0) -> 0 | ... AK31: =IFERROR(VLOOKUP($C31+AK$6,$C$11:$AK$38,4,FALSE)/$H31,0) -> 0
B32: 2023Q2 | C32: =C33+3 -> 21 | D32: =_xlfn.XLOOKUP($B$8,Paid_DFs!$G$5:$S$5,Paid_DFs!$G28:$S28) -> 1 | E32: =PRODUCT($D$11:$D32) -> 1.0144618 | F32: =G32-G33 -> 0.0016484008 | G32: =1/E32 -> 0.98574438 | H32: =1-G32 -> 0.014255624 | I32: =SUM(J32:AK32) -> 1 | J32: =IF($H32=0%,100%,IFERROR(VLOOKUP($C32+J$6,$C$11:$AK$38,4,FALSE)/$H32,0)) -> 0 | K32: =IFERROR(VLOOKUP($C32+K$6,$C$11:$AK$38,4,FALSE)/$H32,0) -> 0.42954925 | L32: =IFERROR(VLOOKUP($C32+L$6,$C$11:$AK$38,4,FALSE)/$H32,0) -> 0 | M32: =IFERROR(VLOOKUP($C32+M$6,$C$11:$AK$38,4,FALSE)/$H32,0) -> 0 | N32: =IFERROR(VLOOKUP($C32+N$6,$C$11:$AK$38,4,FALSE)/$H32,0) -> 0 | O32: =IFERROR(VLOOKUP($C32+O$6,$C$11:$AK$38,4,FALSE)/$H32,0) -> 0 | P32: =IFERROR(VLOOKUP($C32+P$6,$C$11:$AK$38,4,FALSE)/$H32,0) -> 0 | Q32: =IFERROR(VLOOKUP($C32+Q$6,$C$11:$AK$38,4,FALSE)/$H32,0) -> 0 | R32: =IFERROR(VLOOKUP($C32+R$6,$C$11:$AK$38,4,FALSE)/$H32,0) -> 0 | ... AK32: =IFERROR(VLOOKUP($C32+AK$6,$C$11:$AK$38,4,FALSE)/$H32,0) -> 0
B33: 2023Q3 | C33: =C34+3 -> 18 | D33: =_xlfn.XLOOKUP($B$8,Paid_DFs!$G$5:$S$5,Paid_DFs!$G29:$S29) -> 1.001675 | E33: =PRODUCT($D$11:$D33) -> 1.0161611 | F33: =G33-G34 -> 0.00015556575 | G33: =1/E33 -> 0.98409597 | H33: =1-G33 -> 0.015904025 | I33: =SUM(J33:AK33) -> 1 | J33: =IF($H33=0%,100%,IFERROR(VLOOKUP($C33+J$6,$C$11:$AK$38,4,FALSE)/$H33,0)) -> 0.10364677 | K33: =IFERROR(VLOOKUP($C33+K$6,$C$11:$AK$38,4,FALSE)/$H33,0) -> 0 | L33: =IFERROR(VLOOKUP($C33+L$6,$C$11:$AK$38,4,FALSE)/$H33,0) -> 0.38502786 | M33: =IFERROR(VLOOKUP($C33+M$6,$C$11:$AK$38,4,FALSE)/$H33,0) -> 0 | N33: =IFERROR(VLOOKUP($C33+N$6,$C$11:$AK$38,4,FALSE)/$H33,0) -> 0 | O33: =IFERROR(VLOOKUP($C33+O$6,$C$11:$AK$38,4,FALSE)/$H33,0) -> 0 | P33: =IFERROR(VLOOKUP($C33+P$6,$C$11:$AK$38,4,FALSE)/$H33,0) -> 0 | Q33: =IFERROR(VLOOKUP($C33+Q$6,$C$11:$AK$38,4,FALSE)/$H33,0) -> 0 | R33: =IFERROR(VLOOKUP($C33+R$6,$C$11:$AK$38,4,FALSE)/$H33,0) -> 0 | ... AK33: =IFERROR(VLOOKUP($C33+AK$6,$C$11:$AK$38,4,FALSE)/$H33,0) -> 0
B34: 2023Q4 | C34: =C35+3 -> 15 | D34: =_xlfn.XLOOKUP($B$8,Paid_DFs!$G$5:$S$5,Paid_DFs!$G30:$S30) -> 1.0001581 | E34: =PRODUCT($D$11:$D34) -> 1.0163217 | F34: =G34-G35 -> 0.0011796207 | G34: =1/E34 -> 0.98394041 | H34: =1-G34 -> 0.016059591 | I34: =SUM(J34:AK34) -> 1 | J34: =IF($H34=0%,100%,IFERROR(VLOOKUP($C34+J$6,$C$11:$AK$38,4,FALSE)/$H34,0)) -> 0.0096867814 | K34: =IFERROR(VLOOKUP($C34+K$6,$C$11:$AK$38,4,FALSE)/$H34,0) -> 0.10264276 | L34: =IFERROR(VLOOKUP($C34+L$6,$C$11:$AK$38,4,FALSE)/$H34,0) -> 0 | M34: =IFERROR(VLOOKUP($C34+M$6,$C$11:$AK$38,4,FALSE)/$H34,0) -> 0.38129818 | N34: =IFERROR(VLOOKUP($C34+N$6,$C$11:$AK$38,4,FALSE)/$H34,0) -> 0 | O34: =IFERROR(VLOOKUP($C34+O$6,$C$11:$AK$38,4,FALSE)/$H34,0) -> 0 | P34: =IFERROR(VLOOKUP($C34+P$6,$C$11:$AK$38,4,FALSE)/$H34,0) -> 0 | Q34: =IFERROR(VLOOKUP($C34+Q$6,$C$11:$AK$38,4,FALSE)/$H34,0) -> 0 | R34: =IFERROR(VLOOKUP($C34+R$6,$C$11:$AK$38,4,FALSE)/$H34,0) -> 0 | ... AK34: =IFERROR(VLOOKUP($C34+AK$6,$C$11:$AK$38,4,FALSE)/$H34,0) -> 0
B35: 2024Q1 | C35: =C36+3 -> 12 | D35: =_xlfn.XLOOKUP($B$8,Paid_DFs!$G$5:$S$5,Paid_DFs!$G31:$S31) -> 1.0012003 | E35: =PRODUCT($D$11:$D35) -> 1.0175416 | F35: =G35-G36 -> 0.0062680783 | G35: =1/E35 -> 0.98276079 | H35: =1-G35 -> 0.017239212 | I35: =SUM(J35:AK35) -> 1 | J35: =IF($H35=0%,100%,IFERROR(VLOOKUP($C35+J$6,$C$11:$AK$38,4,FALSE)/$H35,0)) -> 0.068426605 | K35: =IFERROR(VLOOKUP($C35+K$6,$C$11:$AK$38,4,FALSE)/$H35,0) -> 0.0090239478 | L35: =IFERROR(VLOOKUP($C35+L$6,$C$11:$AK$38,4,FALSE)/$H35,0) -> 0.095619267 | M35: =IFERROR(VLOOKUP($C35+M$6,$C$11:$AK$38,4,FALSE)/$H35,0) -> 0 | N35: =IFERROR(VLOOKUP($C35+N$6,$C$11:$AK$38,4,FALSE)/$H35,0) -> 0.35520724 | O35: =IFERROR(VLOOKUP($C35+O$6,$C$11:$AK$38,4,FALSE)/$H35,0) -> 0 | P35: =IFERROR(VLOOKUP($C35+P$6,$C$11:$AK$38,4,FALSE)/$H35,0) -> 0 | Q35: =IFERROR(VLOOKUP($C35+Q$6,$C$11:$AK$38,4,FALSE)/$H35,0) -> 0 | R35: =IFERROR(VLOOKUP($C35+R$6,$C$11:$AK$38,4,FALSE)/$H35,0) -> 0 | ... AK35: =IFERROR(VLOOKUP($C35+AK$6,$C$11:$AK$38,4,FALSE)/$H35,0) -> 0
B36: 2024Q2 | C36: =C37+3 -> 9 | D36: =_xlfn.XLOOKUP($B$8,Paid_DFs!$G$5:$S$5,Paid_DFs!$G32:$S32) -> 1.006419 | E36: =PRODUCT($D$11:$D36) -> 1.0240732 | F36: =G36-G37 -> 0.0056126331 | G36: =1/E36 -> 0.97649271 | H36: =1-G36 -> 0.02350729 | I36: =SUM(J36:AK36) -> 1 | J36: =IF($H36=0%,100%,IFERROR(VLOOKUP($C36+J$6,$C$11:$AK$38,4,FALSE)/$H36,0)) -> 0.26664402 | K36: =IFERROR(VLOOKUP($C36+K$6,$C$11:$AK$38,4,FALSE)/$H36,0) -> 0.05018106 | L36: =IFERROR(VLOOKUP($C36+L$6,$C$11:$AK$38,4,FALSE)/$H36,0) -> 0.0066177661 | M36: =IFERROR(VLOOKUP($C36+M$6,$C$11:$AK$38,4,FALSE)/$H36,0) -> 0.070122961 | N36: =IFERROR(VLOOKUP($C36+N$6,$C$11:$AK$38,4,FALSE)/$H36,0) -> 0 | O36: =IFERROR(VLOOKUP($C36+O$6,$C$11:$AK$38,4,FALSE)/$H36,0) -> 0.26049335 | P36: =IFERROR(VLOOKUP($C36+P$6,$C$11:$AK$38,4,FALSE)/$H36,0) -> 0 | Q36: =IFERROR(VLOOKUP($C36+Q$6,$C$11:$AK$38,4,FALSE)/$H36,0) -> 0 | R36: =IFERROR(VLOOKUP($C36+R$6,$C$11:$AK$38,4,FALSE)/$H36,0) -> 0 | ... AK36: =IFERROR(VLOOKUP($C36+AK$6,$C$11:$AK$38,4,FALSE)/$H36,0) -> 0
B37: 2024Q3 | C37: =C38+3 -> 6 | D37: =_xlfn.XLOOKUP($B$8,Paid_DFs!$G$5:$S$5,Paid_DFs!$G33:$S33) -> 1.005781 | E37: =PRODUCT($D$11:$D37) -> 1.0299933 | F37: =G37-G38 -> 0.055483336 | G37: =1/E37 -> 0.97088008 | H37: =1-G37 -> 0.029119923 | I37: =SUM(J37:AK37) -> 1 | J37: =IF($H37=0%,100%,IFERROR(VLOOKUP($C37+J$6,$C$11:$AK$38,4,FALSE)/$H37,0)) -> 0.19274203 | K37: =IFERROR(VLOOKUP($C37+K$6,$C$11:$AK$38,4,FALSE)/$H37,0) -> 0.21525051 | L37: =IFERROR(VLOOKUP($C37+L$6,$C$11:$AK$38,4,FALSE)/$H37,0) -> 0.040509061 | M37: =IFERROR(VLOOKUP($C37+M$6,$C$11:$AK$38,4,FALSE)/$H37,0) -> 0.0053422444 | N37: =IFERROR(VLOOKUP($C37+N$6,$C$11:$AK$38,4,FALSE)/$H37,0) -> 0.056607319 | O37: =IFERROR(VLOOKUP($C37+O$6,$C$11:$AK$38,4,FALSE)/$H37,0) -> 0 | P37: =IFERROR(VLOOKUP($C37+P$6,$C$11:$AK$38,4,FALSE)/$H37,0) -> 0.21028534 | Q37: =IFERROR(VLOOKUP($C37+Q$6,$C$11:$AK$38,4,FALSE)/$H37,0) -> 0 | R37: =IFERROR(VLOOKUP($C37+R$6,$C$11:$AK$38,4,FALSE)/$H37,0) -> 0 | ... AK37: =IFERROR(VLOOKUP($C37+AK$6,$C$11:$AK$38,4,FALSE)/$H37,0) -> 0
B38: 2024Q4 | C38: =C39+3 -> 3 | D38: =_xlfn.XLOOKUP($B$8,Paid_DFs!$G$5:$S$5,Paid_DFs!$G34:$S34) -> 1.0606112 | E38: =PRODUCT($D$11:$D38) -> 1.0924225 | F38: =G38-G39 -> 0.91539674 | G38: =1/E38 -> 0.91539674 | H38: =1-G38 -> 0.084603259 | I38: =SUM(J38:AK38) -> 1 | J38: =IF($H38=0%,100%,IFERROR(VLOOKUP($C38+J$6,$C$11:$AK$38,4,FALSE)/$H38,0)) -> 0.65580613 | K38: =IFERROR(VLOOKUP($C38+K$6,$C$11:$AK$38,4,FALSE)/$H38,0) -> 0.066340625 | L38: =IFERROR(VLOOKUP($C38+L$6,$C$11:$AK$38,4,FALSE)/$H38,0) -> 0.074087906 | M38: =IFERROR(VLOOKUP($C38+M$6,$C$11:$AK$38,4,FALSE)/$H38,0) -> 0.01394297 | N38: =IFERROR(VLOOKUP($C38+N$6,$C$11:$AK$38,4,FALSE)/$H38,0) -> 0.0018387678 | O38: =IFERROR(VLOOKUP($C38+O$6,$C$11:$AK$38,4,FALSE)/$H38,0) -> 0.019483892 | P38: =IFERROR(VLOOKUP($C38+P$6,$C$11:$AK$38,4,FALSE)/$H38,0) -> 0 | Q38: =IFERROR(VLOOKUP($C38+Q$6,$C$11:$AK$38,4,FALSE)/$H38,0) -> 0.072378923 | R38: =IFERROR(VLOOKUP($C38+R$6,$C$11:$AK$38,4,FALSE)/$H38,0) -> 0 | ... AK38: =IFERROR(VLOOKUP($C38+AK$6,$C$11:$AK$38,4,FALSE)/$H38,0) -> 0
B39: Total | H39: =SUM(H11:H38) -> 0.29626586 | J39: =SUM(J11:J38) -> 12.726502 | K39: =SUM(K11:K38) -> 1.8729882 | L39: =SUM(L11:L38) -> 1.6018619 | M39: =SUM(M11:M38) -> 1.4707064 | N39: =SUM(N11:N38) -> 1.4136533 | O39: =SUM(O11:O38) -> 1.2799772 | P39: =SUM(P11:P38) -> 1.2102853 | Q39: =SUM(Q11:Q38) -> 1.0723789 | ... AK39: =SUM(AK11:AK38) -> 0
I41: =1-I38 -> 0 | K41: =F33/H38 -> 0.0018387678
H42: =H39-H40 -> 0.29626586
B45: =B8 -> Liability | J45: =$H$48/4 -> 1615427 | K45: =$H$48/4 -> 1615427 | L45: =$H$48/4 -> 1615427 | M45: =$H$48/4 -> 1615427
J46: Time (in years)
E47: Origin | F47: OCR | G47: IBNR | H47: Claims Provision | I47: Check | J47: =J10 -> 0.12 | K47: =K10 -> 0.38 | L47: =L10 -> 0.62 | M47: =M10 -> 0.88 | N47: =N10 -> 1.12 | O47: =O10 -> 1.38 | P47: =P10 -> 1.62 | Q47: =Q10 -> 1.88 | ... AD47: =AD10 -> 5.12 | AE47: 5.38 | AF47: 5.62 | AG47: 5.88 | AH47: 6.12 | AI47: 6.38 | AJ47: 6.62 | AK47: 6.88
E48: =B11 -> 2018Q1 | F48: =_xlfn.XLOOKUP($B$8,OCR!$D$2:$P$2,OCR!$D4:$P4) -> 6461708 | G48: =_xlfn.XLOOKUP($B$8,IBNR!$G$5:$S$5,IBNR!$G7:$S7) -> 2.3702478e-10 | H48: =SUM(F48:G48) -> 6461708 | I48: =SUM(J48:AK48) -> 6461708 | J48: =$H48*J11 -> 6461708 | K48: =$H48*K11 -> 0 | L48: =$H48*L11 -> 0 | M48: =$H48*M11 -> 0 | N48: =$H48*N11 -> 0 | O48: =$H48*O11 -> 0 | P48: =$H48*P11 -> 0 | Q48: =$H48*Q11 -> 0 | ... AK48: =$H48*AK11 -> 0
E49: =B12 -> 2018Q2 | F49: =_xlfn.XLOOKUP($B$8,OCR!$D$2:$P$2,OCR!$D5:$P5) -> 165000 | G49: =_xlfn.XLOOKUP($B$8,IBNR!$G$5:$S$5,IBNR!$G8:$S8) -> 4.4442147e-11 | H49: =SUM(F49:G49) -> 165000 | I49: =SUM(J49:AK49) -> 165000 | J49: =$H49*J12 -> 165000 | K49: =$H49*K12 -> 0 | L49: =$H49*L12 -> 0 | M49: =$H49*M12 -> 0 | N49: =$H49*N12 -> 0 | O49: =$H49*O12 -> 0 | P49: =$H49*P12 -> 0 | Q49: =$H49*Q12 -> 0 | ... AK49: =$H49*AK12 -> 0
E50: =B13 -> 2018Q3 | F50: =_xlfn.XLOOKUP($B$8,OCR!$D$2:$P$2,OCR!$D6:$P6) -> 110000 | G50: =_xlfn.XLOOKUP($B$8,IBNR!$G$5:$S$5,IBNR!$G9:$S9) -> 1.8961983e-09 | H50: =SUM(F50:G50) -> 110000 | I50: =SUM(J50:AK50) -> 110000 | J50: =$H50*J13 -> 110000 | K50: =$H50*K13 -> 0 | L50: =$H50*L13 -> 0 | M50: =$H50*M13 -> 0 | N50: =$H50*N13 -> 0 | O50: =$H50*O13 -> 0 | P50: =$H50*P13 -> 0 | Q50: =$H50*Q13 -> 0 | ... AK50: =$H50*AK13 -> 0
E51: =B14 -> 2018Q4 | F51: =_xlfn.XLOOKUP($B$8,OCR!$D$2:$P$2,OCR!$D7:$P7) -> 0 | G51: =_xlfn.XLOOKUP($B$8,IBNR!$G$5:$S$5,IBNR!$G10:$S10) -> 8.8884293e-11 | H51: =SUM(F51:G51) -> 8.8884293e-11 | I51: =SUM(J51:AK51) -> 8.8884293e-11 | J51: =$H51*J14 -> 8.8884293e-11 | K51: =$H51*K14 -> 0 | L51: =$H51*L14 -> 0 | M51: =$H51*M14 -> 0 | N51: =$H51*N14 -> 0 | O51: =$H51*O14 -> 0 | P51: =$H51*P14 -> 0 | Q51: =$H51*Q14 -> 0 | ... AK51: =$H51*AK14 -> 0
E52: =B15 -> 2019Q1 | F52: =_xlfn.XLOOKUP($B$8,OCR!$D$2:$P$2,OCR!$D8:$P8) -> 220000 | G52: =_xlfn.XLOOKUP($B$8,IBNR!$G$5:$S$5,IBNR!$G11:$S11) -> 1.7776859e-10 | H52: =SUM(F52:G52) -> 220000 | I52: =SUM(J52:AK52) -> 220000 | J52: =$H52*J15 -> 220000 | K52: =$H52*K15 -> 0 | L52: =$H52*L15 -> 0 | M52: =$H52*M15 -> 0 | N52: =$H52*N15 -> 0 | O52: =$H52*O15 -> 0 | P52: =$H52*P15 -> 0 | Q52: =$H52*Q15 -> 0 | ... AK52: =$H52*AK15 -> 0
E53: =B16 -> 2019Q2 | F53: =_xlfn.XLOOKUP($B$8,OCR!$D$2:$P$2,OCR!$D9:$P9) -> 0 | G53: =_xlfn.XLOOKUP($B$8,IBNR!$G$5:$S$5,IBNR!$G12:$S12) -> 0 | H53: =SUM(F53:G53) -> 0 | I53: =SUM(J53:AK53) -> 0 | J53: =$H53*J16 -> 0 | K53: =$H53*K16 -> 0 | L53: =$H53*L16 -> 0 | M53: =$H53*M16 -> 0 | N53: =$H53*N16 -> 0 | O53: =$H53*O16 -> 0 | P53: =$H53*P16 -> 0 | Q53: =$H53*Q16 -> 0 | ... AK53: =$H53*AK16 -> 0
E54: =B17 -> 2019Q3 | F54: =_xlfn.XLOOKUP($B$8,OCR!$D$2:$P$2,OCR!$D10:$P10) -> 0 | G54: =_xlfn.XLOOKUP($B$8,IBNR!$G$5:$S$5,IBNR!$G13:$S13) -> 4.7404956e-10 | H54: =SUM(F54:G54) -> 4.7404956e-10 | I54: =SUM(J54:AK54) -> 4.7404956e-10 | J54: =$H54*J17 -> 4.7404956e-10 | K54: =$H54*K17 -> 0 | L54: =$H54*L17 -> 0 | M54: =$H54*M17 -> 0 | N54: =$H54*N17 -> 0 | O54: =$H54*O17 -> 0 | P54: =$H54*P17 -> 0 | Q54: =$H54*Q17 -> 0 | ... AK54: =$H54*AK17 -> 0
E55: =B18 -> 2019Q4 | F55: =_xlfn.XLOOKUP($B$8,OCR!$D$2:$P$2,OCR!$D11:$P11) -> 1760000 | G55: =_xlfn.XLOOKUP($B$8,IBNR!$G$5:$S$5,IBNR!$G14:$S14) -> 0 | H55: =SUM(F55:G55) -> 1760000 | I55: =SUM(J55:AK55) -> 1760000 | J55: =$H55*J18 -> 1760000 | K55: =$H55*K18 -> 0 | L55: =$H55*L18 -> 0 | M55: =$H55*M18 -> 0 | N55: =$H55*N18 -> 0 | O55: =$H55*O18 -> 0 | P55: =$H55*P18 -> 0 | Q55: =$H55*Q18 -> 0 | ... AK55: =$H55*AK18 -> 0
E56: =B19 -> 2020Q1 | F56: =_xlfn.XLOOKUP($B$8,OCR!$D$2:$P$2,OCR!$D12:$P12) -> 0 | G56: =_xlfn.XLOOKUP($B$8,IBNR!$G$5:$S$5,IBNR!$G15:$S15) -> 1.8517561e-12 | H56: =SUM(F56:G56) -> 1.8517561e-12 | I56: =SUM(J56:AK56) -> 1.8517561e-12 | J56: =$H56*J19 -> 1.8517561e-12 | K56: =$H56*K19 -> 0 | L56: =$H56*L19 -> 0 | M56: =$H56*M19 -> 0 | N56: =$H56*N19 -> 0 | O56: =$H56*O19 -> 0 | P56: =$H56*P19 -> 0 | Q56: =$H56*Q19 -> 0 | ... AK56: =$H56*AK19 -> 0
E57: =B20 -> 2020Q2 | F57: =_xlfn.XLOOKUP($B$8,OCR!$D$2:$P$2,OCR!$D13:$P13) -> 0 | G57: =_xlfn.XLOOKUP($B$8,IBNR!$G$5:$S$5,IBNR!$G16:$S16) -> 3095.1111 | H57: =SUM(F57:G57) -> 3095.1111 | I57: =SUM(J57:AK57) -> 3095.1111 | J57: =$H57*J20 -> 3095.1111 | K57: =$H57*K20 -> 0 | L57: =$H57*L20 -> 0 | M57: =$H57*M20 -> 0 | N57: =$H57*N20 -> 0 | O57: =$H57*O20 -> 0 | P57: =$H57*P20 -> 0 | Q57: =$H57*Q20 -> 0 | ... AK57: =$H57*AK20 -> 0
E58: =B21 -> 2020Q3 | F58: =_xlfn.XLOOKUP($B$8,OCR!$D$2:$P$2,OCR!$D14:$P14) -> 220000 | G58: =_xlfn.XLOOKUP($B$8,IBNR!$G$5:$S$5,IBNR!$G17:$S17) -> 21521.836 | H58: =SUM(F58:G58) -> 241521.84 | I58: =SUM(J58:AK58) -> 241521.84 | J58: =$H58*J21 -> 241521.84 | K58: =$H58*K21 -> 0 | L58: =$H58*L21 -> 0 | M58: =$H58*M21 -> 0 | N58: =$H58*N21 -> 0 | O58: =$H58*O21 -> 0 | P58: =$H58*P21 -> 0 | Q58: =$H58*Q21 -> 0 | ... AK58: =$H58*AK21 -> 0
E59: =B22 -> 2020Q4 | F59: =_xlfn.XLOOKUP($B$8,OCR!$D$2:$P$2,OCR!$D15:$P15) -> 874500 | G59: =_xlfn.XLOOKUP($B$8,IBNR!$G$5:$S$5,IBNR!$G18:$S18) -> 14265.297 | H59: =SUM(F59:G59) -> 888765.3 | I59: =SUM(J59:AK59) -> 888765.3 | J59: =$H59*J22 -> 0 | K59: =$H59*K22 -> 888765.3 | L59: =$H59*L22 -> 0 | M59: =$H59*M22 -> 0 | N59: =$H59*N22 -> 0 | O59: =$H59*O22 -> 0 | P59: =$H59*P22 -> 0 | Q59: =$H59*Q22 -> 0 | ... AK59: =$H59*AK22 -> 0
... E67: =B30 -> 2022Q4 | F67: =_xlfn.XLOOKUP($B$8,OCR!$D$2:$P$2,OCR!$D23:$P23) -> 40603790 | G67: =_xlfn.XLOOKUP($B$8,IBNR!$G$5:$S$5,IBNR!$G26:$S26) -> 30838.212 | H67: =SUM(F67:G67) -> 40634628 | I67: =SUM(J67:AK67) -> 40634628 | J67: =$H67*J30 -> 0 | K67: =$H67*K30 -> 0 | L67: =$H67*L30 -> 0 | M67: =$H67*M30 -> 0 | N67: =$H67*N30 -> 0 | O67: =$H67*O30 -> 0 | P67: =$H67*P30 -> 0 | Q67: =$H67*Q30 -> 0 | ... AK67: =$H67*AK30 -> 0
E68: 2023Q1 | F68: =_xlfn.XLOOKUP($B$8,OCR!$D$2:$P$2,OCR!$D24:$P24) -> 6543900 | G68: =_xlfn.XLOOKUP($B$8,IBNR!$G$5:$S$5,IBNR!$G27:$S27) -> 117303.52 | H68: =SUM(F68:G68) -> 6661203.5 | I68: =SUM(J68:AK68) -> 6661203.5 | J68: =$H68*J31 -> 2861315 | K68: =$H68*K31 -> 0 | L68: =$H68*L31 -> 0 | M68: =$H68*M31 -> 0 | N68: =$H68*N31 -> 0 | O68: =$H68*O31 -> 0 | P68: =$H68*P31 -> 0 | Q68: =$H68*Q31 -> 0 | ... AK68: =$H68*AK31 -> 0
E69: 2023Q2 | F69: =_xlfn.XLOOKUP($B$8,OCR!$D$2:$P$2,OCR!$D25:$P25) -> 2365000 | G69: =_xlfn.XLOOKUP($B$8,IBNR!$G$5:$S$5,IBNR!$G28:$S28) -> 311685.89 | H69: =SUM(F69:G69) -> 2676685.9 | I69: =SUM(J69:AK69) -> 2676685.9 | J69: =$H69*J32 -> 0 | K69: =$H69*K32 -> 1149768.4 | L69: =$H69*L32 -> 0 | M69: =$H69*M32 -> 0 | N69: =$H69*N32 -> 0 | O69: =$H69*O32 -> 0 | P69: =$H69*P32 -> 0 | Q69: =$H69*Q32 -> 0 | ... AK69: =$H69*AK32 -> 0
E70: 2023Q3 | F70: =_xlfn.XLOOKUP($B$8,OCR!$D$2:$P$2,OCR!$D26:$P26) -> 2860000 | G70: =_xlfn.XLOOKUP($B$8,IBNR!$G$5:$S$5,IBNR!$G29:$S29) -> 394539.58 | H70: =SUM(F70:G70) -> 3254539.6 | I70: =SUM(J70:AK70) -> 3254539.6 | J70: =$H70*J33 -> 337322.5 | K70: =$H70*K33 -> 0 | L70: =$H70*L33 -> 1253088.4 | M70: =$H70*M33 -> 0 | N70: =$H70*N33 -> 0 | O70: =$H70*O33 -> 0 | P70: =$H70*P33 -> 0 | Q70: =$H70*Q33 -> 0 | ... AK70: =$H70*AK33 -> 0
E71: 2023Q4 | F71: =_xlfn.XLOOKUP($B$8,OCR!$D$2:$P$2,OCR!$D27:$P27) -> 1265000 | G71: =_xlfn.XLOOKUP($B$8,IBNR!$G$5:$S$5,IBNR!$G30:$S30) -> 1286705.4 | H71: =SUM(F71:G71) -> 2551705.4 | I71: =SUM(J71:AK71) -> 2551705.4 | J71: =$H71*J34 -> 24717.813 | K71: =$H71*K34 -> 261914.09 | L71: =$H71*L34 -> 0 | M71: =$H71*M34 -> 972960.64 | N71: =$H71*N34 -> 0 | O71: =$H71*O34 -> 0 | P71: =$H71*P34 -> 0 | Q71: =$H71*Q34 -> 0 | ... AK71: =$H71*AK34 -> 0
E72: 2024Q1 | F72: =_xlfn.XLOOKUP($B$8,OCR!$D$2:$P$2,OCR!$D28:$P28) -> 6563429.4 | G72: =_xlfn.XLOOKUP($B$8,IBNR!$G$5:$S$5,IBNR!$G31:$S31) -> 117303.52 | H72: =SUM(F72:G72) -> 6680732.9 | I72: =SUM(J72:AK72) -> 6680732.9 | J72: =$H72*J35 -> 457139.87 | K72: =$H72*K35 -> 60286.585 | L72: =$H72*L35 -> 638806.78 | M72: =$H72*M35 -> 0 | N72: =$H72*N35 -> 2373044.7 | O72: =$H72*O35 -> 0 | P72: =$H72*P35 -> 0 | Q72: =$H72*Q35 -> 0 | ... AK72: =$H72*AK35 -> 0
E73: 2024Q2 | F73: =_xlfn.XLOOKUP($B$8,OCR!$D$2:$P$2,OCR!$D29:$P29) -> 17703400 | G73: =_xlfn.XLOOKUP($B$8,IBNR!$G$5:$S$5,IBNR!$G32:$S32) -> 311685.89 | H73: =SUM(F73:G73) -> 18015086 | I73: =SUM(J73:AK73) -> 18015086 | J73: =$H73*J36 -> 4803615 | K73: =$H73*K36 -> 904016.1 | L73: =$H73*L36 -> 119219.62 | M73: =$H73*M36 -> 1263271.2 | N73: =$H73*N36 -> 0 | O73: =$H73*O36 -> 4692810.2 | P73: =$H73*P36 -> 0 | Q73: =$H73*Q36 -> 0 | ... AK73: =$H73*AK36 -> 0
E74: 2024Q3 | F74: =_xlfn.XLOOKUP($B$8,OCR!$D$2:$P$2,OCR!$D30:$P30) -> 24107628 | G74: =_xlfn.XLOOKUP($B$8,IBNR!$G$5:$S$5,IBNR!$G33:$S33) -> 394539.58 | H74: =SUM(F74:G74) -> 24502167 | I74: =SUM(J74:AK74) -> 24502167 | J74: =$H74*J37 -> 4722597.4 | K74: =$H74*K37 -> 5274104 | L74: =$H74*L37 -> 992559.77 | M74: =$H74*M37 -> 130896.56 | N74: =$H74*N37 -> 1387002 | O74: =$H74*O37 -> 0 | P74: =$H74*P37 -> 5152446.4 | Q74: =$H74*Q37 -> 0 | ... AK74: =$H74*AK37 -> 0
E75: 2024Q4 | F75: =_xlfn.XLOOKUP($B$8,OCR!$D$2:$P$2,OCR!$D31:$P31) -> 14190000 | G75: =_xlfn.XLOOKUP($B$8,IBNR!$G$5:$S$5,IBNR!$G34:$S34) -> 1286705.4 | H75: =SUM(F75:G75) -> 15476705 | I75: =SUM(J75:AK75) -> 15476705 | J75: =$H75*J38 -> 10149718 | K75: =$H75*K38 -> 1026734.3 | L75: =$H75*L38 -> 1146636.7 | M75: =$H75*M38 -> 215791.24 | N75: =$H75*N38 -> 28458.067 | O75: =$H75*O38 -> 301546.46 | P75: =$H75*P38 -> 0 | Q75: =$H75*Q38 -> 1120187.3 | ... AK75: =$H75*AK38 -> 0
E76: =B39 -> Total | F76: =SUM(F48:F75) -> 1.4532053e+08 | G76: =SUM(G48:G75) -> 5117447.9 | H76: =SUM(F76:G76) -> 1.5043798e+08 | I76: =SUM(J76:AK76) -> 1.5043798e+08 | J76: =SUM(J48:J75) -> 32317751 | K76: =SUM(K48:K75) -> 9565588.8 | L76: =SUM(L48:L75) -> 5832776.3 | M76: =SUM(M48:M75) -> 4239183.2 | N76: =SUM(N48:N75) -> 3901174.2 | O76: =SUM(O48:O75) -> 5215943.5 | P76: =SUM(P48:P75) -> 7298927.3 | Q76: =SUM(Q48:Q75) -> 4988280.5 | ... AK76: =SUM(AK48:AK75) -> 0
I77: =ROUNDDOWN(I76,0)=ROUNDDOWN(H76,0) -> TRUE

Sheet MISC
J3: 2025 | K3: 2025 | L3: 2025 | M3: 2025 | N3: =J3+1 -> 2026 | O3: =K3+1 -> 2026 | P3: =L3+1 -> 2026 | Q3: =M3+1 -> 2026 | R3: =N3+1 -> 2027 | S3: =O3+1 -> 2027 | T3: =P3+1 -> 2027 | U3: =Q3+1 -> 2027 | ... AK3: =AG3+1 -> 2031
J4: Q1 | K4: Q2 | L4: Q3 | M4: Q4 | N4: Q1 | O4: Q2 | P4: Q3 | Q4: Q4 | R4: Q1 | S4: Q2 | T4: Q3 | U4: Q4 | V4: Q1 | W4: Q2 | X4: Q3 | Y4: Q4 | Z4: Q1 | AA4: Q2 | AB4: Q3 | AC4: Q4 | AD4: Q1 | AE4: Q2 | AF4: Q3 | AG4: Q4 | AH4: Q1 | AI4: Q2 | AJ4: Q3 | AK4: Q4
J5: =J4&"-"&J3 -> Q1-2025 | K5: =K4&"-"&K3 -> Q2-2025 | L5: =L4&"-"&L3 -> Q3-2025 | M5: =M4&"-"&M3 -> Q4-2025 | N5: =N4&"-"&N3 -> Q1-2026 | O5: =O4&"-"&O3 -> Q2-2026 | P5: =P4&"-"&P3 -> Q3-2026 | Q5: =Q4&"-"&Q3 -> Q4-2026 | ... AK5: =AK4&"-"&AK3 -> Q4-2031
H6: Payments in | J6: 3 | K6: =J6+3 -> 6 | L6: =K6+3 -> 9 | M6: =L6+3 -> 12 | N6: =M6+3 -> 15 | O6: =N6+3 -> 18 | P6: =O6+3 -> 21 | Q6: =P6+3 -> 24 | R6: =Q6+3 -> 27 | ... AK6: =AJ6+3 -> 84
K7: =K10-J10 -> 0.26 | L7: =L10-K10 -> 0.24 | M7: =M10-L10 -> 0.26 | N7: =N10-M10 -> 0.24 | O7: =O10-N10 -> 0.26 | P7: =P10-O10 -> 0.24 | Q7: =Q10-P10 -> 0.26 | R7: =R10-Q10 -> 0.24 | ... AK7: =AK10-AJ10 -> 0.26
B8: Miscellaneous | K8: =SUM(J10:K10) -> 0.5 | L8: =SUM(K10:L10) -> 1 | M8: =SUM(L10:M10) -> 1.5 | N8: =SUM(M10:N10) -> 2 | O8: =SUM(N10:O10) -> 2.5 | P8: =SUM(O10:P10) -> 3 | Q8: =SUM(P10:Q10) -> 3.5 | R8: =SUM(Q10:R10) -> 4 | ... AK8: =SUM(AJ10:AK10) -> 13.5
J9: Time (in years)
B10: Origin | C10: Age | D10: Paid DF's | E10: Cumulative Development Factors | F10: Incremental Payments | G10: Cumulative Payments | H10: Expected Unpaid % | I10: Check | J10: 0.12 | K10: 0.38 | L10: 0.62 | M10: 0.88 | N10: 1.12 | O10: 1.38 | P10: 1.62 | Q10: 1.88 | R10: 2.12 | S10: 2.38 | T10: 2.62 | U10: 2.88 | V10: 3.12 | W10: 3.38 | X10: 3.62 | Y10: 3.88 | Z10: 4.12 | AA10: 4.38 | AB10: 4.62 | AC10: 4.88 | AD10: 5.12 | AE10: 5.38 | AF10: 5.62 | AG10: 5.88 | AH10: 6.12 | AI10: 6.38 | AJ10: 6.62 | AK10: 6.88
B11: =IBNR!F7 -> 2018Q1 | C11: =C12+3 -> 84 | D11: =_xlfn.XLOOKUP($B$8,Paid_DFs!$G$5:$S$5,Paid_DFs!$G7:$S7) -> 1 | E11: =PRODUCT($D$11:$D11) -> 1 | F11: =G11-G12 -> 0 | G11: =1/E11 -> 1 | H11: =1-G11 -> 0 | I11: =SUM(J11:AK11) -> 1 | J11: =IF($H11=0%,100%,IFERROR(VLOOKUP($C11+J$6,$C$11:$AK$38,4,FALSE)/$H11,0)) -> 1 | K11: =IFERROR(VLOOKUP($C11+K$6,$C$11:$AK$38,4,FALSE)/$H11,0) -> 0 | L11: =IFERROR(VLOOKUP($C11+L$6,$C$11:$AK$38,4,FALSE)/$H11,0) -> 0 | M11: =IFERROR(VLOOKUP($C11+M$6,$C$11:$AK$38,4,FALSE)/$H11,0) -> 0 | N11: =IFERROR(VLOOKUP($C11+N$6,$C$11:$AK$38,4,FALSE)/$H11,0) -> 0 | O11: =IFERROR(VLOOKUP($C11+O$6,$C$11:$AK$38,4,FALSE)/$H11,0) -> 0 | P11: =IFERROR(VLOOKUP($C11+P$6,$C$11:$AK$38,4,FALSE)/$H11,0) -> 0 | Q11: =IFERROR(VLOOKUP($C11+Q$6,$C$11:$AK$38,4,FALSE)/$H11,0) -> 0 | R11: =IFERROR(VLOOKUP($C11+R$6,$C$11:$AK$38,4,FALSE)/$H11,0) -> 0 | ... AK11: =IFERROR(VLOOKUP($C11+AK$6,$C$11:$AK$38,4,FALSE)/$H11,0) -> 0
B12: =IBNR!F8 -> 2018Q2 | C12: =C13+3 -> 81 | D12: =_xlfn.XLOOKUP($B$8,Paid_DFs!$G$5:$S$5,Paid_DFs!$G8:$S8) -> 1 | E12: =PRODUCT($D$11:$D12) -> 1 | F12: =G12-G13 -> 0 | G12: =1/E12 -> 1 | H12: =1-G12 -> 0 | I12: =SUM(J12:AK12) -> 1 | J12: =IF($H12=0%,100%,IFERROR(VLOOKUP($C12+J$6,$C$11:$AK$38,4,FALSE)/$H12,0)) -> 1 | K12: =IFERROR(VLOOKUP($C12+K$6,$C$11:$AK$38,4,FALSE)/$H12,0) -> 0 | L12: =IFERROR(VLOOKUP($C12+L$6,$C$11:$AK$38,4,FALSE)/$H12,0) -> 0 | M12: =IFERROR(VLOOKUP($C12+M$6,$C$11:$AK$38,4,FALSE)/$H12,0) -> 0 | N12: =IFERROR(VLOOKUP($C12+N$6,$C$11:$AK$38,4,FALSE)/$H12,0) -> 0 | O12: =IFERROR(VLOOKUP($C12+O$6,$C$11:$AK$38,4,FALSE)/$H12,0) -> 0 | P12: =IFERROR(VLOOKUP($C12+P$6,$C$11:$AK$38,4,FALSE)/$H12,0) -> 0 | Q12: =IFERROR(VLOOKUP($C12+Q$6,$C$11:$AK$38,4,FALSE)/$H12,0) -> 0 | R12: =IFERROR(VLOOKUP($C12+R$6,$C$11:$AK$38,4,FALSE)/$H12,0) -> 0 | ... AK12: =IFERROR(VLOOKUP($C12+AK$6,$C$11:$AK$38,4,FALSE)/$H12,0) -> 0
B13: =IBNR!F9 -> 2018Q3 | C13: =C14+3 -> 78 | D13: =_xlfn.XLOOKUP($B$8,Paid_DFs!$G$5:$S$5,Paid_DFs!$G9:$S9) -> 1 | E13: =PRODUCT($D$11:$D13) -> 1 | F13: =G13-G14 -> 0 | G13: =1/E13 -> 1 | H13: =1-G13 -> 0 | I13: =SUM(J13:AK13) -> 1 | J13: =IF($H13=0%,100%,IFERROR(VLOOKUP($C13+J$6,$C$11:$AK$38,4,FALSE)/$H13,0)) -> 1 | K13: =IFERROR(VLOOKUP($C13+K$6,$C$11:$AK$38,4,FALSE)/$H13,0) -> 0 | L13: =IFERROR(VLOOKUP($C13+L$6,$C$11:$AK$38,4,FALSE)/$H13,0) -> 0 | M13: =IFERROR(VLOOKUP($C13+M$6,$C$11:$AK$38,4,FALSE)/$H13,0) -> 0 | N13: =IFERROR(VLOOKUP($C13+N$6,$C$11:$AK$38,4,FALSE)/$H13,0) -> 0 | O13: =IFERROR(VLOOKUP($C13+O$6,$C$11:$AK$38,4,FALSE)/$H13,0) -> 0 | P13: =IFERROR(VLOOKUP($C13+P$6,$C$11:$AK$38,4,FALSE)/$H13,0) -> 0 | Q13: =IFERROR(VLOOKUP($C13+Q$6,$C$11:$AK$38,4,FALSE)/$H13,0) -> 0 | R13: =IFERROR(VLOOKUP($C13+R$6,$C$11:$AK$38,4,FALSE)/$H13,0) -> 0 | ... AK13: =IFERROR(VLOOKUP($C13+AK$6,$C$11:$AK$38,4,FALSE)/$H13,0) -> 0
B14: =IBNR!F10 -> 2018Q4 | C14: =C15+3 -> 75 | D14: =_xlfn.XLOOKUP($B$8,Paid_DFs!$G$5:$S$5,Paid_DFs!$G10:$S10) -> 1 | E14: =PRODUCT($D$11:$D14) -> 1 | F14: =G14-G15 -> 0 | G14: =1/E14 -> 1 | H14: =1-G14 -> 0 | I14: =SUM(J14:AK14) -> 1 | J14: =IF($H14=0%,100%,IFERROR(VLOOKUP($C14+J$6,$C$11:$AK$38,4,FALSE)/$H14,0)) -> 1 | K14: =IFERROR(VLOOKUP($C14+K$6,$C$11:$AK$38,4,FALSE)/$H14,0) -> 0 | L14: =IFERROR(VLOOKUP($C14+L$6,$C$11:$AK$38,4,FALSE)/$H14,0) -> 0 | M14: =IFERROR(VLOOKUP($C14+M$6,$C$11:$AK$38,4,FALSE)/$H14,0) -> 0 | N14: =IFERROR(VLOOKUP($C14+N$6,$C$11:$AK$38,4,FALSE)/$H14,0) -> 0 | O14: =IFERROR(VLOOKUP($C14+O$6,$C$11:$AK$38,4,FALSE)/$H14,0) -> 0 | P14: =IFERROR(VLOOKUP($C14+P$6,$C$11:$AK$38,4,FALSE)/$H14,0) -> 0 | Q14: =IFERROR(VLOOKUP($C14+Q$6,$C$11:$AK$38,4,FALSE)/$H14,0) -> 0 | R14: =IFERROR(VLOOKUP($C14+R$6,$C$11:$AK$38,4,FALSE)/$H14,0) -> 0 | ... AK14: =IFERROR(VLOOKUP($C14+AK$6,$C$11:$AK$38,4,FALSE)/$H14,0) -> 0
B15: =IBNR!F11 -> 2019Q1 | C15: =C16+3 -> 72 | D15: =_xlfn.XLOOKUP($B$8,Paid_DFs!$G$5:$S$5,Paid_DFs!$G11:$S11) -> 1 | E15: =PRODUCT($D$11:$D15) -> 1 | F15: =G15-G16 -> 0 | G15: =1/E15 -> 1 | H15: =1-G15 -> 0 | I15: =SUM(J15:AK15) -> 1 | J15: =IF($H15=0%,100%,IFERROR(VLOOKUP($C15+J$6,$C$11:$AK$38,4,FALSE)/$H15,0)) -> 1 | K15: =IFERROR(VLOOKUP($C15+K$6,$C$11:$AK$38,4,FALSE)/$H15,0) -> 0 | L15: =IFERROR(VLOOKUP($C15+L$6,$C$11:$AK$38,4,FALSE)/$H15,0) -> 0 | M15: =IFERROR(VLOOKUP($C15+M$6,$C$11:$AK$38,4,FALSE)/$H15,0) -> 0 | N15: =IFERROR(VLOOKUP($C15+N$6,$C$11:$AK$38,4,FALSE)/$H15,0) -> 0 | O15: =IFERROR(VLOOKUP($C15+O$6,$C$11:$AK$38,4,FALSE)/$H15,0) -> 0 | P15: =IFERROR(VLOOKUP($C15+P$6,$C$11:$AK$38,4,FALSE)/$H15,0) -> 0 | Q15: =IFERROR(VLOOKUP($C15+Q$6,$C$11:$AK$38,4,FALSE)/$H15,0) -> 0 | R15: =IFERROR(VLOOKUP($C15+R$6,$C$11:$AK$38,4,FALSE)/$H15,0) -> 0 | ... AK15: =IFERROR(VLOOKUP($C15+AK$6,$C$11:$AK$38,4,FALSE)/$H15,0) -> 0
B16: =IBNR!F12 -> 2019Q2 | C16: =C17+3 -> 69 | D16: =_xlfn.XLOOKUP($B$8,Paid_DFs!$G$5:$S$5,Paid_DFs!$G12:$S12) -> 1 | E16: =PRODUCT($D$11:$D16) -> 1 | F16: =G16-G17 -> 0 | G16: =1/E16 -> 1 | H16: =1-G16 -> 0 | I16: =SUM(J16:AK16) -> 1 | J16: =IF($H16=0%,100%,IFERROR(VLOOKUP($C16+J$6,$C$11:$AK$38,4,FALSE)/$H16,0)) -> 1 | K16: =IFERROR(VLOOKUP($C16+K$6,$C$11:$AK$38,4,FALSE)/$H16,0) -> 0 | L16: =IFERROR(VLOOKUP($C16+L$6,$C$11:$AK$38,4,FALSE)/$H16,0) -> 0 | M16: =IFERROR(VLOOKUP($C16+M$6,$C$11:$AK$38,4,FALSE)/$H16,0) -> 0 | N16: =IFERROR(VLOOKUP($C16+N$6,$C$11:$AK$38,4,FALSE)/$H16,0) -> 0 | O16: =IFERROR(VLOOKUP($C16+O$6,$C$11:$AK$38,4,FALSE)/$H16,0) -> 0 | P16: =IFERROR(VLOOKUP($C16+P$6,$C$11:$AK$38,4,FALSE)/$H16,0) -> 0 | Q16: =IFERROR(VLOOKUP($C16+Q$6,$C$11:$AK$38,4,FALSE)/$H16,0) -> 0 | R16: =IFERROR(VLOOKUP($C16+R$6,$C$11:$AK$38,4,FALSE)/$H16,0) -> 0 | ... AK16: =IFERROR(VLOOKUP($C16+AK$6,$C$11:$AK$38,4,FALSE)/$H16,0) -> 0
B17: =IBNR!F13 -> 2019Q3 | C17: =C18+3 -> 66 | D17: =_xlfn.XLOOKUP($B$8,Paid_DFs!$G$5:$S$5,Paid_DFs!$G13:$S13) -> 1 | E17: =PRODUCT($D$11:$D17) -> 1 | F17: =G17-G18 -> 0 | G17: =1/E17 -> 1 | H17: =1-G17 -> 0 | I17: =SUM(J17:AK17) -> 1 | J17: =IF($H17=0%,100%,IFERROR(VLOOKUP($C17+J$6,$C$11:$AK$38,4,FALSE)/$H17,0)) -> 1 | K17: =IFERROR(VLOOKUP($C17+K$6,$C$11:$AK$38,4,FALSE)/$H17,0) -> 0 | L17: =IFERROR(VLOOKUP($C17+L$6,$C$11:$AK$38,4,FALSE)/$H17,0) -> 0 | M17: =IFERROR(VLOOKUP($C17+M$6,$C$11:$AK$38,4,FALSE)/$H17,0) -> 0 | N17: =IFERROR(VLOOKUP($C17+N$6,$C$11:$AK$38,4,FALSE)/$H17,0) -> 0 | O17: =IFERROR(VLOOKUP($C17+O$6,$C$11:$AK$38,4,FALSE)/$H17,0) -> 0 | P17: =IFERROR(VLOOKUP($C17+P$6,$C$11:$AK$38,4,FALSE)/$H17,0) -> 0 | Q17: =IFERROR(VLOOKUP($C17+Q$6,$C$11:$AK$38,4,FALSE)/$H17,0) -> 0 | R17: =IFERROR(VLOOKUP($C17+R$6,$C$11:$AK$38,4,FALSE)/$H17,0) -> 0 | ... AK17: =IFERROR(VLOOKUP($C17+AK$6,$C$11:$AK$38,4,FALSE)/$H17,0) -> 0
B18: =IBNR!F14 -> 2019Q4 | C18: =C19+3 -> 63 | D18: =_xlfn.XLOOKUP($B$8,Paid_DFs!$G$5:$S$5,Paid_DFs!$G14:$S14) -> 1 | E18: =PRODUCT($D$11:$D18) -> 1 | F18: =G18-G19 -> 0 | G18: =1/E18 -> 1 | H18: =1-G18 -> 0 | I18: =SUM(J18:AK18) -> 1 | J18: =IF($H18=0%,100%,IFERROR(VLOOKUP($C18+J$6,$C$11:$AK$38,4,FALSE)/$H18,0)) -> 1 | K18: =IFERROR(VLOOKUP($C18+K$6,$C$11:$AK$38,4,FALSE)/$H18,0) -> 0 | L18: =IFERROR(VLOOKUP($C18+L$6,$C$11:$AK$38,4,FALSE)/$H18,0) -> 0 | M18: =IFERROR(VLOOKUP($C18+M$6,$C$11:$AK$38,4,FALSE)/$H18,0) -> 0 | N18: =IFERROR(VLOOKUP($C18+N$6,$C$11:$AK$38,4,FALSE)/$H18,0) -> 0 | O18: =IFERROR(VLOOKUP($C18+O$6,$C$11:$AK$38,4,FALSE)/$H18,0) -> 0 | P18: =IFERROR(VLOOKUP($C18+P$6,$C$11:$AK$38,4,FALSE)/$H18,0) -> 0 | Q18: =IFERROR(VLOOKUP($C18+Q$6,$C$11:$AK$38,4,FALSE)/$H18,0) -> 0 | R18: =IFERROR(VLOOKUP($C18+R$6,$C$11:$AK$38,4,FALSE)/$H18,0) -> 0 | ... AK18: =IFERROR(VLOOKUP($C18+AK$6,$C$11:$AK$38,4,FALSE)/$H18,0) -> 0
B19: =IBNR!F15 -> 2020Q1 | C19: =C20+3 -> 60 | D19: =_xlfn.XLOOKUP($B$8,Paid_DFs!$G$5:$S$5,Paid_DFs!$G15:$S15) -> 1 | E19: =PRODUCT($D$11:$D19) -> 1 | F19: =G19-G20 -> 0 | G19: =1/E19 -> 1 | H19: =1-G19 -> 0 | I19: =SUM(J19:AK19) -> 1 | J19: =IF($H19=0%,100%,IFERROR(VLOOKUP($C19+J$6,$C$11:$AK$38,4,FALSE)/$H19,0)) -> 1 | K19: =IFERROR(VLOOKUP($C19+K$6,$C$11:$AK$38,4,FALSE)/$H19,0) -> 0 | L19: =IFERROR(VLOOKUP($C19+L$6,$C$11:$AK$38,4,FALSE)/$H19,0) -> 0 | M19: =IFERROR(VLOOKUP($C19+M$6,$C$11:$AK$38,4,FALSE)/$H19,0) -> 0 | N19: =IFERROR(VLOOKUP($C19+N$6,$C$11:$AK$38,4,FALSE)/$H19,0) -> 0 | O19: =IFERROR(VLOOKUP($C19+O$6,$C$11:$AK$38,4,FALSE)/$H19,0) -> 0 | P19: =IFERROR(VLOOKUP($C19+P$6,$C$11:$AK$38,4,FALSE)/$H19,0) -> 0 | Q19: =IFERROR(VLOOKUP($C19+Q$6,$C$11:$AK$38,4,FALSE)/$H19,0) -> 0 | R19: =IFERROR(VLOOKUP($C19+R$6,$C$11:$AK$38,4,FALSE)/$H19,0) -> 0 | ... AK19: =IFERROR(VLOOKUP($C19+AK$6,$C$11:$AK$38,4,FALSE)/$H19,0) -> 0
B20: =IBNR!F16 -> 2020Q2 | C20: =C21+3 -> 57 | D20: =_xlfn.XLOOKUP($B$8,Paid_DFs!$G$5:$S$5,Paid_DFs!$G16:$S16) -> 1 | E20: =PRODUCT($D$11:$D20) -> 1 | F20: =G20-G21 -> 0 | G20: =1/E20 -> 1 | H20: =1-G20 -> 0 | I20: =SUM(J20:AK20) -> 1 | J20: =IF($H20=0%,100%,IFERROR(VLOOKUP($C20+J$6,$C$11:$AK$38,4,FALSE)/$H20,0)) -> 1 | K20: =IFERROR(VLOOKUP($C20+K$6,$C$11:$AK$38,4,FALSE)/$H20,0) -> 0 | L20: =IFERROR(VLOOKUP($C20+L$6,$C$11:$AK$38,4,FALSE)/$H20,0) -> 0 | M20: =IFERROR(VLOOKUP($C20+M$6,$C$11:$AK$38,4,FALSE)/$H20,0) -> 0 | N20: =IFERROR(VLOOKUP($C20+N$6,$C$11:$AK$38,4,FALSE)/$H20,0) -> 0 | O20: =IFERROR(VLOOKUP($C20+O$6,$C$11:$AK$38,4,FALSE)/$H20,0) -> 0 | P20: =IFERROR(VLOOKUP($C20+P$6,$C$11:$AK$38,4,FALSE)/$H20,0) -> 0 | Q20: =IFERROR(VLOOKUP($C20+Q$6,$C$11:$AK$38,4,FALSE)/$H20,0) -> 0 | R20: =IFERROR(VLOOKUP($C20+R$6,$C$11:$AK$38,4,FALSE)/$H20,0) -> 0 | ... AK20: =IFERROR(VLOOKUP($C20+AK$6,$C$11:$AK$38,4,FALSE)/$H20,0) -> 0
B21: =IBNR!F17 -> 2020Q3 | C21: =C22+3 -> 54 | D21: =_xlfn.XLOOKUP($B$8,Paid_DFs!$G$5:$S$5,Paid_DFs!$G17:$S17) -> 1 | E21: =PRODUCT($D$11:$D21) -> 1 | F21: =G21-G22 -> 0 | G21: =1/E21 -> 1 | H21: =1-G21 -> 0 | I21: =SUM(J21:AK21) -> 1 | J21: =IF($H21=0%,100%,IFERROR(VLOOKUP($C21+J$6,$C$11:$AK$38,4,FALSE)/$H21,0)) -> 1 | K21: =IFERROR(VLOOKUP($C21+K$6,$C$11:$AK$38,4,FALSE)/$H21,0) -> 0 | L21: =IFERROR(VLOOKUP($C21+L$6,$C$11:$AK$38,4,FALSE)/$H21,0) -> 0 | M21: =IFERROR(VLOOKUP($C21+M$6,$C$11:$AK$38,4,FALSE)/$H21,0) -> 0 | N21: =IFERROR(VLOOKUP($C21+N$6,$C$11:$AK$38,4,FALSE)/$H21,0) -> 0 | O21: =IFERROR(VLOOKUP($C21+O$6,$C$11:$AK$38,4,FALSE)/$H21,0) -> 0 | P21: =IFERROR(VLOOKUP($C21+P$6,$C$11:$AK$38,4,FALSE)/$H21,0) -> 0 | Q21: =IFERROR(VLOOKUP($C21+Q$6,$C$11:$AK$38,4,FALSE)/$H21,0) -> 0 | R21: =IFERROR(VLOOKUP($C21+R$6,$C$11:$AK$38,4,FALSE)/$H21,0) -> 0 | ... AK21: =IFERROR(VLOOKUP($C21+AK$6,$C$11:$AK$38,4,FALSE)/$H21,0) -> 0
B22: =IBNR!F18 -> 2020Q4 | C22: =C23+3 -> 51 | D22: =_xlfn.XLOOKUP($B$8,Paid_DFs!$G$5:$S$5,Paid_DFs!$G18:$S18) -> 1 | E22: =PRODUCT($D$11:$D22) -> 1 | F22: =G22-G23 -> 0 | G22: =1/E22 -> 1 | H22: =1-G22 -> 0 | I22: =SUM(J22:AK22) -> 1 | J22: =IF($H22=0%,100%,IFERROR(VLOOKUP($C22+J$6,$C$11:$AK$38,4,FALSE)/$H22,0)) -> 1 | K22: =IFERROR(VLOOKUP($C22+K$6,$C$11:$AK$38,4,FALSE)/$H22,0) -> 0 | L22: =IFERROR(VLOOKUP($C22+L$6,$C$11:$AK$38,4,FALSE)/$H22,0) -> 0 | M22: =IFERROR(VLOOKUP($C22+M$6,$C$11:$AK$38,4,FALSE)/$H22,0) -> 0 | N22: =IFERROR(VLOOKUP($C22+N$6,$C$11:$AK$38,4,FALSE)/$H22,0) -> 0 | O22: =IFERROR(VLOOKUP($C22+O$6,$C$11:$AK$38,4,FALSE)/$H22,0) -> 0 | P22: =IFERROR(VLOOKUP($C22+P$6,$C$11:$AK$38,4,FALSE)/$H22,0) -> 0 | Q22: =IFERROR(VLOOKUP($C22+Q$6,$C$11:$AK$38,4,FALSE)/$H22,0) -> 0 | R22: =IFERROR(VLOOKUP($C22+R$6,$C$11:$AK$38,4,FALSE)/$H22,0) -> 0 | ... AK22: =IFERROR(VLOOKUP($C22+AK$6,$C$11:$AK$38,4,FALSE)/$H22,0) -> 0
... B30: =IBNR!F26 -> 2022Q4 | C30: =C31+3 -> 27 | D30: =_xlfn.XLOOKUP($B$8,Paid_DFs!$G$5:$S$5,Paid_DFs!$G26:$S26) -> 1 | E30: =PRODUCT($D$11:$D30) -> 1 | F30: =G30-G31 -> 0 | G30: =1/E30 -> 1 | H30: =1-G30 -> 0 | I30: =SUM(J30:AK30) -> 1 | J30: =IF($H30=0%,100%,IFERROR(VLOOKUP($C30+J$6,$C$11:$AK$38,4,FALSE)/$H30,0)) -> 1 | K30: =IFERROR(VLOOKUP($C30+K$6,$C$11:$AK$38,4,FALSE)/$H30,0) -> 0 | L30: =IFERROR(VLOOKUP($C30+L$6,$C$11:$AK$38,4,FALSE)/$H30,0) -> 0 | M30: =IFERROR(VLOOKUP($C30+M$6,$C$11:$AK$38,4,FALSE)/$H30,0) -> 0 | N30: =IFERROR(VLOOKUP($C30+N$6,$C$11:$AK$38,4,FALSE)/$H30,0) -> 0 | O30: =IFERROR(VLOOKUP($C30+O$6,$C$11:$AK$38,4,FALSE)/$H30,0) -> 0 | P30: =IFERROR(VLOOKUP($C30+P$6,$C$11:$AK$38,4,FALSE)/$H30,0) -> 0 | Q30: =IFERROR(VLOOKUP($C30+Q$6,$C$11:$AK$38,4,FALSE)/$H30,0) -> 0 | R30: =IFERROR(VLOOKUP($C30+R$6,$C$11:$AK$38,4,FALSE)/$H30,0) -> 0 | ... AK30: =IFERROR(VLOOKUP($C30+AK$6,$C$11:$AK$38,4,FALSE)/$H30,0) -> 0
B31: 2023Q1 | C31: =C32+3 -> 24 | D31: =_xlfn.XLOOKUP($B$8,Paid_DFs!$G$5:$S$5,Paid_DFs!$G27:$S27) -> 1 | E31: =PRODUCT($D$11:$D31) -> 1 | F31: =G31-G32 -> 0 | G31: =1/E31 -> 1 | H31: =1-G31 -> 0 | I31: =SUM(J31:AK31) -> 1 | J31: =IF($H31=0%,100%,IFERROR(VLOOKUP($C31+J$6,$C$11:$AK$38,4,FALSE)/$H31,0)) -> 1 | K31: =IFERROR(VLOOKUP($C31+K$6,$C$11:$AK$38,4,FALSE)/$H31,0) -> 0 | L31: =IFERROR(VLOOKUP($C31+L$6,$C$11:$AK$38,4,FALSE)/$H31,0) -> 0 | M31: =IFERROR(VLOOKUP($C31+M$6,$C$11:$AK$38,4,FALSE)/$H31,0) -> 0 | N31: =IFERROR(VLOOKUP($C31+N$6,$C$11:$AK$38,4,FALSE)/$H31,0) -> 0 | O31: =IFERROR(VLOOKUP($C31+O$6,$C$11:$AK$38,4,FALSE)/$H31,0) -> 0 | P31: =IFERROR(VLOOKUP($C31+P$6,$C$11:$AK$38,4,FALSE)/$H31,0) -> 0 | Q31: =IFERROR(VLOOKUP($C31+Q$6,$C$11:$AK$38,4,FALSE)/$H31,0) -> 0 | R31: =IFERROR(VLOOKUP($C31+R$6,$C$11:$AK$38,4,FALSE)/$H31,0) -> 0 | ... AK31: =IFERROR(VLOOKUP($C31+AK$6,$C$11:$AK$38,4,FALSE)/$H31,0) -> 0
B32: 2023Q2 | C32: =C33+3 -> 21 | D32: =_xlfn.XLOOKUP($B$8,Paid_DFs!$G$5:$S$5,Paid_DFs!$G28:$S28) -> 1 | E32: =PRODUCT($D$11:$D32) -> 1 | F32: =G32-G33 -> 0 | G32: =1/E32 -> 1 | H32: =1-G32 -> 0 | I32: =SUM(J32:AK32) -> 1 | J32: =IF($H32=0%,100%,IFERROR(VLOOKUP($C32+J$6,$C$11:$AK$38,4,FALSE)/$H32,0)) -> 1 | K32: =IFERROR(VLOOKUP($C32+K$6,$C$11:$AK$38,4,FALSE)/$H32,0) -> 0 | L32: =IFERROR(VLOOKUP($C32+L$6,$C$11:$AK$38,4,FALSE)/$H32,0) -> 0 | M32: =IFERROR(VLOOKUP($C32+M$6,$C$11:$AK$38,4,FALSE)/$H32,0) -> 0 | N32: =IFERROR(VLOOKUP($C32+N$6,$C$11:$AK$38,4,FALSE)/$H32,0) -> 0 | O32: =IFERROR(VLOOKUP($C32+O$6,$C$11:$AK$38,4,FALSE)/$H32,0) -> 0 | P32: =IFERROR(VLOOKUP($C32+P$6,$C$11:$AK$38,4,FALSE)/$H32,0) -> 0 | Q32: =IFERROR(VLOOKUP($C32+Q$6,$C$11:$AK$38,4,FALSE)/$H32,0) -> 0 | R32: =IFERROR(VLOOKUP($C32+R$6,$C$11:$AK$38,4,FALSE)/$H32,0) -> 0 | ... AK32: =IFERROR(VLOOKUP($C32+AK$6,$C$11:$AK$38,4,FALSE)/$H32,0) -> 0
B33: 2023Q3 | C33: =C34+3 -> 18 | D33: =_xlfn.XLOOKUP($B$8,Paid_DFs!$G$5:$S$5,Paid_DFs!$G29:$S29) -> 1 | E33: =PRODUCT($D$11:$D33) -> 1 | F33: =G33-G34 -> 0 | G33: =1/E33 -> 1 | H33: =1-G33 -> 0 | I33: =SUM(J33:AK33) -> 1 | J33: =IF($H33=0%,100%,IFERROR(VLOOKUP($C33+J$6,$C$11:$AK$38,4,FALSE)/$H33,0)) -> 1 | K33: =IFERROR(VLOOKUP($C33+K$6,$C$11:$AK$38,4,FALSE)/$H33,0) -> 0 | L33: =IFERROR(VLOOKUP($C33+L$6,$C$11:$AK$38,4,FALSE)/$H33,0) -> 0 | M33: =IFERROR(VLOOKUP($C33+M$6,$C$11:$AK$38,4,FALSE)/$H33,0) -> 0 | N33: =IFERROR(VLOOKUP($C33+N$6,$C$11:$AK$38,4,FALSE)/$H33,0) -> 0 | O33: =IFERROR(VLOOKUP($C33+O$6,$C$11:$AK$38,4,FALSE)/$H33,0) -> 0 | P33: =IFERROR(VLOOKUP($C33+P$6,$C$11:$AK$38,4,FALSE)/$H33,0) -> 0 | Q33: =IFERROR(VLOOKUP($C33+Q$6,$C$11:$AK$38,4,FALSE)/$H33,0) -> 0 | R33: =IFERROR(VLOOKUP($C33+R$6,$C$11:$AK$38,4,FALSE)/$H33,0) -> 0 | ... AK33: =IFERROR(VLOOKUP($C33+AK$6,$C$11:$AK$38,4,FALSE)/$H33,0) -> 0
B34: 2023Q4 | C34: =C35+3 -> 15 | D34: =_xlfn.XLOOKUP($B$8,Paid_DFs!$G$5:$S$5,Paid_DFs!$G30:$S30) -> 1 | E34: =PRODUCT($D$11:$D34) -> 1 | F34: =G34-G35 -> 0 | G34: =1/E34 -> 1 | H34: =1-G34 -> 0 | I34: =SUM(J34:AK34) -> 1 | J34: =IF($H34=0%,100%,IFERROR(VLOOKUP($C34+J$6,$C$11:$AK$38,4,FALSE)/$H34,0)) -> 1 | K34: =IFERROR(VLOOKUP($C34+K$6,$C$11:$AK$38,4,FALSE)/$H34,0) -> 0 | L34: =IFERROR(VLOOKUP($C34+L$6,$C$11:$AK$38,4,FALSE)/$H34,0) -> 0 | M34: =IFERROR(VLOOKUP($C34+M$6,$C$11:$AK$38,4,FALSE)/$H34,0) -> 0 | N34: =IFERROR(VLOOKUP($C34+N$6,$C$11:$AK$38,4,FALSE)/$H34,0) -> 0 | O34: =IFERROR(VLOOKUP($C34+O$6,$C$11:$AK$38,4,FALSE)/$H34,0) -> 0 | P34: =IFERROR(VLOOKUP($C34+P$6,$C$11:$AK$38,4,FALSE)/$H34,0) -> 0 | Q34: =IFERROR(VLOOKUP($C34+Q$6,$C$11:$AK$38,4,FALSE)/$H34,0) -> 0 | R34: =IFERROR(VLOOKUP($C34+R$6,$C$11:$AK$38,4,FALSE)/$H34,0) -> 0 | ... AK34: =IFERROR(VLOOKUP($C34+AK$6,$C$11:$AK$38,4,FALSE)/$H34,0) -> 0
B35: 2024Q1 | C35: =C36+3 -> 12 | D35: =_xlfn.XLOOKUP($B$8,Paid_DFs!$G$5:$S$5,Paid_DFs!$G31:$S31) -> 1 | E35: =PRODUCT($D$11:$D35) -> 1 | F35: =G35-G36 -> 0.059117405 | G35: =1/E35 -> 1 | H35: =1-G35 -> 0 | I35: =SUM(J35:AK35) -> 1 | J35: =IF($H35=0%,100%,IFERROR(VLOOKUP($C35+J$6,$C$11:$AK$38,4,FALSE)/$H35,0)) -> 1 | K35: =IFERROR(VLOOKUP($C35+K$6,$C$11:$AK$38,4,FALSE)/$H35,0) -> 0 | L35: =IFERROR(VLOOKUP($C35+L$6,$C$11:$AK$38,4,FALSE)/$H35,0) -> 0 | M35: =IFERROR(VLOOKUP($C35+M$6,$C$11:$AK$38,4,FALSE)/$H35,0) -> 0 | N35: =IFERROR(VLOOKUP($C35+N$6,$C$11:$AK$38,4,FALSE)/$H35,0) -> 0 | O35: =IFERROR(VLOOKUP($C35+O$6,$C$11:$AK$38,4,FALSE)/$H35,0) -> 0 | P35: =IFERROR(VLOOKUP($C35+P$6,$C$11:$AK$38,4,FALSE)/$H35,0) -> 0 | Q35: =IFERROR(VLOOKUP($C35+Q$6,$C$11:$AK$38,4,FALSE)/$H35,0) -> 0 | R35: =IFERROR(VLOOKUP($C35+R$6,$C$11:$AK$38,4,FALSE)/$H35,0) -> 0 | ... AK35: =IFERROR(VLOOKUP($C35+AK$6,$C$11:$AK$38,4,FALSE)/$H35,0) -> 0
B36: 2024Q2 | C36: =C37+3 -> 9 | D36: =_xlfn.XLOOKUP($B$8,Paid_DFs!$G$5:$S$5,Paid_DFs!$G32:$S32) -> 1.0628319 | E36: =PRODUCT($D$11:$D36) -> 1.0628319 | F36: =G36-G37 -> 0.2125996 | G36: =1/E36 -> 0.94088259 | H36: =1-G36 -> 0.059117405 | I36: =SUM(J36:AK36) -> 1 | J36: =IF($H36=0%,100%,IFERROR(VLOOKUP($C36+J$6,$C$11:$AK$38,4,FALSE)/$H36,0)) -> 1 | K36: =IFERROR(VLOOKUP($C36+K$6,$C$11:$AK$38,4,FALSE)/$H36,0) -> 0 | L36: =IFERROR(VLOOKUP($C36+L$6,$C$11:$AK$38,4,FALSE)/$H36,0) -> 0 | M36: =IFERROR(VLOOKUP($C36+M$6,$C$11:$AK$38,4,FALSE)/$H36,0) -> 0 | N36: =IFERROR(VLOOKUP($C36+N$6,$C$11:$AK$38,4,FALSE)/$H36,0) -> 0 | O36: =IFERROR(VLOOKUP($C36+O$6,$C$11:$AK$38,4,FALSE)/$H36,0) -> 0 | P36: =IFERROR(VLOOKUP($C36+P$6,$C$11:$AK$38,4,FALSE)/$H36,0) -> 0 | Q36: =IFERROR(VLOOKUP($C36+Q$6,$C$11:$AK$38,4,FALSE)/$H36,0) -> 0 | R36: =IFERROR(VLOOKUP($C36+R$6,$C$11:$AK$38,4,FALSE)/$H36,0) -> 0 | ... AK36: =IFERROR(VLOOKUP($C36+AK$6,$C$11:$AK$38,4,FALSE)/$H36,0) -> 0
B37: 2024Q3 | C37: =C38+3 -> 6 | D37: =_xlfn.XLOOKUP($B$8,Paid_DFs!$G$5:$S$5,Paid_DFs!$G33:$S33) -> 1.2919189 | E37: =PRODUCT($D$11:$D37) -> 1.3730926 | F37: =G37-G38 -> 0.12737757 | G37: =1/E37 -> 0.72828299 | H37: =1-G37 -> 0.27171701 | I37: =SUM(J37:AK37) -> 1 | J37: =IF($H37=0%,100%,IFERROR(VLOOKUP($C37+J$6,$C$11:$AK$38,4,FALSE)/$H37,0)) -> 0.78243024 | K37: =IFERROR(VLOOKUP($C37+K$6,$C$11:$AK$38,4,FALSE)/$H37,0) -> 0.21756976 | L37: =IFERROR(VLOOKUP($C37+L$6,$C$11:$AK$38,4,FALSE)/$H37,0) -> 0 | M37: =IFERROR(VLOOKUP($C37+M$6,$C$11:$AK$38,4,FALSE)/$H37,0) -> 0 | N37: =IFERROR(VLOOKUP($C37+N$6,$C$11:$AK$38,4,FALSE)/$H37,0) -> 0 | O37: =IFERROR(VLOOKUP($C37+O$6,$C$11:$AK$38,4,FALSE)/$H37,0) -> 0 | P37: =IFERROR(VLOOKUP($C37+P$6,$C$11:$AK$38,4,FALSE)/$H37,0) -> 0 | Q37: =IFERROR(VLOOKUP($C37+Q$6,$C$11:$AK$38,4,FALSE)/$H37,0) -> 0 | R37: =IFERROR(VLOOKUP($C37+R$6,$C$11:$AK$38,4,FALSE)/$H37,0) -> 0 | ... AK37: =IFERROR(VLOOKUP($C37+AK$6,$C$11:$AK$38,4,FALSE)/$H37,0) -> 0
B38: 2024Q4 | C38: =C39+3 -> 3 | D38: =_xlfn.XLOOKUP($B$8,Paid_DFs!$G$5:$S$5,Paid_DFs!$G34:$S34) -> 1.2119761 | E38: =PRODUCT($D$11:$D38) -> 1.6641554 | F38: =G38-G39 -> 0.60090542 | G38: =1/E38 -> 0.60090542 | H38: =1-G38 -> 0.39909458 | I38: =SUM(J38:AK38) -> 1 | J38: =IF($H38=0%,100%,IFERROR(VLOOKUP($C38+J$6,$C$11:$AK$38,4,FALSE)/$H38,0)) -> 0.31916637 | K38: =IFERROR(VLOOKUP($C38+K$6,$C$11:$AK$38,4,FALSE)/$H38,0) -> 0.53270481 | L38: =IFERROR(VLOOKUP($C38+L$6,$C$11:$AK$38,4,FALSE)/$H38,0) -> 0.14812881 | M38: =IFERROR(VLOOKUP($C38+M$6,$C$11:$AK$38,4,FALSE)/$H38,0) -> 0 | N38: =IFERROR(VLOOKUP($C38+N$6,$C$11:$AK$38,4,FALSE)/$H38,0) -> 0 | O38: =IFERROR(VLOOKUP($C38+O$6,$C$11:$AK$38,4,FALSE)/$H38,0) -> 0 | P38: =IFERROR(VLOOKUP($C38+P$6,$C$11:$AK$38,4,FALSE)/$H38,0) -> 0 | Q38: =IFERROR(VLOOKUP($C38+Q$6,$C$11:$AK$38,4,FALSE)/$H38,0) -> 0 | R38: =IFERROR(VLOOKUP($C38+R$6,$C$11:$AK$38,4,FALSE)/$H38,0) -> 0 | ... AK38: =IFERROR(VLOOKUP($C38+AK$6,$C$11:$AK$38,4,FALSE)/$H38,0) -> 0
B39: Total | H39: =SUM(H11:H38) -> 0.72992899 | J39: =SUM(J11:J38) -> 27.101597 | K39: =SUM(K11:K38) -> 0.75027458 | L39: =SUM(L11:L38) -> 0.14812881 | M39: =SUM(M11:M38) -> 0 | N39: =SUM(N11:N38) -> 0 | O39: =SUM(O11:O38) -> 0 | P39: =SUM(P11:P38) -> 0 | Q39: =SUM(Q11:Q38) -> 0 | ... AK39: =SUM(AK11:AK38) -> 0
I41: =1-I38 -> 0 | K41: =F33/H38 -> 0
H42: =H39-H40 -> 0.72992899 | I42: =1-I38 -> 0
I43: 0.017272934
B45: =B8 -> Miscellaneous
J46: Time (in years)
E47: Origin | F47: OCR | G47: IBNR | H47: Claims Provision | I47: Check | J47: =J10 -> 0.12 | K47: =K10 -> 0.38 | L47: =L10 -> 0.62 | M47: =M10 -> 0.88 | N47: =N10 -> 1.12 | O47: =O10 -> 1.38 | P47: =P10 -> 1.62 | Q47: =Q10 -> 1.88 | ... AD47: =AD10 -> 5.12 | AE47: 5.38 | AF47: 5.62 | AG47: 5.88 | AH47: 6.12 | AI47: 6.38 | AJ47: 6.62 | AK47: 6.88
E48: =B11 -> 2018Q1 | F48: =_xlfn.XLOOKUP($B$8,OCR!$D$2:$P$2,OCR!$D4:$P4) -> 78925 | G48: =_xlfn.XLOOKUP($B$8,IBNR!$G$5:$S$5,IBNR!$G7:$S7) -> 0 | H48: =SUM(F48:G48) -> 78925 | I48: =SUM(J48:AK48) -> 78925 | J48: =$H48*J11 -> 78925 | K48: =$H48*K11 -> 0 | L48: =$H48*L11 -> 0 | M48: =$H48*M11 -> 0 | N48: =$H48*N11 -> 0 | O48: =$H48*O11 -> 0 | P48: =$H48*P11 -> 0 | Q48: =$H48*Q11 -> 0 | ... AK48: =$H48*AK11 -> 0
E49: =B12 -> 2018Q2 | F49: =_xlfn.XLOOKUP($B$8,OCR!$D$2:$P$2,OCR!$D5:$P5) -> 0 | G49: =_xlfn.XLOOKUP($B$8,IBNR!$G$5:$S$5,IBNR!$G8:$S8) -> 0 | H49: =SUM(F49:G49) -> 0 | I49: =SUM(J49:AK49) -> 0 | J49: =$H49*J12 -> 0 | K49: =$H49*K12 -> 0 | L49: =$H49*L12 -> 0 | M49: =$H49*M12 -> 0 | N49: =$H49*N12 -> 0 | O49: =$H49*O12 -> 0 | P49: =$H49*P12 -> 0 | Q49: =$H49*Q12 -> 0 | ... AK49: =$H49*AK12 -> 0
E50: =B13 -> 2018Q3 | F50: =_xlfn.XLOOKUP($B$8,OCR!$D$2:$P$2,OCR!$D6:$P6) -> 0 | G50: =_xlfn.XLOOKUP($B$8,IBNR!$G$5:$S$5,IBNR!$G9:$S9) -> 0 | H50: =SUM(F50:G50) -> 0 | I50: =SUM(J50:AK50) -> 0 | J50: =$H50*J13 -> 0 | K50: =$H50*K13 -> 0 | L50: =$H50*L13 -> 0 | M50: =$H50*M13 -> 0 | N50: =$H50*N13 -> 0 | O50: =$H50*O13 -> 0 | P50: =$H50*P13 -> 0 | Q50: =$H50*Q13 -> 0 | ... AK50: =$H50*AK13 -> 0
E51: =B14 -> 2018Q4 | F51: =_xlfn.XLOOKUP($B$8,OCR!$D$2:$P$2,OCR!$D7:$P7) -> 0 | G51: =_xlfn.XLOOKUP($B$8,IBNR!$G$5:$S$5,IBNR!$G10:$S10) -> 0 | H51: =SUM(F51:G51) -> 0 | I51: =SUM(J51:AK51) -> 0 | J51: =$H51*J14 -> 0 | K51: =$H51*K14 -> 0 | L51: =$H51*L14 -> 0 | M51: =$H51*M14 -> 0 | N51: =$H51*N14 -> 0 | O51: =$H51*O14 -> 0 | P51: =$H51*P14 -> 0 | Q51: =$H51*Q14 -> 0 | ... AK51: =$H51*AK14 -> 0
E52: =B15 -> 2019Q1 | F52: =_xlfn.XLOOKUP($B$8,OCR!$D$2:$P$2,OCR!$D8:$P8) -> 0 | G52: =_xlfn.XLOOKUP($B$8,IBNR!$G$5:$S$5,IBNR!$G11:$S11) -> 0 | H52: =SUM(F52:G52) -> 0 | I52: =SUM(J52:AK52) -> 0 | J52: =$H52*J15 -> 0 | K52: =$H52*K15 -> 0 | L52: =$H52*L15 -> 0 | M52: =$H52*M15 -> 0 | N52: =$H52*N15 -> 0 | O52: =$H52*O15 -> 0 | P52: =$H52*P15 -> 0 | Q52: =$H52*Q15 -> 0 | ... AK52: =$H52*AK15 -> 0
E53: =B16 -> 2019Q2 | F53: =_xlfn.XLOOKUP($B$8,OCR!$D$2:$P$2,OCR!$D9:$P9) -> 0 | G53: =_xlfn.XLOOKUP($B$8,IBNR!$G$5:$S$5,IBNR!$G12:$S12) -> 0 | H53: =SUM(F53:G53) -> 0 | I53: =SUM(J53:AK53) -> 0 | J53: =$H53*J16 -> 0 | K53: =$H53*K16 -> 0 | L53: =$H53*L16 -> 0 | M53: =$H53*M16 -> 0 | N53: =$H53*N16 -> 0 | O53: =$H53*O16 -> 0 | P53: =$H53*P16 -> 0 | Q53: =$H53*Q16 -> 0 | ... AK53: =$H53*AK16 -> 0
E54: =B17 -> 2019Q3 | F54: =_xlfn.XLOOKUP($B$8,OCR!$D$2:$P$2,OCR!$D10:$P10) -> 0 | G54: =_xlfn.XLOOKUP($B$8,IBNR!$G$5:$S$5,IBNR!$G13:$S13) -> 0 | H54: =SUM(F54:G54) -> 0 | I54: =SUM(J54:AK54) -> 0 | J54: =$H54*J17 -> 0 | K54: =$H54*K17 -> 0 | L54: =$H54*L17 -> 0 | M54: =$H54*M17 -> 0 | N54: =$H54*N17 -> 0 | O54: =$H54*O17 -> 0 | P54: =$H54*P17 -> 0 | Q54: =$H54*Q17 -> 0 | ... AK54: =$H54*AK17 -> 0
E55: =B18 -> 2019Q4 | F55: =_xlfn.XLOOKUP($B$8,OCR!$D$2:$P$2,OCR!$D11:$P11) -> 0 | G55: =_xlfn.XLOOKUP($B$8,IBNR!$G$5:$S$5,IBNR!$G14:$S14) -> 0 | H55: =SUM(F55:G55) -> 0 | I55: =SUM(J55:AK55) -> 0 | J55: =$H55*J18 -> 0 | K55: =$H55*K18 -> 0 | L55: =$H55*L18 -> 0 | M55: =$H55*M18 -> 0 | N55: =$H55*N18 -> 0 | O55: =$H55*O18 -> 0 | P55: =$H55*P18 -> 0 | Q55: =$H55*Q18 -> 0 | ... AK55: =$H55*AK18 -> 0
E56: =B19 -> 2020Q1 | F56: =_xlfn.XLOOKUP($B$8,OCR!$D$2:$P$2,OCR!$D12:$P12) -> 0 | G56: =_xlfn.XLOOKUP($B$8,IBNR!$G$5:$S$5,IBNR!$G15:$S15) -> 0 | H56: =SUM(F56:G56) -> 0 | I56: =SUM(J56:AK56) -> 0 | J56: =$H56*J19 -> 0 | K56: =$H56*K19 -> 0 | L56: =$H56*L19 -> 0 | M56: =$H56*M19 -> 0 | N56: =$H56*N19 -> 0 | O56: =$H56*O19 -> 0 | P56: =$H56*P19 -> 0 | Q56: =$H56*Q19 -> 0 | ... AK56: =$H56*AK19 -> 0
E57: =B20 -> 2020Q2 | F57: =_xlfn.XLOOKUP($B$8,OCR!$D$2:$P$2,OCR!$D13:$P13) -> 0 | G57: =_xlfn.XLOOKUP($B$8,IBNR!$G$5:$S$5,IBNR!$G16:$S16) -> 0 | H57: =SUM(F57:G57) -> 0 | I57: =SUM(J57:AK57) -> 0 | J57: =$H57*J20 -> 0 | K57: =$H57*K20 -> 0 | L57: =$H57*L20 -> 0 | M57: =$H57*M20 -> 0 | N57: =$H57*N20 -> 0 | O57: =$H57*O20 -> 0 | P57: =$H57*P20 -> 0 | Q57: =$H57*Q20 -> 0 | ... AK57: =$H57*AK20 -> 0
E58: =B21 -> 2020Q3 | F58: =_xlfn.XLOOKUP($B$8,OCR!$D$2:$P$2,OCR!$D14:$P14) -> 1100000 | G58: =_xlfn.XLOOKUP($B$8,IBNR!$G$5:$S$5,IBNR!$G17:$S17) -> 0 | H58: =SUM(F58:G58) -> 1100000 | I58: =SUM(J58:AK58) -> 1100000 | J58: =$H58*J21 -> 1100000 | K58: =$H58*K21 -> 0 | L58: =$H58*L21 -> 0 | M58: =$H58*M21 -> 0 | N58: =$H58*N21 -> 0 | O58: =$H58*O21 -> 0 | P58: =$H58*P21 -> 0 | Q58: =$H58*Q21 -> 0 | ... AK58: =$H58*AK21 -> 0
E59: =B22 -> 2020Q4 | F59: =_xlfn.XLOOKUP($B$8,OCR!$D$2:$P$2,OCR!$D15:$P15) -> 0 | G59: =_xlfn.XLOOKUP($B$8,IBNR!$G$5:$S$5,IBNR!$G18:$S18) -> 0 | H59: =SUM(F59:G59) -> 0 | I59: =SUM(J59:AK59) -> 0 | J59: =$H59*J22 -> 0 | K59: =$H59*K22 -> 0 | L59: =$H59*L22 -> 0 | M59: =$H59*M22 -> 0 | N59: =$H59*N22 -> 0 | O59: =$H59*O22 -> 0 | P59: =$H59*P22 -> 0 | Q59: =$H59*Q22 -> 0 | ... AK59: =$H59*AK22 -> 0
... E67: =B30 -> 2022Q4 | F67: =_xlfn.XLOOKUP($B$8,OCR!$D$2:$P$2,OCR!$D23:$P23) -> 0 | G67: =_xlfn.XLOOKUP($B$8,IBNR!$G$5:$S$5,IBNR!$G26:$S26) -> 1082553.8 | H67: =SUM(F67:G67) -> 1082553.8 | I67: =SUM(J67:AK67) -> 1082553.8 | J67: =$H67*J30 -> 1082553.8 | K67: =$H67*K30 -> 0 | L67: =$H67*L30 -> 0 | M67: =$H67*M30 -> 0 | N67: =$H67*N30 -> 0 | O67: =$H67*O30 -> 0 | P67: =$H67*P30 -> 0 | Q67: =$H67*Q30 -> 0 | ... AK67: =$H67*AK30 -> 0
E68: 2023Q1 | F68: =_xlfn.XLOOKUP($B$8,OCR!$D$2:$P$2,OCR!$D24:$P24) -> 0 | G68: =_xlfn.XLOOKUP($B$8,IBNR!$G$5:$S$5,IBNR!$G27:$S27) -> 962488.77 | H68: =SUM(F68:G68) -> 962488.77 | I68: =SUM(J68:AK68) -> 962488.77 | J68: =$H68*J31 -> 962488.77 | K68: =$H68*K31 -> 0 | L68: =$H68*L31 -> 0 | M68: =$H68*M31 -> 0 | N68: =$H68*N31 -> 0 | O68: =$H68*O31 -> 0 | P68: =$H68*P31 -> 0 | Q68: =$H68*Q31 -> 0 | ... AK68: =$H68*AK31 -> 0
E69: 2023Q2 | F69: =_xlfn.XLOOKUP($B$8,OCR!$D$2:$P$2,OCR!$D25:$P25) -> 55000 | G69: =_xlfn.XLOOKUP($B$8,IBNR!$G$5:$S$5,IBNR!$G28:$S28) -> 962488.77 | H69: =SUM(F69:G69) -> 1017488.8 | I69: =SUM(J69:AK69) -> 1017488.8 | J69: =$H69*J32 -> 1017488.8 | K69: =$H69*K32 -> 0 | L69: =$H69*L32 -> 0 | M69: =$H69*M32 -> 0 | N69: =$H69*N32 -> 0 | O69: =$H69*O32 -> 0 | P69: =$H69*P32 -> 0 | Q69: =$H69*Q32 -> 0 | ... AK69: =$H69*AK32 -> 0
E70: 2023Q3 | F70: =_xlfn.XLOOKUP($B$8,OCR!$D$2:$P$2,OCR!$D26:$P26) -> 0 | G70: =_xlfn.XLOOKUP($B$8,IBNR!$G$5:$S$5,IBNR!$G29:$S29) -> 962488.77 | H70: =SUM(F70:G70) -> 962488.77 | I70: =SUM(J70:AK70) -> 962488.77 | J70: =$H70*J33 -> 962488.77 | K70: =$H70*K33 -> 0 | L70: =$H70*L33 -> 0 | M70: =$H70*M33 -> 0 | N70: =$H70*N33 -> 0 | O70: =$H70*O33 -> 0 | P70: =$H70*P33 -> 0 | Q70: =$H70*Q33 -> 0 | ... AK70: =$H70*AK33 -> 0
E71: 2023Q4 | F71: =_xlfn.XLOOKUP($B$8,OCR!$D$2:$P$2,OCR!$D27:$P27) -> 66000 | G71: =_xlfn.XLOOKUP($B$8,IBNR!$G$5:$S$5,IBNR!$G30:$S30) -> 962488.77 | H71: =SUM(F71:G71) -> 1028488.8 | I71: =SUM(J71:AK71) -> 1028488.8 | J71: =$H71*J34 -> 1028488.8 | K71: =$H71*K34 -> 0 | L71: =$H71*L34 -> 0 | M71: =$H71*M34 -> 0 | N71: =$H71*N34 -> 0 | O71: =$H71*O34 -> 0 | P71: =$H71*P34 -> 0 | Q71: =$H71*Q34 -> 0 | ... AK71: =$H71*AK34 -> 0
E72: 2024Q1 | F72: =_xlfn.XLOOKUP($B$8,OCR!$D$2:$P$2,OCR!$D28:$P28) -> 0 | G72: =_xlfn.XLOOKUP($B$8,IBNR!$G$5:$S$5,IBNR!$G31:$S31) -> 0 | H72: =SUM(F72:G72) -> 0 | I72: =SUM(J72:AK72) -> 0 | J72: =$H72*J35 -> 0 | K72: =$H72*K35 -> 0 | L72: =$H72*L35 -> 0 | M72: =$H72*M35 -> 0 | N72: =$H72*N35 -> 0 | O72: =$H72*O35 -> 0 | P72: =$H72*P35 -> 0 | Q72: =$H72*Q35 -> 0 | ... AK72: =$H72*AK35 -> 0
E73: 2024Q2 | F73: =_xlfn.XLOOKUP($B$8,OCR!$D$2:$P$2,OCR!$D29:$P29) -> 0 | G73: =_xlfn.XLOOKUP($B$8,IBNR!$G$5:$S$5,IBNR!$G32:$S32) -> 0 | H73: =SUM(F73:G73) -> 0 | I73: =SUM(J73:AK73) -> 0 | J73: =$H73*J36 -> 0 | K73: =$H73*K36 -> 0 | L73: =$H73*L36 -> 0 | M73: =$H73*M36 -> 0 | N73: =$H73*N36 -> 0 | O73: =$H73*O36 -> 0 | P73: =$H73*P36 -> 0 | Q73: =$H73*Q36 -> 0 | ... AK73: =$H73*AK36 -> 0
E74: 2024Q3 | F74: =_xlfn.XLOOKUP($B$8,OCR!$D$2:$P$2,OCR!$D30:$P30) -> 15569950 | G74: =_xlfn.XLOOKUP($B$8,IBNR!$G$5:$S$5,IBNR!$G33:$S33) -> 0 | H74: =SUM(F74:G74) -> 15569950 | I74: =SUM(J74:AK74) -> 15569950 | J74: =$H74*J37 -> 12182400 | K74: =$H74*K37 -> 3387550.3 | L74: =$H74*L37 -> 0 | M74: =$H74*M37 -> 0 | N74: =$H74*N37 -> 0 | O74: =$H74*O37 -> 0 | P74: =$H74*P37 -> 0 | Q74: =$H74*Q37 -> 0 | ... AK74: =$H74*AK37 -> 0
E75: 2024Q4 | F75: =_xlfn.XLOOKUP($B$8,OCR!$D$2:$P$2,OCR!$D31:$P31) -> 99000 | G75: =_xlfn.XLOOKUP($B$8,IBNR!$G$5:$S$5,IBNR!$G34:$S34) -> 0 | H75: =SUM(F75:G75) -> 99000 | I75: =SUM(J75:AK75) -> 99000 | J75: =$H75*J38 -> 31597.471 | K75: =$H75*K38 -> 52737.777 | L75: =$H75*L38 -> 14664.752 | M75: =$H75*M38 -> 0 | N75: =$H75*N38 -> 0 | O75: =$H75*O38 -> 0 | P75: =$H75*P38 -> 0 | Q75: =$H75*Q38 -> 0 | ... AK75: =$H75*AK38 -> 0
