Workbook
Name A_Million: Investments!$D$1
Name A_Thousand: Investments!$D$2
Name Val_Date: [1]INTRO!$E$23

Sheet Intro
C15: Pioneer General Insurance Limited
D17: Financial Condition Report — Working File
D21: Valuation Date | E21: 45291

Sheet Data
G1: From (Prem Analysis) Exposure Tab - Unique Policies Per Source File
B3: Pioneer General Insurance Limited Summary of Data Provided | G3: Pioneer General Insurance Limited Unique Policy Count
B4: Paid Claims Data | C4: Premium Data | D4: Outstanding Claims Data | H4: Underwriting Year
B5: Unique Policy Identifier | C5: Unique Policy Identifier | D5: Unique Policy Identifier | G5: Business Class | H5: 2017 | I5: 2018 | J5: =I5+1 -> 2019 | K5: =J5+1 -> 2020 | L5: 2021 | M5: =L5+1 -> 2022
B6: Class of Business | C6: Class of Business | D6: Class of Business | G6: Engineering | H6: 67 | I6: 202 | J6: 266 | K6: 247 | L6: 299 | M6: 324 | N6: =M6/J6-1 -> 0.21804511 | O6: =K6/J6-1 -> -0.071428571
B7: Inward/Outward Indicator | C7: Product Description | D7: Product Description | G7: Fire Domestic | H7: 141 | I7: 321 | J7: 364 | K7: 550 | L7: 431 | M7: 332 | N7: =M7/J7-1 -> -0.087912088 | O7: =K7/J7-1 -> 0.51098901
B8: Start Date of Cover Period | C8: Date of Loss | D8: Date of Accident | G8: Fire Industrial | H8: 220 | I8: 499 | J8: 572 | K8: 579 | L8: 594 | M8: 761 | N8: =M8/J8-1 -> 0.33041958 | O8: =K8/J8-1 -> 0.012237762
B9: End Date of Cover Period | C9: Date of Report | D9: Outstanding Claim Amount - Gross | G9: Liability | H9: 111 | I9: 377 | J9: 509 | K9: 503 | L9: 629 | M9: 693 | N9: =M9/J9-1 -> 0.36149312 | O9: =K9/J9-1 -> -0.011787819
B10: Gross written premium | C10: Date of Payment | D10: Outstanding Claim Amount - Reinsurance estimate | G10: Marine | H10: 556 | I10: 1148 | J10: 368 | K10: 260 | L10: 540 | M10: 335 | N10: =M10/J10-1 -> -0.089673913 | O10: =K10/J10-1 -> -0.29347826
B11: Reinsurance Premium Amount Paid | C11: Amount of Gross Claim Payment | G11: Miscellaneous | H11: 207 | I11: 368 | J11: 246 | K11: 201 | L11: 688 | M11: 311 | N11: =M11/J11-1 -> 0.26422764 | O11: =K11/J11-1 -> -0.18292683
B12: Commissions Paid | C12: Amount of Reinsurance Recovery | G12: Motor Commercial | H12: 511 | I12: 2422 | J12: 3281 | K12: 3478 | L12: 5462 | M12: 6454 | N12: =M12/J12-1 -> 0.96708321 | O12: =K12/J12-1 -> 0.06004267
G13: Motor Private | H13: 1702 | I13: 7323 | J13: 11676 | K13: 14306 | L13: 21996 | M13: 22849 | N13: =M13/J13-1 -> 0.95692018 | O13: =K13/J13-1 -> 0.22524837
B14: Other General Information | G14: Personal Accident | H14: 106 | I14: 555 | J14: 1246 | K14: 938 | L14: 949 | M14: 1047 | N14: =M14/J14-1 -> -0.15971108 | O14: =K14/J14-1 -> -0.24719101
B15: Organization Structure, including Board details | G15: Theft | H15: 78 | I15: 208 | J15: 435 | K15: 348 | L15: 534 | M15: 1107 | N15: =M15/J15-1 -> 1.5448276 | O15: =K15/J15-1 -> -0.2
B16: Risk Management strategy | G16: Workmen's Compensation | H16: 65 | I16: 223 | J16: 298 | K16: 313 | L16: 402 | M16: 420 | N16: =M16/J16-1 -> 0.40939597 | O16: =K16/J16-1 -> 0.05033557
B17: Reinsurance Strategy and Treaties (2022 & 2023) | G17: TOTAL | H17: =SUM(H6:H16) -> 3764 | I17: =SUM(I6:I16) -> 13646 | J17: =SUM(J6:J16) -> 19261 | K17: 21723 | L17: 32524 | M17: =SUM(M6:M16) -> 34633 | N17: =M17/J17-1 -> 0.7980894 | O17: =K17/J17-1 -> 0.12782306
B18: Underwriting Manual | I18: =I17/H17-1 -> 2.6253985 | J18: =J17/I17-1 -> 0.41147589 | K18: =K17/J17-1 -> 0.12782306 | L18: =L17/K17-1 -> 0.49721493 | M18: =M17/L17-1 -> 0.064844423
B19: Claims Manual

Sheet Data_Recon
B4: Pioneer General Insurance Limited | H4: Pioneer General Insurance Limited | N4: Pioneer General Insurance Limited | T4: Pioneer General Insurance Limited
B5: Premium Data Variation Checks as at 31 December 2023 | H5: Summary of Claims Valuation Data as at 31 December 2023 | N5: Premium Data Variation Checks as at 31 December 2022 | T5: Summary of Claims Valuation Data as at 31 December 2022
B6: Business Class | C6: Gross Written Premium | H6: Business Class | I6: Paid Claims | N6: Business Class | O6: Gross Written Premium | T6: Business Class | U6: Paid Claims
C7: Data | D7: Financials | E7: Variation | I7: Data | J7: Financials | K7: Variation | O7: Data | P7: Financials | Q7: Variation | U7: Data | V7: Financials | W7: Variation
B8: Engineering | C8: 32682894 | D8: =_xlfn.XLOOKUP(B8,RA!$C$8:$N$8,RA!$C$9:$N$9) -> 32682894 | E8: =IFERROR(C9/D8-1,0) -> -0.66998492 | H8: Engineering | I8: 1696807 | J8: =_xlfn.XLOOKUP(H8,RA!$C$8:$N$8,RA!$C$19:$N$19) -> 1418131 | K8: =I8/J8-1 -> 0.19650935 | N8: Engineering | O8: 40945277 | P8: =_xlfn.XLOOKUP(N8,RA!$C$8:$N$8,RA!$C$44:$N$44) -> 40945277 | Q8: =IFERROR(O8/P8-1,0) -> 0 | T8: Engineering | U8: 3670143 | V8: =_xlfn.XLOOKUP(T8,RA!$C$8:$N$8,RA!$C$54:$N$54) -> 3851902 | W8: =U8/V8-1 -> -0.047186818
B9: Fire Domestic | C9: 10785848 | D9: =_xlfn.XLOOKUP(B9,RA!$C$8:$N$8,RA!$C$9:$N$9) -> 10785848 | E9: =IFERROR(C10/D9-1,0) -> 6.0699136 | H9: Fire Domestic | I9: 1111024 | J9: =_xlfn.XLOOKUP(H9,RA!$C$8:$N$8,RA!$C$19:$N$19) -> 1842476 | K9: =I9/J9-1 -> -0.39699404 | N9: Fire Domestic | O9: 8873879 | P9: =_xlfn.XLOOKUP(N9,RA!$C$8:$N$8,RA!$C$44:$N$44) -> 8873879 | Q9: =IFERROR(O9/P9-1,0) -> 0 | T9: Fire Domestic | U9: 436821 | V9: =_xlfn.XLOOKUP(T9,RA!$C$8:$N$8,RA!$C$54:$N$54) -> 435021 | W9: =U9/V9-1 -> 0.0041377313
B10: Fire Industrial | C10: 76255014 | D10: =_xlfn.XLOOKUP(B10,RA!$C$8:$N$8,RA!$C$9:$N$9) -> 76255014 | E10: =IFERROR(C11/D10-1,0) -> -0.47670735 | H10: Fire Industrial | I10: 13983797 | J10: =_xlfn.XLOOKUP(H10,RA!$C$8:$N$8,RA!$C$19:$N$19) -> 32243776 | K10: =I10/J10-1 -> -0.56631019 | N10: Fire Industrial | O10: 78279579 | P10: =_xlfn.XLOOKUP(N10,RA!$C$8:$N$8,RA!$C$44:$N$44) -> 78279579 | Q10: =IFERROR(O10/P10-1,0) -> 0 | T10: Fire Industrial | U10: 2535775 | V10: =_xlfn.XLOOKUP(T10,RA!$C$8:$N$8,RA!$C$54:$N$54) -> 2535775 | W10: =U10/V10-1 -> 0
B11: Liability | C11: 39903688 | D11: =_xlfn.XLOOKUP(B11,RA!$C$8:$N$8,RA!$C$9:$N$9) -> 39903688 | E11: =IFERROR(C12/D11-1,0) -> -0.6984694 | H11: Liability | I11: 7875581 | J11: =_xlfn.XLOOKUP(H11,RA!$C$8:$N$8,RA!$C$19:$N$19) -> 4746034 | K11: =I11/J11-1 -> 0.65940257 | N11: Liability | O11: 34436388 | P11: =_xlfn.XLOOKUP(N11,RA!$C$8:$N$8,RA!$C$44:$N$44) -> 34436388 | Q11: =IFERROR(O11/P11-1,0) -> 0 | T11: Liability | U11: 3684013 | V11: =_xlfn.XLOOKUP(T11,RA!$C$8:$N$8,RA!$C$54:$N$54) -> 3684013 | W11: =U11/V11-1 -> 0
B12: Marine | C12: 12032183 | D12: =_xlfn.XLOOKUP(B12,RA!$C$8:$N$8,RA!$C$9:$N$9) -> 12032183 | E12: =IFERROR(C13/D12-1,0) -> -0.54699384 | H12: Marine | I12: 0 | J12: =_xlfn.XLOOKUP(H12,RA!$C$8:$N$8,RA!$C$19:$N$19) -> 3277913 | K12: =I12/J12-1 -> -1 | N12: Marine | O12: 12488935 | P12: =_xlfn.XLOOKUP(N12,RA!$C$8:$N$8,RA!$C$44:$N$44) -> 12488935 | Q12: =IFERROR(O12/P12-1,0) -> 0 | T12: Marine | U12: 3262515 | V12: =_xlfn.XLOOKUP(T12,RA!$C$8:$N$8,RA!$C$54:$N$54) -> 3262515 | W12: =U12/V12-1 -> 0
B13: Miscellaneous | C13: 5450653 | D13: =_xlfn.XLOOKUP(B13,RA!$C$8:$N$8,RA!$C$9:$N$9) -> 5450653 | E13: =IFERROR(C14/D13-1,0) -> 67.086712 | H13: Miscellaneous | I13: 1465774 | J13: =_xlfn.XLOOKUP(H13,RA!$C$8:$N$8,RA!$C$19:$N$19) -> 30087 | K13: =I13/J13-1 -> 47.717852 | N13: Miscellaneous | O13: 19171387 | P13: =_xlfn.XLOOKUP(N13,RA!$C$8:$N$8,RA!$C$44:$N$44) -> 19171387 | Q13: =IFERROR(O13/P13-1,0) -> 0 | T13: Miscellaneous | U13: 711302 | V13: =_xlfn.XLOOKUP(T13,RA!$C$8:$N$8,RA!$C$54:$N$54) -> 299905 | W13: =U13/V13-1 -> 1.3717577
B14: Motor Commercial | C14: 371117040 | D14: =_xlfn.XLOOKUP(B14,RA!$C$8:$N$8,RA!$C$9:$N$9) -> 371117040 | E14: =IFERROR(C15/D14-1,0) -> 1.467254 | H14: Motor Commercial | I14: 221638337 | J14: =_xlfn.XLOOKUP(H14,RA!$C$8:$N$8,RA!$C$19:$N$19) -> 290849318 | K14: =I14/J14-1 -> -0.23796164 | N14: Motor Commercial | O14: 305362725 | P14: =_xlfn.XLOOKUP(N14,RA!$C$8:$N$8,RA!$C$44:$N$44) -> 305362726 | Q14: =IFERROR(O14/P14-1,0) -> -3.2747939e-09 | T14: Motor Commercial | U14: 170846151 | V14: =_xlfn.XLOOKUP(T14,RA!$C$8:$N$8,RA!$C$54:$N$54) -> 168089826 | W14: =U14/V14-1 -> 0.016397929
B15: Motor Private | C15: 915640011 | D15: =_xlfn.XLOOKUP(B15,RA!$C$8:$N$8,RA!$C$9:$N$9) -> 915640011 | E15: =IFERROR(C16/D15-1,0) -> -0.98977804 | H15: Motor Private | I15: 496327594 | J15: =_xlfn.XLOOKUP(H15,RA!$C$8:$N$8,RA!$C$19:$N$19) -> 611465508 | K15: =I15/J15-1 -> -0.1882983 | N15: Motor Private | O15: 818548381 | P15: =_xlfn.XLOOKUP(N15,RA!$C$8:$N$8,RA!$C$44:$N$44) -> 818548382 | Q15: =IFERROR(O15/P15-1,0) -> -1.2216749e-09 | T15: Motor Private | U15: 534598589 | V15: =_xlfn.XLOOKUP(T15,RA!$C$8:$N$8,RA!$C$54:$N$54) -> 527547701 | W15: =U15/V15-1 -> 0.013365404
B16: Personal Accident | C16: 9359638 | D16: =_xlfn.XLOOKUP(B16,RA!$C$8:$N$8,RA!$C$9:$N$9) -> 9359638 | E16: =IFERROR(C17/D16-1,0) -> 0.8117549 | H16: Personal Accident | I16: 1370079 | J16: =_xlfn.XLOOKUP(H16,RA!$C$8:$N$8,RA!$C$19:$N$19) -> 1250041 | K16: =I16/J16-1 -> 0.09602725 | N16: Personal Accident | O16: 7134489 | P16: =_xlfn.XLOOKUP(N16,RA!$C$8:$N$8,RA!$C$44:$N$44) -> 7134489 | Q16: =IFERROR(O16/P16-1,0) -> 0 | T16: Personal Accident | U16: 506105 | V16: =_xlfn.XLOOKUP(T16,RA!$C$8:$N$8,RA!$C$54:$N$54) -> 506105 | W16: =U16/V16-1 -> 0
B17: Theft | C17: 16957370 | D17: =_xlfn.XLOOKUP(B17,RA!$C$8:$N$8,RA!$C$9:$N$9) -> 16957370 | E17: =IFERROR(C18/D17-1,0) -> 5.2147394 | H17: Theft | I17: 192755 | J17: =_xlfn.XLOOKUP(H17,RA!$C$8:$N$8,RA!$C$19:$N$19) -> 702509 | K17: =I17/J17-1 -> -0.72561917 | N17: Theft | O17: 14671830 | P17: =_xlfn.XLOOKUP(N17,RA!$C$8:$N$8,RA!$C$44:$N$44) -> 14671830 | Q17: =IFERROR(O17/P17-1,0) -> 0 | T17: Theft | U17: 600134 | V17: =_xlfn.XLOOKUP(T17,RA!$C$8:$N$8,RA!$C$54:$N$54) -> 600134 | W17: =U17/V17-1 -> 0
B18: Workmen's Compensation | C18: 105385636 | D18: =_xlfn.XLOOKUP(B18,RA!$C$8:$N$8,RA!$C$9:$N$9) -> 105385636 | E18: =IFERROR(C19/D18-1,0) -> 14.140298 | H18: Workmen's Compensation | I18: 47855391 | J18: =_xlfn.XLOOKUP(H18,RA!$C$8:$N$8,RA!$C$19:$N$19) -> 64293934 | K18: =I18/J18-1 -> -0.25567798 | N18: Workmen's Compensation | O18: 295958506 | P18: =_xlfn.XLOOKUP(N18,RA!$C$8:$N$8,RA!$C$44:$N$44) -> 295958506 | Q18: =IFERROR(O18/P18-1,0) -> 0 | T18: Workmen's Compensation | U18: 18455701 | V18: =_xlfn.XLOOKUP(T18,RA!$C$8:$N$8,RA!$C$54:$N$54) -> 18623238 | W18: =U18/V18-1 -> -0.0089961262
B19: TOTAL | C19: 1595569975 | D19: =SUM(D8:D18) -> 1595569975 | E19: =IFERROR(#REF!/D19-1,0) -> 0 | H19: TOTAL | I19: 793517139 | J19: =SUM(J8:J18) -> 1012119727 | K19: =I19/J19-1 -> -0.21598491 | N19: TOTAL | O19: 1635871377 | P19: =SUM(P8:P18) -> 1635871378 | Q19: =IFERROR(O19/P19-1,0) -> -6.1129501e-10 | T19: TOTAL | U19: 745397273 | V19: =SUM(V8:V18) -> 729436135 | W19: =U19/V19-1 -> 0.021881474
B25: Pioneer General Insurance Limited | N25: Pioneer General Insurance Limited
B26: Summary of Historical Paid Claims Data | N26: Summary of Historical Paid Claims Data
B27: Year | C27: Data | D27: Financials | E27: Variation | N27: Year | O27: Data | P27: Financials | Q27: Variation
B28: 2017 | C28: 16693084 | D28: 16445890 | E28: -0.01 | N28: 2017 | O28: 16693084 | P28: 16445890 | Q28: -0.01
B29: 2018 | C29: 203087756 | D29: 203183186 | E29: 0 | N29: 2018 | O29: 203087756 | P29: 203183186 | Q29: 0
B30: 2019 | C30: 333749230 | D30: 333775300 | E30: 0 | N30: 2019 | O30: 333749230 | P30: 333775300 | Q30: 0
B31: 2020 | C31: 410615315 | D31: 402655339 | E31: -0.02 | N31: 2020 | O31: 410615315 | P31: 402655339 | Q31: -0.02
B32: 2021 | C32: 513592593 | D32: 520243988 | E32: 0.01 | N32: 2021 | O32: 513592593 | P32: 520243988 | Q32: 0.01
B33: 2022 | C33: =U19 -> 745397273 | D33: =V19 -> 729436135 | E33: =C33/D33-1 -> 0.021881474 | N33: 2022 | O33: =U19 -> 745397273 | P33: =V19 -> 729436135 | Q33: =O33/P33-1 -> 0.021881474
B34: 2023 | C34: =I19 -> 793517139 | D34: =J19 -> 1012119727 | E34: =C34/D34-1 -> -0.21598491 | N34: 2023 | O34: =I19 -> 793517139 | P34: =J19 -> 1012119727 | Q34: =O34/P34-1 -> -0.21598491

Sheet Stakeholders
B5: Pioneer General Insurance Company Shareholders and Directors | L5: Pioneer General Insurance Limited
B6: Name | C6: Description | D6: Nationality/Location | E6: Ordinary Shares | F6: Stake | L6: Management Team
B7: Pioneer Insurance Holdings | C7: Shareholder | D7: Kenya | E7: 360000 | F7: 0.6 | L7: Title | M7: Name
B8: Parkview Inv. Ltd | C8: Shareholder | D8: Dubai | E8: 120000 | F8: 0.2 | L8: Managing Director | M8: Ms. Milcah Kinyua
B9: Medillon Trading FZE | C9: Shareholder | D9: Dubai | E9: 78000 | F9: 0.13 | L9: Assistant General Manager - Operations | M9: Mrs. Anne Muhindi
B10: Abcon Int. LLC | C10: Shareholder | D10: Dubai | E10: 42000 | F10: 0.07 | L10: Underwriting Manager | M10: Stephen Okeyo
B11: Brigid Cherono | C11: Director | D11: Kenyan | E11: - | F11: 0 | L11: Claims Manager | M11: Gershom Mulwa Mutua
B12: Michael Mure | C12: Director | D12: Kenyan | E12: - | F12: 0 | L12: Business Development Manager | M12: Chris G. Mbugua
B13: Moses Kimani | C13: Director | D13: Kenyan | E13: - | F13: 0 | L13: Finance Manager | M13: Ms. Flora Muthomi
B14: Shiraz A. Jeraj | C14: Director | D14: Kenyan | E14: - | F14: 0 | L14: Head of Human Resources & Administration | M14: Ms. Margaret Mwashimba
B15: Wamuyu Catherine | C15: Director | D15: Kenyan | E15: - | F15: 0 | L15: ICT Manager | M15: Stephen Masinde
B16: Total Shares | E16: 600000 | F16: 1

Sheet Reserves
B2: Refer to the IBNR Computations in Valuation Working Files
B6: FORM NO. INS57-lb
B7: GENERAL BUSINESS OF PIONEER GENERAL INSURANCE LIMITED
B8: SUMMARY OF DISCOUNTED RESERVES AND THE VALUATION OF POLICIES AS AT 31 DECEMBER 2023
C10: Gross Discounted Technical Reserve | H10: Net Discounted Technical Reserve
B11: Insurance Business | C11: Outstanding Claims Reported | D11: Incurred But Not Reported (IBNR) Claims Reserves* | E11: Liability for Remaining Coverage | F11: Loss Component | G11: Total Gross Technical Reserves | H11: Outstanding Claims Reported | I11: Incurred But Not Reported (IBNR) Claims Reserves* | J11: Liability for Remaining Coverage | K11: Loss Component | L11: Total Net Technical Reserves
B12: Engineering | C12: 720888 | D12: 1129958.7 | E12: 11751170 | F12: 0 | G12: 13602017 | H12: 244194 | I12: 773696.78 | J12: 8046177.2 | K12: 0 | L12: 9064068
B13: Fire Domestic | C13: 1053592 | D13: 100635.35 | E13: 4275813.2 | F13: 0 | G13: 5430040.5 | H13: 1053592 | I13: 95221.165 | J13: 3771743.4 | K13: 0 | L13: 4920556.5
B14: Fire Industrial | C14: 22370600 | D14: 3772967.5 | E14: 35502836 | F14: 0 | G14: 61646403 | H14: 2023004.6 | I14: 1345416 | J14: 12660085 | K14: 0 | L14: 16028506
B15: Liability | C15: 7876415.6 | D15: 3151354.2 | E15: 22751668 | F15: 0 | G15: 33779437 | H15: 3924366.5 | I15: 2920878.8 | J15: 21087714 | K15: 0 | L15: 27932959
B16: Marine | C16: 3277913.4 | D16: 271069.47 | E16: 1041311 | F16: 0 | G16: 4590293.8 | H16: 3182556.4 | I16: 263183.61 | J16: 816734.8 | K16: 0 | L16: 4262474.8
B17: Miscellaneous | C17: 304072.06 | D17: 240982.05 | E17: 3420439.5 | F17: 0 | G17: 3965493.6 | H17: 304072.06 | I17: 209362.22 | J17: 2971636.9 | K17: 0 | L17: 3485071.1
B18: Motor Commercial | C18: 1.8108534e+08 | D18: 56238267 | E18: 1.264396e+08 | F18: 10555188 | G18: 3.7431839e+08 | H18: 1.4720465e+08 | I18: 56101688 | J18: 1.2609261e+08 | K18: 10529554 | L18: 3.399285e+08
B19: Motor Private | C19: 3.9336455e+08 | D19: 1.6468584e+08 | E19: 3.44562e+08 | F19: 27871187 | G19: 9.3048358e+08 | H19: 3.6240602e+08 | I19: 1.6438035e+08 | J19: 3.4353663e+08 | K19: 27819485 | L19: 8.9814249e+08
B20: Personal Accident | C20: 756365.79 | D20: 1158921.1 | E20: 3428032 | F20: 0 | G20: 5343318.9 | H20: 747712.97 | I20: 953278.03 | J20: 2819750.7 | K20: 0 | L20: 4520741.7
B21: Theft | C21: 829305.44 | D21: 668503.4 | E21: 8116281.3 | F21: 0 | G21: 9614090.1 | H21: 829305.44 | I21: 668503.15 | J21: 6313782 | K21: 0 | L21: 7811590.6
B22: Workmen's Compensation | C22: 40111080 | D22: 3.0488615e+08 | E22: 1.2253209e+08 | F22: 0 | G22: 4.6752932e+08 | H22: 20355942 | I22: 2.7964555e+08 | J22: 40060419 | K22: 0 | L22: 3.4006191e+08
B23: Total Business | C23: 6.5175012e+08 | D23: 5.3630465e+08 | E23: 6.8382124e+08 | F23: 38426375 | G23: 1.9103024e+09 | H23: 5.4227542e+08 | I23: 5.0735713e+08 | J23: 5.6817728e+08 | K23: 38349039 | L23: 1.6561589e+09
B24: *Includes Incurred But Not Enough Reported Claims Reserve & Risk Margin
D25: =D23/SUM(C23:D23) -> 0.45141408
H28: =SUM(H30:H31)=C23+D23 -> TRUE | I28: =SUM(I30:I31)=F23+E23 -> TRUE
G29: Gross | H29: Claims Reserves | I29: Premium Reserves
G30: Motor Classes | H30: =SUM(C18:D19) -> 7.95374e+08 | I30: =SUM(E18:E19,F23) -> 5.0942797e+08
G31: Non-Motor Classes | H31: =SUM(C23:D23)-H30 -> 3.9268077e+08 | I31: =SUM(E23:F23)-I30 -> 2.1281964e+08
H32: =SUM(H34:H35)=H23+I23 -> TRUE | I32: =SUM(I34:I35)=K23+J23 -> TRUE
G33: Net | H33: Claims Reserves | I33: Premium Reserves
G34: Motor Classes | H34: =SUM(H18:I19) -> 7.3009271e+08 | I34: =SUM(J18:J19,K23) -> 5.0797828e+08
G35: Non-Motor Classes | H35: =SUM(H23:I23)-H34 -> 3.1953984e+08 | I35: =SUM(J23:K23)-I34 -> 98548043
H38: =H30/SUM(H30:H31) -> 0.66947587 | I38: =I30/SUM(I30:I31) -> 0.70533701
H39: =H34/SUM(H34:H35) -> 0.69556981 | I39: =I34/SUM(I34:I35) -> 0.83752058

Sheet Reinsurance
E2: Pioneer General Insurance Limited
E3: Summary of Reinsurance Treaties (in Kes M)
E4: Form & Type of Reinsurance | G4: Class of Insurance | H4: Pioneer General | L4: Reinsurers | P4: Treaty Capacity
H5: 2023 | J5: 2024 | L5: 2023 | N5: 2024
H6: %/Lines | I6: Limit | J6: %/Lines | K6: Limit | L6: %/Lines | M6: Limit | N6: %/Lines | O6: Limit | P6: 2023 | Q6: 2024
E7: Proportional Business | F7: Surplus | G7: Fire & Engineering | H7: 1 | I7: 50 | J7: 1 | K7: 50 | L7: 15 | M7: 750 | N7: 20 | O7: 1000 | P7: 800 | Q7: 1050
G8: Personal Accident & WIBA
G9: Any one Loss | H9: 1 | I9: 10 | J9: 1 | K9: 10 | L9: 25 | M9: 250 | N9: 25 | O9: 250 | P9: 260 | Q9: 260
G10: Known Accumulation | H10: 1 | I10: 20 | J10: 1 | K10: 20 | L10: 25 | M10: 500 | N10: 25 | O10: 500 | P10: 520 | Q10: 520
G11: Marine
G12: Cargo | H12: 1 | I12: 50 | J12: 1 | K12: 50 | L12: 6 | M12: 300 | N12: 6 | O12: 300 | P12: 350 | Q12: 350
G13: Hull | H13: 1 | I13: 6 | J13: 1 | K13: 6 | L13: 5 | M13: 30 | N13: 5 | O13: 30 | P13: 36 | Q13: 36
F14: Quota Share | G14: Bonds & Guarantees
G15: Any one bond | H15: 0.2 | I15: 12 | J15: 0.2 | K15: 12 | L15: 0.8 | M15: 48 | N15: 0.8 | O15: 48 | P15: 60 | Q15: 60
G16: Any one contractor | H16: 0.2 | I16: 30 | J16: 0.2 | K16: 30 | L16: 0.8 | M16: 120 | N16: 0.8 | O16: 120 | P16: 150 | Q16: 150
G17: Terrorism & Political Risks | H17: 0.2 | I17: 60 | J17: 0.2 | K17: 100 | L17: 0.8 | M17: 240 | N17: 0.8 | O17: 400 | P17: 300 | Q17: 500
G18: Travel | H18: 0.1 | J18: 0.1 | L18: 0.9 | N18: 0.9
E21: Non-Proportional Business | F21: Excess of Loss | G21: Fire & Engineering | I21: 15 | K21: 15 | M21: 485 | O21: 485 | P21: 500 | Q21: 500
G22: Motor, Marine, Accident & Liability | I22: 5 | K22: 5 | M22: 295 | O22: 295 | P22: 300 | Q22: 300
E29: Pioneer General Insurance Limited
E30: Summary of Reinsurance Treaties (Amounts in KES M)
E31: Form & Type of Reinsurance | G31: Class of Insurance | H31: Pioneer General | L31: Reinsurers | P31: Treaty Capacity
H32: 2022 | J32: 2023 | L32: 2022 | N32: 2023
H33: %/Lines | I33: Limit | J33: %/Lines | K33: Limit | L33: %/Lines | M33: Limit | N33: %/Lines | O33: Limit | P33: 2022 | Q33: 2023
E34: Proportional Business | F34: Surplus | G34: Fire & Engineering | H34: 1 | I34: 50 | J34: 1 | K34: 30 | L34: 14 | M34: 700 | N34: 29 | O34: 870 | P34: 750 | Q34: 900
G35: Personal Accident & WIBA
G36: Any one Loss | H36: 1 | I36: 10 | J36: 1 | K36: 10 | L36: 14 | M36: 140 | N36: 24 | O36: 240 | P36: 150 | Q36: 250
G37: Known Accumulation | H37: 1 | I37: 20 | J37: 1 | K37: 20 | L37: 14 | M37: 280 | N37: 24 | O37: 480 | P37: 300 | Q37: 500
G38: Marine
G39: Cargo | H39: 1 | I39: 50 | J39: 1 | K39: 50 | L39: 5 | M39: 250 | N39: 5 | O39: 250 | P39: 300 | Q39: 300
G40: Hull | H40: 1 | I40: 6 | J40: 1 | K40: 6 | L40: 4 | M40: 24 | N40: 4 | O40: 24 | P40: 30 | Q40: 30
F41: Quota Share | G41: Bonds & Guarantees
G42: Any one bond | H42: 0.2 | I42: 12 | J42: 0.2 | K42: 12 | L42: 0.8 | M42: 48 | N42: 0.8 | O42: 48 | P42: 60 | Q42: 60
G43: Any one contractor | H43: 0.2 | I43: 30 | J43: 0.2 | K43: 30 | L43: 0.8 | M43: 120 | N43: 0.8 | O43: 120 | P43: 150 | Q43: 150
G44: Terrorism & Political Risks | H44: 0.2 | I44: 40 | J44: 0.2 | K44: 40 | L44: 0.8 | M44: 160 | N44: 0.8 | O44: 160 | P44: 200 | Q44: 200
G45: Travel
G46: Aviation | J46: 0.1 | K46: 10 | N46: 0.9 | O46: 90 | Q46: 100
E48: Non-Proportional Business | F48: Excess of Loss | G48: Fire & Engineering | I48: 15 | K48: 15 | M48: 485 | O48: 485 | P48: 500 | Q48: 500
G49: Motor, Marine, Accident & Liability | I49: 3 | K49: 4 | M49: 297 | O49: 296 | P49: 300 | Q49: 300

Sheet Ratios
C5: Pioneer General Insurance Limited Key Net Ratio Analysis - 2017 | J5: Pioneer General Insurance Limited Management Expense Amounts (KES '000) | S5: Pioneer General Insurance Limited Management Expense Ratios (2018 - 2023)
C6: Class | D6: Loss Ratios | E6: Commission Ratios | F6: Expense Ratios | G6: Combined Ratio | J6: Class | K6: 2017 | L6: =K6+1 -> 2018 | M6: =L6+1 -> 2019 | N6: =M6+1 -> 2020 | O6: 2021 | P6: 2022 | Q6: 2023 | S6: Class | T6: 2017 | U6: =T6+1 -> 2018 | V6: =U6+1 -> 2019 | W6: =V6+1 -> 2020 | X6: 2021 | Y6: 2022 | Z6: 2023 | AB6: 2018 | AC6: 2019 | AD6: 2020 | AE6: 2021 | AF6: 2022 | AG6: 2023
C7: Engineering | D7: =HLOOKUP($C7,RA!$D$244:$O$248,2,0) -> 0.34107794 | E7: =HLOOKUP($C7,RA!$D$244:$O$248,3,0) -> -0.21516982 | F7: =HLOOKUP($C7,RA!$D$244:$O$248,4,0) -> 0.75330162 | G7: =SUM(D7:F7) -> 0.87920975 | J7: Engineering | K7: =HLOOKUP($J7,RA!$D$219:$O$241,19,0) -> 979552 | L7: =HLOOKUP($J7,RA!$D$184:$O$209,22,0) -> 4858196.6 | M7: =HLOOKUP($J7,RA!$D$148:$O$173,22,0) -> 5245342.3 | N7: =HLOOKUP($J7,RA!$B$113:$O$144,21,0) -> 5588180.5 | O7: =_xlfn.XLOOKUP(J7,RA!$C$78:$N$78,RA!$C$98:$N$98) -> 4234328.4 | P7: =HLOOKUP($J7,RA!$B$43:$O$74,21,0) -> 9129181.9 | Q7: =HLOOKUP($J7,RA!$B$8:$O$39,21,0) -> 9043615.1 | S7: Engineering | T7: =HLOOKUP($S7,RA!$D$244:$O$248,4,0) -> 0.75330162 | U7: =HLOOKUP($S7,RA!$D$212:$O$216,4,0) -> 1.2993485 | V7: =HLOOKUP($S7,RA!$D$176:$O$180,4,0) -> 0.56924266 | W7: =HLOOKUP($S7,RA!$B$140:$O$144,4,0) -> 0.63398977 | X7: =_xlfn.XLOOKUP(S7,RA!$C$78:$N$78,RA!$C$108:$N$108) -> 0.36232679 | Y7: =HLOOKUP($S7,RA!$B$70:$O$74,4,0) -> 0.59310099 | Z7: =HLOOKUP($S7,RA!$B$35:$O$39,4,0) -> 0.39998375 | AB7: =U7-T7 -> 0.54604692 | AC7: =V7-U7 -> -0.73010588 | AD7: =W7-V7 -> 0.064747112 | AE7: =X7-W7 -> -0.27166299 | AF7: =Y7-X7 -> 0.23077421 | AG7: =Z7-Y7 -> -0.19311725
C8: Fire Domestic | D8: =HLOOKUP($C8,RA!$D$244:$O$248,2,0) -> 0.20194533 | E8: =HLOOKUP($C8,RA!$D$244:$O$248,3,0) -> 0.1185166 | F8: =HLOOKUP($C8,RA!$D$244:$O$248,4,0) -> 4.0337687 | G8: =SUM(D8:F8) -> 4.3542307 | J8: Fire Domestic | K8: =HLOOKUP($J8,RA!$D$219:$O$241,19,0) -> 2938657 | L8: =HLOOKUP($J8,RA!$D$184:$O$209,22,0) -> 2996730.9 | M8: =HLOOKUP($J8,RA!$D$148:$O$173,22,0) -> 3256838.8 | N8: =HLOOKUP($J8,RA!$B$113:$O$144,21,0) -> 2605813.4 | O8: =_xlfn.XLOOKUP(J8,RA!$C$78:$N$78,RA!$C$98:$N$98) -> 2180353.4 | P8: =HLOOKUP($J8,RA!$B$43:$O$74,21,0) -> 1978525 | Q8: =HLOOKUP($J8,RA!$B$8:$O$39,21,0) -> 2984529.4 | S8: Fire Domestic | T8: =HLOOKUP($S8,RA!$D$244:$O$248,4,0) -> 4.0337687 | U8: =HLOOKUP($S8,RA!$D$212:$O$216,4,0) -> 1.585457 | V8: =HLOOKUP($S8,RA!$D$176:$O$180,4,0) -> 0.38173936 | W8: =HLOOKUP($S8,RA!$B$140:$O$144,4,0) -> 0.25409067 | X8: =_xlfn.XLOOKUP(S8,RA!$C$78:$N$78,RA!$C$108:$N$108) -> 0.34281995 | Y8: =HLOOKUP($S8,RA!$B$70:$O$74,4,0) -> 0.34694921 | Z8: =HLOOKUP($S8,RA!$B$35:$O$39,4,0) -> 0.32011116 | AB8: =U8-T8 -> -2.4483118 | AC8: =V8-U8 -> -1.2037176 | AD8: =W8-V8 -> -0.12764869 | AE8: =X8-W8 -> 0.088729281 | AF8: =Y8-X8 -> 0.0041292598 | AG8: =Z8-Y8 -> -0.026838049
C9: Fire Industrial | D9: =HLOOKUP($C9,RA!$D$244:$O$248,2,0) -> 0.11835056 | E9: =HLOOKUP($C9,RA!$D$244:$O$248,3,0) -> -0.35021924 | F9: =HLOOKUP($C9,RA!$D$244:$O$248,4,0) -> 1.2508289 | G9: =SUM(D9:F9) -> 1.0189602 | J9: Fire Industrial | K9: =HLOOKUP($J9,RA!$D$219:$O$241,19,0) -> 4897762 | L9: =HLOOKUP($J9,RA!$D$184:$O$209,22,0) -> 17238341 | M9: =HLOOKUP($J9,RA!$D$148:$O$173,22,0) -> 18174754 | N9: =HLOOKUP($J9,RA!$B$113:$O$144,21,0) -> 19278172 | O9: =_xlfn.XLOOKUP(J9,RA!$C$78:$N$78,RA!$C$98:$N$98) -> 12661741 | P9: =HLOOKUP($J9,RA!$B$43:$O$74,21,0) -> 17453259 | Q9: =HLOOKUP($J9,RA!$B$8:$O$39,21,0) -> 21100365 | S9: Fire Industrial | T9: =HLOOKUP($S9,RA!$D$244:$O$248,4,0) -> 1.2508289 | U9: =HLOOKUP($S9,RA!$D$212:$O$216,4,0) -> 2.2683675 | V9: =HLOOKUP($S9,RA!$D$176:$O$180,4,0) -> 1.5760211 | W9: =HLOOKUP($S9,RA!$B$140:$O$144,4,0) -> 1.4582014 | X9: =_xlfn.XLOOKUP(S9,RA!$C$78:$N$78,RA!$C$108:$N$108) -> 0.74343312 | Y9: =HLOOKUP($S9,RA!$B$70:$O$74,4,0) -> 0.94560067 | Z9: =HLOOKUP($S9,RA!$B$35:$O$39,4,0) -> 0.87692619 | AB9: =U9-T9 -> 1.0175386 | AC9: =V9-U9 -> -0.69234643 | AD9: =W9-V9 -> -0.11781972 | AE9: =X9-W9 -> -0.71476825 | AF9: =Y9-X9 -> 0.20216754 | AG9: =Z9-Y9 -> -0.068674475
C10: Liability | D10: =HLOOKUP($C10,RA!$D$244:$O$248,2,0) -> 0.16550506 | E10: =HLOOKUP($C10,RA!$D$244:$O$248,3,0) -> 0.2287398 | F10: =HLOOKUP($C10,RA!$D$244:$O$248,4,0) -> 0.77660657 | G10: =SUM(D10:F10) -> 1.1708514 | J10: Liability | K10: =HLOOKUP($J10,RA!$D$219:$O$241,19,0) -> 1959105 | L10: =HLOOKUP($J10,RA!$D$184:$O$209,22,0) -> 9258901.7 | M10: =HLOOKUP($J10,RA!$D$148:$O$173,22,0) -> 12328622 | N10: =HLOOKUP($J10,RA!$B$113:$O$144,21,0) -> 10312228 | O10: =_xlfn.XLOOKUP(J10,RA!$C$78:$N$78,RA!$C$98:$N$98) -> 9098653.7 | P10: =HLOOKUP($J10,RA!$B$43:$O$74,21,0) -> 7677956.4 | Q10: =HLOOKUP($J10,RA!$B$8:$O$39,21,0) -> 11041666 | S10: Liability | T10: =HLOOKUP($S10,RA!$D$244:$O$248,4,0) -> 0.77660657 | U10: =HLOOKUP($S10,RA!$D$212:$O$216,4,0) -> 0.63275899 | V10: =HLOOKUP($S10,RA!$D$176:$O$180,4,0) -> 0.44846347 | W10: =HLOOKUP($S10,RA!$B$140:$O$144,4,0) -> 0.29912443 | X10: =_xlfn.XLOOKUP(S10,RA!$C$78:$N$78,RA!$C$108:$N$108) -> 0.26725141 | Y10: =HLOOKUP($S10,RA!$B$70:$O$74,4,0) -> 0.24780634 | Z10: =HLOOKUP($S10,RA!$B$35:$O$39,4,0) -> 0.33711696 | AB10: =U10-T10 -> -0.14384757 | AC10: =V10-U10 -> -0.18429552 | AD10: =W10-V10 -> -0.14933904 | AE10: =X10-W10 -> -0.031873021 | AF10: =Y10-X10 -> -0.019445063 | AG10: =Z10-Y10 -> 0.089310613
C11: Marine | D11: =HLOOKUP($C11,RA!$D$244:$O$248,2,0) -> 0.2113787 | E11: =HLOOKUP($C11,RA!$D$244:$O$248,3,0) -> -0.48304974 | F11: =HLOOKUP($C11,RA!$D$244:$O$248,4,0) -> 1.4588523 | G11: =SUM(D11:F11) -> 1.1871813 | J11: Marine | K11: =HLOOKUP($J11,RA!$D$219:$O$241,19,0) -> 10775076 | L11: =HLOOKUP($J11,RA!$D$184:$O$209,22,0) -> 12248039 | M11: =HLOOKUP($J11,RA!$D$148:$O$173,22,0) -> 5795968.5 | N11: =HLOOKUP($J11,RA!$B$113:$O$144,21,0) -> 2059114.8 | O11: =_xlfn.XLOOKUP(J11,RA!$C$78:$N$78,RA!$C$98:$N$98) -> 7366945.8 | P11: =HLOOKUP($J11,RA!$B$43:$O$74,21,0) -> 2784540 | Q11: =HLOOKUP($J11,RA!$B$8:$O$39,21,0) -> 3329400.1 | S11: Marine | T11: =HLOOKUP($S11,RA!$D$244:$O$248,4,0) -> 1.4588523 | U11: =HLOOKUP($S11,RA!$D$212:$O$216,4,0) -> 1.07313 | V11: =HLOOKUP($S11,RA!$D$176:$O$180,4,0) -> 0.6948806 | W11: =HLOOKUP($S11,RA!$B$140:$O$144,4,0) -> 0.23371364 | X11: =_xlfn.XLOOKUP(S11,RA!$C$78:$N$78,RA!$C$108:$N$108) -> 0.47756874 | Y11: =HLOOKUP($S11,RA!$B$70:$O$74,4,0) -> 0.30236354 | Z11: =HLOOKUP($S11,RA!$B$35:$O$39,4,0) -> 0.41018256 | AB11: =U11-T11 -> -0.38572235 | AC11: =V11-U11 -> -0.37824938 | AD11: =W11-V11 -> -0.46116697 | AE11: =X11-W11 -> 0.24385511 | AF11: =Y11-X11 -> -0.1752052 | AG11: =Z11-Y11 -> 0.10781902
C12: Miscellaneous | D12: =HLOOKUP($C12,RA!$D$244:$O$248,2,0) -> 0.18272568 | E12: =HLOOKUP($C12,RA!$D$244:$O$248,3,0) -> -0.18299357 | F12: =HLOOKUP($C12,RA!$D$244:$O$248,4,0) -> 0.28299294 | G12: =SUM(D12:F12) -> 0.28272505 | J12: Miscellaneous | K12: =HLOOKUP($J12,RA!$D$219:$O$241,19,0) -> 3918209 | L12: =HLOOKUP($J12,RA!$D$184:$O$209,22,0) -> 4887102.9 | M12: =HLOOKUP($J12,RA!$D$148:$O$173,22,0) -> 15728956 | N12: =HLOOKUP($J12,RA!$B$113:$O$144,21,0) -> 13391710 | O12: =_xlfn.XLOOKUP(J12,RA!$C$78:$N$78,RA!$C$98:$N$98) -> 19555865 | P12: =HLOOKUP($J12,RA!$B$43:$O$74,21,0) -> 4274463.2 | Q12: =HLOOKUP($J12,RA!$B$8:$O$39,21,0) -> 1508238.8 | S12: Miscellaneous | T12: =HLOOKUP($S12,RA!$D$244:$O$248,4,0) -> 0.28299294 | U12: =HLOOKUP($S12,RA!$D$212:$O$216,4,0) -> 0.63819711 | V12: =HLOOKUP($S12,RA!$D$176:$O$180,4,0) -> 4.2395993 | W12: =HLOOKUP($S12,RA!$B$140:$O$144,4,0) -> 6.4723328 | X12: =_xlfn.XLOOKUP(S12,RA!$C$78:$N$78,RA!$C$108:$N$108) -> 2.0561346 | Y12: =HLOOKUP($S12,RA!$B$70:$O$74,4,0) -> 0.37267518 | Z12: =HLOOKUP($S12,RA!$B$35:$O$39,4,0) -> 0.60277912 | AB12: =U12-T12 -> 0.35520417 | AC12: =V12-U12 -> 3.6014022 | AD12: =W12-V12 -> 2.2327335 | AE12: =X12-W12 -> -4.4161982 | AF12: =Y12-X12 -> -1.6834594 | AG12: =Z12-Y12 -> 0.23010394
C13: Motor Commercial | D13: =HLOOKUP($C13,RA!$D$244:$O$248,2,0) -> 0.70970537 | E13: =HLOOKUP($C13,RA!$D$244:$O$248,3,0) -> 0.100265 | F13: =HLOOKUP($C13,RA!$D$244:$O$248,4,0) -> 1.000805 | G13: =SUM(D13:F13) -> 1.8107753 | J13: Motor Commercial | K13: =HLOOKUP($J13,RA!$D$219:$O$241,19,0) -> 15672837 | L13: =HLOOKUP($J13,RA!$D$184:$O$209,22,0) -> 34447566 | M13: =HLOOKUP($J13,RA!$D$148:$O$173,22,0) -> 45812338 | N13: =HLOOKUP($J13,RA!$B$113:$O$144,21,0) -> 51335107 | O13: =_xlfn.XLOOKUP(J13,RA!$C$78:$N$78,RA!$C$98:$N$98) -> 52495222 | P13: =HLOOKUP($J13,RA!$B$43:$O$74,21,0) -> 68083845 | Q13: =HLOOKUP($J13,RA!$B$8:$O$39,21,0) -> 1.0269102e+08 | S13: Motor Commercial | T13: =HLOOKUP($S13,RA!$D$244:$O$248,4,0) -> 1.000805 | U13: =HLOOKUP($S13,RA!$D$212:$O$216,4,0) -> 0.44265047 | V13: =HLOOKUP($S13,RA!$D$176:$O$180,4,0) -> 0.30096014 | W13: =HLOOKUP($S13,RA!$B$140:$O$144,4,0) -> 0.35222116 | X13: =_xlfn.XLOOKUP(S13,RA!$C$78:$N$78,RA!$C$108:$N$108) -> 0.26856952 | Y13: =HLOOKUP($S13,RA!$B$70:$O$74,4,0) -> 0.23267272 | Z13: =HLOOKUP($S13,RA!$B$35:$O$39,4,0) -> 0.29103809 | AB13: =U13-T13 -> -0.5581545 | AC13: =V13-U13 -> -0.14169033 | AD13: =W13-V13 -> 0.051261017 | AE13: =X13-W13 -> -0.08365164 | AF13: =Y13-X13 -> -0.035896794 | AG13: =Z13-Y13 -> 0.058365366
C14: Motor Private | D14: =HLOOKUP($C14,RA!$D$244:$O$248,2,0) -> 0.79828609 | E14: =HLOOKUP($C14,RA!$D$244:$O$248,3,0) -> 0.14767045 | F14: =HLOOKUP($C14,RA!$D$244:$O$248,4,0) -> 2.1981426 | G14: =SUM(D14:F14) -> 3.1440992 | J14: Motor Private | K14: =HLOOKUP($J14,RA!$D$219:$O$241,19,0) -> 50653168 | L14: =HLOOKUP($J14,RA!$D$184:$O$209,22,0) -> 66463189 | M14: =HLOOKUP($J14,RA!$D$148:$O$173,22,0) -> 1.0843598e+08 | N14: =HLOOKUP($J14,RA!$B$113:$O$144,21,0) -> 1.3367977e+08 | O14: =_xlfn.XLOOKUP(J14,RA!$C$78:$N$78,RA!$C$98:$N$98) -> 1.3826429e+08 | P14: =HLOOKUP($J14,RA!$B$43:$O$74,21,0) -> 1.8250401e+08 | Q14: =HLOOKUP($J14,RA!$B$8:$O$39,21,0) -> 2.5336483e+08 | S14: Motor Private | T14: =HLOOKUP($S14,RA!$D$244:$O$248,4,0) -> 2.1981426 | U14: =HLOOKUP($S14,RA!$D$212:$O$216,4,0) -> 0.52106495 | V14: =HLOOKUP($S14,RA!$D$176:$O$180,4,0) -> 0.3119834 | W14: =HLOOKUP($S14,RA!$B$140:$O$144,4,0) -> 0.31006818 | X14: =_xlfn.XLOOKUP(S14,RA!$C$78:$N$78,RA!$C$108:$N$108) -> 0.26131748 | Y14: =HLOOKUP($S14,RA!$B$70:$O$74,4,0) -> 0.24038686 | Z14: =HLOOKUP($S14,RA!$B$35:$O$39,4,0) -> 0.2906666 | AB14: =U14-T14 -> -1.6770777 | AC14: =V14-U14 -> -0.20908155 | AD14: =W14-V14 -> -0.0019152145 | AE14: =X14-W14 -> -0.048750707 | AF14: =Y14-X14 -> -0.020930621 | AG14: =Z14-Y14 -> 0.050279744
C15: Personal Accident | D15: =HLOOKUP($C15,RA!$D$244:$O$248,2,0) -> 0.28817519 | E15: =HLOOKUP($C15,RA!$D$244:$O$248,3,0) -> 0.10918498 | F15: =HLOOKUP($C15,RA!$D$244:$O$248,4,0) -> 0.35140103 | G15: =SUM(D15:F15) -> 0.74876119 | J15: Personal Accident | K15: =HLOOKUP($J15,RA!$D$219:$O$241,19,0) -> 1959105 | L15: =HLOOKUP($J15,RA!$D$184:$O$209,22,0) -> 9580110.3 | M15: =HLOOKUP($J15,RA!$D$148:$O$173,22,0) -> 9479105 | N15: =HLOOKUP($J15,RA!$B$113:$O$144,21,0) -> 1870774.6 | O15: =_xlfn.XLOOKUP(J15,RA!$C$78:$N$78,RA!$C$98:$N$98) -> 1416352.7 | P15: =HLOOKUP($J15,RA!$B$43:$O$74,21,0) -> 1590709.7 | Q15: =HLOOKUP($J15,RA!$B$8:$O$39,21,0) -> 2589885.8 | S15: Personal Accident | T15: =HLOOKUP($S15,RA!$D$244:$O$248,4,0) -> 0.35140103 | U15: =HLOOKUP($S15,RA!$D$212:$O$216,4,0) -> 0.25034917 | V15: =HLOOKUP($S15,RA!$D$176:$O$180,4,0) -> 1.0544724 | W15: =HLOOKUP($S15,RA!$B$140:$O$144,4,0) -> 0.16029787 | X15: =_xlfn.XLOOKUP(S15,RA!$C$78:$N$78,RA!$C$108:$N$108) -> -0.69075143 | Y15: =HLOOKUP($S15,RA!$B$70:$O$74,4,0) -> 0.25078053 | Z15: =HLOOKUP($S15,RA!$B$35:$O$39,4,0) -> 0.35856044 | AB15: =U15-T15 -> -0.10105185 | AC15: =V15-U15 -> 0.80412325 | AD15: =W15-V15 -> -0.89417455 | AE15: =X15-W15 -> -0.85104931 | AF15: =Y15-X15 -> 0.94153196 | AG15: =Z15-Y15 -> 0.10777991
C16: Theft | D16: =HLOOKUP($C16,RA!$D$244:$O$248,2,0) -> 2.1182289 | E16: =HLOOKUP($C16,RA!$D$244:$O$248,3,0) -> -0.43391257 | F16: =HLOOKUP($C16,RA!$D$244:$O$248,4,0) -> 19.693585 | G16: =SUM(D16:F16) -> 21.377901 | J16: Theft | K16: =HLOOKUP($J16,RA!$D$219:$O$241,19,0) -> 2938657 | L16: =HLOOKUP($J16,RA!$D$184:$O$209,22,0) -> 4234667 | M16: =HLOOKUP($J16,RA!$D$148:$O$173,22,0) -> 4310598.7 | N16: =HLOOKUP($J16,RA!$B$113:$O$144,21,0) -> 4599512.1 | O16: =_xlfn.XLOOKUP(J16,RA!$C$78:$N$78,RA!$C$98:$N$98) -> 3658504.4 | P16: =HLOOKUP($J16,RA!$B$43:$O$74,21,0) -> 3271239.4 | Q16: =HLOOKUP($J16,RA!$B$8:$O$39,21,0) -> 4692238.3 | S16: Theft | T16: =HLOOKUP($S16,RA!$D$244:$O$248,4,0) -> 19.693585 | U16: =HLOOKUP($S16,RA!$D$212:$O$216,4,0) -> 0.63583093 | V16: =HLOOKUP($S16,RA!$D$176:$O$180,4,0) -> 0.21275605 | W16: =HLOOKUP($S16,RA!$B$140:$O$144,4,0) -> 0.29663086 | X16: =_xlfn.XLOOKUP(S16,RA!$C$78:$N$78,RA!$C$108:$N$108) -> 0.26704873 | Y16: =HLOOKUP($S16,RA!$B$70:$O$74,4,0) -> 0.31806962 | Z16: =HLOOKUP($S16,RA!$B$35:$O$39,4,0) -> 0.37293373 | AB16: =U16-T16 -> -19.057754 | AC16: =V16-U16 -> -0.42307488 | AD16: =W16-V16 -> 0.083874803 | AE16: =X16-W16 -> -0.029582122 | AF16: =Y16-X16 -> 0.051020882 | AG16: =Z16-Y16 -> 0.054864111
C17: Workmen's Compensation | D17: =HLOOKUP($C17,RA!$D$244:$O$248,2,0) -> 0.22947418 | E17: =HLOOKUP($C17,RA!$D$244:$O$248,3,0) -> 0.13705546 | F17: =HLOOKUP($C17,RA!$D$244:$O$248,4,0) -> 0.19555317 | G17: =SUM(D17:F17) -> 0.56208281 | J17: Workmen's Compensation | K17: =HLOOKUP($J17,RA!$D$219:$O$241,19,0) -> 1959105 | L17: =HLOOKUP($J17,RA!$D$184:$O$209,22,0) -> 10230990 | M17: =HLOOKUP($J17,RA!$D$148:$O$173,22,0) -> 10368035 | N17: =HLOOKUP($J17,RA!$B$113:$O$144,21,0) -> 14904287 | O17: =_xlfn.XLOOKUP(J17,RA!$C$78:$N$78,RA!$C$98:$N$98) -> 54271616 | P17: =HLOOKUP($J17,RA!$B$43:$O$74,21,0) -> 65987074 | Q17: =HLOOKUP($J17,RA!$B$8:$O$39,21,0) -> 29161038 | S17: Workmen's Compensation | T17: =HLOOKUP($S17,RA!$D$244:$O$248,4,0) -> 0.19555317 | U17: =HLOOKUP($S17,RA!$D$212:$O$216,4,0) -> 0.45927326 | V17: =HLOOKUP($S17,RA!$D$176:$O$180,4,0) -> 0.2965652 | W17: =HLOOKUP($S17,RA!$B$140:$O$144,4,0) -> 0.52229695 | X17: =_xlfn.XLOOKUP(S17,RA!$C$78:$N$78,RA!$C$108:$N$108) -> 0.3277822 | Y17: =HLOOKUP($S17,RA!$B$70:$O$74,4,0) -> 0.26732437 | Z17: =HLOOKUP($S17,RA!$B$35:$O$39,4,0) -> 0.37957283 | AB17: =U17-T17 -> 0.26372009 | AC17: =V17-U17 -> -0.16270806 | AD17: =W17-V17 -> 0.22573175 | AE17: =X17-W17 -> -0.19451474 | AF17: =Y17-X17 -> -0.060457828 | AG17: =Z17-Y17 -> 0.11224845
C18: Total | D18: =HLOOKUP($C18,RA!$D$244:$O$248,2,0) -> 0.46697779 | E18: =HLOOKUP($C18,RA!$D$244:$O$248,3,0) -> -0.0023666355 | F18: =HLOOKUP($C18,RA!$D$244:$O$248,4,0) -> 1.172393 | G18: =SUM(D18:F18) -> 1.6370041 | J18: Total | K18: =SUM(K7:K17) -> 98651233 | L18: =SUM(L7:L17) -> 1.7644383e+08 | M18: =SUM(M7:M17) -> 2.3893654e+08 | N18: =SUM(N7:N17) -> 259624669 | O18: =SUM(O6:O17) -> 3.052059e+08 | P18: =SUM(P7:P17) -> 3.647348e+08 | Q18: =SUM(Q7:Q17) -> 441506822 | S18: Total | T18: =HLOOKUP($S18,RA!$D$244:$O$248,4,0) -> 1.172393 | U18: =HLOOKUP($S18,RA!$D$212:$O$216,4,0) -> 0.55223357 | V18: =HLOOKUP($S18,RA!$D$176:$O$180,4,0) -> 0.37757371 | W18: =HLOOKUP($S18,RA!$B$140:$O$144,4,0) -> 0.36554807 | X18: =RA!O108 -> 0.30688473 | Y18: =HLOOKUP($S18,RA!$B$70:$O$74,4,0) -> 0.25929434 | Z18: =HLOOKUP($S18,RA!$B$35:$O$39,4,0) -> 0.31080859 | AB18: =U18-T18 -> -0.62015941 | AC18: =V18-U18 -> -0.17465985 | AD18: =W18-V18 -> -0.012025645 | AE18: =X18-W18 -> -0.058663335 | AF18: =Y18-X18 -> -0.047590391 | AG18: =Z18-Y18 -> 0.051514251
C23: Pioneer General Insurance Limited Key Net Ratio Analysis - 2018 | J23: Pioneer General Insurance Limited Management Expense Allocation Proportions
C24: Class | D24: Loss Ratios | E24: Commission Ratios | F24: Expense Ratios | G24: Combined Ratio | J24: Class | K24: 2017 | L24: =K24+1 -> 2018 | M24: =L24+1 -> 2019 | N24: =M24+1 -> 2020 | O24: 2021 | P24: 2022 | Q24: 2023
C25: Engineering | D25: =HLOOKUP($C25,RA!$D$212:$O$216,2,0) -> 0.80877429 | E25: =HLOOKUP($C25,RA!$D$212:$O$216,3,0) -> -0.58119236 | F25: =HLOOKUP($C25,RA!$D$212:$O$216,4,0) -> 1.2993485 | G25: =SUM(D25:F25) -> 1.5269305 | J25: Engineering | K25: =K7/K$18 -> 0.0099294451 | L25: =L7/L$18 -> 0.027533955 | M25: =M7/M$18 -> 0.021952868 | N25: =N7/N$18 -> 0.021524074 | O25: =O7/O$18 -> 0.013873678 | P25: =P7/P$18 -> 0.025029643 | Q25: =Q7/Q$18 -> 0.020483523
C26: Fire Domestic | D26: =HLOOKUP($C26,RA!$D$212:$O$216,2,0) -> 0.52989016 | E26: =HLOOKUP($C26,RA!$D$212:$O$216,3,0) -> -0.16730322 | F26: =HLOOKUP($C26,RA!$D$212:$O$216,4,0) -> 1.585457 | G26: =SUM(D26:F26) -> 1.9480439 | J26: Fire Domestic | K26: =K8/K$18 -> 0.029788345 | L26: =L8/L$18 -> 0.01698405 | M26: =M8/M$18 -> 0.013630559 | N26: =N8/N$18 -> 0.010036848 | O26: =O8/O$18 -> 0.007143877 | P26: =P8/P$18 -> 0.0054245579 | Q26: =Q8/Q$18 -> 0.0067598715
C27: Fire Industrial | D27: =HLOOKUP($C27,RA!$D$212:$O$216,2,0) -> -0.094212764 | E27: =HLOOKUP($C27,RA!$D$212:$O$216,3,0) -> -2.1366104 | F27: =HLOOKUP($C27,RA!$D$212:$O$216,4,0) -> 2.2683675 | G27: =SUM(D27:F27) -> 0.037544303 | J27: Fire Industrial | K27: =K9/K$18 -> 0.049647246 | L27: =L9/L$18 -> 0.097698744 | M27: =M9/M$18 -> 0.076065192 | N27: =N9/N$18 -> 0.074254006 | O27: =O9/O$18 -> 0.041485899 | P27: =P9/P$18 -> 0.047851916 | Q27: =Q9/Q$18 -> 0.047791708
C28: Liability | D28: =HLOOKUP($C28,RA!$D$212:$O$216,2,0) -> 0.60882948 | E28: =HLOOKUP($C28,RA!$D$212:$O$216,3,0) -> 0.17531123 | F28: =HLOOKUP($C28,RA!$D$212:$O$216,4,0) -> 0.63275899 | G28: =SUM(D28:F28) -> 1.4168997 | J28: Liability | K28: =K10/K$18 -> 0.0198589 | L28: =L10/L$18 -> 0.052475065 | M28: =M10/M$18 -> 0.051597893 | N28: =N10/N$18 -> 0.039719756 | O28: =O10/O$18 -> 0.029811527 | P28: =P10/P$18 -> 0.021050792 | Q28: =Q10/Q$18 -> 0.025009049
C29: Marine | D29: =HLOOKUP($C29,RA!$D$212:$O$216,2,0) -> 0.23567657 | E29: =HLOOKUP($C29,RA!$D$212:$O$216,3,0) -> -0.48108242 | F29: =HLOOKUP($C29,RA!$D$212:$O$216,4,0) -> 1.07313 | G29: =SUM(D29:F29) -> 0.82772413 | J29: Marine | K29: =K11/K$18 -> 0.10922394 | L29: =L11/L$18 -> 0.069416079 | M29: =M11/M$18 -> 0.024257355 | N29: =N11/N$18 -> 0.0079311216 | O29: =O11/O$18 -> 0.024137626 | P29: =P11/P$18 -> 0.0076344236 | Q29: =Q11/Q$18 -> 0.0075409936
C30: Miscellaneous | D30: =HLOOKUP($C30,RA!$D$212:$O$216,2,0) -> 0.13197631 | E30: =HLOOKUP($C30,RA!$D$212:$O$216,3,0) -> -0.57357551 | F30: =HLOOKUP($C30,RA!$D$212:$O$216,4,0) -> 0.63819711 | G30: =SUM(D30:F30) -> 0.1965979 | J30: Miscellaneous | K30: =K12/K$18 -> 0.03971779 | L30: =L12/L$18 -> 0.027697782 | M30: =M12/M$18 -> 0.065829008 | N30: =N12/N$18 -> 0.051581037 | O30: =O12/O$18 -> 0.064074336 | P30: =P12/P$18 -> 0.011719373 | Q30: =Q12/Q$18 -> 0.0034161166
C31: Motor Commercial | D31: =HLOOKUP($C31,RA!$D$212:$O$216,2,0) -> 0.70658548 | E31: =HLOOKUP($C31,RA!$D$212:$O$216,3,0) -> 0.14997414 | F31: =HLOOKUP($C31,RA!$D$212:$O$216,4,0) -> 0.44265047 | G31: =SUM(D31:F31) -> 1.2992101 | J31: Motor Commercial | K31: =K13/K$18 -> 0.15887117 | L31: =L13/L$18 -> 0.19523247 | M31: =M13/M$18 -> 0.19173433 | N31: =N13/N$18 -> 0.19772815 | O31: =O13/O$18 -> 0.17199937 | P31: =P13/P$18 -> 0.18666671 | Q31: =Q13/Q$18 -> 0.23259214
C32: Motor Private | D32: =HLOOKUP($C32,RA!$D$212:$O$216,2,0) -> 0.93270649 | E32: =HLOOKUP($C32,RA!$D$212:$O$216,3,0) -> 0.17539146 | F32: =HLOOKUP($C32,RA!$D$212:$O$216,4,0) -> 0.52106495 | G32: =SUM(D32:F32) -> 1.6291629 | J32: Motor Private | K32: =K14/K$18 -> 0.51345702 | L32: =L14/L$18 -> 0.37668184 | M32: =M14/M$18 -> 0.45382755 | N32: =N14/N$18 -> 0.51489626 | O32: =O14/O$18 -> 0.45301973 | P32: =P14/P$18 -> 0.50037454 | Q32: =Q14/Q$18 -> 0.5738639
C33: Personal Accident | D33: =HLOOKUP($C33,RA!$D$212:$O$216,2,0) -> 0.056020679 | E33: =HLOOKUP($C33,RA!$D$212:$O$216,3,0) -> 0.10708649 | F33: =HLOOKUP($C33,RA!$D$212:$O$216,4,0) -> 0.25034917 | G33: =SUM(D33:F33) -> 0.41345634 | J33: Personal Accident | K33: =K15/K$18 -> 0.0198589 | L33: =L15/L$18 -> 0.054295523 | M33: =M15/M$18 -> 0.039672061 | N33: =N15/N$18 -> 0.007205689 | O33: =O15/O$18 -> 0.0046406464 | P33: =P15/P$18 -> 0.0043612775 | Q33: =Q15/Q$18 -> 0.0058660154
C34: Theft | D34: =HLOOKUP($C34,RA!$D$212:$O$216,2,0) -> 0.090126774 | E34: =HLOOKUP($C34,RA!$D$212:$O$216,3,0) -> 0.17900701 | F34: =HLOOKUP($C34,RA!$D$212:$O$216,4,0) -> 0.63583093 | G34: =SUM(D34:F34) -> 0.90496471 | J34: Theft | K34: =K16/K$18 -> 0.029788345 | L34: =L16/L$18 -> 0.024000085 | M34: =M16/M$18 -> 0.018040768 | N34: =N16/N$18 -> 0.017716006 | O34: =O16/O$18 -> 0.011987004 | P34: =P16/P$18 -> 0.0089688164 | Q34: =Q16/Q$18 -> 0.010627782
C35: Workmen's Compensation | D35: =HLOOKUP($C35,RA!$D$212:$O$216,2,0) -> 0.31488202 | E35: =HLOOKUP($C35,RA!$D$212:$O$216,3,0) -> 0.24501644 | F35: =HLOOKUP($C35,RA!$D$212:$O$216,4,0) -> 0.45927326 | G35: =SUM(D35:F35) -> 1.0191717 | J35: Workmen's Compensation | K35: =K17/K$18 -> 0.0198589 | L35: =L17/L$18 -> 0.057984402 | M35: =M17/M$18 -> 0.043392419 | N35: =N17/N$18 -> 0.057407051 | O35: =O17/O$18 -> 0.17781968 | P35: =P17/P$18 -> 0.18091796 | Q35: =Q17/Q$18 -> 0.066048896
C36: Total | D36: =HLOOKUP($C36,RA!$D$212:$O$216,2,0) -> 0.62481314 | E36: =HLOOKUP($C36,RA!$D$212:$O$216,3,0) -> 0.058673911 | F36: =HLOOKUP($C36,RA!$D$212:$O$216,4,0) -> 0.55223357 | G36: =SUM(D36:F36) -> 1.2357206 | J36: Total | K36: =SUM(K25:K35) -> 1 | L36: =L18/L$18 -> 1 | M36: =M18/M$18 -> 1 | N36: =N18/N$18 -> 1 | O36: =O18/O$18 -> 1 | P36: =P18/P$18 -> 1 | Q36: =Q18/Q$18 -> 1
C41: Pioneer General Insurance Limited 2019 Key Net Ratios Analysis | J41: Pioneer General Insurance Limited Combined Net Ratios 2019 - 2023 | S41: Pioneer General Insurance Limited Combined Gross Ratios 2018 - 2023
C42: Class | D42: Loss Ratio | E42: Commission Ratio | F42: Expense Ratio | G42: Combined Ratio | J42: Class | K42: 2017 | L42: =K42+1 -> 2018 | M42: =L42+1 -> 2019 | N42: =M42+1 -> 2020 | O42: 2021 | P42: 2022 | Q42: 2023 | S42: Class | T42: 2017 | U42: =T42+1 -> 2018 | V42: =U42+1 -> 2019 | W42: =V42+1 -> 2020 | X42: 2021 | Y42: 2022 | Z42: 2023
C43: Engineering | D43: =HLOOKUP($S7,RA!$D$176:$O$180,2,0) -> -0.032544013 | E43: =HLOOKUP($S7,RA!$D$176:$O$180,3,0) -> -0.040905637 | F43: =HLOOKUP($S7,RA!$D$176:$O$180,4,0) -> 0.56924266 | G43: =HLOOKUP($S7,RA!$D$176:$O$180,5,0) -> 0.49579301 | J43: Engineering | K43: =G7 -> 0.87920975 | L43: =G25 -> 1.5269305 | M43: =G43 -> 0.49579301 | N43: =G61 -> 1.0022395 | O43: =G78 -> 0.53706642 | P43: =G96 -> 1.125584 | Q43: =G114 -> 0.56182767 | S43: Engineering
C44: Fire Domestic | D44: =HLOOKUP($S8,RA!$D$176:$O$180,2,0) -> 0.14807063 | E44: =HLOOKUP($S8,RA!$D$176:$O$180,3,0) -> -0.007926905 | F44: =HLOOKUP($S8,RA!$D$176:$O$180,4,0) -> 0.38173936 | G44: =HLOOKUP($S8,RA!$D$176:$O$180,5,0) -> 0.52188309 | J44: Fire Domestic | K44: =G8 -> 4.3542307 | L44: =G26 -> 1.9480439 | M44: =G44 -> 0.52188309 | N44: =G62 -> 0.42929883 | O44: =G79 -> 0.6078004 | P44: =G97 -> 0.6144555 | Q44: =G115 -> 0.69880073 | S44: Fire Domestic
C45: Fire Industrial | D45: =HLOOKUP($S9,RA!$D$176:$O$180,2,0) -> 0.35006751 | E45: =HLOOKUP($S9,RA!$D$176:$O$180,3,0) -> 0.19958177 | F45: =HLOOKUP($S9,RA!$D$176:$O$180,4,0) -> 1.5760211 | G45: =HLOOKUP($S9,RA!$D$176:$O$180,5,0) -> 2.1256704 | J45: Fire Industrial | K45: =G9 -> 1.0189602 | L45: =G27 -> 0.037544303 | M45: =G45 -> 2.1256704 | N45: =G63 -> 2.0626935 | O45: =G80 -> 0.51962952 | P45: =G98 -> 1.1694803 | Q45: =G116 -> 1.2919562 | S45: Fire Industrial
C46: Liability | D46: =HLOOKUP($S10,RA!$D$176:$O$180,2,0) -> 0.16716862 | E46: =HLOOKUP($S10,RA!$D$176:$O$180,3,0) -> 0.16838131 | F46: =HLOOKUP($S10,RA!$D$176:$O$180,4,0) -> 0.44846347 | G46: =HLOOKUP($S10,RA!$D$176:$O$180,5,0) -> 0.7840134 | J46: Liability | K46: =G10 -> 1.1708514 | L46: =G28 -> 1.4168997 | M46: =G46 -> 0.7840134 | N46: =G64 -> 0.442339 | O46: =G81 -> 0.50805949 | P46: =G99 -> 0.85501547 | Q46: =G117 -> 0.5876303 | S46: Liability
C47: Marine | D47: =HLOOKUP($S11,RA!$D$176:$O$180,2,0) -> 0.53760564 | E47: =HLOOKUP($S11,RA!$D$176:$O$180,3,0) -> -0.057407808 | F47: =HLOOKUP($S11,RA!$D$176:$O$180,4,0) -> 0.6948806 | G47: =HLOOKUP($S11,RA!$D$176:$O$180,5,0) -> 1.1750784 | J47: Marine | K47: =G11 -> 1.1871813 | L47: =G29 -> 0.82772413 | M47: =G47 -> 1.1750784 | N47: =G65 -> 0.13251095 | O47: =G82 -> 0.56051164 | P47: =G100 -> 0.55061278 | Q47: =G118 -> 1.0258123 | S47: Marine
C48: Miscellaneous | D48: =HLOOKUP($S12,RA!$D$176:$O$180,2,0) -> -0.0058129223 | E48: =HLOOKUP($S12,RA!$D$176:$O$180,3,0) -> -3.4001415 | F48: =HLOOKUP($S12,RA!$D$176:$O$180,4,0) -> 4.2395993 | G48: =HLOOKUP($S12,RA!$D$176:$O$180,5,0) -> 0.83364483 | J48: Miscellaneous | K48: =G12 -> 0.28272505 | L48: =G30 -> 0.1965979 | M48: =G48 -> 0.83364483 | N48: =G66 -> 7.0242986 | O48: =G83 -> 0.86168891 | P48: =G101 -> 1.2161557 | Q48: =G119 -> 0.93191796 | S48: Miscellaneous
C49: Motor Commercial | D49: =HLOOKUP($S13,RA!$D$176:$O$180,2,0) -> 0.54653369 | E49: =HLOOKUP($S13,RA!$D$176:$O$180,3,0) -> 0.09424883 | F49: =HLOOKUP($S13,RA!$D$176:$O$180,4,0) -> 0.30096014 | G49: =HLOOKUP($S13,RA!$D$176:$O$180,5,0) -> 0.94174266 | J49: Motor Commercial | K49: =G13 -> 1.8107753 | L49: =G31 -> 1.2992101 | M49: =G49 -> 0.94174266 | N49: =G67 -> 1.1536875 | O49: =G84 -> 1.0805601 | P49: =G102 -> 0.86544924 | Q49: =G120 -> 1.0852415 | S49: Motor Commercial
C50: Motor Private | D50: =HLOOKUP($S14,RA!$D$176:$O$180,2,0) -> 0.69797934 | E50: =HLOOKUP($S14,RA!$D$176:$O$180,3,0) -> 0.092430159 | F50: =HLOOKUP($S14,RA!$D$176:$O$180,4,0) -> 0.3119834 | G50: =HLOOKUP($S14,RA!$D$176:$O$180,5,0) -> 1.1023929 | J50: Motor Private | K50: =G14 -> 3.1440992 | L50: =G32 -> 1.6291629 | M50: =G50 -> 1.1023929 | N50: =G68 -> 1.1181325 | O50: =G85 -> 1.2437547 | P50: =G103 -> 1.0357456 | Q50: =G121 -> 1.0333027 | S50: Motor Private
C51: Personal Accident | D51: =HLOOKUP($S15,RA!$D$176:$O$180,2,0) -> 0.47070031 | E51: =HLOOKUP($S15,RA!$D$176:$O$180,3,0) -> 0.6399164 | F51: =HLOOKUP($S15,RA!$D$176:$O$180,4,0) -> 1.0544724 | G51: =HLOOKUP($S15,RA!$D$176:$O$180,5,0) -> 2.1650891 | J51: Personal Accident | K51: =G15 -> 0.74876119 | L51: =G33 -> 0.41345634 | M51: =G51 -> 2.1650891 | N51: =G69 -> -0.36601428 | O51: =G86 -> 1.197025 | P51: =G104 -> 0.5105516 | Q51: =G122 -> 0.67669502 | S51: Personal Accident
C52: Theft | D52: =HLOOKUP($S16,RA!$D$176:$O$180,2,0) -> 0.033016832 | E52: =HLOOKUP($S16,RA!$D$176:$O$180,3,0) -> 0.1851338 | F52: =HLOOKUP($S16,RA!$D$176:$O$180,4,0) -> 0.21275605 | G52: =HLOOKUP($S16,RA!$D$176:$O$180,5,0) -> 0.43090669 | J52: Theft | K52: =G16 -> 21.377901 | L52: =G34 -> 0.90496471 | M52: =G52 -> 0.43090669 | N52: =G70 -> 0.48466453 | O52: =G87 -> 0.51773636 | P52: =G105 -> 0.48754077 | Q52: =G123 -> 0.58743635 | S52: Theft
C53: Workmen's Compensation | D53: =HLOOKUP($S17,RA!$D$176:$O$180,2,0) -> 0.38198388 | E53: =HLOOKUP($S17,RA!$D$176:$O$180,3,0) -> 0.19474932 | F53: =HLOOKUP($S17,RA!$D$176:$O$180,4,0) -> 0.2965652 | G53: =HLOOKUP($S17,RA!$D$176:$O$180,5,0) -> 0.8732984 | J53: Workmen's Compensation | K53: =G17 -> 0.56208281 | L53: =G35 -> 1.0191717 | M53: =G53 -> 0.8732984 | N53: =G71 -> 0.94605392 | O53: =G88 -> 0.99249685 | P53: =G106 -> 1.247322 | Q53: =G124 -> 1.9851437 | S53: Workmen's Compensation
C54: Total | D54: =HLOOKUP($S18,RA!$D$176:$O$180,2,0) -> 0.56588416 | E54: =HLOOKUP($S18,RA!$D$176:$O$180,3,0) -> 0.088772442 | F54: =HLOOKUP($S18,RA!$D$176:$O$180,4,0) -> 0.37757371 | G54: =HLOOKUP($S18,RA!$D$176:$O$180,5,0) -> 1.0322303 | J54: Total | K54: =G18 -> 1.6370041 | L54: =G36 -> 1.2357206 | M54: =G54 -> 1.0322303 | N54: =G72 -> 1.0586715 | O54: =G89 -> 1.0970819 | P54: =G107 -> 1.0261961 | Q54: =G125 -> 1.0740324 | S54: Total
D58: 2 | E58: 3 | F58: 4 | G58: 5
C59: Pioneer General Insurance Limited 2020 Key Net Ratios Analysis
C60: Class | D60: Loss Ratio | E60: Commission Ratio | F60: Expense Ratio | G60: Combined Ratio
B61: =D61-D43 -> 0.28849414 | C61: Engineering | D61: =HLOOKUP($C61,RA!$B$140:$O$144,D$58,0) -> 0.25595013 | E61: =HLOOKUP($C61,RA!$B$140:$O$144,E$58,0) -> 0.11229958 | F61: =HLOOKUP($C61,RA!$B$140:$O$144,F$58,0) -> 0.63398977 | G61: =SUM(D61:F61) -> 1.0022395
B62: =D62-D44 -> -0.069284598 | C62: Fire Domestic | D62: =HLOOKUP($C62,RA!$B$140:$O$144,D$58,0) -> 0.078786034 | E62: =HLOOKUP($C62,RA!$B$140:$O$144,E$58,0) -> 0.096422126 | F62: =HLOOKUP($C62,RA!$B$140:$O$144,F$58,0) -> 0.25409067 | G62: =SUM(D62:F62) -> 0.42929883
B63: =D63-D45 -> 0.06735537 | C63: Fire Industrial | D63: =HLOOKUP($C63,RA!$B$140:$O$144,D$58,0) -> 0.41742288 | E63: =HLOOKUP($C63,RA!$B$140:$O$144,E$58,0) -> 0.18706928 | F63: =HLOOKUP($C63,RA!$B$140:$O$144,F$58,0) -> 1.4582014 | G63: =SUM(D63:F63) -> 2.0626935
B64: =D64-D46 -> -0.20826036 | C64: Liability | D64: =HLOOKUP($C64,RA!$B$140:$O$144,D$58,0) -> -0.041091743 | E64: =HLOOKUP($C64,RA!$B$140:$O$144,E$58,0) -> 0.18430631 | F64: =HLOOKUP($C64,RA!$B$140:$O$144,F$58,0) -> 0.29912443 | G64: =SUM(D64:F64) -> 0.442339
B65: =D65-D47 -> -0.74269137 | C65: Marine | D65: =HLOOKUP($C65,RA!$B$140:$O$144,D$58,0) -> -0.20508573 | E65: =HLOOKUP($C65,RA!$B$140:$O$144,E$58,0) -> 0.10388304 | F65: =HLOOKUP($C65,RA!$B$140:$O$144,F$58,0) -> 0.23371364 | G65: =SUM(D65:F65) -> 0.13251095
B66: =D66-D48 -> 1.0937191 | C66: Miscellaneous | D66: =HLOOKUP($C66,RA!$B$140:$O$144,D$58,0) -> 1.0879062 | E66: =HLOOKUP($C66,RA!$B$140:$O$144,E$58,0) -> -0.5359403 | F66: =HLOOKUP($C66,RA!$B$140:$O$144,F$58,0) -> 6.4723328 | G66: =SUM(D66:F66) -> 7.0242986
B67: =D67-D49 -> 0.14015284 | C67: Motor Commercial | D67: =HLOOKUP($C67,RA!$B$140:$O$144,D$58,0) -> 0.68668653 | E67: =HLOOKUP($C67,RA!$B$140:$O$144,E$58,0) -> 0.11477978 | F67: =HLOOKUP($C67,RA!$B$140:$O$144,F$58,0) -> 0.35222116 | G67: =SUM(D67:F67) -> 1.1536875
B68: =D68-D50 -> 0.0092579807 | C68: Motor Private | D68: =HLOOKUP($C68,RA!$B$140:$O$144,D$58,0) -> 0.70723732 | E68: =HLOOKUP($C68,RA!$B$140:$O$144,E$58,0) -> 0.10082704 | F68: =HLOOKUP($C68,RA!$B$140:$O$144,F$58,0) -> 0.31006818 | G68: =SUM(D68:F68) -> 1.1181325
B69: =D69-D51 -> -1.1807857 | C69: Personal Accident | D69: =HLOOKUP($C69,RA!$B$140:$O$144,D$58,0) -> -0.71008535 | E69: =HLOOKUP($C69,RA!$B$140:$O$144,E$58,0) -> 0.18377319 | F69: =HLOOKUP($C69,RA!$B$140:$O$144,F$58,0) -> 0.16029787 | G69: =SUM(D69:F69) -> -0.36601428
B70: =D70-D52 -> -0.038964718 | C70: Theft | D70: =HLOOKUP($C70,RA!$B$140:$O$144,D$58,0) -> -0.0059478861 | E70: =HLOOKUP($C70,RA!$B$140:$O$144,E$58,0) -> 0.19398156 | F70: =HLOOKUP($C70,RA!$B$140:$O$144,F$58,0) -> 0.29663086 | G70: =SUM(D70:F70) -> 0.48466453
B71: =D71-D53 -> 0.14362658 | C71: Workmen's Compensation | D71: =HLOOKUP($C71,RA!$B$140:$O$144,D$58,0) -> 0.52561046 | E71: =HLOOKUP($C71,RA!$B$140:$O$144,E$58,0) -> -0.10185348 | F71: =HLOOKUP($C71,RA!$B$140:$O$144,F$58,0) -> 0.52229695 | G71: =SUM(D71:F71) -> 0.94605392
C72: Total | D72: =HLOOKUP($C72,RA!$B$140:$O$144,D$58,0) -> 0.59026071 | E72: =HLOOKUP($C72,RA!$B$140:$O$144,E$58,0) -> 0.10286269 | F72: =HLOOKUP($C72,RA!$B$140:$O$144,F$58,0) -> 0.36554807 | G72: =SUM(D72:F72) -> 1.0586715
D75: 2 | E75: 3 | F75: 4 | G75: 5
C76: Pioneer General Insurance Limited 2021 Key Net Ratios Analysis
C77: Class | D77: Loss Ratio | E77: Commission Ratio | F77: Expense Ratio | G77: Combined Ratio
C78: Engineering | D78: =HLOOKUP($C78,RA!$B$105:$O$109,D$75,0) -> 0.25959129 | E78: =HLOOKUP($C78,RA!$B$105:$O$109,E$75,0) -> -0.084851653 | F78: =HLOOKUP($C78,RA!$B$105:$O$109,F$75,0) -> 0.36232679 | G78: =SUM(D78:F78) -> 0.53706642
C79: Fire Domestic | D79: =HLOOKUP($C79,RA!$B$105:$O$109,D$75,0) -> 0.12213198 | E79: =HLOOKUP($C79,RA!$B$105:$O$109,E$75,0) -> 0.14284847 | F79: =HLOOKUP($C79,RA!$B$105:$O$109,F$75,0) -> 0.34281995 | G79: =SUM(D79:F79) -> 0.6078004
C80: Fire Industrial | D80: =HLOOKUP($C80,RA!$B$105:$O$109,D$75,0) -> 0.026917914 | E80: =HLOOKUP($C80,RA!$B$105:$O$109,E$75,0) -> -0.25072152 | F80: =HLOOKUP($C80,RA!$B$105:$O$109,F$75,0) -> 0.74343312 | G80: =SUM(D80:F80) -> 0.51962952
C81: Liability | D81: =HLOOKUP($C81,RA!$B$105:$O$109,D$75,0) -> 0.041876767 | E81: =HLOOKUP($C81,RA!$B$105:$O$109,E$75,0) -> 0.19893132 | F81: =HLOOKUP($C81,RA!$B$105:$O$109,F$75,0) -> 0.26725141 | G81: =SUM(D81:F81) -> 0.50805949
C82: Marine | D82: =HLOOKUP($C82,RA!$B$105:$O$109,D$75,0) -> 0.058886403 | E82: =HLOOKUP($C82,RA!$B$105:$O$109,E$75,0) -> 0.024056495 | F82: =HLOOKUP($C82,RA!$B$105:$O$109,F$75,0) -> 0.47756874 | G82: =SUM(D82:F82) -> 0.56051164
C83: Miscellaneous | D83: =HLOOKUP($C83,RA!$B$105:$O$109,D$75,0) -> 0.10469031 | E83: =HLOOKUP($C83,RA!$B$105:$O$109,E$75,0) -> -1.299136 | F83: =HLOOKUP($C83,RA!$B$105:$O$109,F$75,0) -> 2.0561346 | G83: =SUM(D83:F83) -> 0.86168891
C84: Motor Commercial | D84: =HLOOKUP($C84,RA!$B$105:$O$109,D$75,0) -> 0.70686177 | E84: =HLOOKUP($C84,RA!$B$105:$O$109,E$75,0) -> 0.1051288 | F84: =HLOOKUP($C84,RA!$B$105:$O$109,F$75,0) -> 0.26856952 | G84: =SUM(D84:F84) -> 1.0805601
C85: Motor Private | D85: =HLOOKUP($C85,RA!$B$105:$O$109,D$75,0) -> 0.88046359 | E85: =HLOOKUP($C85,RA!$B$105:$O$109,E$75,0) -> 0.10197362 | F85: =HLOOKUP($C85,RA!$B$105:$O$109,F$75,0) -> 0.26131748 | G85: =SUM(D85:F85) -> 1.2437547
C86: Personal Accident | D86: =HLOOKUP($C86,RA!$B$105:$O$109,D$75,0) -> -0.42880497 | E86: =HLOOKUP($C86,RA!$B$105:$O$109,E$75,0) -> 2.3165814 | F86: =HLOOKUP($C86,RA!$B$105:$O$109,F$75,0) -> -0.69075143 | G86: =SUM(D86:F86) -> 1.197025
C87: Theft | D87: =HLOOKUP($C87,RA!$B$105:$O$109,D$75,0) -> 0.050414303 | E87: =HLOOKUP($C87,RA!$B$105:$O$109,E$75,0) -> 0.20027332 | F87: =HLOOKUP($C87,RA!$B$105:$O$109,F$75,0) -> 0.26704873 | G87: =SUM(D87:F87) -> 0.51773636
C88: Workmen's Compensation | D88: =HLOOKUP($C88,RA!$B$105:$O$109,D$75,0) -> 0.49094487 | E88: =HLOOKUP($C88,RA!$B$105:$O$109,E$75,0) -> 0.17376978 | F88: =HLOOKUP($C88,RA!$B$105:$O$109,F$75,0) -> 0.3277822 | G88: =SUM(D88:F88) -> 0.99249685
C89: Total | D89: =HLOOKUP($C89,RA!$B$105:$O$109,D$75,0) -> 0.69811079 | E89: =HLOOKUP($C89,RA!$B$105:$O$109,E$75,0) -> 0.092086417 | F89: =HLOOKUP($C89,RA!$B$105:$O$109,F$75,0) -> 0.30688473 | G89: =SUM(D89:F89) -> 1.0970819
D93: 2 | E93: 3 | F93: 4 | G93: 5
C94: Pioneer General Insurance Limited 2022 Key Net Ratios Analysis
C95: Class | D95: Loss Ratio | E95: Commission Ratio | F95: Expense Ratio | G95: Combined Ratio
C96: Engineering | D96: =HLOOKUP($C96,RA!$B$70:$O$74,D$58,0) -> 0.30594618 | E96: =HLOOKUP($C96,RA!$B$70:$O$74,E$58,0) -> 0.22653687 | F96: =HLOOKUP($C96,RA!$B$70:$O$74,F$58,0) -> 0.59310099 | G96: =SUM(D96:F96) -> 1.125584
C97: Fire Domestic | D97: =HLOOKUP($C97,RA!$B$70:$O$74,D$58,0) -> 0.10296098 | E97: =HLOOKUP($C97,RA!$B$70:$O$74,E$58,0) -> 0.16454531 | F97: =HLOOKUP($C97,RA!$B$70:$O$74,F$58,0) -> 0.34694921 | G97: =SUM(D97:F97) -> 0.6144555
C98: Fire Industrial | D98: =HLOOKUP($C98,RA!$B$70:$O$74,D$58,0) -> 0.17240272 | E98: =HLOOKUP($C98,RA!$B$70:$O$74,E$58,0) -> 0.051476961 | F98: =HLOOKUP($C98,RA!$B$70:$O$74,F$58,0) -> 0.94560067 | G98: =SUM(D98:F98) -> 1.1694803
C99: Liability | D99: =HLOOKUP($C99,RA!$B$70:$O$74,D$58,0) -> 0.41365904 | E99: =HLOOKUP($C99,RA!$B$70:$O$74,E$58,0) -> 0.19355009 | F99: =HLOOKUP($C99,RA!$B$70:$O$74,F$58,0) -> 0.24780634 | G99: =SUM(D99:F99) -> 0.85501547
C100: Marine | D100: =HLOOKUP($C100,RA!$B$70:$O$74,D$58,0) -> 0.075255355 | E100: =HLOOKUP($C100,RA!$B$70:$O$74,E$58,0) -> 0.17299388 | F100: =HLOOKUP($C100,RA!$B$70:$O$74,F$58,0) -> 0.30236354 | G100: =SUM(D100:F100) -> 0.55061278
C101: Miscellaneous | D101: =HLOOKUP($C101,RA!$B$70:$O$74,D$58,0) -> 0.037802902 | E101: =HLOOKUP($C101,RA!$B$70:$O$74,E$58,0) -> 0.80567767 | F101: =HLOOKUP($C101,RA!$B$70:$O$74,F$58,0) -> 0.37267518 | G101: =SUM(D101:F101) -> 1.2161557
C102: Motor Commercial | D102: =HLOOKUP($C102,RA!$B$70:$O$74,D$58,0) -> 0.53373464 | E102: =HLOOKUP($C102,RA!$B$70:$O$74,E$58,0) -> 0.099041877 | F102: =HLOOKUP($C102,RA!$B$70:$O$74,F$58,0) -> 0.23267272 | G102: =SUM(D102:F102) -> 0.86544924
C103: Motor Private | D103: =HLOOKUP($C103,RA!$B$70:$O$74,D$58,0) -> 0.69626432 | E103: =HLOOKUP($C103,RA!$B$70:$O$74,E$58,0) -> 0.099094399 | F103: =HLOOKUP($C103,RA!$B$70:$O$74,F$58,0) -> 0.24038686 | G103: =SUM(D103:F103) -> 1.0357456
C104: Personal Accident | D104: =HLOOKUP($C104,RA!$B$70:$O$74,D$58,0) -> 0.085415736 | E104: =HLOOKUP($C104,RA!$B$70:$O$74,E$58,0) -> 0.17435534 | F104: =HLOOKUP($C104,RA!$B$70:$O$74,F$58,0) -> 0.25078053 | G104: =SUM(D104:F104) -> 0.5105516
C105: Theft | D105: =HLOOKUP($C105,RA!$B$70:$O$74,D$58,0) -> 0.031083657 | E105: =HLOOKUP($C105,RA!$B$70:$O$74,E$58,0) -> 0.13838749 | F105: =HLOOKUP($C105,RA!$B$70:$O$74,F$58,0) -> 0.31806962 | G105: =SUM(D105:F105) -> 0.48754077
C106: Workmen's Compensation | D106: =HLOOKUP($C106,RA!$B$70:$O$74,D$58,0) -> 0.79428592 | E106: =HLOOKUP($C106,RA!$B$70:$O$74,E$58,0) -> 0.18571172 | F106: =HLOOKUP($C106,RA!$B$70:$O$74,F$58,0) -> 0.26732437 | G106: =SUM(D106:F106) -> 1.247322
C107: Total | D107: =HLOOKUP($C107,RA!$B$70:$O$74,D$58,0) -> 0.64270551 | E107: =HLOOKUP($C107,RA!$B$70:$O$74,E$58,0) -> 0.12419623 | F107: =HLOOKUP($C107,RA!$B$70:$O$74,F$58,0) -> 0.25929434 | G107: =SUM(D107:F107) -> 1.0261961
D111: 2 | E111: 3 | F111: 4 | G111: 5
C112: Pioneer General Insurance Limited 2023 Key Net Ratios Analysis
C113: Class | D113: Loss Ratio | E113: Commission Ratio | F113: Expense Ratio | G113: Combined Ratio
C114: Engineering | D114: =HLOOKUP($C114,RA!$B$35:$O$39,D$111,0) -> 0.060685612 | E114: =HLOOKUP($C114,RA!$B$35:$O$39,E$111,0) -> 0.10115831 | F114: =HLOOKUP($C114,RA!$B$35:$O$39,F$111,0) -> 0.39998375 | G114: =SUM(D114:F114) -> 0.56182767
C115: Fire Domestic | D115: =HLOOKUP($C115,RA!$B$35:$O$39,D$111,0) -> 0.2007166 | E115: =HLOOKUP($C115,RA!$B$35:$O$39,E$111,0) -> 0.17797297 | F115: =HLOOKUP($C115,RA!$B$35:$O$39,F$111,0) -> 0.32011116 | G115: =SUM(D115:F115) -> 0.69880073
C116: Fire Industrial | D116: =HLOOKUP($C116,RA!$B$35:$O$39,D$111,0) -> 0.2305446 | E116: =HLOOKUP($C116,RA!$B$35:$O$39,E$111,0) -> 0.18448541 | F116: =HLOOKUP($C116,RA!$B$35:$O$39,F$111,0) -> 0.87692619 | G116: =SUM(D116:F116) -> 1.2919562
C117: Liability | D117: =HLOOKUP($C117,RA!$B$35:$O$39,D$111,0) -> 0.034014231 | E117: =HLOOKUP($C117,RA!$B$35:$O$39,E$111,0) -> 0.21649911 | F117: =HLOOKUP($C117,RA!$B$35:$O$39,F$111,0) -> 0.33711696 | G117: =SUM(D117:F117) -> 0.5876303
C118: Marine | D118: =HLOOKUP($C118,RA!$B$35:$O$39,D$111,0) -> 0.41152703 | E118: =HLOOKUP($C118,RA!$B$35:$O$39,E$111,0) -> 0.20410272 | F118: =HLOOKUP($C118,RA!$B$35:$O$39,F$111,0) -> 0.41018256 | G118: =SUM(D118:F118) -> 1.0258123
C119: Miscellaneous | D119: =HLOOKUP($C119,RA!$B$35:$O$39,D$111,0) -> 0.012024499 | E119: =HLOOKUP($C119,RA!$B$35:$O$39,E$111,0) -> 0.31711434 | F119: =HLOOKUP($C119,RA!$B$35:$O$39,F$111,0) -> 0.60277912 | G119: =SUM(D119:F119) -> 0.93191796
C120: Motor Commercial | D120: =HLOOKUP($C120,RA!$B$35:$O$39,D$111,0) -> 0.6920532 | E120: =HLOOKUP($C120,RA!$B$35:$O$39,E$111,0) -> 0.1021502 | F120: =HLOOKUP($C120,RA!$B$35:$O$39,F$111,0) -> 0.29103809 | G120: =SUM(D120:F120) -> 1.0852415
C121: Motor Private | D121: =HLOOKUP($C121,RA!$B$35:$O$39,D$111,0) -> 0.64010258 | E121: =HLOOKUP($C121,RA!$B$35:$O$39,E$111,0) -> 0.1025335 | F121: =HLOOKUP($C121,RA!$B$35:$O$39,F$111,0) -> 0.2906666 | G121: =SUM(D121:F121) -> 1.0333027
C122: Personal Accident | D122: =HLOOKUP($C122,RA!$B$35:$O$39,D$111,0) -> 0.11304543 | E122: =HLOOKUP($C122,RA!$B$35:$O$39,E$111,0) -> 0.20508914 | F122: =HLOOKUP($C122,RA!$B$35:$O$39,F$111,0) -> 0.35856044 | G122: =SUM(D122:F122) -> 0.67669502
C123: Theft | D123: =HLOOKUP($C123,RA!$B$35:$O$39,D$111,0) -> 0.055834611 | E123: =HLOOKUP($C123,RA!$B$35:$O$39,E$111,0) -> 0.15866801 | F123: =HLOOKUP($C123,RA!$B$35:$O$39,F$111,0) -> 0.37293373 | G123: =SUM(D123:F123) -> 0.58743635
...

Sheet Past_FCR_Recs
B6: Pioneer General Insurance Limited | F6: Pioneer General Insurance Limited | M6: Pioneer General Insurance Company
B7: Past FCR Recommendations | F7: Past FCR Recommendations | M7: Past FCR Recommendations - 2021 | S7: Pioneer Insurance Kenya Limited
B8: 2019 Key Recommendations | D8: Extent Addressed in 2021 | F8: Key Recommendations | H8: Extent Addressed in 2021 | M8: 2021 FCR Recommendations | O8: Extent Addressed as at 2022 | S8: Past FCR Recommendations - 2022
B9: 1 | C9: Historical Reserve Adequacy Tests | D9: Under Continuous Review | F9: 1 | G9: Business Strategy | H9: The company has strived to diversify its business and reduce its exposure in motor business in line with the actuary’s recommendation. As a result, as at the end of 2021, the company’s book comprised of 62% motor business and 38% non-motor. | M9: 1 | N9: Business Strategy | O9: The company has strived to diversify its business and reduce its exposure in motor business in line with the actuary’s recommendation. Further the rates charged on motor business which has been loss making industrywide have been revised upwards to address this. | S9: 2022 FCR Recommendations | U9: Extent Addressed as at 2023
C10: A continuous review and monitoring of the Outstanding Claims Reserves methodology to ensure that any gaps between set reserves and actual pay-outs on settlement are minimal. | G10: Management should explore profitable product lines and create strategies to skew the product mix towards more non-Motor business which is generally more profitable. The book comprised over 70% Motor business which is less profitable due to high loss ratios. | M10: (i) | N10: The proportion of the Motor book reduced from 70% in 2020 to 62% in 2021. However, this remains much higher than the industry average, which has ranged between 30% and 36% over the past five years. We recommend continued efforts by the business to increase exposure to the more profitable non-Motor classes of business. | S10: 1 | T10: Product Mix and Diversification | U10: The company has strived to diversify its business and reduce its exposure in motor business in line with the actuary’s recommendation. Further the rates charged on motor business which has been loss making industrywide have been revised upwards to address this.
B11: 2 | C11: Pricing and Premium Adequacy | D11: Addressed in February 2021 | F11: 1 | G11: Historical Reserve Adequacy Tests | H11: Pioneer has taken steps to address the inadequacies in its case estimates. As at the valuation date, a proposal is under discussion at the senior management level to review the individual case estimate amount to a minimum of Ksh 200,000 from the current Ksh 150,000. | T11: Pioneer’s business mix has historically been mainly dominated by Motor insurance business. Motor business remains dominant for the insurer as at the end of 2022. The company should put in place measures to profitably grow its non-Motor portfolio and hence achieve better diversification.
C12: Review its underwriting procedures as well as its system capabilities to ensure the focus is shifted towards key risk factors e.g. age, gender and experience of driver. | G12: A continuous review and monitoring of the Outstanding Claims Reserves methodology to ensure that any gaps between set reserves and actual pay-outs on settlement are minimal. | M12: 2 | N12: Historical Reserve Adequacy Tests | O12: Pioneer has taken steps to address the inadequacies in its case estimates. As at present the individual case estimate amount has been reviewed upwards from KES 150,000 to KES 180,000. | S12: 2 | T12: Expenses
B13: 3 | C13: Capital Management and Capital Adequacy | D13: Capital Management and Credit Control Policies are in place. | F13: 2 | G13: Pricing and Premium Adequacy | H13: Ongoing implementation | M13: (i) | N13: From the test on the adequacy of previous reserves, the Case Estimates held as at December 2018, 2019, and 2020 are expected to be inadequate. The inadequacy is mainly driven by the Motor classes. | T13: There was a notable decrease in the expense ratio, from 31% in 2021 to 26% in 2022, We recommend that the insurer continues with the strategies aimed at growing the business volume to ensure expense levels are within the statutory allowable limits. | U13: Strategies are in place to grow the business volumes and reduce the expense ratio.
C14: Adoption of a Credit Management Policy to manage credit risk exposure. | G14: We recommend that for Motor insurance business, risk factors such as make and model of vehicles, age, gender and experience of driver etc are included in the Underwriting Manual to be captured and recorded at the underwriting stage. With industry focus shifting towards risk-based pricing, the company needs to review both its underwriting procedures as well as its system capabilities to ensure the focus is shifted towards key risk factors. | N14: As at the valuation date, a proposal is under discussion at the senior management level to review the individual case estimate amount to a minimum of KES. 200,000 from the current KES. 150,000. We recommend adoption and implementation of this proposal | T14: Reinsurance Arrangements | U14: At the end of the year 2023, an assessment of the adequacy of reinsurance strategies and arrangements proposed to cover of the insurer’s underwriting risks was done. Given the company’s plan for the year 2024, the treaty arrangements proposed were appropriate.
C15: The company’s business strategy to focus on capital preservation to improve the company’s Capital Adequacy Ratio | F15: 3 | G15: Capital Management and Capital Adequacy | H15: We have reviewed our product pricing policy especially for loss making classes of business to improve experience. A Credit management policy is in place. | M15: 3 | N15: Pricing and Premium Adequacy | O15: The rates charged on motor business which has been loss making industrywide have been revised upwards to address this. | S15: 3 (i) | T15: The company’s financial results show consistently lower profits on a net basis compared to the gross position, as the company is ceding away more of its profitable non-Motor business than the less profitable Motor business.
B16: 4 | C16: Reinsurance Arrangements | D16: At the end of the year 2020, an assessment of the adequacy of reinsurance strategies and arrangements proposed by the insurer to cover of the insurer’s underwriting risks was done. Given the company’s Plan for the year 2021, the treaty arrangements proposed were appropriate. | G16: We recommend that Pioneer General adopts a Credit Management Policy to help manage its credit risk expose which makes up the most proportion of the Risk Based Capital. | M16: i) | N16: The Motor Private and Motor Commercial classes are loss making, registering a combined loss ratio of more than 100% over the past five years. We recommend that the performance of these classes continue to be monitored and if necessary, premium reviews be conducted. | S16: (ii) | T16: We recommend that Pioneer continuously monitors the cost-effectiveness of these arrangements as the business grows, against actual claims experience to ensure the price paid for reinsurance is commensurate with expected recoveries to be made.
C17: An assessment on the appropriateness of existing reinsurance arrangements for Miscellaneous, Engineering, Fire Industrial, Liability and Marine classes and the cost-effectiveness of these arrangements to ensure the price paid for reinsurance is commensurate with expected recoveries to be made. | G17: Further, the company’s Business Strategy should focus on capital preservation to improve the company’s Capital Adequacy Ratio which currently falls short of the Prescribed Capital Requirements (“PCR”) of 200% provided for in the final capital requirements guidelines. | M17: (ii) | N17: With industry focus shifting towards risk-based pricing, the company needs to review both its underwriting procedures as well as its system capabilities to ensure the focus is shifted towards key risk factors. As at the valuation date, we were informed that this proposal is undergoing implementation. We encourage adoption of the report once complete. | S17: (iii) | T17: We also recommend that Pioneer conducts a Reinsurance Optimisation Exercise to assess the adequacy of its reinsurance arrangements.
B18: 5 | C18: Internal Processes | D18: Under Continuous Review | F18: 4 | G18: Investment Policy | H18: The Investment policy was reviewed in line with recommendation which has seen an increase in investment in government securities. | M18: 4 | N18: Capital Management and Capital Adequacy | O18: We are on course to meet this. A Credit management policy is in place. | T18: Reserving | U18: Pioneer continues to monitor this closely given that it adjusted its minimum case estimates from Kshs. 150,000 to Kshs. 180,000.
C19: The Manual to be: | G19: The Investment Policy should be reviewed to allow more allocation to Treasury Bonds which should help to yield higher investment return (average of 12%, compared to insurer’s actual return of 6.7% in 2020) and improve liquidity. | M19: (i) | N19: We recommend that Pioneer General implements the Credit Management Policy to manage its credit risk exposure. | S19: 4 (i) | T19: From the test on the adequacy of previous reserves, the Case Estimates held as at December 2019, 2020, and 2021 are expected to be inadequate. The inadequacy is mainly driven by the Motor classes.
C20: - Periodically updated to reflect any changes in the policies and procedures arising from the deliberations of the departmental meetings and the company’s changes in philosophies; | F20: 4 | G20: Reinsurance Arrangements | H20: At the end of the year 2021, an assessment of the adequacy of reinsurance strategies and arrangements proposed by the insurer to cover of the insurer’s underwriting risks was done. Given the company’s Plan for the year 2022, the treaty arrangements proposed were appropriate. | M20: (ii) | N20: We recommend Pioneer’s Business Strategy should focus on capital preservation to improve the company’s Capital Adequacy Ratio which currently falls short of the Prescribed Capital Requirements (“PCR”) of 200% provided for in the final capital requirements guidelines | S20: (ii) | T20: Case Estimates should be reviewed by management to ensure adequate reserves are set for Outstanding Claims.
C21: - Reviewed to include all sub-classes of business that the company deals in. | G21: An assessment should be performed on the appropriateness of existing reinsurance arrangements for Miscellaneous, Fire Industrial, Personal Accident and Workmen’s Compensation classes of business. The cost-effectiveness of these arrangements should be monitored as the business grows, against actual claims experience to ensure the price paid for reinsurance is commensurate with expected recoveries to be made. | M21: 5 | N21: Investment Policy | O21: The Investment policy was reviewed in line with recommendation which has seen an increase in investment in government securities.
F22: 5 | G22: Internal Processes | H22: Ongoing implementation | N22: Liquidity ratio is noted to have been declining over the past five years, from 76% in 2017 to 24% in 2021. Liquid assets cover over liabilities is also noted to have declined significantly to 43% as at the end of 2021, from 73% in the previous year. Given the short-term nature of the company’s liabilities, we recommend that the company increases investment allocation to liquid assets.
G23: The Manual to be: | M23: 6 | N23: Reinsurance Arrangements
G24: - Periodically updated to reflect any changes in the policies and procedures arising from the deliberations of the departmental meetings and the company’s changes in philosophies; | M24: (i) | N24: It was noted that the reinsurance cover served to reduce underwriting profit volatility from 11% to 8% over 2018 to 2021. However, the company’s financial results show consistently lower profits on a net basis compared to the gross position, as the company is ceding away more of its profitable non-Motor business than the less profitable Motor business. The cost-effectiveness of these arrangements should be monitored as the business grows, against actual claims experience to ensure the price paid for reinsurance is commensurate with expected recoveries to be made. | O24: At the end of the year 2022, an assessment of the adequacy of reinsurance strategies and arrangements proposed to cover of the insurer’s underwriting risks was done. Given the company’s plan for the year 2023, the treaty arrangements proposed were appropriate.
G25: - Reviewed to include all sub-classes of business that the company deals in. | M25: 7 | N25: Internal Processes Review | O25: Launch of the medical class of business was postponed to a later date.
N26: Pioneer General should review the underwriting manual to include the medical sub-class of business, which the company intends to launch in 2022.
F31: Pioneer General Insurance Limited
F32: Past FCR Recommendations
F33: 2019 Key Recommendations | H33: Extent Addressed in 2020
F34: 1 | G34: Historical Reserve Adequacy Tests | H34: Under Continuous Review
G35: A continuous review and monitoring of the Outstanding Claims Reserves methodology to ensure that any gaps between set reserves and actual pay-outs on settlement are minimal.
F36: 2 | G36: Pricing and Premium Adequacy | H36: Addressed in February 2021
G37: Review its underwriting procedures as well as its system capabilities to ensure the focus is shifted towards key risk factors e.g., age, gender and experience of driver.
F38: 3 | G38: Capital Management and Capital Adequacy | H38: Capital Management and Credit Control Policies are in place.
G39: Adoption of a Credit Management Policy to manage credit risk exposure.
G40: The company’s business strategy to focus on capital preservation to improve the company’s Capital Adequacy Ratio
F41: 4 | G41: Reinsurance Arrangements | H41: At the end of the year 2020, an assessment of the adequacy of reinsurance strategies and arrangements proposed by the insurer to cover of the insurer’s underwriting risks was done. Given the company’s Plan for the year 2021, the treaty arrangements proposed were appropriate.
G42: An assessment on the appropriateness of existing reinsurance arrangements for Miscellaneous, Engineering, Fire Industrial, Liability and Marine classes and the cost-effectiveness of these arrangements to ensure the price paid for reinsurance is commensurate with expected recoveries to be made.
F43: 5 | G43: Internal Processes | H43: Under Continuous Review
G44: The Manual to be:
G45: - Periodically updated to reflect any changes in the policies and procedures arising from the deliberations of the departmental meetings and the company’s changes in philosophies;
G46: - Reviewed to include all sub-classes of business that the company deals in.

Sheet CAR
B2: Refer to the CAR Computations in Valuations Working Files
C6: Capital Form 8
C7: Capital Adequacy Ratio
C8: Company: | K8: 1000000
C9: Reporting Period:
C11: Capital | D11: Line | E11: General Business | I11: RISK BASED CAPITAL - COMPONENTS (in KES. millions) | K11: 45291 | N11: Pioneer General Insurance Limited
E12: [B] | N12: Capital Adequacy Assessment (Amounts in KES Millions) | W12: =U15/U20 -> 0.61224615
I13: A | J13: Credit Risk | K13: 320.22895 | N13: RISK BASED CAPITAL - COMPONENTS | P13: 43465 | Q13: 43830 | R13: 44196 | S13: 44561 | T13: 44926 | U13: 45291
C14: Tier-1 Capital | D14: 10 | E14: 1693560848 | I14: B | J14: Market Risk | K14: 199.41506
C15: Tier-2 Capital | D15: 11 | E15: 100000000 | I15: C | J15: Insurance Risk | K15: 139.86783 | N15: A | O15: Credit Risk | P15: 142 | Q15: 192 | R15: 128 | S15: 192 | T15: 184 | U15: =K13 -> 320.22895 | W15: =T15/SUM(T15:T18) -> 0.30717863 | X15: =U15/SUM(U15:U18) -> 0.41043771
C16: Deductions | D16: 12 | E16: 988077266 | I16: D | J16: Operational Risk Charge | K16: 120.70143 | N16: B | O16: Market Risk | P16: 0 | Q16: 90 | R16: 114 | S16: 116 | T16: 133 | U16: =K14 -> 199.41506
C17: Total Capital Available (TCA) | D17: 13 | E17: 805483582 | I17: E | J17: Diversification Benefits | K17: -257.17373 | N17: C | O17: Insurance Risk | P17: 21 | Q17: 32 | R17: 78 | S17: 136 | T17: 193 | U17: =K15 -> 139.86783
I18: F = SUM (A .. E) | J18: Risk Based Capital | K18: 523.03954 | N18: D | O18: Operational Risk Charge | P18: 43 | Q18: 64 | R18: 56 | S18: 79 | T18: 89 | U18: =K16 -> 120.70143
C19: Absolute Amount Minimum1 | D19: 14 | E19: 600000000 | N19: E | O19: Diversification Benefits | P19: -20 | Q19: -100 | R19: -132 | S19: -181 | T19: -212 | U19: =K17 -> -257.17373
C20: Volume of Business Minimum2 | D20: 15 | E20: 2.8130955e+08 | N20: F = SUM (A .. E) | O20: Risk Based Capital | P20: 186 | Q20: 279 | R20: 245 | S20: 341 | T20: 387 | U20: =K18 -> 523.03954
C21: Risk Based Capital Minimum | D21: 16 | E21: 5.2303954e+08 | I21: REQUIRED CAPITAL (RISK BASED CAPITAL) (in KES. millions) | K21: 45291
C22: Minimum Required Capital | D22: 17 | E22: 600000000 | I22: G | J22: Minimum Capital of KES. 600m | K22: 600
I23: H | J23: 20% of Net Earned Premium in 2023 | K23: 281.30955 | N23: REQUIRED CAPITAL (RISK BASED CAPITAL) | P23: 43465 | Q23: 43830 | R23: 44196 | S23: 44561 | T23: 44926 | U23: =U13 -> 45291
C24: Capital Adequacy Ratio | D24: 18 | E24: =IFERROR(E17/E22,"") -> 1.3424726 | I24: I | J24: Calculated Risk Based Capital | K24: 523.03954 | N24: G | O24: Minimum Capital of KES 600m | P24: 600 | Q24: 600 | R24: 600 | S24: 600 | T24: 600 | U24: =K22 -> 600
I25: J= Max (G, H, I) | J25: Minimum Required Capital | K25: 600 | N25: H | O25: 20% of Net Earned Premium in the Previous Year | P25: 36 | Q25: 64 | R25: 127 | S25: 142 | T25: 199 | U25: =K23 -> 281.30955
N26: I | O26: Calculated Risk Based Capital | P26: 186 | Q26: 279 | R26: 245 | S26: 341 | T26: 387 | U26: =K24 -> 523.03954
C27: Risk | D27: Line | E27: General Business | N27: J= MAX (G, H, I) | O27: Minimum Required Capital | P27: 600 | Q27: 600 | R27: 600 | S27: 600 | T27: 600 | U27: 653
E28: [B] | I28: SOLVENCY RATIO (in KES. millions) | K28: 45291
I29: K | J29: Available Capital | K29: 805.48358
C30: Credit risk capital charges | D30: 10 | E30: 3.2022895e+08 | I30: L | J30: Required Capital | K30: 600 | N30: SOLVENCY RATIO | P30: 43465 | Q30: 43830 | R30: 44196 | S30: 44561 | T30: 44926 | U30: =U23 -> 45291
C31: Market risk capital charges | D31: 11 | E31: 1.9941506e+08 | I31: M= K/L | J31: Solvency Ratio / Capital Adequacy Ratio (CAR) | K31: 1.3424726 | N31: K | O31: Available Capital | P31: 169 | Q31: 483 | R31: 610 | S31: 611 | T31: 681 | U31: =K29 -> 805.48358
C32: Insurance risk capital charges | D32: 12 | E32: 1.3986783e+08 | N32: L | O32: Required Capital | P32: 600 | Q32: 600 | R32: 600 | S32: 600 | T32: 600 | U32: 600
C33: Operational risk capital charges | D33: 13 | E33: 1.2070143e+08 | I33: N = K - L | J33: At 100% Minimum Capital: Surplus / - Deficit | K33: 205.48358 | N33: M= K/L | O33: Solvency Ratio / Capital Adequacy Ratio (CAR) | P33: 0.28 | Q33: 0.8 | R33: 1.02 | S33: 1.02 | T33: 1.13 | U33: =K31 -> 1.3424726
I34: M = K - 2L | J34: At 200% Minimum Capital: Surplus / - Deficit | K34: -394.51642
C35: Risk Based Capital1 | D35: 19 | E35: =E33+SQRT((E30^2)+(E31^2)+(E32^2)) -> 5.2303954e+08 | N35: N = K - L | O35: At 100% Minimum Capital: Surplus / - Deficit | P35: -431 | Q35: -118 | R35: 10 | S35: 11 | T35: 81 | U35: =K33 -> 205.48358
N36: M = K - 2L | O36: At 200% Minimum Capital: Surplus / - Deficit | P36: -1031 | Q36: -718 | R36: -590 | S36: -589 | T36: -519 | U36: =K34 -> -394.51642
C42: Capital Form 1
C43: Total Capital Available | O43: Pioneer General Insurance Limited
C44: Company: | O44: Risk-Based Capital Composition (Amounts in KES Millions)
C45: Reporting Period: | O45: Risk-Based Capital Components (in KES millions) | Q45: Amount
O46: A | P46: Credit Risk | Q46: =U15 -> 320.22895
D47: Line | E47: General Business | O47: B | P47: Market Risk | Q47: =U16 -> 199.41506 | S47: =Q46/Q51 -> 0.61224615
C48: All amounts in KES | E48: [B] | O48: C | P48: Insurance Risk | Q48: =U17 -> 139.86783
C49: Tier-1 Capital | O49: D | P49: Operational Risk Charge | Q49: =U18 -> 120.70143
C50: Fully paid-up ordinary shares | D50: 10 | E50: 600000000 | O50: E | P50: Diversification Benefits | Q50: =U19 -> -257.17373
C51: Share Premiums | D51: 11 | E51: 0 | O51: F = SUM (A .. E) | P51: Risk Based Capital | Q51: =U20 -> 523.03954
C52: Statutory Reserves | D52: 12 | E52: 1031184440
C53: Retained profits/(accumulated losses) | D53: 13 | E53: 62376408
C54: Total Amount | D54: 15 | E54: 1693560848
O55: Risk-Based Capital Composition (Amounts in KES Millions)
C56: Tier-2 Capital | O56: Risk Category | Q56: Amount | R56: % Composition
C57: Irredeemable preference shares | D57: 16 | E57: 100000000 | O57: Market Risk | P57: Investment Property | Q57: 132.79248 | R57: 0.22236047
C58: Capital loan stocks or similar instruments | D58: 17 | E58: 0 | O58: Credit Risk | P58: Investment in Subsidiaries, Associates & Joint Ventures | Q58: 0 | R58: 0
C59: Subordinated loans | D59: 18 | E59: 0 | O59: Credit Risk | P59: Reinsurance Assets | Q59: 9.9135497 | R59: 0.016600199
C60: Convertible preference shares | D60: 19 | E60: 0 | O60: Credit Risk | P60: Premium Receivables | Q60: 98.45644 | R60: 0.16486491
C61: Revaluation reserves | D61: 20 | E61: 0 | O61: Credit Risk | P61: Other debt obligations | Q61: 0 | R61: 0
C62: Available-for-sale reserves | D62: 21 | E62: 0 | O62: Operational Risk | P62: Operational Risk Charge | Q62: 122.23604 | R62: 0.20468377
C63: General reserves | D63: 22 | E63: 0 | O63: Insurance Risk | P63: Premium and Claims Reserves | Q63: 215.74473 | R63: 0.36126368
C64: Total Amount | D64: 23 | E64: 100000000 | O64: Insurance Risk | P64: Catastrophe Risk Charge under Claim Reserves | Q64: 18.051385 | R64: 0.030226972
C66: Deductions
C67: Goodwill & other intangible assets | D67: 24 | E67: 0
C68: Deferred tax income/(expenses) and deferred tax assets | D68: 25 | E68: 46360080
C69: Assets pledged to support credit facilities obtained by an insurer | D69: 26
C70: Unsecured loans | D70: 27 | E70: 0
C71: Credit facilities granted against an insurer's own shares | D71: 28 | E71: 9008176
C72: Other Fixed Assets 1 | D72: 29 | E72: 12413417
C73: Assets with over concentration limits | D73: 30 | E73: 920295593
C74: Total Amount | D74: 31 | E74: =SUM(E67:E73) -> 988077266
C76: Total Capital Available | D76: 32 | E76: =E54+E64-E74 -> 805483582

Sheet BS
A1: NOT UPDATED
A4: Pioneer General Insurance Limited Statement of Financial Position For the Period Ended: | J4: STATEMENT OF FINANCIAL POSITION
B5: 2017 KES | C5: 2018 KES | D5: 2019 KES | E5: 2020 KES | F5: 2021 KES | G5: 2022 KES | H5: 2023 KES | L5: As at 31 December
A6: ASSETS | K6: 2023 | L6: 2022 | M6: 2021 | N6: 2020
K7: Shs | L7: Shs | M7: Shs | N7: Shs
A8: Investment Property | B8: 0 | C8: 0 | D8: 300000000 | E8: 380000000 | F8: 385805800 | G8: =L24 -> 442641593 | H8: =K24 -> 442641593
A9: Property & Equipment | B9: 3366814 | C9: 7635287 | D9: 14359741 | E9: 13112431 | F9: 8936992 | G9: =L21 -> 8761597 | H9: =K21 -> 12413417 | J9: CAPITAL EMPLOYED
A10: Intangible assets | B10: 18074613 | C10: 23329481 | D10: 18599593 | E10: 25388733 | F10: 21048193 | G10: =L22 -> 15483906 | H10: =K22 -> 12766367 | J10: Share capital | K10: 700000000 | L10: 700000000 | M10: 700000000 | N10: 700000000
A11: Receivables arising out of direct insurance arrangements | B11: 108636264 | C11: 135642016 | D11: 165321955 | E11: 1.4084606e+08 | F11: 1.4724106e+08 | G11: =L26 -> 195431609 | H11: =K25 -> 163562753 | J11: Preference shares | N11: 0
A12: Reinsurers' share of insurance contract liabilities | B12: 73125064 | C12: 69177909 | D12: 130036556 | E12: 123242602 | F12: 222465372 | G12: =L27 -> 306351732 | H12: =K27 -> 362076347 | J12: Capital contribution reserve | K12: 1031184440
A13: Deferred acquisition costs | B13: 18123305 | C13: 31156639 | D13: 43706151 | E13: 38250582 | F13: 59950515 | G13: =L28 -> 67790569 | H13: =K28 -> 0 | J13: Retained earnings | K13: 62376408 | L13: 36761184 | M13: -20052637 | N13: 7472417
A14: Other receivables | B14: 24371864 | C14: 89106515 | D14: 105396569 | E14: 39993111 | F14: 140892839 | G14: =L29 -> 102284515 | H14: =K29 -> 228694681
A15: Available for sale asset | H15: =K23 -> 1292220684 | J15: Shareholders’ funds | K15: =SUM(K10:K13) -> 1793560848 | L15: =SUM(L10:L13) -> 736761184 | M15: 679947363 | N15: =SUM(N10:N13) -> 707472417
A16: Right of use assets | B16: 0 | C16: 0 | D16: 13075624 | E16: 6529497 | F16: 6668510 | G16: =L30 -> 9851593 | H16: =K30 -> 26912670
A17: Government securities - 'Held to maturity' | B17: 38008041 | C17: 69026318 | D17: 79265992 | E17: 188311093 | F17: 445261854 | G17: =L31 -> 659147280 | H17: =K31 -> 718914067
A18: Deposits with financial institutions | B18: 623505807 | C18: 682543610 | D18: 390367619 | E18: 257822659 | F18: 252494469 | G18: =L32 -> 179352203 | H18: =K32 -> 120339403 | J18: REPRESENTED BY:
A19: Cash and bank balances | B19: 138761514 | C19: 59194629 | D19: 137165443 | E19: 173140647 | F19: 149417025 | G19: =L33 -> 187825695 | H19: =K33 -> 292348848
A20: Deferred tax | B20: 381476 | C20: 3417682 | D20: 5557363 | E20: 11363792 | F20: 13693349 | G20: =L34 -> 15918627 | H20: =K34 -> 23934603 | J20: Assets
A21: Tax recoverable | B21: 0 | C21: 10556713 | D21: 2267202 | E21: 13686192 | F21: 24720558 | G21: =L35 -> 21763730 | H21: =K35 -> 22425477 | J21: Property and equipment | K21: 12413417 | L21: 8761597 | M21: 8936992 | N21: 13112431
J22: Intangible assets | K22: 12766367 | L22: 15483906 | M22: 21048193 | N22: 25388733
A23: Total Assets | B23: =SUM(B8:B22) -> 1046354762 | C23: =SUM(C8:C22) -> 1180786799 | D23: =SUM(D8:D22) -> 1405119808 | E23: 1.4116874e+09 | F23: 1.8785965e+09 | G23: =SUM(G8:G22) -> 2212604649 | H23: =(SUM(H8:H22)) -> 3719250910 | J23: Available for sale asset | K23: 1292220684
J24: Investment property | K24: 442641593 | L24: 442641593 | M24: 385805800 | N24: 380000000
A25: EQUITY | J25: Receivables arising out of direct insurance | K25: 163562753
J26: arrangements | L26: 195431609 | M26: 1.4724106e+08 | N26: 1.4084606e+08
A27: Share capital | B27: 600000000 | C27: 600000000 | D27: 600000000 | E27: 700000000 | F27: 700000000 | G27: =L10 -> 700000000 | H27: =K10 -> 700000000 | J27: Reinsurers' share of insurance contract liabilities | K27: 362076347 | L27: 306351732 | M27: 222465372 | N27: 123242602
A28: Retained earnings | B28: 3143232 | C28: -23513030 | D28: -2411431 | E28: 7472417 | F28: -20052637 | G28: =L13 -> 36761184 | H28: =K13 -> 62376408 | J28: Deferred acquisition costs | L28: 67790569 | M28: 59950515 | N28: 38250582
A29: Preference Shares | B29: 0 | C29: 0 | D29: 100000000 | E29: 0 | F29: 0 | G29: =L11 -> 0 | H29: =K11 -> 0 | J29: Other receivables | K29: =228524599+K55 -> 228694681 | L29: 102284515 | M29: 140892839 | N29: 39993111
A30: Proposed Dividend | J30: Right of use asset | K30: 26912670 | L30: 9851593 | M30: 6668510 | N30: 6529497
A31: Capital contribution reserve | H31: =K12 -> 1031184440 | J31: Government securities - 'Held to maturity' | K31: 718914067 | L31: 659147280 | M31: 445261854 | N31: 188311093
A32: Total Shareholder's Funds | B32: =SUM(B27:B29) -> 603143232 | C32: =SUM(C27:C29) -> 576486970 | D32: =SUM(D27:D30) -> 697588569 | E32: 707472417 | F32: 679947363 | G32: =SUM(G27:G30) -> 736761184 | H32: =SUM(H27:H31) -> 1793560848 | J32: Deposits with financial institutions | K32: 120339403 | L32: 179352203 | M32: 252494469 | N32: 257822659
J33: Cash and bank balances | K33: 292348848 | L33: 187825695 | M33: 149417025 | N33: 173140647
A34: LIABILITIES | J34: Deferred tax | K34: 23934603 | L34: 15918627 | M34: 13693349 | N34: 11363792
J35: Tax recoverable | K35: 22425477 | L35: 21763730 | M35: 24720558 | N35: 13686192
A36: Insurance contract liabilities | B36: 47589498 | C36: 119994148 | D36: 233713139 | E36: 302904130 | F36: 556949447 | G36: =L41 -> 837024600 | H36: =K41 -> 1655123296
A37: Payables arising out of reinsurance arrangements | B37: 76235461 | C37: 9132447 | D37: 34799518 | E37: 52672060 | F37: 113728635 | G37: =L42 -> 68612216 | H37: =K42 -> 69542498 | J37: Total assets | K37: =SUM(K21:K35) -> 3719250910 | L37: =SUM(L21:L35) -> 2212604649 | M37: 1.8785965e+09 | N37: =SUM(N21:N35) -> 1.4116874e+09
A38: Unearned premium reserve | B38: 155650105 | C38: 274680598 | D38: 348079472 | E38: 311019072 | F38: 492706379 | G38: =L40 -> 542467979 | H38: =K40 -> 0
A39: Other payables | B39: 162160393 | C39: 148664270 | D39: 76685752 | E39: 29306952 | F39: 26790232 | G39: =L43 -> 16596512 | H39: =K43 -> 24952605 | J39: Liabilities
A40: Credit Lease Obligations/Lease Liabilities | B40: 0 | C40: 0 | D40: 14253358 | E40: 8312773.1 | F40: 8474480.1 | G40: =L44 -> 11142158 | H40: =K44 -> 29391384 | J40: Unearned premium reserve | K40: 0 | L40: 542467979 | M40: 492706379 | N40: 311019072
A41: Bank overdraft | B41: 0 | C41: 51828366 | D41: 0 | E41: 0 | F41: 0 | G41: =L45 -> 0 | H41: =K45 -> 146680279 | J41: Insurance contract liabilities | K41: 1655123296 | L41: 837024600 | M41: 556949447 | N41: 302904130
A42: Current tax | B42: 1576073 | C42: 0 | D42: 0 | J42: Payables arising out of reinsurance arrangements | K42: 69542498 | L42: 68612216 | M42: 113728635 | N42: 52672060
J43: Other payables | K43: 24952605 | L43: 16596512 | M43: 26790232 | N43: 29306952
A44: Total Liabilities | B44: =SUM(B36:B42) -> 443211530 | C44: =SUM(C36:C42) -> 604299829 | D44: =SUM(D36:D42) -> 707531239 | E44: 7.0421499e+08 | F44: 1.1986492e+09 | G44: =SUM(G36:G42) -> 1.4758435e+09 | H44: =SUM(H36:H42) -> 1925690062 | J44: Lease liabilities | K44: 29391384 | L44: 11142158 | M44: 8474480.1 | N44: 8312773.1
J45: Bank overdraft | K45: 146680279 | N45: 0
A46: TOTAL EQUITY AND LIABILITIES | B46: =B32+B44 -> 1046354762 | C46: =C32+C44 -> 1180786799 | D46: =D32+D44 -> 1405119808 | E46: 1.4116874e+09 | F46: 1.8785965e+09 | G46: =G32+G44 -> 2.2126046e+09 | H46: =H32+H44 -> 3719250910
B47: =B23-B46 -> 0 | C47: =C23-C46 -> 0 | D47: =D23-D46 -> 0 | G47: =G23-G46 -> -0.11350155 | H47: =H23-H46 -> 0 | J47: Total liabilities | K47: =SUM(K40:K45) -> 1925690062 | L47: =SUM(L40:L45) -> 1.4758435e+09 | M47: 1.1986492e+09 | N47: 7.0421499e+08
J49: Net assets | K49: =K37-K47 -> 1793560848 | L49: =L37-L47 -> 7.3676118e+08 | M49: 6.7994736e+08 | N49: =N37-N47 -> 7.0747242e+08
K51: =K47+K15 -> 3719250910 | L51: =L47+L15 -> 2.2126046e+09 | M51: 1.8785965e+09 | N51: =N47+N15 -> 1.4116874e+09
K55: 170082
A57: Note 22 Deposits with Financial Institutions | B57: 2017 | C57: 2018 | D57: 2019 | E57: 2020 | F57: 2021 | G57: 2022 | H57: 2023
F58: Kshs | G58: Kshs | H58: Kshs
A59: Total Deposits with Financial Institutions | B59: 723505807 | C59: 724748918 | D59: 452984592 | E59: 420382493 | F59: 368448460 | G59: 326356432 | H59: 391972688
A60: Maturing within 90 days | B60: -100000000 | C60: -38800000 | D60: -60266018 | E60: -159169188 | F60: -113415779 | G60: -145078166 | H60: -269697910
A61: Expected Credit Losses | C61: -3405308 | D61: -2350955 | E61: -3390646 | F61: -2538212 | G61: -1926063 | H61: -1935375
A63: Net Deposits | B63: =SUM(B59:B61) -> 623505807 | C63: =SUM(C59:C61) -> 682543610 | D63: =SUM(D59:D61) -> 390367619 | E63: =SUM(E59:E61) -> 257822659 | F63: =SUM(F59:F61) -> 252494469 | G63: =SUM(G59:G61) -> 179352203 | H63: =SUM(H59:H61) -> 120339403
B65: =B18 -> 623505807 | C65: =C18 -> 682543610 | D65: =D18 -> 390367619 | E65: =E18 -> 257822659 | F65: =F18 -> 252494469 | G65: =G18 -> 179352203 | H65: =H18 -> 120339403
C66: =C63+-C61 -> 685948918

Sheet RA
B4: PIONEER GENERAL INSURANCE LIMITED
B5: REVENUE ACCOUNT | I5: =(I44+J44)/O44 -> 0.68708821
B6: FOR THE PERIOD ENDED 31 DECEMBER 2023
B7: Business Class | D7: ENGINEERING | E7: FIRE DOMESTIC | F7: FIRE INDUSTRIAL | G7: LIABILITY | H7: MARINE | I7: MOTOR PRIVATE | J7: MOTOR COMMERCIAL | K7: PERSONAL ACCIDENT | L7: THEFT | M7: WORKMEN'S COMPENSATION | N7: MISCELLANEOUS | O7: TOTAL
A8: 1 | B8: 2023 | C8: Aviation | D8: Engineering | E8: Fire Domestic | F8: Fire Industrial | G8: Liability | H8: Marine | I8: Motor Private | J8: Motor Commercial | K8: Personal Accident | L8: Theft | M8: Workmen's Compensation | N8: Miscellaneous | O8: Total
B9: Gross premiums written | D9: 32682894 | E9: 10785848 | F9: 76255014 | G9: 39903688 | H9: 12032183 | I9: 915640011 | J9: 371117040 | K9: 9359638 | L9: 16957370 | M9: 105385636 | N9: 5450653 | O9: 1595569975
B10: Unearned Premium Reserve BF | D10: -16143912 | E10: -4135577.1 | F10: -23677359 | G10: -11939999 | H10: -1223725.8 | I10: -2.9624602e+08 | J10: -1.068744e+08 | K10: -2188534.8 | L10: -5580636.2 | M10: -72357819 | N10: -2099997.9 | O10: -5.4246798e+08
B11: Unearned Premium Reserve CF | D11: -10245732 | E11: -4465462.1 | F11: -34283461 | G11: -16879343 | H11: -3435533.7 | I11: -3.3471451e+08 | J11: -1.2299823e+08 | K11: -3161035.2 | L11: -6435019.5 | M11: -43862824 | N11: -2851496.2 | O11: -5.8333265e+08
B12: Change in gross unearned premiums | D12: -5898179.6 | E12: 329885.05 | F12: 10606102 | G12: 4939344 | H12: 2211808 | I12: 38468493 | J12: 16123831 | K12: 972500.47 | L12: 854383.3 | M12: -28494995 | N12: 751498.37 | O12: 40864669
B14: Gross premiums earned | D14: 33029948 | E14: 10633062 | F14: 68236165 | G14: 34687472 | H14: 10738309 | I14: 8.7738572e+08 | J14: 3.5517281e+08 | K14: 8916891.8 | L14: 16415974 | M14: 1.4812941e+08 | N14: 3236633.8 | O14: 1.5665824e+09
B15: Less: reinsurers premiums ceded | D15: 10419991 | E15: 1309646.2 | F15: 44174431 | G15: 1934251.6 | H15: 2621435.4 | I15: 5717532.6 | J15: 2328901 | K15: 1693881.4 | L15: 3834010.7 | M15: 71303468 | N15: 734492.1 | O15: 1.4607204e+08
B17: Net premiums earned | D17: 22609956 | E17: 9323415.7 | F17: 24061734 | G17: 32753220 | H17: 8116873.9 | I17: 8.7166818e+08 | J17: 3.5284391e+08 | K17: 7223010.4 | L17: 12581963 | M17: 76825937 | N17: 2502141.7 | O17: 1.4205103e+09
B19: Gross claims paid | D19: 1418131 | E19: 1842476 | F19: 32243776 | G19: 4746034 | H19: 3277913 | I19: 611465508 | J19: 290849318 | K19: 1250041 | L19: 702509 | M19: 64293934 | N19: 30087 | O19: 1012119727
B20: Changes in gross outstanding claims | D20: 0 | E20: 0 | F20: 0 | G20: 0 | H20: 0 | I20: 0 | J20: 0 | K20: 0 | L20: 0 | M20: 0 | N20: 0 | O20: 0
B21: IBNR Reserve | D21: 751918.03 | E21: 28888.249 | F21: 2054879.9 | G21: 126089.58 | H21: 62400 | I21: 10949880 | J21: 6490819 | K21: 69556.343 | L21: 0 | M21: 94980538 | N21: 0 | O21: 1.1551497e+08
B22: Less: reinsurance recoverable | D22: -797950 | E22: 0 | F22: -28519914 | G22: 0 | H22: 0 | I22: -21259988 | J22: -37072783 | K22: -503069 | L22: 0 | M22: -39776532 | N22: 0 | O22: -127930236
O23: 1012119727
B24: Net claims incurred | D24: 1372099 | E24: 1871364.2 | F24: 5547302.9 | G24: 1114075.6 | H24: 3340313 | I24: 5.5795705e+08 | J24: 2.4418676e+08 | K24: 816528.34 | L24: 702509 | M24: 1.1949794e+08 | N24: 30087 | O24: 9.3643603e+08
B26: Commissions earned | D26: -4791022 | E26: -383051 | F26: -14758027 | G26: -798813 | H26: -456333 | I26: -452926 | J26: -167579 | K26: -339314 | L26: -865402 | M26: -17206177 | N26: -127351 | O26: -40345995
B27: Commissions payable | D27: 7078207 | E27: 2042367 | F27: 19197066 | G27: 7889856 | H27: 2113009 | I27: 89828117 | J27: 36210655 | K27: 1820675 | L27: 2861757 | M27: 21057724 | N27: 920816 | O27: 188077324
B28: Expenses of management | D28: 9043615.1 | E28: 2984529.4 | F28: 21100365 | G28: 11041666 | H28: 3329400.1 | I28: 2.5336483e+08 | J28: 1.0269102e+08 | K28: 2589885.8 | L28: 4692238.3 | M28: 29161038 | N28: 1508238.8 | O28: 441506822
B30: Total expenses and commissions | D30: 11330800 | E30: 4643845.4 | F30: 25539404 | G30: 18132709 | H30: 4986076.1 | I30: 3.4274002e+08 | J30: 1.3873409e+08 | K30: 4071246.8 | L30: 6688593.3 | M30: 33012585 | N30: 2301703.8 | O30: 592181076
B32: Underwriting profit/(loss) | D32: 8594035.6 | E32: 2879604.7 | F32: -4195457 | G32: 14516284 | H32: 182329.9 | I32: -25324147 | J32: -28618400 | K32: 2522580.5 | L32: 5346092.9 | M32: -81419506 | N32: 352751.67 | O32: -1.0516383e+08
B35: Key Ratios | C35: Aviation | D35: Engineering | E35: Fire Domestic | F35: Fire Industrial | G35: Liability | H35: Marine | I35: Motor Private | J35: Motor Commercial | K35: Personal Accident | L35: Theft | M35: Workmen's Compensation | N35: Miscellaneous | O35: Total
B36: Loss Ratio | C36: 0 | D36: =D24/D17 -> 0.060685612 | E36: =E24/E17 -> 0.2007166 | F36: =F24/F17 -> 0.2305446 | G36: =G24/G17 -> 0.034014231 | H36: =H24/H17 -> 0.41152703 | I36: =I24/I17 -> 0.64010258 | J36: =J24/J17 -> 0.6920532 | K36: =K24/K17 -> 0.11304543 | ... O36: =O24/O17 -> 0.65922507
B37: Commission Ratio | C37: 0 | D37: =SUM(D26:D27)/D17 -> 0.10115831 | E37: =SUM(E26:E27)/E17 -> 0.17797297 | F37: =SUM(F26:F27)/F17 -> 0.18448541 | G37: =SUM(G26:G27)/G17 -> 0.21649911 | H37: =SUM(H26:H27)/H17 -> 0.20410272 | I37: =SUM(I26:I27)/I17 -> 0.1025335 | J37: =SUM(J26:J27)/J17 -> 0.1021502 | K37: =SUM(K26:K27)/K17 -> 0.20508914 | ... O37: =SUM(O26:O27)/O17 -> 0.10399877
B38: Management Expense Ratio | C38: 0 | D38: =D28/D17 -> 0.39998375 | E38: =E28/E17 -> 0.32011116 | F38: =F28/F17 -> 0.87692619 | G38: =G28/G17 -> 0.33711696 | H38: =H28/H17 -> 0.41018256 | I38: =I28/I17 -> 0.2906666 | J38: =J28/J17 -> 0.29103809 | K38: =K28/K17 -> 0.35856044 | ... O38: =O28/O17 -> 0.31080859
B39: Combined Ratio | C39: =SUM(C36:C38) -> 0 | D39: =SUM(D36:D38) -> 0.56182767 | E39: =SUM(E36:E38) -> 0.69880073 | F39: =SUM(F36:F38) -> 1.2919562 | G39: =SUM(G36:G38) -> 0.5876303 | H39: =SUM(H36:H38) -> 1.0258123 | I39: =SUM(I36:I38) -> 1.0333027 | J39: =SUM(J36:J38) -> 1.0852415 | ... O39: =SUM(O36:O38) -> 1.0740324
B42: Business Class | D42: ENGINEERING | E42: FIRE DOMESTIC | F42: FIRE INDUSTRIAL | G42: LIABILITY | H42: MARINE | I42: MOTOR PRIVATE | J42: MOTOR COMMERCIAL | K42: PERSONAL ACCIDENT | L42: THEFT | M42: WORKMEN'S COMPENSATION | N42: MISCELLANEOUS | O42: TOTAL
B43: 2022 | C43: Aviation | D43: Engineering | E43: Fire Domestic | F43: Fire Industrial | G43: Liability | H43: Marine | I43: Motor Private | J43: Motor Commercial | K43: Personal Accident | L43: Theft | M43: Workmen's Compensation | N43: Miscellaneous
A44: 2 | B44: Gross premiums written | C44: -111821 | D44: 40945277 | E44: 8873879 | F44: 78279579 | G44: 34436388 | H44: 12488935 | I44: 818548382 | J44: 305362726 | K44: 7134489 | L44: 14671830 | M44: 295958506 | N44: 19171387 | O44: 1635759557
A45: 3 | B45: Unearned Premium Reserve BF | C45: 36501 | D45: 4022297 | E45: 2949289 | F45: 5743029 | G45: 10442870 | H45: 1144553 | I45: 246265733 | J45: 97513211 | K45: 2110576 | L45: 4159649 | M45: 48318198 | N45: 5393216 | O45: 428099122
A46: 4 | B46: Unearned Premium Reserve CF | C46: 0 | D46: -8460532 | E46: -3755063 | F46: -8679384 | G46: -10703736 | H46: -1121253 | I46: -295381175 | J46: -106631381 | K46: -1895752 | L46: -4678444 | M46: -60178045 | N46: -3641144 | O46: -505125909
A47: 5 | B47: Change in gross unearned premiums | C47: 36501 | D47: -4438236 | E47: -805775 | F47: -2936355 | G47: -260866 | H47: 23300 | I47: -49115442 | J47: -9118169 | K47: 214824 | L47: -518795 | M47: -11859847 | N47: 1752073 | O47: -77026787
A48: 6
A49: 7 | B49: Gross premiums earned | C49: -75320 | D49: 36507041 | E49: 8068104 | F49: 75343224 | G49: 34175522 | H49: 12512235 | I49: 769432940 | J49: 296244557 | K49: 7349313 | L49: 14153035 | M49: 284098659 | N49: 20923460 | O49: 1558732770
A50: 8 | B50: Less: reinsurers premiums ceded | C50: 111821 | D50: -21114752 | E50: -2365468 | F50: -56885899 | G50: -3191826.3 | H50: -3302989.6 | I50: -10223351 | J50: -3628201.7 | K50: -1006278.2 | L50: -3868369.7 | M50: -37255943 | N50: -9453784.6 | O50: -152185042
A51: 9
A52: 10 | B52: Net premiums earned | C52: 36501 | D52: 15392289 | E52: 5702636 | F52: 18457325 | G52: 30983696 | H52: 9209245 | I52: 759209589 | J52: 292616355 | K52: 6343035 | L52: 10284665 | M52: 246842716 | N52: 11469675 | O52: 1406547728
A53: 11
A54: 12 | B54: Gross claims paid | C54: 6090024 | D54: 3851902 | E54: 435021 | F54: 2535775 | G54: 3684013 | H54: 3262515 | I54: 527547701 | J54: 168089826 | K54: 506105 | L54: 600134 | M54: 18623238 | N54: 299905 | O54: 735526159
A55: 13 | B55: Changes in gross outstanding claims | C55: -7500000 | D55: 1727951 | E55: 234697 | F55: 8148580 | G55: 9592673 | H55: -500000 | I55: 12439577 | J55: -2508160 | K55: 647031 | L55: -280449 | M55: 199125327 | N55: 133682 | O55: 221260909
A56: 14 | B56: MDPS
A57: 15 | B57: Less: reinsurance recoverable | C57: 1268978 | D57: -870641 | E57: -82569 | F57: -7502262 | G57: -460000 | H57: -2069470 | I57: -11376728 | J57: -9402182 | K57: -611341 | L57: 0 | M57: -21684872 | N57: 0 | O57: -52791087
A58: 16 | O58: =SUM(O54:O55) -> 956787068
A59: 17 | B59: Net claims incurred | C59: -140998 | D59: 4709212 | E59: 587149 | F59: 3182093 | G59: 12816686 | H59: 693045 | I59: 528610550 | J59: 156179484 | K59: 541795 | L59: 319685 | M59: 196063693 | N59: 433587 | O59: 903995981
A60: 18
A61: 19 | B61: Commissions earned | C61: -240120 | D61: -4787424 | E61: -851666 | F61: -18003397 | G61: -717955 | H61: -875711 | I61: -324933 | J61: -95895 | K61: -434693 | L61: -871780 | M61: -10169829 | N61: -9570788 | O61: -46944191
A62: 20 | B62: Commissions payable | C62: 136274 | D62: 8274345 | E62: 1790008 | F62: 18953524 | G62: 6714852 | H62: 2468854 | I62: 75558351 | J62: 29077168 | K62: 1540635 | L62: 2295049 | M62: 56011414 | N62: 18811649 | O62: 221632123
A63: 21 | B63: Expenses of management | C63: -24931.673 | D63: 9129181.9 | E63: 1978525 | F63: 17453259 | G63: 7677956.4 | H63: 2784540 | I63: 1.8250401e+08 | J63: 68083845 | K63: 1590709.7 | L63: 3271239.4 | M63: 65987074 | N63: 4274463.2 | O63: 3.6470987e+08
A64: 22
A65: 23 | B65: Total expenses and commissions | C65: -128778 | D65: 12616103 | E65: 2916867 | F65: 18403386 | G65: 13674853 | H65: 4377683 | I65: 257737424 | J65: 97065118 | K65: 2696652 | L65: 4694508 | M65: 111828659 | N65: 13515324 | O65: 539397800
A66: 24
A67: 25 | B67: Underwriting profit/(loss) | C67: 306277 | D67: -1933026 | E67: 2198620 | F67: -3128154 | G67: 4492157 | H67: 4138517 | I67: -27138385 | J67: 39371753 | K67: 3104588 | L67: 5270472 | M67: -61049636 | N67: -2479236 | O67: -36846053
B70: Key Ratios | C70: Aviation | D70: Engineering | E70: Fire Domestic | F70: Fire Industrial | G70: Liability | H70: Marine | I70: Motor Private | J70: Motor Commercial | K70: Personal Accident | L70: Theft | M70: Workmen's Compensation | N70: Miscellaneous | O70: Total
B71: Loss Ratio | C71: =C59/C52 -> -3.8628531 | D71: =D59/D52 -> 0.30594618 | E71: =E59/E52 -> 0.10296098 | F71: =F59/F52 -> 0.17240272 | G71: =G59/G52 -> 0.41365904 | H71: =H59/H52 -> 0.075255355 | I71: =I59/I52 -> 0.69626432 | J71: =J59/J52 -> 0.53373464 | ... O71: =O59/O52 -> 0.64270551
B72: Commission Ratio | C72: =SUM(C61:C62)/C52 -> -2.8450179 | D72: =SUM(D61:D62)/D52 -> 0.22653687 | E72: =SUM(E61:E62)/E52 -> 0.16454531 | F72: =SUM(F61:F62)/F52 -> 0.051476961 | G72: =SUM(G61:G62)/G52 -> 0.19355009 | H72: =SUM(H61:H62)/H52 -> 0.17299388 | I72: =SUM(I61:I62)/I52 -> 0.099094399 | J72: =SUM(J61:J62)/J52 -> 0.099041877 | ... O72: =SUM(O61:O62)/O52 -> 0.12419623
B73: Management Expense Ratio | C73: =C63/C52 -> -0.68304082 | D73: =D63/D52 -> 0.59310099 | E73: =E63/E52 -> 0.34694921 | F73: =F63/F52 -> 0.94560067 | G73: =G63/G52 -> 0.24780634 | H73: =H63/H52 -> 0.30236354 | I73: =I63/I52 -> 0.24038686 | J73: =J63/J52 -> 0.23267272 | ... O73: =O63/O52 -> 0.25929434
B74: Combined Ratio | C74: =SUM(C71:C73) -> -7.3909118 | D74: =SUM(D71:D73) -> 1.125584 | E74: =SUM(E71:E73) -> 0.6144555 | F74: =SUM(F71:F73) -> 1.1694803 | G74: =SUM(G71:G73) -> 0.85501547 | H74: =SUM(H71:H73) -> 0.55061278 | I74: =SUM(I71:I73) -> 1.0357456 | J74: =SUM(J71:J73) -> 0.86544924 | ... O74: =SUM(O71:O73) -> 1.0261961
I75: =SUM(I59:J59)/SUM(I52:J52) -> 0.65104881
B77: Business Class | D77: ENGINEERING | E77: FIRE DOMESTIC | F77: FIRE INDUSTRIAL | G77: LIABILITY | H77: MARINE | I77: MOTOR PRIVATE | J77: MOTOR COMMERCIAL | K77: PERSONAL ACCIDENT | L77: THEFT | M77: WORKMEN'S COMPENSATION | N77: MISCELLANEOUS | O77: TOTAL
B78: 2021 | C78: Aviation | D78: Engineering | E78: Fire Domestic | F78: Fire Industrial | G78: Liability | H78: Marine | I78: Motor Private | J78: Motor Commercial | K78: Personal Accident | L78: Theft | M78: Workmen's Compensation | N78: Miscellaneous
B79: Gross premiums written | C79: 1898815 | D79: 19446301 | E79: 10013349 | F79: 58149488 | G79: 41785885 | H79: 33832956 | I79: 634983591 | J79: 241086140 | K79: 6504649 | L79: 16801809 | M79: 249244290 | N79: 89810994 | O79: 1403558267
B80: Unearned Premium Reserve BF | C80: 0 | D80: 7496745 | E80: 3966708 | F80: 9384890 | G80: 9836782 | H80: 290544 | I80: 166095657 | J80: 61181558 | K80: -5569462 | L80: 2815620 | M80: 6630348 | N80: 1261880 | O80: 263391270
B81: Unearned Premium Reserve CF | C81: -36501 | D81: -4022297 | E81: -2949289 | F81: -5743029 | G81: -10442870 | H81: -1144553 | I81: -246265733 | J81: -97513211 | K81: -2110576 | L81: -4159649 | M81: -48318198 | N81: -5393216 | O81: -428099122
B82: Change in gross unearned premiums | C82: -36501 | D82: 3474448 | E82: 1017419 | F82: 3641861 | G82: -606088 | H82: -854009 | I82: -80170076 | J82: -36331653 | K82: -7680038 | L82: -1344029 | M82: -41687850 | N82: -4131336 | O82: -164707852
B84: Gross premiums earned | C84: 1862314 | D84: 22920749 | E84: 11030768 | F84: 61791349 | G84: 41179797 | H84: 32978947 | I84: 554813515 | J84: 204754487 | K84: -1175389 | L84: 15457780 | M84: 207556440 | N84: 85679658 | O84: 1238850415
B85: Less: reinsurers premiums ceded | C85: -1840890 | D85: -11234259 | E85: -4670714 | F85: -44759903 | G85: -7134499.1 | H85: -17553009 | I85: -25708864 | J85: -9292164.3 | K85: -875063 | L85: -1758017.2 | M85: -41984254 | N85: -76168673 | O85: -242980310
B87: Net premiums earned | C87: 21424 | D87: 11686490 | E87: 6360054 | F87: 17031446 | G87: 34045298 | H87: 15425938 | I87: 529104651 | J87: 195462323 | K87: -2050452 | L87: 13699763 | M87: 165572186 | N87: 9510985 | O87: 995870106
B89: Gross claims paid | C89: 0 | D89: 4501917 | E89: 1095706 | F89: 2110499 | G89: 1234829 | H89: 383343 | I89: 395798468 | J89: 105660587 | K89: 1198206 | L89: 82650 | M89: 7736087 | N89: 441696 | O89: 520243988
B90: Changes in gross outstanding claims | C90: 7500000 | D90: -1598182 | E90: -289535 | F90: 259465 | G90: 190169 | H90: 525035 | I90: 84068223 | J90: 40747878 | K90: -343126 | L90: 608014 | M90: 78588410 | N90: 554012 | O90: 210810363
B91: MDPS
B92: Less: reinsurance recoverable | C92: -6750000 | D92: 129976 | E92: -29405 | F92: -1911513 | G92: 709 | H92: 0 | I92: -14009312 | J92: -8243622 | K92: 24164 | L92: 0 | M92: -5037682 | N92: 0 | O92: -35826685
O93: =SUM(O89:O90) -> 731054351
B94: Net claims incurred | C94: 750000 | D94: 3033711 | E94: 776766 | F94: 458451 | G94: 1425707 | H94: 908378 | I94: 465857379 | J94: 138164843 | K94: 879244 | L94: 690664 | M94: 81286815 | N94: 995708 | O94: 695227666
B96: Commissions earned | C96: -39319 | D96: -5282518 | E96: -847316 | F96: -19866207 | G96: -967149 | H96: -6222262 | I96: -867842 | J96: -193050 | K96: -5927440 | L96: -244367 | M96: -23699978 | N96: -18992054 | O96: -83149502
B97: Commissions payable | C97: 42427 | D97: 4290900 | E97: 1755840 | F97: 15596057 | G97: 7739825 | H97: 6593356 | I97: 54822561 | J97: 20741769 | K97: 1177401 | L97: 2988064 | M97: 52471421 | N97: 6635991 | O97: 174855612
B98: Expenses of management | C98: 413456.85 | D98: 4234328.4 | E98: 2180353.4 | F98: 12661741 | G98: 9098653.7 | H98: 7366945.8 | I98: 1.3826429e+08 | J98: 52495222 | K98: 1416352.7 | L98: 3658504.4 | M98: 54271616 | N98: 19555865 | O98: 305617332
B100: Total expenses and commissions | C100: 416565 | D100: 3242710 | E100: 3088877 | F100: 8391591 | G100: 15871330 | H100: 7738040 | I100: 192219012 | J100: 73043941 | K100: -3333686 | L100: 6402201 | M100: 83043059 | N100: 7199802 | O100: 397323442
B102: Underwriting profit/(loss) | C102: -1145141 | D102: 5410069 | E102: 2494411 | F102: 8181404 | G102: 16748261 | H102: 6779520 | I102: -128971740 | J102: -15746461 | K102: 403990 | L102: 6606898 | M102: 1242312 | N102: 1315475 | O102: -96681002
B105: Key Ratios | C105: Aviation | D105: Engineering | E105: Fire Domestic | F105: Fire Industrial | G105: Liability | H105: Marine | I105: Motor Private | J105: Motor Commercial | K105: Personal Accident | L105: Theft | M105: Workmen's Compensation | N105: Miscellaneous | O105: Total
B106: Loss Ratio | C106: 35.007468 | D106: 0.25959129 | E106: 0.12213198 | F106: 0.026917914 | G106: 0.041876767 | H106: 0.058886403 | I106: 0.88046359 | J106: 0.70686177 | K106: -0.42880497 | L106: 0.050414303 | M106: 0.49094487 | N106: 0.10469031 | O106: 0.69811079
B107: Commission Ratio | C107: 0.14507095 | D107: -0.084851653 | E107: 0.14284847 | F107: -0.25072152 | G107: 0.19893132 | H107: 0.024056495 | I107: 0.10197362 | J107: 0.1051288 | K107: 2.3165814 | L107: 0.20027332 | M107: 0.17376978 | N107: -1.299136 | O107: 0.092086417
B108: Management Expense Ratio | C108: 19.29877 | D108: 0.36232679 | E108: 0.34281995 | F108: 0.74343312 | G108: 0.26725141 | H108: 0.47756874 | I108: 0.26131748 | J108: 0.26856952 | K108: -0.69075143 | L108: 0.26704873 | M108: 0.3277822 | N108: 2.0561346 | O108: 0.30688473
B109: Combined Ratio | C109: 54.451309 | D109: 0.53706642 | E109: 0.6078004 | F109: 0.51962952 | G109: 0.50805949 | H109: 0.56051164 | I109: 1.2437547 | J109: 1.0805601 | K109: 1.197025 | L109: 0.51773636 | M109: 0.99249685 | N109: 0.86168891 | O109: 1.0970819
B112: Business Class | D112: ENGINEERING | E112: FIRE DOMESTIC | F112: FIRE INDUSTRIAL | G112: LIABILITY | H112: MARINE | I112: MOTOR PRIVATE | J112: MOTOR COMMERCIAL | K112: PERSONAL ACCIDENT | L112: THEFT | M112: WORKMEN'S COMPENSATION | N112: MISCELLANEOUS | O112: TOTAL
B113: 2020 | D113: Engineering | E113: Fire Domestic | F113: Fire Industrial | G113: Liability | H113: Marine | I113: Motor Private | J113: Motor Commercial | K113: Personal Accident | L113: Theft | M113: Workmen's Compensation | N113: Miscellaneous
B114: Gross premiums written | D114: 19023323 | E114: 8870728 | F114: 65626886 | G114: 35104960 | H114: 7009653 | I114: 455073607 | J114: 174755327 | K114: 6368504 | L114: 15657691 | M114: 50737276 | N114: 45588151 | O114: 883816106
B115: Unearned Premium Reserve BF | D115: 5819242 | E115: 6588922 | F115: 6002214 | G115: 12035019 | H115: 3002242 | I115: 169897377 | J115: 68094010 | K115: 1893320 | L115: 2849526 | M115: 17161391 | N115: -415031 | O115: 292928232
B116: Unearned Premium Reserve CF | D116: -7496745 | E116: -3966708 | F116: -9384890 | G116: -9836782 | H116: -290544 | I116: -166095657 | J116: -61181558 | K116: 5569462 | L116: -2815620 | M116: -6630348 | N116: -1261880 | O116: -263391270
B117: Change in gross unearned premiums | D117: -1677503 | E117: 2622214 | F117: -3382676 | G117: 2198237 | H117: 2711698 | I117: 3801720 | J117: 6912452 | K117: 7462782 | L117: 33906 | M117: 10531043 | N117: -1676911 | O117: 29536962
B119: Gross premiums earned | D119: 17345820 | E119: 11492942 | F119: 62244210 | G119: 37303197 | H119: 9721351 | I119: 458875327 | J119: 181667779 | K119: 13831286 | L119: 15691597 | M119: 61268319 | N119: 43911240 | O119: 913353068
B120: Less: reinsurers premiums ceded | D120: -8531513 | E120: -1237495 | F120: -49023696 | G120: -2828485 | H120: -910933 | I120: -27745087 | J120: -35920980 | K120: -2160672 | L120: -185752 | M120: -32732279 | N120: -41842170 | O120: -203119062
B122: Net premiums earned | D122: 8814307 | E122: 10255447 | F122: 13220514 | G122: 34474712 | H122: 8810418 | I122: 431130240 | J122: 145746799 | K122: 11670614 | L122: 15505845 | M122: 28536040 | N122: 2069070 | O122: 710234006
B124: Gross claims paid | D124: 499072 | E124: 680167 | F124: 12644048 | G124: 885260 | H124: 379436 | I124: 269685341 | J124: 79105331 | K124: 8265790 | L124: 40000 | M124: 26543951 | N124: 3926943 | O124: 402655339
B125: Changes in gross outstanding claims | D125: 2131583 | E125: 190858 | F125: -2940270 | G125: -2301886 | H125: -2243557 | I125: 45756163 | J125: 26697305 | K125: -11265499 | L125: -132227 | M125: -10104969 | N125: -1675989 | O125: 44111512
B126: MDPS
B127: Less: reinsurance recoverable | D127: -374632 | E127: -63039 | F127: -4185233 | G127: 0 | H127: 57230 | I127: -10530109 | J127: -5720272 | K127: -5287423 | L127: 0 | M127: -1440141 | N127: 0 | O127: -27543619
O128: =SUM(O124:O125) -> 446766851
B129: Net claims incurred | D129: 2256023 | E129: 807986 | F129: 5518545 | G129: -1416626 | H129: -1806891 | I129: 304911395 | J129: 100082364 | K129: -8287132 | L129: -92227 | M129: 14998841 | N129: 2250954 | O129: 419223231
...

Sheet Industry_Results
AH1: Projected Figures for 2022
B2: Industry Statistics | AH2: Motor Commercial and Motor Commercial PSV figures have been grouped
AH3: Industry Statistics
B4: Source: 2021 IRA Annual Reports
B5: Gross written Premiums - Industry Statistics in Billions | K5: Gross written Premiums - Industry Statistics in Billions | T5: 2022 Gross written Premiums Factors - Industry Statistics | AA5: Q3/Q4 Grossing Up Factors | AB5: Q4/Q3 grossing up factors | AH5: Gross written Premiums - Industry Statistics in Millions | AP5: Gross written Premiums - Industry Statistics in Millions
B6: Class of Business | C6: 2018 | D6: =C6+1 -> 2019 | E6: =D6+1 -> 2020 | F6: =E6+1 -> 2021 | G6: 2022 | H6: *2023 | L6: Q1 2023 | M6: Q2 2023 | N6: Q3 2023 | O6: *Q4 2023 | P6: Q3/Q4 Growth | T6: Class of Business | U6: Q2 | V6: Q3 | W6: Q4 | X6: Average | Z6: 2022 | AA6: 2021 | AB6: 2020 | AC6: 2019 | AD6: 2018 | AE6: 2017 | AH6: Class of Business | AI6: Q1 2017 | AJ6: Q2 2017 | AK6: Q3 2017 | AL6: Q4 2017 | AP6: Class of Business | AQ6: Q1 2018 | AR6: Q2 2018 | AS6: Q3 2018 | AT6: Q4 2018
B7: Aviation | C7: 2134254 | D7: 2109320 | E7: 2963413 | F7: 3094410 | G7: 3564550 | H7: =_xlfn.XLOOKUP(B7,$K$7:$K$19,$O$7:$O$19) -> 5251175.2 | K7: Aviation | L7: 1229480 | M7: 2608203 | N7: 3849383 | O7: =N7*(1+$P7) -> 5251175.2 | P7: =X7 -> 0.36416024 | T7: Aviation | U7: =IFERROR((M7-L7)/L7,0) -> 1.1213871 | V7: =IFERROR((N7-M7)/M7,0) -> 0.47587554 | W7: =IFERROR((O7-N7)/N7,0) -> 0.36416024 | X7: =AVERAGE(Z7:AD7) -> 0.36416024 | Z7: =(AT46/AS46)-1 -> 0.30291053 | AA7: =(AL46/AK46)-1 -> 0.29239327 | AB7: =(AT27/AS27)-1 -> 0.42826791 | AC7: =(AL27/AK27)-1 -> 0.28845052 | AD7: =(AT7/AS7)-1 -> 0.50877899 | AE7: =(AL7/AK7)-1 -> 0.35758364 | AH7: Aviation | AI7: 496.976 | AJ7: 852.893 | AK7: 1217.897 | AL7: 1653.397 | AP7: Aviation | AQ7: 497.007 | AR7: 1256.67 | AS7: 1447.092 | AT7: 2183.342
B8: Engineering | C8: 3691508 | D8: 3502268 | E8: 3250661 | F8: 4283167 | G8: 5064942 | H8: =_xlfn.XLOOKUP(B8,$K$7:$K$19,$O$7:$O$19) -> 4994202.7 | K8: Engineering | L8: 1649360 | M8: 2563482 | N8: 4147670 | O8: =N8*(1+$P8) -> 4994202.7 | P8: =X8 -> 0.20409838 | T8: Engineering | U8: =IFERROR((M8-L8)/L8,0) -> 0.55422831 | V8: =IFERROR((N8-M8)/M8,0) -> 0.61798288 | W8: =IFERROR((O8-N8)/N8,0) -> 0.20409838 | X8: =AVERAGE(Z8:AD8) -> 0.20409838 | Z8: =(AT47/AS47)-1 -> 0.12449371 | AA8: =(AL47/AK47)-1 -> 0.18657249 | AB8: =(AT28/AS28)-1 -> 0.24354574 | AC8: =(AL28/AK28)-1 -> 0.22650787 | AD8: =(AT8/AS8)-1 -> 0.2393721 | AE8: =(AL8/AK8)-1 -> 0.18113372 | AH8: Engineering | AI8: 1111.15 | AJ8: 2085.758 | AK8: 3608.7387 | AL8: 4262.403 | AP8: Engineering | AQ8: 1076.551 | AR8: 2066.696 | AS8: 3099.225 | AT8: 3841.093
B9: Fire Domestic | C9: 1595804 | D9: 1672639 | E9: 1759941 | F9: 1770893 | G9: 1815381 | H9: =_xlfn.XLOOKUP(B9,$K$7:$K$19,$O$7:$O$19) -> 2061651.2 | K9: Fire Domestic | L9: 680608 | M9: 1128076 | N9: 1641782 | O9: =N9*(1+$P9) -> 2061651.2 | P9: =X9 -> 0.25573993 | T9: Fire Domestic | U9: =IFERROR((M9-L9)/L9,0) -> 0.65745334 | V9: =IFERROR((N9-M9)/M9,0) -> 0.45538244 | W9: =IFERROR((O9-N9)/N9,0) -> 0.25573993 | X9: =AVERAGE(Z9:AD9) -> 0.25573993 | Z9: =(AT48/AS48)-1 -> 0.23533424 | AA9: =(AL48/AK48)-1 -> 0.2532091 | AB9: =(AT29/AS29)-1 -> 0.25705188 | AC9: =(AL29/AK29)-1 -> 0.27478718 | AD9: =(AT9/AS9)-1 -> 0.25831727 | AE9: =(AL9/AK9)-1 -> 0.26259721 | AH9: Fire Domestic | AI9: 567.121 | AJ9: 891.813 | AK9: 1255.7829 | AL9: 1585.548 | AP9: Fire Domestic | AQ9: 567.059 | AR9: 909.451 | AS9: 1272.052 | AT9: 1600.645
B10: Fire Industrial | C10: 10824386 | D10: 10870577 | E10: 10817704 | F10: 12949770 | G10: 16828541 | H10: =_xlfn.XLOOKUP(B10,$K$7:$K$19,$O$7:$O$19) -> 20404972 | K10: Fire Industrial | L10: 7389065 | M10: 11302519 | N10: 16915976 | O10: =N10*(1+$P10) -> 20404972 | P10: =X10 -> 0.20625452 | T10: Fire Industrial | U10: =IFERROR((M10-L10)/L10,0) -> 0.52962777 | V10: =IFERROR((N10-M10)/M10,0) -> 0.49665539 | W10: =IFERROR((O10-N10)/N10,0) -> 0.20625452 | X10: =AVERAGE(Z10:AD10) -> 0.20625452 | Z10: =(AT49/AS49)-1 -> 0.16994113 | AA10: =(AL49/AK49)-1 -> 0.19610133 | AB10: =(AT30/AS30)-1 -> 0.20532341 | AC10: =(AL30/AK30)-1 -> 0.20854477 | AD10: =(AT10/AS10)-1 -> 0.25136195 | AE10: =(AL10/AK10)-1 -> 0.19565792 | AH10: Fire Industrial | AI10: 3844.508 | AJ10: 6027.505 | AK10: 9596.2681 | AL10: 11473.854 | AP10: Fire Industrial | AQ10: 4119.432 | AR10: 6146.522 | AS10: 9022.189 | AT10: 11290.024
B11: Liability | C11: 2728902 | D11: 3124267 | E11: 3124239 | F11: 3358022 | G11: 3723336 | H11: =_xlfn.XLOOKUP(B11,$K$7:$K$19,$O$7:$O$19) -> 4713308.1 | K11: Liability | L11: 1622451 | M11: 2803166 | N11: 3983862 | O11: =N11*(1+$P11) -> 4713308.1 | P11: =X11 -> 0.18310024 | T11: Liability | U11: =IFERROR((M11-L11)/L11,0) -> 0.72773538 | V11: =IFERROR((N11-M11)/M11,0) -> 0.42120088 | W11: =IFERROR((O11-N11)/N11,0) -> 0.18310024 | X11: =AVERAGE(Z11:AD11) -> 0.18310024 | Z11: =(AT50/AS50)-1 -> 0.17925107 | AA11: =(AL50/AK50)-1 -> 0.2037131 | AB11: =(AT31/AS31)-1 -> 0.18490743 | AC11: =(AL31/AK31)-1 -> 0.17586738 | AD11: =(AT11/AS11)-1 -> 0.17176224 | AE11: =(AL11/AK11)-1 -> 0.18228362 | AH11: Liability | AI11: 966.096 | AJ11: 1416.912 | AK11: 2370.3128 | AL11: 2802.382 | AP11: Liability | AQ11: 966.61 | AR11: 1535.194 | AS11: 2332.189 | AT11: 2732.771
B12: Marine | C12: 3370608 | D12: 3188714 | E12: 3062526 | F12: 3637910 | G12: 4054753 | H12: =_xlfn.XLOOKUP(B12,$K$7:$K$19,$O$7:$O$19) -> 4422532.8 | K12: Marine | L12: 1427892 | M12: 2388070 | N12: 3475770 | O12: =N12*(1+$P12) -> 4422532.8 | P12: =X12 -> 0.27238937 | T12: Marine | U12: =IFERROR((M12-L12)/L12,0) -> 0.67244441 | V12: =IFERROR((N12-M12)/M12,0) -> 0.45547241 | W12: =IFERROR((O12-N12)/N12,0) -> 0.27238937 | X12: =AVERAGE(Z12:AD12) -> 0.27238937 | Z12: =(AT51/AS51)-1 -> 0.23737821 | AA12: =(AL51/AK51)-1 -> 0.29589658 | AB12: =(AT32/AS32)-1 -> 0.28945442 | AC12: =(AL32/AK32)-1 -> 0.3143683 | AD12: =(AT12/AS12)-1 -> 0.22484934 | AE12: =(AL12/AK12)-1 -> 0.30236789 | AH12: Marine | AI12: 1037.377 | AJ12: 1835.294 | AK12: 2787.3453 | AL12: 3630.149 | AP12: Marine | AQ12: 1127.989 | AR12: 2007.426 | AS12: 2864.696 | AT12: 3508.821
B13: Motor Private | C13: 22495605 | D13: 23431002 | E13: 23438810 | F13: 24626670 | G13: 27855160 | H13: =_xlfn.XLOOKUP(B13,$K$7:$K$19,$O$7:$O$19) -> 29261434 | K13: Motor Private | L13: 8208941 | M13: 14682933 | N13: 22133362 | O13: =N13*(1+$P13) -> 29261434 | P13: =X13 -> 0.32205101 | T13: Motor Private | U13: =IFERROR((M13-L13)/L13,0) -> 0.7886513 | V13: =IFERROR((N13-M13)/M13,0) -> 0.50742103 | W13: =IFERROR((O13-N13)/N13,0) -> 0.32205101 | X13: =AVERAGE(Z13:AD13) -> 0.32205101 | Z13: =(AT52/AS52)-1 -> 0.36613746 | AA13: =(AL52/AK52)-1 -> 0.32661777 | AB13: =(AT33/AS33)-1 -> 0.29008375 | AC13: =(AL33/AK33)-1 -> 0.30068766 | AD13: =(AT13/AS13)-1 -> 0.3267284 | AE13: =(AL13/AK13)-1 -> 0.31786192 | AH13: Motor Private | AI13: 6100.284 | AJ13: 10558.339 | AK13: 15975.963 | AL13: 21054.114 | AP13: Motor Private | AQ13: 6449.414 | AR13: 11382.726 | AS13: 17053.831 | AT13: 22625.802
B14: Motor Commercial | C14: 23593081 | D14: 23049684 | E14: 21289589 | F14: 24279823 | G14: 26132363 | H14: =_xlfn.XLOOKUP(B14,$K$7:$K$19,$O$7:$O$19) -> 26342102 | K14: Motor Commercial | L14: 8141577 | M14: 14194172 | N14: 20610762 | O14: =N14*(1+$P14) -> 26342102 | P14: =X14 -> 0.27807512 | T14: Motor Commercial | U14: =IFERROR((M14-L14)/L14,0) -> 0.74341801 | V14: =IFERROR((N14-M14)/M14,0) -> 0.45205807 | W14: =IFERROR((O14-N14)/N14,0) -> 0.27807512 | X14: =AVERAGE(Z14:AD14) -> 0.27807512 | Z14: =(AT53/AS53)-1 -> 0.36002702 | AA14: =(AL53/AK53)-1 -> 0.10585851 | AB14: =(AT34/AS34)-1 -> 0.22016265 | AC14: =(AL34/AK34)-1 -> 0.42077591 | AD14: =(AT14/AS14)-1 -> 0.28355154 | AE14: =(AL14/AK14)-1 -> 0.25437046 | AH14: Motor Commercial | AI14: 6570.885 | AJ14: 12305.545 | AK14: 18117.258 | AL14: 22725.753 | AP14: Motor Commercial | AQ14: 6750.957 | AR14: 12542.326 | AS14: 18419.304 | AT14: 23642.126
B15: Personal Accident | C15: 3157233 | D15: 3283857 | E15: 2362117 | F15: 2400674 | G15: 2331266 | H15: =_xlfn.XLOOKUP(B15,$K$7:$K$19,$O$7:$O$19) -> 3105840.8 | K15: Personal Accident | L15: 972667 | M15: 1590036 | N15: 2545112 | O15: =N15*(1+$P15) -> 3105840.8 | P15: =X15 -> 0.22031598 | T15: Personal Accident | U15: =IFERROR((M15-L15)/L15,0) -> 0.63471774 | V15: =IFERROR((N15-M15)/M15,0) -> 0.60066313 | W15: =IFERROR((O15-N15)/N15,0) -> 0.22031598 | X15: =AVERAGE(Z15:AD15) -> 0.22031598 | Z15: =(AT54/AS54)-1 -> 0.23206333 | AA15: =(AL54/AK54)-1 -> 0.20675201 | AB15: =(AT35/AS35)-1 -> 0.24825519 | AC15: =(AL35/AK35)-1 -> 0.20714329 | AD15: =(AT15/AS15)-1 -> 0.20736607 | AE15: =(AL15/AK15)-1 -> 0.24730551 | AH15: Personal Accident | AI15: 1498.569 | AJ15: 2269.139 | AK15: 2907.9644 | AL15: 3627.12 | AP15: Personal Accident | AQ15: 1279.257 | AR15: 2005.617 | AS15: 2634.756 | AT15: 3181.115
B16: Theft | C16: 3863654 | D16: 3835945 | E16: 3845254 | F16: 3992205 | G16: 4119725 | H16: =_xlfn.XLOOKUP(B16,$K$7:$K$19,$O$7:$O$19) -> 5020706.7 | K16: Theft | L16: 2189085 | M16: 2899977 | N16: 4387108 | O16: =N16*(1+$P16) -> 5020706.7 | P16: =X16 -> 0.14442286 | T16: Theft | U16: =IFERROR((M16-L16)/L16,0) -> 0.3247439 | V16: =IFERROR((N16-M16)/M16,0) -> 0.51280786 | W16: =IFERROR((O16-N16)/N16,0) -> 0.14442286 | X16: =AVERAGE(Z16:AD16) -> 0.14442286 | Z16: =(AT55/AS55)-1 -> 0.16524373 | AA16: =(AL55/AK55)-1 -> 0.14965817 | AB16: =(AT36/AS36)-1 -> 0.14529486 | AC16: =(AL36/AK36)-1 -> 0.13304496 | AD16: =(AT16/AS16)-1 -> 0.12887256 | AE16: =(AL16/AK16)-1 -> 0.16880437 | AH16: Theft | AI16: 1820.249 | AJ16: 2482.3 | AK16: 3250.8083 | AL16: 3799.559 | AP16: Theft | AQ16: 1874.785 | AR16: 2621.093 | AS16: 3429.776 | AT16: 3871.78
B17: Workmen's Compensation | C17: 6225354 | D17: 6358473 | E17: 6234247 | F17: 10659325 | G17: 11712076 | H17: =_xlfn.XLOOKUP(B17,$K$7:$K$19,$O$7:$O$19) -> 12976448 | K17: Workmen's Compensation | L17: 5234620 | M17: 7770426 | N17: 11127974 | O17: =N17*(1+$P17) -> 12976448 | P17: =X17 -> 0.16611056 | T17: Workmen's Compensation | U17: =IFERROR((M17-L17)/L17,0) -> 0.48442982 | V17: =IFERROR((N17-M17)/M17,0) -> 0.43209317 | W17: =IFERROR((O17-N17)/N17,0) -> 0.16611056 | X17: =AVERAGE(Z17:AD17) -> 0.16611056 | Z17: =(AT56/AS56)-1 -> 0.14609769 | AA17: =(AL56/AK56)-1 -> 0.11387973 | AB17: =(AT37/AS37)-1 -> 0.16291506 | AC17: =(AL37/AK37)-1 -> 0.18843617 | AD17: =(AT17/AS17)-1 -> 0.21922414 | AE17: =(AL17/AK17)-1 -> 0.13626383 | AH17: Workmen's Compensation | AI17: 2231.098 | AJ17: 3480.388 | AK17: 5060.7208 | AL17: 5750.314 | AP17: Workmen's Compensation | AQ17: 2326.2 | AR17: 3570.184 | AS17: 5293.094 | AT17: 6453.468
B18: Medical | C18: 40195984 | D18: 42348102 | E18: 45061539 | F18: 47586164 | G18: 54839172 | H18: =_xlfn.XLOOKUP(B18,$K$7:$K$19,$O$7:$O$19) -> 67912071 | K18: Medical | L18: 22212326 | M18: 37717733 | N18: 54152914 | O18: =N18*(1+$P18) -> 67912071 | P18: =X18 -> 0.25407971 | T18: Medical | U18: =IFERROR((M18-L18)/L18,0) -> 0.69805418 | V18: =IFERROR((N18-M18)/M18,0) -> 0.43574149 | W18: =IFERROR((O18-N18)/N18,0) -> 0.25407971 | X18: =AVERAGE(Z18:AD18) -> 0.25407971 | Z18: =(AT57/AS57)-1 -> 0.24635575 | AA18: =(AL57/AK57)-1 -> 0.25872872 | AB18: =(AT38/AS38)-1 -> 0.24051227 | AC18: =(AL38/AK38)-1 -> 0.260378 | AD18: =(AT18/AS18)-1 -> 0.26442381 | AE18: =(AL18/AK18)-1 -> 0.24647705 | AH18: Medical | AI18: 14288.674 | AJ18: 21811.658 | AK18: 30836.145 | AL18: 38436.547 | AP18: Medical | AQ18: 15313.231 | AR18: 23053.96 | AS18: 31861.155 | AT18: 40286.003
B19: Miscellaneous | C19: 3635343 | D19: 3741207 | E19: 3847218 | F19: 4142108 | G19: 3698214 | H19: =_xlfn.XLOOKUP(B19,$K$7:$K$19,$O$7:$O$19) -> 6554087.5 | K19: Miscellaneous | L19: 1558557 | M19: 3394023 | N19: 4750625 | O19: =N19*(1+$P19) -> 6554087.5 | P19: =X19 -> 0.37962636 | T19: Miscellaneous | U19: =IFERROR((M19-L19)/L19,0) -> 1.1776701 | V19: =IFERROR((N19-M19)/M19,0) -> 0.39970324 | W19: =IFERROR((O19-N19)/N19,0) -> 0.37962636 | X19: =AVERAGE(Z19:AD19) -> 0.37962636 | Z19: =(AT58/AS58)-1 -> 0.27695914 | AA19: =(AL58/AK58)-1 -> 0.41845482 | AB19: =(AT39/AS39)-1 -> 0.44296945 | AC19: =(AL39/AK39)-1 -> 0.36580306 | AD19: =(AT19/AS19)-1 -> 0.39394534 | AE19: =(AL19/AK19)-1 -> 0.41186544 | AH19: Miscellaneous | AI19: 1026.085 | AJ19: 1914.298 | AK19: 2767.8827 | AL19: 3907.878 | AP19: Miscellaneous | AQ19: 959.127 | AR19: 1900.201 | AS19: 2733.496 | AT19: 3810.344
C20: =SUM(C7:C19) -> 127511716 | D20: =SUM(D7:D19) -> 130516055 | E20: =SUM(E7:E19) -> 131057258 | F20: =SUM(F7:F19) -> 146781141 | G20: =SUM(G7:G19) -> 165739479 | H20: =SUM(H7:H19) -> 1.9302053e+08 | L20: =SUM(L7:L19) -> 62516629 | M20: =SUM(M7:M19) -> 105042816 | N20: =SUM(N7:N19) -> 153722300 | O20: =N20*(1+$P20) -> 1.9302999e+08 | P20: =X20 -> 0.25570587 | U20: =IFERROR((M20-L20)/L20,0) -> 0.68023801 | V20: =IFERROR((N20-M20)/M20,0) -> 0.46342516 | W20: =IFERROR((O20-N20)/N20,0) -> 0.25570587 | X20: =AVERAGE(Z20:AD20) -> 0.25570587 | Z20: =(AT59/AS59)-1 -> 0.256746 | AA20: =(AL59/AK59)-1 -> 0.22241832 | AB20: =(AT40/AS40)-1 -> 0.24489051 | AC20: =(AL40/AK40)-1 -> 0.28280389 | AD20: =(AT20/AS20)-1 -> 0.27167064 | AE20: =(AL20/AK20)-1 -> 0.25017703 | AI20: =SUM(AI7:AI19) -> 41559.072 | AJ20: =SUM(AJ7:AJ19) -> 67931.842 | AK20: =SUM(AK7:AK19) -> 99753.087 | AL20: =SUM(AL7:AL19) -> 124709.02 | AQ20: =SUM(AQ7:AQ19) -> 43307.619 | AR20: =SUM(AR7:AR19) -> 70998.066 | AS20: =SUM(AS7:AS19) -> 101462.85 | AT20: =SUM(AT7:AT19) -> 129027.33
B21: *2022 Projected Figures | N21: =SUM(N7:N19) -> 153722300 | O21: =O20-N20 -> 39307695 | W21: =IFERROR((O21-N21)/N21,0) -> -0.74429413
C22: =D20/C20-1 -> 0.023561278 | D22: =E20/D20-1 -> 0.0041466393 | E22: =F20/E20-1 -> 0.1199772 | F22: =G20/F20-1 -> 0.12916058 | G22: =H20/G20-1 -> 0.16460202 | H22: =I20/H20-1 -> -1
AH25: Gross written Premiums - Industry Statistics in Millions | AP25: Gross written Premiums - Industry Statistics in Millions
AI26: Q1 2019 | AJ26: Q2 2019 | AK26: Q3 2019 | AL26: Q4 2019 | AQ26: Q1 2020 | AR26: Q2 2020 | AS26: Q3 2020 | AT26: Q4 2020
AH27: Aviation | AI27: 382.323 | AJ27: 931.386 | AK27: 1652.221 | AL27: 2128.805 | AP27: Aviation | AQ27: 767.973 | AR27: 1556.87 | AS27: 2076.107 | AT27: 2965.237
AH28: Engineering | AI28: 1091.626 | AJ28: 2007.48 | AK28: 3025.758 | AL28: 3711.116 | AP28: Engineering | AQ28: 1056.039 | AR28: 1722.909 | AS28: 2727.348 | AT28: 3391.582
AH29: Fire Domestic | AI29: 542.392 | AJ29: 943.148 | AK29: 1310.123 | AL29: 1670.128 | AP29: Fire Domestic | AQ29: 582.008 | AR29: 993.051 | AS29: 1387.148 | AT29: 1743.717
AH30: Fire Industrial | AI30: 4242.631 | AJ30: 6411.126 | AK30: 9448.82 | AL30: 11419.322 | AP30: Fire Industrial | AQ30: 4086.022 | AR30: 6678.662 | AS30: 9484.038 | AT30: 11431.333
AH31: Liability | AI31: 1213.2 | AJ31: 1924.423 | AK31: 2764.93 | AL31: 3251.191 | AP31: Liability | AQ31: 1245.89 | AR31: 1914.385 | AS31: 2705.013 | AT31: 3205.19
AH32: Marine | AI32: 953.364 | AJ32: 1686.692 | AK32: 2498.229 | AL32: 3283.593 | AP32: Marine | AQ32: 1022.39 | AR32: 1720.27 | AS32: 2451.443 | AT32: 3161.024
AH33: Motor Private | AI33: 6550.202 | AJ33: 11992.405 | AK33: 17965.656 | AL33: 23367.707 | AP33: Motor Private | AQ33: 6571.646 | AR33: 11579.042 | AS33: 17773.498 | AT33: 22929.301
AH34: Motor Commercial | AI34: 6916.44 | AJ34: 12382.902 | AK34: 18331.185 | AL34: 26044.506 | AP34: Motor Commercial | AQ34: 6641.298 | AR34: 10966.491 | AS34: 16582.077 | AT34: 20232.831
AH35: Personal Accident | AI35: 1242.082 | AJ35: 2116.21 | AK35: 2898.134 | AL35: 3498.463 | AP35: Personal Accident | AQ35: 999.433 | AR35: 1445.424 | AS35: 1861.806 | AT35: 2324.009
AH36: Theft | AI36: 1928.651 | AJ36: 2598.19 | AK36: 3451.352 | AL36: 3910.537 | AP36: Theft | AQ36: 1931.464 | AR36: 2570.304 | AS36: 3305.788 | AT36: 3786.102
AH37: Workmen's Compensation | AI37: 2792.918 | AJ37: 3653.025 | AK37: 5368.237 | AL37: 6379.807 | AP37: Workmen's Compensation | AQ37: 2455.777 | AR37: 3683.77 | AS37: 5565.305 | AT37: 6471.977
AH38: Medical | AI38: 15666.953 | AJ38: 24425.128 | AK38: 33660.613 | AL38: 42425.096 | AP38: Medical | AQ38: 16823.293 | AR38: 26514.901 | AS38: 36255.68 | AT38: 44975.616
AH39: Miscellaneous | AI39: 1057.774 | AJ39: 1957.847 | AK39: 2856.753 | AL39: 3901.762 | AP39: Miscellaneous | AQ39: 1064.173 | AR39: 1835.177 | AS39: 2923.486 | AT39: 4218.501
AI40: =SUM(AI27:AI39) -> 44580.556 | AJ40: =SUM(AJ27:AJ39) -> 73029.962 | AK40: =SUM(AK27:AK39) -> 105232.01 | AL40: =SUM(AL27:AL39) -> 134992.03 | AQ40: =SUM(AQ27:AQ39) -> 45247.406 | AR40: =SUM(AR27:AR39) -> 73181.256 | AS40: =SUM(AS27:AS39) -> 105098.74 | AT40: =SUM(AT27:AT39) -> 130836.42
AH44: Gross written Premiums - Industry Statistics in Millions | AP44: Gross written Premiums - Industry Statistics in Millions
AI45: Q1 2021 | AJ45: Q2 2021 | AK45: Q3 2021 | AL45: Q4 2021 | AQ45: Q1 2022 | AR45: Q2 2022 | AS45: Q3 2022 | AT45: Q4 2022
AH46: Aviation | AI46: 1180.042 | AJ46: 1985.82 | AK46: 2398.653 | AL46: 3100.003 | AP46: Aviation | AQ46: 990 | AR46: 2151 | AS46: 2783 | AT46: 3626
AH47: Engineering | AI47: 1442.61 | AJ47: 2200.009 | AK47: 3766.552 | AL47: 4469.287 | AP47: Engineering | AQ47: 1652 | AR47: 2346 | AS47: 4691 | AT47: 5275
AH48: Fire Domestic | AI48: 615.521 | AJ48: 999.178 | AK48: 1412.702 | AL48: 1770.411 | AP48: Fire Domestic | AQ48: 692 | AR48: 1031 | AS48: 1466 | AT48: 1811
AH49: Fire Industrial | AI49: 4574.206 | AJ49: 7583.709 | AK49: 11547.979 | AL49: 13812.553 | AP49: Fire Industrial | AQ49: 6379 | AR49: 9775 | AS49: 15117 | AT49: 17686
AH50: Liability | AI50: 1407.27 | AJ50: 2164.978 | AK50: 2839.513 | AL50: 3417.959 | AP50: Liability | AQ50: 1509 | AR50: 2490 | AS50: 3258 | AT50: 3842
AH51: Marine | AI51: 1129.699 | AJ51: 1974.174 | AK51: 2959.017 | AL51: 3834.58 | AP51: Marine | AQ51: 1316 | AR51: 2302 | AS51: 3387 | AT51: 4191
AH52: Motor Private | AI52: 6875.137 | AJ52: 12021.283 | AK52: 18222.061 | AL52: 24173.71 | AP52: Motor Private | AQ52: 7518 | AR52: 13041 | AS52: 20282 | AT52: 27708
AH53: Motor Commercial | AI53: 7744.975 | AJ53: 13623.446 | AK53: 20855.556 | AL53: 23063.294 | AP53: Motor Commercial | AQ53: 7340 | AR53: 12913 | AS53: 19243 | AT53: 26171
AH54: Personal Accident | AI54: 888.882 | AJ54: 1373.016 | AK54: 2116.821 | AL54: 2554.478 | AP54: Personal Accident | AQ54: 1071 | AR54: 1502 | AS54: 2021 | AT54: 2490
AH55: Theft | AI55: 2044.807 | AJ55: 2607.486 | AK55: 3563.454 | AL55: 4096.754 | AP55: Theft | AQ55: 1820 | AR55: 2819 | AS55: 3631 | AT55: 4231
AH56: Workmen's Compensation | AI56: 2586.167 | AJ56: 9309.418 | AK56: 11028.416 | AL56: 12284.329 | AP56: Workmen's Compensation | AQ56: 3190 | AR56: 8344 | AS56: 11506 | AT56: 13187
AH57: Medical | AI57: 17693.672 | AJ57: 29457.594 | AK57: 40851.368 | AL57: 51420.79 | AP57: Medical | AQ57: 19356 | AR57: 31841 | AS57: 44042 | AT57: 54892
AH58: Miscellaneous | AI58: 1213.347 | AJ58: 2002.293 | AK58: 3068.716 | AL58: 4352.835 | AP58: Miscellaneous | AQ58: 1085 | AR58: 1843 | AS58: 2986 | AT58: 3813
AI59: =SUM(AI46:AI58) -> 49396.335 | AJ59: =SUM(AJ46:AJ58) -> 87302.404 | AK59: =SUM(AK46:AK58) -> 124630.81 | AL59: =SUM(AL46:AL58) -> 152350.98 | AQ59: =SUM(AQ46:AQ58) -> 53918 | AR59: =SUM(AR46:AR58) -> 92398 | AS59: =SUM(AS46:AS58) -> 134413 | AT59: =SUM(AT46:AT58) -> 168923
AH64: Gross written Premiums - Industry Statistics in Millions
AI65: Q1 2023 | AJ65: Q2 2023 | AK65: Q3 2023 | AL65: Q4 2023
AH66: Aviation | AI66: 1229 | AJ66: 2608 | AK66: 3849.383
AH67: Engineering | AI67: 1649 | AJ67: 2563 | AK67: 4147.67
AH68: Fire Domestic | AI68: 681 | AJ68: 1128 | AK68: 1641.782
AH69: Fire Industrial | AI69: 7389 | AJ69: 11303 | AK69: 16915.976
AH70: Liability | AI70: 1622 | AJ70: 2803 | AK70: 3983.862
AH71: Marine | AI71: 1428 | AJ71: 2388 | AK71: 3475.77
AH72: Motor Private | AI72: 8209 | AJ72: 14683 | AK72: 22133.362
AH73: Motor Commercial | AI73: 8142 | AJ73: 14194 | AK73: 20610.762
AH74: Personal Accident | AI74: 973 | AJ74: 1590 | AK74: 2545.112
AH75: Theft | AI75: 2189 | AJ75: 2900 | AK75: 4387.108
AH76: Workmen's Compensation | AI76: 5235 | AJ76: 7770 | AK76: 11127.974
AH77: Medical | AI77: 22212 | AJ77: 37718 | AK77: 54152.914
AH78: Miscellaneous | AI78: 1559 | AJ78: 3394 | AK78: 4750.625
AI79: =SUM(AI66:AI78) -> 62517 | AJ79: =SUM(AJ66:AJ78) -> 105042 | AK79: =SUM(AK66:AK78) -> 153722.3 | AL79: =SUM(AL66:AL78) -> 0

Sheet Pioneer  vs Industry
CQ2: 2017 | CR2: 2018 | CS2: 2019 | CT2: 2020 | CU2: 2021
M3: 1000 | CP3: GWP | CQ3: =C22 -> 326.29735 | CR3: =D22 -> 591.85707 | CS3: =E22 -> 860.49337 | CT3: =F22 -> 883.81611 | CU3: =H22 -> 1635.7596
B4: Business Growth | AD4: Market Share | CH4: 1000 | CP4: Market Share | CQ4: =AE22 -> 0.0040165901 | CR4: =AF22 -> 0.0067783554 | CS4: =AG22 -> 0.0097597068 | CT4: =AH22 -> 0.010277443 | CU4: =AJ22 -> 0.01474982
BL5: Industry Statistics and Projection
C6: 2 | D6: 3 | E6: 4 | F6: 5 | I6: 6 | BL6: 2017 | BQ6: 2018 | BV6: 2019 | CA6: 2020 | CH6: 2021 | CN6: Total Incurred Claims | CP6: Claims Analysis | CQ6: 2017 | CR6: =CQ6+1 -> 2018 | CS6: =CR6+1 -> 2019 | CT6: =CS6+1 -> 2020 | CU6: =CT6+1 -> 2021
B7: Pioneer General Insurance Limited Business Growth 2018 - 2022 (Amounts in KES. Millions) | AD7: Pioneer General Insurance Limited Market Share & Product Mix 2019 - 2023 | BE7: Insurance Penetration 2018 | BL7: CoB | BM7: Q3 | BN7: Q4 | BO7: Growth Rate | BQ7: CoB | BR7: Q3 | BS7: Q4 | BT7: Growth Rate | BV7: CoB | BW7: Q3 | BX7: Q4 | BY7: Growth Rate | CA7: CoB | CB7: Q3 | CC7: Projected Q4 | CD7: Growth Rate | CF7: Q3/Q4 Adopted Growth | CH7: CoB | CI7: Q3 | CJ7: Projected Q4 | CM7: 2021 | CN7: 4.2979309e+08 | CP7: Gross Claims Severity | CQ7: 52761.578 | CR7: =CN10/A_Thousand -> 300164.54 | CS7: =CN9/A_Thousand -> 422676.54 | CT7: =CN8/A_Thousand -> 429793.09 | CU7: =CO7/A_Thousand -> 0
C8: Pioneer General GWP | J8: Industry GWP | Q8: Pioneer General Growth | W8: Industry Growth | AE8: Pioneer General Market Share | AL8: Pioneer General Product Mix | AS8: Industry Product Mix | BF8: Life | BG8: General | BH8: Combined | BL8: Aviation | BM8: 1217897 | BN8: 1653397 | BO8: =(BN8-BM8)/BM8 -> 0.35758364 | BQ8: Aviation | BR8: 1447092 | BS8: 2183342 | BT8: =(BS8-BR8)/BR8 -> 0.50877899 | BV8: Aviation | BW8: 1652221 | BX8: 2109320 | BY8: =(BX8-BW8)/BW8 -> 0.2766573 | CA8: Aviation | CB8: 2076107 | CC8: 2965237 | CD8: =(CC8-CB8)/CB8 -> 0.42826791 | CF8: 0.40849914 | CH8: Aviation | CI8: 2398653 | CJ8: =CI8*(1+CF8) -> 3378500.7 | CM8: 2020 | CN8: 4.2979309e+08 | CP8: Claim Frequency | CQ8: 0.088780013 | CR8: 0.06949547 | CS8: 0.081088808 | CT8: 0.078281085 | CU8: 0.078281085
B9: Business Class | C9: 2017 | D9: =C9+1 -> 2018 | E9: =D9+1 -> 2019 | F9: =E9+1 -> 2020 | G9: 2021 | H9: 2022 | I9: 2023 | J9: 2017 | K9: 2018 | L9: 2019 | M9: 2020 | N9: 2021 | O9: 2022 | P9: 2023 | Q9: 2018 | R9: =Q9+1 -> 2019 | S9: =R9+1 -> 2020 | T9: 2021 | U9: 2022 | V9: 2023 | W9: 2018 | X9: 2019 | Y9: 2020 | Z9: 2021 | AA9: 2022 | AB9: 2023 | AD9: Business Class | AE9: 2017 | AF9: =AE9+1 -> 2018 | AG9: =AF9+1 -> 2019 | AH9: =AG9+1 -> 2020 | AI9: 2021 | AJ9: 2022 | AK9: 2023 | AL9: 2017 | AM9: =AL9+1 -> 2018 | AN9: =AM9+1 -> 2019 | AO9: =AN9+1 -> 2020 | AP9: 2021 | AQ9: 2022 | AR9: 2023 | AS9: 2017 | AT9: 2018 | AU9: 2019 | AV9: 2020 | AW9: 2021 | AX9: 2022 | AY9: 2023 | BE9: Kenya | BF9: 0.96 | BG9: 1.42 | BH9: 2.37 | BL9: Engineering | BM9: 3608738.7 | BN9: 4262403 | BO9: =(BN9-BM9)/BM9 -> 0.18113372 | BQ9: Engineering | BR9: 3099225 | BS9: 3841093 | BT9: =(BS9-BR9)/BR9 -> 0.2393721 | BV9: Engineering | BW9: 3025758 | BX9: 3502268 | BY9: =(BX9-BW9)/BW9 -> 0.1574845 | CA9: Engineering | CB9: 2727348 | CC9: 3391582 | CD9: =(CC9-CB9)/CB9 -> 0.24354574 | CF9: 0.23647524 | CH9: Engineering | CI9: 3766552 | CJ9: =CI9*(1+CF9) -> 4657248.3 | CM9: =CM8-1 -> 2019 | CN9: 422676541 | CV9: =SUM(CV11:CV12) -> 0.64556188 | CW9: =SUM(CW11:CW12) -> 0.71262441 | CX9: =SUM(CX11:CX12) -> 0.68708821
A10: Aviation | B10: Aviation | G10: =_xlfn.XLOOKUP(B10,RA!$C$78:$N$78,RA!$C$79:$N$79)/A_Million -> 1.898815 | H10: =_xlfn.XLOOKUP(B10,RA!$C$43:$N$43,RA!$C$44:$N$44)/A_Million -> -0.111821 | I10: =_xlfn.XLOOKUP(B10,RA!$C$8:$N$8,RA!$C$9:$N$9)/A_Million -> 0 | J10: 1653.397 | K10: =(_xlfn.XLOOKUP($A10,Industry_Results!$B$7:$B$19,Industry_Results!C$7:C$19))/A_Thousand -> 2134.254 | L10: =(_xlfn.XLOOKUP($A10,Industry_Results!$B$7:$B$19,Industry_Results!D$7:D$19))/A_Thousand -> 2109.32 | M10: =(_xlfn.XLOOKUP($A10,Industry_Results!$B$7:$B$19,Industry_Results!E$7:E$19))/A_Thousand -> 2963.413 | N10: =(_xlfn.XLOOKUP($A10,Industry_Results!$B$7:$B$19,Industry_Results!F$7:F$19))/A_Thousand -> 3094.41 | O10: =(_xlfn.XLOOKUP($A10,Industry_Results!$B$7:$B$19,Industry_Results!G$7:G$19))/A_Thousand -> 3564.55 | P10: =(_xlfn.XLOOKUP($A10,Industry_Results!$B$7:$B$19,Industry_Results!H$7:H$19))/A_Thousand -> 5251.1752 | Q10: =IFERROR((D10-C10)/C10,0) -> 0 | R10: =IFERROR((E10-D10)/D10,0) -> 0 | S10: =IFERROR((F10-E10)/E10,0) -> 0 | T10: =IFERROR((G10-F10)/F10,0) -> 0 | U10: =IFERROR((H10-G10)/G10,0) -> -1.0588899 | V10: =IFERROR((I10-H10)/H10,0) -> -1 | W10: =IFERROR((K10-J10)/J10,0) -> 0.29082973 | X10: =IFERROR((L10-K10)/K10,0) -> -0.011682771 | Y10: =IFERROR((M10-L10)/L10,0) -> 0.40491391 | Z10: =IFERROR((N10-M10)/M10,0) -> 0.044204773 | AA10: =IFERROR((O10-N10)/N10,0) -> 0.15193203 | AB10: =IFERROR((P10-O10)/O10,0) -> 0.47316639 | AD10: Aviation | AE10: =IFERROR(C10/J10,0) -> 0 | AF10: =IFERROR(D10/K10,0) -> 0 | AG10: =IFERROR(E10/L10,0) -> 0 | AH10: =IFERROR(F10/M10,0) -> 0 | AI10: =IFERROR(G10/N10,0) -> 0.00061362748 | AJ10: =IFERROR(H10/O10,0) -> -3.1370299e-05 | AK10: =IFERROR(I10/P10,0) -> 0 | AL10: =IFERROR(C10/C$22,0) -> 0 | AM10: =IFERROR(D10/D$22,0) -> 0 | AN10: =IFERROR(E10/E$22,0) -> 0 | AO10: =IFERROR(F10/F$22,0) -> 0 | AP10: =IFERROR(G10/G$22,0) -> 0.001352858 | AQ10: =IFERROR(H10/H$22,0) -> -6.8360291e-05 | AR10: =IFERROR(I10/I$22,0) -> 0 | AS10: =IFERROR(J10/J$22,0) -> 0.020352657 | ... AY10: =IFERROR(P10/P$22,0) -> 0.041972982 | AZ10: =AQ10-AN10 -> -6.8360291e-05 | BE10: South Africa | BF10: 10.27 | BG10: 2.62 | BH10: 12.89 | BL10: Fire Domestic | BM10: 1255782.9 | BN10: 1585548 | BO10: =(BN10-BM10)/BM10 -> 0.26259721 | BQ10: Fire Domestic | BR10: 1272052 | BS10: 1600645 | BT10: =(BS10-BR10)/BR10 -> 0.25831727 | BV10: Fire Domestic | BW10: 1310123 | BX10: 1672639 | BY10: =(BX10-BW10)/BW10 -> 0.27670379 | CA10: Fire Domestic | CB10: 1387148 | CC10: 1743717 | CD10: =(CC10-CB10)/CB10 -> 0.25705188 | CF10: 0.26338544 | CH10: Fire Domestic | CI10: 1412702 | CJ10: =CI10*(1+CF10) -> 1784787.1 | CM10: =CM9-1 -> 2018 | CN10: 3.0016454e+08 | CR10: 2018 | CS10: 2019 | CT10: 2020 | CU10: 2021
A11: Engineering | B11: Engineering | C11: =VLOOKUP($B11,RA!$R$150:$X$162,C$6,0)/A_Million -> 14.368391 | D11: =VLOOKUP($B11,RA!$R$150:$X$162,D$6,0)/A_Million -> 16.296166 | E11: =VLOOKUP($B11,RA!$R$150:$X$162,E$6,0)/A_Million -> 18.890297 | F11: =VLOOKUP($B11,RA!$R$150:$X$162,F$6,0)/A_Million -> 19.023323 | G11: =_xlfn.XLOOKUP(B11,RA!$C$78:$N$78,RA!$C$79:$N$79)/A_Million -> 19.446301 | H11: =_xlfn.XLOOKUP(B11,RA!$C$8:$N$8,RA!$C$44:$N$44)/A_Million -> 40.945277 | I11: =_xlfn.XLOOKUP(B11,RA!$C$8:$N$8,RA!$C$9:$N$9)/A_Million -> 32.682894 | J11: 4262.403 | K11: =(_xlfn.XLOOKUP($A11,Industry_Results!$B$7:$B$19,Industry_Results!C$7:C$19))/A_Thousand -> 3691.508 | L11: =(_xlfn.XLOOKUP($A11,Industry_Results!$B$7:$B$19,Industry_Results!D$7:D$19))/A_Thousand -> 3502.268 | M11: =(_xlfn.XLOOKUP($A11,Industry_Results!$B$7:$B$19,Industry_Results!E$7:E$19))/A_Thousand -> 3250.661 | N11: =(_xlfn.XLOOKUP($A11,Industry_Results!$B$7:$B$19,Industry_Results!F$7:F$19))/A_Thousand -> 4283.167 | O11: =(_xlfn.XLOOKUP($A11,Industry_Results!$B$7:$B$19,Industry_Results!G$7:G$19))/A_Thousand -> 5064.942 | P11: =(_xlfn.XLOOKUP($A11,Industry_Results!$B$7:$B$19,Industry_Results!H$7:H$19))/A_Thousand -> 4994.2027 | Q11: =IFERROR((D11-C11)/C11,0) -> 0.13416777 | R11: =IFERROR((E11-D11)/D11,0) -> 0.15918658 | S11: =IFERROR((F11-E11)/E11,0) -> 0.007042028 | T11: =IFERROR((G11-F11)/F11,0) -> 0.022234706 | U11: =IFERROR((H11-G11)/G11,0) -> 1.1055561 | V11: =IFERROR((I11-H11)/H11,0) -> -0.20179087 | W11: =IFERROR((K11-J11)/J11,0) -> -0.13393736 | X11: =IFERROR((L11-K11)/K11,0) -> -0.051263603 | Y11: =IFERROR((M11-L11)/L11,0) -> -0.071841161 | Z11: =IFERROR((N11-M11)/M11,0) -> 0.31762955 | AA11: =IFERROR((O11-N11)/N11,0) -> 0.18252265 | AB11: =IFERROR((P11-O11)/O11,0) -> -0.013966449 | AD11: Engineering | AE11: =IFERROR(C11/J11,0) -> 0.0033709602 | AF11: =IFERROR(D11/K11,0) -> 0.0044145011 | AG11: =IFERROR(E11/L11,0) -> 0.0053937326 | AH11: =IFERROR(F11/M11,0) -> 0.0058521399 | AI11: =IFERROR(G11/N11,0) -> 0.0045401688 | AJ11: =IFERROR(H11/O11,0) -> 0.0080840564 | AK11: =IFERROR(I11/P11,0) -> 0.0065441664 | AL11: =IFERROR(C11/C$22,0) -> 0.044034655 | AM11: =IFERROR(D11/D$22,0) -> 0.027533955 | AN11: =IFERROR(E11/E$22,0) -> 0.021952868 | AO11: =IFERROR(F11/F$22,0) -> 0.021524074 | AP11: =IFERROR(G11/G$22,0) -> 0.013855001 | AQ11: =IFERROR(H11/H$22,0) -> 0.025031354 | AR11: =IFERROR(I11/I$22,0) -> 0.020483523 | AS11: =IFERROR(J11/J$22,0) -> 0.05246848 | ... AY11: =IFERROR(P11/P$22,0) -> 0.039918985 | AZ11: =AQ11-AN11 -> 0.0030784866 | BE11: UK | BF11: 8.32 | BG11: 2.29 | BH11: 10.61 | BL11: Fire Industrial | BM11: 9596268.1 | BN11: 11473854 | BO11: =(BN11-BM11)/BM11 -> 0.19565792 | BQ11: Fire Industrial | BR11: 9022189 | BS11: 11290024 | BT11: =(BS11-BR11)/BR11 -> 0.25136195 | BV11: Fire Industrial | BW11: 9448820 | BX11: 10870577 | BY11: =(BX11-BW11)/BW11 -> 0.15046926 | CA11: Fire Industrial | CB11: 9484038 | CC11: 11431333 | CD11: =(CC11-CB11)/CB11 -> 0.20532341 | CF11: 0.22174338 | CH11: Fire Industrial | CI11: 11547979 | CJ11: =CI11*(1+CF11) -> 14108667 | CN11: 1.1526342e+09 | CQ11: Motor Commercial | CR11: =D17 -> 115.54972 | CS11: =E17 -> 164.98612 | CT11: =F17 -> 174.75533 | CU11: =H17 -> 305.36273 | CV11: =CS11/SUM(CS11:CS13) -> 0.19173433 | CW11: =CT11/SUM(CT11:CT13) -> 0.19772815 | CX11: =CU11/SUM(CU11:CU13) -> 0.18667947
A12: Fire Domestic | B12: Fire Domestic | C12: =VLOOKUP($B12,RA!$R$150:$X$162,C$6,0)/A_Million -> 1.856402 | D12: =VLOOKUP($B12,RA!$R$150:$X$162,D$6,0)/A_Million -> 10.05213 | E12: =VLOOKUP($B12,RA!$R$150:$X$162,E$6,0)/A_Million -> 11.729006 | F12: =VLOOKUP($B12,RA!$R$150:$X$162,F$6,0)/A_Million -> 8.870728 | G12: =_xlfn.XLOOKUP(B12,RA!$C$78:$N$78,RA!$C$79:$N$79)/A_Million -> 10.013349 | H12: =_xlfn.XLOOKUP(B12,RA!$C$8:$N$8,RA!$C$44:$N$44)/A_Million -> 8.873879 | I12: =_xlfn.XLOOKUP(B12,RA!$C$8:$N$8,RA!$C$9:$N$9)/A_Million -> 10.785848 | J12: 1585.548 | K12: =(_xlfn.XLOOKUP($A12,Industry_Results!$B$7:$B$19,Industry_Results!C$7:C$19))/A_Thousand -> 1595.804 | L12: =(_xlfn.XLOOKUP($A12,Industry_Results!$B$7:$B$19,Industry_Results!D$7:D$19))/A_Thousand -> 1672.639 | M12: =(_xlfn.XLOOKUP($A12,Industry_Results!$B$7:$B$19,Industry_Results!E$7:E$19))/A_Thousand -> 1759.941 | N12: =(_xlfn.XLOOKUP($A12,Industry_Results!$B$7:$B$19,Industry_Results!F$7:F$19))/A_Thousand -> 1770.893 | O12: =(_xlfn.XLOOKUP($A12,Industry_Results!$B$7:$B$19,Industry_Results!G$7:G$19))/A_Thousand -> 1815.381 | P12: =(_xlfn.XLOOKUP($A12,Industry_Results!$B$7:$B$19,Industry_Results!H$7:H$19))/A_Thousand -> 2061.6512 | Q12: =IFERROR((D12-C12)/C12,0) -> 4.4148455 | R12: =IFERROR((E12-D12)/D12,0) -> 0.16681798 | S12: =IFERROR((F12-E12)/E12,0) -> -0.24369311 | T12: =IFERROR((G12-F12)/F12,0) -> 0.12880803 | U12: =IFERROR((H12-G12)/G12,0) -> -0.11379509 | V12: =IFERROR((I12-H12)/H12,0) -> 0.21546034 | W12: =IFERROR((K12-J12)/J12,0) -> 0.0064684261 | X12: =IFERROR((L12-K12)/K12,0) -> 0.048148144 | Y12: =IFERROR((M12-L12)/L12,0) -> 0.052194167 | Z12: =IFERROR((N12-M12)/M12,0) -> 0.0062229359 | AA12: =IFERROR((O12-N12)/N12,0) -> 0.025121789 | AB12: =IFERROR((P12-O12)/O12,0) -> 0.13565759 | AD12: Fire Domestic | AE12: =IFERROR(C12/J12,0) -> 0.0011708267 | AF12: =IFERROR(D12/K12,0) -> 0.0062991006 | AG12: =IFERROR(E12/L12,0) -> 0.0070122758 | AH12: =IFERROR(F12/M12,0) -> 0.0050403553 | AI12: =IFERROR(G12/N12,0) -> 0.0056544066 | AJ12: =IFERROR(H12/O12,0) -> 0.0048881634 | AK12: =IFERROR(I12/P12,0) -> 0.005231655 | AL12: =IFERROR(C12/C$22,0) -> 0.0056892954 | AM12: =IFERROR(D12/D$22,0) -> 0.01698405 | AN12: =IFERROR(E12/E$22,0) -> 0.013630559 | AO12: =IFERROR(F12/F$22,0) -> 0.010036848 | AP12: =IFERROR(G12/G$22,0) -> 0.0071342596 | AQ12: =IFERROR(H12/H$22,0) -> 0.0054249287 | AR12: =IFERROR(I12/I$22,0) -> 0.0067598715 | AS12: =IFERROR(J12/J$22,0) -> 0.019517463 | ... AY12: =IFERROR(P12/P$22,0) -> 0.016478911 | AZ12: =AQ12-AN12 -> -0.0082056307 | BE12: US | BF12: 2.88 | BG12: 4.26 | BH12: 7.14 | BL12: Liability | BM12: 2370312.8 | BN12: 2802382 | BO12: =(BN12-BM12)/BM12 -> 0.18228362 | BQ12: Liability | BR12: 2332189 | BS12: 2732771 | BT12: =(BS12-BR12)/BR12 -> 0.17176224 | BV12: Liability | BW12: 2764930 | BX12: 3124267 | BY12: =(BX12-BW12)/BW12 -> 0.12996242 | CA12: Liability | CB12: 2705013 | CC12: 3205190 | CD12: =(CC12-CB12)/CB12 -> 0.18490743 | CF12: 0.17751235 | CH12: Liability | CI12: 2839513 | CJ12: =CI12*(1+CF12) -> 3343561.6 | CQ12: Motor Private | CR12: =D18 -> 222.94181 | CS12: =E18 -> 390.51559 | CT12: =F18 -> 455.07361 | CU12: =H18 -> 818.54838 | CV12: =CS12/SUM(CS11:CS13) -> 0.45382755 | CW12: =CT12/SUM(CT11:CT13) -> 0.51489626 | CX12: =CU12/SUM(CU11:CU13) -> 0.50040874
A13: Fire Industrial | B13: Fire Industrial | C13: =VLOOKUP($B13,RA!$R$150:$X$162,C$6,0)/A_Million -> 46.293575 | D13: =VLOOKUP($B13,RA!$R$150:$X$162,D$6,0)/A_Million -> 57.823692 | E13: =VLOOKUP($B13,RA!$R$150:$X$162,E$6,0)/A_Million -> 65.453593 | F13: =VLOOKUP($B13,RA!$R$150:$X$162,F$6,0)/A_Million -> 65.626886 | G13: =_xlfn.XLOOKUP(B13,RA!$C$78:$N$78,RA!$C$79:$N$79)/A_Million -> 58.149488 | H13: =_xlfn.XLOOKUP(B13,RA!$C$8:$N$8,RA!$C$44:$N$44)/A_Million -> 78.279579 | I13: =_xlfn.XLOOKUP(B13,RA!$C$8:$N$8,RA!$C$9:$N$9)/A_Million -> 76.255014 | J13: 11473.854 | K13: =(_xlfn.XLOOKUP($A13,Industry_Results!$B$7:$B$19,Industry_Results!C$7:C$19))/A_Thousand -> 10824.386 | L13: =(_xlfn.XLOOKUP($A13,Industry_Results!$B$7:$B$19,Industry_Results!D$7:D$19))/A_Thousand -> 10870.577 | M13: =(_xlfn.XLOOKUP($A13,Industry_Results!$B$7:$B$19,Industry_Results!E$7:E$19))/A_Thousand -> 10817.704 | N13: =(_xlfn.XLOOKUP($A13,Industry_Results!$B$7:$B$19,Industry_Results!F$7:F$19))/A_Thousand -> 12949.77 | O13: =(_xlfn.XLOOKUP($A13,Industry_Results!$B$7:$B$19,Industry_Results!G$7:G$19))/A_Thousand -> 16828.541 | P13: =(_xlfn.XLOOKUP($A13,Industry_Results!$B$7:$B$19,Industry_Results!H$7:H$19))/A_Thousand -> 20404.972 | Q13: =IFERROR((D13-C13)/C13,0) -> 0.24906517 | R13: =IFERROR((E13-D13)/D13,0) -> 0.13195112 | S13: =IFERROR((F13-E13)/E13,0) -> 0.0026475705 | T13: =IFERROR((G13-F13)/F13,0) -> -0.11393803 | U13: =IFERROR((H13-G13)/G13,0) -> 0.3461783 | V13: =IFERROR((I13-H13)/H13,0) -> -0.025863259 | W13: =IFERROR((K13-J13)/J13,0) -> -0.056604172 | X13: =IFERROR((L13-K13)/K13,0) -> 0.004267309 | Y13: =IFERROR((M13-L13)/L13,0) -> -0.0048638633 | Z13: =IFERROR((N13-M13)/M13,0) -> 0.19709044 | AA13: =IFERROR((O13-N13)/N13,0) -> 0.29952432 | AB13: =IFERROR((P13-O13)/O13,0) -> 0.21252178 | AD13: Fire Industrial | AE13: =IFERROR(C13/J13,0) -> 0.0040347014 | AF13: =IFERROR(D13/K13,0) -> 0.0053419836 | AG13: =IFERROR(E13/L13,0) -> 0.0060211701 | AH13: =IFERROR(F13/M13,0) -> 0.0060666188 | AI13: =IFERROR(G13/N13,0) -> 0.0044903877 | AJ13: =IFERROR(H13/O13,0) -> 0.0046515963 | AK13: =IFERROR(I13/P13,0) -> 0.00373708 | AL13: =IFERROR(C13/C$22,0) -> 0.14187543 | AM13: =IFERROR(D13/D$22,0) -> 0.097698744 | AN13: =IFERROR(E13/E$22,0) -> 0.076065192 | AO13: =IFERROR(F13/F$22,0) -> 0.074254006 | AP13: =IFERROR(G13/G$22,0) -> 0.041430049 | AQ13: =IFERROR(H13/H$22,0) -> 0.047855187 | AR13: =IFERROR(I13/I$22,0) -> 0.047791708 | AS13: =IFERROR(J13/J$22,0) -> 0.14123856 | ... AY13: =IFERROR(P13/P$22,0) -> 0.16309826 | AZ13: =AQ13-AN13 -> -0.028210005 | BE13: Africa | BF13: 2.02 | BG13: 0.96 | BH13: 2.98 | BL13: Marine | BM13: 2787345.3 | BN13: 3630149 | BO13: =(BN13-BM13)/BM13 -> 0.30236789 | BQ13: Marine | BR13: 2864696 | BS13: 3508821 | BT13: =(BS13-BR13)/BR13 -> 0.22484934 | BV13: Marine | BW13: 2498229 | BX13: 3188714 | BY13: =(BX13-BW13)/BW13 -> 0.27638979 | CA13: Marine | CB13: 2451443 | CC13: 3161024 | CD13: =(CC13-CB13)/CB13 -> 0.28945442 | CF13: 0.27622402 | CH13: Marine | CI13: 2959017 | CJ13: =CI13*(1+CF13) -> 3776368.6 | CQ13: Other Classes | CR13: =D22-SUM(CR11:CR12) -> 253.36554 | CS13: =E22-SUM(CS11:CS12) -> 304.99165 | CT13: =F22-SUM(CT11:CT12) -> 253.98717 | CU13: =H22-SUM(CU11:CU12) -> 511.84845 | CV13: =CS13/SUM(CS11:CS13) -> 0.35443812 | CW13: =CT13/SUM(CT11:CT13) -> 0.28737559 | CX13: =CU13/SUM(CU11:CU13) -> 0.31291179
A14: Liability | B14: Liability | C14: =VLOOKUP($B14,RA!$R$150:$X$162,C$6,0)/A_Million -> 14.852294 | D14: =VLOOKUP($B14,RA!$R$150:$X$162,D$6,0)/A_Million -> 31.057738 | E14: =VLOOKUP($B14,RA!$R$150:$X$162,E$6,0)/A_Million -> 44.399645 | F14: =VLOOKUP($B14,RA!$R$150:$X$162,F$6,0)/A_Million -> 35.10496 | G14: =_xlfn.XLOOKUP(B14,RA!$C$78:$N$78,RA!$C$79:$N$79)/A_Million -> 41.785885 | H14: =_xlfn.XLOOKUP(B14,RA!$C$8:$N$8,RA!$C$44:$N$44)/A_Million -> 34.436388 | I14: =_xlfn.XLOOKUP(B14,RA!$C$8:$N$8,RA!$C$9:$N$9)/A_Million -> 39.903688 | J14: 2802.382 | K14: =(_xlfn.XLOOKUP($A14,Industry_Results!$B$7:$B$19,Industry_Results!C$7:C$19))/A_Thousand -> 2728.902 | L14: =(_xlfn.XLOOKUP($A14,Industry_Results!$B$7:$B$19,Industry_Results!D$7:D$19))/A_Thousand -> 3124.267 | M14: =(_xlfn.XLOOKUP($A14,Industry_Results!$B$7:$B$19,Industry_Results!E$7:E$19))/A_Thousand -> 3124.239 | N14: =(_xlfn.XLOOKUP($A14,Industry_Results!$B$7:$B$19,Industry_Results!F$7:F$19))/A_Thousand -> 3358.022 | O14: =(_xlfn.XLOOKUP($A14,Industry_Results!$B$7:$B$19,Industry_Results!G$7:G$19))/A_Thousand -> 3723.336 | P14: =(_xlfn.XLOOKUP($A14,Industry_Results!$B$7:$B$19,Industry_Results!H$7:H$19))/A_Thousand -> 4713.3081 | Q14: =IFERROR((D14-C14)/C14,0) -> 1.0911071 | R14: =IFERROR((E14-D14)/D14,0) -> 0.42958399 | S14: =IFERROR((F14-E14)/E14,0) -> -0.20934143 | T14: =IFERROR((G14-F14)/F14,0) -> 0.19031285 | U14: =IFERROR((H14-G14)/G14,0) -> -0.17588468 | V14: =IFERROR((I14-H14)/H14,0) -> 0.1587652 | W14: =IFERROR((K14-J14)/J14,0) -> -0.026220551 | X14: =IFERROR((L14-K14)/K14,0) -> 0.14488061 | Y14: =IFERROR((M14-L14)/L14,0) -> -8.9621022e-06 | Z14: =IFERROR((N14-M14)/M14,0) -> 0.074828782 | AA14: =IFERROR((O14-N14)/N14,0) -> 0.10878845 | AB14: =IFERROR((P14-O14)/O14,0) -> 0.2658831 | AD14: Liability | AE14: =IFERROR(C14/J14,0) -> 0.005299882 | AF14: =IFERROR(D14/K14,0) -> 0.011381038 | AG14: =IFERROR(E14/L14,0) -> 0.01421122 | AH14: =IFERROR(F14/M14,0) -> 0.011236323 | AI14: =IFERROR(G14/N14,0) -> 0.012443601 | AJ14: =IFERROR(H14/O14,0) -> 0.0092487995 | AK14: =IFERROR(I14/P14,0) -> 0.0084661743 | AL14: =IFERROR(C14/C$22,0) -> 0.045517667 | AM14: =IFERROR(D14/D$22,0) -> 0.052475065 | AN14: =IFERROR(E14/E$22,0) -> 0.051597893 | AO14: =IFERROR(F14/F$22,0) -> 0.039719756 | AP14: =IFERROR(G14/G$22,0) -> 0.029771393 | AQ14: =IFERROR(H14/H$22,0) -> 0.021052231 | AR14: =IFERROR(I14/I$22,0) -> 0.025009049 | AS14: =IFERROR(J14/J$22,0) -> 0.034496204 | ... AY14: =IFERROR(P14/P$22,0) -> 0.037673776 | AZ14: =AQ14-AN14 -> -0.030545662 | BE14: India | BF14: 2.74 | BG14: 0.97 | BH14: 3.7 | BL14: Motor Private | BM14: 15975963 | BN14: 21054114 | BO14: =(BN14-BM14)/BM14 -> 0.31786192 | BQ14: Motor Private | BR14: 17053831 | BS14: 22625802 | BT14: =(BS14-BR14)/BR14 -> 0.3267284 | BV14: Motor Private | BW14: 17965656 | BX14: 23431002 | BY14: =(BX14-BW14)/BW14 -> 0.30421077 | CA14: Motor Private | CB14: 17773498 | CC14: 22929301 | CD14: =(CC14-CB14)/CB14 -> 0.29008375 | CF14: 0.30583327 | CH14: Motor Private | CI14: 18222061 | CJ14: =CI14*(1+CF14) -> 23794974 | CR14: =SUM(CR11:CR13)=D22 -> TRUE | CS14: =SUM(CS11:CS13)=E22 -> TRUE | CT14: =SUM(CT11:CT13)=F22 -> TRUE | CU14: =SUM(CU11:CU13)=H22 -> TRUE
A15: Marine | B15: Marine | C15: =VLOOKUP($B15,RA!$R$150:$X$162,C$6,0)/A_Million -> 52.320818 | D15: =VLOOKUP($B15,RA!$R$150:$X$162,D$6,0)/A_Million -> 41.084397 | E15: =VLOOKUP($B15,RA!$R$150:$X$162,E$6,0)/A_Million -> 20.873293 | F15: =VLOOKUP($B15,RA!$R$150:$X$162,F$6,0)/A_Million -> 7.009653 | G15: =_xlfn.XLOOKUP(B15,RA!$C$78:$N$78,RA!$C$79:$N$79)/A_Million -> 33.832956 | H15: =_xlfn.XLOOKUP(B15,RA!$C$8:$N$8,RA!$C$44:$N$44)/A_Million -> 12.488935 | I15: =_xlfn.XLOOKUP(B15,RA!$C$8:$N$8,RA!$C$9:$N$9)/A_Million -> 12.032183 | J15: 3630.149 | K15: =(_xlfn.XLOOKUP($A15,Industry_Results!$B$7:$B$19,Industry_Results!C$7:C$19))/A_Thousand -> 3370.608 | L15: =(_xlfn.XLOOKUP($A15,Industry_Results!$B$7:$B$19,Industry_Results!D$7:D$19))/A_Thousand -> 3188.714 | M15: =(_xlfn.XLOOKUP($A15,Industry_Results!$B$7:$B$19,Industry_Results!E$7:E$19))/A_Thousand -> 3062.526 | N15: =(_xlfn.XLOOKUP($A15,Industry_Results!$B$7:$B$19,Industry_Results!F$7:F$19))/A_Thousand -> 3637.91 | O15: =(_xlfn.XLOOKUP($A15,Industry_Results!$B$7:$B$19,Industry_Results!G$7:G$19))/A_Thousand -> 4054.753 | P15: =(_xlfn.XLOOKUP($A15,Industry_Results!$B$7:$B$19,Industry_Results!H$7:H$19))/A_Thousand -> 4422.5328 | Q15: =IFERROR((D15-C15)/C15,0) -> -0.21476004 | R15: =IFERROR((E15-D15)/D15,0) -> -0.49194111 | S15: =IFERROR((F15-E15)/E15,0) -> -0.66418078 | T15: =IFERROR((G15-F15)/F15,0) -> 3.8266235 | U15: =IFERROR((H15-G15)/G15,0) -> -0.6308648 | V15: =IFERROR((I15-H15)/H15,0) -> -0.036572534 | W15: =IFERROR((K15-J15)/J15,0) -> -0.071495963 | X15: =IFERROR((L15-K15)/K15,0) -> -0.053964745 | Y15: =IFERROR((M15-L15)/L15,0) -> -0.03957332 | Z15: =IFERROR((N15-M15)/M15,0) -> 0.18787889 | AA15: =IFERROR((O15-N15)/N15,0) -> 0.1145831 | AB15: =IFERROR((P15-O15)/O15,0) -> 0.090703378 | AD15: Marine | AE15: =IFERROR(C15/J15,0) -> 0.014412857 | AF15: =IFERROR(D15/K15,0) -> 0.012189017 | AG15: =IFERROR(E15/L15,0) -> 0.006545991 | AH15: =IFERROR(F15/M15,0) -> 0.0022888469 | AI15: =IFERROR(G15/N15,0) -> 0.009300108 | AJ15: =IFERROR(H15/O15,0) -> 0.0030800729 | AK15: =IFERROR(I15/P15,0) -> 0.0027206543 | AL15: =IFERROR(C15/C$22,0) -> 0.16034705 | AM15: =IFERROR(D15/D$22,0) -> 0.069416079 | AN15: =IFERROR(E15/E$22,0) -> 0.024257355 | AO15: =IFERROR(F15/F$22,0) -> 0.0079311216 | AP15: =IFERROR(G15/G$22,0) -> 0.024105131 | AQ15: =IFERROR(H15/H$22,0) -> 0.0076349455 | AR15: =IFERROR(I15/I$22,0) -> 0.0075409936 | AS15: =IFERROR(J15/J$22,0) -> 0.044685686 | ... AY15: =IFERROR(P15/P$22,0) -> 0.03534959 | AZ15: =AQ15-AN15 -> -0.016622409 | BE15: Malaysia | BF15: 3.32 | BG15: 1.45 | BH15: 4.77 | BL15: Motor Commercial | BM15: 14102349 | BN15: 17690684 | BO15: =(BN15-BM15)/BM15 -> 0.25444948 | BQ15: Motor Commercial | BR15: 14653645 | BS15: 18331597 | BT15: =(BS15-BR15)/BR15 -> 0.2509923 | BV15: Motor Commercial | BW15: 14850185 | BX15: 23049684 | BY15: =(BX15-BW15)/BW15 -> 0.55214794 | CA15: Motor Commercial | CB15: 16582077 | CC15: 20232831 | CD15: =(CC15-CB15)/CB15 -> 0.22016265 | CF15: 0.32154614 | CH15: Motor Commercial | CI15: 17635556 | CJ15: =CI15*(1+CF15) -> 23306201
A16: Miscellaneous | B16: Miscellaneous | C16: =VLOOKUP($B16,RA!$R$150:$X$162,C$6,0)/A_Million -> 51.253865 | D16: =VLOOKUP($B16,RA!$R$150:$X$162,D$6,0)/A_Million -> 16.393128 | E16: =VLOOKUP($B16,RA!$R$150:$X$162,E$6,0)/A_Million -> 56.645425 | F16: =VLOOKUP($B16,RA!$R$150:$X$162,F$6,0)/A_Million -> 45.588151 | G16: =_xlfn.XLOOKUP(B16,RA!$C$78:$N$78,RA!$C$79:$N$79)/A_Million -> 89.810994 | H16: =_xlfn.XLOOKUP(B16,RA!$C$8:$N$8,RA!$C$44:$N$44)/A_Million -> 19.171387 | I16: =_xlfn.XLOOKUP(B16,RA!$C$8:$N$8,RA!$C$9:$N$9)/A_Million -> 5.450653 | J16: 3907.878 | K16: =(_xlfn.XLOOKUP($A16,Industry_Results!$B$7:$B$19,Industry_Results!C$7:C$19))/A_Thousand -> 3635.343 | L16: =(_xlfn.XLOOKUP($A16,Industry_Results!$B$7:$B$19,Industry_Results!D$7:D$19))/A_Thousand -> 3741.207 | M16: =(_xlfn.XLOOKUP($A16,Industry_Results!$B$7:$B$19,Industry_Results!E$7:E$19))/A_Thousand -> 3847.218 | N16: =(_xlfn.XLOOKUP($A16,Industry_Results!$B$7:$B$19,Industry_Results!F$7:F$19))/A_Thousand -> 4142.108 | O16: =(_xlfn.XLOOKUP($A16,Industry_Results!$B$7:$B$19,Industry_Results!G$7:G$19))/A_Thousand -> 3698.214 | P16: =(_xlfn.XLOOKUP($A16,Industry_Results!$B$7:$B$19,Industry_Results!H$7:H$19))/A_Thousand -> 6554.0875 | Q16: =IFERROR((D16-C16)/C16,0) -> -0.68015821 | R16: =IFERROR((E16-D16)/D16,0) -> 2.4554372 | S16: =IFERROR((F16-E16)/E16,0) -> -0.19520154 | T16: =IFERROR((G16-F16)/F16,0) -> 0.97005125 | U16: =IFERROR((H16-G16)/G16,0) -> -0.7865363 | V16: =IFERROR((I16-H16)/H16,0) -> -0.71568812 | W16: =IFERROR((K16-J16)/J16,0) -> -0.069739895 | X16: =IFERROR((L16-K16)/K16,0) -> 0.029120773 | Y16: =IFERROR((M16-L16)/L16,0) -> 0.028336042 | Z16: =IFERROR((N16-M16)/M16,0) -> 0.076650192 | AA16: =IFERROR((O16-N16)/N16,0) -> -0.10716621 | AB16: =IFERROR((P16-O16)/O16,0) -> 0.77223046 | AD16: Miscellaneous | AE16: =IFERROR(C16/J16,0) -> 0.013115523 | AF16: =IFERROR(D16/K16,0) -> 0.0045093759 | AG16: =IFERROR(E16/L16,0) -> 0.015140949 | AH16: =IFERROR(F16/M16,0) -> 0.011849641 | AI16: =IFERROR(G16/N16,0) -> 0.021682437 | AJ16: =IFERROR(H16/O16,0) -> 0.0051839583 | AK16: =IFERROR(I16/P16,0) -> 0.00083164178 | AL16: =IFERROR(C16/C$22,0) -> 0.15707717 | AM16: =IFERROR(D16/D$22,0) -> 0.027697782 | AN16: =IFERROR(E16/E$22,0) -> 0.065829008 | AO16: =IFERROR(F16/F$22,0) -> 0.051581037 | AP16: =IFERROR(G16/G$22,0) -> 0.063988077 | AQ16: =IFERROR(H16/H$22,0) -> 0.011720174 | AR16: =IFERROR(I16/I$22,0) -> 0.0034161166 | AS16: =IFERROR(J16/J$22,0) -> 0.048104419 | ... AY16: =IFERROR(P16/P$22,0) -> 0.052387244 | AZ16: =AQ16-AN16 -> -0.054108834 | BL16: Motor Commercial PSV | BM16: 4014909 | BN16: 5035069 | BO16: =(BN16-BM16)/BM16 -> 0.25409293 | BQ16: Motor Commercial PSV | BR16: 3765659 | BS16: 5310529 | BT16: =(BS16-BR16)/BR16 -> 0.41025223 | BV16: Motor Commercial PSV | BW16: 3481084 | BX16: 3866000 | BY16: =(BX16-BW16)/BW16 -> 0.1105736 | CA16: Motor Commercial PSV | CB16: 2576000 | CC16: 2869000 | CD16: =(CC16-CB16)/CB16 -> 0.11374224 | CF16: 0.21153162 | CH16: Motor Commercial PSV | CI16: 3220000 | CJ16: =CI16*(1+CF16) -> 3901131.8
A17: Motor Commercial | B17: Motor Commercial | C17: =VLOOKUP($B17,RA!$R$150:$X$162,C$6,0)/A_Million -> 41.901179 | D17: =VLOOKUP($B17,RA!$R$150:$X$162,D$6,0)/A_Million -> 115.54972 | E17: =VLOOKUP($B17,RA!$R$150:$X$162,E$6,0)/A_Million -> 164.98612 | F17: =VLOOKUP($B17,RA!$R$150:$X$162,F$6,0)/A_Million -> 174.75533 | G17: =_xlfn.XLOOKUP(B17,RA!$C$78:$N$78,RA!$C$79:$N$79)/A_Million -> 241.08614 | H17: =_xlfn.XLOOKUP(B17,RA!$C$8:$N$8,RA!$C$44:$N$44)/A_Million -> 305.36273 | I17: =_xlfn.XLOOKUP(B17,RA!$C$8:$N$8,RA!$C$9:$N$9)/A_Million -> 371.11704 | J17: 17690.684 | K17: =(_xlfn.XLOOKUP($A17,Industry_Results!$B$7:$B$19,Industry_Results!C$7:C$19))/A_Thousand -> 23593.081 | L17: =(_xlfn.XLOOKUP($A17,Industry_Results!$B$7:$B$19,Industry_Results!D$7:D$19))/A_Thousand -> 23049.684 | M17: =(_xlfn.XLOOKUP($A17,Industry_Results!$B$7:$B$19,Industry_Results!E$7:E$19))/A_Thousand -> 21289.589 | N17: =(_xlfn.XLOOKUP($A17,Industry_Results!$B$7:$B$19,Industry_Results!F$7:F$19))/A_Thousand -> 24279.823 | O17: =(_xlfn.XLOOKUP($A17,Industry_Results!$B$7:$B$19,Industry_Results!G$7:G$19))/A_Thousand -> 26132.363 | P17: =(_xlfn.XLOOKUP($A17,Industry_Results!$B$7:$B$19,Industry_Results!H$7:H$19))/A_Thousand -> 26342.102 | Q17: =IFERROR((D17-C17)/C17,0) -> 1.7576722 | R17: =IFERROR((E17-D17)/D17,0) -> 0.42783664 | S17: =IFERROR((F17-E17)/E17,0) -> 0.059212296 | T17: =IFERROR((G17-F17)/F17,0) -> 0.3795639 | U17: =IFERROR((H17-G17)/G17,0) -> 0.26661253 | V17: =IFERROR((I17-H17)/H17,0) -> 0.21533183 | W17: =IFERROR((K17-J17)/J17,0) -> 0.33364436 | X17: =IFERROR((L17-K17)/K17,0) -> -0.023032049 | Y17: =IFERROR((M17-L17)/L17,0) -> -0.076360917 | Z17: =IFERROR((N17-M17)/M17,0) -> 0.14045522 | AA17: =IFERROR((O17-N17)/N17,0) -> 0.076299568 | AB17: =IFERROR((P17-O17)/O17,0) -> 0.0080260334 | AD17: Motor Commercial | AE17: =IFERROR(C17/J17,0) -> 0.0023685449 | AF17: =IFERROR(D17/K17,0) -> 0.0048976103 | AG17: =IFERROR(E17/L17,0) -> 0.0071578474 | AH17: =IFERROR(F17/M17,0) -> 0.0082084876 | AI17: =IFERROR(G17/N17,0) -> 0.0099294851 | AJ17: =IFERROR(H17/O17,0) -> 0.011685232 | AK17: =IFERROR(I17/P17,0) -> 0.014088361 | AL17: =IFERROR(C17/C$22,0) -> 0.1284141 | AM17: =IFERROR(D17/D$22,0) -> 0.19523247 | AN17: =IFERROR(E17/E$22,0) -> 0.19173433 | AO17: =IFERROR(F17/F$22,0) -> 0.19772815 | AP17: =IFERROR(G17/G$22,0) -> 0.17176782 | AQ17: =IFERROR(H17/H$22,0) -> 0.18667947 | AR17: =IFERROR(I17/I$22,0) -> 0.23259214 | AS17: =IFERROR(J17/J$22,0) -> 0.21776526 | ... AY17: =IFERROR(P17/P$22,0) -> 0.21055412 | AZ17: =AQ17-AN17 -> -0.0050548616 | BE17: Source: Swiss Re Sigma No 3/2019 | BL17: Personal Accident | BM17: 2907964.4 | BN17: 3627120 | BO17: =(BN17-BM17)/BM17 -> 0.24730551 | BQ17: Personal Accident | BR17: 2634756 | BS17: 3181115 | BT17: =(BS17-BR17)/BR17 -> 0.20736607 | BV17: Personal Accident | BW17: 2898134 | BX17: 3283857 | BY17: =(BX17-BW17)/BW17 -> 0.13309357 | CA17: Personal Accident | CB17: 1861806 | CC17: 2324009 | CD17: =(CC17-CB17)/CB17 -> 0.24825519 | CF17: 0.22092152 | CH17: Personal Accident | CI17: 2116821 | CJ17: =CI17*(1+CF17) -> 2584472.3
A18: Motor Private | B18: Motor Private | C18: =VLOOKUP($B18,RA!$R$150:$X$162,C$6,0)/A_Million -> 69.118265 | D18: =VLOOKUP($B18,RA!$R$150:$X$162,D$6,0)/A_Million -> 222.94181 | E18: =VLOOKUP($B18,RA!$R$150:$X$162,E$6,0)/A_Million -> 390.51559 | F18: =VLOOKUP($B18,RA!$R$150:$X$162,F$6,0)/A_Million -> 455.07361 | G18: =_xlfn.XLOOKUP(B18,RA!$C$78:$N$78,RA!$C$79:$N$79)/A_Million -> 634.98359 | H18: =_xlfn.XLOOKUP(B18,RA!$C$8:$N$8,RA!$C$44:$N$44)/A_Million -> 818.54838 | I18: =_xlfn.XLOOKUP(B18,RA!$C$8:$N$8,RA!$C$9:$N$9)/A_Million -> 915.64001 | J18: 21054.114 | K18: =(_xlfn.XLOOKUP($A18,Industry_Results!$B$7:$B$19,Industry_Results!C$7:C$19))/A_Thousand -> 22495.605 | L18: =(_xlfn.XLOOKUP($A18,Industry_Results!$B$7:$B$19,Industry_Results!D$7:D$19))/A_Thousand -> 23431.002 | M18: =(_xlfn.XLOOKUP($A18,Industry_Results!$B$7:$B$19,Industry_Results!E$7:E$19))/A_Thousand -> 23438.81 | N18: =(_xlfn.XLOOKUP($A18,Industry_Results!$B$7:$B$19,Industry_Results!F$7:F$19))/A_Thousand -> 24626.67 | O18: =(_xlfn.XLOOKUP($A18,Industry_Results!$B$7:$B$19,Industry_Results!G$7:G$19))/A_Thousand -> 27855.16 | P18: =(_xlfn.XLOOKUP($A18,Industry_Results!$B$7:$B$19,Industry_Results!H$7:H$19))/A_Thousand -> 29261.434 | Q18: =IFERROR((D18-C18)/C18,0) -> 2.2255123 | R18: =IFERROR((E18-D18)/D18,0) -> 0.75164807 | S18: =IFERROR((F18-E18)/E18,0) -> 0.16531482 | T18: =IFERROR((G18-F18)/F18,0) -> 0.3953426 | U18: =IFERROR((H18-G18)/G18,0) -> 0.28908588 | V18: =IFERROR((I18-H18)/H18,0) -> 0.1186144 | W18: =IFERROR((K18-J18)/J18,0) -> 0.068466001 | X18: =IFERROR((L18-K18)/K18,0) -> 0.041581322 | Y18: =IFERROR((M18-L18)/L18,0) -> 0.00033323372 | Z18: =IFERROR((N18-M18)/M18,0) -> 0.050679194 | AA18: =IFERROR((O18-N18)/N18,0) -> 0.1310973 | AB18: =IFERROR((P18-O18)/O18,0) -> 0.050485209 | AD18: Motor Private | AE18: =IFERROR(C18/J18,0) -> 0.0032828864 | AF18: =IFERROR(D18/K18,0) -> 0.0099104608 | AG18: =IFERROR(E18/L18,0) -> 0.016666619 | AH18: =IFERROR(F18/M18,0) -> 0.019415389 | AI18: =IFERROR(G18/N18,0) -> 0.025784387 | AJ18: =IFERROR(H18/O18,0) -> 0.02938588 | AK18: =IFERROR(I18/P18,0) -> 0.0312917 | AL18: =IFERROR(C18/C$22,0) -> 0.21182601 | AM18: =IFERROR(D18/D$22,0) -> 0.37668184 | AN18: =IFERROR(E18/E$22,0) -> 0.45382755 | AO18: =IFERROR(F18/F$22,0) -> 0.51489626 | AP18: =IFERROR(G18/G$22,0) -> 0.45240985 | AQ18: =IFERROR(H18/H$22,0) -> 0.50040874 | AR18: =IFERROR(I18/I$22,0) -> 0.5738639 | AS18: =IFERROR(J18/J$22,0) -> 0.25916774 | ... AY18: =IFERROR(P18/P$22,0) -> 0.23388853 | AZ18: =AQ18-AN18 -> 0.046581196 | BL18: Theft | BM18: 3250808.3 | BN18: 3799559 | BO18: =(BN18-BM18)/BM18 -> 0.16880437 | BQ18: Theft | BR18: 3429776 | BS18: 3871780 | BT18: =(BS18-BR18)/BR18 -> 0.12887256 | BV18: Theft | BW18: 3451352 | BX18: 3835945 | BY18: =(BX18-BW18)/BW18 -> 0.11143256 | CA18: Theft | CB18: 3305788 | CC18: 3786102 | CD18: =(CC18-CB18)/CB18 -> 0.14529486 | CF18: 0.13573746 | CH18: Theft | CI18: 3563454 | CJ18: =CI18*(1+CF18) -> 4047148.2
A19: Personal Accident | B19: Personal Accident | C19: =VLOOKUP($B19,RA!$R$150:$X$162,C$6,0)/A_Million -> 13.713238 | D19: =VLOOKUP($B19,RA!$R$150:$X$162,D$6,0)/A_Million -> 32.135189 | E19: =VLOOKUP($B19,RA!$R$150:$X$162,E$6,0)/A_Million -> 34.137545 | F19: =VLOOKUP($B19,RA!$R$150:$X$162,F$6,0)/A_Million -> 6.368504 | G19: =_xlfn.XLOOKUP(B19,RA!$C$78:$N$78,RA!$C$79:$N$79)/A_Million -> 6.504649 | H19: =_xlfn.XLOOKUP(B19,RA!$C$8:$N$8,RA!$C$44:$N$44)/A_Million -> 7.134489 | I19: =_xlfn.XLOOKUP(B19,RA!$C$8:$N$8,RA!$C$9:$N$9)/A_Million -> 9.359638 | J19: 3627.12 | K19: =(_xlfn.XLOOKUP($A19,Industry_Results!$B$7:$B$19,Industry_Results!C$7:C$19))/A_Thousand -> 3157.233 | L19: =(_xlfn.XLOOKUP($A19,Industry_Results!$B$7:$B$19,Industry_Results!D$7:D$19))/A_Thousand -> 3283.857 | M19: =(_xlfn.XLOOKUP($A19,Industry_Results!$B$7:$B$19,Industry_Results!E$7:E$19))/A_Thousand -> 2362.117 | N19: =(_xlfn.XLOOKUP($A19,Industry_Results!$B$7:$B$19,Industry_Results!F$7:F$19))/A_Thousand -> 2400.674 | O19: =(_xlfn.XLOOKUP($A19,Industry_Results!$B$7:$B$19,Industry_Results!G$7:G$19))/A_Thousand -> 2331.266 | P19: =(_xlfn.XLOOKUP($A19,Industry_Results!$B$7:$B$19,Industry_Results!H$7:H$19))/A_Thousand -> 3105.8408 | Q19: =IFERROR((D19-C19)/C19,0) -> 1.3433699 | R19: =IFERROR((E19-D19)/D19,0) -> 0.062310385 | S19: =IFERROR((F19-E19)/E19,0) -> -0.81344575 | T19: =IFERROR((G19-F19)/F19,0) -> 0.021377862 | U19: =IFERROR((H19-G19)/G19,0) -> 0.096829206 | V19: =IFERROR((I19-H19)/H19,0) -> 0.31188625 | W19: =IFERROR((K19-J19)/J19,0) -> -0.12954824 | X19: =IFERROR((L19-K19)/K19,0) -> 0.040106004 | Y19: =IFERROR((M19-L19)/L19,0) -> -0.28068823 | Z19: =IFERROR((N19-M19)/M19,0) -> 0.01632307 | AA19: =IFERROR((O19-N19)/N19,0) -> -0.028911881 | AB19: =IFERROR((P19-O19)/O19,0) -> 0.33225502 | AD19: Personal Accident | AE19: =IFERROR(C19/J19,0) -> 0.0037807511 | AF19: =IFERROR(D19/K19,0) -> 0.010178276 | AG19: =IFERROR(E19/L19,0) -> 0.010395564 | AH19: =IFERROR(F19/M19,0) -> 0.0026961002 | AI19: =IFERROR(G19/N19,0) -> 0.0027095095 | AJ19: =IFERROR(H19/O19,0) -> 0.0030603496 | AK19: =IFERROR(I19/P19,0) -> 0.0030135601 | AL19: =IFERROR(C19/C$22,0) -> 0.042026814 | AM19: =IFERROR(D19/D$22,0) -> 0.054295523 | AN19: =IFERROR(E19/E$22,0) -> 0.039672061 | AO19: =IFERROR(F19/F$22,0) -> 0.007205689 | AP19: =IFERROR(G19/G$22,0) -> 0.004634399 | AQ19: =IFERROR(H19/H$22,0) -> 0.0043615756 | AR19: =IFERROR(I19/I$22,0) -> 0.0058660154 | AS19: =IFERROR(J19/J$22,0) -> 0.0446484 | ... AY19: =IFERROR(P19/P$22,0) -> 0.024825186 | AZ19: =AQ19-AN19 -> -0.035310485 | BE19: Insurance Penetration 2017 | BL19: Workmen's Compensation | BM19: 5060720.8 | BN19: 5750314 | BO19: =(BN19-BM19)/BM19 -> 0.13626383 | BQ19: Workmen's Compensation | BR19: 5293094 | BS19: 6453468 | BT19: =(BS19-BR19)/BR19 -> 0.21922414 | BV19: Workmen's Compensation | BW19: 5368237 | BX19: 6358473 | BY19: =(BX19-BW19)/BW19 -> 0.18446205 | CA19: Workmen's Compensation | CB19: 5565305 | CC19: 6471977 | CD19: =(CC19-CB19)/CB19 -> 0.16291506 | CF19: 0.19019179 | CH19: Workmen's Compensation | CI19: 11028416 | CJ19: =CI19*(1+CF19) -> 13125930
A20: Theft | B20: Theft | C20: =VLOOKUP($B20,RA!$R$150:$X$162,C$6,0)/A_Million -> 3.353895 | D20: =VLOOKUP($B20,RA!$R$150:$X$162,D$6,0)/A_Million -> 14.20462 | E20: =VLOOKUP($B20,RA!$R$150:$X$162,E$6,0)/A_Million -> 15.523961 | F20: =VLOOKUP($B20,RA!$R$150:$X$162,F$6,0)/A_Million -> 15.657691 | G20: =_xlfn.XLOOKUP(B20,RA!$C$78:$N$78,RA!$C$79:$N$79)/A_Million -> 16.801809 | H20: =_xlfn.XLOOKUP(B20,RA!$C$8:$N$8,RA!$C$44:$N$44)/A_Million -> 14.67183 | I20: =_xlfn.XLOOKUP(B20,RA!$C$8:$N$8,RA!$C$9:$N$9)/A_Million -> 16.95737 | J20: 3799.559 | K20: =(_xlfn.XLOOKUP($A20,Industry_Results!$B$7:$B$19,Industry_Results!C$7:C$19))/A_Thousand -> 3863.654 | L20: =(_xlfn.XLOOKUP($A20,Industry_Results!$B$7:$B$19,Industry_Results!D$7:D$19))/A_Thousand -> 3835.945 | M20: =(_xlfn.XLOOKUP($A20,Industry_Results!$B$7:$B$19,Industry_Results!E$7:E$19))/A_Thousand -> 3845.254 | N20: =(_xlfn.XLOOKUP($A20,Industry_Results!$B$7:$B$19,Industry_Results!F$7:F$19))/A_Thousand -> 3992.205 | O20: =(_xlfn.XLOOKUP($A20,Industry_Results!$B$7:$B$19,Industry_Results!G$7:G$19))/A_Thousand -> 4119.725 | P20: =(_xlfn.XLOOKUP($A20,Industry_Results!$B$7:$B$19,Industry_Results!H$7:H$19))/A_Thousand -> 5020.7067 | Q20: =IFERROR((D20-C20)/C20,0) -> 3.2352608 | R20: =IFERROR((E20-D20)/D20,0) -> 0.092881119 | S20: =IFERROR((F20-E20)/E20,0) -> 0.0086144251 | T20: =IFERROR((G20-F20)/F20,0) -> 0.073070672 | U20: =IFERROR((H20-G20)/G20,0) -> -0.12677081 | V20: =IFERROR((I20-H20)/H20,0) -> 0.15577743 | W20: =IFERROR((K20-J20)/J20,0) -> 0.016869063 | X20: =IFERROR((L20-K20)/K20,0) -> -0.0071717084 | Y20: =IFERROR((M20-L20)/L20,0) -> 0.0024267814 | Z20: =IFERROR((N20-M20)/M20,0) -> 0.038216201 | AA20: =IFERROR((O20-N20)/N20,0) -> 0.031942247 | AB20: =IFERROR((P20-O20)/O20,0) -> 0.21869947 | AD20: Theft | AE20: =IFERROR(C20/J20,0) -> 0.00088270639 | AF20: =IFERROR(D20/K20,0) -> 0.0036764731 | AG20: =IFERROR(E20/L20,0) -> 0.0040469717 | AH20: =IFERROR(F20/M20,0) -> 0.0040719523 | AI20: =IFERROR(G20/N20,0) -> 0.0042086539 | AJ20: =IFERROR(H20/O20,0) -> 0.0035613615 | AK20: =IFERROR(I20/P20,0) -> 0.0033774867 | AL20: =IFERROR(C20/C$22,0) -> 0.010278646 | AM20: =IFERROR(D20/D$22,0) -> 0.024000085 | AN20: =IFERROR(E20/E$22,0) -> 0.018040768 | AO20: =IFERROR(F20/F$22,0) -> 0.017716006 | AP20: =IFERROR(G20/G$22,0) -> 0.011970867 | AQ20: =IFERROR(H20/H$22,0) -> 0.0089694295 | AR20: =IFERROR(I20/I$22,0) -> 0.010627782 | AS20: =IFERROR(J20/J$22,0) -> 0.046771055 | ... AY20: =IFERROR(P20/P$22,0) -> 0.040130832 | AZ20: =AQ20-AN20 -> -0.0090713383 | BF20: Life | BG20: General | BH20: Combined | BL20: Medical | BM20: 30836145 | BN20: 38436547 | BO20: =(BN20-BM20)/BM20 -> 0.24647705 | BQ20: Medical | BR20: 31861155 | BS20: 40286003 | BT20: =(BS20-BR20)/BR20 -> 0.26442381 | BV20: Medical | BW20: 33660613 | BX20: 42348102 | BY20: =(BX20-BW20)/BW20 -> 0.25809064 | CA20: Medical | CB20: 36255680 | CC20: 44975616 | CD20: =(CC20-CB20)/CB20 -> 0.24051227 | CF20: 0.25510469 | CH20: Medical | CI20: 40851368 | CJ20: =CI20*(1+CF20) -> 51272744
A21: Workmen's Compensation | B21: Workmen's Compensation | C21: =VLOOKUP($B21,RA!$R$150:$X$162,C$6,0)/A_Million -> 17.265425 | D21: =VLOOKUP($B21,RA!$R$150:$X$162,D$6,0)/A_Million -> 34.318478 | E21: =VLOOKUP($B21,RA!$R$150:$X$162,E$6,0)/A_Million -> 37.338889 | F21: =VLOOKUP($B21,RA!$R$150:$X$162,F$6,0)/A_Million -> 50.737276 | G21: =_xlfn.XLOOKUP(B21,RA!$C$78:$N$78,RA!$C$79:$N$79)/A_Million -> 249.24429 | H21: =_xlfn.XLOOKUP(B21,RA!$C$8:$N$8,RA!$C$44:$N$44)/A_Million -> 295.95851 | I21: =_xlfn.XLOOKUP(B21,RA!$C$8:$N$8,RA!$C$9:$N$9)/A_Million -> 105.38564 | J21: 5750.314 | K21: =(_xlfn.XLOOKUP($A21,Industry_Results!$B$7:$B$19,Industry_Results!C$7:C$19))/A_Thousand -> 6225.354 | L21: =(_xlfn.XLOOKUP($A21,Industry_Results!$B$7:$B$19,Industry_Results!D$7:D$19))/A_Thousand -> 6358.473 | M21: =(_xlfn.XLOOKUP($A21,Industry_Results!$B$7:$B$19,Industry_Results!E$7:E$19))/A_Thousand -> 6234.247 | N21: =(_xlfn.XLOOKUP($A21,Industry_Results!$B$7:$B$19,Industry_Results!F$7:F$19))/A_Thousand -> 10659.325 | O21: =(_xlfn.XLOOKUP($A21,Industry_Results!$B$7:$B$19,Industry_Results!G$7:G$19))/A_Thousand -> 11712.076 | P21: =(_xlfn.XLOOKUP($A21,Industry_Results!$B$7:$B$19,Industry_Results!H$7:H$19))/A_Thousand -> 12976.448 | Q21: =IFERROR((D21-C21)/C21,0) -> 0.98769958 | R21: =IFERROR((E21-D21)/D21,0) -> 0.088011217 | S21: =IFERROR((F21-E21)/E21,0) -> 0.35883197 | T21: =IFERROR((G21-F21)/F21,0) -> 3.9124492 | U21: =IFERROR((H21-G21)/G21,0) -> 0.18742341 | V21: =IFERROR((I21-H21)/H21,0) -> -0.64391753 | W21: =IFERROR((K21-J21)/J21,0) -> 0.082611141 | X21: =IFERROR((L21-K21)/K21,0) -> 0.021383362 | Y21: =IFERROR((M21-L21)/L21,0) -> -0.019537081 | Z21: =IFERROR((N21-M21)/M21,0) -> 0.70980152 | AA21: =IFERROR((O21-N21)/N21,0) -> 0.098763383 | AB21: =IFERROR((P21-O21)/O21,0) -> 0.10795456 | AD21: Workmen's Compensation | AE21: =IFERROR(C21/J21,0) -> 0.0030025186 | AF21: =IFERROR(D21/K21,0) -> 0.005512695 | AG21: =IFERROR(E21/L21,0) -> 0.0058723044 | AH21: =IFERROR(F21/M21,0) -> 0.008138477 | AI21: =IFERROR(G21/N21,0) -> 0.023382746 | AJ21: =IFERROR(H21/O21,0) -> 0.025269517 | AK21: =IFERROR(I21/P21,0) -> 0.0081213007 | AL21: =IFERROR(C21/C$22,0) -> 0.052913164 | AM21: =IFERROR(D21/D$22,0) -> 0.057984402 | AN21: =IFERROR(E21/E$22,0) -> 0.043392419 | AO21: =IFERROR(F21/F$22,0) -> 0.057407051 | AP21: =IFERROR(G21/G$22,0) -> 0.17758029 | AQ21: =IFERROR(H21/H$22,0) -> 0.18093032 | AR21: =IFERROR(I21/I$22,0) -> 0.066048896 | AS21: =IFERROR(J21/J$22,0) -> 0.070784071 | ... AY21: =IFERROR(P21/P$22,0) -> 0.10372159 | AZ21: =AQ21-AN21 -> 0.1375379 | BE21: Kenya | BF21: 1.05 | BG21: 1.55 | BH21: 2.6 | BL21: Miscellaneous | BM21: 2767882.7 | BN21: 3907878 | BO21: =(BN21-BM21)/BM21 -> 0.41186544 | BQ21: Miscellaneous | BR21: 2733496 | BS21: 3810344 | BT21: =(BS21-BR21)/BR21 -> 0.39394534 | BV21: Miscellaneous | BW21: 2856753 | BX21: 3741207 | BY21: =(BX21-BW21)/BW21 -> 0.30960115 | CA21: Miscellaneous | CB21: 2923486 | CC21: 4218501 | CD21: =(CC21-CB21)/CB21 -> 0.44296945 | CF21: 0.40090595 | CH21: Miscellaneous | CI21: 3068716 | CJ21: =CI21*(1+CF21) -> 4298982.5
A22: Medical | B22: Total | C22: =SUM(C10:C21) -> 326.29735 | D22: =SUM(D10:D21) -> 591.85707 | E22: =SUM(E10:E21) -> 860.49337 | F22: =SUM(F10:F21) -> 883.81611 | G22: =SUM(G10:G21) -> 1403.5583 | H22: =SUM(H10:H21) -> 1635.7596 | I22: =SUM(I10:I21) -> 1595.57 | J22: 81237.402 | K22: =SUM(K10:K21) -> 87315.732 | L22: =SUM(L10:L21) -> 88167.953 | M22: =SUM(M10:M21) -> 85995.719 | N22: =SUM(N10:N21) -> 99194.977 | O22: =SUM(O10:O21) -> 110900.31 | P22: =SUM(P10:P21) -> 125108.46 | Q22: =IFERROR((D22-C22)/C22,0) -> 0.81385804 | R22: =IFERROR((E22-D22)/D22,0) -> 0.45388712 | S22: =IFERROR((F22-E22)/E22,0) -> 0.027103915 | T22: =IFERROR((G22-F22)/F22,0) -> 0.58806595 | U22: =IFERROR((H22-G22)/G22,0) -> 0.16543758 | V22: =IFERROR((I22-H22)/H22,0) -> -0.02456937 | W22: =IFERROR((K22-J22)/J22,0) -> 0.074821817 | X22: =IFERROR((L22-K22)/K22,0) -> 0.0097602228 | Y22: =IFERROR((M22-L22)/L22,0) -> -0.024637455 | Z22: =IFERROR((N22-M22)/M22,0) -> 0.15348738 | AA22: =IFERROR((O22-N22)/N22,0) -> 0.11800325 | AB22: =IFERROR((P22-O22)/O22,0) -> 0.12811646 | AD22: Total | AE22: =IFERROR(C22/J22,0) -> 0.0040165901 | AF22: =IFERROR(D22/K22,0) -> 0.0067783554 | AG22: =IFERROR(E22/L22,0) -> 0.0097597068 | AH22: =IFERROR(F22/M22,0) -> 0.010277443 | AI22: =IFERROR(G22/N22,0) -> 0.014149489 | AJ22: =IFERROR(H22/O22,0) -> 0.01474982 | AK22: =IFERROR(I22/P22,0) -> 0.012753494 | AL22: =IFERROR(C22/C$22,0) -> 1 | AM22: =IFERROR(D22/D$22,0) -> 1 | AN22: =IFERROR(E22/E$22,0) -> 1 | AO22: =IFERROR(F22/F$22,0) -> 1 | AP22: =IFERROR(G22/G$22,0) -> 1 | AQ22: =IFERROR(H22/H$22,0) -> 1 | AR22: =IFERROR(I22/I$22,0) -> 1 | AS22: =IFERROR(J22/J$22,0) -> 1 | ... AY22: =IFERROR(P22/P$22,0) -> 1 | BE22: South Africa | BF22: 11.02 | BG22: 2.74 | BH22: 13.75 | BL22: Total | BM22: =SUM(BM8:BM21) -> 99753087 | BN22: =SUM(BN8:BN21) -> 124709018 | BO22: =(BN22-BM22)/BM22 -> 0.25017703 | BQ22: Total | BR22: =SUM(BR8:BR21) -> 101462855 | BS22: =SUM(BS8:BS21) -> 129027334 | BT22: =(BS22-BR22)/BR22 -> 0.27167064 | BV22: Total | BW22: =SUM(BW8:BW21) -> 105232095 | BX22: 130516055 | BY22: =(BX22-BW22)/BW22 -> 0.24026852 | CA22: Total | CB22: =SUM(CB8:CB21) -> 107674737 | CC22: =SUM(CC8:CC21) -> 133705420 | CD22: =(CC22-CB22)/CB22 -> 0.24175293 | CF22: 0.26540915 | CH22: Total | CI22: =SUM(CI8:CI21) -> 124630808 | CJ22: =SUM(CJ8:CJ21) -> 1.5738072e+08
AD23: *Based on Projected Industry Results | BE23: UK | BF23: 7.22 | BG23: 2.36 | BH23: 9.58
B24: Industry Totals | J24: 124709.02 | K24: =Industry_Results!C20/A_Thousand -> 127511.72 | L24: =Industry_Results!D20/A_Thousand -> 130516.05 | M24: =Industry_Results!E20/A_Thousand -> 131057.26 | N24: =Industry_Results!F20/A_Thousand -> 146781.14 | O24: =Industry_Results!G20/A_Thousand -> 165739.48 | P24: =Industry_Results!H20/A_Thousand -> 193020.53 | AD24: **Industry results exclude Medical and Motor Commercial PSV Lines of Business | BE24: US | BF24: 2.82 | BG24: 4.28 | BH24: 7.1 | BN24: =(BN22-BN16-BN20)/A_Thousand -> 81237.402 | BS24: =(BS22-BS16-BS20)/A_Thousand -> 83430.802 | BX24: =(BX22-BX20)/A_Thousand -> 88167.953 | CC24: =(CC22-CC16-CC20)/A_Thousand -> 85860.804 | CJ24: =(CJ22-CJ16-CJ20)/A_Thousand -> 102206.84
B25: *Based on Projected Industry Results | AL25: =SUM(AL17:AL18) -> 0.34024011 | AM25: =SUM(AM17:AM18) -> 0.57191431 | AN25: =SUM(AN17:AN18) -> 0.64556188 | AO25: =SUM(AO17:AO18) -> 0.71262441 | AP25: =SUM(AP17:AP18) -> 0.62417767 | AQ25: =SUM(AQ17:AQ18) -> 0.68708821 | AR25: =SUM(AR17:AR18) -> 0.80645604 | AS25: =SUM(AS17:AS18) -> 0.476933 | ... AY25: =SUM(AY17:AY18) -> 0.44444265 | BE25: Africa | BF25: 2 | BG25: 0.9 | BH25: 2.96
E26: Overall Growth | F26: =H22/G22-1 -> 0.16543758 | BE26: India | BF26: 2.76 | BG26: 0.93 | BH26: 3.69
E27: Motor Growth | F27: =SUM(H17:H18)/SUM(G17:G18)-1 -> 0.28290143 | BE27: Malaysia | BF27: 3.32 | BG27: 1.44 | BH27: 4.77
E28: Non-Motor Growth | F28: =(H22-SUM(H17:H18))/(G22-SUM(G17:G18))-1 -> -0.029650098 | AX28: =AVERAGE(AU25:AY25) -> 0.49431899 | BE28: Source: Swiss Re Sigma No 3/2018
D30: =SUM(D17:D18)/D22 -> 0.57191431 | E30: =SUM(E17:E18)/E22 -> 0.64556188 | F30: =SUM(F17:F18)/F22 -> 0.71262441 | G30: =SUM(G17:G18)/G22 -> 0.62417767 | H30: =SUM(H17:H18)/H22 -> 0.68708821 | I30: =SUM(I17:I18)/I22 -> 0.80645604 | J30: =SUM(J17:J18)/J22 -> 0.476933 | K30: =SUM(K17:K18)/K22 -> 0.52783943 | ... P30: =SUM(P17:P18)/P22 -> 0.44444265
BE32: Insurance Penetration 2018
BF33: Life | BG33: General | BH33: Combined
BE34: Kenya | BF34: 0.96 | BG34: 1.42 | BH34: 2.37
BE35: South Africa | BF35: 10.27 | BG35: 2.62 | BH35: 12.89
C36: 2017 | D36: 2018 | E36: 2019 | F36: 2020 | G36: 2021 | H36: 2022 | I36: 2023 | BE36: Namibia | BF36: 5.19 | BG36: 2.06 | BH36: 7.25
B37: GWP | D37: =D22 -> 591.85707 | E37: =E22 -> 860.49337 | F37: =F22 -> 883.81611 | G37: =G22 -> 1403.5583 | H37: =H22 -> 1635.7596 | I37: =I22 -> 1595.57 | BE37: UK | BF37: 8.32 | BG37: 2.29 | BH37: 10.61
B38: Market Share | D38: =AF22 -> 0.0067783554 | E38: =AG22 -> 0.0097597068 | F38: =AH22 -> 0.010277443 | G38: =AI22 -> 0.014149489 | H38: =AJ22 -> 0.01474982 | I38: =AK22 -> 0.012753494 | BE38: US | BF38: 2.88 | BG38: 4.26 | BH38: 7.14
BE39: India | BF39: 3.7 | BG39: 2.74 | BH39: 0.97
BE40: Malaysia | BF40: 4.77 | BG40: 3.32 | BH40: 1.45
BE41: Source: Swiss Re Sigma No 3/2019
BE44: Insurance Penetration 2019
BF45: Life | BG45: General | BH45: Combined
BE46: Kenya | BF46: 0.99 | BG46: 1.33 | BH46: =SUM(BF46:BG46) -> 2.32
BE47: South Africa | BF47: 10.73 | BG47: 2.67 | BH47: =SUM(BF47:BG47) -> 13.4
BE48: UK | BF48: 7.99 | BG48: 2.31 | BH48: 10.3
BE49: US | BF49: 2.92 | BG49: 8.51 | BH49: 11.43
BE50: India | BF50: 2.82 | BG50: 0.94 | BH50: 3.76
BE51: Malaysia | BF51: 3.35 | BG51: 1.37 | BH51: 4.72
BE52: World | BF52: 3.35 | BG52: 3.88 | BH52: =SUM(BF52:BG52) -> 7.23
BE53: Source: Swiss Re Sigma No 4/2020
BE56: Insurance Penetration 2020
BF57: Life | BG57: General | BH57: Combined
BE58: Kenya | BF58: 1 | BG58: 1.2 | BH58: =SUM(BF58:BG58) -> 2.2
BE59: South Africa | BF59: 11.2 | BG59: 2.5 | BH59: =SUM(BF59:BG59) -> 13.7
BE60: UK | BF60: 8.8 | BG60: 2.3 | BH60: 11.1
BE61: US | BF61: 3 | BG61: 9 | BH61: 12
BE62: India | BF62: 3.2 | BG62: 1 | BH62: 4.2
BE63: Malaysia | BF63: 4 | BG63: 1.5 | BH63: 5.5
BE64: World | BF64: 3.3 | BG64: 4.1 | BH64: =SUM(BF64:BG64) -> 7.4
BE65: Source: Swiss Re Sigma No 3/2021
BE68: Insurance Penetration – Year 2021
BF69: Life | BG69: General | BH69: Combined
BE70: Kenya | BF70: 0.01 | BG70: 0.012 | BH70: 0.022
BE71: South Africa | BF71: 0.1 | BG71: 0.022 | BH71: 0.122
BE72: UK | BF72: 0.089 | BG72: 0.022 | BH72: 0.111
BE73: US | BF73: 0.026 | BG73: 0.091 | BH73: 0.117
BE74: India | BF74: 0.032 | BG74: 0.01 | BH74: 0.042
BE75: Malaysia | BF75: 0.014 | BG75: 0.039 | BH75: 0.053
BE76: World | BF76: 0.03 | BG76: 0.039 | BH76: 0.07
BE77: Source: Swiss Re Sigma No 4/2022
BE80: Insurance Penetration 2022
BF81: Life | BG81: General | BH81: Combined
BE82: Kenya | BF82: 1.1 | BG82: 1.2 | BH82: 2.3
BE83: South Africa | BF83: 9.1 | BG83: 2.2 | BH83: 11.3
BE84: UK | BF84: 8.1 | BG84: 2.4 | BH84: 10.5
BE85: US | BF85: 2.6 | BG85: 9 | BH85: 11.6
BE86: India | BF86: 3 | BG86: 1 | BH86: 4
BE87: Malaysia | BF87: 3.7 | BG87: 1.3 | BH87: 5
BE88: World | BF88: 2.8 | BG88: 4 | BH88: 6.8
BE89: Source: Swiss Re Sigma No 3/2023

Sheet Profitability
A1: Based on Financials | AC1: Compared to the budget
B3: Pioneer General Insurance Limited Past Profitability - Net of Reinsurance (KES' 000) | O3: Pioneer General Insurance Limited Past Profitability - Gross of Reinsurance (KES' 000) | AC3: Pioneer General Insurance Limited Budget Vs Actual Analysis (2019- 2023) - KES. '000 | BE3: 2018 | BF3: =BE3+1 -> 2019 | BG3: =BF3+1 -> 2020 | BH3: 2021 | BI3: 2022 | BJ3: 2023 | BN3: Pioneer General Insurance Limited Track-record in Budget Achievements - KES '000
C4: 2018 | D4: =C4+1 -> 2019 | E4: =D4+1 -> 2020 | F4: 2021 | G4: 2022 | H4: 2023 | I4: 5 years | J4: CAGR (4YRS) | P4: 2018 | Q4: =P4+1 -> 2019 | R4: =Q4+1 -> 2020 | S4: 2021 | T4: 2022 | U4: 2023 | V4: 5 years | W4: CAGR (4YRS) | AD4: Actual | AJ4: Budget | AP4: Achievement | AV4: Plan | BD4: Net Earned Premium | BE4: =C5 -> 319509.43 | BF4: =D5 -> 632820.92 | BG4: =E5 -> 710234.01 | BH4: =F5 -> 995870.11 | BI4: =G5 -> 1406547.7 | BJ4: =H5 -> 1420510.3 | BP4: 2018 | BQ4: =BP4+1 -> 2019 | BR4: =BQ4+1 -> 2020 | BS4: =BR4+1 -> 2021 | BT4: =BS4+1 -> 2022 | BU4: 2023
B5: Net Earned Premium | C5: =RA!O193/A_Thousand -> 319509.43 | D5: =RA!O157/A_Thousand -> 632820.92 | E5: =RA!O122/A_Thousand -> 710234.01 | F5: =RA!O87/A_Thousand -> 995870.11 | G5: =RA!O52/A_Thousand -> 1406547.7 | H5: =RA!O17/A_Thousand -> 1420510.3 | I5: =SUM(D5:H5) -> 5165983.1 | J5: =(H5/D5)^(1/4)-1 -> 0.22402671 | K5: =(D5-C5)/C5 -> 0.98060166 | L5: =H5/G5-1 -> 0.0099268712 | O5: Gross Earned Premium | P5: =RA!O190/A_Thousand -> 455527.19 | Q5: =RA!O154/A_Thousand -> 799885.35 | R5: =RA!O119/A_Thousand -> 913353.07 | S5: =RA!O84/A_Thousand -> 1238850.4 | T5: =RA!O49/A_Thousand -> 1558732.8 | U5: =RA!O14/A_Thousand -> 1566582.4 | V5: =SUM(Q5:U5) -> 6077404 | W5: =(U5/Q5)^(1/4)-1 -> 0.18299082 | AD5: 2018 | AE5: =AD5+1 -> 2019 | AF5: 2020 | AG5: 2021 | AH5: 2022 | AI5: 2023 | AJ5: 2018 | AK5: 2019 | AL5: 2020 | AM5: 2021 | AN5: 2022 | AO5: 2023 | AP5: 2018 | AQ5: 2019 | AR5: 2020 | AS5: 2021 | AT5: 2022 | AU5: 2023 | AV5: 2023 | AW5: 2024 | BD5: Loss Ratio | BE5: =C12 -> 0.62481314 | BF5: =D12 -> 0.56588416 | BG5: =E12 -> 0.59026071 | BH5: =F12 -> 0.69811079 | BI5: =G12 -> 0.64270551 | BJ5: =H12 -> 0.65922507 | BN5: FCR 2017 | BP5: =AJ6 -> 650000 | BQ5: =AK6 -> 857500
B6: Net Incurred Claims | C6: =RA!O200/A_Thousand -> 199633.69 | D6: =RA!O164/A_Thousand -> 358103.33 | E6: =RA!O129/A_Thousand -> 419223.23 | F6: =RA!O94/A_Thousand -> 695227.67 | G6: =RA!O59/A_Thousand -> 903995.98 | H6: =RA!O24/A_Thousand -> 936436.03 | I6: =SUM(D6:H6) -> 3312986.2 | J6: =(H6/D6)^(1/4)-1 -> 0.27164954 | L6: =H6/G6-1 -> 0.035885166 | O6: Gross Incurred Claims | P6: =RA!O199/A_Thousand -> 272967.14 | Q6: =RA!O163/A_Thousand -> 428218.47 | R6: =RA!O128/A_Thousand -> 446766.85 | S6: =RA!O93/A_Thousand -> 731054.35 | T6: =(RA!O54+RA!O55)/A_Thousand -> 956787.07 | U6: =(RA!O19+RA!O20)/A_Thousand -> 1012119.7 | V6: =SUM(Q6:U6) -> 3574946.5 | W6: =(U6/Q6)^(1/4)-1 -> 0.23991417 | AC6: GWP | AD6: =RA!O185/A_Thousand -> 591857.07 | AE6: =RA!O149/A_Thousand -> 860493.37 | AF6: =RA!O114/A_Thousand -> 883816.11 | AG6: =RA!O79/A_Thousand -> 1403558.3 | AH6: =RA!O44/A_Thousand -> 1635759.6 | AI6: =RA!O9/A_Thousand -> 1595570 | AJ6: 650000 | AK6: 857500 | AL6: 1064000 | AM6: 1209378.9 | AN6: 1644293.4 | AO6: ='2023_Budget'!C7/A_Thousand -> 2002265.7 | AP6: =AD6/AJ6 -> 0.91054933 | AQ6: =AE6/AK6 -> 1.0034908 | AR6: =AF6/AL6 -> 0.83065423 | AS6: =AG6/AM6 -> 1.1605612 | AT6: =AH6/AN6 -> 0.99481002 | AU6: =AI6/AO6 -> 0.79688223 | AV6: ='2023_Budget'!C7/A_Thousand -> 2002265.7 | AW6: ='2023_Budget'!D7/A_Thousand -> 2110000 | AX6: =AH7/AH6 -> 0.85987438 | AY6: =AN7/AN6 -> 0.66165578 | BD6: Combined Ratio | BE6: =C15 -> 1.2357206 | BF6: =D15 -> 1.0322303 | BG6: =E15 -> 1.0586715 | BH6: =F15 -> 1.0970819 | BI6: =G15 -> 1.0261961 | BJ6: =H15 -> 1.0740324 | BN6: FCR 2018 | BP6: =AD6 -> 591857.07 | BQ6: =AK6 -> 857500 | BR6: =AL6 -> 1064000
B7: Management Expenses | C7: =RA!O205/A_Thousand -> 176443.83 | D7: =RA!O169/A_Thousand -> 238936.54 | E7: =RA!O133/A_Thousand -> 259624.67 | F7: =RA!O98/A_Thousand -> 305617.33 | G7: =RA!O63/A_Thousand -> 364709.87 | H7: =RA!O28/A_Thousand -> 441506.82 | I7: =SUM(D7:H7) -> 1610395.2 | J7: =(H7/D7)^(1/4)-1 -> 0.16590647 | L7: =H7/G7-1 -> 0.21056999 | O7: Management Expenses | P7: =C7 -> 176443.83 | Q7: =D7 -> 238936.54 | R7: =E7 -> 259624.67 | S7: =RA!O98/A_Thousand -> 305617.33 | T7: =G7 -> 364709.87 | U7: =H7 -> 441506.82 | V7: =SUM(Q7:U7) -> 1610395.2 | W7: =(U7/Q7)^(1/4)-1 -> 0.16590647 | AC7: Net Earned Premium | AD7: =C5 -> 319509.43 | AE7: =D5 -> 632820.92 | AF7: =RA!O122/A_Thousand -> 710234.01 | AG7: =RA!O87/A_Thousand -> 995870.11 | AH7: =RA!O52/A_Thousand -> 1406547.7 | AI7: =RA!O17/A_Thousand -> 1420510.3 | AJ7: 401241 | AK7: 606213 | AL7: 813229.45 | AM7: 771754.75 | AN7: 1087956.2 | AO7: ='2023_Budget'!C10/A_Thousand -> 1510958.6 | AP7: =AD7/AJ7 -> 0.79630305 | AQ7: =AE7/AK7 -> 1.043892 | AR7: =AF7/AL7 -> 0.87335008 | AS7: =AG7/AM7 -> 1.2903971 | AT7: =AH7/AN7 -> 1.2928348 | AU7: =AI7/AO7 -> 0.9401385 | AV7: ='2023_Budget'!C10/A_Thousand -> 1510958.6 | AW7: ='2023_Budget'!D10/A_Thousand -> 1601686 | BN7: FCR 2019 | BP7: =$BP$6 -> 591857.07 | BQ7: =$AE$6 -> 860493.37 | BR7: =AL6 -> 1064000 | BS7: =AM6 -> 1209378.9
B8: Commissions Expenses | C8: =RA!O204/A_Thousand -> 18746.868 | D8: =RA!O168/A_Thousand -> 56177.058 | E8: =SUM(RA!O131:O132)/A_Thousand -> 73056.581 | F8: =SUM(RA!O96:O97)/A_Thousand -> 91706.11 | G8: =SUM(RA!O61:O62)/A_Thousand -> 174687.93 | H8: =SUM(RA!O26:O27)/A_Thousand -> 147731.33 | I8: =SUM(D8:H8) -> 543359.01 | J8: =(H8/D8)^(1/4)-1 -> 0.27343975 | L8: =H8/G8-1 -> -0.15431291 | O8: Commissions Expenses | P8: =RA!O203/A_Thousand -> 80582.454 | Q8: =RA!O167/A_Thousand -> 106720.41 | R8: =RA!O132/A_Thousand -> 109900.73 | S8: =RA!O97/A_Thousand -> 174855.61 | T8: =RA!O62/A_Thousand -> 221632.12 | U8: =RA!O27/A_Thousand -> 188077.32 | V8: =SUM(Q8:U8) -> 801186.2 | W8: =(U8/Q8)^(1/4)-1 -> 0.15218505 | AC8: Ceded Premiums | AD8: =-RA!O191/A_Thousand -> 136017.75 | AE8: =-RA!O155/A_Thousand -> 167064.44 | AF8: =-RA!O120/A_Thousand -> 203119.06 | AG8: =-RA!O85/A_Thousand -> 242980.31 | AH8: =-RA!O50/A_Thousand -> 152185.04 | AI8: =RA!O15/A_Thousand -> 146072.04 | AJ8: 136500 | AK8: 155862 | AL8: 178268.55 | AM8: 255649.59 | AN8: 277635.11 | AO8: =-'2023_Budget'!C9/A_Thousand -> 215488.29 | AP8: =AD8/AJ8 -> 0.99646705 | AQ8: =AE8/AK8 -> 1.0718741 | AR8: =AF8/AL8 -> 1.1393993 | AS8: =AG8/AM8 -> 0.9504428 | AT8: =AH8/AN8 -> 0.54814768 | AU8: =AI8/AO8 -> 0.67786532 | AV8: =-'2023_Budget'!C9/A_Thousand -> 215488.29 | AW8: =-'2023_Budget'!D9/A_Thousand -> 217685.47 | BN8: FCR 2020 | BP8: =$BP$6 -> 591857.07 | BQ8: =$AE$6 -> 860493.37 | BR8: =$AF$6 -> 883816.11 | BS8: =AM6 -> 1209378.9 | BT8: =AN6 -> 1644293.4
B9: Underwriting Profit | C9: =C5-C6-C7-C8 -> -75314.961 | D9: =D5-D6-D7-D8 -> -20396.017 | E9: =E5-E6-E7-E8 -> -41670.475 | F9: =F5-F6-F7-F8 -> -96681.002 | G9: =G5-G6-G7-G8 -> -36846.053 | H9: =H5-H6-H7-H8 -> -105163.83 | I9: =I5-I6-I7-I8 -> -300757.38 | J9: =(H9/D9)^(1/4)-1 -> 0.50688552 | O9: Underwriting Profit | P9: =P5-P6-P7-P8 -> -74466.241 | Q9: =Q5-Q6-Q7-Q8 -> 26009.924 | R9: =R5-R6-R7-R8 -> 97060.816 | S9: =S5-S6-S7-S8 -> 27323.12 | T9: =T5-T6-T7-T8 -> 15603.711 | U9: =U5-U6-U7-U8 -> -75121.486 | V9: =V5-V6-V7-V8 -> 90876.085 | AC9: Net Claims | AD9: =C6 -> 199633.69 | AE9: =D6 -> 358103.33 | AF9: =RA!O129/A_Thousand -> 419223.23 | AG9: =RA!O94/A_Thousand -> 695227.67 | AH9: =RA!O59/A_Thousand -> 903995.98 | AI9: =RA!O24/A_Thousand -> 936436.03 | AJ9: 248769 | AK9: 343366 | AL9: 514662.22 | AM9: 444942.85 | AN9: 657056.22 | AO9: ='2023_Budget'!C17/A_Thousand -> 927018.37 | AP9: =AD9/AJ9 -> 0.80248621 | AQ9: =AE9/AK9 -> 1.0429202 | AR9: =AF9/AL9 -> 0.81455995 | AS9: =AG9/AM9 -> 1.56251 | AT9: =AH9/AN9 -> 1.3758274 | AU9: =AI9/AO9 -> 1.0101591 | AV9: ='2023_Budget'!C17/A_Thousand -> 927018.37 | AW9: ='2023_Budget'!D17/A_Thousand -> 965844.6 | BE9: 2018 | BF9: =BE9+1 -> 2019 | BG9: =BF9+1 -> 2020 | BH9: 2021 | BI9: 2022 | BJ9: 2023 | BN9: FCR 2021 | BP9: =$BP$6 -> 591857.07 | BQ9: =$AE$6 -> 860493.37 | BR9: =$AF$6 -> 883816.11 | BS9: =AG6 -> 1403558.3 | BT9: =AN6 -> 1644293.4 | BU9: =AV6 -> 2002265.7
AC10: Net Commissions | AD10: =C8 -> 18746.868 | AE10: =D8 -> 56177.058 | AF10: =E8 -> 73056.581 | AG10: =F8 -> 91706.11 | AH10: =G8 -> 174687.93 | AI10: =H8 -> 147731.33 | AJ10: 53326 | AK10: 75308 | AL10: 80268.766 | AM10: 77890.875 | AN10: 110638.16 | AO10: =('2023_Budget'!C18-'2023_Budget'!C12+'2023_Budget'!C19)/A_Thousand -> 156086.94 | AP10: =AD10/AJ10 -> 0.35155211 | AQ10: =AE10/AK10 -> 0.74596401 | AR10: =AF10/AL10 -> 0.91014955 | AS10: =AG10/AM10 -> 1.1773665 | AT10: =AH10/AN10 -> 1.5789122 | AU10: =AI10/AO10 -> 0.94646825 | AV10: =('2023_Budget'!C18-'2023_Budget'!C12+'2023_Budget'!C19)/A_Thousand -> 156086.94 | AW10: =('2023_Budget'!D18-'2023_Budget'!D12+'2023_Budget'!D19)/A_Thousand -> 148650.04 | BD10: Gross Earned Premium | BE10: =P5 -> 455527.19 | BF10: =Q5 -> 799885.35 | BG10: =R5 -> 913353.07 | BH10: =S5 -> 1238850.4 | BI10: =T5 -> 1558732.8 | BJ10: =U5 -> 1566582.4 | BN10: FCR 2022 | BP10: =$BP$6 -> 591857.07 | BQ10: =$AE$6 -> 860493.37 | BR10: =$AF$6 -> 883816.11 | BS10: =BS9 -> 1403558.3 | BT10: =AH6 -> 1635759.6 | BU10: =AV6 -> 2002265.7
B11: Ratios | O11: Ratios | AC11: Management Expenses | AD11: =C7 -> 176443.83 | AE11: =D7 -> 238936.54 | AF11: =RA!O133/A_Thousand -> 259624.67 | AG11: =RA!O98/A_Thousand -> 305617.33 | AH11: =RA!O63/A_Thousand -> 364709.87 | AI11: =RA!O28/A_Thousand -> 441506.82 | AJ11: 141971 | AK11: 264368 | AL11: 260482.7 | AM11: 280705.66 | AN11: 352832.75 | AO11: ='2023_Budget'!C20/A_Thousand -> 405721.24 | AP11: =AD11/AJ11 -> 1.242816 | AQ11: =AE11/AK11 -> 0.90380282 | AR11: =AF11/AL11 -> 0.99670599 | AS11: =AG11/AM11 -> 1.0887466 | AT11: =AH11/AN11 -> 1.0336622 | AU11: =AI11/AO11 -> 1.0882024 | AV11: ='2023_Budget'!C20/A_Thousand -> 405721.24 | AW11: ='2023_Budget'!D20/A_Thousand -> 486494.39 | BD11: Loss Ratio | BE11: =P12 -> 0.59923348 | BF11: =Q12 -> 0.53534981 | BG11: =R12 -> 0.48915022 | BH11: =S12 -> 0.59010704 | BI11: =T12 -> 0.61382367 | BJ11: =U12 -> 0.64606862 | BN11: Budget Achievement | BP11: =BP6/BP5 -> 0.91054933 | BQ11: =BQ7/BQ6 -> 1.0034908 | BR11: =BR8/BR7 -> 0.83065423 | BS11: =BS9/BS8 -> 1.1605612 | BT11: =BT10/BT9 -> 0.99481002
B12: Claim Ratio | C12: =C6/C$5 -> 0.62481314 | D12: =IFERROR(D6/D$5,0) -> 0.56588416 | E12: =IFERROR(E6/E$5,0) -> 0.59026071 | F12: =IFERROR(F6/F$5,0) -> 0.69811079 | G12: =IFERROR(G6/G$5,0) -> 0.64270551 | H12: =IFERROR(H6/H$5,0) -> 0.65922507 | I12: =I6/I$5 -> 0.64130799 | K12: =_xlfn.STDEV.S(D12:H12) -> 0.053237704 | O12: Claim Ratio | P12: =P6/P$5 -> 0.59923348 | Q12: =IFERROR(Q6/Q$5,0) -> 0.53534981 | R12: =IFERROR(R6/R$5,0) -> 0.48915022 | S12: =IFERROR(S6/S$5,0) -> 0.59010704 | T12: =IFERROR(T6/T$5,0) -> 0.61382367 | U12: =IFERROR(U6/U$5,0) -> 0.64606862 | V12: =V6/V$5 -> 0.58823578 | X12: =_xlfn.STDEV.S(Q12:U12) -> 0.062706702 | AC12: Underwriting Result | AD12: =AD7-SUM(AD9:AD11) -> -75314.961 | AE12: =AE7-SUM(AE9:AE11) -> -20396.017 | AF12: =AF7-SUM(AF9:AF11) -> -41670.475 | AG12: =AG7-SUM(AG9:AG11) -> -96681.002 | AH12: =AH7-SUM(AH9:AH11) -> -36846.053 | AI12: =AI7-SUM(AI9:AI11) -> -105163.83 | AJ12: =AJ7-SUM(AJ9:AJ11) -> -42825 | AK12: =AK7-SUM(AK9:AK11) -> -76829 | ... AO12: =AO7-SUM(AO9:AO11) -> 22132.042 | AP12: =AD12/AJ12 -> 1.7586681 | AQ12: =AE12/AK12 -> 0.26547289 | AR12: =AF12/AL12 -> 0.98782107 | AS12: =AG12/AM12 -> 3.0417528 | AT12: =AH12/AN12 -> 1.1312571 | AU12: =AI12/AO12 -> -4.7516551 | AV12: =AV7-SUM(AV9:AV11) -> 22132.042 | AW12: =AW7-SUM(AW9:AW11) -> 696.93929 | BD12: Combined Ratio | BE12: =P15 -> 1.1634727 | BF12: =Q15 -> 0.96748293 | BG12: =R15 -> 0.89373133 | BH12: =S15 -> 0.97794478 | BI12: =T15 -> 0.98998949 | BJ12: =U15 -> 1.0479525 | BN12: Actual Premium Growth | BQ12: =(BQ10-BP10)/BP10 -> 0.45388712 | BR12: =(BR10-BQ10)/BQ10 -> 0.027103915 | BS12: =(BS10-BR10)/BR10 -> 0.58806595 | BT12: =(BT10-BS10)/BS10 -> 0.16543758
B13: Expense Ratio | C13: =C7/C$5 -> 0.55223357 | D13: =D7/D$5 -> 0.37757371 | E13: =E7/E$5 -> 0.36554807 | F13: =F7/F$5 -> 0.30688473 | G13: =G7/G$5 -> 0.25929434 | H13: =H7/H$5 -> 0.31080859 | I13: =I7/I$5 -> 0.31173064 | K13: =_xlfn.STDEV.S(D13:H13) -> 0.04808885 | O13: Expense Ratio | P13: =P7/P$5 -> 0.38733985 | Q13: =Q7/Q$5 -> 0.29871349 | R13: =R7/R$5 -> 0.28425444 | S13: =S7/S$5 -> 0.2466943 | T13: =T7/T$5 -> 0.23397844 | U13: =U7/U$5 -> 0.28182803 | V13: =V7/V$5 -> 0.26498078 | X13: =_xlfn.STDEV.S(Q13:U13) -> 0.027405098 | BN13: Budgeted Premium Growth | BT13: =(BU10-BT10)/BT10 -> 0.2240587
B14: Commission Ratio | C14: =C8/C$5 -> 0.058673911 | D14: =D8/D$5 -> 0.088772442 | E14: =E8/E$5 -> 0.10286269 | F14: =F8/F$5 -> 0.092086417 | G14: =G8/G$5 -> 0.12419623 | H14: =H8/H$5 -> 0.10399877 | I14: =I8/I$5 -> 0.10518018 | K14: =_xlfn.STDEV.S(D14:H14) -> 0.013873761 | O14: Commission Ratio | P14: =P8/P$5 -> 0.17689933 | Q14: =Q8/Q$5 -> 0.13341963 | R14: =R8/R$5 -> 0.12032667 | S14: =S8/S$5 -> 0.14114344 | T14: =T8/T$5 -> 0.14218738 | U14: =U8/U$5 -> 0.12005581 | V14: =V8/V$5 -> 0.13183033 | X14: =_xlfn.STDEV.S(Q14:U14) -> 0.010801467 | AC14: RATIOS
B15: Combined Ratio | C15: =SUM(C12:C14) -> 1.2357206 | D15: =SUM(D12:D14) -> 1.0322303 | E15: =SUM(E12:E14) -> 1.0586715 | F15: =SUM(F12:F14) -> 1.0970819 | G15: =SUM(G12:G14) -> 1.0261961 | H15: =SUM(H12:H14) -> 1.0740324 | I15: =SUM(I12:I14) -> 1.0582188 | J15: =H15=RA!O39 -> TRUE | K15: =_xlfn.STDEV.S(D15:H15) -> 0.029410091 | O15: Combined Ratio | P15: =SUM(P12:P14) -> 1.1634727 | Q15: =SUM(Q12:Q14) -> 0.96748293 | R15: =SUM(R12:R14) -> 0.89373133 | S15: =SUM(S12:S14) -> 0.97794478 | T15: =SUM(T12:T14) -> 0.98998949 | U15: =SUM(U12:U14) -> 1.0479525 | V15: =SUM(V12:V14) -> 0.98504689 | X15: =_xlfn.STDEV.S(Q15:U15) -> 0.05526219 | AC15: Growth | AE15: =(AE6-AD6)/AD6 -> 0.45388712 | AF15: =(AF6-AE6)/AE6 -> 0.027103915 | AG15: =(AG6-AF6)/AF6 -> 0.58806595 | AH15: =(AH6-AG6)/AG6 -> 0.16543758 | AI15: =(AI6-AH6)/AH6 -> -0.02456937 | AK15: =(AK6-AJ6)/AJ6 -> 0.31923077 | AL15: =(AL6-AK6)/AK6 -> 0.24081633 | AM15: =(AM6-AL6)/AL6 -> 0.13663431 | AN15: =(AN6-AM6)/AM6 -> 0.35961806 | AO15: =(AO6-AN6)/AN6 -> 0.21770586 | AV15: =(AV6-AH6)/AH6 -> 0.2240587 | AW15: =(AW6-AI6)/AI6 -> 0.32241145 | AX15: =(AV6-AH6)/AH6 -> 0.2240587 | BE15: 2018 | BF15: 2019 | BG15: 2020 | BH15: 2021 | BI15: 2022 | BJ15: 2023
B16: Profit Ratio | C16: =IFERROR(C9/C$5,0) -> -0.23572062 | D16: =IFERROR(D9/D$5,0) -> -0.032230314 | E16: =IFERROR(E9/E$5,0) -> -0.058671473 | F16: =IFERROR(F9/F$5,0) -> -0.09708194 | G16: =IFERROR(G9/G$5,0) -> -0.026196092 | H16: =IFERROR(H9/H$5,0) -> -0.074032429 | I16: =IFERROR(I9/I$5,0) -> -0.058218808 | K16: =_xlfn.STDEV.S(D16:H16) -> 0.029410091 | O16: Profit Ratio | P16: =IFERROR(P9/P$5,0) -> -0.16347266 | Q16: =IFERROR(Q9/Q$5,0) -> 0.032517065 | R16: =IFERROR(R9/R$5,0) -> 0.10626867 | S16: =IFERROR(S9/S$5,0) -> 0.022055221 | T16: =IFERROR(T9/T$5,0) -> 0.010010511 | U16: =IFERROR(U9/U$5,0) -> -0.047952464 | V16: =IFERROR(V9/V$5,0) -> 0.014953109 | X16: =_xlfn.STDEV.S(Q16:U16) -> 0.05526219 | AC16: Ceding Ratio | AD16: =AD8/AD6 -> 0.22981521 | AE16: =AE8/AE6 -> 0.19414959 | AF16: =AF8/AF6 -> 0.2298205 | AG16: =AG8/AG6 -> 0.17311737 | AH16: =AH8/AH6 -> 0.093036315 | AI16: =AI8/AI6 -> 0.091548502 | AJ16: =AJ8/AJ6 -> 0.21 | AK16: =AK8/AK6 -> 0.18176327 | ... AO16: =AO8/AO6 -> 0.10762223 | AV16: =AV8/AV6 -> 0.10762223 | AW16: =AW8/AW6 -> 0.10316847 | BD16: GWP | BE16: =AD6 -> 591857.07 | BF16: =AE6 -> 860493.37 | BG16: =AF6 -> 883816.11 | BH16: =AG6 -> 1403558.3 | BI16: =AH6 -> 1635759.6 | BJ16: =AI6 -> 1595570 | BN16: KEY :
AC17: Claims Ratio | AD17: =AD9/AD7 -> 0.62481314 | AE17: =AE9/AE7 -> 0.56588416 | AF17: =AF9/AF7 -> 0.59026071 | AG17: =AG9/AG7 -> 0.69811079 | AH17: =AH9/AH7 -> 0.64270551 | AI17: =AI9/AI7 -> 0.65922507 | AJ17: =AJ9/AJ7 -> 0.61999895 | AK17: =AK9/AK7 -> 0.56641148 | ... AO17: =AO9/AO7 -> 0.61352997 | AV17: =AV9/AV7 -> 0.61352997 | AW17: =AW9/AW7 -> 0.60301746 | BD17: GWP Budget | BE17: =AJ6 -> 650000 | BF17: =AK6 -> 857500 | BG17: =AL6 -> 1064000 | BH17: =AM6 -> 1209378.9 | BI17: =AN6 -> 1644293.4 | BJ17: =AO6 -> 2002265.7 | BO17: One year plan as at the FCR Period | BP17: One year plan as at the FCR Period
W18: =X16/K16-1 -> 0.87902141 | AC18: Commission Ratio | AD18: =AD10/AD7 -> 0.058673911 | AE18: =AE10/AE7 -> 0.088772442 | AF18: =AF10/AF7 -> 0.10286269 | AG18: =AG10/AG7 -> 0.092086417 | AH18: =AH10/AH7 -> 0.12419623 | AI18: =AI10/AI7 -> 0.10399877 | AJ18: =AJ10/AJ7 -> 0.13290267 | AK18: =AK10/AK7 -> 0.12422696 | ... AO18: =AO10/AO7 -> 0.10330325 | AV18: =AV10/AV7 -> 0.10330325 | AW18: =AW10/AW7 -> 0.092808479 | BO18: Actual GWP | BP18: Actual GWP
W19: =X12/K12-1 -> 0.17786263 | AC19: Expense Ratio | AD19: =AD11/AD7 -> 0.55223357 | AE19: =AE11/AE7 -> 0.37757371 | AF19: =AF11/AF7 -> 0.36554807 | AG19: =AG11/AG7 -> 0.30688473 | AH19: =AH11/AH7 -> 0.25929434 | AI19: =AI11/AI7 -> 0.31080859 | AJ19: =AJ11/AJ7 -> 0.35382974 | AK19: =AK11/AK7 -> 0.43609754 | ... AO19: =AO11/AO7 -> 0.2685191 | AV19: =AV11/AV7 -> 0.2685191 | AW19: =AW11/AW7 -> 0.30373894 | AY19: =AE7/AD7-1 -> 0.98060166 | AZ19: =AH7/AE7-1 -> 1.2226631 | BD19: NEP | BE19: Actual | BF19: Budget | BO19: Future year plans (year 2+) for the future period as at FCR period | BP19: Future year plans (year 2+) for the future period as at FCR period
AC20: Profit Ratio | AD20: =AD12/AD7 -> -0.23572062 | AE20: =AE12/AE7 -> -0.032230314 | AF20: =AF12/AF7 -> -0.058671473 | AG20: =AG12/AG7 -> -0.09708194 | AH20: =AH12/AH7 -> -0.026196092 | AI20: =AI12/AI7 -> -0.074032429 | AJ20: =AJ12/AJ7 -> -0.10673137 | AK20: =AK12/AK7 -> -0.12673598 | ... AO20: =AO12/AO7 -> 0.014647683 | AV20: =AV12/AV7 -> 0.014647683 | AW20: =AW12/AW7 -> 0.00043512855 | AY20: =AE11/AD11-1 -> 0.35417905 | AZ20: =AH11/AE11-1 -> 0.52638798 | BD20: 2018 | BE20: =_xlfn.XLOOKUP(BD20,$AD$5:$AI$5,$AD$7:$AI$7) -> 319509.43 | BF20: =_xlfn.XLOOKUP(BD20,$AJ$5:$AO$5,$AJ$7:$AO$7) -> 401241
BD21: 2019 | BE21: =_xlfn.XLOOKUP(BD21,$AD$5:$AI$5,$AD$7:$AI$7) -> 632820.92 | BF21: =_xlfn.XLOOKUP(BD21,$AJ$5:$AO$5,$AJ$7:$AO$7) -> 606213
BD22: 2020 | BE22: =_xlfn.XLOOKUP(BD22,$AD$5:$AI$5,$AD$7:$AI$7) -> 710234.01 | BF22: =_xlfn.XLOOKUP(BD22,$AJ$5:$AO$5,$AJ$7:$AO$7) -> 813229.45 | BN22: Pioneer General Insurance Limited Track-record in Budget Achievements - KES '000
