Workbook
Name a_billion: Assumptions!$C$17
Name a_million: Assumptions!$C$16
Name a_thousand: Assumptions!$C$15
Name a_trillion: Assumptions!$C$18
Name Age: 'Membership Analysis'!$T$4:$T$950
Name Analysis_Date: Intro!$F$12
Name Ann_Loading: 'Mortality Tables'!$G$1
Name Ann_Salary_Growth_Rate: Assumptions!$C$4
Name Annuity_Ratio: 'Membership Analysis'!$DL$1
Name Comm_Date: 'Membership Analysis'!$B$1
Name Contr_Rate: Assumptions!$C$9
Name Discount_Table: 'v(t)'!$B$5:$DD$111
Name EE_Cont: 'Scheme Details'!$C$13
Name ER: 'Scheme Details'!$C$6
Name ER_Cont: 'Scheme Details'!$C$14
Name Fe_Annuity_Factor: 'Mortality Tables'!$G$4
Name Fe_Annuity_Tables: 'Mortality Tables'!$K$3:$DN$98
Name Fe_MDT: MDT!$O$3:$U$100
Name Fund_Credits: 'Membership Analysis'!$L$4:$L$950
Name Gender: 'Membership Analysis'!$D$4:$D$950
Name Inv_Return: Assumptions!$C$5
Name Male_Annuity_Factor: 'Mortality Tables'!$H$4
Name Male_Annuity_Tables: 'Mortality Tables'!$DQ$3:$HT$98
Name Male_MDT: MDT!$G$3:$M$100
Name Membership_Analysis: 'Membership Analysis'!$A$3:$X$950
Name Membership_Status: 'Membership Analysis'!$C$4:$C$950
Name Mortality_Table: 'Mortality Tables'!$A$3:$C$100
Name NRA: 'Scheme Details'!$C$5
Name scheme_acronym: Assumptions!$C$21
Name Scheme_Name: Assumptions!$C$20
Name Withdrawal_Probs: MDT!$A$3:$B$100
Name Years_To_Retirement: 'Membership Analysis'!$W$4:$W$950

Sheet Intro
C4: =Scheme_Name -> SOLARA SUMMIT STAFF PENSION SCHEME
C10: INVESTMENT POLICY STATEMENT
D12: Analysis Date | F12: 45656

Sheet New Report Sections
B2: 1 | C2: Growth in Assets
B8: Rules
B10: 1 | C10: Show value in maximum three digits ( make value as millions, billions, etc)
B11: 2 | C11: Where items are blank or zero then remove them or categorise as "Others"
B12: 3 | C12: Report assumptions / approach should be disclosed
B13: 4 | C13: The excel should have few hard coded numbers (preferably none)
B14: 5 | C14: In the excel, numbers used in formulas should be colored
B15: 6 | C15: Uniformity of Font Size
B16: 7 | C16: All tables from Excel should use the Atkinson Font
B17: 8 | C17: All numbers to have commas for every thousand

Sheet Scheme Details
B2: =Scheme_Name&" SCHEME DETAILS AS AT THE ANALYSIS DATE" -> SOLARA SUMMIT STAFF PENSION SCHEME SCHEME DETAILS AS AT THE ANALYSIS DATE
B3: Scheme Type | C3: Defined Contribution Scheme
B4: Scheme Commencement Date | C4: 35674
B5: Normal Retirement Age – NRA - (years) | C5: 60
B6: Early Retirement Age (years) | C6: 50
B7: Ill Health Retirement Age (years) | C7: Any age
B8: Scheme Membership | C8: =COUNTA(Membership_Status) -> 500
B9: Average Scheme Age (years) | C9: =AVERAGE(Age) -> 47.262
B10: Average Scheme Age - weighted by fund credits (years) | C10: =SUMPRODUCT(Age,Fund_Credits)/SUM(Fund_Credits) -> 47.591129
B11: Average Years to Retirement (simple average) | C11: =AVERAGE(Years_To_Retirement) -> 12.912
B12: Average Years to Retirement (weighted by fund credits) | C12: =SUMPRODUCT(Years_To_Retirement,Fund_Credits)/SUM(Fund_Credits) -> 12.60523
B13: Scheme Contribution Rate - Employee | C13: 0.15
B14: Scheme Contribution Rate - Employer | C14: 0.15
B15: Additional Voluntary Contributions | C15: Minimum of 3% p.a of Annual Salary
B16: Period before vesting of employee contributions (years) | C16: 0 (immediate)
B17: Period before vesting of employer contributions (years) | C17: 0 (immediate)
B18: Payment of Immediate Pension (mode) | C18: Annuity/Income Drawdown/Lumpsum
B19: Maximum Lump sum (% of Accrued Benefits) | C19: 0.3333
B20: Financial Year | C20: 01 Jan XXXX - 31 Dec XXXX
B22: Service providers as at Analysis Date:
B23: Administrator | C23: Keystone Financial Services Limited
B24: Approved Issuer | C24: Horizon Asset Managers Limited
B25: Custodian | C25: Alpha Bank Kenya Limited
B26: Founder | C26: Solara Company Limited

Sheet Assumptions
B3: Item | C3: Assumption
B4: Salary Growth Rate | C4: =AVERAGE('Fund Performance'!J19:K19) -> 0.05095
B5: Net Annual Investment Return | C5: ='Investment Income'!X47 -> 0.027644324
B6: Administrative Expenses (Proportion of Assets) | C6: ='Investment Income'!K21 -> 0.011555776
B7: Mortality Assumption | C7: a55 - UK table
B8: Discount Rate | C8: ='v(t)'!B2 -> 0.1
B9: Contribution Rate | C9: =EE_Cont+ER_Cont -> 0.3
B15: thousand | C15: 1000
B16: million | C16: 1000000
B17: billion | C17: 1000000000
B18: trillion | C18: 1000000000000
B20: Scheme Name | C20: SOLARA SUMMIT STAFF PENSION SCHEME
B21: Scheme Acronym | C21: SOS-SPS

Sheet v(t)
A2: Investment Return | B2: 0.1
C3: 0 | D3: 1 | E3: 2 | F3: =E3+1 -> 3 | G3: =F3+1 -> 4 | H3: =G3+1 -> 5 | I3: =H3+1 -> 6 | J3: =I3+1 -> 7 | K3: =J3+1 -> 8 | L3: =K3+1 -> 9 | M3: =L3+1 -> 10 | ... DD3: =DC3+1 -> 105
E4: t
B5: Age x | C5: ="v("&C3&")" -> v(0) | D5: ="v("&D3&")" -> v(1) | E5: ="v("&E3&")" -> v(2) | F5: ="v("&F3&")" -> v(3) | G5: ="v("&G3&")" -> v(4) | H5: ="v("&H3&")" -> v(5) | I5: ="v("&I3&")" -> v(6) | J5: ="v("&J3&")" -> v(7) | ... DD5: ="v("&DD3&")" -> v(105)
B6: 15 | C6: =(1+$B$2)^(-C$3) -> 1 | D6: =(1+$B$2)^(-D$3) -> 0.90909091 | E6: =(1+$B$2)^(-E$3) -> 0.82644628 | F6: =(1+$B$2)^(-F$3) -> 0.7513148 | G6: =(1+$B$2)^(-G$3) -> 0.68301346 | H6: =(1+$B$2)^(-H$3) -> 0.62092132 | I6: =(1+$B$2)^(-I$3) -> 0.56447393 | J6: =(1+$B$2)^(-J$3) -> 0.51315812 | ... DD6: =(1+$B$2)^(-DD$3) -> 4.50576e-05
B7: =B6+1 -> 16 | C7: =(1+$B$2)^(-C$3) -> 1 | D7: =(1+$B$2)^(-D$3) -> 0.90909091 | E7: =(1+$B$2)^(-E$3) -> 0.82644628 | F7: =(1+$B$2)^(-F$3) -> 0.7513148 | G7: =(1+$B$2)^(-G$3) -> 0.68301346 | H7: =(1+$B$2)^(-H$3) -> 0.62092132 | I7: =(1+$B$2)^(-I$3) -> 0.56447393 | J7: =(1+$B$2)^(-J$3) -> 0.51315812 | ... DD7: =(1+$B$2)^(-DD$3) -> 4.50576e-05
B8: =B7+1 -> 17 | C8: =(1+$B$2)^(-C$3) -> 1 | D8: =(1+$B$2)^(-D$3) -> 0.90909091 | E8: =(1+$B$2)^(-E$3) -> 0.82644628 | F8: =(1+$B$2)^(-F$3) -> 0.7513148 | G8: =(1+$B$2)^(-G$3) -> 0.68301346 | H8: =(1+$B$2)^(-H$3) -> 0.62092132 | I8: =(1+$B$2)^(-I$3) -> 0.56447393 | J8: =(1+$B$2)^(-J$3) -> 0.51315812 | ... DD8: =(1+$B$2)^(-DD$3) -> 4.50576e-05
B9: =B8+1 -> 18 | C9: =(1+$B$2)^(-C$3) -> 1 | D9: =(1+$B$2)^(-D$3) -> 0.90909091 | E9: =(1+$B$2)^(-E$3) -> 0.82644628 | F9: =(1+$B$2)^(-F$3) -> 0.7513148 | G9: =(1+$B$2)^(-G$3) -> 0.68301346 | H9: =(1+$B$2)^(-H$3) -> 0.62092132 | I9: =(1+$B$2)^(-I$3) -> 0.56447393 | J9: =(1+$B$2)^(-J$3) -> 0.51315812 | ... DD9: =(1+$B$2)^(-DD$3) -> 4.50576e-05
B10: =B9+1 -> 19 | C10: =(1+$B$2)^(-C$3) -> 1 | D10: =(1+$B$2)^(-D$3) -> 0.90909091 | E10: =(1+$B$2)^(-E$3) -> 0.82644628 | F10: =(1+$B$2)^(-F$3) -> 0.7513148 | G10: =(1+$B$2)^(-G$3) -> 0.68301346 | H10: =(1+$B$2)^(-H$3) -> 0.62092132 | I10: =(1+$B$2)^(-I$3) -> 0.56447393 | J10: =(1+$B$2)^(-J$3) -> 0.51315812 | ... DD10: =(1+$B$2)^(-DD$3) -> 4.50576e-05
B11: =B10+1 -> 20 | C11: =(1+$B$2)^(-C$3) -> 1 | D11: =(1+$B$2)^(-D$3) -> 0.90909091 | E11: =(1+$B$2)^(-E$3) -> 0.82644628 | F11: =(1+$B$2)^(-F$3) -> 0.7513148 | G11: =(1+$B$2)^(-G$3) -> 0.68301346 | H11: =(1+$B$2)^(-H$3) -> 0.62092132 | I11: =(1+$B$2)^(-I$3) -> 0.56447393 | J11: =(1+$B$2)^(-J$3) -> 0.51315812 | ... DD11: =(1+$B$2)^(-DD$3) -> 4.50576e-05
B12: =B11+1 -> 21 | C12: =(1+$B$2)^(-C$3) -> 1 | D12: =(1+$B$2)^(-D$3) -> 0.90909091 | E12: =(1+$B$2)^(-E$3) -> 0.82644628 | F12: =(1+$B$2)^(-F$3) -> 0.7513148 | G12: =(1+$B$2)^(-G$3) -> 0.68301346 | H12: =(1+$B$2)^(-H$3) -> 0.62092132 | I12: =(1+$B$2)^(-I$3) -> 0.56447393 | J12: =(1+$B$2)^(-J$3) -> 0.51315812 | ... DD12: =(1+$B$2)^(-DD$3) -> 4.50576e-05
B13: =B12+1 -> 22 | C13: =(1+$B$2)^(-C$3) -> 1 | D13: =(1+$B$2)^(-D$3) -> 0.90909091 | E13: =(1+$B$2)^(-E$3) -> 0.82644628 | F13: =(1+$B$2)^(-F$3) -> 0.7513148 | G13: =(1+$B$2)^(-G$3) -> 0.68301346 | H13: =(1+$B$2)^(-H$3) -> 0.62092132 | I13: =(1+$B$2)^(-I$3) -> 0.56447393 | J13: =(1+$B$2)^(-J$3) -> 0.51315812 | ... DD13: =(1+$B$2)^(-DD$3) -> 4.50576e-05
B14: =B13+1 -> 23 | C14: =(1+$B$2)^(-C$3) -> 1 | D14: =(1+$B$2)^(-D$3) -> 0.90909091 | E14: =(1+$B$2)^(-E$3) -> 0.82644628 | F14: =(1+$B$2)^(-F$3) -> 0.7513148 | G14: =(1+$B$2)^(-G$3) -> 0.68301346 | H14: =(1+$B$2)^(-H$3) -> 0.62092132 | I14: =(1+$B$2)^(-I$3) -> 0.56447393 | J14: =(1+$B$2)^(-J$3) -> 0.51315812 | ... DD14: =(1+$B$2)^(-DD$3) -> 4.50576e-05
B15: =B14+1 -> 24 | C15: =(1+$B$2)^(-C$3) -> 1 | D15: =(1+$B$2)^(-D$3) -> 0.90909091 | E15: =(1+$B$2)^(-E$3) -> 0.82644628 | F15: =(1+$B$2)^(-F$3) -> 0.7513148 | G15: =(1+$B$2)^(-G$3) -> 0.68301346 | H15: =(1+$B$2)^(-H$3) -> 0.62092132 | I15: =(1+$B$2)^(-I$3) -> 0.56447393 | J15: =(1+$B$2)^(-J$3) -> 0.51315812 | ... DD15: =(1+$B$2)^(-DD$3) -> 4.50576e-05
B16: =B15+1 -> 25 | C16: =(1+$B$2)^(-C$3) -> 1 | D16: =(1+$B$2)^(-D$3) -> 0.90909091 | E16: =(1+$B$2)^(-E$3) -> 0.82644628 | F16: =(1+$B$2)^(-F$3) -> 0.7513148 | G16: =(1+$B$2)^(-G$3) -> 0.68301346 | H16: =(1+$B$2)^(-H$3) -> 0.62092132 | I16: =(1+$B$2)^(-I$3) -> 0.56447393 | J16: =(1+$B$2)^(-J$3) -> 0.51315812 | ... DD16: =(1+$B$2)^(-DD$3) -> 4.50576e-05
B17: =B16+1 -> 26 | C17: =(1+$B$2)^(-C$3) -> 1 | D17: =(1+$B$2)^(-D$3) -> 0.90909091 | E17: =(1+$B$2)^(-E$3) -> 0.82644628 | F17: =(1+$B$2)^(-F$3) -> 0.7513148 | G17: =(1+$B$2)^(-G$3) -> 0.68301346 | H17: =(1+$B$2)^(-H$3) -> 0.62092132 | I17: =(1+$B$2)^(-I$3) -> 0.56447393 | J17: =(1+$B$2)^(-J$3) -> 0.51315812 | ... DD17: =(1+$B$2)^(-DD$3) -> 4.50576e-05
B18: =B17+1 -> 27 | C18: =(1+$B$2)^(-C$3) -> 1 | D18: =(1+$B$2)^(-D$3) -> 0.90909091 | E18: =(1+$B$2)^(-E$3) -> 0.82644628 | F18: =(1+$B$2)^(-F$3) -> 0.7513148 | G18: =(1+$B$2)^(-G$3) -> 0.68301346 | H18: =(1+$B$2)^(-H$3) -> 0.62092132 | I18: =(1+$B$2)^(-I$3) -> 0.56447393 | J18: =(1+$B$2)^(-J$3) -> 0.51315812 | ... DD18: =(1+$B$2)^(-DD$3) -> 4.50576e-05
... B111: =B110+1 -> 120 | C111: =(1+$B$2)^(-C$3) -> 1 | D111: =(1+$B$2)^(-D$3) -> 0.90909091 | E111: =(1+$B$2)^(-E$3) -> 0.82644628 | F111: =(1+$B$2)^(-F$3) -> 0.7513148 | G111: =(1+$B$2)^(-G$3) -> 0.68301346 | H111: =(1+$B$2)^(-H$3) -> 0.62092132 | I111: =(1+$B$2)^(-I$3) -> 0.56447393 | J111: =(1+$B$2)^(-J$3) -> 0.51315812 | ... DD111: =(1+$B$2)^(-DD$3) -> 4.50576e-05

Sheet Mortality Tables
A1: a55 - UK table | F1: Loading Factor | G1: 0.1 | M1: 0 | N1: 1 | O1: 2 | P1: =O1+1 -> 3 | Q1: =P1+1 -> 4 | R1: =Q1+1 -> 5 | S1: =R1+1 -> 6 | T1: =S1+1 -> 7 | U1: =T1+1 -> 8 | V1: =U1+1 -> 9 | W1: =V1+1 -> 10 | ... DN1: =DM1+1 -> 105 | DS1: 0 | DT1: 1 | DU1: 2 | DV1: =DU1+1 -> 3 | DW1: =DV1+1 -> 4 | DX1: =DW1+1 -> 5 | DY1: =DX1+1 -> 6 | DZ1: =DY1+1 -> 7 | EA1: =DZ1+1 -> 8 | EB1: =EA1+1 -> 9 | EC1: =EB1+1 -> 10 | ... HT1: =HS1+1 -> 105
F2: Annuity Factors | K2: FEMALE | O2: t | DQ2: MALE | DU2: t
A3: Age x | B3: Female | C3: Male | F3: NRA | G3: Female | H3: Male | K3: Age x | L3: (aq)x | M3: =M1&"(ap)x" -> 0(ap)x | N3: =N1&"(ap)x" -> 1(ap)x | O3: =O1&"(ap)x" -> 2(ap)x | P3: =P1&"(ap)x" -> 3(ap)x | Q3: =Q1&"(ap)x" -> 4(ap)x | R3: =R1&"(ap)x" -> 5(ap)x | S3: =S1&"(ap)x" -> 6(ap)x | T3: =T1&"(ap)x" -> 7(ap)x | ... DN3: =DN1&"(ap)x" -> 105(ap)x | DQ3: Age x | DR3: (aq)x | DS3: =DS1&"(ap)x" -> 0(ap)x | DT3: =DT1&"(ap)x" -> 1(ap)x | DU3: =DU1&"(ap)x" -> 2(ap)x | DV3: =DV1&"(ap)x" -> 3(ap)x | DW3: =DW1&"(ap)x" -> 4(ap)x | DX3: =DX1&"(ap)x" -> 5(ap)x | DY3: =DY1&"(ap)x" -> 6(ap)x | DZ3: =DZ1&"(ap)x" -> 7(ap)x | ... HT3: =HT1&"(ap)x" -> 105(ap)x
A4: 20 | B4: 0.00117 | C4: 0.00118 | F4: =NRA -> 60 | G4: =SUMPRODUCT($N$44:$DN$44,'v(t)'!$D$51:$DD$51)*(1+Ann_Loading) -> 8.8017766 | H4: =SUMPRODUCT($DT$44:$HT$44,'v(t)'!$D$51:$DD$51)*(1+Ann_Loading) -> 8.0909278 | K4: =A4 -> 20 | L4: =VLOOKUP(K4,Fe_MDT,6,0) -> 0.200936 | M4: 1 | N4: =1-L4 -> 0.799064 | O4: =N4*IFERROR(VLOOKUP($K4+N$1,$K$3:$DN$98,4,0),0) -> 0.63849688 | P4: =O4*IFERROR(VLOOKUP($K4+O$1,$K$3:$DN$98,4,0),0) -> 0.51018966 | Q4: =P4*IFERROR(VLOOKUP($K4+P$1,$K$3:$DN$98,4,0),0) -> 0.40766194 | R4: =Q4*IFERROR(VLOOKUP($K4+Q$1,$K$3:$DN$98,4,0),0) -> 0.32573494 | S4: =R4*IFERROR(VLOOKUP($K4+R$1,$K$3:$DN$98,4,0),0) -> 0.26026743 | T4: =S4*IFERROR(VLOOKUP($K4+S$1,$K$3:$DN$98,4,0),0) -> 0.20795576 | U4: =T4*IFERROR(VLOOKUP($K4+T$1,$K$3:$DN$98,4,0),0) -> 0.16615499 | V4: =U4*IFERROR(VLOOKUP($K4+U$1,$K$3:$DN$98,4,0),0) -> 0.13275385 | ... DN4: =DM4*IFERROR(VLOOKUP($K4+DM$1,$K$3:$DN$98,4,0),0) -> 0 | DQ4: =$A4 -> 20 | DR4: =VLOOKUP(DQ4,Male_MDT,6,0) -> 0.200944 | DS4: 1 | DT4: =1-DR4 -> 0.799056 | DU4: =DT4*IFERROR(VLOOKUP($DQ4+DT$1,$DQ$3:$HT$98,4,0),0) -> 0.63847771 | DV4: =DU4*IFERROR(VLOOKUP($DQ4+DU$1,$DQ$3:$HT$98,4,0),0) -> 0.5101539 | DW4: =DV4*IFERROR(VLOOKUP($DQ4+DV$1,$DQ$3:$HT$98,4,0),0) -> 0.40761705 | DX4: =DW4*IFERROR(VLOOKUP($DQ4+DW$1,$DQ$3:$HT$98,4,0),0) -> 0.32568276 | DY4: =DX4*IFERROR(VLOOKUP($DQ4+DX$1,$DQ$3:$HT$98,4,0),0) -> 0.26021271 | DZ4: =DY4*IFERROR(VLOOKUP($DQ4+DY$1,$DQ$3:$HT$98,4,0),0) -> 0.20790163 | EA4: =DZ4*IFERROR(VLOOKUP($DQ4+DZ$1,$DQ$3:$HT$98,4,0),0) -> 0.16610342 | EB4: =EA4*IFERROR(VLOOKUP($DQ4+EA$1,$DQ$3:$HT$98,4,0),0) -> 0.132706 | ... HT4: =HS4*IFERROR(VLOOKUP($DQ4+HS$1,$DQ$3:$HT$98,4,0),0) -> 0
A5: 21 | B5: 0.00118 | C5: 0.0012 | K5: =K4+1 -> 21 | L5: =VLOOKUP(K5,Fe_MDT,6,0) -> 0.200944 | M5: 1 | N5: =1-L5 -> 0.799056 | O5: =N5*IFERROR(VLOOKUP($K5+N$1,$K$3:$DN$98,4,0),0) -> 0.6384841 | P5: =O5*IFERROR(VLOOKUP($K5+O$1,$K$3:$DN$98,4,0),0) -> 0.51017433 | Q5: =P5*IFERROR(VLOOKUP($K5+P$1,$K$3:$DN$98,4,0),0) -> 0.40764562 | R5: =Q5*IFERROR(VLOOKUP($K5+Q$1,$K$3:$DN$98,4,0),0) -> 0.32571537 | S5: =R5*IFERROR(VLOOKUP($K5+R$1,$K$3:$DN$98,4,0),0) -> 0.26024919 | T5: =S5*IFERROR(VLOOKUP($K5+S$1,$K$3:$DN$98,4,0),0) -> 0.20793702 | U5: =T5*IFERROR(VLOOKUP($K5+T$1,$K$3:$DN$98,4,0),0) -> 0.16613669 | V5: =U5*IFERROR(VLOOKUP($K5+U$1,$K$3:$DN$98,4,0),0) -> 0.13273657 | ... DN5: =DM5*IFERROR(VLOOKUP($K5+DM$1,$K$3:$DN$98,4,0),0) -> 0 | DQ5: =DQ4+1 -> 21 | DR5: =VLOOKUP(DQ5,Male_MDT,6,0) -> 0.20096 | DS5: 1 | DT5: =1-DR5 -> 0.79904 | DU5: =DT5*IFERROR(VLOOKUP($DQ5+DT$1,$DQ$3:$HT$98,4,0),0) -> 0.63844574 | DV5: =DU5*IFERROR(VLOOKUP($DQ5+DU$1,$DQ$3:$HT$98,4,0),0) -> 0.51012326 | DW5: =DV5*IFERROR(VLOOKUP($DQ5+DV$1,$DQ$3:$HT$98,4,0),0) -> 0.4075844 | DX5: =DW5*IFERROR(VLOOKUP($DQ5+DW$1,$DQ$3:$HT$98,4,0),0) -> 0.32565015 | DY5: =DX5*IFERROR(VLOOKUP($DQ5+DX$1,$DQ$3:$HT$98,4,0),0) -> 0.26018405 | DZ5: =DY5*IFERROR(VLOOKUP($DQ5+DY$1,$DQ$3:$HT$98,4,0),0) -> 0.20787457 | EA5: =DZ5*IFERROR(VLOOKUP($DQ5+DZ$1,$DQ$3:$HT$98,4,0),0) -> 0.16607848 | EB5: =EA5*IFERROR(VLOOKUP($DQ5+EA$1,$DQ$3:$HT$98,4,0),0) -> 0.13268209 | ... HT5: =HS5*IFERROR(VLOOKUP($DQ5+HS$1,$DQ$3:$HT$98,4,0),0) -> 0
A6: 22 | B6: 0.00119 | C6: 0.00123 | K6: =K5+1 -> 22 | L6: =VLOOKUP(K6,Fe_MDT,6,0) -> 0.200952 | M6: 1 | N6: =1-L6 -> 0.799048 | O6: =N6*IFERROR(VLOOKUP($K6+N$1,$K$3:$DN$98,4,0),0) -> 0.63847131 | P6: =O6*IFERROR(VLOOKUP($K6+O$1,$K$3:$DN$98,4,0),0) -> 0.51015901 | Q6: =P6*IFERROR(VLOOKUP($K6+P$1,$K$3:$DN$98,4,0),0) -> 0.40762521 | R6: =Q6*IFERROR(VLOOKUP($K6+Q$1,$K$3:$DN$98,4,0),0) -> 0.32569581 | S6: =R6*IFERROR(VLOOKUP($K6+R$1,$K$3:$DN$98,4,0),0) -> 0.26022834 | T6: =S6*IFERROR(VLOOKUP($K6+S$1,$K$3:$DN$98,4,0),0) -> 0.2079162 | U6: =T6*IFERROR(VLOOKUP($K6+T$1,$K$3:$DN$98,4,0),0) -> 0.16611673 | V6: =U6*IFERROR(VLOOKUP($K6+U$1,$K$3:$DN$98,4,0),0) -> 0.13271796 | ... DN6: =DM6*IFERROR(VLOOKUP($K6+DM$1,$K$3:$DN$98,4,0),0) -> 0 | DQ6: =DQ5+1 -> 22 | DR6: =VLOOKUP(DQ6,Male_MDT,6,0) -> 0.200984 | DS6: 1 | DT6: =1-DR6 -> 0.799016 | DU6: =DT6*IFERROR(VLOOKUP($DQ6+DT$1,$DQ$3:$HT$98,4,0),0) -> 0.63842018 | DV6: =DU6*IFERROR(VLOOKUP($DQ6+DU$1,$DQ$3:$HT$98,4,0),0) -> 0.51009261 | DW6: =DV6*IFERROR(VLOOKUP($DQ6+DV$1,$DQ$3:$HT$98,4,0),0) -> 0.40755176 | DX6: =DW6*IFERROR(VLOOKUP($DQ6+DW$1,$DQ$3:$HT$98,4,0),0) -> 0.32562081 | DY6: =DX6*IFERROR(VLOOKUP($DQ6+DX$1,$DQ$3:$HT$98,4,0),0) -> 0.2601554 | DZ6: =DY6*IFERROR(VLOOKUP($DQ6+DY$1,$DQ$3:$HT$98,4,0),0) -> 0.20784751 | EA6: =DZ6*IFERROR(VLOOKUP($DQ6+DZ$1,$DQ$3:$HT$98,4,0),0) -> 0.16605187 | EB6: =EA6*IFERROR(VLOOKUP($DQ6+EA$1,$DQ$3:$HT$98,4,0),0) -> 0.13265685 | ... HT6: =HS6*IFERROR(VLOOKUP($DQ6+HS$1,$DQ$3:$HT$98,4,0),0) -> 0
A7: 23 | B7: 0.0012 | C7: 0.00124 | K7: =K6+1 -> 23 | L7: =VLOOKUP(K7,Fe_MDT,6,0) -> 0.20096 | M7: 1 | N7: =1-L7 -> 0.79904 | O7: =N7*IFERROR(VLOOKUP($K7+N$1,$K$3:$DN$98,4,0),0) -> 0.63845853 | P7: =O7*IFERROR(VLOOKUP($K7+O$1,$K$3:$DN$98,4,0),0) -> 0.51013858 | Q7: =P7*IFERROR(VLOOKUP($K7+P$1,$K$3:$DN$98,4,0),0) -> 0.40760481 | R7: =Q7*IFERROR(VLOOKUP($K7+Q$1,$K$3:$DN$98,4,0),0) -> 0.32567298 | S7: =R7*IFERROR(VLOOKUP($K7+R$1,$K$3:$DN$98,4,0),0) -> 0.26020489 | T7: =S7*IFERROR(VLOOKUP($K7+S$1,$K$3:$DN$98,4,0),0) -> 0.2078933 | U7: =T7*IFERROR(VLOOKUP($K7+T$1,$K$3:$DN$98,4,0),0) -> 0.16609511 | V7: =U7*IFERROR(VLOOKUP($K7+U$1,$K$3:$DN$98,4,0),0) -> 0.1326967 | ... DN7: =DM7*IFERROR(VLOOKUP($K7+DM$1,$K$3:$DN$98,4,0),0) -> 0 | DQ7: =DQ6+1 -> 23 | DR7: =VLOOKUP(DQ7,Male_MDT,6,0) -> 0.200992 | DS7: 1 | DT7: =1-DR7 -> 0.799008 | DU7: =DT7*IFERROR(VLOOKUP($DQ7+DT$1,$DQ$3:$HT$98,4,0),0) -> 0.638401 | DV7: =DU7*IFERROR(VLOOKUP($DQ7+DU$1,$DQ$3:$HT$98,4,0),0) -> 0.51006708 | DW7: =DV7*IFERROR(VLOOKUP($DQ7+DV$1,$DQ$3:$HT$98,4,0),0) -> 0.40752727 | DX7: =DW7*IFERROR(VLOOKUP($DQ7+DW$1,$DQ$3:$HT$98,4,0),0) -> 0.32559473 | DY7: =DX7*IFERROR(VLOOKUP($DQ7+DX$1,$DQ$3:$HT$98,4,0),0) -> 0.26012935 | DZ7: =DY7*IFERROR(VLOOKUP($DQ7+DY$1,$DQ$3:$HT$98,4,0),0) -> 0.20782046 | EA7: =DZ7*IFERROR(VLOOKUP($DQ7+DZ$1,$DQ$3:$HT$98,4,0),0) -> 0.16602527 | EB7: =EA7*IFERROR(VLOOKUP($DQ7+EA$1,$DQ$3:$HT$98,4,0),0) -> 0.13263028 | ... HT7: =HS7*IFERROR(VLOOKUP($DQ7+HS$1,$DQ$3:$HT$98,4,0),0) -> 0
A8: 24 | B8: 0.00121 | C8: 0.00126 | K8: =K7+1 -> 24 | L8: =VLOOKUP(K8,Fe_MDT,6,0) -> 0.200968 | M8: 1 | N8: =1-L8 -> 0.799032 | O8: =N8*IFERROR(VLOOKUP($K8+N$1,$K$3:$DN$98,4,0),0) -> 0.63843935 | P8: =O8*IFERROR(VLOOKUP($K8+O$1,$K$3:$DN$98,4,0),0) -> 0.51011815 | Q8: =P8*IFERROR(VLOOKUP($K8+P$1,$K$3:$DN$98,4,0),0) -> 0.40758032 | R8: =Q8*IFERROR(VLOOKUP($K8+Q$1,$K$3:$DN$98,4,0),0) -> 0.32564689 | S8: =R8*IFERROR(VLOOKUP($K8+R$1,$K$3:$DN$98,4,0),0) -> 0.26017884 | T8: =S8*IFERROR(VLOOKUP($K8+S$1,$K$3:$DN$98,4,0),0) -> 0.20786833 | U8: =T8*IFERROR(VLOOKUP($K8+T$1,$K$3:$DN$98,4,0),0) -> 0.16607016 | V8: =U8*IFERROR(VLOOKUP($K8+U$1,$K$3:$DN$98,4,0),0) -> 0.13267279 | ... DN8: =DM8*IFERROR(VLOOKUP($K8+DM$1,$K$3:$DN$98,4,0),0) -> 0 | DQ8: =DQ7+1 -> 24 | DR8: =VLOOKUP(DQ8,Male_MDT,6,0) -> 0.201008 | DS8: 1 | DT8: =1-DR8 -> 0.798992 | DU8: =DT8*IFERROR(VLOOKUP($DQ8+DT$1,$DQ$3:$HT$98,4,0),0) -> 0.63837543 | DV8: =DU8*IFERROR(VLOOKUP($DQ8+DU$1,$DQ$3:$HT$98,4,0),0) -> 0.51004154 | DW8: =DV8*IFERROR(VLOOKUP($DQ8+DV$1,$DQ$3:$HT$98,4,0),0) -> 0.40749871 | DX8: =DW8*IFERROR(VLOOKUP($DQ8+DW$1,$DQ$3:$HT$98,4,0),0) -> 0.32556539 | DY8: =DX8*IFERROR(VLOOKUP($DQ8+DX$1,$DQ$3:$HT$98,4,0),0) -> 0.2600981 | DZ8: =DY8*IFERROR(VLOOKUP($DQ8+DY$1,$DQ$3:$HT$98,4,0),0) -> 0.20778925 | EA8: =DZ8*IFERROR(VLOOKUP($DQ8+DZ$1,$DQ$3:$HT$98,4,0),0) -> 0.16599369 | EB8: =EA8*IFERROR(VLOOKUP($DQ8+EA$1,$DQ$3:$HT$98,4,0),0) -> 0.13259841 | ... HT8: =HS8*IFERROR(VLOOKUP($DQ8+HS$1,$DQ$3:$HT$98,4,0),0) -> 0
A9: 25 | B9: 0.00123 | C9: 0.00128 | K9: =K8+1 -> 25 | L9: =VLOOKUP(K9,Fe_MDT,6,0) -> 0.200984 | M9: 1 | N9: =1-L9 -> 0.799016 | O9: =N9*IFERROR(VLOOKUP($K9+N$1,$K$3:$DN$98,4,0),0) -> 0.63842018 | P9: =O9*IFERROR(VLOOKUP($K9+O$1,$K$3:$DN$98,4,0),0) -> 0.51009261 | Q9: =P9*IFERROR(VLOOKUP($K9+P$1,$K$3:$DN$98,4,0),0) -> 0.40755176 | R9: =Q9*IFERROR(VLOOKUP($K9+Q$1,$K$3:$DN$98,4,0),0) -> 0.32561755 | S9: =R9*IFERROR(VLOOKUP($K9+R$1,$K$3:$DN$98,4,0),0) -> 0.26015019 | T9: =S9*IFERROR(VLOOKUP($K9+S$1,$K$3:$DN$98,4,0),0) -> 0.20783919 | U9: =T9*IFERROR(VLOOKUP($K9+T$1,$K$3:$DN$98,4,0),0) -> 0.1660419 | V9: =U9*IFERROR(VLOOKUP($K9+U$1,$K$3:$DN$98,4,0),0) -> 0.13264489 | ... DN9: =DM9*IFERROR(VLOOKUP($K9+DM$1,$K$3:$DN$98,4,0),0) -> 0 | DQ9: =DQ8+1 -> 25 | DR9: =VLOOKUP(DQ9,Male_MDT,6,0) -> 0.201024 | DS9: 1 | DT9: =1-DR9 -> 0.798976 | DU9: =DT9*IFERROR(VLOOKUP($DQ9+DT$1,$DQ$3:$HT$98,4,0),0) -> 0.63835626 | DV9: =DU9*IFERROR(VLOOKUP($DQ9+DU$1,$DQ$3:$HT$98,4,0),0) -> 0.51001601 | DW9: =DV9*IFERROR(VLOOKUP($DQ9+DV$1,$DQ$3:$HT$98,4,0),0) -> 0.40747015 | DX9: =DW9*IFERROR(VLOOKUP($DQ9+DW$1,$DQ$3:$HT$98,4,0),0) -> 0.32553279 | DY9: =DX9*IFERROR(VLOOKUP($DQ9+DX$1,$DQ$3:$HT$98,4,0),0) -> 0.26006424 | DZ9: =DY9*IFERROR(VLOOKUP($DQ9+DY$1,$DQ$3:$HT$98,4,0),0) -> 0.20775388 | EA9: =DZ9*IFERROR(VLOOKUP($DQ9+DZ$1,$DQ$3:$HT$98,4,0),0) -> 0.16595712 | EB9: =EA9*IFERROR(VLOOKUP($DQ9+EA$1,$DQ$3:$HT$98,4,0),0) -> 0.13256257 | ... HT9: =HS9*IFERROR(VLOOKUP($DQ9+HS$1,$DQ$3:$HT$98,4,0),0) -> 0
A10: 26 | B10: 0.00124 | C10: 0.00129 | K10: =K9+1 -> 26 | L10: =VLOOKUP(K10,Fe_MDT,6,0) -> 0.200992 | M10: 1 | N10: =1-L10 -> 0.799008 | O10: =N10*IFERROR(VLOOKUP($K10+N$1,$K$3:$DN$98,4,0),0) -> 0.638401 | P10: =O10*IFERROR(VLOOKUP($K10+O$1,$K$3:$DN$98,4,0),0) -> 0.51006708 | Q10: =P10*IFERROR(VLOOKUP($K10+P$1,$K$3:$DN$98,4,0),0) -> 0.40752319 | R10: =Q10*IFERROR(VLOOKUP($K10+Q$1,$K$3:$DN$98,4,0),0) -> 0.32558821 | S10: =R10*IFERROR(VLOOKUP($K10+R$1,$K$3:$DN$98,4,0),0) -> 0.26011893 | T10: =S10*IFERROR(VLOOKUP($K10+S$1,$K$3:$DN$98,4,0),0) -> 0.20780797 | U10: =T10*IFERROR(VLOOKUP($K10+T$1,$K$3:$DN$98,4,0),0) -> 0.16601031 | V10: =U10*IFERROR(VLOOKUP($K10+U$1,$K$3:$DN$98,4,0),0) -> 0.13261302 | ... DN10: =DM10*IFERROR(VLOOKUP($K10+DM$1,$K$3:$DN$98,4,0),0) -> 0 | DQ10: =DQ9+1 -> 26 | DR10: =VLOOKUP(DQ10,Male_MDT,6,0) -> 0.201032 | DS10: 1 | DT10: =1-DR10 -> 0.798968 | DU10: =DT10*IFERROR(VLOOKUP($DQ10+DT$1,$DQ$3:$HT$98,4,0),0) -> 0.63833708 | DV10: =DU10*IFERROR(VLOOKUP($DQ10+DU$1,$DQ$3:$HT$98,4,0),0) -> 0.50999047 | DW10: =DV10*IFERROR(VLOOKUP($DQ10+DV$1,$DQ$3:$HT$98,4,0),0) -> 0.40743751 | DX10: =DW10*IFERROR(VLOOKUP($DQ10+DW$1,$DQ$3:$HT$98,4,0),0) -> 0.32549694 | DY10: =DX10*IFERROR(VLOOKUP($DQ10+DX$1,$DQ$3:$HT$98,4,0),0) -> 0.26002518 | DZ10: =DY10*IFERROR(VLOOKUP($DQ10+DY$1,$DQ$3:$HT$98,4,0),0) -> 0.20771228 | EA10: =DZ10*IFERROR(VLOOKUP($DQ10+DZ$1,$DQ$3:$HT$98,4,0),0) -> 0.16591558 | EB10: =EA10*IFERROR(VLOOKUP($DQ10+EA$1,$DQ$3:$HT$98,4,0),0) -> 0.13252009 | ... HT10: =HS10*IFERROR(VLOOKUP($DQ10+HS$1,$DQ$3:$HT$98,4,0),0) -> 0
A11: 27 | B11: 0.00126 | C11: 0.00131 | K11: =K10+1 -> 27 | L11: =VLOOKUP(K11,Fe_MDT,6,0) -> 0.201008 | M11: 1 | N11: =1-L11 -> 0.798992 | O11: =N11*IFERROR(VLOOKUP($K11+N$1,$K$3:$DN$98,4,0),0) -> 0.63837543 | P11: =O11*IFERROR(VLOOKUP($K11+O$1,$K$3:$DN$98,4,0),0) -> 0.51003644 | Q11: =P11*IFERROR(VLOOKUP($K11+P$1,$K$3:$DN$98,4,0),0) -> 0.40749055 | R11: =Q11*IFERROR(VLOOKUP($K11+Q$1,$K$3:$DN$98,4,0),0) -> 0.32555235 | S11: =R11*IFERROR(VLOOKUP($K11+R$1,$K$3:$DN$98,4,0),0) -> 0.26008247 | T11: =S11*IFERROR(VLOOKUP($K11+S$1,$K$3:$DN$98,4,0),0) -> 0.20777052 | U11: =T11*IFERROR(VLOOKUP($K11+T$1,$K$3:$DN$98,4,0),0) -> 0.16597208 | V11: =U11*IFERROR(VLOOKUP($K11+U$1,$K$3:$DN$98,4,0),0) -> 0.13257451 | ... DN11: =DM11*IFERROR(VLOOKUP($K11+DM$1,$K$3:$DN$98,4,0),0) -> 0 | DQ11: =DQ10+1 -> 27 | DR11: =VLOOKUP(DQ11,Male_MDT,6,0) -> 0.201048 | DS11: 1 | DT11: =1-DR11 -> 0.798952 | DU11: =DT11*IFERROR(VLOOKUP($DQ11+DT$1,$DQ$3:$HT$98,4,0),0) -> 0.63831152 | DV11: =DU11*IFERROR(VLOOKUP($DQ11+DU$1,$DQ$3:$HT$98,4,0),0) -> 0.50995473 | DW11: =DV11*IFERROR(VLOOKUP($DQ11+DV$1,$DQ$3:$HT$98,4,0),0) -> 0.40739671 | DX11: =DW11*IFERROR(VLOOKUP($DQ11+DW$1,$DQ$3:$HT$98,4,0),0) -> 0.32545131 | DY11: =DX11*IFERROR(VLOOKUP($DQ11+DX$1,$DQ$3:$HT$98,4,0),0) -> 0.25997571 | DZ11: =DY11*IFERROR(VLOOKUP($DQ11+DY$1,$DQ$3:$HT$98,4,0),0) -> 0.20766236 | EA11: =DZ11*IFERROR(VLOOKUP($DQ11+DZ$1,$DQ$3:$HT$98,4,0),0) -> 0.16586408 | EB11: =EA11*IFERROR(VLOOKUP($DQ11+EA$1,$DQ$3:$HT$98,4,0),0) -> 0.13246834 | ... HT11: =HS11*IFERROR(VLOOKUP($DQ11+HS$1,$DQ$3:$HT$98,4,0),0) -> 0
A12: 28 | B12: 0.00128 | C12: 0.00133 | K12: =K11+1 -> 28 | L12: =VLOOKUP(K12,Fe_MDT,6,0) -> 0.201024 | M12: 1 | N12: =1-L12 -> 0.798976 | O12: =N12*IFERROR(VLOOKUP($K12+N$1,$K$3:$DN$98,4,0),0) -> 0.63834986 | P12: =O12*IFERROR(VLOOKUP($K12+O$1,$K$3:$DN$98,4,0),0) -> 0.51000579 | Q12: =P12*IFERROR(VLOOKUP($K12+P$1,$K$3:$DN$98,4,0),0) -> 0.40745383 | R12: =Q12*IFERROR(VLOOKUP($K12+Q$1,$K$3:$DN$98,4,0),0) -> 0.32551323 | S12: =R12*IFERROR(VLOOKUP($K12+R$1,$K$3:$DN$98,4,0),0) -> 0.2600408 | T12: =S12*IFERROR(VLOOKUP($K12+S$1,$K$3:$DN$98,4,0),0) -> 0.20772684 | U12: =T12*IFERROR(VLOOKUP($K12+T$1,$K$3:$DN$98,4,0),0) -> 0.16592721 | V12: =U12*IFERROR(VLOOKUP($K12+U$1,$K$3:$DN$98,4,0),0) -> 0.13253204 | ... DN12: =DM12*IFERROR(VLOOKUP($K12+DM$1,$K$3:$DN$98,4,0),0) -> 0 | DQ12: =DQ11+1 -> 28 | DR12: =VLOOKUP(DQ12,Male_MDT,6,0) -> 0.201064 | DS12: 1 | DT12: =1-DR12 -> 0.798936 | DU12: =DT12*IFERROR(VLOOKUP($DQ12+DT$1,$DQ$3:$HT$98,4,0),0) -> 0.63827956 | DV12: =DU12*IFERROR(VLOOKUP($DQ12+DU$1,$DQ$3:$HT$98,4,0),0) -> 0.50991388 | DW12: =DV12*IFERROR(VLOOKUP($DQ12+DV$1,$DQ$3:$HT$98,4,0),0) -> 0.40734776 | DX12: =DW12*IFERROR(VLOOKUP($DQ12+DW$1,$DQ$3:$HT$98,4,0),0) -> 0.32539591 | DY12: =DX12*IFERROR(VLOOKUP($DQ12+DX$1,$DQ$3:$HT$98,4,0),0) -> 0.25991844 | DZ12: =DY12*IFERROR(VLOOKUP($DQ12+DY$1,$DQ$3:$HT$98,4,0),0) -> 0.20760206 | EA12: =DZ12*IFERROR(VLOOKUP($DQ12+DZ$1,$DQ$3:$HT$98,4,0),0) -> 0.16580263 | EB12: =EA12*IFERROR(VLOOKUP($DQ12+EA$1,$DQ$3:$HT$98,4,0),0) -> 0.13240733 | ... HT12: =HS12*IFERROR(VLOOKUP($DQ12+HS$1,$DQ$3:$HT$98,4,0),0) -> 0
A13: 29 | B13: 0.0013 | C13: 0.00136 | K13: =K12+1 -> 29 | L13: =VLOOKUP(K13,Fe_MDT,6,0) -> 0.20104 | M13: 1 | N13: =1-L13 -> 0.79896 | O13: =N13*IFERROR(VLOOKUP($K13+N$1,$K$3:$DN$98,4,0),0) -> 0.6383243 | P13: =O13*IFERROR(VLOOKUP($K13+O$1,$K$3:$DN$98,4,0),0) -> 0.50997005 | Q13: =P13*IFERROR(VLOOKUP($K13+P$1,$K$3:$DN$98,4,0),0) -> 0.40741303 | R13: =Q13*IFERROR(VLOOKUP($K13+Q$1,$K$3:$DN$98,4,0),0) -> 0.3254676 | S13: =R13*IFERROR(VLOOKUP($K13+R$1,$K$3:$DN$98,4,0),0) -> 0.25999133 | T13: =S13*IFERROR(VLOOKUP($K13+S$1,$K$3:$DN$98,4,0),0) -> 0.20767484 | U13: =T13*IFERROR(VLOOKUP($K13+T$1,$K$3:$DN$98,4,0),0) -> 0.16587737 | V13: =U13*IFERROR(VLOOKUP($K13+U$1,$K$3:$DN$98,4,0),0) -> 0.13248294 | ... DN13: =DM13*IFERROR(VLOOKUP($K13+DM$1,$K$3:$DN$98,4,0),0) -> 0 | DQ13: =DQ12+1 -> 29 | DR13: =VLOOKUP(DQ13,Male_MDT,6,0) -> 0.201088 | DS13: 1 | DT13: =1-DR13 -> 0.798912 | DU13: =DT13*IFERROR(VLOOKUP($DQ13+DT$1,$DQ$3:$HT$98,4,0),0) -> 0.63824121 | DV13: =DU13*IFERROR(VLOOKUP($DQ13+DU$1,$DQ$3:$HT$98,4,0),0) -> 0.50986282 | DW13: =DV13*IFERROR(VLOOKUP($DQ13+DV$1,$DQ$3:$HT$98,4,0),0) -> 0.40728658 | DX13: =DW13*IFERROR(VLOOKUP($DQ13+DW$1,$DQ$3:$HT$98,4,0),0) -> 0.32533074 | DY13: =DX13*IFERROR(VLOOKUP($DQ13+DX$1,$DQ$3:$HT$98,4,0),0) -> 0.25984817 | DZ13: =DY13*IFERROR(VLOOKUP($DQ13+DY$1,$DQ$3:$HT$98,4,0),0) -> 0.2075293 | EA13: =DZ13*IFERROR(VLOOKUP($DQ13+DZ$1,$DQ$3:$HT$98,4,0),0) -> 0.16572958 | EB13: =EA13*IFERROR(VLOOKUP($DQ13+EA$1,$DQ$3:$HT$98,4,0),0) -> 0.13233573 | ... HT13: =HS13*IFERROR(VLOOKUP($DQ13+HS$1,$DQ$3:$HT$98,4,0),0) -> 0
A14: 30 | B14: 0.00132 | C14: 0.00139 | K14: =K13+1 -> 30 | L14: =VLOOKUP(K14,Fe_MDT,6,0) -> 0.201056 | M14: 1 | N14: =1-L14 -> 0.798944 | O14: =N14*IFERROR(VLOOKUP($K14+N$1,$K$3:$DN$98,4,0),0) -> 0.63829234 | P14: =O14*IFERROR(VLOOKUP($K14+O$1,$K$3:$DN$98,4,0),0) -> 0.5099292 | Q14: =P14*IFERROR(VLOOKUP($K14+P$1,$K$3:$DN$98,4,0),0) -> 0.40736408 | R14: =Q14*IFERROR(VLOOKUP($K14+Q$1,$K$3:$DN$98,4,0),0) -> 0.3254122 | S14: =R14*IFERROR(VLOOKUP($K14+R$1,$K$3:$DN$98,4,0),0) -> 0.25993146 | T14: =S14*IFERROR(VLOOKUP($K14+S$1,$K$3:$DN$98,4,0),0) -> 0.20761661 | U14: =T14*IFERROR(VLOOKUP($K14+T$1,$K$3:$DN$98,4,0),0) -> 0.16581924 | V14: =U14*IFERROR(VLOOKUP($K14+U$1,$K$3:$DN$98,4,0),0) -> 0.1324259 | ... DN14: =DM14*IFERROR(VLOOKUP($K14+DM$1,$K$3:$DN$98,4,0),0) -> 0 | DQ14: =DQ13+1 -> 30 | DR14: =VLOOKUP(DQ14,Male_MDT,6,0) -> 0.201112 | DS14: 1 | DT14: =1-DR14 -> 0.798888 | DU14: =DT14*IFERROR(VLOOKUP($DQ14+DT$1,$DQ$3:$HT$98,4,0),0) -> 0.63819647 | DV14: =DU14*IFERROR(VLOOKUP($DQ14+DU$1,$DQ$3:$HT$98,4,0),0) -> 0.50980155 | DW14: =DV14*IFERROR(VLOOKUP($DQ14+DV$1,$DQ$3:$HT$98,4,0),0) -> 0.40721725 | DX14: =DW14*IFERROR(VLOOKUP($DQ14+DW$1,$DQ$3:$HT$98,4,0),0) -> 0.32525256 | DY14: =DX14*IFERROR(VLOOKUP($DQ14+DX$1,$DQ$3:$HT$98,4,0),0) -> 0.25976491 | DZ14: =DY14*IFERROR(VLOOKUP($DQ14+DY$1,$DQ$3:$HT$98,4,0),0) -> 0.2074441 | EA14: =DZ14*IFERROR(VLOOKUP($DQ14+DZ$1,$DQ$3:$HT$98,4,0),0) -> 0.16564494 | EB14: =EA14*IFERROR(VLOOKUP($DQ14+EA$1,$DQ$3:$HT$98,4,0),0) -> 0.13225092 | ... HT14: =HS14*IFERROR(VLOOKUP($DQ14+HS$1,$DQ$3:$HT$98,4,0),0) -> 0
A15: 31 | B15: 0.00135 | C15: 0.00143 | K15: =K14+1 -> 31 | L15: =VLOOKUP(K15,Fe_MDT,6,0) -> 0.20108 | M15: 1 | N15: =1-L15 -> 0.79892 | O15: =N15*IFERROR(VLOOKUP($K15+N$1,$K$3:$DN$98,4,0),0) -> 0.63825399 | P15: =O15*IFERROR(VLOOKUP($K15+O$1,$K$3:$DN$98,4,0),0) -> 0.50987814 | Q15: =P15*IFERROR(VLOOKUP($K15+P$1,$K$3:$DN$98,4,0),0) -> 0.40730289 | R15: =Q15*IFERROR(VLOOKUP($K15+Q$1,$K$3:$DN$98,4,0),0) -> 0.32534378 | S15: =R15*IFERROR(VLOOKUP($K15+R$1,$K$3:$DN$98,4,0),0) -> 0.25986379 | T15: =S15*IFERROR(VLOOKUP($K15+S$1,$K$3:$DN$98,4,0),0) -> 0.20754801 | U15: =T15*IFERROR(VLOOKUP($K15+T$1,$K$3:$DN$98,4,0),0) -> 0.16575116 | V15: =U15*IFERROR(VLOOKUP($K15+U$1,$K$3:$DN$98,4,0),0) -> 0.13235959 | ... DN15: =DM15*IFERROR(VLOOKUP($K15+DM$1,$K$3:$DN$98,4,0),0) -> 0 | DQ15: =DQ14+1 -> 31 | DR15: =VLOOKUP(DQ15,Male_MDT,6,0) -> 0.201144 | DS15: 1 | DT15: =1-DR15 -> 0.798856 | DU15: =DT15*IFERROR(VLOOKUP($DQ15+DT$1,$DQ$3:$HT$98,4,0),0) -> 0.63813895 | DV15: =DU15*IFERROR(VLOOKUP($DQ15+DU$1,$DQ$3:$HT$98,4,0),0) -> 0.50973008 | DW15: =DV15*IFERROR(VLOOKUP($DQ15+DV$1,$DQ$3:$HT$98,4,0),0) -> 0.40713161 | DX15: =DW15*IFERROR(VLOOKUP($DQ15+DW$1,$DQ$3:$HT$98,4,0),0) -> 0.3251581 | DY15: =DX15*IFERROR(VLOOKUP($DQ15+DX$1,$DQ$3:$HT$98,4,0),0) -> 0.25966606 | DZ15: =DY15*IFERROR(VLOOKUP($DQ15+DY$1,$DQ$3:$HT$98,4,0),0) -> 0.20734439 | EA15: =DZ15*IFERROR(VLOOKUP($DQ15+DZ$1,$DQ$3:$HT$98,4,0),0) -> 0.16554376 | EB15: =EA15*IFERROR(VLOOKUP($DQ15+EA$1,$DQ$3:$HT$98,4,0),0) -> 0.1321516 | ... HT15: =HS15*IFERROR(VLOOKUP($DQ15+HS$1,$DQ$3:$HT$98,4,0),0) -> 0
A16: 32 | B16: 0.00138 | C16: 0.00148 | K16: =K15+1 -> 32 | L16: =VLOOKUP(K16,Fe_MDT,6,0) -> 0.201104 | M16: 1 | N16: =1-L16 -> 0.798896 | O16: =N16*IFERROR(VLOOKUP($K16+N$1,$K$3:$DN$98,4,0),0) -> 0.63820925 | P16: =O16*IFERROR(VLOOKUP($K16+O$1,$K$3:$DN$98,4,0),0) -> 0.50981687 | Q16: =P16*IFERROR(VLOOKUP($K16+P$1,$K$3:$DN$98,4,0),0) -> 0.40722948 | R16: =Q16*IFERROR(VLOOKUP($K16+Q$1,$K$3:$DN$98,4,0),0) -> 0.32526885 | S16: =R16*IFERROR(VLOOKUP($K16+R$1,$K$3:$DN$98,4,0),0) -> 0.25978572 | T16: =S16*IFERROR(VLOOKUP($K16+S$1,$K$3:$DN$98,4,0),0) -> 0.20746903 | U16: =T16*IFERROR(VLOOKUP($K16+T$1,$K$3:$DN$98,4,0),0) -> 0.16567315 | V16: =U16*IFERROR(VLOOKUP($K16+U$1,$K$3:$DN$98,4,0),0) -> 0.14055321 | ... DN16: =DM16*IFERROR(VLOOKUP($K16+DM$1,$K$3:$DN$98,4,0),0) -> 0 | DQ16: =DQ15+1 -> 32 | DR16: =VLOOKUP(DQ16,Male_MDT,6,0) -> 0.201184 | DS16: 1 | DT16: =1-DR16 -> 0.798816 | DU16: =DT16*IFERROR(VLOOKUP($DQ16+DT$1,$DQ$3:$HT$98,4,0),0) -> 0.63807505 | DV16: =DU16*IFERROR(VLOOKUP($DQ16+DU$1,$DQ$3:$HT$98,4,0),0) -> 0.5096433 | DW16: =DV16*IFERROR(VLOOKUP($DQ16+DV$1,$DQ$3:$HT$98,4,0),0) -> 0.40702968 | DX16: =DW16*IFERROR(VLOOKUP($DQ16+DW$1,$DQ$3:$HT$98,4,0),0) -> 0.32504739 | DY16: =DX16*IFERROR(VLOOKUP($DQ16+DX$1,$DQ$3:$HT$98,4,0),0) -> 0.25955164 | DZ16: =DY16*IFERROR(VLOOKUP($DQ16+DY$1,$DQ$3:$HT$98,4,0),0) -> 0.20722603 | EA16: =DZ16*IFERROR(VLOOKUP($DQ16+DZ$1,$DQ$3:$HT$98,4,0),0) -> 0.16542605 | EB16: =EA16*IFERROR(VLOOKUP($DQ16+EA$1,$DQ$3:$HT$98,4,0),0) -> 0.14028874 | ... HT16: =HS16*IFERROR(VLOOKUP($DQ16+HS$1,$DQ$3:$HT$98,4,0),0) -> 0
... A98: 114 | B98: 0.829 | C98: 1 | K98: =K97+1 -> 114 | L98: =VLOOKUP(K98,Fe_MDT,6,0) -> 0.829 | M98: 1 | N98: =1-L98 -> 0.171 | O98: =N98*IFERROR(VLOOKUP($K98+N$1,$K$3:$DN$98,4,0),0) -> 0 | P98: =O98*IFERROR(VLOOKUP($K98+O$1,$K$3:$DN$98,4,0),0) -> 0 | Q98: =P98*IFERROR(VLOOKUP($K98+P$1,$K$3:$DN$98,4,0),0) -> 0 | R98: =Q98*IFERROR(VLOOKUP($K98+Q$1,$K$3:$DN$98,4,0),0) -> 0 | S98: =R98*IFERROR(VLOOKUP($K98+R$1,$K$3:$DN$98,4,0),0) -> 0 | T98: =S98*IFERROR(VLOOKUP($K98+S$1,$K$3:$DN$98,4,0),0) -> 0 | U98: =T98*IFERROR(VLOOKUP($K98+T$1,$K$3:$DN$98,4,0),0) -> 0 | V98: =U98*IFERROR(VLOOKUP($K98+U$1,$K$3:$DN$98,4,0),0) -> 0 | ... DN98: =DM98*IFERROR(VLOOKUP($K98+DM$1,$K$3:$DN$98,4,0),0) -> 0 | DQ98: =DQ97+1 -> 114 | DR98: =VLOOKUP(DQ98,Male_MDT,6,0) -> 1 | DS98: 1 | DT98: =1-DR98 -> 0 | DU98: =DT98*IFERROR(VLOOKUP($DQ98+DT$1,$DQ$3:$HT$98,4,0),0) -> 0 | DV98: =DU98*IFERROR(VLOOKUP($DQ98+DU$1,$DQ$3:$HT$98,4,0),0) -> 0 | DW98: =DV98*IFERROR(VLOOKUP($DQ98+DV$1,$DQ$3:$HT$98,4,0),0) -> 0 | DX98: =DW98*IFERROR(VLOOKUP($DQ98+DW$1,$DQ$3:$HT$98,4,0),0) -> 0 | DY98: =DX98*IFERROR(VLOOKUP($DQ98+DX$1,$DQ$3:$HT$98,4,0),0) -> 0 | DZ98: =DY98*IFERROR(VLOOKUP($DQ98+DY$1,$DQ$3:$HT$98,4,0),0) -> 0 | EA98: =DZ98*IFERROR(VLOOKUP($DQ98+DZ$1,$DQ$3:$HT$98,4,0),0) -> 0 | EB98: =EA98*IFERROR(VLOOKUP($DQ98+EA$1,$DQ$3:$HT$98,4,0),0) -> 0 | ... HT98: =HS98*IFERROR(VLOOKUP($DQ98+HS$1,$DQ$3:$HT$98,4,0),0) -> 0
A99: 115 | B99: 0.909 | C99: 1
A100: 116 | B100: 1 | C100: 1

Sheet MDT
G1: 1 | H1: 2 | I1: 3 | J1: 4 | K1: 5 | L1: 6 | M1: 7 | O1: 1 | P1: 2 | Q1: 3 | R1: 4 | S1: 5 | T1: 6 | U1: 7
A2: Withdrawal Probabilities | H2: MALES | P2: FEMALES
A3: Age x | B3: Withdrawal | D3: Age limit | E3: Withdrawal | G3: Age x | H3: qxd | I3: qxw | J3: (aq)dX | K3: (aq)wX | L3: (aq)X | M3: (ap)X | O3: Age x | P3: qxd | Q3: qxw | R3: (aq)dX | S3: (aq)wX | T3: (aq)X | U3: (ap)X
A4: 20 | B4: =IF(A4<$D$4,0,IF(A4<$D$5,$E$4,IF(A4<$D$6,$E$5,IF(A4<$D$7,$E$6,IF(A4<$D$8,$E$7,0))))) -> 0.2 | D4: 20 | E4: 0.2 | G4: 20 | H4: =VLOOKUP($G4,Mortality_Table,3,FALSE) -> 0.00118 | I4: =VLOOKUP($G4,Withdrawal_Probs,2,FALSE) -> 0.2 | J4: =$H4*(1-0.5*$I4) -> 0.001062 | K4: =$I4*(1-0.5*$H4) -> 0.199882 | L4: =SUM(J4:K4) -> 0.200944 | M4: =1-L4 -> 0.799056 | O4: 20 | P4: =VLOOKUP($G4,Mortality_Table,2,FALSE) -> 0.00117 | Q4: =VLOOKUP($G4,Withdrawal_Probs,2,FALSE) -> 0.2 | R4: =$P4*(1-0.5*$Q4) -> 0.001053 | S4: =$Q4*(1-0.5*$P4) -> 0.199883 | T4: =SUM(R4:S4) -> 0.200936 | U4: =1-T4 -> 0.799064
A5: 21 | B5: =IF(A5<$D$4,0,IF(A5<$D$5,$E$4,IF(A5<$D$6,$E$5,IF(A5<$D$7,$E$6,IF(A5<$D$8,$E$7,0))))) -> 0.2 | D5: 40 | E5: 0.15 | G5: 21 | H5: =VLOOKUP($G5,Mortality_Table,3,FALSE) -> 0.0012 | I5: =VLOOKUP($G5,Withdrawal_Probs,2,FALSE) -> 0.2 | J5: =$H5*(1-0.5*$I5) -> 0.00108 | K5: =$I5*(1-0.5*$H5) -> 0.19988 | L5: =SUM(J5:K5) -> 0.20096 | M5: =1-L5 -> 0.79904 | O5: 21 | P5: =VLOOKUP($G5,Mortality_Table,2,FALSE) -> 0.00118 | Q5: =VLOOKUP($G5,Withdrawal_Probs,2,FALSE) -> 0.2 | R5: =$P5*(1-0.5*$Q5) -> 0.001062 | S5: =$Q5*(1-0.5*$P5) -> 0.199882 | T5: =SUM(R5:S5) -> 0.200944 | U5: =1-T5 -> 0.799056
A6: 22 | B6: =IF(A6<$D$4,0,IF(A6<$D$5,$E$4,IF(A6<$D$6,$E$5,IF(A6<$D$7,$E$6,IF(A6<$D$8,$E$7,0))))) -> 0.2 | D6: 50 | E6: 0.1 | G6: 22 | H6: =VLOOKUP($G6,Mortality_Table,3,FALSE) -> 0.00123 | I6: =VLOOKUP($G6,Withdrawal_Probs,2,FALSE) -> 0.2 | J6: =$H6*(1-0.5*$I6) -> 0.001107 | K6: =$I6*(1-0.5*$H6) -> 0.199877 | L6: =SUM(J6:K6) -> 0.200984 | M6: =1-L6 -> 0.799016 | O6: 22 | P6: =VLOOKUP($G6,Mortality_Table,2,FALSE) -> 0.00119 | Q6: =VLOOKUP($G6,Withdrawal_Probs,2,FALSE) -> 0.2 | R6: =$P6*(1-0.5*$Q6) -> 0.001071 | S6: =$Q6*(1-0.5*$P6) -> 0.199881 | T6: =SUM(R6:S6) -> 0.200952 | U6: =1-T6 -> 0.799048
A7: 23 | B7: =IF(A7<$D$4,0,IF(A7<$D$5,$E$4,IF(A7<$D$6,$E$5,IF(A7<$D$7,$E$6,IF(A7<$D$8,$E$7,0))))) -> 0.2 | D7: 55 | E7: 0.05 | G7: 23 | H7: =VLOOKUP($G7,Mortality_Table,3,FALSE) -> 0.00124 | I7: =VLOOKUP($G7,Withdrawal_Probs,2,FALSE) -> 0.2 | J7: =$H7*(1-0.5*$I7) -> 0.001116 | K7: =$I7*(1-0.5*$H7) -> 0.199876 | L7: =SUM(J7:K7) -> 0.200992 | M7: =1-L7 -> 0.799008 | O7: 23 | P7: =VLOOKUP($G7,Mortality_Table,2,FALSE) -> 0.0012 | Q7: =VLOOKUP($G7,Withdrawal_Probs,2,FALSE) -> 0.2 | R7: =$P7*(1-0.5*$Q7) -> 0.00108 | S7: =$Q7*(1-0.5*$P7) -> 0.19988 | T7: =SUM(R7:S7) -> 0.20096 | U7: =1-T7 -> 0.79904
A8: 24 | B8: =IF(A8<$D$4,0,IF(A8<$D$5,$E$4,IF(A8<$D$6,$E$5,IF(A8<$D$7,$E$6,IF(A8<$D$8,$E$7,0))))) -> 0.2 | D8: 60 | G8: 24 | H8: =VLOOKUP($G8,Mortality_Table,3,FALSE) -> 0.00126 | I8: =VLOOKUP($G8,Withdrawal_Probs,2,FALSE) -> 0.2 | J8: =$H8*(1-0.5*$I8) -> 0.001134 | K8: =$I8*(1-0.5*$H8) -> 0.199874 | L8: =SUM(J8:K8) -> 0.201008 | M8: =1-L8 -> 0.798992 | O8: 24 | P8: =VLOOKUP($G8,Mortality_Table,2,FALSE) -> 0.00121 | Q8: =VLOOKUP($G8,Withdrawal_Probs,2,FALSE) -> 0.2 | R8: =$P8*(1-0.5*$Q8) -> 0.001089 | S8: =$Q8*(1-0.5*$P8) -> 0.199879 | T8: =SUM(R8:S8) -> 0.200968 | U8: =1-T8 -> 0.799032
A9: 25 | B9: =IF(A9<$D$4,0,IF(A9<$D$5,$E$4,IF(A9<$D$6,$E$5,IF(A9<$D$7,$E$6,IF(A9<$D$8,$E$7,0))))) -> 0.2 | G9: 25 | H9: =VLOOKUP($G9,Mortality_Table,3,FALSE) -> 0.00128 | I9: =VLOOKUP($G9,Withdrawal_Probs,2,FALSE) -> 0.2 | J9: =$H9*(1-0.5*$I9) -> 0.001152 | K9: =$I9*(1-0.5*$H9) -> 0.199872 | L9: =SUM(J9:K9) -> 0.201024 | M9: =1-L9 -> 0.798976 | O9: 25 | P9: =VLOOKUP($G9,Mortality_Table,2,FALSE) -> 0.00123 | Q9: =VLOOKUP($G9,Withdrawal_Probs,2,FALSE) -> 0.2 | R9: =$P9*(1-0.5*$Q9) -> 0.001107 | S9: =$Q9*(1-0.5*$P9) -> 0.199877 | T9: =SUM(R9:S9) -> 0.200984 | U9: =1-T9 -> 0.799016
A10: 26 | B10: =IF(A10<$D$4,0,IF(A10<$D$5,$E$4,IF(A10<$D$6,$E$5,IF(A10<$D$7,$E$6,IF(A10<$D$8,$E$7,0))))) -> 0.2 | G10: 26 | H10: =VLOOKUP($G10,Mortality_Table,3,FALSE) -> 0.00129 | I10: =VLOOKUP($G10,Withdrawal_Probs,2,FALSE) -> 0.2 | J10: =$H10*(1-0.5*$I10) -> 0.001161 | K10: =$I10*(1-0.5*$H10) -> 0.199871 | L10: =SUM(J10:K10) -> 0.201032 | M10: =1-L10 -> 0.798968 | O10: 26 | P10: =VLOOKUP($G10,Mortality_Table,2,FALSE) -> 0.00124 | Q10: =VLOOKUP($G10,Withdrawal_Probs,2,FALSE) -> 0.2 | R10: =$P10*(1-0.5*$Q10) -> 0.001116 | S10: =$Q10*(1-0.5*$P10) -> 0.199876 | T10: =SUM(R10:S10) -> 0.200992 | U10: =1-T10 -> 0.799008
A11: 27 | B11: =IF(A11<$D$4,0,IF(A11<$D$5,$E$4,IF(A11<$D$6,$E$5,IF(A11<$D$7,$E$6,IF(A11<$D$8,$E$7,0))))) -> 0.2 | G11: 27 | H11: =VLOOKUP($G11,Mortality_Table,3,FALSE) -> 0.00131 | I11: =VLOOKUP($G11,Withdrawal_Probs,2,FALSE) -> 0.2 | J11: =$H11*(1-0.5*$I11) -> 0.001179 | K11: =$I11*(1-0.5*$H11) -> 0.199869 | L11: =SUM(J11:K11) -> 0.201048 | M11: =1-L11 -> 0.798952 | O11: 27 | P11: =VLOOKUP($G11,Mortality_Table,2,FALSE) -> 0.00126 | Q11: =VLOOKUP($G11,Withdrawal_Probs,2,FALSE) -> 0.2 | R11: =$P11*(1-0.5*$Q11) -> 0.001134 | S11: =$Q11*(1-0.5*$P11) -> 0.199874 | T11: =SUM(R11:S11) -> 0.201008 | U11: =1-T11 -> 0.798992
A12: 28 | B12: =IF(A12<$D$4,0,IF(A12<$D$5,$E$4,IF(A12<$D$6,$E$5,IF(A12<$D$7,$E$6,IF(A12<$D$8,$E$7,0))))) -> 0.2 | G12: 28 | H12: =VLOOKUP($G12,Mortality_Table,3,FALSE) -> 0.00133 | I12: =VLOOKUP($G12,Withdrawal_Probs,2,FALSE) -> 0.2 | J12: =$H12*(1-0.5*$I12) -> 0.001197 | K12: =$I12*(1-0.5*$H12) -> 0.199867 | L12: =SUM(J12:K12) -> 0.201064 | M12: =1-L12 -> 0.798936 | O12: 28 | P12: =VLOOKUP($G12,Mortality_Table,2,FALSE) -> 0.00128 | Q12: =VLOOKUP($G12,Withdrawal_Probs,2,FALSE) -> 0.2 | R12: =$P12*(1-0.5*$Q12) -> 0.001152 | S12: =$Q12*(1-0.5*$P12) -> 0.199872 | T12: =SUM(R12:S12) -> 0.201024 | U12: =1-T12 -> 0.798976
A13: 29 | B13: =IF(A13<$D$4,0,IF(A13<$D$5,$E$4,IF(A13<$D$6,$E$5,IF(A13<$D$7,$E$6,IF(A13<$D$8,$E$7,0))))) -> 0.2 | G13: 29 | H13: =VLOOKUP($G13,Mortality_Table,3,FALSE) -> 0.00136 | I13: =VLOOKUP($G13,Withdrawal_Probs,2,FALSE) -> 0.2 | J13: =$H13*(1-0.5*$I13) -> 0.001224 | K13: =$I13*(1-0.5*$H13) -> 0.199864 | L13: =SUM(J13:K13) -> 0.201088 | M13: =1-L13 -> 0.798912 | O13: 29 | P13: =VLOOKUP($G13,Mortality_Table,2,FALSE) -> 0.0013 | Q13: =VLOOKUP($G13,Withdrawal_Probs,2,FALSE) -> 0.2 | R13: =$P13*(1-0.5*$Q13) -> 0.00117 | S13: =$Q13*(1-0.5*$P13) -> 0.19987 | T13: =SUM(R13:S13) -> 0.20104 | U13: =1-T13 -> 0.79896
A14: 30 | B14: =IF(A14<$D$4,0,IF(A14<$D$5,$E$4,IF(A14<$D$6,$E$5,IF(A14<$D$7,$E$6,IF(A14<$D$8,$E$7,0))))) -> 0.2 | G14: 30 | H14: =VLOOKUP($G14,Mortality_Table,3,FALSE) -> 0.00139 | I14: =VLOOKUP($G14,Withdrawal_Probs,2,FALSE) -> 0.2 | J14: =$H14*(1-0.5*$I14) -> 0.001251 | K14: =$I14*(1-0.5*$H14) -> 0.199861 | L14: =SUM(J14:K14) -> 0.201112 | M14: =1-L14 -> 0.798888 | O14: 30 | P14: =VLOOKUP($G14,Mortality_Table,2,FALSE) -> 0.00132 | Q14: =VLOOKUP($G14,Withdrawal_Probs,2,FALSE) -> 0.2 | R14: =$P14*(1-0.5*$Q14) -> 0.001188 | S14: =$Q14*(1-0.5*$P14) -> 0.199868 | T14: =SUM(R14:S14) -> 0.201056 | U14: =1-T14 -> 0.798944
A15: 31 | B15: =IF(A15<$D$4,0,IF(A15<$D$5,$E$4,IF(A15<$D$6,$E$5,IF(A15<$D$7,$E$6,IF(A15<$D$8,$E$7,0))))) -> 0.2 | G15: 31 | H15: =VLOOKUP($G15,Mortality_Table,3,FALSE) -> 0.00143 | I15: =VLOOKUP($G15,Withdrawal_Probs,2,FALSE) -> 0.2 | J15: =$H15*(1-0.5*$I15) -> 0.001287 | K15: =$I15*(1-0.5*$H15) -> 0.199857 | L15: =SUM(J15:K15) -> 0.201144 | M15: =1-L15 -> 0.798856 | O15: 31 | P15: =VLOOKUP($G15,Mortality_Table,2,FALSE) -> 0.00135 | Q15: =VLOOKUP($G15,Withdrawal_Probs,2,FALSE) -> 0.2 | R15: =$P15*(1-0.5*$Q15) -> 0.001215 | S15: =$Q15*(1-0.5*$P15) -> 0.199865 | T15: =SUM(R15:S15) -> 0.20108 | U15: =1-T15 -> 0.79892
A16: 32 | B16: =IF(A16<$D$4,0,IF(A16<$D$5,$E$4,IF(A16<$D$6,$E$5,IF(A16<$D$7,$E$6,IF(A16<$D$8,$E$7,0))))) -> 0.2 | G16: 32 | H16: =VLOOKUP($G16,Mortality_Table,3,FALSE) -> 0.00148 | I16: =VLOOKUP($G16,Withdrawal_Probs,2,FALSE) -> 0.2 | J16: =$H16*(1-0.5*$I16) -> 0.001332 | K16: =$I16*(1-0.5*$H16) -> 0.199852 | L16: =SUM(J16:K16) -> 0.201184 | M16: =1-L16 -> 0.798816 | O16: 32 | P16: =VLOOKUP($G16,Mortality_Table,2,FALSE) -> 0.00138 | Q16: =VLOOKUP($G16,Withdrawal_Probs,2,FALSE) -> 0.2 | R16: =$P16*(1-0.5*$Q16) -> 0.001242 | S16: =$Q16*(1-0.5*$P16) -> 0.199862 | T16: =SUM(R16:S16) -> 0.201104 | U16: =1-T16 -> 0.798896
A17: 33 | B17: =IF(A17<$D$4,0,IF(A17<$D$5,$E$4,IF(A17<$D$6,$E$5,IF(A17<$D$7,$E$6,IF(A17<$D$8,$E$7,0))))) -> 0.2 | G17: 33 | H17: =VLOOKUP($G17,Mortality_Table,3,FALSE) -> 0.00153 | I17: =VLOOKUP($G17,Withdrawal_Probs,2,FALSE) -> 0.2 | J17: =$H17*(1-0.5*$I17) -> 0.001377 | K17: =$I17*(1-0.5*$H17) -> 0.199847 | L17: =SUM(J17:K17) -> 0.201224 | M17: =1-L17 -> 0.798776 | O17: 33 | P17: =VLOOKUP($G17,Mortality_Table,2,FALSE) -> 0.00142 | Q17: =VLOOKUP($G17,Withdrawal_Probs,2,FALSE) -> 0.2 | R17: =$P17*(1-0.5*$Q17) -> 0.001278 | S17: =$Q17*(1-0.5*$P17) -> 0.199858 | T17: =SUM(R17:S17) -> 0.201136 | U17: =1-T17 -> 0.798864
A18: 34 | B18: =IF(A18<$D$4,0,IF(A18<$D$5,$E$4,IF(A18<$D$6,$E$5,IF(A18<$D$7,$E$6,IF(A18<$D$8,$E$7,0))))) -> 0.2 | G18: 34 | H18: =VLOOKUP($G18,Mortality_Table,3,FALSE) -> 0.0016 | I18: =VLOOKUP($G18,Withdrawal_Probs,2,FALSE) -> 0.2 | J18: =$H18*(1-0.5*$I18) -> 0.00144 | K18: =$I18*(1-0.5*$H18) -> 0.19984 | L18: =SUM(J18:K18) -> 0.20128 | M18: =1-L18 -> 0.79872 | O18: 34 | P18: =VLOOKUP($G18,Mortality_Table,2,FALSE) -> 0.00147 | Q18: =VLOOKUP($G18,Withdrawal_Probs,2,FALSE) -> 0.2 | R18: =$P18*(1-0.5*$Q18) -> 0.001323 | S18: =$Q18*(1-0.5*$P18) -> 0.199853 | T18: =SUM(R18:S18) -> 0.201176 | U18: =1-T18 -> 0.798824
A19: 35 | B19: =IF(A19<$D$4,0,IF(A19<$D$5,$E$4,IF(A19<$D$6,$E$5,IF(A19<$D$7,$E$6,IF(A19<$D$8,$E$7,0))))) -> 0.2 | G19: 35 | H19: =VLOOKUP($G19,Mortality_Table,3,FALSE) -> 0.00168 | I19: =VLOOKUP($G19,Withdrawal_Probs,2,FALSE) -> 0.2 | J19: =$H19*(1-0.5*$I19) -> 0.001512 | K19: =$I19*(1-0.5*$H19) -> 0.199832 | L19: =SUM(J19:K19) -> 0.201344 | M19: =1-L19 -> 0.798656 | O19: 35 | P19: =VLOOKUP($G19,Mortality_Table,2,FALSE) -> 0.00153 | Q19: =VLOOKUP($G19,Withdrawal_Probs,2,FALSE) -> 0.2 | R19: =$P19*(1-0.5*$Q19) -> 0.001377 | S19: =$Q19*(1-0.5*$P19) -> 0.199847 | T19: =SUM(R19:S19) -> 0.201224 | U19: =1-T19 -> 0.798776
A20: 36 | B20: =IF(A20<$D$4,0,IF(A20<$D$5,$E$4,IF(A20<$D$6,$E$5,IF(A20<$D$7,$E$6,IF(A20<$D$8,$E$7,0))))) -> 0.2 | G20: 36 | H20: =VLOOKUP($G20,Mortality_Table,3,FALSE) -> 0.00177 | I20: =VLOOKUP($G20,Withdrawal_Probs,2,FALSE) -> 0.2 | J20: =$H20*(1-0.5*$I20) -> 0.001593 | K20: =$I20*(1-0.5*$H20) -> 0.199823 | L20: =SUM(J20:K20) -> 0.201416 | M20: =1-L20 -> 0.798584 | O20: 36 | P20: =VLOOKUP($G20,Mortality_Table,2,FALSE) -> 0.00158 | Q20: =VLOOKUP($G20,Withdrawal_Probs,2,FALSE) -> 0.2 | R20: =$P20*(1-0.5*$Q20) -> 0.001422 | S20: =$Q20*(1-0.5*$P20) -> 0.199842 | T20: =SUM(R20:S20) -> 0.201264 | U20: =1-T20 -> 0.798736
... A100: 116 | B100: =IF(A100<$D$4,0,IF(A100<$D$5,$E$4,IF(A100<$D$6,$E$5,IF(A100<$D$7,$E$6,IF(A100<$D$8,$E$7,0))))) -> 0 | G100: 116 | H100: =VLOOKUP($G100,Mortality_Table,3,FALSE) -> 1 | I100: =VLOOKUP($G100,Withdrawal_Probs,2,FALSE) -> 0 | J100: =$H100*(1-0.5*$I100) -> 1 | K100: =$I100*(1-0.5*$H100) -> 0 | L100: =SUM(J100:K100) -> 1 | M100: =1-L100 -> 0 | O100: 116 | P100: =VLOOKUP($G100,Mortality_Table,2,FALSE) -> 1 | Q100: =VLOOKUP($G100,Withdrawal_Probs,2,FALSE) -> 0 | R100: =$P100*(1-0.5*$Q100) -> 1 | S100: =$Q100*(1-0.5*$P100) -> 0 | T100: =SUM(R100:S100) -> 1 | U100: =1-T100 -> 0

Sheet Membership Analysis
A1: Scheme Establishment | B1: ='Scheme Details'!C4 -> 35674 | C1: MALE | D1: =COUNTIF($D$4:$D$950,C1)/COUNTA($D$4:$D$950) -> 0.5 | F1: =0.5*SUMIF(Age,"<35",Fund_Credits)/SUM(Fund_Credits) -> 0.058121574 | I1: =SUMIF(Age,">=50",Fund_Credits)/SUM(Fund_Credits) -> 0.43762519 | J1: =0.5*SUMIF(Age,"<35",Fund_Credits)/SUM(Fund_Credits) -> 0.058121574 | K1: ='Investment Income'!$J$5 -> 714517650 | L1: =K1/L2-1 -> 4.3421432 | Y1: =Y2/SUM(Fund_Credits) -> 0.0053792055 | BS1: =SUM(BS4:BS950) -> 3.1482148e+08 | BT1: =SUM(BT4:BT950) -> 4.4780565e+08 | BU1: =SUM(BU4:BU950) -> 5.1423604e+08 | BV1: =SUM(BV4:BV204) -> 2.2565505e+08 | BW1: =SUM(BW4:BW204) -> 2.4116694e+08 | BX1: =SUM(BX4:BX204) -> 2.4458892e+08 | BY1: =SUM(BY4:BY204) -> 2.3902586e+08 | BZ1: =SUM(BZ4:BZ204) -> 2.4772777e+08 | CA1: =SUM(CA4:CA204) -> 2.4282735e+08 | CB1: =SUM(CB4:CB204) -> 2.4159995e+08 | CC1: =SUM(CC4:CC204) -> 2.4189079e+08 | ... DH1: =SUM(DH4:DH204) -> 0 | DK1: Annuity Ratio | DL1: 0.67 | DM1: =AVERAGE(DN4:DN950) -> 0.066916379 | DN1: =SUMPRODUCT($DJ$4:$DJ$950,$DN$4:$DN$950)/SUMIF($DN$4:$DN$950,">"&0,$DJ$4:$DJ$950) -> 0.09427732 | DP1: =SUM(DP4:DP950)/$L$2 -> 0.31254403 | DQ1: =SUM(DQ4:DQ950)/$L$2 -> 0.43880089 | DR1: =SUM(DR4:DR950)/$L$2 -> 0.50345286
A2: =COUNTA(A4:A950) -> 500 | C2: FEMALE | D2: =COUNTIF($D$4:$D$950,C2)/COUNTA($D$4:$D$950) -> 0.5 | H2: 12 | I2: Fund Credit as at Analysis Date | L2: =SUM(L4:L950) -> 1.3375112e+08 | M2: DATA CHECKS | T2: =AVERAGE(Age) -> 47.262 | W2: =SUMPRODUCT(Years_To_Retirement,Fund_Credits)/SUM(Fund_Credits) -> 12.60523 | X2: =SUM(X4:X950) -> 1.6859637e+09 | Y2: =SUMPRODUCT($Y$4:$Y$950,Fund_Credits) -> 719474.77 | AB2: SALARY PROJECTIONS (ADDITIONAL PENSIONABLE YEARS OF SERVICE) | BS2: PROJECTED FUND CREDITS (ADDITIONAL PENSIONABLE YEARS OF SERVICE) | DJ2: IRR Calcs | DP2: Liquidity Requirement
A3: M/No | B3: Member Name | C3: Membership Status | D3: Gender | E3: Date of Birth | F3: Date of Employment | G3: Date of Joining Scheme | H3: Annual Salary as at Analysis Date | I3: Employee | J3: Employer | K3: AVC | L3: Accumulated Fund Credit as at Analysis Date | M3: Check for Duplicates in ID | N3: Unusual Ages | O3: DOJS>DOB | P3: DOJS after Est | Q3: DOJS after DOE | R3: DOE>DOB | S3: Age at Employment | T3: Age Last Birthday | U3: Age at Joining Scheme | V3: Years in Service | W3: Years To Retirement | X3: FC*YTR | Y3: qx | Z3: ytr(ap)x | AB3: 1 | AC3: 2 | AD3: 3 | AE3: 4 | AF3: 5 | AG3: 6 | AH3: 7 | AI3: 8 | AJ3: 9 | AK3: 10 | AL3: 11 | AM3: 12 | AN3: 13 | AO3: 14 | AP3: 15 | AQ3: 16 | AR3: 17 | AS3: 18 | AT3: 19 | AU3: 20 | AV3: 21 | AW3: 22 | AX3: 23 | AY3: 24 | AZ3: 25 | BA3: 26 | BB3: 27 | BC3: 28 | BD3: 29 | BE3: 30 | BF3: 31 | BG3: 32 | BH3: 33 | BI3: 34 | BJ3: 35 | BK3: 36 | BL3: 37 | BM3: 38 | BN3: 39 | BO3: 40 | BP3: 41 | BQ3: 42 | BS3: 1 | BT3: 2 | BU3: 3 | BV3: 4 | BW3: 5 | BX3: 6 | BY3: 7 | BZ3: 8 | CA3: 9 | CB3: 10 | CC3: 11 | CD3: 12 | CE3: 13 | CF3: 14 | CG3: 15 | CH3: 16 | CI3: 17 | CJ3: 18 | CK3: 19 | CL3: 20 | CM3: 21 | CN3: 22 | CO3: 23 | CP3: 24 | CQ3: 25 | CR3: 26 | CS3: 27 | CT3: 28 | CU3: 29 | CV3: 30 | CW3: 31 | CX3: 32 | CY3: 33 | CZ3: 34 | DA3: 35 | DB3: 36 | DC3: 37 | DD3: 38 | DE3: 39 | DF3: 40 | DG3: 41 | DH3: 42 | DJ3: Expected Fund Credits at Retirement | DK3: Annuity Factor | DL3: Annual Pension | DM3: Annual Salary b4 Retirement | DN3: IRR | DP3: 1 | DQ3: =DP3+1 -> 2 | DR3: =DQ3+1 -> 3
A4: M0001 | B4: Allison Hill | C4: Active | D4: Male | E4: 27372 | F4: 36708 | G4: 37981 | H4: 1453556 | I4: 90476 | J4: 82819.11 | L4: 173295.11 | M4: =IF(COUNTIF($A$4:A204,A4)=1,0,1) -> 0 | N4: =IF(T4<=18,"WHAT!!!",IF(T4>100,"EERM","Okay")) -> Okay | O4: =IF(G4>E4,"TRUE","FALSE") -> TRUE | P4: =G4>=Comm_Date -> TRUE | Q4: =$G4>=$F4 -> TRUE | R4: =$F4>$E4 -> TRUE | S4: =YEARFRAC(E4,F4,3) -> 25.578082 | T4: =ROUNDDOWN(YEARFRAC($E4,Analysis_Date,3),0) -> 50 | U4: =ROUNDDOWN(YEARFRAC($E4,$G4,3),0) -> 29 | V4: =YEARFRAC($G4,Analysis_Date,3) -> 21.027397 | W4: =MAX(ROUNDDOWN(NRA-T4,0),0) -> 10 | X4: =L4*W4 -> 1732951.1 | Y4: =IF($D4=$C$1,VLOOKUP($T4,Mortality_Table,3,FALSE),VLOOKUP($T4,Mortality_Table,2,FALSE)) -> 0.00547 | Z4: =IF($D4=$C$1,VLOOKUP($T4,Male_Annuity_Tables,MATCH($W4+2,'Mortality Tables'!$DS$1:$HT$1,0),FALSE),VLOOKUP($T4,Fe_Annuity_Tables,MATCH($W4+2,'Mortality Tables'!$M$1:$DN$1,0),FALSE)) -> 0.41898499 | AB4: =IFERROR(IF($W4>=AB$3,($H4*(1+Ann_Salary_Growth_Rate)^AB$3),""),0) -> 1527614.7 | AC4: =IFERROR(IF($W4>=AC$3,($H4*(1+Ann_Salary_Growth_Rate)^AC$3),""),0) -> 1605446.6 | AD4: =IFERROR(IF($W4>=AD$3,($H4*(1+Ann_Salary_Growth_Rate)^AD$3),""),0) -> 1687244.2 | AE4: =IFERROR(IF($W4>=AE$3,($H4*(1+Ann_Salary_Growth_Rate)^AE$3),""),0) -> 1773209.2 | AF4: =IFERROR(IF($W4>=AF$3,($H4*(1+Ann_Salary_Growth_Rate)^AF$3),""),0) -> 1863554.3 | AG4: =IFERROR(IF($W4>=AG$3,($H4*(1+Ann_Salary_Growth_Rate)^AG$3),""),0) -> 1958502.3 | AH4: =IFERROR(IF($W4>=AH$3,($H4*(1+Ann_Salary_Growth_Rate)^AH$3),""),0) -> 2058288 | AI4: =IFERROR(IF($W4>=AI$3,($H4*(1+Ann_Salary_Growth_Rate)^AI$3),""),0) -> 2163157.8 | ... BQ4: =IFERROR(IF($W4>=BQ$3,($H4*(1+Ann_Salary_Growth_Rate)^BQ$3),""),0) | BS4: =IFERROR(($L4+AB4*Contr_Rate)*(1+Inv_Return)*IF($D4=$C$1,VLOOKUP($T4,Male_Annuity_Tables,MATCH($BS$3+3,'Mortality Tables'!$N$1:$DN$1,0),FALSE),VLOOKUP($T4,Fe_Annuity_Tables,MATCH(BS$3+3,'Mortality Tables'!$N$1:$DN$1,0),FALSE)),"") -> 580939.97 | BT4: =IFERROR(($BS4+AC4*Contr_Rate)*(1+Inv_Return)*IF($D4=$C$1,VLOOKUP($T4,Male_Annuity_Tables,MATCH($BS$3+3,'Mortality Tables'!$N$1:$DN$1,0),FALSE),VLOOKUP($T4,Fe_Annuity_Tables,MATCH(BT$3+3,'Mortality Tables'!$N$1:$DN$1,0),FALSE)),"") -> 977377.63 | BU4: =IFERROR((BT4+AD4*Contr_Rate)*(1+Inv_Return)*IF($D4=$C$1,VLOOKUP($T4,Male_Annuity_Tables,MATCH($BS$3+3,'Mortality Tables'!$N$1:$DN$1,0),FALSE),VLOOKUP($T4,Fe_Annuity_Tables,MATCH(BU$3+3,'Mortality Tables'!$N$1:$DN$1,0),FALSE)),"") -> 1364601 | BV4: =IFERROR((BU4+AE4*Contr_Rate)*(1+Inv_Return)*IF($D4=$C$1,VLOOKUP($T4,Male_Annuity_Tables,MATCH($BS$3+3,'Mortality Tables'!$N$1:$DN$1,0),FALSE),VLOOKUP($T4,Fe_Annuity_Tables,MATCH(BV$3+3,'Mortality Tables'!$N$1:$DN$1,0),FALSE)),"") -> 1744498.8 | BW4: =IFERROR((BV4+AF4*Contr_Rate)*(1+Inv_Return)*IF($D4=$C$1,VLOOKUP($T4,Male_Annuity_Tables,MATCH($BS$3+3,'Mortality Tables'!$N$1:$DN$1,0),FALSE),VLOOKUP($T4,Fe_Annuity_Tables,MATCH(BW$3+3,'Mortality Tables'!$N$1:$DN$1,0),FALSE)),"") -> 2118867 | BX4: =IFERROR((BW4+AG4*Contr_Rate)*(1+Inv_Return)*IF($D4=$C$1,VLOOKUP($T4,Male_Annuity_Tables,MATCH($BS$3+3,'Mortality Tables'!$N$1:$DN$1,0),FALSE),VLOOKUP($T4,Fe_Annuity_Tables,MATCH(BX$3+3,'Mortality Tables'!$N$1:$DN$1,0),FALSE)),"") -> 2489419.3 | BY4: =IFERROR((BX4+AH4*Contr_Rate)*(1+Inv_Return)*IF($D4=$C$1,VLOOKUP($T4,Male_Annuity_Tables,MATCH($BS$3+3,'Mortality Tables'!$N$1:$DN$1,0),FALSE),VLOOKUP($T4,Fe_Annuity_Tables,MATCH(BY$3+3,'Mortality Tables'!$N$1:$DN$1,0),FALSE)),"") -> 2857796.5 | BZ4: =IFERROR((BY4+AI4*Contr_Rate)*(1+Inv_Return)*IF($D4=$C$1,VLOOKUP($T4,Male_Annuity_Tables,MATCH($BS$3+3,'Mortality Tables'!$N$1:$DN$1,0),FALSE),VLOOKUP($T4,Fe_Annuity_Tables,MATCH(BZ$3+3,'Mortality Tables'!$N$1:$DN$1,0),FALSE)),"") -> 3225575.9 | CA4: =IFERROR((BZ4+AJ4*Contr_Rate)*(1+Inv_Return)*IF($D4=$C$1,VLOOKUP($T4,Male_Annuity_Tables,MATCH($BS$3+3,'Mortality Tables'!$N$1:$DN$1,0),FALSE),VLOOKUP($T4,Fe_Annuity_Tables,MATCH(CA$3+3,'Mortality Tables'!$N$1:$DN$1,0),FALSE)),"") -> 3594279.9 | CB4: =IFERROR((CA4+AK4*Contr_Rate)*(1+Inv_Return)*IF($D4=$C$1,VLOOKUP($T4,Male_Annuity_Tables,MATCH($BS$3+3,'Mortality Tables'!$N$1:$DN$1,0),FALSE),VLOOKUP($T4,Fe_Annuity_Tables,MATCH(CB$3+3,'Mortality Tables'!$N$1:$DN$1,0),FALSE)),"") -> 3965383.9 | ... DH4: =IFERROR((DG4+BQ4*Contr_Rate)*(1+Inv_Return)*IF($D4=$C$1,VLOOKUP($T4,Male_Annuity_Tables,MATCH($BS$3+3,'Mortality Tables'!$N$1:$DN$1,0),FALSE),VLOOKUP($T4,Fe_Annuity_Tables,MATCH(DH$3+3,'Mortality Tables'!$N$1:$DN$1,0),FALSE)),"") | DJ4: =MAX(BS4:DH4) -> 3965383.9 | DK4: =IF($D4="FEMALE",Fe_Annuity_Factor,Male_Annuity_Factor) -> 8.0909278 | DL4: =(DJ4*Annuity_Ratio)/DK4 -> 328368.67 | DM4: =MAX($AB4:$BQ4) -> 2389198.9 | DN4: =IFERROR((DL4/DM4),"") -> 0.13743882 | DP4: =IFERROR(IF($D4=$C$1,VLOOKUP($T4+DP$3-1,Male_Annuity_Tables,2,FALSE),VLOOKUP($T4,Fe_Annuity_Tables,2,FALSE))*BS4,"") -> 60953.965 | DQ4: =IFERROR(IF($D4=$C$1,VLOOKUP($T4+DQ$3-1,Male_Annuity_Tables,2,FALSE),VLOOKUP($T4,Fe_Annuity_Tables,2,FALSE))*BT4,"") -> 103015.6 | DR4: =IFERROR(IF($D4=$C$1,VLOOKUP($T4+DR$3-1,Male_Annuity_Tables,2,FALSE),VLOOKUP($T4,Fe_Annuity_Tables,2,FALSE))*BU4,"") -> 144553.54
A5: M0002 | B5: Stephanie Miller | C5: Active | D5: Female | E5: 25736 | F5: 35368 | G5: 35738 | H5: 433306 | I5: 22310.87 | J5: 26402.16 | K5: 6194.12 | L5: 54907.15 | M5: =IF(COUNTIF($A$4:A204,A5)=1,0,1) -> 0 | N5: =IF(T5<=18,"WHAT!!!",IF(T5>100,"EERM","Okay")) -> Okay | O5: =IF(G5>E5,"TRUE","FALSE") -> TRUE | P5: =G5>=Comm_Date -> TRUE | Q5: =$G5>=$F5 -> TRUE | R5: =$F5>$E5 -> TRUE | S5: =YEARFRAC(E5,F5,3) -> 26.389041 | T5: =ROUNDDOWN(YEARFRAC($E5,Analysis_Date,3),0) -> 54 | U5: =ROUNDDOWN(YEARFRAC($E5,$G5,3),0) -> 27 | V5: =YEARFRAC($G5,Analysis_Date,3) -> 27.172603 | W5: =MAX(ROUNDDOWN(NRA-T5,0),0) -> 6 | X5: =L5*W5 -> 329442.9 | Y5: =IF($D5=$C$1,VLOOKUP($T5,Mortality_Table,3,FALSE),VLOOKUP($T5,Mortality_Table,2,FALSE)) -> 0.0051 | Z5: =IF($D5=$C$1,VLOOKUP($T5,Male_Annuity_Tables,MATCH($W5+2,'Mortality Tables'!$DS$1:$HT$1,0),FALSE),VLOOKUP($T5,Fe_Annuity_Tables,MATCH($W5+2,'Mortality Tables'!$M$1:$DN$1,0),FALSE)) -> 0.67029933 | AB5: =IFERROR(IF($W5>=AB$3,($H5*(1+Ann_Salary_Growth_Rate)^AB$3),""),0) -> 455382.94 | AC5: =IFERROR(IF($W5>=AC$3,($H5*(1+Ann_Salary_Growth_Rate)^AC$3),""),0) -> 478584.7 | AD5: =IFERROR(IF($W5>=AD$3,($H5*(1+Ann_Salary_Growth_Rate)^AD$3),""),0) -> 502968.59 | AE5: =IFERROR(IF($W5>=AE$3,($H5*(1+Ann_Salary_Growth_Rate)^AE$3),""),0) -> 528594.84 | AF5: =IFERROR(IF($W5>=AF$3,($H5*(1+Ann_Salary_Growth_Rate)^AF$3),""),0) -> 555526.75 | AG5: =IFERROR(IF($W5>=AG$3,($H5*(1+Ann_Salary_Growth_Rate)^AG$3),""),0) -> 583830.84 | AH5: =IFERROR(IF($W5>=AH$3,($H5*(1+Ann_Salary_Growth_Rate)^AH$3),""),0) | AI5: =IFERROR(IF($W5>=AI$3,($H5*(1+Ann_Salary_Growth_Rate)^AI$3),""),0) | ... BQ5: =IFERROR(IF($W5>=BQ$3,($H5*(1+Ann_Salary_Growth_Rate)^BQ$3),""),0) | BS5: =IFERROR(($L5+AB5*Contr_Rate)*(1+Inv_Return)*IF($D5=$C$1,VLOOKUP($T5,Male_Annuity_Tables,MATCH($BS$3+3,'Mortality Tables'!$N$1:$DN$1,0),FALSE),VLOOKUP($T5,Fe_Annuity_Tables,MATCH(BS$3+3,'Mortality Tables'!$N$1:$DN$1,0),FALSE)),"") -> 176231.49 | BT5: =IFERROR(($BS5+AC5*Contr_Rate)*(1+Inv_Return)*IF($D5=$C$1,VLOOKUP($T5,Male_Annuity_Tables,MATCH($BS$3+3,'Mortality Tables'!$N$1:$DN$1,0),FALSE),VLOOKUP($T5,Fe_Annuity_Tables,MATCH(BT$3+3,'Mortality Tables'!$N$1:$DN$1,0),FALSE)),"") -> 278014.78 | BU5: =IFERROR((BT5+AD5*Contr_Rate)*(1+Inv_Return)*IF($D5=$C$1,VLOOKUP($T5,Male_Annuity_Tables,MATCH($BS$3+3,'Mortality Tables'!$N$1:$DN$1,0),FALSE),VLOOKUP($T5,Fe_Annuity_Tables,MATCH(BU$3+3,'Mortality Tables'!$N$1:$DN$1,0),FALSE)),"") -> 352088.24 | BV5: =IFERROR((BU5+AE5*Contr_Rate)*(1+Inv_Return)*IF($D5=$C$1,VLOOKUP($T5,Male_Annuity_Tables,MATCH($BS$3+3,'Mortality Tables'!$N$1:$DN$1,0),FALSE),VLOOKUP($T5,Fe_Annuity_Tables,MATCH(BV$3+3,'Mortality Tables'!$N$1:$DN$1,0),FALSE)),"") -> 395645.24 | BW5: =IFERROR((BV5+AF5*Contr_Rate)*(1+Inv_Return)*IF($D5=$C$1,VLOOKUP($T5,Male_Annuity_Tables,MATCH($BS$3+3,'Mortality Tables'!$N$1:$DN$1,0),FALSE),VLOOKUP($T5,Fe_Annuity_Tables,MATCH(BW$3+3,'Mortality Tables'!$N$1:$DN$1,0),FALSE)),"") -> 410917.85 | BX5: =IFERROR((BW5+AG5*Contr_Rate)*(1+Inv_Return)*IF($D5=$C$1,VLOOKUP($T5,Male_Annuity_Tables,MATCH($BS$3+3,'Mortality Tables'!$N$1:$DN$1,0),FALSE),VLOOKUP($T5,Fe_Annuity_Tables,MATCH(BX$3+3,'Mortality Tables'!$N$1:$DN$1,0),FALSE)),"") -> 403700.19 | BY5: =IFERROR((BX5+AH5*Contr_Rate)*(1+Inv_Return)*IF($D5=$C$1,VLOOKUP($T5,Male_Annuity_Tables,MATCH($BS$3+3,'Mortality Tables'!$N$1:$DN$1,0),FALSE),VLOOKUP($T5,Fe_Annuity_Tables,MATCH(BY$3+3,'Mortality Tables'!$N$1:$DN$1,0),FALSE)),"") | BZ5: =IFERROR((BY5+AI5*Contr_Rate)*(1+Inv_Return)*IF($D5=$C$1,VLOOKUP($T5,Male_Annuity_Tables,MATCH($BS$3+3,'Mortality Tables'!$N$1:$DN$1,0),FALSE),VLOOKUP($T5,Fe_Annuity_Tables,MATCH(BZ$3+3,'Mortality Tables'!$N$1:$DN$1,0),FALSE)),"") | CA5: =IFERROR((BZ5+AJ5*Contr_Rate)*(1+Inv_Return)*IF($D5=$C$1,VLOOKUP($T5,Male_Annuity_Tables,MATCH($BS$3+3,'Mortality Tables'!$N$1:$DN$1,0),FALSE),VLOOKUP($T5,Fe_Annuity_Tables,MATCH(CA$3+3,'Mortality Tables'!$N$1:$DN$1,0),FALSE)),"") | CB5: =IFERROR((CA5+AK5*Contr_Rate)*(1+Inv_Return)*IF($D5=$C$1,VLOOKUP($T5,Male_Annuity_Tables,MATCH($BS$3+3,'Mortality Tables'!$N$1:$DN$1,0),FALSE),VLOOKUP($T5,Fe_Annuity_Tables,MATCH(CB$3+3,'Mortality Tables'!$N$1:$DN$1,0),FALSE)),"") | ... DH5: =IFERROR((DG5+BQ5*Contr_Rate)*(1+Inv_Return)*IF($D5=$C$1,VLOOKUP($T5,Male_Annuity_Tables,MATCH($BS$3+3,'Mortality Tables'!$N$1:$DN$1,0),FALSE),VLOOKUP($T5,Fe_Annuity_Tables,MATCH(DH$3+3,'Mortality Tables'!$N$1:$DN$1,0),FALSE)),"") | DJ5: =MAX(BS5:DH5) -> 410917.85 | DK5: =IF($D5="FEMALE",Fe_Annuity_Factor,Male_Annuity_Factor) -> 8.8017766 | DL5: =(DJ5*Annuity_Ratio)/DK5 -> 31279.476 | DM5: =MAX($AB5:$BQ5) -> 583830.84 | DN5: =IFERROR((DL5/DM5),"") -> 0.053576266 | DP5: =IFERROR(IF($D5=$C$1,VLOOKUP($T5+DP$3-1,Male_Annuity_Tables,2,FALSE),VLOOKUP($T5,Fe_Annuity_Tables,2,FALSE))*BS5,"") -> 18432.051 | DQ5: =IFERROR(IF($D5=$C$1,VLOOKUP($T5+DQ$3-1,Male_Annuity_Tables,2,FALSE),VLOOKUP($T5,Fe_Annuity_Tables,2,FALSE))*BT5,"") -> 29077.566 | DR5: =IFERROR(IF($D5=$C$1,VLOOKUP($T5+DR$3-1,Male_Annuity_Tables,2,FALSE),VLOOKUP($T5,Fe_Annuity_Tables,2,FALSE))*BU5,"") -> 36824.909
A6: M0003 | B6: David Guzman | C6: Deferred | D6: Female | E6: 29199 | F6: 37445 | G6: 45521 | H6: 1224594 | I6: 88734.64 | J6: 78263.23 | K6: 39146.33 | L6: 206144.2 | M6: =IF(COUNTIF($A$4:A204,A6)=1,0,1) -> 0 | N6: =IF(T6<=18,"WHAT!!!",IF(T6>100,"EERM","Okay")) -> Okay | O6: =IF(G6>E6,"TRUE","FALSE") -> TRUE | P6: =G6>=Comm_Date -> TRUE | Q6: =$G6>=$F6 -> TRUE | R6: =$F6>$E6 -> TRUE | S6: =YEARFRAC(E6,F6,3) -> 22.591781 | T6: =ROUNDDOWN(YEARFRAC($E6,Analysis_Date,3),0) -> 45 | U6: =ROUNDDOWN(YEARFRAC($E6,$G6,3),0) -> 44 | V6: =YEARFRAC($G6,Analysis_Date,3) -> 0.36986301 | W6: =MAX(ROUNDDOWN(NRA-T6,0),0) -> 15 | X6: =L6*W6 -> 3092163 | Y6: =IF($D6=$C$1,VLOOKUP($T6,Mortality_Table,3,FALSE),VLOOKUP($T6,Mortality_Table,2,FALSE)) -> 0.00261 | Z6: =IF($D6=$C$1,VLOOKUP($T6,Male_Annuity_Tables,MATCH($W6+2,'Mortality Tables'!$DS$1:$HT$1,0),FALSE),VLOOKUP($T6,Fe_Annuity_Tables,MATCH($W6+2,'Mortality Tables'!$M$1:$DN$1,0),FALSE)) -> 0.18896813 | AB6: =IFERROR(IF($W6>=AB$3,($H6*(1+Ann_Salary_Growth_Rate)^AB$3),""),0) -> 1286987.1 | AC6: =IFERROR(IF($W6>=AC$3,($H6*(1+Ann_Salary_Growth_Rate)^AC$3),""),0) -> 1352559.1 | AD6: =IFERROR(IF($W6>=AD$3,($H6*(1+Ann_Salary_Growth_Rate)^AD$3),""),0) -> 1421471.9 | AE6: =IFERROR(IF($W6>=AE$3,($H6*(1+Ann_Salary_Growth_Rate)^AE$3),""),0) -> 1493895.9 | AF6: =IFERROR(IF($W6>=AF$3,($H6*(1+Ann_Salary_Growth_Rate)^AF$3),""),0) -> 1570009.9 | AG6: =IFERROR(IF($W6>=AG$3,($H6*(1+Ann_Salary_Growth_Rate)^AG$3),""),0) -> 1650001.9 | AH6: =IFERROR(IF($W6>=AH$3,($H6*(1+Ann_Salary_Growth_Rate)^AH$3),""),0) -> 1734069.5 | AI6: =IFERROR(IF($W6>=AI$3,($H6*(1+Ann_Salary_Growth_Rate)^AI$3),""),0) -> 1822420.4 | ... BQ6: =IFERROR(IF($W6>=BQ$3,($H6*(1+Ann_Salary_Growth_Rate)^BQ$3),""),0) | BS6: =IFERROR(($L6+AB6*Contr_Rate)*(1+Inv_Return)*IF($D6=$C$1,VLOOKUP($T6,Male_Annuity_Tables,MATCH($BS$3+3,'Mortality Tables'!$N$1:$DN$1,0),FALSE),VLOOKUP($T6,Fe_Annuity_Tables,MATCH(BS$3+3,'Mortality Tables'!$N$1:$DN$1,0),FALSE)),"") -> 515970.34 | BT6: =IFERROR(($BS6+AC6*Contr_Rate)*(1+Inv_Return)*IF($D6=$C$1,VLOOKUP($T6,Male_Annuity_Tables,MATCH($BS$3+3,'Mortality Tables'!$N$1:$DN$1,0),FALSE),VLOOKUP($T6,Fe_Annuity_Tables,MATCH(BT$3+3,'Mortality Tables'!$N$1:$DN$1,0),FALSE)),"") -> 680668.22 | BU6: =IFERROR((BT6+AD6*Contr_Rate)*(1+Inv_Return)*IF($D6=$C$1,VLOOKUP($T6,Male_Annuity_Tables,MATCH($BS$3+3,'Mortality Tables'!$N$1:$DN$1,0),FALSE),VLOOKUP($T6,Fe_Annuity_Tables,MATCH(BU$3+3,'Mortality Tables'!$N$1:$DN$1,0),FALSE)),"") -> 692825.76 | BV6: =IFERROR((BU6+AE6*Contr_Rate)*(1+Inv_Return)*IF($D6=$C$1,VLOOKUP($T6,Male_Annuity_Tables,MATCH($BS$3+3,'Mortality Tables'!$N$1:$DN$1,0),FALSE),VLOOKUP($T6,Fe_Annuity_Tables,MATCH(BV$3+3,'Mortality Tables'!$N$1:$DN$1,0),FALSE)),"") -> 604959.67 | BW6: =IFERROR((BV6+AF6*Contr_Rate)*(1+Inv_Return)*IF($D6=$C$1,VLOOKUP($T6,Male_Annuity_Tables,MATCH($BS$3+3,'Mortality Tables'!$N$1:$DN$1,0),FALSE),VLOOKUP($T6,Fe_Annuity_Tables,MATCH(BW$3+3,'Mortality Tables'!$N$1:$DN$1,0),FALSE)),"") -> 483220.11 | BX6: =IFERROR((BW6+AG6*Contr_Rate)*(1+Inv_Return)*IF($D6=$C$1,VLOOKUP($T6,Male_Annuity_Tables,MATCH($BS$3+3,'Mortality Tables'!$N$1:$DN$1,0),FALSE),VLOOKUP($T6,Fe_Annuity_Tables,MATCH(BX$3+3,'Mortality Tables'!$N$1:$DN$1,0),FALSE)),"") -> 393904.67 | BY6: =IFERROR((BX6+AH6*Contr_Rate)*(1+Inv_Return)*IF($D6=$C$1,VLOOKUP($T6,Male_Annuity_Tables,MATCH($BS$3+3,'Mortality Tables'!$N$1:$DN$1,0),FALSE),VLOOKUP($T6,Fe_Annuity_Tables,MATCH(BY$3+3,'Mortality Tables'!$N$1:$DN$1,0),FALSE)),"") -> 329943.95 | BZ6: =IFERROR((BY6+AI6*Contr_Rate)*(1+Inv_Return)*IF($D6=$C$1,VLOOKUP($T6,Male_Annuity_Tables,MATCH($BS$3+3,'Mortality Tables'!$N$1:$DN$1,0),FALSE),VLOOKUP($T6,Fe_Annuity_Tables,MATCH(BZ$3+3,'Mortality Tables'!$N$1:$DN$1,0),FALSE)),"") -> 283537.82 | CA6: =IFERROR((BZ6+AJ6*Contr_Rate)*(1+Inv_Return)*IF($D6=$C$1,VLOOKUP($T6,Male_Annuity_Tables,MATCH($BS$3+3,'Mortality Tables'!$N$1:$DN$1,0),FALSE),VLOOKUP($T6,Fe_Annuity_Tables,MATCH(CA$3+3,'Mortality Tables'!$N$1:$DN$1,0),FALSE)),"") -> 248605.33 | CB6: =IFERROR((CA6+AK6*Contr_Rate)*(1+Inv_Return)*IF($D6=$C$1,VLOOKUP($T6,Male_Annuity_Tables,MATCH($BS$3+3,'Mortality Tables'!$N$1:$DN$1,0),FALSE),VLOOKUP($T6,Fe_Annuity_Tables,MATCH(CB$3+3,'Mortality Tables'!$N$1:$DN$1,0),FALSE)),"") -> 221136.08 | ... DH6: =IFERROR((DG6+BQ6*Contr_Rate)*(1+Inv_Return)*IF($D6=$C$1,VLOOKUP($T6,Male_Annuity_Tables,MATCH($BS$3+3,'Mortality Tables'!$N$1:$DN$1,0),FALSE),VLOOKUP($T6,Fe_Annuity_Tables,MATCH(DH$3+3,'Mortality Tables'!$N$1:$DN$1,0),FALSE)),"") | DJ6: =MAX(BS6:DH6) -> 692825.76 | DK6: =IF($D6="FEMALE",Fe_Annuity_Factor,Male_Annuity_Factor) -> 8.8017766 | DL6: =(DJ6*Annuity_Ratio)/DK6 -> 52738.587 | DM6: =MAX($AB6:$BQ6) -> 2580613.4 | DN6: =IFERROR((DL6/DM6),"") -> 0.020436454 | DP6: =IFERROR(IF($D6=$C$1,VLOOKUP($T6+DP$3-1,Male_Annuity_Tables,2,FALSE),VLOOKUP($T6,Fe_Annuity_Tables,2,FALSE))*BS6,"") -> 78540.231 | DQ6: =IFERROR(IF($D6=$C$1,VLOOKUP($T6+DQ$3-1,Male_Annuity_Tables,2,FALSE),VLOOKUP($T6,Fe_Annuity_Tables,2,FALSE))*BT6,"") -> 103610.3 | DR6: =IFERROR(IF($D6=$C$1,VLOOKUP($T6+DR$3-1,Male_Annuity_Tables,2,FALSE),VLOOKUP($T6,Fe_Annuity_Tables,2,FALSE))*BU6,"") -> 105460.9
A7: M0004 | B7: Jennifer Cole | C7: Deferred | D7: Female | E7: 28739 | F7: 45033 | G7: 45038 | H7: 1727114 | I7: 110351.47 | J7: 104949.27 | K7: 9599.46 | L7: 224900.2 | M7: =IF(COUNTIF($A$4:A204,A7)=1,0,1) -> 0 | N7: =IF(T7<=18,"WHAT!!!",IF(T7>100,"EERM","Okay")) -> Okay | O7: =IF(G7>E7,"TRUE","FALSE") -> TRUE | P7: =G7>=Comm_Date -> TRUE | Q7: =$G7>=$F7 -> TRUE | R7: =$F7>$E7 -> TRUE | S7: =YEARFRAC(E7,F7,3) -> 44.641096 | T7: =ROUNDDOWN(YEARFRAC($E7,Analysis_Date,3),0) -> 46 | U7: =ROUNDDOWN(YEARFRAC($E7,$G7,3),0) -> 44 | V7: =YEARFRAC($G7,Analysis_Date,3) -> 1.6931507 | W7: =MAX(ROUNDDOWN(NRA-T7,0),0) -> 14 | X7: =L7*W7 -> 3148602.8 | Y7: =IF($D7=$C$1,VLOOKUP($T7,Mortality_Table,3,FALSE),VLOOKUP($T7,Mortality_Table,2,FALSE)) -> 0.0028 | Z7: =IF($D7=$C$1,VLOOKUP($T7,Male_Annuity_Tables,MATCH($W7+2,'Mortality Tables'!$DS$1:$HT$1,0),FALSE),VLOOKUP($T7,Fe_Annuity_Tables,MATCH($W7+2,'Mortality Tables'!$M$1:$DN$1,0),FALSE)) -> 0.2228972 | AB7: =IFERROR(IF($W7>=AB$3,($H7*(1+Ann_Salary_Growth_Rate)^AB$3),""),0) -> 1815110.5 | AC7: =IFERROR(IF($W7>=AC$3,($H7*(1+Ann_Salary_Growth_Rate)^AC$3),""),0) -> 1907590.3 | AD7: =IFERROR(IF($W7>=AD$3,($H7*(1+Ann_Salary_Growth_Rate)^AD$3),""),0) -> 2004782.1 | AE7: =IFERROR(IF($W7>=AE$3,($H7*(1+Ann_Salary_Growth_Rate)^AE$3),""),0) -> 2106925.7 | AF7: =IFERROR(IF($W7>=AF$3,($H7*(1+Ann_Salary_Growth_Rate)^AF$3),""),0) -> 2214273.6 | AG7: =IFERROR(IF($W7>=AG$3,($H7*(1+Ann_Salary_Growth_Rate)^AG$3),""),0) -> 2327090.8 | AH7: =IFERROR(IF($W7>=AH$3,($H7*(1+Ann_Salary_Growth_Rate)^AH$3),""),0) -> 2445656.1 | AI7: =IFERROR(IF($W7>=AI$3,($H7*(1+Ann_Salary_Growth_Rate)^AI$3),""),0) -> 2570262.3 | ... BQ7: =IFERROR(IF($W7>=BQ$3,($H7*(1+Ann_Salary_Growth_Rate)^BQ$3),""),0) | BS7: =IFERROR(($L7+AB7*Contr_Rate)*(1+Inv_Return)*IF($D7=$C$1,VLOOKUP($T7,Male_Annuity_Tables,MATCH($BS$3+3,'Mortality Tables'!$N$1:$DN$1,0),FALSE),VLOOKUP($T7,Fe_Annuity_Tables,MATCH(BS$3+3,'Mortality Tables'!$N$1:$DN$1,0),FALSE)),"") -> 670216.36 | BT7: =IFERROR(($BS7+AC7*Contr_Rate)*(1+Inv_Return)*IF($D7=$C$1,VLOOKUP($T7,Male_Annuity_Tables,MATCH($BS$3+3,'Mortality Tables'!$N$1:$DN$1,0),FALSE),VLOOKUP($T7,Fe_Annuity_Tables,MATCH(BT$3+3,'Mortality Tables'!$N$1:$DN$1,0),FALSE)),"") -> 917156.62 | BU7: =IFERROR((BT7+AD7*Contr_Rate)*(1+Inv_Return)*IF($D7=$C$1,VLOOKUP($T7,Male_Annuity_Tables,MATCH($BS$3+3,'Mortality Tables'!$N$1:$DN$1,0),FALSE),VLOOKUP($T7,Fe_Annuity_Tables,MATCH(BU$3+3,'Mortality Tables'!$N$1:$DN$1,0),FALSE)),"") -> 949729.25 | BV7: =IFERROR((BU7+AE7*Contr_Rate)*(1+Inv_Return)*IF($D7=$C$1,VLOOKUP($T7,Male_Annuity_Tables,MATCH($BS$3+3,'Mortality Tables'!$N$1:$DN$1,0),FALSE),VLOOKUP($T7,Fe_Annuity_Tables,MATCH(BV$3+3,'Mortality Tables'!$N$1:$DN$1,0),FALSE)),"") -> 837948.54 | BW7: =IFERROR((BV7+AF7*Contr_Rate)*(1+Inv_Return)*IF($D7=$C$1,VLOOKUP($T7,Male_Annuity_Tables,MATCH($BS$3+3,'Mortality Tables'!$N$1:$DN$1,0),FALSE),VLOOKUP($T7,Fe_Annuity_Tables,MATCH(BW$3+3,'Mortality Tables'!$N$1:$DN$1,0),FALSE)),"") -> 713521.33 | BX7: =IFERROR((BW7+AG7*Contr_Rate)*(1+Inv_Return)*IF($D7=$C$1,VLOOKUP($T7,Male_Annuity_Tables,MATCH($BS$3+3,'Mortality Tables'!$N$1:$DN$1,0),FALSE),VLOOKUP($T7,Fe_Annuity_Tables,MATCH(BX$3+3,'Mortality Tables'!$N$1:$DN$1,0),FALSE)),"") -> 601003.49 | BY7: =IFERROR((BX7+AH7*Contr_Rate)*(1+Inv_Return)*IF($D7=$C$1,VLOOKUP($T7,Male_Annuity_Tables,MATCH($BS$3+3,'Mortality Tables'!$N$1:$DN$1,0),FALSE),VLOOKUP($T7,Fe_Annuity_Tables,MATCH(BY$3+3,'Mortality Tables'!$N$1:$DN$1,0),FALSE)),"") -> 509183.88 | BZ7: =IFERROR((BY7+AI7*Contr_Rate)*(1+Inv_Return)*IF($D7=$C$1,VLOOKUP($T7,Male_Annuity_Tables,MATCH($BS$3+3,'Mortality Tables'!$N$1:$DN$1,0),FALSE),VLOOKUP($T7,Fe_Annuity_Tables,MATCH(BZ$3+3,'Mortality Tables'!$N$1:$DN$1,0),FALSE)),"") -> 437499.65 | CA7: =IFERROR((BZ7+AJ7*Contr_Rate)*(1+Inv_Return)*IF($D7=$C$1,VLOOKUP($T7,Male_Annuity_Tables,MATCH($BS$3+3,'Mortality Tables'!$N$1:$DN$1,0),FALSE),VLOOKUP($T7,Fe_Annuity_Tables,MATCH(CA$3+3,'Mortality Tables'!$N$1:$DN$1,0),FALSE)),"") -> 381828.32 | CB7: =IFERROR((CA7+AK7*Contr_Rate)*(1+Inv_Return)*IF($D7=$C$1,VLOOKUP($T7,Male_Annuity_Tables,MATCH($BS$3+3,'Mortality Tables'!$N$1:$DN$1,0),FALSE),VLOOKUP($T7,Fe_Annuity_Tables,MATCH(CB$3+3,'Mortality Tables'!$N$1:$DN$1,0),FALSE)),"") -> 356573.09 | ... DH7: =IFERROR((DG7+BQ7*Contr_Rate)*(1+Inv_Return)*IF($D7=$C$1,VLOOKUP($T7,Male_Annuity_Tables,MATCH($BS$3+3,'Mortality Tables'!$N$1:$DN$1,0),FALSE),VLOOKUP($T7,Fe_Annuity_Tables,MATCH(DH$3+3,'Mortality Tables'!$N$1:$DN$1,0),FALSE)),"") | DJ7: =MAX(BS7:DH7) -> 949729.25 | DK7: =IF($D7="FEMALE",Fe_Annuity_Factor,Male_Annuity_Factor) -> 8.8017766 | DL7: =(DJ7*Annuity_Ratio)/DK7 -> 72294.336 | DM7: =MAX($AB7:$BQ7) -> 3463137.8 | DN7: =IFERROR((DL7/DM7),"") -> 0.020875386 | DP7: =IFERROR(IF($D7=$C$1,VLOOKUP($T7+DP$3-1,Male_Annuity_Tables,2,FALSE),VLOOKUP($T7,Fe_Annuity_Tables,2,FALSE))*BS7,"") -> 102127.57 | DQ7: =IFERROR(IF($D7=$C$1,VLOOKUP($T7+DQ$3-1,Male_Annuity_Tables,2,FALSE),VLOOKUP($T7,Fe_Annuity_Tables,2,FALSE))*BT7,"") -> 139756.33 | DR7: =IFERROR(IF($D7=$C$1,VLOOKUP($T7+DR$3-1,Male_Annuity_Tables,2,FALSE),VLOOKUP($T7,Fe_Annuity_Tables,2,FALSE))*BU7,"") -> 144719.74
A8: M0005 | B8: Caitlin Henderson | C8: Exited | D8: Male | E8: 28731 | F8: 36906 | G8: 39581 | H8: 1805668 | I8: 166798.07 | J8: 144789.84 | K8: 37837.93 | L8: 349425.84 | M8: =IF(COUNTIF($A$4:A204,A8)=1,0,1) -> 0 | N8: =IF(T8<=18,"WHAT!!!",IF(T8>100,"EERM","Okay")) -> Okay | O8: =IF(G8>E8,"TRUE","FALSE") -> TRUE | P8: =G8>=Comm_Date -> TRUE | Q8: =$G8>=$F8 -> TRUE | R8: =$F8>$E8 -> TRUE | S8: =YEARFRAC(E8,F8,3) -> 22.39726 | T8: =ROUNDDOWN(YEARFRAC($E8,Analysis_Date,3),0) -> 46 | U8: =ROUNDDOWN(YEARFRAC($E8,$G8,3),0) -> 29 | V8: =YEARFRAC($G8,Analysis_Date,3) -> 16.643836 | W8: =MAX(ROUNDDOWN(NRA-T8,0),0) -> 14 | X8: =L8*W8 -> 4891961.8 | Y8: =IF($D8=$C$1,VLOOKUP($T8,Mortality_Table,3,FALSE),VLOOKUP($T8,Mortality_Table,2,FALSE)) -> 0.00381 | Z8: =IF($D8=$C$1,VLOOKUP($T8,Male_Annuity_Tables,MATCH($W8+2,'Mortality Tables'!$DS$1:$HT$1,0),FALSE),VLOOKUP($T8,Fe_Annuity_Tables,MATCH($W8+2,'Mortality Tables'!$M$1:$DN$1,0),FALSE)) -> 0.2149038 | AB8: =IFERROR(IF($W8>=AB$3,($H8*(1+Ann_Salary_Growth_Rate)^AB$3),""),0) -> 1897666.8 | AC8: =IFERROR(IF($W8>=AC$3,($H8*(1+Ann_Salary_Growth_Rate)^AC$3),""),0) -> 1994352.9 | AD8: =IFERROR(IF($W8>=AD$3,($H8*(1+Ann_Salary_Growth_Rate)^AD$3),""),0) -> 2095965.2 | AE8: =IFERROR(IF($W8>=AE$3,($H8*(1+Ann_Salary_Growth_Rate)^AE$3),""),0) -> 2202754.6 | AF8: =IFERROR(IF($W8>=AF$3,($H8*(1+Ann_Salary_Growth_Rate)^AF$3),""),0) -> 2314985 | AG8: =IFERROR(IF($W8>=AG$3,($H8*(1+Ann_Salary_Growth_Rate)^AG$3),""),0) -> 2432933.4 | AH8: =IFERROR(IF($W8>=AH$3,($H8*(1+Ann_Salary_Growth_Rate)^AH$3),""),0) -> 2556891.4 | AI8: =IFERROR(IF($W8>=AI$3,($H8*(1+Ann_Salary_Growth_Rate)^AI$3),""),0) -> 2687165 | ... BQ8: =IFERROR(IF($W8>=BQ$3,($H8*(1+Ann_Salary_Growth_Rate)^BQ$3),""),0) | BS8: =IFERROR(($L8+AB8*Contr_Rate)*(1+Inv_Return)*IF($D8=$C$1,VLOOKUP($T8,Male_Annuity_Tables,MATCH($BS$3+3,'Mortality Tables'!$N$1:$DN$1,0),FALSE),VLOOKUP($T8,Fe_Annuity_Tables,MATCH(BS$3+3,'Mortality Tables'!$N$1:$DN$1,0),FALSE)),"") -> 799447.37 | BT8: =IFERROR(($BS8+AC8*Contr_Rate)*(1+Inv_Return)*IF($D8=$C$1,VLOOKUP($T8,Male_Annuity_Tables,MATCH($BS$3+3,'Mortality Tables'!$N$1:$DN$1,0),FALSE),VLOOKUP($T8,Fe_Annuity_Tables,MATCH(BT$3+3,'Mortality Tables'!$N$1:$DN$1,0),FALSE)),"") -> 1216282.5 | BU8: =IFERROR((BT8+AD8*Contr_Rate)*(1+Inv_Return)*IF($D8=$C$1,VLOOKUP($T8,Male_Annuity_Tables,MATCH($BS$3+3,'Mortality Tables'!$N$1:$DN$1,0),FALSE),VLOOKUP($T8,Fe_Annuity_Tables,MATCH(BU$3+3,'Mortality Tables'!$N$1:$DN$1,0),FALSE)),"") -> 1605525.7 | BV8: =IFERROR((BU8+AE8*Contr_Rate)*(1+Inv_Return)*IF($D8=$C$1,VLOOKUP($T8,Male_Annuity_Tables,MATCH($BS$3+3,'Mortality Tables'!$N$1:$DN$1,0),FALSE),VLOOKUP($T8,Fe_Annuity_Tables,MATCH(BV$3+3,'Mortality Tables'!$N$1:$DN$1,0),FALSE)),"") -> 1972110.8 | BW8: =IFERROR((BV8+AF8*Contr_Rate)*(1+Inv_Return)*IF($D8=$C$1,VLOOKUP($T8,Male_Annuity_Tables,MATCH($BS$3+3,'Mortality Tables'!$N$1:$DN$1,0),FALSE),VLOOKUP($T8,Fe_Annuity_Tables,MATCH(BW$3+3,'Mortality Tables'!$N$1:$DN$1,0),FALSE)),"") -> 2320399.8 | BX8: =IFERROR((BW8+AG8*Contr_Rate)*(1+Inv_Return)*IF($D8=$C$1,VLOOKUP($T8,Male_Annuity_Tables,MATCH($BS$3+3,'Mortality Tables'!$N$1:$DN$1,0),FALSE),VLOOKUP($T8,Fe_Annuity_Tables,MATCH(BX$3+3,'Mortality Tables'!$N$1:$DN$1,0),FALSE)),"") -> 2654261 | BY8: =IFERROR((BX8+AH8*Contr_Rate)*(1+Inv_Return)*IF($D8=$C$1,VLOOKUP($T8,Male_Annuity_Tables,MATCH($BS$3+3,'Mortality Tables'!$N$1:$DN$1,0),FALSE),VLOOKUP($T8,Fe_Annuity_Tables,MATCH(BY$3+3,'Mortality Tables'!$N$1:$DN$1,0),FALSE)),"") -> 2977136.1 | BZ8: =IFERROR((BY8+AI8*Contr_Rate)*(1+Inv_Return)*IF($D8=$C$1,VLOOKUP($T8,Male_Annuity_Tables,MATCH($BS$3+3,'Mortality Tables'!$N$1:$DN$1,0),FALSE),VLOOKUP($T8,Fe_Annuity_Tables,MATCH(BZ$3+3,'Mortality Tables'!$N$1:$DN$1,0),FALSE)),"") -> 3292100.3 | CA8: =IFERROR((BZ8+AJ8*Contr_Rate)*(1+Inv_Return)*IF($D8=$C$1,VLOOKUP($T8,Male_Annuity_Tables,MATCH($BS$3+3,'Mortality Tables'!$N$1:$DN$1,0),FALSE),VLOOKUP($T8,Fe_Annuity_Tables,MATCH(CA$3+3,'Mortality Tables'!$N$1:$DN$1,0),FALSE)),"") -> 3601913.4 | CB8: =IFERROR((CA8+AK8*Contr_Rate)*(1+Inv_Return)*IF($D8=$C$1,VLOOKUP($T8,Male_Annuity_Tables,MATCH($BS$3+3,'Mortality Tables'!$N$1:$DN$1,0),FALSE),VLOOKUP($T8,Fe_Annuity_Tables,MATCH(CB$3+3,'Mortality Tables'!$N$1:$DN$1,0),FALSE)),"") -> 3909065 | ... DH8: =IFERROR((DG8+BQ8*Contr_Rate)*(1+Inv_Return)*IF($D8=$C$1,VLOOKUP($T8,Male_Annuity_Tables,MATCH($BS$3+3,'Mortality Tables'!$N$1:$DN$1,0),FALSE),VLOOKUP($T8,Fe_Annuity_Tables,MATCH(DH$3+3,'Mortality Tables'!$N$1:$DN$1,0),FALSE)),"") | DJ8: =MAX(BS8:DH8) -> 5153485.1 | DK8: =IF($D8="FEMALE",Fe_Annuity_Factor,Male_Annuity_Factor) -> 8.0909278 | DL8: =(DJ8*Annuity_Ratio)/DK8 -> 426753.91 | DM8: =MAX($AB8:$BQ8) -> 3620651 | DN8: =IFERROR((DL8/DM8),"") -> 0.11786662 | DP8: =IFERROR(IF($D8=$C$1,VLOOKUP($T8+DP$3-1,Male_Annuity_Tables,2,FALSE),VLOOKUP($T8,Fe_Annuity_Tables,2,FALSE))*BS8,"") -> 122506.12 | DQ8: =IFERROR(IF($D8=$C$1,VLOOKUP($T8+DQ$3-1,Male_Annuity_Tables,2,FALSE),VLOOKUP($T8,Fe_Annuity_Tables,2,FALSE))*BT8,"") -> 186753.48 | DR8: =IFERROR(IF($D8=$C$1,VLOOKUP($T8+DR$3-1,Male_Annuity_Tables,2,FALSE),VLOOKUP($T8,Fe_Annuity_Tables,2,FALSE))*BU8,"") -> 247038.22
A9: M0006 | B9: Gabrielle Davis | C9: Active | D9: Female | E9: 24228 | F9: 39435 | G9: 43709 | H9: 630511 | I9: 48928.93 | J9: 57672.99 | K9: 43776.81 | L9: 150378.73 | M9: =IF(COUNTIF($A$4:A204,A9)=1,0,1) -> 0 | N9: =IF(T9<=18,"WHAT!!!",IF(T9>100,"EERM","Okay")) -> Okay | O9: =IF(G9>E9,"TRUE","FALSE") -> TRUE | P9: =G9>=Comm_Date -> TRUE | Q9: =$G9>=$F9 -> TRUE | R9: =$F9>$E9 -> TRUE | S9: =YEARFRAC(E9,F9,3) -> 41.663014 | T9: =ROUNDDOWN(YEARFRAC($E9,Analysis_Date,3),0) -> 58 | U9: =ROUNDDOWN(YEARFRAC($E9,$G9,3),0) -> 53 | V9: =YEARFRAC($G9,Analysis_Date,3) -> 5.3342466 | W9: =MAX(ROUNDDOWN(NRA-T9,0),0) -> 2 | X9: =L9*W9 -> 300757.46 | Y9: =IF($D9=$C$1,VLOOKUP($T9,Mortality_Table,3,FALSE),VLOOKUP($T9,Mortality_Table,2,FALSE)) -> 0.00713 | Z9: =IF($D9=$C$1,VLOOKUP($T9,Male_Annuity_Tables,MATCH($W9+2,'Mortality Tables'!$DS$1:$HT$1,0),FALSE),VLOOKUP($T9,Fe_Annuity_Tables,MATCH($W9+2,'Mortality Tables'!$M$1:$DN$1,0),FALSE)) -> 0.88908483 | AB9: =IFERROR(IF($W9>=AB$3,($H9*(1+Ann_Salary_Growth_Rate)^AB$3),""),0) -> 662635.54 | AC9: =IFERROR(IF($W9>=AC$3,($H9*(1+Ann_Salary_Growth_Rate)^AC$3),""),0) -> 696396.82 | AD9: =IFERROR(IF($W9>=AD$3,($H9*(1+Ann_Salary_Growth_Rate)^AD$3),""),0) | AE9: =IFERROR(IF($W9>=AE$3,($H9*(1+Ann_Salary_Growth_Rate)^AE$3),""),0) | AF9: =IFERROR(IF($W9>=AF$3,($H9*(1+Ann_Salary_Growth_Rate)^AF$3),""),0) | AG9: =IFERROR(IF($W9>=AG$3,($H9*(1+Ann_Salary_Growth_Rate)^AG$3),""),0) | AH9: =IFERROR(IF($W9>=AH$3,($H9*(1+Ann_Salary_Growth_Rate)^AH$3),""),0) | AI9: =IFERROR(IF($W9>=AI$3,($H9*(1+Ann_Salary_Growth_Rate)^AI$3),""),0) | ... BQ9: =IFERROR(IF($W9>=BQ$3,($H9*(1+Ann_Salary_Growth_Rate)^BQ$3),""),0) | BS9: =IFERROR(($L9+AB9*Contr_Rate)*(1+Inv_Return)*IF($D9=$C$1,VLOOKUP($T9,Male_Annuity_Tables,MATCH($BS$3+3,'Mortality Tables'!$N$1:$DN$1,0),FALSE),VLOOKUP($T9,Fe_Annuity_Tables,MATCH(BS$3+3,'Mortality Tables'!$N$1:$DN$1,0),FALSE)),"") -> 338450.36 | BT9: =IFERROR(($BS9+AC9*Contr_Rate)*(1+Inv_Return)*IF($D9=$C$1,VLOOKUP($T9,Male_Annuity_Tables,MATCH($BS$3+3,'Mortality Tables'!$N$1:$DN$1,0),FALSE),VLOOKUP($T9,Fe_Annuity_Tables,MATCH(BT$3+3,'Mortality Tables'!$N$1:$DN$1,0),FALSE)),"") -> 500111.16 | BU9: =IFERROR((BT9+AD9*Contr_Rate)*(1+Inv_Return)*IF($D9=$C$1,VLOOKUP($T9,Male_Annuity_Tables,MATCH($BS$3+3,'Mortality Tables'!$N$1:$DN$1,0),FALSE),VLOOKUP($T9,Fe_Annuity_Tables,MATCH(BU$3+3,'Mortality Tables'!$N$1:$DN$1,0),FALSE)),"") | BV9: =IFERROR((BU9+AE9*Contr_Rate)*(1+Inv_Return)*IF($D9=$C$1,VLOOKUP($T9,Male_Annuity_Tables,MATCH($BS$3+3,'Mortality Tables'!$N$1:$DN$1,0),FALSE),VLOOKUP($T9,Fe_Annuity_Tables,MATCH(BV$3+3,'Mortality Tables'!$N$1:$DN$1,0),FALSE)),"") | BW9: =IFERROR((BV9+AF9*Contr_Rate)*(1+Inv_Return)*IF($D9=$C$1,VLOOKUP($T9,Male_Annuity_Tables,MATCH($BS$3+3,'Mortality Tables'!$N$1:$DN$1,0),FALSE),VLOOKUP($T9,Fe_Annuity_Tables,MATCH(BW$3+3,'Mortality Tables'!$N$1:$DN$1,0),FALSE)),"") | BX9: =IFERROR((BW9+AG9*Contr_Rate)*(1+Inv_Return)*IF($D9=$C$1,VLOOKUP($T9,Male_Annuity_Tables,MATCH($BS$3+3,'Mortality Tables'!$N$1:$DN$1,0),FALSE),VLOOKUP($T9,Fe_Annuity_Tables,MATCH(BX$3+3,'Mortality Tables'!$N$1:$DN$1,0),FALSE)),"") | BY9: =IFERROR((BX9+AH9*Contr_Rate)*(1+Inv_Return)*IF($D9=$C$1,VLOOKUP($T9,Male_Annuity_Tables,MATCH($BS$3+3,'Mortality Tables'!$N$1:$DN$1,0),FALSE),VLOOKUP($T9,Fe_Annuity_Tables,MATCH(BY$3+3,'Mortality Tables'!$N$1:$DN$1,0),FALSE)),"") | BZ9: =IFERROR((BY9+AI9*Contr_Rate)*(1+Inv_Return)*IF($D9=$C$1,VLOOKUP($T9,Male_Annuity_Tables,MATCH($BS$3+3,'Mortality Tables'!$N$1:$DN$1,0),FALSE),VLOOKUP($T9,Fe_Annuity_Tables,MATCH(BZ$3+3,'Mortality Tables'!$N$1:$DN$1,0),FALSE)),"") | CA9: =IFERROR((BZ9+AJ9*Contr_Rate)*(1+Inv_Return)*IF($D9=$C$1,VLOOKUP($T9,Male_Annuity_Tables,MATCH($BS$3+3,'Mortality Tables'!$N$1:$DN$1,0),FALSE),VLOOKUP($T9,Fe_Annuity_Tables,MATCH(CA$3+3,'Mortality Tables'!$N$1:$DN$1,0),FALSE)),"") | CB9: =IFERROR((CA9+AK9*Contr_Rate)*(1+Inv_Return)*IF($D9=$C$1,VLOOKUP($T9,Male_Annuity_Tables,MATCH($BS$3+3,'Mortality Tables'!$N$1:$DN$1,0),FALSE),VLOOKUP($T9,Fe_Annuity_Tables,MATCH(CB$3+3,'Mortality Tables'!$N$1:$DN$1,0),FALSE)),"") | ... DH9: =IFERROR((DG9+BQ9*Contr_Rate)*(1+Inv_Return)*IF($D9=$C$1,VLOOKUP($T9,Male_Annuity_Tables,MATCH($BS$3+3,'Mortality Tables'!$N$1:$DN$1,0),FALSE),VLOOKUP($T9,Fe_Annuity_Tables,MATCH(DH$3+3,'Mortality Tables'!$N$1:$DN$1,0),FALSE)),"") | DJ9: =MAX(BS9:DH9) -> 500111.16 | DK9: =IF($D9="FEMALE",Fe_Annuity_Factor,Male_Annuity_Factor) -> 8.8017766 | DL9: =(DJ9*Annuity_Ratio)/DK9 -> 38068.96 | DM9: =MAX($AB9:$BQ9) -> 696396.82 | DN9: =IFERROR((DL9/DM9),"") -> 0.054665614 | DP9: =IFERROR(IF($D9=$C$1,VLOOKUP($T9+DP$3-1,Male_Annuity_Tables,2,FALSE),VLOOKUP($T9,Fe_Annuity_Tables,2,FALSE))*BS9,"") -> 19215.012 | DQ9: =IFERROR(IF($D9=$C$1,VLOOKUP($T9+DQ$3-1,Male_Annuity_Tables,2,FALSE),VLOOKUP($T9,Fe_Annuity_Tables,2,FALSE))*BT9,"") -> 28393.061 | DR9: =IFERROR(IF($D9=$C$1,VLOOKUP($T9+DR$3-1,Male_Annuity_Tables,2,FALSE),VLOOKUP($T9,Fe_Annuity_Tables,2,FALSE))*BU9,"")
A10: M0007 | B10: Renee Blair | C10: Deferred | D10: Male | E10: 28578 | F10: 36525 | G10: 41229 | H10: 492201 | I10: 40883.77 | J10: 43635.3 | K10: 43489.3 | L10: 128008.37 | M10: =IF(COUNTIF($A$4:A204,A10)=1,0,1) -> 0 | N10: =IF(T10<=18,"WHAT!!!",IF(T10>100,"EERM","Okay")) -> Okay | O10: =IF(G10>E10,"TRUE","FALSE") -> TRUE | P10: =G10>=Comm_Date -> TRUE | Q10: =$G10>=$F10 -> TRUE | R10: =$F10>$E10 -> TRUE | S10: =YEARFRAC(E10,F10,3) -> 21.772603 | T10: =ROUNDDOWN(YEARFRAC($E10,Analysis_Date,3),0) -> 46 | U10: =ROUNDDOWN(YEARFRAC($E10,$G10,3),0) -> 34 | V10: =YEARFRAC($G10,Analysis_Date,3) -> 12.128767 | W10: =MAX(ROUNDDOWN(NRA-T10,0),0) -> 14 | X10: =L10*W10 -> 1792117.2 | Y10: =IF($D10=$C$1,VLOOKUP($T10,Mortality_Table,3,FALSE),VLOOKUP($T10,Mortality_Table,2,FALSE)) -> 0.00381 | Z10: =IF($D10=$C$1,VLOOKUP($T10,Male_Annuity_Tables,MATCH($W10+2,'Mortality Tables'!$DS$1:$HT$1,0),FALSE),VLOOKUP($T10,Fe_Annuity_Tables,MATCH($W10+2,'Mortality Tables'!$M$1:$DN$1,0),FALSE)) -> 0.2149038 | AB10: =IFERROR(IF($W10>=AB$3,($H10*(1+Ann_Salary_Growth_Rate)^AB$3),""),0) -> 517278.64 | AC10: =IFERROR(IF($W10>=AC$3,($H10*(1+Ann_Salary_Growth_Rate)^AC$3),""),0) -> 543633.99 | AD10: =IFERROR(IF($W10>=AD$3,($H10*(1+Ann_Salary_Growth_Rate)^AD$3),""),0) -> 571332.14 | AE10: =IFERROR(IF($W10>=AE$3,($H10*(1+Ann_Salary_Growth_Rate)^AE$3),""),0) -> 600441.51 | AF10: =IFERROR(IF($W10>=AF$3,($H10*(1+Ann_Salary_Growth_Rate)^AF$3),""),0) -> 631034.01 | AG10: =IFERROR(IF($W10>=AG$3,($H10*(1+Ann_Salary_Growth_Rate)^AG$3),""),0) -> 663185.19 | AH10: =IFERROR(IF($W10>=AH$3,($H10*(1+Ann_Salary_Growth_Rate)^AH$3),""),0) -> 696974.47 | AI10: =IFERROR(IF($W10>=AI$3,($H10*(1+Ann_Salary_Growth_Rate)^AI$3),""),0) -> 732485.32 | ... BQ10: =IFERROR(IF($W10>=BQ$3,($H10*(1+Ann_Salary_Growth_Rate)^BQ$3),""),0) | BS10: =IFERROR(($L10+AB10*Contr_Rate)*(1+Inv_Return)*IF($D10=$C$1,VLOOKUP($T10,Male_Annuity_Tables,MATCH($BS$3+3,'Mortality Tables'!$N$1:$DN$1,0),FALSE),VLOOKUP($T10,Fe_Annuity_Tables,MATCH(BS$3+3,'Mortality Tables'!$N$1:$DN$1,0),FALSE)),"") -> 246425.05 | BT10: =IFERROR(($BS10+AC10*Contr_Rate)*(1+Inv_Return)*IF($D10=$C$1,VLOOKUP($T10,Male_Annuity_Tables,MATCH($BS$3+3,'Mortality Tables'!$N$1:$DN$1,0),FALSE),VLOOKUP($T10,Fe_Annuity_Tables,MATCH(BT$3+3,'Mortality Tables'!$N$1:$DN$1,0),FALSE)),"") -> 356347.74 | BU10: =IFERROR((BT10+AD10*Contr_Rate)*(1+Inv_Return)*IF($D10=$C$1,VLOOKUP($T10,Male_Annuity_Tables,MATCH($BS$3+3,'Mortality Tables'!$N$1:$DN$1,0),FALSE),VLOOKUP($T10,Fe_Annuity_Tables,MATCH(BU$3+3,'Mortality Tables'!$N$1:$DN$1,0),FALSE)),"") -> 459229.75 | BV10: =IFERROR((BU10+AE10*Contr_Rate)*(1+Inv_Return)*IF($D10=$C$1,VLOOKUP($T10,Male_Annuity_Tables,MATCH($BS$3+3,'Mortality Tables'!$N$1:$DN$1,0),FALSE),VLOOKUP($T10,Fe_Annuity_Tables,MATCH(BV$3+3,'Mortality Tables'!$N$1:$DN$1,0),FALSE)),"") -> 556353.59 | BW10: =IFERROR((BV10+AF10*Contr_Rate)*(1+Inv_Return)*IF($D10=$C$1,VLOOKUP($T10,Male_Annuity_Tables,MATCH($BS$3+3,'Mortality Tables'!$N$1:$DN$1,0),FALSE),VLOOKUP($T10,Fe_Annuity_Tables,MATCH(BW$3+3,'Mortality Tables'!$N$1:$DN$1,0),FALSE)),"") -> 648854 | BX10: =IFERROR((BW10+AG10*Contr_Rate)*(1+Inv_Return)*IF($D10=$C$1,VLOOKUP($T10,Male_Annuity_Tables,MATCH($BS$3+3,'Mortality Tables'!$N$1:$DN$1,0),FALSE),VLOOKUP($T10,Fe_Annuity_Tables,MATCH(BX$3+3,'Mortality Tables'!$N$1:$DN$1,0),FALSE)),"") -> 737738.14 | BY10: =IFERROR((BX10+AH10*Contr_Rate)*(1+Inv_Return)*IF($D10=$C$1,VLOOKUP($T10,Male_Annuity_Tables,MATCH($BS$3+3,'Mortality Tables'!$N$1:$DN$1,0),FALSE),VLOOKUP($T10,Fe_Annuity_Tables,MATCH(BY$3+3,'Mortality Tables'!$N$1:$DN$1,0),FALSE)),"") -> 823903.15 | BZ10: =IFERROR((BY10+AI10*Contr_Rate)*(1+Inv_Return)*IF($D10=$C$1,VLOOKUP($T10,Male_Annuity_Tables,MATCH($BS$3+3,'Mortality Tables'!$N$1:$DN$1,0),FALSE),VLOOKUP($T10,Fe_Annuity_Tables,MATCH(BZ$3+3,'Mortality Tables'!$N$1:$DN$1,0),FALSE)),"") -> 908151.47 | CA10: =IFERROR((BZ10+AJ10*Contr_Rate)*(1+Inv_Return)*IF($D10=$C$1,VLOOKUP($T10,Male_Annuity_Tables,MATCH($BS$3+3,'Mortality Tables'!$N$1:$DN$1,0),FALSE),VLOOKUP($T10,Fe_Annuity_Tables,MATCH(CA$3+3,'Mortality Tables'!$N$1:$DN$1,0),FALSE)),"") -> 991204.25 | CB10: =IFERROR((CA10+AK10*Contr_Rate)*(1+Inv_Return)*IF($D10=$C$1,VLOOKUP($T10,Male_Annuity_Tables,MATCH($BS$3+3,'Mortality Tables'!$N$1:$DN$1,0),FALSE),VLOOKUP($T10,Fe_Annuity_Tables,MATCH(CB$3+3,'Mortality Tables'!$N$1:$DN$1,0),FALSE)),"") -> 1073713.1 | ... DH10: =IFERROR((DG10+BQ10*Contr_Rate)*(1+Inv_Return)*IF($D10=$C$1,VLOOKUP($T10,Male_Annuity_Tables,MATCH($BS$3+3,'Mortality Tables'!$N$1:$DN$1,0),FALSE),VLOOKUP($T10,Fe_Annuity_Tables,MATCH(DH$3+3,'Mortality Tables'!$N$1:$DN$1,0),FALSE)),"") | DJ10: =MAX(BS10:DH10) -> 1409446.4 | DK10: =IF($D10="FEMALE",Fe_Annuity_Factor,Male_Annuity_Factor) -> 8.0909278 | DL10: =(DJ10*Annuity_Ratio)/DK10 -> 116714.56 | DM10: =MAX($AB10:$BQ10) -> 986941.15 | DN10: =IFERROR((DL10/DM10),"") -> 0.11825889 | DP10: =IFERROR(IF($D10=$C$1,VLOOKUP($T10+DP$3-1,Male_Annuity_Tables,2,FALSE),VLOOKUP($T10,Fe_Annuity_Tables,2,FALSE))*BS10,"") -> 37761.805 | DQ10: =IFERROR(IF($D10=$C$1,VLOOKUP($T10+DQ$3-1,Male_Annuity_Tables,2,FALSE),VLOOKUP($T10,Fe_Annuity_Tables,2,FALSE))*BT10,"") -> 54715.235 | DR10: =IFERROR(IF($D10=$C$1,VLOOKUP($T10+DR$3-1,Male_Annuity_Tables,2,FALSE),VLOOKUP($T10,Fe_Annuity_Tables,2,FALSE))*BU10,"") -> 70660.534
A11: M0008 | B11: Edward Fuller | C11: Active | D11: Female | E11: 30813 | F11: 42149 | G11: 43343 | H11: 1465905 | I11: 106528.07 | J11: 134431.58 | L11: 240959.65 | M11: =IF(COUNTIF($A$4:A204,A11)=1,0,1) -> 0 | N11: =IF(T11<=18,"WHAT!!!",IF(T11>100,"EERM","Okay")) -> Okay | O11: =IF(G11>E11,"TRUE","FALSE") -> TRUE | P11: =G11>=Comm_Date -> TRUE | Q11: =$G11>=$F11 -> TRUE | R11: =$F11>$E11 -> TRUE | S11: =YEARFRAC(E11,F11,3) -> 31.057534 | T11: =ROUNDDOWN(YEARFRAC($E11,Analysis_Date,3),0) -> 40 | U11: =ROUNDDOWN(YEARFRAC($E11,$G11,3),0) -> 34 | V11: =YEARFRAC($G11,Analysis_Date,3) -> 6.3369863 | W11: =MAX(ROUNDDOWN(NRA-T11,0),0) -> 20 | X11: =L11*W11 -> 4819193 | Y11: =IF($D11=$C$1,VLOOKUP($T11,Mortality_Table,3,FALSE),VLOOKUP($T11,Mortality_Table,2,FALSE)) -> 0.00191 | Z11: =IF($D11=$C$1,VLOOKUP($T11,Male_Annuity_Tables,MATCH($W11+2,'Mortality Tables'!$DS$1:$HT$1,0),FALSE),VLOOKUP($T11,Fe_Annuity_Tables,MATCH($W11+2,'Mortality Tables'!$M$1:$DN$1,0),FALSE)) -> 0.082941194 | AB11: =IFERROR(IF($W11>=AB$3,($H11*(1+Ann_Salary_Growth_Rate)^AB$3),""),0) -> 1540592.9 | AC11: =IFERROR(IF($W11>=AC$3,($H11*(1+Ann_Salary_Growth_Rate)^AC$3),""),0) -> 1619086.1 | AD11: =IFERROR(IF($W11>=AD$3,($H11*(1+Ann_Salary_Growth_Rate)^AD$3),""),0) -> 1701578.5 | AE11: =IFERROR(IF($W11>=AE$3,($H11*(1+Ann_Salary_Growth_Rate)^AE$3),""),0) -> 1788273.9 | AF11: =IFERROR(IF($W11>=AF$3,($H11*(1+Ann_Salary_Growth_Rate)^AF$3),""),0) -> 1879386.5 | AG11: =IFERROR(IF($W11>=AG$3,($H11*(1+Ann_Salary_Growth_Rate)^AG$3),""),0) -> 1975141.2 | AH11: =IFERROR(IF($W11>=AH$3,($H11*(1+Ann_Salary_Growth_Rate)^AH$3),""),0) -> 2075774.7 | AI11: =IFERROR(IF($W11>=AI$3,($H11*(1+Ann_Salary_Growth_Rate)^AI$3),""),0) -> 2181535.4 | ... BQ11: =IFERROR(IF($W11>=BQ$3,($H11*(1+Ann_Salary_Growth_Rate)^BQ$3),""),0) | BS11: =IFERROR(($L11+AB11*Contr_Rate)*(1+Inv_Return)*IF($D11=$C$1,VLOOKUP($T11,Male_Annuity_Tables,MATCH($BS$3+3,'Mortality Tables'!$N$1:$DN$1,0),FALSE),VLOOKUP($T11,Fe_Annuity_Tables,MATCH(BS$3+3,'Mortality Tables'!$N$1:$DN$1,0),FALSE)),"") -> 613015.88 | BT11: =IFERROR(($BS11+AC11*Contr_Rate)*(1+Inv_Return)*IF($D11=$C$1,VLOOKUP($T11,Male_Annuity_Tables,MATCH($BS$3+3,'Mortality Tables'!$N$1:$DN$1,0),FALSE),VLOOKUP($T11,Fe_Annuity_Tables,MATCH(BT$3+3,'Mortality Tables'!$N$1:$DN$1,0),FALSE)),"") -> 812575.04 | BU11: =IFERROR((BT11+AD11*Contr_Rate)*(1+Inv_Return)*IF($D11=$C$1,VLOOKUP($T11,Male_Annuity_Tables,MATCH($BS$3+3,'Mortality Tables'!$N$1:$DN$1,0),FALSE),VLOOKUP($T11,Fe_Annuity_Tables,MATCH(BU$3+3,'Mortality Tables'!$N$1:$DN$1,0),FALSE)),"") -> 829895.67 | BV11: =IFERROR((BU11+AE11*Contr_Rate)*(1+Inv_Return)*IF($D11=$C$1,VLOOKUP($T11,Male_Annuity_Tables,MATCH($BS$3+3,'Mortality Tables'!$N$1:$DN$1,0),FALSE),VLOOKUP($T11,Fe_Annuity_Tables,MATCH(BV$3+3,'Mortality Tables'!$N$1:$DN$1,0),FALSE)),"") -> 726844.93 | BW11: =IFERROR((BV11+AF11*Contr_Rate)*(1+Inv_Return)*IF($D11=$C$1,VLOOKUP($T11,Male_Annuity_Tables,MATCH($BS$3+3,'Mortality Tables'!$N$1:$DN$1,0),FALSE),VLOOKUP($T11,Fe_Annuity_Tables,MATCH(BW$3+3,'Mortality Tables'!$N$1:$DN$1,0),FALSE)),"") -> 582152.41 | BX11: =IFERROR((BW11+AG11*Contr_Rate)*(1+Inv_Return)*IF($D11=$C$1,VLOOKUP($T11,Male_Annuity_Tables,MATCH($BS$3+3,'Mortality Tables'!$N$1:$DN$1,0),FALSE),VLOOKUP($T11,Fe_Annuity_Tables,MATCH(BX$3+3,'Mortality Tables'!$N$1:$DN$1,0),FALSE)),"") -> 449193.57 | BY11: =IFERROR((BX11+AH11*Contr_Rate)*(1+Inv_Return)*IF($D11=$C$1,VLOOKUP($T11,Male_Annuity_Tables,MATCH($BS$3+3,'Mortality Tables'!$N$1:$DN$1,0),FALSE),VLOOKUP($T11,Fe_Annuity_Tables,MATCH(BY$3+3,'Mortality Tables'!$N$1:$DN$1,0),FALSE)),"") -> 347435.73 | BZ11: =IFERROR((BY11+AI11*Contr_Rate)*(1+Inv_Return)*IF($D11=$C$1,VLOOKUP($T11,Male_Annuity_Tables,MATCH($BS$3+3,'Mortality Tables'!$N$1:$DN$1,0),FALSE),VLOOKUP($T11,Fe_Annuity_Tables,MATCH(BZ$3+3,'Mortality Tables'!$N$1:$DN$1,0),FALSE)),"") -> 275193.3 | CA11: =IFERROR((BZ11+AJ11*Contr_Rate)*(1+Inv_Return)*IF($D11=$C$1,VLOOKUP($T11,Male_Annuity_Tables,MATCH($BS$3+3,'Mortality Tables'!$N$1:$DN$1,0),FALSE),VLOOKUP($T11,Fe_Annuity_Tables,MATCH(CA$3+3,'Mortality Tables'!$N$1:$DN$1,0),FALSE)),"") -> 224104.34 | CB11: =IFERROR((CA11+AK11*Contr_Rate)*(1+Inv_Return)*IF($D11=$C$1,VLOOKUP($T11,Male_Annuity_Tables,MATCH($BS$3+3,'Mortality Tables'!$N$1:$DN$1,0),FALSE),VLOOKUP($T11,Fe_Annuity_Tables,MATCH(CB$3+3,'Mortality Tables'!$N$1:$DN$1,0),FALSE)),"") -> 186662.96 | ... DH11: =IFERROR((DG11+BQ11*Contr_Rate)*(1+Inv_Return)*IF($D11=$C$1,VLOOKUP($T11,Male_Annuity_Tables,MATCH($BS$3+3,'Mortality Tables'!$N$1:$DN$1,0),FALSE),VLOOKUP($T11,Fe_Annuity_Tables,MATCH(DH$3+3,'Mortality Tables'!$N$1:$DN$1,0),FALSE)),"") | DJ11: =MAX(BS11:DH11) -> 829895.67 | DK11: =IF($D11="FEMALE",Fe_Annuity_Factor,Male_Annuity_Factor) -> 8.8017766 | DL11: =(DJ11*Annuity_Ratio)/DK11 -> 63172.485 | DM11: =MAX($AB11:$BQ11) -> 3960471.7 | DN11: =IFERROR((DL11/DM11),"") -> 0.015950748 | DP11: =IFERROR(IF($D11=$C$1,VLOOKUP($T11+DP$3-1,Male_Annuity_Tables,2,FALSE),VLOOKUP($T11,Fe_Annuity_Tables,2,FALSE))*BS11,"") -> 92947.613 | DQ11: =IFERROR(IF($D11=$C$1,VLOOKUP($T11+DQ$3-1,Male_Annuity_Tables,2,FALSE),VLOOKUP($T11,Fe_Annuity_Tables,2,FALSE))*BT11,"") -> 123205.47 | DR11: =IFERROR(IF($D11=$C$1,VLOOKUP($T11+DR$3-1,Male_Annuity_Tables,2,FALSE),VLOOKUP($T11,Fe_Annuity_Tables,2,FALSE))*BU11,"") -> 125831.69
A12: M0009 | B12: Amber Perez | C12: Dormant | D12: Male | E12: 29017 | F12: 35965 | G12: 38858 | H12: 1419786 | I12: 120811.03 | J12: 119513.87 | L12: 240324.9 | M12: =IF(COUNTIF($A$4:A204,A12)=1,0,1) -> 0 | N12: =IF(T12<=18,"WHAT!!!",IF(T12>100,"EERM","Okay")) -> Okay | O12: =IF(G12>E12,"TRUE","FALSE") -> TRUE | P12: =G12>=Comm_Date -> TRUE | Q12: =$G12>=$F12 -> TRUE | R12: =$F12>$E12 -> TRUE | S12: =YEARFRAC(E12,F12,3) -> 19.035616 | T12: =ROUNDDOWN(YEARFRAC($E12,Analysis_Date,3),0) -> 45 | U12: =ROUNDDOWN(YEARFRAC($E12,$G12,3),0) -> 26 | V12: =YEARFRAC($G12,Analysis_Date,3) -> 18.624658 | W12: =MAX(ROUNDDOWN(NRA-T12,0),0) -> 15 | X12: =L12*W12 -> 3604873.5 | Y12: =IF($D12=$C$1,VLOOKUP($T12,Mortality_Table,3,FALSE),VLOOKUP($T12,Mortality_Table,2,FALSE)) -> 0.00349 | Z12: =IF($D12=$C$1,VLOOKUP($T12,Male_Annuity_Tables,MATCH($W12+2,'Mortality Tables'!$DS$1:$HT$1,0),FALSE),VLOOKUP($T12,Fe_Annuity_Tables,MATCH($W12+2,'Mortality Tables'!$M$1:$DN$1,0),FALSE)) -> 0.18203071 | AB12: =IFERROR(IF($W12>=AB$3,($H12*(1+Ann_Salary_Growth_Rate)^AB$3),""),0) -> 1492124.1 | AC12: =IFERROR(IF($W12>=AC$3,($H12*(1+Ann_Salary_Growth_Rate)^AC$3),""),0) -> 1568147.8 | AD12: =IFERROR(IF($W12>=AD$3,($H12*(1+Ann_Salary_Growth_Rate)^AD$3),""),0) -> 1648045 | AE12: =IFERROR(IF($W12>=AE$3,($H12*(1+Ann_Salary_Growth_Rate)^AE$3),""),0) -> 1732012.8 | AF12: =IFERROR(IF($W12>=AF$3,($H12*(1+Ann_Salary_Growth_Rate)^AF$3),""),0) -> 1820258.9 | AG12: =IFERROR(IF($W12>=AG$3,($H12*(1+Ann_Salary_Growth_Rate)^AG$3),""),0) -> 1913001.1 | AH12: =IFERROR(IF($W12>=AH$3,($H12*(1+Ann_Salary_Growth_Rate)^AH$3),""),0) -> 2010468.5 | AI12: =IFERROR(IF($W12>=AI$3,($H12*(1+Ann_Salary_Growth_Rate)^AI$3),""),0) -> 2112901.9 | ... BQ12: =IFERROR(IF($W12>=BQ$3,($H12*(1+Ann_Salary_Growth_Rate)^BQ$3),""),0) | BS12: =IFERROR(($L12+AB12*Contr_Rate)*(1+Inv_Return)*IF($D12=$C$1,VLOOKUP($T12,Male_Annuity_Tables,MATCH($BS$3+3,'Mortality Tables'!$N$1:$DN$1,0),FALSE),VLOOKUP($T12,Fe_Annuity_Tables,MATCH(BS$3+3,'Mortality Tables'!$N$1:$DN$1,0),FALSE)),"") -> 598836.06 | BT12: =IFERROR(($BS12+AC12*Contr_Rate)*(1+Inv_Return)*IF($D12=$C$1,VLOOKUP($T12,Male_Annuity_Tables,MATCH($BS$3+3,'Mortality Tables'!$N$1:$DN$1,0),FALSE),VLOOKUP($T12,Fe_Annuity_Tables,MATCH(BT$3+3,'Mortality Tables'!$N$1:$DN$1,0),FALSE)),"") -> 930754.24 | BU12: =IFERROR((BT12+AD12*Contr_Rate)*(1+Inv_Return)*IF($D12=$C$1,VLOOKUP($T12,Male_Annuity_Tables,MATCH($BS$3+3,'Mortality Tables'!$N$1:$DN$1,0),FALSE),VLOOKUP($T12,Fe_Annuity_Tables,MATCH(BU$3+3,'Mortality Tables'!$N$1:$DN$1,0),FALSE)),"") -> 1240536.1 | BV12: =IFERROR((BU12+AE12*Contr_Rate)*(1+Inv_Return)*IF($D12=$C$1,VLOOKUP($T12,Male_Annuity_Tables,MATCH($BS$3+3,'Mortality Tables'!$N$1:$DN$1,0),FALSE),VLOOKUP($T12,Fe_Annuity_Tables,MATCH(BV$3+3,'Mortality Tables'!$N$1:$DN$1,0),FALSE)),"") -> 1532112.3 | BW12: =IFERROR((BV12+AF12*Contr_Rate)*(1+Inv_Return)*IF($D12=$C$1,VLOOKUP($T12,Male_Annuity_Tables,MATCH($BS$3+3,'Mortality Tables'!$N$1:$DN$1,0),FALSE),VLOOKUP($T12,Fe_Annuity_Tables,MATCH(BW$3+3,'Mortality Tables'!$N$1:$DN$1,0),FALSE)),"") -> 1808958.8 | BX12: =IFERROR((BW12+AG12*Contr_Rate)*(1+Inv_Return)*IF($D12=$C$1,VLOOKUP($T12,Male_Annuity_Tables,MATCH($BS$3+3,'Mortality Tables'!$N$1:$DN$1,0),FALSE),VLOOKUP($T12,Fe_Annuity_Tables,MATCH(BX$3+3,'Mortality Tables'!$N$1:$DN$1,0),FALSE)),"") -> 2074157.7 | BY12: =IFERROR((BX12+AH12*Contr_Rate)*(1+Inv_Return)*IF($D12=$C$1,VLOOKUP($T12,Male_Annuity_Tables,MATCH($BS$3+3,'Mortality Tables'!$N$1:$DN$1,0),FALSE),VLOOKUP($T12,Fe_Annuity_Tables,MATCH(BY$3+3,'Mortality Tables'!$N$1:$DN$1,0),FALSE)),"") -> 2330452 | BZ12: =IFERROR((BY12+AI12*Contr_Rate)*(1+Inv_Return)*IF($D12=$C$1,VLOOKUP($T12,Male_Annuity_Tables,MATCH($BS$3+3,'Mortality Tables'!$N$1:$DN$1,0),FALSE),VLOOKUP($T12,Fe_Annuity_Tables,MATCH(BZ$3+3,'Mortality Tables'!$N$1:$DN$1,0),FALSE)),"") -> 2580292.1 | CA12: =IFERROR((BZ12+AJ12*Contr_Rate)*(1+Inv_Return)*IF($D12=$C$1,VLOOKUP($T12,Male_Annuity_Tables,MATCH($BS$3+3,'Mortality Tables'!$N$1:$DN$1,0),FALSE),VLOOKUP($T12,Fe_Annuity_Tables,MATCH(CA$3+3,'Mortality Tables'!$N$1:$DN$1,0),FALSE)),"") -> 2825877 | CB12: =IFERROR((CA12+AK12*Contr_Rate)*(1+Inv_Return)*IF($D12=$C$1,VLOOKUP($T12,Male_Annuity_Tables,MATCH($BS$3+3,'Mortality Tables'!$N$1:$DN$1,0),FALSE),VLOOKUP($T12,Fe_Annuity_Tables,MATCH(CB$3+3,'Mortality Tables'!$N$1:$DN$1,0),FALSE)),"") -> 3069190.2 | ... DH12: =IFERROR((DG12+BQ12*Contr_Rate)*(1+Inv_Return)*IF($D12=$C$1,VLOOKUP($T12,Male_Annuity_Tables,MATCH($BS$3+3,'Mortality Tables'!$N$1:$DN$1,0),FALSE),VLOOKUP($T12,Fe_Annuity_Tables,MATCH(DH$3+3,'Mortality Tables'!$N$1:$DN$1,0),FALSE)),"") | DJ12: =MAX(BS12:DH12) -> 4309678.3 | DK12: =IF($D12="FEMALE",Fe_Annuity_Factor,Male_Annuity_Factor) -> 8.0909278 | DL12: =(DJ12*Annuity_Ratio)/DK12 -> 356879.28 | DM12: =MAX($AB12:$BQ12) -> 2991945.7 | DN12: =IFERROR((DL12/DM12),"") -> 0.11928 | DP12: =IFERROR(IF($D12=$C$1,VLOOKUP($T12+DP$3-1,Male_Annuity_Tables,2,FALSE),VLOOKUP($T12,Fe_Annuity_Tables,2,FALSE))*BS12,"") -> 91601.857 | DQ12: =IFERROR(IF($D12=$C$1,VLOOKUP($T12+DQ$3-1,Male_Annuity_Tables,2,FALSE),VLOOKUP($T12,Fe_Annuity_Tables,2,FALSE))*BT12,"") -> 142627.38 | DR12: =IFERROR(IF($D12=$C$1,VLOOKUP($T12+DR$3-1,Male_Annuity_Tables,2,FALSE),VLOOKUP($T12,Fe_Annuity_Tables,2,FALSE))*BU12,"") -> 190477.49
A13: M0010 | B13: Jamie Chavez | C13: Deferred | D13: Male | E13: 24317 | F13: 36995 | G13: 41595 | H13: 985359 | I13: 72042.56 | J13: 62567.73 | K13: 35967.29 | L13: 170577.58 | M13: =IF(COUNTIF($A$4:A204,A13)=1,0,1) -> 0 | N13: =IF(T13<=18,"WHAT!!!",IF(T13>100,"EERM","Okay")) -> Okay | O13: =IF(G13>E13,"TRUE","FALSE") -> TRUE | P13: =G13>=Comm_Date -> TRUE | Q13: =$G13>=$F13 -> TRUE | R13: =$F13>$E13 -> TRUE | S13: =YEARFRAC(E13,F13,3) -> 34.734247 | T13: =ROUNDDOWN(YEARFRAC($E13,Analysis_Date,3),0) -> 58 | U13: =ROUNDDOWN(YEARFRAC($E13,$G13,3),0) -> 47 | V13: =YEARFRAC($G13,Analysis_Date,3) -> 11.126027 | W13: =MAX(ROUNDDOWN(NRA-T13,0),0) -> 2 | X13: =L13*W13 -> 341155.16 | Y13: =IF($D13=$C$1,VLOOKUP($T13,Mortality_Table,3,FALSE),VLOOKUP($T13,Mortality_Table,2,FALSE)) -> 0.01155 | Z13: =IF($D13=$C$1,VLOOKUP($T13,Male_Annuity_Tables,MATCH($W13+2,'Mortality Tables'!$DS$1:$HT$1,0),FALSE),VLOOKUP($T13,Fe_Annuity_Tables,MATCH($W13+2,'Mortality Tables'!$M$1:$DN$1,0),FALSE)) -> 0.88072892 | AB13: =IFERROR(IF($W13>=AB$3,($H13*(1+Ann_Salary_Growth_Rate)^AB$3),""),0) -> 1035563 | AC13: =IFERROR(IF($W13>=AC$3,($H13*(1+Ann_Salary_Growth_Rate)^AC$3),""),0) -> 1088325 | AD13: =IFERROR(IF($W13>=AD$3,($H13*(1+Ann_Salary_Growth_Rate)^AD$3),""),0) | AE13: =IFERROR(IF($W13>=AE$3,($H13*(1+Ann_Salary_Growth_Rate)^AE$3),""),0) | AF13: =IFERROR(IF($W13>=AF$3,($H13*(1+Ann_Salary_Growth_Rate)^AF$3),""),0) | AG13: =IFERROR(IF($W13>=AG$3,($H13*(1+Ann_Salary_Growth_Rate)^AG$3),""),0) | AH13: =IFERROR(IF($W13>=AH$3,($H13*(1+Ann_Salary_Growth_Rate)^AH$3),""),0) | AI13: =IFERROR(IF($W13>=AI$3,($H13*(1+Ann_Salary_Growth_Rate)^AI$3),""),0) | ... BQ13: =IFERROR(IF($W13>=BQ$3,($H13*(1+Ann_Salary_Growth_Rate)^BQ$3),""),0) | BS13: =IFERROR(($L13+AB13*Contr_Rate)*(1+Inv_Return)*IF($D13=$C$1,VLOOKUP($T13,Male_Annuity_Tables,MATCH($BS$3+3,'Mortality Tables'!$N$1:$DN$1,0),FALSE),VLOOKUP($T13,Fe_Annuity_Tables,MATCH(BS$3+3,'Mortality Tables'!$N$1:$DN$1,0),FALSE)),"") -> 464396.26 | BT13: =IFERROR(($BS13+AC13*Contr_Rate)*(1+Inv_Return)*IF($D13=$C$1,VLOOKUP($T13,Male_Annuity_Tables,MATCH($BS$3+3,'Mortality Tables'!$N$1:$DN$1,0),FALSE),VLOOKUP($T13,Fe_Annuity_Tables,MATCH(BT$3+3,'Mortality Tables'!$N$1:$DN$1,0),FALSE)),"") -> 763201.62 | BU13: =IFERROR((BT13+AD13*Contr_Rate)*(1+Inv_Return)*IF($D13=$C$1,VLOOKUP($T13,Male_Annuity_Tables,MATCH($BS$3+3,'Mortality Tables'!$N$1:$DN$1,0),FALSE),VLOOKUP($T13,Fe_Annuity_Tables,MATCH(BU$3+3,'Mortality Tables'!$N$1:$DN$1,0),FALSE)),"") | BV13: =IFERROR((BU13+AE13*Contr_Rate)*(1+Inv_Return)*IF($D13=$C$1,VLOOKUP($T13,Male_Annuity_Tables,MATCH($BS$3+3,'Mortality Tables'!$N$1:$DN$1,0),FALSE),VLOOKUP($T13,Fe_Annuity_Tables,MATCH(BV$3+3,'Mortality Tables'!$N$1:$DN$1,0),FALSE)),"") | BW13: =IFERROR((BV13+AF13*Contr_Rate)*(1+Inv_Return)*IF($D13=$C$1,VLOOKUP($T13,Male_Annuity_Tables,MATCH($BS$3+3,'Mortality Tables'!$N$1:$DN$1,0),FALSE),VLOOKUP($T13,Fe_Annuity_Tables,MATCH(BW$3+3,'Mortality Tables'!$N$1:$DN$1,0),FALSE)),"") | BX13: =IFERROR((BW13+AG13*Contr_Rate)*(1+Inv_Return)*IF($D13=$C$1,VLOOKUP($T13,Male_Annuity_Tables,MATCH($BS$3+3,'Mortality Tables'!$N$1:$DN$1,0),FALSE),VLOOKUP($T13,Fe_Annuity_Tables,MATCH(BX$3+3,'Mortality Tables'!$N$1:$DN$1,0),FALSE)),"") | BY13: =IFERROR((BX13+AH13*Contr_Rate)*(1+Inv_Return)*IF($D13=$C$1,VLOOKUP($T13,Male_Annuity_Tables,MATCH($BS$3+3,'Mortality Tables'!$N$1:$DN$1,0),FALSE),VLOOKUP($T13,Fe_Annuity_Tables,MATCH(BY$3+3,'Mortality Tables'!$N$1:$DN$1,0),FALSE)),"") | BZ13: =IFERROR((BY13+AI13*Contr_Rate)*(1+Inv_Return)*IF($D13=$C$1,VLOOKUP($T13,Male_Annuity_Tables,MATCH($BS$3+3,'Mortality Tables'!$N$1:$DN$1,0),FALSE),VLOOKUP($T13,Fe_Annuity_Tables,MATCH(BZ$3+3,'Mortality Tables'!$N$1:$DN$1,0),FALSE)),"") | CA13: =IFERROR((BZ13+AJ13*Contr_Rate)*(1+Inv_Return)*IF($D13=$C$1,VLOOKUP($T13,Male_Annuity_Tables,MATCH($BS$3+3,'Mortality Tables'!$N$1:$DN$1,0),FALSE),VLOOKUP($T13,Fe_Annuity_Tables,MATCH(CA$3+3,'Mortality Tables'!$N$1:$DN$1,0),FALSE)),"") | CB13: =IFERROR((CA13+AK13*Contr_Rate)*(1+Inv_Return)*IF($D13=$C$1,VLOOKUP($T13,Male_Annuity_Tables,MATCH($BS$3+3,'Mortality Tables'!$N$1:$DN$1,0),FALSE),VLOOKUP($T13,Fe_Annuity_Tables,MATCH(CB$3+3,'Mortality Tables'!$N$1:$DN$1,0),FALSE)),"") | ... DH13: =IFERROR((DG13+BQ13*Contr_Rate)*(1+Inv_Return)*IF($D13=$C$1,VLOOKUP($T13,Male_Annuity_Tables,MATCH($BS$3+3,'Mortality Tables'!$N$1:$DN$1,0),FALSE),VLOOKUP($T13,Fe_Annuity_Tables,MATCH(DH$3+3,'Mortality Tables'!$N$1:$DN$1,0),FALSE)),"") | DJ13: =MAX(BS13:DH13) -> 763201.62 | DK13: =IF($D13="FEMALE",Fe_Annuity_Factor,Male_Annuity_Factor) -> 8.0909278 | DL13: =(DJ13*Annuity_Ratio)/DK13 -> 63199.809 | DM13: =MAX($AB13:$BQ13) -> 1088325 | DN13: =IFERROR((DL13/DM13),"") -> 0.058070714 | DP13: =IFERROR(IF($D13=$C$1,VLOOKUP($T13+DP$3-1,Male_Annuity_Tables,2,FALSE),VLOOKUP($T13,Fe_Annuity_Tables,2,FALSE))*BS13,"") -> 28315.401 | DQ13: =IFERROR(IF($D13=$C$1,VLOOKUP($T13+DQ$3-1,Male_Annuity_Tables,2,FALSE),VLOOKUP($T13,Fe_Annuity_Tables,2,FALSE))*BT13,"") -> 47382.61 | DR13: =IFERROR(IF($D13=$C$1,VLOOKUP($T13+DR$3-1,Male_Annuity_Tables,2,FALSE),VLOOKUP($T13,Fe_Annuity_Tables,2,FALSE))*BU13,"")
A14: M0011 | B14: Michael Miles | C14: Deferred | D14: Female | E14: 23599 | F14: 42544 | G14: 43607 | H14: 534620 | I14: 32853.68 | J14: 27589.07 | K14: 17048.34 | L14: 77491.09 | M14: =IF(COUNTIF($A$4:A204,A14)=1,0,1) -> 0 | N14: =IF(T14<=18,"WHAT!!!",IF(T14>100,"EERM","Okay")) -> Okay | O14: =IF(G14>E14,"TRUE","FALSE") -> TRUE | P14: =G14>=Comm_Date -> TRUE | Q14: =$G14>=$F14 -> TRUE | R14: =$F14>$E14 -> TRUE | S14: =YEARFRAC(E14,F14,3) -> 51.90411 | T14: =ROUNDDOWN(YEARFRAC($E14,Analysis_Date,3),0) -> 60 | U14: =ROUNDDOWN(YEARFRAC($E14,$G14,3),0) -> 54 | V14: =YEARFRAC($G14,Analysis_Date,3) -> 5.6136986 | W14: =MAX(ROUNDDOWN(NRA-T14,0),0) -> 0 | X14: =L14*W14 -> 0 | Y14: =IF($D14=$C$1,VLOOKUP($T14,Mortality_Table,3,FALSE),VLOOKUP($T14,Mortality_Table,2,FALSE)) -> 0.00855 | Z14: =IF($D14=$C$1,VLOOKUP($T14,Male_Annuity_Tables,MATCH($W14+2,'Mortality Tables'!$DS$1:$HT$1,0),FALSE),VLOOKUP($T14,Fe_Annuity_Tables,MATCH($W14+2,'Mortality Tables'!$M$1:$DN$1,0),FALSE)) -> 1 | AB14: =IFERROR(IF($W14>=AB$3,($H14*(1+Ann_Salary_Growth_Rate)^AB$3),""),0) | AC14: =IFERROR(IF($W14>=AC$3,($H14*(1+Ann_Salary_Growth_Rate)^AC$3),""),0) | AD14: =IFERROR(IF($W14>=AD$3,($H14*(1+Ann_Salary_Growth_Rate)^AD$3),""),0) | AE14: =IFERROR(IF($W14>=AE$3,($H14*(1+Ann_Salary_Growth_Rate)^AE$3),""),0) | AF14: =IFERROR(IF($W14>=AF$3,($H14*(1+Ann_Salary_Growth_Rate)^AF$3),""),0) | AG14: =IFERROR(IF($W14>=AG$3,($H14*(1+Ann_Salary_Growth_Rate)^AG$3),""),0) | AH14: =IFERROR(IF($W14>=AH$3,($H14*(1+Ann_Salary_Growth_Rate)^AH$3),""),0) | AI14: =IFERROR(IF($W14>=AI$3,($H14*(1+Ann_Salary_Growth_Rate)^AI$3),""),0) | ... BQ14: =IFERROR(IF($W14>=BQ$3,($H14*(1+Ann_Salary_Growth_Rate)^BQ$3),""),0) | BS14: =IFERROR(($L14+AB14*Contr_Rate)*(1+Inv_Return)*IF($D14=$C$1,VLOOKUP($T14,Male_Annuity_Tables,MATCH($BS$3+3,'Mortality Tables'!$N$1:$DN$1,0),FALSE),VLOOKUP($T14,Fe_Annuity_Tables,MATCH(BS$3+3,'Mortality Tables'!$N$1:$DN$1,0),FALSE)),"") | BT14: =IFERROR(($BS14+AC14*Contr_Rate)*(1+Inv_Return)*IF($D14=$C$1,VLOOKUP($T14,Male_Annuity_Tables,MATCH($BS$3+3,'Mortality Tables'!$N$1:$DN$1,0),FALSE),VLOOKUP($T14,Fe_Annuity_Tables,MATCH(BT$3+3,'Mortality Tables'!$N$1:$DN$1,0),FALSE)),"") | BU14: =IFERROR((BT14+AD14*Contr_Rate)*(1+Inv_Return)*IF($D14=$C$1,VLOOKUP($T14,Male_Annuity_Tables,MATCH($BS$3+3,'Mortality Tables'!$N$1:$DN$1,0),FALSE),VLOOKUP($T14,Fe_Annuity_Tables,MATCH(BU$3+3,'Mortality Tables'!$N$1:$DN$1,0),FALSE)),"") | BV14: =IFERROR((BU14+AE14*Contr_Rate)*(1+Inv_Return)*IF($D14=$C$1,VLOOKUP($T14,Male_Annuity_Tables,MATCH($BS$3+3,'Mortality Tables'!$N$1:$DN$1,0),FALSE),VLOOKUP($T14,Fe_Annuity_Tables,MATCH(BV$3+3,'Mortality Tables'!$N$1:$DN$1,0),FALSE)),"") | BW14: =IFERROR((BV14+AF14*Contr_Rate)*(1+Inv_Return)*IF($D14=$C$1,VLOOKUP($T14,Male_Annuity_Tables,MATCH($BS$3+3,'Mortality Tables'!$N$1:$DN$1,0),FALSE),VLOOKUP($T14,Fe_Annuity_Tables,MATCH(BW$3+3,'Mortality Tables'!$N$1:$DN$1,0),FALSE)),"") | BX14: =IFERROR((BW14+AG14*Contr_Rate)*(1+Inv_Return)*IF($D14=$C$1,VLOOKUP($T14,Male_Annuity_Tables,MATCH($BS$3+3,'Mortality Tables'!$N$1:$DN$1,0),FALSE),VLOOKUP($T14,Fe_Annuity_Tables,MATCH(BX$3+3,'Mortality Tables'!$N$1:$DN$1,0),FALSE)),"") | BY14: =IFERROR((BX14+AH14*Contr_Rate)*(1+Inv_Return)*IF($D14=$C$1,VLOOKUP($T14,Male_Annuity_Tables,MATCH($BS$3+3,'Mortality Tables'!$N$1:$DN$1,0),FALSE),VLOOKUP($T14,Fe_Annuity_Tables,MATCH(BY$3+3,'Mortality Tables'!$N$1:$DN$1,0),FALSE)),"") | BZ14: =IFERROR((BY14+AI14*Contr_Rate)*(1+Inv_Return)*IF($D14=$C$1,VLOOKUP($T14,Male_Annuity_Tables,MATCH($BS$3+3,'Mortality Tables'!$N$1:$DN$1,0),FALSE),VLOOKUP($T14,Fe_Annuity_Tables,MATCH(BZ$3+3,'Mortality Tables'!$N$1:$DN$1,0),FALSE)),"") | CA14: =IFERROR((BZ14+AJ14*Contr_Rate)*(1+Inv_Return)*IF($D14=$C$1,VLOOKUP($T14,Male_Annuity_Tables,MATCH($BS$3+3,'Mortality Tables'!$N$1:$DN$1,0),FALSE),VLOOKUP($T14,Fe_Annuity_Tables,MATCH(CA$3+3,'Mortality Tables'!$N$1:$DN$1,0),FALSE)),"") | CB14: =IFERROR((CA14+AK14*Contr_Rate)*(1+Inv_Return)*IF($D14=$C$1,VLOOKUP($T14,Male_Annuity_Tables,MATCH($BS$3+3,'Mortality Tables'!$N$1:$DN$1,0),FALSE),VLOOKUP($T14,Fe_Annuity_Tables,MATCH(CB$3+3,'Mortality Tables'!$N$1:$DN$1,0),FALSE)),"") | ... DH14: =IFERROR((DG14+BQ14*Contr_Rate)*(1+Inv_Return)*IF($D14=$C$1,VLOOKUP($T14,Male_Annuity_Tables,MATCH($BS$3+3,'Mortality Tables'!$N$1:$DN$1,0),FALSE),VLOOKUP($T14,Fe_Annuity_Tables,MATCH(DH$3+3,'Mortality Tables'!$N$1:$DN$1,0),FALSE)),"") | DJ14: =MAX(BS14:DH14) -> 0 | DK14: =IF($D14="FEMALE",Fe_Annuity_Factor,Male_Annuity_Factor) -> 8.8017766 | DL14: =(DJ14*Annuity_Ratio)/DK14 -> 0 | DM14: =MAX($AB14:$BQ14) -> 0 | DN14: =IFERROR((DL14/DM14),"") | DP14: =IFERROR(IF($D14=$C$1,VLOOKUP($T14+DP$3-1,Male_Annuity_Tables,2,FALSE),VLOOKUP($T14,Fe_Annuity_Tables,2,FALSE))*BS14,"") | DQ14: =IFERROR(IF($D14=$C$1,VLOOKUP($T14+DQ$3-1,Male_Annuity_Tables,2,FALSE),VLOOKUP($T14,Fe_Annuity_Tables,2,FALSE))*BT14,"") | DR14: =IFERROR(IF($D14=$C$1,VLOOKUP($T14+DR$3-1,Male_Annuity_Tables,2,FALSE),VLOOKUP($T14,Fe_Annuity_Tables,2,FALSE))*BU14,"")
A15: M0012 | B15: Danielle Ford | C15: Deferred | D15: Female | E15: 28534 | F15: 42927 | G15: 45065 | H15: 1191820 | I15: 98649.25 | J15: 83167.1 | K15: 25648.33 | L15: 207464.68 | M15: =IF(COUNTIF($A$4:A204,A15)=1,0,1) -> 0 | N15: =IF(T15<=18,"WHAT!!!",IF(T15>100,"EERM","Okay")) -> Okay | O15: =IF(G15>E15,"TRUE","FALSE") -> TRUE | P15: =G15>=Comm_Date -> TRUE | Q15: =$G15>=$F15 -> TRUE | R15: =$F15>$E15 -> TRUE | S15: =YEARFRAC(E15,F15,3) -> 39.432877 | T15: =ROUNDDOWN(YEARFRAC($E15,Analysis_Date,3),0) -> 46 | U15: =ROUNDDOWN(YEARFRAC($E15,$G15,3),0) -> 45 | V15: =YEARFRAC($G15,Analysis_Date,3) -> 1.6191781 | W15: =MAX(ROUNDDOWN(NRA-T15,0),0) -> 14 | X15: =L15*W15 -> 2904505.5 | Y15: =IF($D15=$C$1,VLOOKUP($T15,Mortality_Table,3,FALSE),VLOOKUP($T15,Mortality_Table,2,FALSE)) -> 0.0028 | Z15: =IF($D15=$C$1,VLOOKUP($T15,Male_Annuity_Tables,MATCH($W15+2,'Mortality Tables'!$DS$1:$HT$1,0),FALSE),VLOOKUP($T15,Fe_Annuity_Tables,MATCH($W15+2,'Mortality Tables'!$M$1:$DN$1,0),FALSE)) -> 0.2228972 | AB15: =IFERROR(IF($W15>=AB$3,($H15*(1+Ann_Salary_Growth_Rate)^AB$3),""),0) -> 1252543.2 | AC15: =IFERROR(IF($W15>=AC$3,($H15*(1+Ann_Salary_Growth_Rate)^AC$3),""),0) -> 1316360.3 | AD15: =IFERROR(IF($W15>=AD$3,($H15*(1+Ann_Salary_Growth_Rate)^AD$3),""),0) -> 1383428.9 | AE15: =IFERROR(IF($W15>=AE$3,($H15*(1+Ann_Salary_Growth_Rate)^AE$3),""),0) -> 1453914.6 | AF15: =IFERROR(IF($W15>=AF$3,($H15*(1+Ann_Salary_Growth_Rate)^AF$3),""),0) -> 1527991.5 | AG15: =IFERROR(IF($W15>=AG$3,($H15*(1+Ann_Salary_Growth_Rate)^AG$3),""),0) -> 1605842.7 | AH15: =IFERROR(IF($W15>=AH$3,($H15*(1+Ann_Salary_Growth_Rate)^AH$3),""),0) -> 1687660.4 | AI15: =IFERROR(IF($W15>=AI$3,($H15*(1+Ann_Salary_Growth_Rate)^AI$3),""),0) -> 1773646.7 | ... BQ15: =IFERROR(IF($W15>=BQ$3,($H15*(1+Ann_Salary_Growth_Rate)^BQ$3),""),0) | BS15: =IFERROR(($L15+AB15*Contr_Rate)*(1+Inv_Return)*IF($D15=$C$1,VLOOKUP($T15,Male_Annuity_Tables,MATCH($BS$3+3,'Mortality Tables'!$N$1:$DN$1,0),FALSE),VLOOKUP($T15,Fe_Annuity_Tables,MATCH(BS$3+3,'Mortality Tables'!$N$1:$DN$1,0),FALSE)),"") -> 508021.54 | BT15: =IFERROR(($BS15+AC15*Contr_Rate)*(1+Inv_Return)*IF($D15=$C$1,VLOOKUP($T15,Male_Annuity_Tables,MATCH($BS$3+3,'Mortality Tables'!$N$1:$DN$1,0),FALSE),VLOOKUP($T15,Fe_Annuity_Tables,MATCH(BT$3+3,'Mortality Tables'!$N$1:$DN$1,0),FALSE)),"") -> 666504.83 | BU15: =IFERROR((BT15+AD15*Contr_Rate)*(1+Inv_Return)*IF($D15=$C$1,VLOOKUP($T15,Male_Annuity_Tables,MATCH($BS$3+3,'Mortality Tables'!$N$1:$DN$1,0),FALSE),VLOOKUP($T15,Fe_Annuity_Tables,MATCH(BU$3+3,'Mortality Tables'!$N$1:$DN$1,0),FALSE)),"") -> 676392.67 | BV15: =IFERROR((BU15+AE15*Contr_Rate)*(1+Inv_Return)*IF($D15=$C$1,VLOOKUP($T15,Male_Annuity_Tables,MATCH($BS$3+3,'Mortality Tables'!$N$1:$DN$1,0),FALSE),VLOOKUP($T15,Fe_Annuity_Tables,MATCH(BV$3+3,'Mortality Tables'!$N$1:$DN$1,0),FALSE)),"") -> 589372.76 | BW15: =IFERROR((BV15+AF15*Contr_Rate)*(1+Inv_Return)*IF($D15=$C$1,VLOOKUP($T15,Male_Annuity_Tables,MATCH($BS$3+3,'Mortality Tables'!$N$1:$DN$1,0),FALSE),VLOOKUP($T15,Fe_Annuity_Tables,MATCH(BW$3+3,'Mortality Tables'!$N$1:$DN$1,0),FALSE)),"") -> 497664.2 | BX15: =IFERROR((BW15+AG15*Contr_Rate)*(1+Inv_Return)*IF($D15=$C$1,VLOOKUP($T15,Male_Annuity_Tables,MATCH($BS$3+3,'Mortality Tables'!$N$1:$DN$1,0),FALSE),VLOOKUP($T15,Fe_Annuity_Tables,MATCH(BX$3+3,'Mortality Tables'!$N$1:$DN$1,0),FALSE)),"") -> 416982.7 | BY15: =IFERROR((BX15+AH15*Contr_Rate)*(1+Inv_Return)*IF($D15=$C$1,VLOOKUP($T15,Male_Annuity_Tables,MATCH($BS$3+3,'Mortality Tables'!$N$1:$DN$1,0),FALSE),VLOOKUP($T15,Fe_Annuity_Tables,MATCH(BY$3+3,'Mortality Tables'!$N$1:$DN$1,0),FALSE)),"") -> 352228.66 | BZ15: =IFERROR((BY15+AI15*Contr_Rate)*(1+Inv_Return)*IF($D15=$C$1,VLOOKUP($T15,Male_Annuity_Tables,MATCH($BS$3+3,'Mortality Tables'!$N$1:$DN$1,0),FALSE),VLOOKUP($T15,Fe_Annuity_Tables,MATCH(BZ$3+3,'Mortality Tables'!$N$1:$DN$1,0),FALSE)),"") -> 302196.49 | CA15: =IFERROR((BZ15+AJ15*Contr_Rate)*(1+Inv_Return)*IF($D15=$C$1,VLOOKUP($T15,Male_Annuity_Tables,MATCH($BS$3+3,'Mortality Tables'!$N$1:$DN$1,0),FALSE),VLOOKUP($T15,Fe_Annuity_Tables,MATCH(CA$3+3,'Mortality Tables'!$N$1:$DN$1,0),FALSE)),"") -> 263575.97 | CB15: =IFERROR((CA15+AK15*Contr_Rate)*(1+Inv_Return)*IF($D15=$C$1,VLOOKUP($T15,Male_Annuity_Tables,MATCH($BS$3+3,'Mortality Tables'!$N$1:$DN$1,0),FALSE),VLOOKUP($T15,Fe_Annuity_Tables,MATCH(CB$3+3,'Mortality Tables'!$N$1:$DN$1,0),FALSE)),"") -> 246084.38 | ... DH15: =IFERROR((DG15+BQ15*Contr_Rate)*(1+Inv_Return)*IF($D15=$C$1,VLOOKUP($T15,Male_Annuity_Tables,MATCH($BS$3+3,'Mortality Tables'!$N$1:$DN$1,0),FALSE),VLOOKUP($T15,Fe_Annuity_Tables,MATCH(DH$3+3,'Mortality Tables'!$N$1:$DN$1,0),FALSE)),"") | DJ15: =MAX(BS15:DH15) -> 676392.67 | DK15: =IF($D15="FEMALE",Fe_Annuity_Factor,Male_Annuity_Factor) -> 8.8017766 | DL15: =(DJ15*Annuity_Ratio)/DK15 -> 51487.684 | DM15: =MAX($AB15:$BQ15) -> 2389788.3 | DN15: =IFERROR((DL15/DM15),"") -> 0.021544872 | DP15: =IFERROR(IF($D15=$C$1,VLOOKUP($T15+DP$3-1,Male_Annuity_Tables,2,FALSE),VLOOKUP($T15,Fe_Annuity_Tables,2,FALSE))*BS15,"") -> 77412.322 | DQ15: =IFERROR(IF($D15=$C$1,VLOOKUP($T15+DQ$3-1,Male_Annuity_Tables,2,FALSE),VLOOKUP($T15,Fe_Annuity_Tables,2,FALSE))*BT15,"") -> 101562.01 | DR15: =IFERROR(IF($D15=$C$1,VLOOKUP($T15+DR$3-1,Male_Annuity_Tables,2,FALSE),VLOOKUP($T15,Fe_Annuity_Tables,2,FALSE))*BU15,"") -> 103068.72
A16: M0013 | B16: Melinda Cameron | C16: Dormant | D16: Male | E16: 23215 | F16: 37820 | G16: 38218 | H16: 1334430 | I16: 116428.28 | J16: 102682.87 | K16: 24279.52 | L16: 243390.67 | M16: =IF(COUNTIF($A$4:A204,A16)=1,0,1) -> 0 | N16: =IF(T16<=18,"WHAT!!!",IF(T16>100,"EERM","Okay")) -> Okay | O16: =IF(G16>E16,"TRUE","FALSE") -> TRUE | P16: =G16>=Comm_Date -> TRUE | Q16: =$G16>=$F16 -> TRUE | R16: =$F16>$E16 -> TRUE | S16: =YEARFRAC(E16,F16,3) -> 40.013699 | T16: =ROUNDDOWN(YEARFRAC($E16,Analysis_Date,3),0) -> 61 | U16: =ROUNDDOWN(YEARFRAC($E16,$G16,3),0) -> 41 | V16: =YEARFRAC($G16,Analysis_Date,3) -> 20.378082 | W16: =MAX(ROUNDDOWN(NRA-T16,0),0) -> 0 | X16: =L16*W16 -> 0 | Y16: =IF($D16=$C$1,VLOOKUP($T16,Mortality_Table,3,FALSE),VLOOKUP($T16,Mortality_Table,2,FALSE)) -> 0.01546 | Z16: =IF($D16=$C$1,VLOOKUP($T16,Male_Annuity_Tables,MATCH($W16+2,'Mortality Tables'!$DS$1:$HT$1,0),FALSE),VLOOKUP($T16,Fe_Annuity_Tables,MATCH($W16+2,'Mortality Tables'!$M$1:$DN$1,0),FALSE)) -> 1 | AB16: =IFERROR(IF($W16>=AB$3,($H16*(1+Ann_Salary_Growth_Rate)^AB$3),""),0) | AC16: =IFERROR(IF($W16>=AC$3,($H16*(1+Ann_Salary_Growth_Rate)^AC$3),""),0) | AD16: =IFERROR(IF($W16>=AD$3,($H16*(1+Ann_Salary_Growth_Rate)^AD$3),""),0) | AE16: =IFERROR(IF($W16>=AE$3,($H16*(1+Ann_Salary_Growth_Rate)^AE$3),""),0) | AF16: =IFERROR(IF($W16>=AF$3,($H16*(1+Ann_Salary_Growth_Rate)^AF$3),""),0) | AG16: =IFERROR(IF($W16>=AG$3,($H16*(1+Ann_Salary_Growth_Rate)^AG$3),""),0) | AH16: =IFERROR(IF($W16>=AH$3,($H16*(1+Ann_Salary_Growth_Rate)^AH$3),""),0) | AI16: =IFERROR(IF($W16>=AI$3,($H16*(1+Ann_Salary_Growth_Rate)^AI$3),""),0) | ... BQ16: =IFERROR(IF($W16>=BQ$3,($H16*(1+Ann_Salary_Growth_Rate)^BQ$3),""),0) | BS16: =IFERROR(($L16+AB16*Contr_Rate)*(1+Inv_Return)*IF($D16=$C$1,VLOOKUP($T16,Male_Annuity_Tables,MATCH($BS$3+3,'Mortality Tables'!$N$1:$DN$1,0),FALSE),VLOOKUP($T16,Fe_Annuity_Tables,MATCH(BS$3+3,'Mortality Tables'!$N$1:$DN$1,0),FALSE)),"") | BT16: =IFERROR(($BS16+AC16*Contr_Rate)*(1+Inv_Return)*IF($D16=$C$1,VLOOKUP($T16,Male_Annuity_Tables,MATCH($BS$3+3,'Mortality Tables'!$N$1:$DN$1,0),FALSE),VLOOKUP($T16,Fe_Annuity_Tables,MATCH(BT$3+3,'Mortality Tables'!$N$1:$DN$1,0),FALSE)),"") | BU16: =IFERROR((BT16+AD16*Contr_Rate)*(1+Inv_Return)*IF($D16=$C$1,VLOOKUP($T16,Male_Annuity_Tables,MATCH($BS$3+3,'Mortality Tables'!$N$1:$DN$1,0),FALSE),VLOOKUP($T16,Fe_Annuity_Tables,MATCH(BU$3+3,'Mortality Tables'!$N$1:$DN$1,0),FALSE)),"") | BV16: =IFERROR((BU16+AE16*Contr_Rate)*(1+Inv_Return)*IF($D16=$C$1,VLOOKUP($T16,Male_Annuity_Tables,MATCH($BS$3+3,'Mortality Tables'!$N$1:$DN$1,0),FALSE),VLOOKUP($T16,Fe_Annuity_Tables,MATCH(BV$3+3,'Mortality Tables'!$N$1:$DN$1,0),FALSE)),"") | BW16: =IFERROR((BV16+AF16*Contr_Rate)*(1+Inv_Return)*IF($D16=$C$1,VLOOKUP($T16,Male_Annuity_Tables,MATCH($BS$3+3,'Mortality Tables'!$N$1:$DN$1,0),FALSE),VLOOKUP($T16,Fe_Annuity_Tables,MATCH(BW$3+3,'Mortality Tables'!$N$1:$DN$1,0),FALSE)),"") | BX16: =IFERROR((BW16+AG16*Contr_Rate)*(1+Inv_Return)*IF($D16=$C$1,VLOOKUP($T16,Male_Annuity_Tables,MATCH($BS$3+3,'Mortality Tables'!$N$1:$DN$1,0),FALSE),VLOOKUP($T16,Fe_Annuity_Tables,MATCH(BX$3+3,'Mortality Tables'!$N$1:$DN$1,0),FALSE)),"") | BY16: =IFERROR((BX16+AH16*Contr_Rate)*(1+Inv_Return)*IF($D16=$C$1,VLOOKUP($T16,Male_Annuity_Tables,MATCH($BS$3+3,'Mortality Tables'!$N$1:$DN$1,0),FALSE),VLOOKUP($T16,Fe_Annuity_Tables,MATCH(BY$3+3,'Mortality Tables'!$N$1:$DN$1,0),FALSE)),"") | BZ16: =IFERROR((BY16+AI16*Contr_Rate)*(1+Inv_Return)*IF($D16=$C$1,VLOOKUP($T16,Male_Annuity_Tables,MATCH($BS$3+3,'Mortality Tables'!$N$1:$DN$1,0),FALSE),VLOOKUP($T16,Fe_Annuity_Tables,MATCH(BZ$3+3,'Mortality Tables'!$N$1:$DN$1,0),FALSE)),"") | CA16: =IFERROR((BZ16+AJ16*Contr_Rate)*(1+Inv_Return)*IF($D16=$C$1,VLOOKUP($T16,Male_Annuity_Tables,MATCH($BS$3+3,'Mortality Tables'!$N$1:$DN$1,0),FALSE),VLOOKUP($T16,Fe_Annuity_Tables,MATCH(CA$3+3,'Mortality Tables'!$N$1:$DN$1,0),FALSE)),"") | CB16: =IFERROR((CA16+AK16*Contr_Rate)*(1+Inv_Return)*IF($D16=$C$1,VLOOKUP($T16,Male_Annuity_Tables,MATCH($BS$3+3,'Mortality Tables'!$N$1:$DN$1,0),FALSE),VLOOKUP($T16,Fe_Annuity_Tables,MATCH(CB$3+3,'Mortality Tables'!$N$1:$DN$1,0),FALSE)),"") | ... DH16: =IFERROR((DG16+BQ16*Contr_Rate)*(1+Inv_Return)*IF($D16=$C$1,VLOOKUP($T16,Male_Annuity_Tables,MATCH($BS$3+3,'Mortality Tables'!$N$1:$DN$1,0),FALSE),VLOOKUP($T16,Fe_Annuity_Tables,MATCH(DH$3+3,'Mortality Tables'!$N$1:$DN$1,0),FALSE)),"") | DJ16: =MAX(BS16:DH16) -> 0 | DK16: =IF($D16="FEMALE",Fe_Annuity_Factor,Male_Annuity_Factor) -> 8.0909278 | DL16: =(DJ16*Annuity_Ratio)/DK16 -> 0 | DM16: =MAX($AB16:$BQ16) -> 0 | DN16: =IFERROR((DL16/DM16),"") | DP16: =IFERROR(IF($D16=$C$1,VLOOKUP($T16+DP$3-1,Male_Annuity_Tables,2,FALSE),VLOOKUP($T16,Fe_Annuity_Tables,2,FALSE))*BS16,"") | DQ16: =IFERROR(IF($D16=$C$1,VLOOKUP($T16+DQ$3-1,Male_Annuity_Tables,2,FALSE),VLOOKUP($T16,Fe_Annuity_Tables,2,FALSE))*BT16,"") | DR16: =IFERROR(IF($D16=$C$1,VLOOKUP($T16+DR$3-1,Male_Annuity_Tables,2,FALSE),VLOOKUP($T16,Fe_Annuity_Tables,2,FALSE))*BU16,"")
A17: M0014 | B17: Jennifer Jones | C17: Exited | D17: Female | E17: 35922 | F17: 43895 | G17: 44872 | H17: 1219897 | I17: 121826.59 | J17: 69432.37 | K17: 39010.2 | L17: 230269.16 | M17: =IF(COUNTIF($A$4:A204,A17)=1,0,1) -> 0 | N17: =IF(T17<=18,"WHAT!!!",IF(T17>100,"EERM","Okay")) -> Okay | O17: =IF(G17>E17,"TRUE","FALSE") -> TRUE | P17: =G17>=Comm_Date -> TRUE | Q17: =$G17>=$F17 -> TRUE | R17: =$F17>$E17 -> TRUE | S17: =YEARFRAC(E17,F17,3) -> 21.843836 | T17: =ROUNDDOWN(YEARFRAC($E17,Analysis_Date,3),0) -> 26 | U17: =ROUNDDOWN(YEARFRAC($E17,$G17,3),0) -> 24 | V17: =YEARFRAC($G17,Analysis_Date,3) -> 2.1479452 | W17: =MAX(ROUNDDOWN(NRA-T17,0),0) -> 34 | X17: =L17*W17 -> 7829151.4 | Y17: =IF($D17=$C$1,VLOOKUP($T17,Mortality_Table,3,FALSE),VLOOKUP($T17,Mortality_Table,2,FALSE)) -> 0.00124 | Z17: =IF($D17=$C$1,VLOOKUP($T17,Male_Annuity_Tables,MATCH($W17+2,'Mortality Tables'!$DS$1:$HT$1,0),FALSE),VLOOKUP($T17,Fe_Annuity_Tables,MATCH($W17+2,'Mortality Tables'!$M$1:$DN$1,0),FALSE)) -> 0.0035743278 | AB17: =IFERROR(IF($W17>=AB$3,($H17*(1+Ann_Salary_Growth_Rate)^AB$3),""),0) -> 1282050.8 | AC17: =IFERROR(IF($W17>=AC$3,($H17*(1+Ann_Salary_Growth_Rate)^AC$3),""),0) -> 1347371.2 | AD17: =IFERROR(IF($W17>=AD$3,($H17*(1+Ann_Salary_Growth_Rate)^AD$3),""),0) -> 1416019.8 | AE17: =IFERROR(IF($W17>=AE$3,($H17*(1+Ann_Salary_Growth_Rate)^AE$3),""),0) -> 1488166 | AF17: =IFERROR(IF($W17>=AF$3,($H17*(1+Ann_Salary_Growth_Rate)^AF$3),""),0) -> 1563988.1 | AG17: =IFERROR(IF($W17>=AG$3,($H17*(1+Ann_Salary_Growth_Rate)^AG$3),""),0) -> 1643673.3 | AH17: =IFERROR(IF($W17>=AH$3,($H17*(1+Ann_Salary_Growth_Rate)^AH$3),""),0) -> 1727418.4 | AI17: =IFERROR(IF($W17>=AI$3,($H17*(1+Ann_Salary_Growth_Rate)^AI$3),""),0) -> 1815430.4 | ... BQ17: =IFERROR(IF($W17>=BQ$3,($H17*(1+Ann_Salary_Growth_Rate)^BQ$3),""),0) | BS17: =IFERROR(($L17+AB17*Contr_Rate)*(1+Inv_Return)*IF($D17=$C$1,VLOOKUP($T17,Male_Annuity_Tables,MATCH($BS$3+3,'Mortality Tables'!$N$1:$DN$1,0),FALSE),VLOOKUP($T17,Fe_Annuity_Tables,MATCH(BS$3+3,'Mortality Tables'!$N$1:$DN$1,0),FALSE)),"") -> 504879.13 | BT17: =IFERROR(($BS17+AC17*Contr_Rate)*(1+Inv_Return)*IF($D17=$C$1,VLOOKUP($T17,Male_Annuity_Tables,MATCH($BS$3+3,'Mortality Tables'!$N$1:$DN$1,0),FALSE),VLOOKUP($T17,Fe_Annuity_Tables,MATCH(BT$3+3,'Mortality Tables'!$N$1:$DN$1,0),FALSE)),"") -> 596408.06 | BU17: =IFERROR((BT17+AD17*Contr_Rate)*(1+Inv_Return)*IF($D17=$C$1,VLOOKUP($T17,Male_Annuity_Tables,MATCH($BS$3+3,'Mortality Tables'!$N$1:$DN$1,0),FALSE),VLOOKUP($T17,Fe_Annuity_Tables,MATCH(BU$3+3,'Mortality Tables'!$N$1:$DN$1,0),FALSE)),"") -> 535287.23 | BV17: =IFERROR((BU17+AE17*Contr_Rate)*(1+Inv_Return)*IF($D17=$C$1,VLOOKUP($T17,Male_Annuity_Tables,MATCH($BS$3+3,'Mortality Tables'!$N$1:$DN$1,0),FALSE),VLOOKUP($T17,Fe_Annuity_Tables,MATCH(BV$3+3,'Mortality Tables'!$N$1:$DN$1,0),FALSE)),"") -> 411140.57 | BW17: =IFERROR((BV17+AF17*Contr_Rate)*(1+Inv_Return)*IF($D17=$C$1,VLOOKUP($T17,Male_Annuity_Tables,MATCH($BS$3+3,'Mortality Tables'!$N$1:$DN$1,0),FALSE),VLOOKUP($T17,Fe_Annuity_Tables,MATCH(BW$3+3,'Mortality Tables'!$N$1:$DN$1,0),FALSE)),"") -> 294550.96 | BX17: =IFERROR((BW17+AG17*Contr_Rate)*(1+Inv_Return)*IF($D17=$C$1,VLOOKUP($T17,Male_Annuity_Tables,MATCH($BS$3+3,'Mortality Tables'!$N$1:$DN$1,0),FALSE),VLOOKUP($T17,Fe_Annuity_Tables,MATCH(BX$3+3,'Mortality Tables'!$N$1:$DN$1,0),FALSE)),"") -> 210547.31 | BY17: =IFERROR((BX17+AH17*Contr_Rate)*(1+Inv_Return)*IF($D17=$C$1,VLOOKUP($T17,Male_Annuity_Tables,MATCH($BS$3+3,'Mortality Tables'!$N$1:$DN$1,0),FALSE),VLOOKUP($T17,Fe_Annuity_Tables,MATCH(BY$3+3,'Mortality Tables'!$N$1:$DN$1,0),FALSE)),"") -> 155631.4 | BZ17: =IFERROR((BY17+AI17*Contr_Rate)*(1+Inv_Return)*IF($D17=$C$1,VLOOKUP($T17,Male_Annuity_Tables,MATCH($BS$3+3,'Mortality Tables'!$N$1:$DN$1,0),FALSE),VLOOKUP($T17,Fe_Annuity_Tables,MATCH(BZ$3+3,'Mortality Tables'!$N$1:$DN$1,0),FALSE)),"") -> 119464.13 | CA17: =IFERROR((BZ17+AJ17*Contr_Rate)*(1+Inv_Return)*IF($D17=$C$1,VLOOKUP($T17,Male_Annuity_Tables,MATCH($BS$3+3,'Mortality Tables'!$N$1:$DN$1,0),FALSE),VLOOKUP($T17,Fe_Annuity_Tables,MATCH(CA$3+3,'Mortality Tables'!$N$1:$DN$1,0),FALSE)),"") -> 94283.561 | CB17: =IFERROR((CA17+AK17*Contr_Rate)*(1+Inv_Return)*IF($D17=$C$1,VLOOKUP($T17,Male_Annuity_Tables,MATCH($BS$3+3,'Mortality Tables'!$N$1:$DN$1,0),FALSE),VLOOKUP($T17,Fe_Annuity_Tables,MATCH(CB$3+3,'Mortality Tables'!$N$1:$DN$1,0),FALSE)),"") -> 75744.922 | ... DH17: =IFERROR((DG17+BQ17*Contr_Rate)*(1+Inv_Return)*IF($D17=$C$1,VLOOKUP($T17,Male_Annuity_Tables,MATCH($BS$3+3,'Mortality Tables'!$N$1:$DN$1,0),FALSE),VLOOKUP($T17,Fe_Annuity_Tables,MATCH(DH$3+3,'Mortality Tables'!$N$1:$DN$1,0),FALSE)),"") | DJ17: =MAX(BS17:DH17) -> 596408.06 | DK17: =IF($D17="FEMALE",Fe_Annuity_Factor,Male_Annuity_Factor) -> 8.8017766 | DL17: =(DJ17*Annuity_Ratio)/DK17 -> 45399.176 | DM17: =MAX($AB17:$BQ17) -> 6608654 | DN17: =IFERROR((DL17/DM17),"") -> 0.0068696554 | DP17: =IFERROR(IF($D17=$C$1,VLOOKUP($T17+DP$3-1,Male_Annuity_Tables,2,FALSE),VLOOKUP($T17,Fe_Annuity_Tables,2,FALSE))*BS17,"") -> 101476.67 | DQ17: =IFERROR(IF($D17=$C$1,VLOOKUP($T17+DQ$3-1,Male_Annuity_Tables,2,FALSE),VLOOKUP($T17,Fe_Annuity_Tables,2,FALSE))*BT17,"") -> 119873.25 | DR17: =IFERROR(IF($D17=$C$1,VLOOKUP($T17+DR$3-1,Male_Annuity_Tables,2,FALSE),VLOOKUP($T17,Fe_Annuity_Tables,2,FALSE))*BU17,"") -> 107588.45
A18: M0015 | B18: Jonathan Wilkerson | C18: Active | D18: Male | E18: 26655 | F18: 36749 | G18: 40040 | H18: 2931699 | I18: 170035.9 | J18: 246333.25 | K18: 22314.53 | L18: 438683.68 | M18: =IF(COUNTIF($A$4:A204,A18)=1,0,1) -> 0 | N18: =IF(T18<=18,"WHAT!!!",IF(T18>100,"EERM","Okay")) -> Okay | O18: =IF(G18>E18,"TRUE","FALSE") -> TRUE | P18: =G18>=Comm_Date -> TRUE | Q18: =$G18>=$F18 -> TRUE | R18: =$F18>$E18 -> TRUE | S18: =YEARFRAC(E18,F18,3) -> 27.654795 | T18: =ROUNDDOWN(YEARFRAC($E18,Analysis_Date,3),0) -> 52 | U18: =ROUNDDOWN(YEARFRAC($E18,$G18,3),0) -> 36 | V18: =YEARFRAC($G18,Analysis_Date,3) -> 15.386301 | W18: =MAX(ROUNDDOWN(NRA-T18,0),0) -> 8 | X18: =L18*W18 -> 3509469.4 | Y18: =IF($D18=$C$1,VLOOKUP($T18,Mortality_Table,3,FALSE),VLOOKUP($T18,Mortality_Table,2,FALSE)) -> 0.00659 | Z18: =IF($D18=$C$1,VLOOKUP($T18,Male_Annuity_Tables,MATCH($W18+2,'Mortality Tables'!$DS$1:$HT$1,0),FALSE),VLOOKUP($T18,Fe_Annuity_Tables,MATCH($W18+2,'Mortality Tables'!$M$1:$DN$1,0),FALSE)) -> 0.52324993 | AB18: =IFERROR(IF($W18>=AB$3,($H18*(1+Ann_Salary_Growth_Rate)^AB$3),""),0) -> 3081069.1 | AC18: =IFERROR(IF($W18>=AC$3,($H18*(1+Ann_Salary_Growth_Rate)^AC$3),""),0) -> 3238049.5 | AD18: =IFERROR(IF($W18>=AD$3,($H18*(1+Ann_Salary_Growth_Rate)^AD$3),""),0) -> 3403028.2 | AE18: =IFERROR(IF($W18>=AE$3,($H18*(1+Ann_Salary_Growth_Rate)^AE$3),""),0) -> 3576412.4 | AF18: =IFERROR(IF($W18>=AF$3,($H18*(1+Ann_Salary_Growth_Rate)^AF$3),""),0) -> 3758630.7 | AG18: =IFERROR(IF($W18>=AG$3,($H18*(1+Ann_Salary_Growth_Rate)^AG$3),""),0) -> 3950132.9 | AH18: =IFERROR(IF($W18>=AH$3,($H18*(1+Ann_Salary_Growth_Rate)^AH$3),""),0) -> 4151392.2 | AI18: =IFERROR(IF($W18>=AI$3,($H18*(1+Ann_Salary_Growth_Rate)^AI$3),""),0) -> 4362905.6 | ... BQ18: =IFERROR(IF($W18>=BQ$3,($H18*(1+Ann_Salary_Growth_Rate)^BQ$3),""),0) | BS18: =IFERROR(($L18+AB18*Contr_Rate)*(1+Inv_Return)*IF($D18=$C$1,VLOOKUP($T18,Male_Annuity_Tables,MATCH($BS$3+3,'Mortality Tables'!$N$1:$DN$1,0),FALSE),VLOOKUP($T18,Fe_Annuity_Tables,MATCH(BS$3+3,'Mortality Tables'!$N$1:$DN$1,0),FALSE)),"") -> 1252307.9 | BT18: =IFERROR(($BS18+AC18*Contr_Rate)*(1+Inv_Return)*IF($D18=$C$1,VLOOKUP($T18,Male_Annuity_Tables,MATCH($BS$3+3,'Mortality Tables'!$N$1:$DN$1,0),FALSE),VLOOKUP($T18,Fe_Annuity_Tables,MATCH(BT$3+3,'Mortality Tables'!$N$1:$DN$1,0),FALSE)),"") -> 2043123 | BU18: =IFERROR((BT18+AD18*Contr_Rate)*(1+Inv_Return)*IF($D18=$C$1,VLOOKUP($T18,Male_Annuity_Tables,MATCH($BS$3+3,'Mortality Tables'!$N$1:$DN$1,0),FALSE),VLOOKUP($T18,Fe_Annuity_Tables,MATCH(BU$3+3,'Mortality Tables'!$N$1:$DN$1,0),FALSE)),"") -> 2815185.9 | BV18: =IFERROR((BU18+AE18*Contr_Rate)*(1+Inv_Return)*IF($D18=$C$1,VLOOKUP($T18,Male_Annuity_Tables,MATCH($BS$3+3,'Mortality Tables'!$N$1:$DN$1,0),FALSE),VLOOKUP($T18,Fe_Annuity_Tables,MATCH(BV$3+3,'Mortality Tables'!$N$1:$DN$1,0),FALSE)),"") -> 3572336.6 | BW18: =IFERROR((BV18+AF18*Contr_Rate)*(1+Inv_Return)*IF($D18=$C$1,VLOOKUP($T18,Male_Annuity_Tables,MATCH($BS$3+3,'Mortality Tables'!$N$1:$DN$1,0),FALSE),VLOOKUP($T18,Fe_Annuity_Tables,MATCH(BW$3+3,'Mortality Tables'!$N$1:$DN$1,0),FALSE)),"") -> 4318221 | BX18: =IFERROR((BW18+AG18*Contr_Rate)*(1+Inv_Return)*IF($D18=$C$1,VLOOKUP($T18,Male_Annuity_Tables,MATCH($BS$3+3,'Mortality Tables'!$N$1:$DN$1,0),FALSE),VLOOKUP($T18,Fe_Annuity_Tables,MATCH(BX$3+3,'Mortality Tables'!$N$1:$DN$1,0),FALSE)),"") -> 5056313.1 | BY18: =IFERROR((BX18+AH18*Contr_Rate)*(1+Inv_Return)*IF($D18=$C$1,VLOOKUP($T18,Male_Annuity_Tables,MATCH($BS$3+3,'Mortality Tables'!$N$1:$DN$1,0),FALSE),VLOOKUP($T18,Fe_Annuity_Tables,MATCH(BY$3+3,'Mortality Tables'!$N$1:$DN$1,0),FALSE)),"") -> 5789935.3 | BZ18: =IFERROR((BY18+AI18*Contr_Rate)*(1+Inv_Return)*IF($D18=$C$1,VLOOKUP($T18,Male_Annuity_Tables,MATCH($BS$3+3,'Mortality Tables'!$N$1:$DN$1,0),FALSE),VLOOKUP($T18,Fe_Annuity_Tables,MATCH(BZ$3+3,'Mortality Tables'!$N$1:$DN$1,0),FALSE)),"") -> 6522276.9 | CA18: =IFERROR((BZ18+AJ18*Contr_Rate)*(1+Inv_Return)*IF($D18=$C$1,VLOOKUP($T18,Male_Annuity_Tables,MATCH($BS$3+3,'Mortality Tables'!$N$1:$DN$1,0),FALSE),VLOOKUP($T18,Fe_Annuity_Tables,MATCH(CA$3+3,'Mortality Tables'!$N$1:$DN$1,0),FALSE)),"") | CB18: =IFERROR((CA18+AK18*Contr_Rate)*(1+Inv_Return)*IF($D18=$C$1,VLOOKUP($T18,Male_Annuity_Tables,MATCH($BS$3+3,'Mortality Tables'!$N$1:$DN$1,0),FALSE),VLOOKUP($T18,Fe_Annuity_Tables,MATCH(CB$3+3,'Mortality Tables'!$N$1:$DN$1,0),FALSE)),"") | ... DH18: =IFERROR((DG18+BQ18*Contr_Rate)*(1+Inv_Return)*IF($D18=$C$1,VLOOKUP($T18,Male_Annuity_Tables,MATCH($BS$3+3,'Mortality Tables'!$N$1:$DN$1,0),FALSE),VLOOKUP($T18,Fe_Annuity_Tables,MATCH(DH$3+3,'Mortality Tables'!$N$1:$DN$1,0),FALSE)),"") | DJ18: =MAX(BS18:DH18) -> 6522276.9 | DK18: =IF($D18="FEMALE",Fe_Annuity_Factor,Male_Annuity_Factor) -> 8.0909278 | DL18: =(DJ18*Annuity_Ratio)/DK18 -> 540101.91 | DM18: =MAX($AB18:$BQ18) -> 4362905.6 | DN18: =IFERROR((DL18/DM18),"") -> 0.12379409 | DP18: =IFERROR(IF($D18=$C$1,VLOOKUP($T18+DP$3-1,Male_Annuity_Tables,2,FALSE),VLOOKUP($T18,Fe_Annuity_Tables,2,FALSE))*BS18,"") -> 132658.23 | DQ18: =IFERROR(IF($D18=$C$1,VLOOKUP($T18+DQ$3-1,Male_Annuity_Tables,2,FALSE),VLOOKUP($T18,Fe_Annuity_Tables,2,FALSE))*BT18,"") -> 217625.29 | DR18: =IFERROR(IF($D18=$C$1,VLOOKUP($T18+DR$3-1,Male_Annuity_Tables,2,FALSE),VLOOKUP($T18,Fe_Annuity_Tables,2,FALSE))*BU18,"") -> 301610.57
A19: M0016 | B19: Patrick Ryan | C19: Exited | D19: Female | E19: 29780 | F19: 40298 | G19: 43923 | H19: 2620397 | I19: 243799.08 | J19: 132524.09 | K19: 35676.97 | L19: 412000.14 | M19: =IF(COUNTIF($A$4:A204,A19)=1,0,1) -> 0 | N19: =IF(T19<=18,"WHAT!!!",IF(T19>100,"EERM","Okay")) -> Okay | O19: =IF(G19>E19,"TRUE","FALSE") -> TRUE | P19: =G19>=Comm_Date -> TRUE | Q19: =$G19>=$F19 -> TRUE | R19: =$F19>$E19 -> TRUE | S19: =YEARFRAC(E19,F19,3) -> 28.816438 | T19: =ROUNDDOWN(YEARFRAC($E19,Analysis_Date,3),0) -> 43 | U19: =ROUNDDOWN(YEARFRAC($E19,$G19,3),0) -> 38 | V19: =YEARFRAC($G19,Analysis_Date,3) -> 4.7479452 | W19: =MAX(ROUNDDOWN(NRA-T19,0),0) -> 17 | X19: =L19*W19 -> 7004002.4 | Y19: =IF($D19=$C$1,VLOOKUP($T19,Mortality_Table,3,FALSE),VLOOKUP($T19,Mortality_Table,2,FALSE)) -> 0.00229 | Z19: =IF($D19=$C$1,VLOOKUP($T19,Male_Annuity_Tables,MATCH($W19+2,'Mortality Tables'!$DS$1:$HT$1,0),FALSE),VLOOKUP($T19,Fe_Annuity_Tables,MATCH($W19+2,'Mortality Tables'!$M$1:$DN$1,0),FALSE)) -> 0.13588309 | AB19: =IFERROR(IF($W19>=AB$3,($H19*(1+Ann_Salary_Growth_Rate)^AB$3),""),0) -> 2753906.2 | AC19: =IFERROR(IF($W19>=AC$3,($H19*(1+Ann_Salary_Growth_Rate)^AC$3),""),0) -> 2894217.7 | AD19: =IFERROR(IF($W19>=AD$3,($H19*(1+Ann_Salary_Growth_Rate)^AD$3),""),0) -> 3041678.1 | AE19: =IFERROR(IF($W19>=AE$3,($H19*(1+Ann_Salary_Growth_Rate)^AE$3),""),0) -> 3196651.6 | AF19: =IFERROR(IF($W19>=AF$3,($H19*(1+Ann_Salary_Growth_Rate)^AF$3),""),0) -> 3359521 | AG19: =IFERROR(IF($W19>=AG$3,($H19*(1+Ann_Salary_Growth_Rate)^AG$3),""),0) -> 3530688.6 | AH19: =IFERROR(IF($W19>=AH$3,($H19*(1+Ann_Salary_Growth_Rate)^AH$3),""),0) -> 3710577.2 | AI19: =IFERROR(IF($W19>=AI$3,($H19*(1+Ann_Salary_Growth_Rate)^AI$3),""),0) -> 3899631.1 | ... BQ19: =IFERROR(IF($W19>=BQ$3,($H19*(1+Ann_Salary_Growth_Rate)^BQ$3),""),0) | BS19: =IFERROR(($L19+AB19*Contr_Rate)*(1+Inv_Return)*IF($D19=$C$1,VLOOKUP($T19,Male_Annuity_Tables,MATCH($BS$3+3,'Mortality Tables'!$N$1:$DN$1,0),FALSE),VLOOKUP($T19,Fe_Annuity_Tables,MATCH(BS$3+3,'Mortality Tables'!$N$1:$DN$1,0),FALSE)),"") -> 1079063.6 | BT19: =IFERROR(($BS19+AC19*Contr_Rate)*(1+Inv_Return)*IF($D19=$C$1,VLOOKUP($T19,Male_Annuity_Tables,MATCH($BS$3+3,'Mortality Tables'!$N$1:$DN$1,0),FALSE),VLOOKUP($T19,Fe_Annuity_Tables,MATCH(BT$3+3,'Mortality Tables'!$N$1:$DN$1,0),FALSE)),"") -> 1438994.1 | BU19: =IFERROR((BT19+AD19*Contr_Rate)*(1+Inv_Return)*IF($D19=$C$1,VLOOKUP($T19,Male_Annuity_Tables,MATCH($BS$3+3,'Mortality Tables'!$N$1:$DN$1,0),FALSE),VLOOKUP($T19,Fe_Annuity_Tables,MATCH(BU$3+3,'Mortality Tables'!$N$1:$DN$1,0),FALSE)),"") -> 1473154 | BV19: =IFERROR((BU19+AE19*Contr_Rate)*(1+Inv_Return)*IF($D19=$C$1,VLOOKUP($T19,Male_Annuity_Tables,MATCH($BS$3+3,'Mortality Tables'!$N$1:$DN$1,0),FALSE),VLOOKUP($T19,Fe_Annuity_Tables,MATCH(BV$3+3,'Mortality Tables'!$N$1:$DN$1,0),FALSE)),"") -> 1291501.9 | BW19: =IFERROR((BV19+AF19*Contr_Rate)*(1+Inv_Return)*IF($D19=$C$1,VLOOKUP($T19,Male_Annuity_Tables,MATCH($BS$3+3,'Mortality Tables'!$N$1:$DN$1,0),FALSE),VLOOKUP($T19,Fe_Annuity_Tables,MATCH(BW$3+3,'Mortality Tables'!$N$1:$DN$1,0),FALSE)),"") -> 1034705.7 | BX19: =IFERROR((BW19+AG19*Contr_Rate)*(1+Inv_Return)*IF($D19=$C$1,VLOOKUP($T19,Male_Annuity_Tables,MATCH($BS$3+3,'Mortality Tables'!$N$1:$DN$1,0),FALSE),VLOOKUP($T19,Fe_Annuity_Tables,MATCH(BX$3+3,'Mortality Tables'!$N$1:$DN$1,0),FALSE)),"") -> 798322.16 | BY19: =IFERROR((BX19+AH19*Contr_Rate)*(1+Inv_Return)*IF($D19=$C$1,VLOOKUP($T19,Male_Annuity_Tables,MATCH($BS$3+3,'Mortality Tables'!$N$1:$DN$1,0),FALSE),VLOOKUP($T19,Fe_Annuity_Tables,MATCH(BY$3+3,'Mortality Tables'!$N$1:$DN$1,0),FALSE)),"") -> 617302.3 | BZ19: =IFERROR((BY19+AI19*Contr_Rate)*(1+Inv_Return)*IF($D19=$C$1,VLOOKUP($T19,Male_Annuity_Tables,MATCH($BS$3+3,'Mortality Tables'!$N$1:$DN$1,0),FALSE),VLOOKUP($T19,Fe_Annuity_Tables,MATCH(BZ$3+3,'Mortality Tables'!$N$1:$DN$1,0),FALSE)),"") -> 517490.36 | CA19: =IFERROR((BZ19+AJ19*Contr_Rate)*(1+Inv_Return)*IF($D19=$C$1,VLOOKUP($T19,Male_Annuity_Tables,MATCH($BS$3+3,'Mortality Tables'!$N$1:$DN$1,0),FALSE),VLOOKUP($T19,Fe_Annuity_Tables,MATCH(CA$3+3,'Mortality Tables'!$N$1:$DN$1,0),FALSE)),"") -> 453419.82 | CB19: =IFERROR((CA19+AK19*Contr_Rate)*(1+Inv_Return)*IF($D19=$C$1,VLOOKUP($T19,Male_Annuity_Tables,MATCH($BS$3+3,'Mortality Tables'!$N$1:$DN$1,0),FALSE),VLOOKUP($T19,Fe_Annuity_Tables,MATCH(CB$3+3,'Mortality Tables'!$N$1:$DN$1,0),FALSE)),"") -> 405962.48 | ... DH19: =IFERROR((DG19+BQ19*Contr_Rate)*(1+Inv_Return)*IF($D19=$C$1,VLOOKUP($T19,Male_Annuity_Tables,MATCH($BS$3+3,'Mortality Tables'!$N$1:$DN$1,0),FALSE),VLOOKUP($T19,Fe_Annuity_Tables,MATCH(DH$3+3,'Mortality Tables'!$N$1:$DN$1,0),FALSE)),"") | DJ19: =MAX(BS19:DH19) -> 1473154 | DK19: =IF($D19="FEMALE",Fe_Annuity_Factor,Male_Annuity_Factor) -> 8.8017766 | DL19: =(DJ19*Annuity_Ratio)/DK19 -> 112137.95 | DM19: =MAX($AB19:$BQ19) -> 6099047.6 | DN19: =IFERROR((DL19/DM19),"") -> 0.018386141 | DP19: =IFERROR(IF($D19=$C$1,VLOOKUP($T19+DP$3-1,Male_Annuity_Tables,2,FALSE),VLOOKUP($T19,Fe_Annuity_Tables,2,FALSE))*BS19,"") -> 163959.94 | DQ19: =IFERROR(IF($D19=$C$1,VLOOKUP($T19+DQ$3-1,Male_Annuity_Tables,2,FALSE),VLOOKUP($T19,Fe_Annuity_Tables,2,FALSE))*BT19,"") -> 218650.11 | DR19: =IFERROR(IF($D19=$C$1,VLOOKUP($T19+DR$3-1,Male_Annuity_Tables,2,FALSE),VLOOKUP($T19,Fe_Annuity_Tables,2,FALSE))*BU19,"") -> 223840.59
A20: M0017 | B20: Daniel Bright | C20: Dormant | D20: Female | E20: 34489 | F20: 41107 | G20: 41671 | H20: 767883 | I20: 49662.84 | J20: 44466.48 | L20: 94129.32 | M20: =IF(COUNTIF($A$4:A204,A20)=1,0,1) -> 0 | N20: =IF(T20<=18,"WHAT!!!",IF(T20>100,"EERM","Okay")) -> Okay | O20: =IF(G20>E20,"TRUE","FALSE") -> TRUE | P20: =G20>=Comm_Date -> TRUE | Q20: =$G20>=$F20 -> TRUE | R20: =$F20>$E20 -> TRUE | S20: =YEARFRAC(E20,F20,3) -> 18.131507 | T20: =ROUNDDOWN(YEARFRAC($E20,Analysis_Date,3),0) -> 30 | U20: =ROUNDDOWN(YEARFRAC($E20,$G20,3),0) -> 19 | V20: =YEARFRAC($G20,Analysis_Date,3) -> 10.917808 | W20: =MAX(ROUNDDOWN(NRA-T20,0),0) -> 30 | X20: =L20*W20 -> 2823879.6 | Y20: =IF($D20=$C$1,VLOOKUP($T20,Mortality_Table,3,FALSE),VLOOKUP($T20,Mortality_Table,2,FALSE)) -> 0.00132 | Z20: =IF($D20=$C$1,VLOOKUP($T20,Male_Annuity_Tables,MATCH($W20+2,'Mortality Tables'!$DS$1:$HT$1,0),FALSE),VLOOKUP($T20,Fe_Annuity_Tables,MATCH($W20+2,'Mortality Tables'!$M$1:$DN$1,0),FALSE)) -> 0.0087708575 | AB20: =IFERROR(IF($W20>=AB$3,($H20*(1+Ann_Salary_Growth_Rate)^AB$3),""),0) -> 807006.64 | AC20: =IFERROR(IF($W20>=AC$3,($H20*(1+Ann_Salary_Growth_Rate)^AC$3),""),0) -> 848123.63 | AD20: =IFERROR(IF($W20>=AD$3,($H20*(1+Ann_Salary_Growth_Rate)^AD$3),""),0) -> 891335.53 | AE20: =IFERROR(IF($W20>=AE$3,($H20*(1+Ann_Salary_Growth_Rate)^AE$3),""),0) -> 936749.07 | AF20: =IFERROR(IF($W20>=AF$3,($H20*(1+Ann_Salary_Growth_Rate)^AF$3),""),0) -> 984476.44 | AG20: =IFERROR(IF($W20>=AG$3,($H20*(1+Ann_Salary_Growth_Rate)^AG$3),""),0) -> 1034635.5 | AH20: =IFERROR(IF($W20>=AH$3,($H20*(1+Ann_Salary_Growth_Rate)^AH$3),""),0) -> 1087350.2 | AI20: =IFERROR(IF($W20>=AI$3,($H20*(1+Ann_Salary_Growth_Rate)^AI$3),""),0) -> 1142750.7 | ... BQ20: =IFERROR(IF($W20>=BQ$3,($H20*(1+Ann_Salary_Growth_Rate)^BQ$3),""),0) | BS20: =IFERROR(($L20+AB20*Contr_Rate)*(1+Inv_Return)*IF($D20=$C$1,VLOOKUP($T20,Male_Annuity_Tables,MATCH($BS$3+3,'Mortality Tables'!$N$1:$DN$1,0),FALSE),VLOOKUP($T20,Fe_Annuity_Tables,MATCH(BS$3+3,'Mortality Tables'!$N$1:$DN$1,0),FALSE)),"") -> 276056.08 | BT20: =IFERROR(($BS20+AC20*Contr_Rate)*(1+Inv_Return)*IF($D20=$C$1,VLOOKUP($T20,Male_Annuity_Tables,MATCH($BS$3+3,'Mortality Tables'!$N$1:$DN$1,0),FALSE),VLOOKUP($T20,Fe_Annuity_Tables,MATCH(BT$3+3,'Mortality Tables'!$N$1:$DN$1,0),FALSE)),"") -> 347970.37 | BU20: =IFERROR((BT20+AD20*Contr_Rate)*(1+Inv_Return)*IF($D20=$C$1,VLOOKUP($T20,Male_Annuity_Tables,MATCH($BS$3+3,'Mortality Tables'!$N$1:$DN$1,0),FALSE),VLOOKUP($T20,Fe_Annuity_Tables,MATCH(BU$3+3,'Mortality Tables'!$N$1:$DN$1,0),FALSE)),"") -> 322470.32 | BV20: =IFERROR((BU20+AE20*Contr_Rate)*(1+Inv_Return)*IF($D20=$C$1,VLOOKUP($T20,Male_Annuity_Tables,MATCH($BS$3+3,'Mortality Tables'!$N$1:$DN$1,0),FALSE),VLOOKUP($T20,Fe_Annuity_Tables,MATCH(BV$3+3,'Mortality Tables'!$N$1:$DN$1,0),FALSE)),"") -> 252638.34 | BW20: =IFERROR((BV20+AF20*Contr_Rate)*(1+Inv_Return)*IF($D20=$C$1,VLOOKUP($T20,Male_Annuity_Tables,MATCH($BS$3+3,'Mortality Tables'!$N$1:$DN$1,0),FALSE),VLOOKUP($T20,Fe_Annuity_Tables,MATCH(BW$3+3,'Mortality Tables'!$N$1:$DN$1,0),FALSE)),"") -> 183249.32 | BX20: =IFERROR((BW20+AG20*Contr_Rate)*(1+Inv_Return)*IF($D20=$C$1,VLOOKUP($T20,Male_Annuity_Tables,MATCH($BS$3+3,'Mortality Tables'!$N$1:$DN$1,0),FALSE),VLOOKUP($T20,Fe_Annuity_Tables,MATCH(BX$3+3,'Mortality Tables'!$N$1:$DN$1,0),FALSE)),"") -> 131859.67 | BY20: =IFERROR((BX20+AH20*Contr_Rate)*(1+Inv_Return)*IF($D20=$C$1,VLOOKUP($T20,Male_Annuity_Tables,MATCH($BS$3+3,'Mortality Tables'!$N$1:$DN$1,0),FALSE),VLOOKUP($T20,Fe_Annuity_Tables,MATCH(BY$3+3,'Mortality Tables'!$N$1:$DN$1,0),FALSE)),"") -> 97730.874 | BZ20: =IFERROR((BY20+AI20*Contr_Rate)*(1+Inv_Return)*IF($D20=$C$1,VLOOKUP($T20,Male_Annuity_Tables,MATCH($BS$3+3,'Mortality Tables'!$N$1:$DN$1,0),FALSE),VLOOKUP($T20,Fe_Annuity_Tables,MATCH(BZ$3+3,'Mortality Tables'!$N$1:$DN$1,0),FALSE)),"") -> 75072.164 | CA20: =IFERROR((BZ20+AJ20*Contr_Rate)*(1+Inv_Return)*IF($D20=$C$1,VLOOKUP($T20,Male_Annuity_Tables,MATCH($BS$3+3,'Mortality Tables'!$N$1:$DN$1,0),FALSE),VLOOKUP($T20,Fe_Annuity_Tables,MATCH(CA$3+3,'Mortality Tables'!$N$1:$DN$1,0),FALSE)),"") -> 59247.301 | CB20: =IFERROR((CA20+AK20*Contr_Rate)*(1+Inv_Return)*IF($D20=$C$1,VLOOKUP($T20,Male_Annuity_Tables,MATCH($BS$3+3,'Mortality Tables'!$N$1:$DN$1,0),FALSE),VLOOKUP($T20,Fe_Annuity_Tables,MATCH(CB$3+3,'Mortality Tables'!$N$1:$DN$1,0),FALSE)),"") -> 47586.735 | ... DH20: =IFERROR((DG20+BQ20*Contr_Rate)*(1+Inv_Return)*IF($D20=$C$1,VLOOKUP($T20,Male_Annuity_Tables,MATCH($BS$3+3,'Mortality Tables'!$N$1:$DN$1,0),FALSE),VLOOKUP($T20,Fe_Annuity_Tables,MATCH(DH$3+3,'Mortality Tables'!$N$1:$DN$1,0),FALSE)),"") | DJ20: =MAX(BS20:DH20) -> 347970.37 | DK20: =IF($D20="FEMALE",Fe_Annuity_Factor,Male_Annuity_Factor) -> 8.8017766 | DL20: =(DJ20*Annuity_Ratio)/DK20 -> 26487.851 | DM20: =MAX($AB20:$BQ20) -> 3410018.1 | DN20: =IFERROR((DL20/DM20),"") -> 0.0077676568 | DP20: =IFERROR(IF($D20=$C$1,VLOOKUP($T20+DP$3-1,Male_Annuity_Tables,2,FALSE),VLOOKUP($T20,Fe_Annuity_Tables,2,FALSE))*BS20,"") -> 55502.732 | DQ20: =IFERROR(IF($D20=$C$1,VLOOKUP($T20+DQ$3-1,Male_Annuity_Tables,2,FALSE),VLOOKUP($T20,Fe_Annuity_Tables,2,FALSE))*BT20,"") -> 69961.53 | DR20: =IFERROR(IF($D20=$C$1,VLOOKUP($T20+DR$3-1,Male_Annuity_Tables,2,FALSE),VLOOKUP($T20,Fe_Annuity_Tables,2,FALSE))*BU20,"") -> 64834.593
A21: M0018 | B21: Shannon Hernandez | C21: Dormant | D21: Male | E21: 25801 | F21: 44817 | G21: 45472 | H21: 2429371 | I21: 232324.13 | J21: 227209.18 | L21: 459533.31 | M21: =IF(COUNTIF($A$4:A204,A21)=1,0,1) -> 0 | N21: =IF(T21<=18,"WHAT!!!",IF(T21>100,"EERM","Okay")) -> Okay | O21: =IF(G21>E21,"TRUE","FALSE") -> TRUE | P21: =G21>=Comm_Date -> TRUE | Q21: =$G21>=$F21 -> TRUE | R21: =$F21>$E21 -> TRUE | S21: =YEARFRAC(E21,F21,3) -> 52.09863 | T21: =ROUNDDOWN(YEARFRAC($E21,Analysis_Date,3),0) -> 54 | U21: =ROUNDDOWN(YEARFRAC($E21,$G21,3),0) -> 53 | V21: =YEARFRAC($G21,Analysis_Date,3) -> 0.50410959 | W21: =MAX(ROUNDDOWN(NRA-T21,0),0) -> 6 | X21: =L21*W21 -> 2757199.9 | Y21: =IF($D21=$C$1,VLOOKUP($T21,Mortality_Table,3,FALSE),VLOOKUP($T21,Mortality_Table,2,FALSE)) -> 0.00793 | Z21: =IF($D21=$C$1,VLOOKUP($T21,Male_Annuity_Tables,MATCH($W21+2,'Mortality Tables'!$DS$1:$HT$1,0),FALSE),VLOOKUP($T21,Fe_Annuity_Tables,MATCH($W21+2,'Mortality Tables'!$M$1:$DN$1,0),FALSE)) -> 0.65501517 | AB21: =IFERROR(IF($W21>=AB$3,($H21*(1+Ann_Salary_Growth_Rate)^AB$3),""),0) -> 2553147.5 | AC21: =IFERROR(IF($W21>=AC$3,($H21*(1+Ann_Salary_Growth_Rate)^AC$3),""),0) -> 2683230.3 | AD21: =IFERROR(IF($W21>=AD$3,($H21*(1+Ann_Salary_Growth_Rate)^AD$3),""),0) -> 2819940.9 | AE21: =IFERROR(IF($W21>=AE$3,($H21*(1+Ann_Salary_Growth_Rate)^AE$3),""),0) -> 2963616.9 | AF21: =IFERROR(IF($W21>=AF$3,($H21*(1+Ann_Salary_Growth_Rate)^AF$3),""),0) -> 3114613.2 | AG21: =IFERROR(IF($W21>=AG$3,($H21*(1+Ann_Salary_Growth_Rate)^AG$3),""),0) -> 3273302.7 | AH21: =IFERROR(IF($W21>=AH$3,($H21*(1+Ann_Salary_Growth_Rate)^AH$3),""),0) | AI21: =IFERROR(IF($W21>=AI$3,($H21*(1+Ann_Salary_Growth_Rate)^AI$3),""),0) | ... BQ21: =IFERROR(IF($W21>=BQ$3,($H21*(1+Ann_Salary_Growth_Rate)^BQ$3),""),0) | BS21: =IFERROR(($L21+AB21*Contr_Rate)*(1+Inv_Return)*IF($D21=$C$1,VLOOKUP($T21,Male_Annuity_Tables,MATCH($BS$3+3,'Mortality Tables'!$N$1:$DN$1,0),FALSE),VLOOKUP($T21,Fe_Annuity_Tables,MATCH(BS$3+3,'Mortality Tables'!$N$1:$DN$1,0),FALSE)),"") -> 1124431.5 | BT21: =IFERROR(($BS21+AC21*Contr_Rate)*(1+Inv_Return)*IF($D21=$C$1,VLOOKUP($T21,Male_Annuity_Tables,MATCH($BS$3+3,'Mortality Tables'!$N$1:$DN$1,0),FALSE),VLOOKUP($T21,Fe_Annuity_Tables,MATCH(BT$3+3,'Mortality Tables'!$N$1:$DN$1,0),FALSE)),"") -> 1770313 | BU21: =IFERROR((BT21+AD21*Contr_Rate)*(1+Inv_Return)*IF($D21=$C$1,VLOOKUP($T21,Male_Annuity_Tables,MATCH($BS$3+3,'Mortality Tables'!$N$1:$DN$1,0),FALSE),VLOOKUP($T21,Fe_Annuity_Tables,MATCH(BU$3+3,'Mortality Tables'!$N$1:$DN$1,0),FALSE)),"") -> 2400570.2 | BV21: =IFERROR((BU21+AE21*Contr_Rate)*(1+Inv_Return)*IF($D21=$C$1,VLOOKUP($T21,Male_Annuity_Tables,MATCH($BS$3+3,'Mortality Tables'!$N$1:$DN$1,0),FALSE),VLOOKUP($T21,Fe_Annuity_Tables,MATCH(BV$3+3,'Mortality Tables'!$N$1:$DN$1,0),FALSE)),"") -> 3018408.7 | BW21: =IFERROR((BV21+AF21*Contr_Rate)*(1+Inv_Return)*IF($D21=$C$1,VLOOKUP($T21,Male_Annuity_Tables,MATCH($BS$3+3,'Mortality Tables'!$N$1:$DN$1,0),FALSE),VLOOKUP($T21,Fe_Annuity_Tables,MATCH(BW$3+3,'Mortality Tables'!$N$1:$DN$1,0),FALSE)),"") -> 3626867.5 | BX21: =IFERROR((BW21+AG21*Contr_Rate)*(1+Inv_Return)*IF($D21=$C$1,VLOOKUP($T21,Male_Annuity_Tables,MATCH($BS$3+3,'Mortality Tables'!$N$1:$DN$1,0),FALSE),VLOOKUP($T21,Fe_Annuity_Tables,MATCH(BX$3+3,'Mortality Tables'!$N$1:$DN$1,0),FALSE)),"") -> 4228837.6 | BY21: =IFERROR((BX21+AH21*Contr_Rate)*(1+Inv_Return)*IF($D21=$C$1,VLOOKUP($T21,Male_Annuity_Tables,MATCH($BS$3+3,'Mortality Tables'!$N$1:$DN$1,0),FALSE),VLOOKUP($T21,Fe_Annuity_Tables,MATCH(BY$3+3,'Mortality Tables'!$N$1:$DN$1,0),FALSE)),"") | BZ21: =IFERROR((BY21+AI21*Contr_Rate)*(1+Inv_Return)*IF($D21=$C$1,VLOOKUP($T21,Male_Annuity_Tables,MATCH($BS$3+3,'Mortality Tables'!$N$1:$DN$1,0),FALSE),VLOOKUP($T21,Fe_Annuity_Tables,MATCH(BZ$3+3,'Mortality Tables'!$N$1:$DN$1,0),FALSE)),"") | CA21: =IFERROR((BZ21+AJ21*Contr_Rate)*(1+Inv_Return)*IF($D21=$C$1,VLOOKUP($T21,Male_Annuity_Tables,MATCH($BS$3+3,'Mortality Tables'!$N$1:$DN$1,0),FALSE),VLOOKUP($T21,Fe_Annuity_Tables,MATCH(CA$3+3,'Mortality Tables'!$N$1:$DN$1,0),FALSE)),"") | CB21: =IFERROR((CA21+AK21*Contr_Rate)*(1+Inv_Return)*IF($D21=$C$1,VLOOKUP($T21,Male_Annuity_Tables,MATCH($BS$3+3,'Mortality Tables'!$N$1:$DN$1,0),FALSE),VLOOKUP($T21,Fe_Annuity_Tables,MATCH(CB$3+3,'Mortality Tables'!$N$1:$DN$1,0),FALSE)),"") | ... DH21: =IFERROR((DG21+BQ21*Contr_Rate)*(1+Inv_Return)*IF($D21=$C$1,VLOOKUP($T21,Male_Annuity_Tables,MATCH($BS$3+3,'Mortality Tables'!$N$1:$DN$1,0),FALSE),VLOOKUP($T21,Fe_Annuity_Tables,MATCH(DH$3+3,'Mortality Tables'!$N$1:$DN$1,0),FALSE)),"") | DJ21: =MAX(BS21:DH21) -> 4228837.6 | DK21: =IF($D21="FEMALE",Fe_Annuity_Factor,Male_Annuity_Factor) -> 8.0909278 | DL21: =(DJ21*Annuity_Ratio)/DK21 -> 350184.96 | DM21: =MAX($AB21:$BQ21) -> 3273302.7 | DN21: =IFERROR((DL21/DM21),"") -> 0.10698215 | DP21: =IFERROR(IF($D21=$C$1,VLOOKUP($T21+DP$3-1,Male_Annuity_Tables,2,FALSE),VLOOKUP($T21,Fe_Annuity_Tables,2,FALSE))*BS21,"") -> 120468.22 | DQ21: =IFERROR(IF($D21=$C$1,VLOOKUP($T21+DQ$3-1,Male_Annuity_Tables,2,FALSE),VLOOKUP($T21,Fe_Annuity_Tables,2,FALSE))*BT21,"") -> 103147.29 | DR21: =IFERROR(IF($D21=$C$1,VLOOKUP($T21+DR$3-1,Male_Annuity_Tables,2,FALSE),VLOOKUP($T21,Fe_Annuity_Tables,2,FALSE))*BU21,"") -> 141807.69
A22: M0019 | B22: Janice Carlson | C22: Deferred | D22: Male | E22: 33458 | F22: 41549 | G22: 43111 | H22: 1868308 | I22: 164645.65 | J22: 143801.71 | K22: 28865.92 | L22: 337313.28 | M22: =IF(COUNTIF($A$4:A204,A22)=1,0,1) -> 0 | N22: =IF(T22<=18,"WHAT!!!",IF(T22>100,"EERM","Okay")) -> Okay | O22: =IF(G22>E22,"TRUE","FALSE") -> TRUE | P22: =G22>=Comm_Date -> TRUE | Q22: =$G22>=$F22 -> TRUE | R22: =$F22>$E22 -> TRUE | S22: =YEARFRAC(E22,F22,3) -> 22.167123 | T22: =ROUNDDOWN(YEARFRAC($E22,Analysis_Date,3),0) -> 33 | U22: =ROUNDDOWN(YEARFRAC($E22,$G22,3),0) -> 26 | V22: =YEARFRAC($G22,Analysis_Date,3) -> 6.9726027 | W22: =MAX(ROUNDDOWN(NRA-T22,0),0) -> 27 | X22: =L22*W22 -> 9107458.6 | Y22: =IF($D22=$C$1,VLOOKUP($T22,Mortality_Table,3,FALSE),VLOOKUP($T22,Mortality_Table,2,FALSE)) -> 0.00153 | Z22: =IF($D22=$C$1,VLOOKUP($T22,Male_Annuity_Tables,MATCH($W22+2,'Mortality Tables'!$DS$1:$HT$1,0),FALSE),VLOOKUP($T22,Fe_Annuity_Tables,MATCH($W22+2,'Mortality Tables'!$M$1:$DN$1,0),FALSE)) -> 0.016500088 | AB22: =IFERROR(IF($W22>=AB$3,($H22*(1+Ann_Salary_Growth_Rate)^AB$3),""),0) -> 1963498.3 | AC22: =IFERROR(IF($W22>=AC$3,($H22*(1+Ann_Salary_Growth_Rate)^AC$3),""),0) -> 2063538.5 | AD22: =IFERROR(IF($W22>=AD$3,($H22*(1+Ann_Salary_Growth_Rate)^AD$3),""),0) -> 2168675.8 | AE22: =IFERROR(IF($W22>=AE$3,($H22*(1+Ann_Salary_Growth_Rate)^AE$3),""),0) -> 2279169.9 | AF22: =IFERROR(IF($W22>=AF$3,($H22*(1+Ann_Salary_Growth_Rate)^AF$3),""),0) -> 2395293.6 | AG22: =IFERROR(IF($W22>=AG$3,($H22*(1+Ann_Salary_Growth_Rate)^AG$3),""),0) -> 2517333.8 | AH22: =IFERROR(IF($W22>=AH$3,($H22*(1+Ann_Salary_Growth_Rate)^AH$3),""),0) -> 2645591.9 | AI22: =IFERROR(IF($W22>=AI$3,($H22*(1+Ann_Salary_Growth_Rate)^AI$3),""),0) -> 2780384.8 | ... BQ22: =IFERROR(IF($W22>=BQ$3,($H22*(1+Ann_Salary_Growth_Rate)^BQ$3),""),0) | BS22: =IFERROR(($L22+AB22*Contr_Rate)*(1+Inv_Return)*IF($D22=$C$1,VLOOKUP($T22,Male_Annuity_Tables,MATCH($BS$3+3,'Mortality Tables'!$N$1:$DN$1,0),FALSE),VLOOKUP($T22,Fe_Annuity_Tables,MATCH(BS$3+3,'Mortality Tables'!$N$1:$DN$1,0),FALSE)),"") -> 760411.94 | BT22: =IFERROR(($BS22+AC22*Contr_Rate)*(1+Inv_Return)*IF($D22=$C$1,VLOOKUP($T22,Male_Annuity_Tables,MATCH($BS$3+3,'Mortality Tables'!$N$1:$DN$1,0),FALSE),VLOOKUP($T22,Fe_Annuity_Tables,MATCH(BT$3+3,'Mortality Tables'!$N$1:$DN$1,0),FALSE)),"") -> 1132351.3 | BU22: =IFERROR((BT22+AD22*Contr_Rate)*(1+Inv_Return)*IF($D22=$C$1,VLOOKUP($T22,Male_Annuity_Tables,MATCH($BS$3+3,'Mortality Tables'!$N$1:$DN$1,0),FALSE),VLOOKUP($T22,Fe_Annuity_Tables,MATCH(BU$3+3,'Mortality Tables'!$N$1:$DN$1,0),FALSE)),"") -> 1463551.4 | BV22: =IFERROR((BU22+AE22*Contr_Rate)*(1+Inv_Return)*IF($D22=$C$1,VLOOKUP($T22,Male_Annuity_Tables,MATCH($BS$3+3,'Mortality Tables'!$N$1:$DN$1,0),FALSE),VLOOKUP($T22,Fe_Annuity_Tables,MATCH(BV$3+3,'Mortality Tables'!$N$1:$DN$1,0),FALSE)),"") -> 1762629.5 | BW22: =IFERROR((BV22+AF22*Contr_Rate)*(1+Inv_Return)*IF($D22=$C$1,VLOOKUP($T22,Male_Annuity_Tables,MATCH($BS$3+3,'Mortality Tables'!$N$1:$DN$1,0),FALSE),VLOOKUP($T22,Fe_Annuity_Tables,MATCH(BW$3+3,'Mortality Tables'!$N$1:$DN$1,0),FALSE)),"") -> 2036726.4 | BX22: =IFERROR((BW22+AG22*Contr_Rate)*(1+Inv_Return)*IF($D22=$C$1,VLOOKUP($T22,Male_Annuity_Tables,MATCH($BS$3+3,'Mortality Tables'!$N$1:$DN$1,0),FALSE),VLOOKUP($T22,Fe_Annuity_Tables,MATCH(BX$3+3,'Mortality Tables'!$N$1:$DN$1,0),FALSE)),"") -> 2291774.2 | BY22: =IFERROR((BX22+AH22*Contr_Rate)*(1+Inv_Return)*IF($D22=$C$1,VLOOKUP($T22,Male_Annuity_Tables,MATCH($BS$3+3,'Mortality Tables'!$N$1:$DN$1,0),FALSE),VLOOKUP($T22,Fe_Annuity_Tables,MATCH(BY$3+3,'Mortality Tables'!$N$1:$DN$1,0),FALSE)),"") -> 2532716.6 | BZ22: =IFERROR((BY22+AI22*Contr_Rate)*(1+Inv_Return)*IF($D22=$C$1,VLOOKUP($T22,Male_Annuity_Tables,MATCH($BS$3+3,'Mortality Tables'!$N$1:$DN$1,0),FALSE),VLOOKUP($T22,Fe_Annuity_Tables,MATCH(BZ$3+3,'Mortality Tables'!$N$1:$DN$1,0),FALSE)),"") -> 2763689.7 | CA22: =IFERROR((BZ22+AJ22*Contr_Rate)*(1+Inv_Return)*IF($D22=$C$1,VLOOKUP($T22,Male_Annuity_Tables,MATCH($BS$3+3,'Mortality Tables'!$N$1:$DN$1,0),FALSE),VLOOKUP($T22,Fe_Annuity_Tables,MATCH(CA$3+3,'Mortality Tables'!$N$1:$DN$1,0),FALSE)),"") -> 2988170.8 | CB22: =IFERROR((CA22+AK22*Contr_Rate)*(1+Inv_Return)*IF($D22=$C$1,VLOOKUP($T22,Male_Annuity_Tables,MATCH($BS$3+3,'Mortality Tables'!$N$1:$DN$1,0),FALSE),VLOOKUP($T22,Fe_Annuity_Tables,MATCH(CB$3+3,'Mortality Tables'!$N$1:$DN$1,0),FALSE)),"") -> 3209100.1 | ... DH22: =IFERROR((DG22+BQ22*Contr_Rate)*(1+Inv_Return)*IF($D22=$C$1,VLOOKUP($T22,Male_Annuity_Tables,MATCH($BS$3+3,'Mortality Tables'!$N$1:$DN$1,0),FALSE),VLOOKUP($T22,Fe_Annuity_Tables,MATCH(DH$3+3,'Mortality Tables'!$N$1:$DN$1,0),FALSE)),"") | DJ22: =MAX(BS22:DH22) -> 8031024.7 | DK22: =IF($D22="FEMALE",Fe_Annuity_Factor,Male_Annuity_Factor) -> 8.0909278 | DL22: =(DJ22*Annuity_Ratio)/DK22 -> 665039.5 | DM22: =MAX($AB22:$BQ22) -> 7147661 | DN22: =IFERROR((DL22/DM22),"") -> 0.093042956 | DP22: =IFERROR(IF($D22=$C$1,VLOOKUP($T22+DP$3-1,Male_Annuity_Tables,2,FALSE),VLOOKUP($T22,Fe_Annuity_Tables,2,FALSE))*BS22,"") -> 153013.13 | DQ22: =IFERROR(IF($D22=$C$1,VLOOKUP($T22+DQ$3-1,Male_Annuity_Tables,2,FALSE),VLOOKUP($T22,Fe_Annuity_Tables,2,FALSE))*BT22,"") -> 227919.68 | DR22: =IFERROR(IF($D22=$C$1,VLOOKUP($T22+DR$3-1,Male_Annuity_Tables,2,FALSE),VLOOKUP($T22,Fe_Annuity_Tables,2,FALSE))*BU22,"") -> 294677.3
A23: M0020 | B23: Shannon Smith | C23: Active | D23: Female | E23: 24672 | F23: 43446 | G23: 45114 | H23: 2349360 | I23: 119755.89 | J23: 226607.36 | K23: 42424.95 | L23: 388788.2 | M23: =IF(COUNTIF($A$4:A204,A23)=1,0,1) -> 0 | N23: =IF(T23<=18,"WHAT!!!",IF(T23>100,"EERM","Okay")) -> Okay | O23: =IF(G23>E23,"TRUE","FALSE") -> TRUE | P23: =G23>=Comm_Date -> TRUE | Q23: =$G23>=$F23 -> TRUE | R23: =$F23>$E23 -> TRUE | S23: =YEARFRAC(E23,F23,3) -> 51.435616 | T23: =ROUNDDOWN(YEARFRAC($E23,Analysis_Date,3),0) -> 57 | U23: =ROUNDDOWN(YEARFRAC($E23,$G23,3),0) -> 56 | V23: =YEARFRAC($G23,Analysis_Date,3) -> 1.4849315 | W23: =MAX(ROUNDDOWN(NRA-T23,0),0) -> 3 | X23: =L23*W23 -> 1166364.6 | Y23: =IF($D23=$C$1,VLOOKUP($T23,Mortality_Table,3,FALSE),VLOOKUP($T23,Mortality_Table,2,FALSE)) -> 0.00653 | Z23: =IF($D23=$C$1,VLOOKUP($T23,Male_Annuity_Tables,MATCH($W23+2,'Mortality Tables'!$DS$1:$HT$1,0),FALSE),VLOOKUP($T23,Fe_Annuity_Tables,MATCH($W23+2,'Mortality Tables'!$M$1:$DN$1,0),FALSE)) -> 0.83911515 | AB23: =IFERROR(IF($W23>=AB$3,($H23*(1+Ann_Salary_Growth_Rate)^AB$3),""),0) -> 2469059.9 | AC23: =IFERROR(IF($W23>=AC$3,($H23*(1+Ann_Salary_Growth_Rate)^AC$3),""),0) -> 2594858.5 | AD23: =IFERROR(IF($W23>=AD$3,($H23*(1+Ann_Salary_Growth_Rate)^AD$3),""),0) -> 2727066.5 | AE23: =IFERROR(IF($W23>=AE$3,($H23*(1+Ann_Salary_Growth_Rate)^AE$3),""),0) | AF23: =IFERROR(IF($W23>=AF$3,($H23*(1+Ann_Salary_Growth_Rate)^AF$3),""),0) | AG23: =IFERROR(IF($W23>=AG$3,($H23*(1+Ann_Salary_Growth_Rate)^AG$3),""),0) | AH23: =IFERROR(IF($W23>=AH$3,($H23*(1+Ann_Salary_Growth_Rate)^AH$3),""),0) | AI23: =IFERROR(IF($W23>=AI$3,($H23*(1+Ann_Salary_Growth_Rate)^AI$3),""),0) | ... BQ23: =IFERROR(IF($W23>=BQ$3,($H23*(1+Ann_Salary_Growth_Rate)^BQ$3),""),0) | BS23: =IFERROR(($L23+AB23*Contr_Rate)*(1+Inv_Return)*IF($D23=$C$1,VLOOKUP($T23,Male_Annuity_Tables,MATCH($BS$3+3,'Mortality Tables'!$N$1:$DN$1,0),FALSE),VLOOKUP($T23,Fe_Annuity_Tables,MATCH(BS$3+3,'Mortality Tables'!$N$1:$DN$1,0),FALSE)),"") -> 1095493.5 | BT23: =IFERROR(($BS23+AC23*Contr_Rate)*(1+Inv_Return)*IF($D23=$C$1,VLOOKUP($T23,Male_Annuity_Tables,MATCH($BS$3+3,'Mortality Tables'!$N$1:$DN$1,0),FALSE),VLOOKUP($T23,Fe_Annuity_Tables,MATCH(BT$3+3,'Mortality Tables'!$N$1:$DN$1,0),FALSE)),"") -> 1714333.9 | BU23: =IFERROR((BT23+AD23*Contr_Rate)*(1+Inv_Return)*IF($D23=$C$1,VLOOKUP($T23,Male_Annuity_Tables,MATCH($BS$3+3,'Mortality Tables'!$N$1:$DN$1,0),FALSE),VLOOKUP($T23,Fe_Annuity_Tables,MATCH(BU$3+3,'Mortality Tables'!$N$1:$DN$1,0),FALSE)),"") -> 2183765.2 | BV23: =IFERROR((BU23+AE23*Contr_Rate)*(1+Inv_Return)*IF($D23=$C$1,VLOOKUP($T23,Male_Annuity_Tables,MATCH($BS$3+3,'Mortality Tables'!$N$1:$DN$1,0),FALSE),VLOOKUP($T23,Fe_Annuity_Tables,MATCH(BV$3+3,'Mortality Tables'!$N$1:$DN$1,0),FALSE)),"") | BW23: =IFERROR((BV23+AF23*Contr_Rate)*(1+Inv_Return)*IF($D23=$C$1,VLOOKUP($T23,Male_Annuity_Tables,MATCH($BS$3+3,'Mortality Tables'!$N$1:$DN$1,0),FALSE),VLOOKUP($T23,Fe_Annuity_Tables,MATCH(BW$3+3,'Mortality Tables'!$N$1:$DN$1,0),FALSE)),"") | BX23: =IFERROR((BW23+AG23*Contr_Rate)*(1+Inv_Return)*IF($D23=$C$1,VLOOKUP($T23,Male_Annuity_Tables,MATCH($BS$3+3,'Mortality Tables'!$N$1:$DN$1,0),FALSE),VLOOKUP($T23,Fe_Annuity_Tables,MATCH(BX$3+3,'Mortality Tables'!$N$1:$DN$1,0),FALSE)),"") | BY23: =IFERROR((BX23+AH23*Contr_Rate)*(1+Inv_Return)*IF($D23=$C$1,VLOOKUP($T23,Male_Annuity_Tables,MATCH($BS$3+3,'Mortality Tables'!$N$1:$DN$1,0),FALSE),VLOOKUP($T23,Fe_Annuity_Tables,MATCH(BY$3+3,'Mortality Tables'!$N$1:$DN$1,0),FALSE)),"") | BZ23: =IFERROR((BY23+AI23*Contr_Rate)*(1+Inv_Return)*IF($D23=$C$1,VLOOKUP($T23,Male_Annuity_Tables,MATCH($BS$3+3,'Mortality Tables'!$N$1:$DN$1,0),FALSE),VLOOKUP($T23,Fe_Annuity_Tables,MATCH(BZ$3+3,'Mortality Tables'!$N$1:$DN$1,0),FALSE)),"") | CA23: =IFERROR((BZ23+AJ23*Contr_Rate)*(1+Inv_Return)*IF($D23=$C$1,VLOOKUP($T23,Male_Annuity_Tables,MATCH($BS$3+3,'Mortality Tables'!$N$1:$DN$1,0),FALSE),VLOOKUP($T23,Fe_Annuity_Tables,MATCH(CA$3+3,'Mortality Tables'!$N$1:$DN$1,0),FALSE)),"") | CB23: =IFERROR((CA23+AK23*Contr_Rate)*(1+Inv_Return)*IF($D23=$C$1,VLOOKUP($T23,Male_Annuity_Tables,MATCH($BS$3+3,'Mortality Tables'!$N$1:$DN$1,0),FALSE),VLOOKUP($T23,Fe_Annuity_Tables,MATCH(CB$3+3,'Mortality Tables'!$N$1:$DN$1,0),FALSE)),"") | ... DH23: =IFERROR((DG23+BQ23*Contr_Rate)*(1+Inv_Return)*IF($D23=$C$1,VLOOKUP($T23,Male_Annuity_Tables,MATCH($BS$3+3,'Mortality Tables'!$N$1:$DN$1,0),FALSE),VLOOKUP($T23,Fe_Annuity_Tables,MATCH(DH$3+3,'Mortality Tables'!$N$1:$DN$1,0),FALSE)),"") | DJ23: =MAX(BS23:DH23) -> 2183765.2 | DK23: =IF($D23="FEMALE",Fe_Annuity_Factor,Male_Annuity_Factor) -> 8.8017766 | DL23: =(DJ23*Annuity_Ratio)/DK23 -> 166230.38 | DM23: =MAX($AB23:$BQ23) -> 2727066.5 | DN23: =IFERROR((DL23/DM23),"") -> 0.060955748 | DP23: =IFERROR(IF($D23=$C$1,VLOOKUP($T23+DP$3-1,Male_Annuity_Tables,2,FALSE),VLOOKUP($T23,Fe_Annuity_Tables,2,FALSE))*BS23,"") -> 61570.568 | DQ23: =IFERROR(IF($D23=$C$1,VLOOKUP($T23+DQ$3-1,Male_Annuity_Tables,2,FALSE),VLOOKUP($T23,Fe_Annuity_Tables,2,FALSE))*BT23,"") -> 96351.567 | DR23: =IFERROR(IF($D23=$C$1,VLOOKUP($T23+DR$3-1,Male_Annuity_Tables,2,FALSE),VLOOKUP($T23,Fe_Annuity_Tables,2,FALSE))*BU23,"") -> 122735.25
A24: M0021 | B24: Patricia Peterson | C24: Dormant | D24: Male | E24: 29119 | F24: 40377 | G24: 41359 | H24: 542955 | I24: 33686.87 | J24: 42550.21 | L24: 76237.08 | M24: =IF(COUNTIF($A$4:A204,A24)=1,0,1) -> 0 | N24: =IF(T24<=18,"WHAT!!!",IF(T24>100,"EERM","Okay")) -> Okay | O24: =IF(G24>E24,"TRUE","FALSE") -> TRUE | P24: =G24>=Comm_Date -> TRUE | Q24: =$G24>=$F24 -> TRUE | R24: =$F24>$E24 -> TRUE | S24: =YEARFRAC(E24,F24,3) -> 30.843836 | T24: =ROUNDDOWN(YEARFRAC($E24,Analysis_Date,3),0) -> 45 | U24: =ROUNDDOWN(YEARFRAC($E24,$G24,3),0) -> 33 | V24: =YEARFRAC($G24,Analysis_Date,3) -> 11.772603 | W24: =MAX(ROUNDDOWN(NRA-T24,0),0) -> 15 | X24: =L24*W24 -> 1143556.2 | Y24: =IF($D24=$C$1,VLOOKUP($T24,Mortality_Table,3,FALSE),VLOOKUP($T24,Mortality_Table,2,FALSE)) -> 0.00349 | Z24: =IF($D24=$C$1,VLOOKUP($T24,Male_Annuity_Tables,MATCH($W24+2,'Mortality Tables'!$DS$1:$HT$1,0),FALSE),VLOOKUP($T24,Fe_Annuity_Tables,MATCH($W24+2,'Mortality Tables'!$M$1:$DN$1,0),FALSE)) -> 0.18203071 | AB24: =IFERROR(IF($W24>=AB$3,($H24*(1+Ann_Salary_Growth_Rate)^AB$3),""),0) -> 570618.56 | AC24: =IFERROR(IF($W24>=AC$3,($H24*(1+Ann_Salary_Growth_Rate)^AC$3),""),0) -> 599691.57 | AD24: =IFERROR(IF($W24>=AD$3,($H24*(1+Ann_Salary_Growth_Rate)^AD$3),""),0) -> 630245.86 | AE24: =IFERROR(IF($W24>=AE$3,($H24*(1+Ann_Salary_Growth_Rate)^AE$3),""),0) -> 662356.88 | AF24: =IFERROR(IF($W24>=AF$3,($H24*(1+Ann_Salary_Growth_Rate)^AF$3),""),0) -> 696103.97 | AG24: =IFERROR(IF($W24>=AG$3,($H24*(1+Ann_Salary_Growth_Rate)^AG$3),""),0) -> 731570.47 | AH24: =IFERROR(IF($W24>=AH$3,($H24*(1+Ann_Salary_Growth_Rate)^AH$3),""),0) -> 768843.98 | AI24: =IFERROR(IF($W24>=AI$3,($H24*(1+Ann_Salary_Growth_Rate)^AI$3),""),0) -> 808016.58 | ... BQ24: =IFERROR(IF($W24>=BQ$3,($H24*(1+Ann_Salary_Growth_Rate)^BQ$3),""),0) | BS24: =IFERROR(($L24+AB24*Contr_Rate)*(1+Inv_Return)*IF($D24=$C$1,VLOOKUP($T24,Male_Annuity_Tables,MATCH($BS$3+3,'Mortality Tables'!$N$1:$DN$1,0),FALSE),VLOOKUP($T24,Fe_Annuity_Tables,MATCH(BS$3+3,'Mortality Tables'!$N$1:$DN$1,0),FALSE)),"") -> 215368.84 | BT24: =IFERROR(($BS24+AC24*Contr_Rate)*(1+Inv_Return)*IF($D24=$C$1,VLOOKUP($T24,Male_Annuity_Tables,MATCH($BS$3+3,'Mortality Tables'!$N$1:$DN$1,0),FALSE),VLOOKUP($T24,Fe_Annuity_Tables,MATCH(BT$3+3,'Mortality Tables'!$N$1:$DN$1,0),FALSE)),"") -> 344067.94 | BU24: =IFERROR((BT24+AD24*Contr_Rate)*(1+Inv_Return)*IF($D24=$C$1,VLOOKUP($T24,Male_Annuity_Tables,MATCH($BS$3+3,'Mortality Tables'!$N$1:$DN$1,0),FALSE),VLOOKUP($T24,Fe_Annuity_Tables,MATCH(BU$3+3,'Mortality Tables'!$N$1:$DN$1,0),FALSE)),"") -> 464072.74 | BV24: =IFERROR((BU24+AE24*Contr_Rate)*(1+Inv_Return)*IF($D24=$C$1,VLOOKUP($T24,Male_Annuity_Tables,MATCH($BS$3+3,'Mortality Tables'!$N$1:$DN$1,0),FALSE),VLOOKUP($T24,Fe_Annuity_Tables,MATCH(BV$3+3,'Mortality Tables'!$N$1:$DN$1,0),FALSE)),"") -> 576916.13 | BW24: =IFERROR((BV24+AF24*Contr_Rate)*(1+Inv_Return)*IF($D24=$C$1,VLOOKUP($T24,Male_Annuity_Tables,MATCH($BS$3+3,'Mortality Tables'!$N$1:$DN$1,0),FALSE),VLOOKUP($T24,Fe_Annuity_Tables,MATCH(BW$3+3,'Mortality Tables'!$N$1:$DN$1,0),FALSE)),"") -> 683953.11 | BX24: =IFERROR((BW24+AG24*Contr_Rate)*(1+Inv_Return)*IF($D24=$C$1,VLOOKUP($T24,Male_Annuity_Tables,MATCH($BS$3+3,'Mortality Tables'!$N$1:$DN$1,0),FALSE),VLOOKUP($T24,Fe_Annuity_Tables,MATCH(BX$3+3,'Mortality Tables'!$N$1:$DN$1,0),FALSE)),"") -> 786384.88 | BY24: =IFERROR((BX24+AH24*Contr_Rate)*(1+Inv_Return)*IF($D24=$C$1,VLOOKUP($T24,Male_Annuity_Tables,MATCH($BS$3+3,'Mortality Tables'!$N$1:$DN$1,0),FALSE),VLOOKUP($T24,Fe_Annuity_Tables,MATCH(BY$3+3,'Mortality Tables'!$N$1:$DN$1,0),FALSE)),"") -> 885279.95 | BZ24: =IFERROR((BY24+AI24*Contr_Rate)*(1+Inv_Return)*IF($D24=$C$1,VLOOKUP($T24,Male_Annuity_Tables,MATCH($BS$3+3,'Mortality Tables'!$N$1:$DN$1,0),FALSE),VLOOKUP($T24,Fe_Annuity_Tables,MATCH(BZ$3+3,'Mortality Tables'!$N$1:$DN$1,0),FALSE)),"") -> 981592.4 | CA24: =IFERROR((BZ24+AJ24*Contr_Rate)*(1+Inv_Return)*IF($D24=$C$1,VLOOKUP($T24,Male_Annuity_Tables,MATCH($BS$3+3,'Mortality Tables'!$N$1:$DN$1,0),FALSE),VLOOKUP($T24,Fe_Annuity_Tables,MATCH(CA$3+3,'Mortality Tables'!$N$1:$DN$1,0),FALSE)),"") -> 1076178 | CB24: =IFERROR((CA24+AK24*Contr_Rate)*(1+Inv_Return)*IF($D24=$C$1,VLOOKUP($T24,Male_Annuity_Tables,MATCH($BS$3+3,'Mortality Tables'!$N$1:$DN$1,0),FALSE),VLOOKUP($T24,Fe_Annuity_Tables,MATCH(CB$3+3,'Mortality Tables'!$N$1:$DN$1,0),FALSE)),"") -> 1169808.2 | ... DH24: =IFERROR((DG24+BQ24*Contr_Rate)*(1+Inv_Return)*IF($D24=$C$1,VLOOKUP($T24,Male_Annuity_Tables,MATCH($BS$3+3,'Mortality Tables'!$N$1:$DN$1,0),FALSE),VLOOKUP($T24,Fe_Annuity_Tables,MATCH(DH$3+3,'Mortality Tables'!$N$1:$DN$1,0),FALSE)),"") | DJ24: =MAX(BS24:DH24) -> 1646153.4 | DK24: =IF($D24="FEMALE",Fe_Annuity_Factor,Male_Annuity_Factor) -> 8.0909278 | DL24: =(DJ24*Annuity_Ratio)/DK24 -> 136315.98 | DM24: =MAX($AB24:$BQ24) -> 1144180.8 | DN24: =IFERROR((DL24/DM24),"") -> 0.1191385 | DP24: =IFERROR(IF($D24=$C$1,VLOOKUP($T24+DP$3-1,Male_Annuity_Tables,2,FALSE),VLOOKUP($T24,Fe_Annuity_Tables,2,FALSE))*BS24,"") -> 32944.217 | DQ24: =IFERROR(IF($D24=$C$1,VLOOKUP($T24+DQ$3-1,Male_Annuity_Tables,2,FALSE),VLOOKUP($T24,Fe_Annuity_Tables,2,FALSE))*BT24,"") -> 52724.454 | DR24: =IFERROR(IF($D24=$C$1,VLOOKUP($T24+DR$3-1,Male_Annuity_Tables,2,FALSE),VLOOKUP($T24,Fe_Annuity_Tables,2,FALSE))*BU24,"") -> 71255.817
A25: M0022 | B25: Troy Liu | C25: Exited | D25: Male | E25: 28371 | F25: 41195 | G25: 42305 | H25: 2534331 | I25: 223760.45 | J25: 142985.87 | K25: 29741.16 | L25: 396487.48 | M25: =IF(COUNTIF($A$4:A204,A25)=1,0,1) -> 0 | N25: =IF(T25<=18,"WHAT!!!",IF(T25>100,"EERM","Okay")) -> Okay | O25: =IF(G25>E25,"TRUE","FALSE") -> TRUE | P25: =G25>=Comm_Date -> TRUE | Q25: =$G25>=$F25 -> TRUE | R25: =$F25>$E25 -> TRUE | S25: =YEARFRAC(E25,F25,3) -> 35.134247 | T25: =ROUNDDOWN(YEARFRAC($E25,Analysis_Date,3),0) -> 47 | U25: =ROUNDDOWN(YEARFRAC($E25,$G25,3),0) -> 38 | V25: =YEARFRAC($G25,Analysis_Date,3) -> 9.1808219 | W25: =MAX(ROUNDDOWN(NRA-T25,0),0) -> 13 | X25: =L25*W25 -> 5154337.2 | Y25: =IF($D25=$C$1,VLOOKUP($T25,Mortality_Table,3,FALSE),VLOOKUP($T25,Mortality_Table,2,FALSE)) -> 0.00417 | Z25: =IF($D25=$C$1,VLOOKUP($T25,Male_Annuity_Tables,MATCH($W25+2,'Mortality Tables'!$DS$1:$HT$1,0),FALSE),VLOOKUP($T25,Fe_Annuity_Tables,MATCH($W25+2,'Mortality Tables'!$M$1:$DN$1,0),FALSE)) -> 0.25379495 | AB25: =IFERROR(IF($W25>=AB$3,($H25*(1+Ann_Salary_Growth_Rate)^AB$3),""),0) -> 2663455.2 | AC25: =IFERROR(IF($W25>=AC$3,($H25*(1+Ann_Salary_Growth_Rate)^AC$3),""),0) -> 2799158.2 | AD25: =IFERROR(IF($W25>=AD$3,($H25*(1+Ann_Salary_Growth_Rate)^AD$3),""),0) -> 2941775.3 | AE25: =IFERROR(IF($W25>=AE$3,($H25*(1+Ann_Salary_Growth_Rate)^AE$3),""),0) -> 3091658.8 | AF25: =IFERROR(IF($W25>=AF$3,($H25*(1+Ann_Salary_Growth_Rate)^AF$3),""),0) -> 3249178.8 | AG25: =IFERROR(IF($W25>=AG$3,($H25*(1+Ann_Salary_Growth_Rate)^AG$3),""),0) -> 3414724.4 | AH25: =IFERROR(IF($W25>=AH$3,($H25*(1+Ann_Salary_Growth_Rate)^AH$3),""),0) -> 3588704.7 | AI25: =IFERROR(IF($W25>=AI$3,($H25*(1+Ann_Salary_Growth_Rate)^AI$3),""),0) -> 3771549.2 | ... BQ25: =IFERROR(IF($W25>=BQ$3,($H25*(1+Ann_Salary_Growth_Rate)^BQ$3),""),0) | BS25: =IFERROR(($L25+AB25*Contr_Rate)*(1+Inv_Return)*IF($D25=$C$1,VLOOKUP($T25,Male_Annuity_Tables,MATCH($BS$3+3,'Mortality Tables'!$N$1:$DN$1,0),FALSE),VLOOKUP($T25,Fe_Annuity_Tables,MATCH(BS$3+3,'Mortality Tables'!$N$1:$DN$1,0),FALSE)),"") -> 1039932.8 | BT25: =IFERROR(($BS25+AC25*Contr_Rate)*(1+Inv_Return)*IF($D25=$C$1,VLOOKUP($T25,Male_Annuity_Tables,MATCH($BS$3+3,'Mortality Tables'!$N$1:$DN$1,0),FALSE),VLOOKUP($T25,Fe_Annuity_Tables,MATCH(BT$3+3,'Mortality Tables'!$N$1:$DN$1,0),FALSE)),"") -> 1635049.6 | BU25: =IFERROR((BT25+AD25*Contr_Rate)*(1+Inv_Return)*IF($D25=$C$1,VLOOKUP($T25,Male_Annuity_Tables,MATCH($BS$3+3,'Mortality Tables'!$N$1:$DN$1,0),FALSE),VLOOKUP($T25,Fe_Annuity_Tables,MATCH(BU$3+3,'Mortality Tables'!$N$1:$DN$1,0),FALSE)),"") -> 2189932 | BV25: =IFERROR((BU25+AE25*Contr_Rate)*(1+Inv_Return)*IF($D25=$C$1,VLOOKUP($T25,Male_Annuity_Tables,MATCH($BS$3+3,'Mortality Tables'!$N$1:$DN$1,0),FALSE),VLOOKUP($T25,Fe_Annuity_Tables,MATCH(BV$3+3,'Mortality Tables'!$N$1:$DN$1,0),FALSE)),"") -> 2711712.3 | BW25: =IFERROR((BV25+AF25*Contr_Rate)*(1+Inv_Return)*IF($D25=$C$1,VLOOKUP($T25,Male_Annuity_Tables,MATCH($BS$3+3,'Mortality Tables'!$N$1:$DN$1,0),FALSE),VLOOKUP($T25,Fe_Annuity_Tables,MATCH(BW$3+3,'Mortality Tables'!$N$1:$DN$1,0),FALSE)),"") -> 3206691.5 | BX25: =IFERROR((BW25+AG25*Contr_Rate)*(1+Inv_Return)*IF($D25=$C$1,VLOOKUP($T25,Male_Annuity_Tables,MATCH($BS$3+3,'Mortality Tables'!$N$1:$DN$1,0),FALSE),VLOOKUP($T25,Fe_Annuity_Tables,MATCH(BX$3+3,'Mortality Tables'!$N$1:$DN$1,0),FALSE)),"") -> 3680452 | BY25: =IFERROR((BX25+AH25*Contr_Rate)*(1+Inv_Return)*IF($D25=$C$1,VLOOKUP($T25,Male_Annuity_Tables,MATCH($BS$3+3,'Mortality Tables'!$N$1:$DN$1,0),FALSE),VLOOKUP($T25,Fe_Annuity_Tables,MATCH(BY$3+3,'Mortality Tables'!$N$1:$DN$1,0),FALSE)),"") -> 4137956.3 | BZ25: =IFERROR((BY25+AI25*Contr_Rate)*(1+Inv_Return)*IF($D25=$C$1,VLOOKUP($T25,Male_Annuity_Tables,MATCH($BS$3+3,'Mortality Tables'!$N$1:$DN$1,0),FALSE),VLOOKUP($T25,Fe_Annuity_Tables,MATCH(BZ$3+3,'Mortality Tables'!$N$1:$DN$1,0),FALSE)),"") -> 4583633.2 | CA25: =IFERROR((BZ25+AJ25*Contr_Rate)*(1+Inv_Return)*IF($D25=$C$1,VLOOKUP($T25,Male_Annuity_Tables,MATCH($BS$3+3,'Mortality Tables'!$N$1:$DN$1,0),FALSE),VLOOKUP($T25,Fe_Annuity_Tables,MATCH(CA$3+3,'Mortality Tables'!$N$1:$DN$1,0),FALSE)),"") -> 5021453.2 | CB25: =IFERROR((CA25+AK25*Contr_Rate)*(1+Inv_Return)*IF($D25=$C$1,VLOOKUP($T25,Male_Annuity_Tables,MATCH($BS$3+3,'Mortality Tables'!$N$1:$DN$1,0),FALSE),VLOOKUP($T25,Fe_Annuity_Tables,MATCH(CB$3+3,'Mortality Tables'!$N$1:$DN$1,0),FALSE)),"") -> 5454993.5 | ... DH25: =IFERROR((DG25+BQ25*Contr_Rate)*(1+Inv_Return)*IF($D25=$C$1,VLOOKUP($T25,Male_Annuity_Tables,MATCH($BS$3+3,'Mortality Tables'!$N$1:$DN$1,0),FALSE),VLOOKUP($T25,Fe_Annuity_Tables,MATCH(DH$3+3,'Mortality Tables'!$N$1:$DN$1,0),FALSE)),"") | DJ25: =MAX(BS25:DH25) -> 6760976.3 | DK25: =IF($D25="FEMALE",Fe_Annuity_Factor,Male_Annuity_Factor) -> 8.0909278 | DL25: =(DJ25*Annuity_Ratio)/DK25 -> 559868.32 | DM25: =MAX($AB25:$BQ25) -> 4835373.7 | DN25: =IFERROR((DL25/DM25),"") -> 0.11578595 | DP25: =IFERROR(IF($D25=$C$1,VLOOKUP($T25+DP$3-1,Male_Annuity_Tables,2,FALSE),VLOOKUP($T25,Fe_Annuity_Tables,2,FALSE))*BS25,"") -> 159675.96 | DQ25: =IFERROR(IF($D25=$C$1,VLOOKUP($T25+DQ$3-1,Male_Annuity_Tables,2,FALSE),VLOOKUP($T25,Fe_Annuity_Tables,2,FALSE))*BT25,"") -> 251581 | DR25: =IFERROR(IF($D25=$C$1,VLOOKUP($T25+DR$3-1,Male_Annuity_Tables,2,FALSE),VLOOKUP($T25,Fe_Annuity_Tables,2,FALSE))*BU25,"") -> 337797
A26: M0023 | B26: Ashley Garrett | C26: Dormant | D26: Female | E26: 34443 | F26: 42542 | G26: 43777 | H26: 1188346 | I26: 114610.83 | J26: 104293.12 | K26: 37082.7 | L26: 255986.65 | M26: =IF(COUNTIF($A$4:A204,A26)=1,0,1) -> 0 | N26: =IF(T26<=18,"WHAT!!!",IF(T26>100,"EERM","Okay")) -> Okay | O26: =IF(G26>E26,"TRUE","FALSE") -> TRUE | P26: =G26>=Comm_Date -> TRUE | Q26: =$G26>=$F26 -> TRUE | R26: =$F26>$E26 -> TRUE | S26: =YEARFRAC(E26,F26,3) -> 22.189041 | T26: =ROUNDDOWN(YEARFRAC($E26,Analysis_Date,3),0) -> 30 | U26: =ROUNDDOWN(YEARFRAC($E26,$G26,3),0) -> 25 | V26: =YEARFRAC($G26,Analysis_Date,3) -> 5.1479452 | W26: =MAX(ROUNDDOWN(NRA-T26,0),0) -> 30 | X26: =L26*W26 -> 7679599.5 | Y26: =IF($D26=$C$1,VLOOKUP($T26,Mortality_Table,3,FALSE),VLOOKUP($T26,Mortality_Table,2,FALSE)) -> 0.00132 | Z26: =IF($D26=$C$1,VLOOKUP($T26,Male_Annuity_Tables,MATCH($W26+2,'Mortality Tables'!$DS$1:$HT$1,0),FALSE),VLOOKUP($T26,Fe_Annuity_Tables,MATCH($W26+2,'Mortality Tables'!$M$1:$DN$1,0),FALSE)) -> 0.0087708575 | AB26: =IFERROR(IF($W26>=AB$3,($H26*(1+Ann_Salary_Growth_Rate)^AB$3),""),0) -> 1248892.2 | AC26: =IFERROR(IF($W26>=AC$3,($H26*(1+Ann_Salary_Growth_Rate)^AC$3),""),0) -> 1312523.3 | AD26: =IFERROR(IF($W26>=AD$3,($H26*(1+Ann_Salary_Growth_Rate)^AD$3),""),0) -> 1379396.3 | AE26: =IFERROR(IF($W26>=AE$3,($H26*(1+Ann_Salary_Growth_Rate)^AE$3),""),0) -> 1449676.6 | AF26: =IFERROR(IF($W26>=AF$3,($H26*(1+Ann_Salary_Growth_Rate)^AF$3),""),0) -> 1523537.6 | AG26: =IFERROR(IF($W26>=AG$3,($H26*(1+Ann_Salary_Growth_Rate)^AG$3),""),0) -> 1601161.9 | AH26: =IFERROR(IF($W26>=AH$3,($H26*(1+Ann_Salary_Growth_Rate)^AH$3),""),0) -> 1682741.1 | AI26: =IFERROR(IF($W26>=AI$3,($H26*(1+Ann_Salary_Growth_Rate)^AI$3),""),0) -> 1768476.7 | ... BQ26: =IFERROR(IF($W26>=BQ$3,($H26*(1+Ann_Salary_Growth_Rate)^BQ$3),""),0) | BS26: =IFERROR(($L26+AB26*Contr_Rate)*(1+Inv_Return)*IF($D26=$C$1,VLOOKUP($T26,Male_Annuity_Tables,MATCH($BS$3+3,'Mortality Tables'!$N$1:$DN$1,0),FALSE),VLOOKUP($T26,Fe_Annuity_Tables,MATCH(BS$3+3,'Mortality Tables'!$N$1:$DN$1,0),FALSE)),"") -> 517786.28 | BT26: =IFERROR(($BS26+AC26*Contr_Rate)*(1+Inv_Return)*IF($D26=$C$1,VLOOKUP($T26,Male_Annuity_Tables,MATCH($BS$3+3,'Mortality Tables'!$N$1:$DN$1,0),FALSE),VLOOKUP($T26,Fe_Annuity_Tables,MATCH(BT$3+3,'Mortality Tables'!$N$1:$DN$1,0),FALSE)),"") -> 597915.41 | BU26: =IFERROR((BT26+AD26*Contr_Rate)*(1+Inv_Return)*IF($D26=$C$1,VLOOKUP($T26,Male_Annuity_Tables,MATCH($BS$3+3,'Mortality Tables'!$N$1:$DN$1,0),FALSE),VLOOKUP($T26,Fe_Annuity_Tables,MATCH(BU$3+3,'Mortality Tables'!$N$1:$DN$1,0),FALSE)),"") -> 530174.93 | BV26: =IFERROR((BU26+AE26*Contr_Rate)*(1+Inv_Return)*IF($D26=$C$1,VLOOKUP($T26,Male_Annuity_Tables,MATCH($BS$3+3,'Mortality Tables'!$N$1:$DN$1,0),FALSE),VLOOKUP($T26,Fe_Annuity_Tables,MATCH(BV$3+3,'Mortality Tables'!$N$1:$DN$1,0),FALSE)),"") -> 404006.11 | BW26: =IFERROR((BV26+AF26*Contr_Rate)*(1+Inv_Return)*IF($D26=$C$1,VLOOKUP($T26,Male_Annuity_Tables,MATCH($BS$3+3,'Mortality Tables'!$N$1:$DN$1,0),FALSE),VLOOKUP($T26,Fe_Annuity_Tables,MATCH(BW$3+3,'Mortality Tables'!$N$1:$DN$1,0),FALSE)),"") -> 287947.83 | BX26: =IFERROR((BW26+AG26*Contr_Rate)*(1+Inv_Return)*IF($D26=$C$1,VLOOKUP($T26,Male_Annuity_Tables,MATCH($BS$3+3,'Mortality Tables'!$N$1:$DN$1,0),FALSE),VLOOKUP($T26,Fe_Annuity_Tables,MATCH(BX$3+3,'Mortality Tables'!$N$1:$DN$1,0),FALSE)),"") -> 205225.09 | BY26: =IFERROR((BX26+AH26*Contr_Rate)*(1+Inv_Return)*IF($D26=$C$1,VLOOKUP($T26,Male_Annuity_Tables,MATCH($BS$3+3,'Mortality Tables'!$N$1:$DN$1,0),FALSE),VLOOKUP($T26,Fe_Annuity_Tables,MATCH(BY$3+3,'Mortality Tables'!$N$1:$DN$1,0),FALSE)),"") -> 151492.9 | BZ26: =IFERROR((BY26+AI26*Contr_Rate)*(1+Inv_Return)*IF($D26=$C$1,VLOOKUP($T26,Male_Annuity_Tables,MATCH($BS$3+3,'Mortality Tables'!$N$1:$DN$1,0),FALSE),VLOOKUP($T26,Fe_Annuity_Tables,MATCH(BZ$3+3,'Mortality Tables'!$N$1:$DN$1,0),FALSE)),"") -> 116221.1 | CA26: =IFERROR((BZ26+AJ26*Contr_Rate)*(1+Inv_Return)*IF($D26=$C$1,VLOOKUP($T26,Male_Annuity_Tables,MATCH($BS$3+3,'Mortality Tables'!$N$1:$DN$1,0),FALSE),VLOOKUP($T26,Fe_Annuity_Tables,MATCH(CA$3+3,'Mortality Tables'!$N$1:$DN$1,0),FALSE)),"") -> 91694.589 | CB26: =IFERROR((CA26+AK26*Contr_Rate)*(1+Inv_Return)*IF($D26=$C$1,VLOOKUP($T26,Male_Annuity_Tables,MATCH($BS$3+3,'Mortality Tables'!$N$1:$DN$1,0),FALSE),VLOOKUP($T26,Fe_Annuity_Tables,MATCH(CB$3+3,'Mortality Tables'!$N$1:$DN$1,0),FALSE)),"") -> 73644.014 | ... DH26: =IFERROR((DG26+BQ26*Contr_Rate)*(1+Inv_Return)*IF($D26=$C$1,VLOOKUP($T26,Male_Annuity_Tables,MATCH($BS$3+3,'Mortality Tables'!$N$1:$DN$1,0),FALSE),VLOOKUP($T26,Fe_Annuity_Tables,MATCH(DH$3+3,'Mortality Tables'!$N$1:$DN$1,0),FALSE)),"") | DJ26: =MAX(BS26:DH26) -> 597915.41 | DK26: =IF($D26="FEMALE",Fe_Annuity_Factor,Male_Annuity_Factor) -> 8.8017766 | DL26: =(DJ26*Annuity_Ratio)/DK26 -> 45513.917 | DM26: =MAX($AB26:$BQ26) -> 5277212 | DN26: =IFERROR((DL26/DM26),"") -> 0.008624614 | DP26: =IFERROR(IF($D26=$C$1,VLOOKUP($T26+DP$3-1,Male_Annuity_Tables,2,FALSE),VLOOKUP($T26,Fe_Annuity_Tables,2,FALSE))*BS26,"") -> 104104.04 | DQ26: =IFERROR(IF($D26=$C$1,VLOOKUP($T26+DQ$3-1,Male_Annuity_Tables,2,FALSE),VLOOKUP($T26,Fe_Annuity_Tables,2,FALSE))*BT26,"") -> 120214.48 | DR26: =IFERROR(IF($D26=$C$1,VLOOKUP($T26+DR$3-1,Male_Annuity_Tables,2,FALSE),VLOOKUP($T26,Fe_Annuity_Tables,2,FALSE))*BU26,"") -> 106594.85
A27: M0024 | B27: Phillip Ryan | C27: Exited | D27: Female | E27: 35007 | F27: 42286 | G27: 42424 | H27: 2137524 | I27: 203023.53 | J27: 155129.32 | L27: 358152.85 | M27: =IF(COUNTIF($A$4:A204,A27)=1,0,1) -> 0 | N27: =IF(T27<=18,"WHAT!!!",IF(T27>100,"EERM","Okay")) -> Okay | O27: =IF(G27>E27,"TRUE","FALSE") -> TRUE | P27: =G27>=Comm_Date -> TRUE | Q27: =$G27>=$F27 -> TRUE | R27: =$F27>$E27 -> TRUE | S27: =YEARFRAC(E27,F27,3) -> 19.942466 | T27: =ROUNDDOWN(YEARFRAC($E27,Analysis_Date,3),0) -> 29 | U27: =ROUNDDOWN(YEARFRAC($E27,$G27,3),0) -> 20 | V27: =YEARFRAC($G27,Analysis_Date,3) -> 8.8547945 | W27: =MAX(ROUNDDOWN(NRA-T27,0),0) -> 31 | X27: =L27*W27 -> 11102738 | Y27: =IF($D27=$C$1,VLOOKUP($T27,Mortality_Table,3,FALSE),VLOOKUP($T27,Mortality_Table,2,FALSE)) -> 0.0013 | Z27: =IF($D27=$C$1,VLOOKUP($T27,Male_Annuity_Tables,MATCH($W27+2,'Mortality Tables'!$DS$1:$HT$1,0),FALSE),VLOOKUP($T27,Fe_Annuity_Tables,MATCH($W27+2,'Mortality Tables'!$M$1:$DN$1,0),FALSE)) -> 0.0070075643 | AB27: =IFERROR(IF($W27>=AB$3,($H27*(1+Ann_Salary_Growth_Rate)^AB$3),""),0) -> 2246430.8 | AC27: =IFERROR(IF($W27>=AC$3,($H27*(1+Ann_Salary_Growth_Rate)^AC$3),""),0) -> 2360886.5 | AD27: =IFERROR(IF($W27>=AD$3,($H27*(1+Ann_Salary_Growth_Rate)^AD$3),""),0) -> 2481173.7 | AE27: =IFERROR(IF($W27>=AE$3,($H27*(1+Ann_Salary_Growth_Rate)^AE$3),""),0) -> 2607589.5 | AF27: =IFERROR(IF($W27>=AF$3,($H27*(1+Ann_Salary_Growth_Rate)^AF$3),""),0) -> 2740446.1 | AG27: =IFERROR(IF($W27>=AG$3,($H27*(1+Ann_Salary_Growth_Rate)^AG$3),""),0) -> 2880071.9 | AH27: =IFERROR(IF($W27>=AH$3,($H27*(1+Ann_Salary_Growth_Rate)^AH$3),""),0) -> 3026811.5 | AI27: =IFERROR(IF($W27>=AI$3,($H27*(1+Ann_Salary_Growth_Rate)^AI$3),""),0) -> 3181027.6 | ... BQ27: =IFERROR(IF($W27>=BQ$3,($H27*(1+Ann_Salary_Growth_Rate)^BQ$3),""),0) | BS27: =IFERROR(($L27+AB27*Contr_Rate)*(1+Inv_Return)*IF($D27=$C$1,VLOOKUP($T27,Male_Annuity_Tables,MATCH($BS$3+3,'Mortality Tables'!$N$1:$DN$1,0),FALSE),VLOOKUP($T27,Fe_Annuity_Tables,MATCH(BS$3+3,'Mortality Tables'!$N$1:$DN$1,0),FALSE)),"") -> 847387.62 | BT27: =IFERROR(($BS27+AC27*Contr_Rate)*(1+Inv_Return)*IF($D27=$C$1,VLOOKUP($T27,Male_Annuity_Tables,MATCH($BS$3+3,'Mortality Tables'!$N$1:$DN$1,0),FALSE),VLOOKUP($T27,Fe_Annuity_Tables,MATCH(BT$3+3,'Mortality Tables'!$N$1:$DN$1,0),FALSE)),"") -> 1020462.6 | BU27: =IFERROR((BT27+AD27*Contr_Rate)*(1+Inv_Return)*IF($D27=$C$1,VLOOKUP($T27,Male_Annuity_Tables,MATCH($BS$3+3,'Mortality Tables'!$N$1:$DN$1,0),FALSE),VLOOKUP($T27,Fe_Annuity_Tables,MATCH(BU$3+3,'Mortality Tables'!$N$1:$DN$1,0),FALSE)),"") -> 924882.6 | BV27: =IFERROR((BU27+AE27*Contr_Rate)*(1+Inv_Return)*IF($D27=$C$1,VLOOKUP($T27,Male_Annuity_Tables,MATCH($BS$3+3,'Mortality Tables'!$N$1:$DN$1,0),FALSE),VLOOKUP($T27,Fe_Annuity_Tables,MATCH(BV$3+3,'Mortality Tables'!$N$1:$DN$1,0),FALSE)),"") -> 714746.16 | BW27: =IFERROR((BV27+AF27*Contr_Rate)*(1+Inv_Return)*IF($D27=$C$1,VLOOKUP($T27,Male_Annuity_Tables,MATCH($BS$3+3,'Mortality Tables'!$N$1:$DN$1,0),FALSE),VLOOKUP($T27,Fe_Annuity_Tables,MATCH(BW$3+3,'Mortality Tables'!$N$1:$DN$1,0),FALSE)),"") -> 514032.47 | BX27: =IFERROR((BW27+AG27*Contr_Rate)*(1+Inv_Return)*IF($D27=$C$1,VLOOKUP($T27,Male_Annuity_Tables,MATCH($BS$3+3,'Mortality Tables'!$N$1:$DN$1,0),FALSE),VLOOKUP($T27,Fe_Annuity_Tables,MATCH(BX$3+3,'Mortality Tables'!$N$1:$DN$1,0),FALSE)),"") -> 368186.57 | BY27: =IFERROR((BX27+AH27*Contr_Rate)*(1+Inv_Return)*IF($D27=$C$1,VLOOKUP($T27,Male_Annuity_Tables,MATCH($BS$3+3,'Mortality Tables'!$N$1:$DN$1,0),FALSE),VLOOKUP($T27,Fe_Annuity_Tables,MATCH(BY$3+3,'Mortality Tables'!$N$1:$DN$1,0),FALSE)),"") -> 272367.74 | BZ27: =IFERROR((BY27+AI27*Contr_Rate)*(1+Inv_Return)*IF($D27=$C$1,VLOOKUP($T27,Male_Annuity_Tables,MATCH($BS$3+3,'Mortality Tables'!$N$1:$DN$1,0),FALSE),VLOOKUP($T27,Fe_Annuity_Tables,MATCH(BZ$3+3,'Mortality Tables'!$N$1:$DN$1,0),FALSE)),"") -> 209102.8 | CA27: =IFERROR((BZ27+AJ27*Contr_Rate)*(1+Inv_Return)*IF($D27=$C$1,VLOOKUP($T27,Male_Annuity_Tables,MATCH($BS$3+3,'Mortality Tables'!$N$1:$DN$1,0),FALSE),VLOOKUP($T27,Fe_Annuity_Tables,MATCH(CA$3+3,'Mortality Tables'!$N$1:$DN$1,0),FALSE)),"") -> 165012.65 | CB27: =IFERROR((CA27+AK27*Contr_Rate)*(1+Inv_Return)*IF($D27=$C$1,VLOOKUP($T27,Male_Annuity_Tables,MATCH($BS$3+3,'Mortality Tables'!$N$1:$DN$1,0),FALSE),VLOOKUP($T27,Fe_Annuity_Tables,MATCH(CB$3+3,'Mortality Tables'!$N$1:$DN$1,0),FALSE)),"") -> 132543.84 | ... DH27: =IFERROR((DG27+BQ27*Contr_Rate)*(1+Inv_Return)*IF($D27=$C$1,VLOOKUP($T27,Male_Annuity_Tables,MATCH($BS$3+3,'Mortality Tables'!$N$1:$DN$1,0),FALSE),VLOOKUP($T27,Fe_Annuity_Tables,MATCH(DH$3+3,'Mortality Tables'!$N$1:$DN$1,0),FALSE)),"") | DJ27: =MAX(BS27:DH27) -> 1020462.6 | DK27: =IF($D27="FEMALE",Fe_Annuity_Factor,Male_Annuity_Factor) -> 8.8017766 | DL27: =(DJ27*Annuity_Ratio)/DK27 -> 77678.629 | DM27: =MAX($AB27:$BQ27) -> 9975959.8 | DN27: =IFERROR((DL27/DM27),"") -> 0.007786582 | DP27: =IFERROR(IF($D27=$C$1,VLOOKUP($T27+DP$3-1,Male_Annuity_Tables,2,FALSE),VLOOKUP($T27,Fe_Annuity_Tables,2,FALSE))*BS27,"") -> 170358.81 | DQ27: =IFERROR(IF($D27=$C$1,VLOOKUP($T27+DQ$3-1,Male_Annuity_Tables,2,FALSE),VLOOKUP($T27,Fe_Annuity_Tables,2,FALSE))*BT27,"") -> 205153.8 | DR27: =IFERROR(IF($D27=$C$1,VLOOKUP($T27+DR$3-1,Male_Annuity_Tables,2,FALSE),VLOOKUP($T27,Fe_Annuity_Tables,2,FALSE))*BU27,"") -> 185938.4
A28: M0025 | B28: Alec Hickman | C28: Active | D28: Female | E28: 29468 | F28: 37949 | G28: 38668 | H28: 388224 | I28: 30830.98 | J28: 23878 | L28: 54708.98 | M28: =IF(COUNTIF($A$4:A204,A28)=1,0,1) -> 0 | N28: =IF(T28<=18,"WHAT!!!",IF(T28>100,"EERM","Okay")) -> Okay | O28: =IF(G28>E28,"TRUE","FALSE") -> TRUE | P28: =G28>=Comm_Date -> TRUE | Q28: =$G28>=$F28 -> TRUE | R28: =$F28>$E28 -> TRUE | S28: =YEARFRAC(E28,F28,3) -> 23.235616 | T28: =ROUNDDOWN(YEARFRAC($E28,Analysis_Date,3),0) -> 44 | U28: =ROUNDDOWN(YEARFRAC($E28,$G28,3),0) -> 25 | V28: =YEARFRAC($G28,Analysis_Date,3) -> 19.145205 | W28: =MAX(ROUNDDOWN(NRA-T28,0),0) -> 16 | X28: =L28*W28 -> 875343.68 | Y28: =IF($D28=$C$1,VLOOKUP($T28,Mortality_Table,3,FALSE),VLOOKUP($T28,Mortality_Table,2,FALSE)) -> 0.00245 | Z28: =IF($D28=$C$1,VLOOKUP($T28,Male_Annuity_Tables,MATCH($W28+2,'Mortality Tables'!$DS$1:$HT$1,0),FALSE),VLOOKUP($T28,Fe_Annuity_Tables,MATCH($W28+2,'Mortality Tables'!$M$1:$DN$1,0),FALSE)) -> 0.16022938 | AB28: =IFERROR(IF($W28>=AB$3,($H28*(1+Ann_Salary_Growth_Rate)^AB$3),""),0) -> 408004.01 | AC28: =IFERROR(IF($W28>=AC$3,($H28*(1+Ann_Salary_Growth_Rate)^AC$3),""),0) -> 428791.82 | AD28: =IFERROR(IF($W28>=AD$3,($H28*(1+Ann_Salary_Growth_Rate)^AD$3),""),0) -> 450638.76 | AE28: =IFERROR(IF($W28>=AE$3,($H28*(1+Ann_Salary_Growth_Rate)^AE$3),""),0) -> 473598.81 | AF28: =IFERROR(IF($W28>=AF$3,($H28*(1+Ann_Salary_Growth_Rate)^AF$3),""),0) -> 497728.66 | AG28: =IFERROR(IF($W28>=AG$3,($H28*(1+Ann_Salary_Growth_Rate)^AG$3),""),0) -> 523087.94 | AH28: =IFERROR(IF($W28>=AH$3,($H28*(1+Ann_Salary_Growth_Rate)^AH$3),""),0) -> 549739.27 | AI28: =IFERROR(IF($W28>=AI$3,($H28*(1+Ann_Salary_Growth_Rate)^AI$3),""),0) -> 577748.49 | ... BQ28: =IFERROR(IF($W28>=BQ$3,($H28*(1+Ann_Salary_Growth_Rate)^BQ$3),""),0) | BS28: =IFERROR(($L28+AB28*Contr_Rate)*(1+Inv_Return)*IF($D28=$C$1,VLOOKUP($T28,Male_Annuity_Tables,MATCH($BS$3+3,'Mortality Tables'!$N$1:$DN$1,0),FALSE),VLOOKUP($T28,Fe_Annuity_Tables,MATCH(BS$3+3,'Mortality Tables'!$N$1:$DN$1,0),FALSE)),"") -> 154326.31 | BT28: =IFERROR(($BS28+AC28*Contr_Rate)*(1+Inv_Return)*IF($D28=$C$1,VLOOKUP($T28,Male_Annuity_Tables,MATCH($BS$3+3,'Mortality Tables'!$N$1:$DN$1,0),FALSE),VLOOKUP($T28,Fe_Annuity_Tables,MATCH(BT$3+3,'Mortality Tables'!$N$1:$DN$1,0),FALSE)),"") -> 209031.3 | BU28: =IFERROR((BT28+AD28*Contr_Rate)*(1+Inv_Return)*IF($D28=$C$1,VLOOKUP($T28,Male_Annuity_Tables,MATCH($BS$3+3,'Mortality Tables'!$N$1:$DN$1,0),FALSE),VLOOKUP($T28,Fe_Annuity_Tables,MATCH(BU$3+3,'Mortality Tables'!$N$1:$DN$1,0),FALSE)),"") -> 215536.76 | BV28: =IFERROR((BU28+AE28*Contr_Rate)*(1+Inv_Return)*IF($D28=$C$1,VLOOKUP($T28,Male_Annuity_Tables,MATCH($BS$3+3,'Mortality Tables'!$N$1:$DN$1,0),FALSE),VLOOKUP($T28,Fe_Annuity_Tables,MATCH(BV$3+3,'Mortality Tables'!$N$1:$DN$1,0),FALSE)),"") -> 189759.86 | BW28: =IFERROR((BV28+AF28*Contr_Rate)*(1+Inv_Return)*IF($D28=$C$1,VLOOKUP($T28,Male_Annuity_Tables,MATCH($BS$3+3,'Mortality Tables'!$N$1:$DN$1,0),FALSE),VLOOKUP($T28,Fe_Annuity_Tables,MATCH(BW$3+3,'Mortality Tables'!$N$1:$DN$1,0),FALSE)),"") -> 152439.2 | BX28: =IFERROR((BW28+AG28*Contr_Rate)*(1+Inv_Return)*IF($D28=$C$1,VLOOKUP($T28,Male_Annuity_Tables,MATCH($BS$3+3,'Mortality Tables'!$N$1:$DN$1,0),FALSE),VLOOKUP($T28,Fe_Annuity_Tables,MATCH(BX$3+3,'Mortality Tables'!$N$1:$DN$1,0),FALSE)),"") -> 117807.62 | BY28: =IFERROR((BX28+AH28*Contr_Rate)*(1+Inv_Return)*IF($D28=$C$1,VLOOKUP($T28,Male_Annuity_Tables,MATCH($BS$3+3,'Mortality Tables'!$N$1:$DN$1,0),FALSE),VLOOKUP($T28,Fe_Annuity_Tables,MATCH(BY$3+3,'Mortality Tables'!$N$1:$DN$1,0),FALSE)),"") -> 96533.681 | BZ28: =IFERROR((BY28+AI28*Contr_Rate)*(1+Inv_Return)*IF($D28=$C$1,VLOOKUP($T28,Male_Annuity_Tables,MATCH($BS$3+3,'Mortality Tables'!$N$1:$DN$1,0),FALSE),VLOOKUP($T28,Fe_Annuity_Tables,MATCH(BZ$3+3,'Mortality Tables'!$N$1:$DN$1,0),FALSE)),"") -> 82589.264 | CA28: =IFERROR((BZ28+AJ28*Contr_Rate)*(1+Inv_Return)*IF($D28=$C$1,VLOOKUP($T28,Male_Annuity_Tables,MATCH($BS$3+3,'Mortality Tables'!$N$1:$DN$1,0),FALSE),VLOOKUP($T28,Fe_Annuity_Tables,MATCH(CA$3+3,'Mortality Tables'!$N$1:$DN$1,0),FALSE)),"") -> 72603.186 | CB28: =IFERROR((CA28+AK28*Contr_Rate)*(1+Inv_Return)*IF($D28=$C$1,VLOOKUP($T28,Male_Annuity_Tables,MATCH($BS$3+3,'Mortality Tables'!$N$1:$DN$1,0),FALSE),VLOOKUP($T28,Fe_Annuity_Tables,MATCH(CB$3+3,'Mortality Tables'!$N$1:$DN$1,0),FALSE)),"") -> 64861.203 | ... DH28: =IFERROR((DG28+BQ28*Contr_Rate)*(1+Inv_Return)*IF($D28=$C$1,VLOOKUP($T28,Male_Annuity_Tables,MATCH($BS$3+3,'Mortality Tables'!$N$1:$DN$1,0),FALSE),VLOOKUP($T28,Fe_Annuity_Tables,MATCH(DH$3+3,'Mortality Tables'!$N$1:$DN$1,0),FALSE)),"") | DJ28: =MAX(BS28:DH28) -> 215536.76 | DK28: =IF($D28="FEMALE",Fe_Annuity_Factor,Male_Annuity_Factor) -> 8.8017766 | DL28: =(DJ28*Annuity_Ratio)/DK28 -> 16406.873 | DM28: =MAX($AB28:$BQ28) -> 859795.67 | DN28: =IFERROR((DL28/DM28),"") -> 0.019082293 | DP28: =IFERROR(IF($D28=$C$1,VLOOKUP($T28+DP$3-1,Male_Annuity_Tables,2,FALSE),VLOOKUP($T28,Fe_Annuity_Tables,2,FALSE))*BS28,"") -> 23470.33 | DQ28: =IFERROR(IF($D28=$C$1,VLOOKUP($T28+DQ$3-1,Male_Annuity_Tables,2,FALSE),VLOOKUP($T28,Fe_Annuity_Tables,2,FALSE))*BT28,"") -> 31790.003 | DR28: =IFERROR(IF($D28=$C$1,VLOOKUP($T28+DR$3-1,Male_Annuity_Tables,2,FALSE),VLOOKUP($T28,Fe_Annuity_Tables,2,FALSE))*BU28,"") -> 32779.369
A29: M0026 | B29: Keith Miller | C29: Active | D29: Male | E29: 33904 | F29: 45115 | G29: 45168 | H29: 1260251 | I29: 67259.62 | J29: 64991.96 | K29: 28137.03 | L29: 160388.61 | M29: =IF(COUNTIF($A$4:A204,A29)=1,0,1) -> 0 | N29: =IF(T29<=18,"WHAT!!!",IF(T29>100,"EERM","Okay")) -> Okay | O29: =IF(G29>E29,"TRUE","FALSE") -> TRUE | P29: =G29>=Comm_Date -> TRUE | Q29: =$G29>=$F29 -> TRUE | R29: =$F29>$E29 -> TRUE | S29: =YEARFRAC(E29,F29,3) -> 30.715068 | T29: =ROUNDDOWN(YEARFRAC($E29,Analysis_Date,3),0) -> 32 | U29: =ROUNDDOWN(YEARFRAC($E29,$G29,3),0) -> 30 | V29: =YEARFRAC($G29,Analysis_Date,3) -> 1.3369863 | W29: =MAX(ROUNDDOWN(NRA-T29,0),0) -> 28 | X29: =L29*W29 -> 4490881.1 | Y29: =IF($D29=$C$1,VLOOKUP($T29,Mortality_Table,3,FALSE),VLOOKUP($T29,Mortality_Table,2,FALSE)) -> 0.00148 | Z29: =IF($D29=$C$1,VLOOKUP($T29,Male_Annuity_Tables,MATCH($W29+2,'Mortality Tables'!$DS$1:$HT$1,0),FALSE),VLOOKUP($T29,Fe_Annuity_Tables,MATCH($W29+2,'Mortality Tables'!$M$1:$DN$1,0),FALSE)) -> 0.013180534 | AB29: =IFERROR(IF($W29>=AB$3,($H29*(1+Ann_Salary_Growth_Rate)^AB$3),""),0) -> 1324460.8 | AC29: =IFERROR(IF($W29>=AC$3,($H29*(1+Ann_Salary_Growth_Rate)^AC$3),""),0) -> 1391942.1 | AD29: =IFERROR(IF($W29>=AD$3,($H29*(1+Ann_Salary_Growth_Rate)^AD$3),""),0) -> 1462861.5 | AE29: =IFERROR(IF($W29>=AE$3,($H29*(1+Ann_Salary_Growth_Rate)^AE$3),""),0) -> 1537394.3 | AF29: =IFERROR(IF($W29>=AF$3,($H29*(1+Ann_Salary_Growth_Rate)^AF$3),""),0) -> 1615724.5 | AG29: =IFERROR(IF($W29>=AG$3,($H29*(1+Ann_Salary_Growth_Rate)^AG$3),""),0) -> 1698045.7 | AH29: =IFERROR(IF($W29>=AH$3,($H29*(1+Ann_Salary_Growth_Rate)^AH$3),""),0) -> 1784561.1 | AI29: =IFERROR(IF($W29>=AI$3,($H29*(1+Ann_Salary_Growth_Rate)^AI$3),""),0) -> 1875484.5 | ... BQ29: =IFERROR(IF($W29>=BQ$3,($H29*(1+Ann_Salary_Growth_Rate)^BQ$3),""),0) | BS29: =IFERROR(($L29+AB29*Contr_Rate)*(1+Inv_Return)*IF($D29=$C$1,VLOOKUP($T29,Male_Annuity_Tables,MATCH($BS$3+3,'Mortality Tables'!$N$1:$DN$1,0),FALSE),VLOOKUP($T29,Fe_Annuity_Tables,MATCH(BS$3+3,'Mortality Tables'!$N$1:$DN$1,0),FALSE)),"") -> 457837.26 | BT29: =IFERROR(($BS29+AC29*Contr_Rate)*(1+Inv_Return)*IF($D29=$C$1,VLOOKUP($T29,Male_Annuity_Tables,MATCH($BS$3+3,'Mortality Tables'!$N$1:$DN$1,0),FALSE),VLOOKUP($T29,Fe_Annuity_Tables,MATCH(BT$3+3,'Mortality Tables'!$N$1:$DN$1,0),FALSE)),"") -> 718631.07 | BU29: =IFERROR((BT29+AD29*Contr_Rate)*(1+Inv_Return)*IF($D29=$C$1,VLOOKUP($T29,Male_Annuity_Tables,MATCH($BS$3+3,'Mortality Tables'!$N$1:$DN$1,0),FALSE),VLOOKUP($T29,Fe_Annuity_Tables,MATCH(BU$3+3,'Mortality Tables'!$N$1:$DN$1,0),FALSE)),"") -> 950181.68 | BV29: =IFERROR((BU29+AE29*Contr_Rate)*(1+Inv_Return)*IF($D29=$C$1,VLOOKUP($T29,Male_Annuity_Tables,MATCH($BS$3+3,'Mortality Tables'!$N$1:$DN$1,0),FALSE),VLOOKUP($T29,Fe_Annuity_Tables,MATCH(BV$3+3,'Mortality Tables'!$N$1:$DN$1,0),FALSE)),"") -> 1158616.4 | BW29: =IFERROR((BV29+AF29*Contr_Rate)*(1+Inv_Return)*IF($D29=$C$1,VLOOKUP($T29,Male_Annuity_Tables,MATCH($BS$3+3,'Mortality Tables'!$N$1:$DN$1,0),FALSE),VLOOKUP($T29,Fe_Annuity_Tables,MATCH(BW$3+3,'Mortality Tables'!$N$1:$DN$1,0),FALSE)),"") -> 1349010.6 | BX29: =IFERROR((BW29+AG29*Contr_Rate)*(1+Inv_Return)*IF($D29=$C$1,VLOOKUP($T29,Male_Annuity_Tables,MATCH($BS$3+3,'Mortality Tables'!$N$1:$DN$1,0),FALSE),VLOOKUP($T29,Fe_Annuity_Tables,MATCH(BX$3+3,'Mortality Tables'!$N$1:$DN$1,0),FALSE)),"") -> 1525578.2 | BY29: =IFERROR((BX29+AH29*Contr_Rate)*(1+Inv_Return)*IF($D29=$C$1,VLOOKUP($T29,Male_Annuity_Tables,MATCH($BS$3+3,'Mortality Tables'!$N$1:$DN$1,0),FALSE),VLOOKUP($T29,Fe_Annuity_Tables,MATCH(BY$3+3,'Mortality Tables'!$N$1:$DN$1,0),FALSE)),"") -> 1691828.4 | BZ29: =IFERROR((BY29+AI29*Contr_Rate)*(1+Inv_Return)*IF($D29=$C$1,VLOOKUP($T29,Male_Annuity_Tables,MATCH($BS$3+3,'Mortality Tables'!$N$1:$DN$1,0),FALSE),VLOOKUP($T29,Fe_Annuity_Tables,MATCH(BZ$3+3,'Mortality Tables'!$N$1:$DN$1,0),FALSE)),"") -> 1850694.6 | CA29: =IFERROR((BZ29+AJ29*Contr_Rate)*(1+Inv_Return)*IF($D29=$C$1,VLOOKUP($T29,Male_Annuity_Tables,MATCH($BS$3+3,'Mortality Tables'!$N$1:$DN$1,0),FALSE),VLOOKUP($T29,Fe_Annuity_Tables,MATCH(CA$3+3,'Mortality Tables'!$N$1:$DN$1,0),FALSE)),"") -> 2004640.3 | CB29: =IFERROR((CA29+AK29*Contr_Rate)*(1+Inv_Return)*IF($D29=$C$1,VLOOKUP($T29,Male_Annuity_Tables,MATCH($BS$3+3,'Mortality Tables'!$N$1:$DN$1,0),FALSE),VLOOKUP($T29,Fe_Annuity_Tables,MATCH(CB$3+3,'Mortality Tables'!$N$1:$DN$1,0),FALSE)),"") -> 2155745.5 | ... DH29: =IFERROR((DG29+BQ29*Contr_Rate)*(1+Inv_Return)*IF($D29=$C$1,VLOOKUP($T29,Male_Annuity_Tables,MATCH($BS$3+3,'Mortality Tables'!$N$1:$DN$1,0),FALSE),VLOOKUP($T29,Fe_Annuity_Tables,MATCH(DH$3+3,'Mortality Tables'!$N$1:$DN$1,0),FALSE)),"") | DJ29: =MAX(BS29:DH29) -> 5695622.5 | DK29: =IF($D29="FEMALE",Fe_Annuity_Factor,Male_Annuity_Factor) -> 8.0909278 | DL29: =(DJ29*Annuity_Ratio)/DK29 -> 471647.65 | DM29: =MAX($AB29:$BQ29) -> 5067042.9 | DN29: =IFERROR((DL29/DM29),"") -> 0.093081441 | DP29: =IFERROR(IF($D29=$C$1,VLOOKUP($T29+DP$3-1,Male_Annuity_Tables,2,FALSE),VLOOKUP($T29,Fe_Annuity_Tables,2,FALSE))*BS29,"") -> 92109.531 | DQ29: =IFERROR(IF($D29=$C$1,VLOOKUP($T29+DQ$3-1,Male_Annuity_Tables,2,FALSE),VLOOKUP($T29,Fe_Annuity_Tables,2,FALSE))*BT29,"") -> 144605.82 | DR29: =IFERROR(IF($D29=$C$1,VLOOKUP($T29+DR$3-1,Male_Annuity_Tables,2,FALSE),VLOOKUP($T29,Fe_Annuity_Tables,2,FALSE))*BU29,"") -> 191252.57
A30: M0027 | B30: Kim Martinez | C30: Dormant | D30: Female | E30: 33638 | F30: 41806 | G30: 42832 | H30: 1198574 | I30: 92244.29 | J30: 103278.28 | K30: 30929.52 | L30: 226452.09 | M30: =IF(COUNTIF($A$4:A204,A30)=1,0,1) -> 0 | N30: =IF(T30<=18,"WHAT!!!",IF(T30>100,"EERM","Okay")) -> Okay | O30: =IF(G30>E30,"TRUE","FALSE") -> TRUE | P30: =G30>=Comm_Date -> TRUE | Q30: =$G30>=$F30 -> TRUE | R30: =$F30>$E30 -> TRUE | S30: =YEARFRAC(E30,F30,3) -> 22.378082 | T30: =ROUNDDOWN(YEARFRAC($E30,Analysis_Date,3),0) -> 32 | U30: =ROUNDDOWN(YEARFRAC($E30,$G30,3),0) -> 25 | V30: =YEARFRAC($G30,Analysis_Date,3) -> 7.7369863 | W30: =MAX(ROUNDDOWN(NRA-T30,0),0) -> 28 | X30: =L30*W30 -> 6340658.5 | Y30: =IF($D30=$C$1,VLOOKUP($T30,Mortality_Table,3,FALSE),VLOOKUP($T30,Mortality_Table,2,FALSE)) -> 0.00138 | Z30: =IF($D30=$C$1,VLOOKUP($T30,Male_Annuity_Tables,MATCH($W30+2,'Mortality Tables'!$DS$1:$HT$1,0),FALSE),VLOOKUP($T30,Fe_Annuity_Tables,MATCH($W30+2,'Mortality Tables'!$M$1:$DN$1,0),FALSE)) -> 0.013741129 | AB30: =IFERROR(IF($W30>=AB$3,($H30*(1+Ann_Salary_Growth_Rate)^AB$3),""),0) -> 1259641.3 | AC30: =IFERROR(IF($W30>=AC$3,($H30*(1+Ann_Salary_Growth_Rate)^AC$3),""),0) -> 1323820.1 | AD30: =IFERROR(IF($W30>=AD$3,($H30*(1+Ann_Salary_Growth_Rate)^AD$3),""),0) -> 1391268.7 | AE30: =IFERROR(IF($W30>=AE$3,($H30*(1+Ann_Salary_Growth_Rate)^AE$3),""),0) -> 1462153.8 | AF30: =IFERROR(IF($W30>=AF$3,($H30*(1+Ann_Salary_Growth_Rate)^AF$3),""),0) -> 1536650.6 | AG30: =IFERROR(IF($W30>=AG$3,($H30*(1+Ann_Salary_Growth_Rate)^AG$3),""),0) -> 1614942.9 | AH30: =IFERROR(IF($W30>=AH$3,($H30*(1+Ann_Salary_Growth_Rate)^AH$3),""),0) -> 1697224.3 | AI30: =IFERROR(IF($W30>=AI$3,($H30*(1+Ann_Salary_Growth_Rate)^AI$3),""),0) -> 1783697.8 | ... BQ30: =IFERROR(IF($W30>=BQ$3,($H30*(1+Ann_Salary_Growth_Rate)^BQ$3),""),0) | BS30: =IFERROR(($L30+AB30*Contr_Rate)*(1+Inv_Return)*IF($D30=$C$1,VLOOKUP($T30,Male_Annuity_Tables,MATCH($BS$3+3,'Mortality Tables'!$N$1:$DN$1,0),FALSE),VLOOKUP($T30,Fe_Annuity_Tables,MATCH(BS$3+3,'Mortality Tables'!$N$1:$DN$1,0),FALSE)),"") -> 496155.31 | BT30: =IFERROR(($BS30+AC30*Contr_Rate)*(1+Inv_Return)*IF($D30=$C$1,VLOOKUP($T30,Male_Annuity_Tables,MATCH($BS$3+3,'Mortality Tables'!$N$1:$DN$1,0),FALSE),VLOOKUP($T30,Fe_Annuity_Tables,MATCH(BT$3+3,'Mortality Tables'!$N$1:$DN$1,0),FALSE)),"") -> 585873.57 | BU30: =IFERROR((BT30+AD30*Contr_Rate)*(1+Inv_Return)*IF($D30=$C$1,VLOOKUP($T30,Male_Annuity_Tables,MATCH($BS$3+3,'Mortality Tables'!$N$1:$DN$1,0),FALSE),VLOOKUP($T30,Fe_Annuity_Tables,MATCH(BU$3+3,'Mortality Tables'!$N$1:$DN$1,0),FALSE)),"") -> 525615.31 | BV30: =IFERROR((BU30+AE30*Contr_Rate)*(1+Inv_Return)*IF($D30=$C$1,VLOOKUP($T30,Male_Annuity_Tables,MATCH($BS$3+3,'Mortality Tables'!$N$1:$DN$1,0),FALSE),VLOOKUP($T30,Fe_Annuity_Tables,MATCH(BV$3+3,'Mortality Tables'!$N$1:$DN$1,0),FALSE)),"") -> 403530.95 | BW30: =IFERROR((BV30+AF30*Contr_Rate)*(1+Inv_Return)*IF($D30=$C$1,VLOOKUP($T30,Male_Annuity_Tables,MATCH($BS$3+3,'Mortality Tables'!$N$1:$DN$1,0),FALSE),VLOOKUP($T30,Fe_Annuity_Tables,MATCH(BW$3+3,'Mortality Tables'!$N$1:$DN$1,0),FALSE)),"") -> 288977.09 | BX30: =IFERROR((BW30+AG30*Contr_Rate)*(1+Inv_Return)*IF($D30=$C$1,VLOOKUP($T30,Male_Annuity_Tables,MATCH($BS$3+3,'Mortality Tables'!$N$1:$DN$1,0),FALSE),VLOOKUP($T30,Fe_Annuity_Tables,MATCH(BX$3+3,'Mortality Tables'!$N$1:$DN$1,0),FALSE)),"") -> 206488.54 | BY30: =IFERROR((BX30+AH30*Contr_Rate)*(1+Inv_Return)*IF($D30=$C$1,VLOOKUP($T30,Male_Annuity_Tables,MATCH($BS$3+3,'Mortality Tables'!$N$1:$DN$1,0),FALSE),VLOOKUP($T30,Fe_Annuity_Tables,MATCH(BY$3+3,'Mortality Tables'!$N$1:$DN$1,0),FALSE)),"") -> 152580.95 | BZ30: =IFERROR((BY30+AI30*Contr_Rate)*(1+Inv_Return)*IF($D30=$C$1,VLOOKUP($T30,Male_Annuity_Tables,MATCH($BS$3+3,'Mortality Tables'!$N$1:$DN$1,0),FALSE),VLOOKUP($T30,Fe_Annuity_Tables,MATCH(BZ$3+3,'Mortality Tables'!$N$1:$DN$1,0),FALSE)),"") -> 117081.39 | CA30: =IFERROR((BZ30+AJ30*Contr_Rate)*(1+Inv_Return)*IF($D30=$C$1,VLOOKUP($T30,Male_Annuity_Tables,MATCH($BS$3+3,'Mortality Tables'!$N$1:$DN$1,0),FALSE),VLOOKUP($T30,Fe_Annuity_Tables,MATCH(CA$3+3,'Mortality Tables'!$N$1:$DN$1,0),FALSE)),"") -> 98139.539 | CB30: =IFERROR((CA30+AK30*Contr_Rate)*(1+Inv_Return)*IF($D30=$C$1,VLOOKUP($T30,Male_Annuity_Tables,MATCH($BS$3+3,'Mortality Tables'!$N$1:$DN$1,0),FALSE),VLOOKUP($T30,Fe_Annuity_Tables,MATCH(CB$3+3,'Mortality Tables'!$N$1:$DN$1,0),FALSE)),"") -> 84439.104 | ... DH30: =IFERROR((DG30+BQ30*Contr_Rate)*(1+Inv_Return)*IF($D30=$C$1,VLOOKUP($T30,Male_Annuity_Tables,MATCH($BS$3+3,'Mortality Tables'!$N$1:$DN$1,0),FALSE),VLOOKUP($T30,Fe_Annuity_Tables,MATCH(DH$3+3,'Mortality Tables'!$N$1:$DN$1,0),FALSE)),"") | DJ30: =MAX(BS30:DH30) -> 585873.57 | DK30: =IF($D30="FEMALE",Fe_Annuity_Factor,Male_Annuity_Factor) -> 8.8017766 | DL30: =(DJ30*Annuity_Ratio)/DK30 -> 44597.28 | DM30: =MAX($AB30:$BQ30) -> 4819060.5 | DN30: =IFERROR((DL30/DM30),"") -> 0.0092543515 | DP30: =IFERROR(IF($D30=$C$1,VLOOKUP($T30+DP$3-1,Male_Annuity_Tables,2,FALSE),VLOOKUP($T30,Fe_Annuity_Tables,2,FALSE))*BS30,"") -> 99778.818 | DQ30: =IFERROR(IF($D30=$C$1,VLOOKUP($T30+DQ$3-1,Male_Annuity_Tables,2,FALSE),VLOOKUP($T30,Fe_Annuity_Tables,2,FALSE))*BT30,"") -> 117821.52 | DR30: =IFERROR(IF($D30=$C$1,VLOOKUP($T30+DR$3-1,Male_Annuity_Tables,2,FALSE),VLOOKUP($T30,Fe_Annuity_Tables,2,FALSE))*BU30,"") -> 105703.34
A31: M0028 | B31: Shane Henderson | C31: Deferred | D31: Female | E31: 27089 | F31: 41676 | G31: 42925 | H31: 2007333 | I31: 119477.46 | J31: 110095.27 | K31: 24061.04 | L31: 253633.77 | M31: =IF(COUNTIF($A$4:A204,A31)=1,0,1) -> 0 | N31: =IF(T31<=18,"WHAT!!!",IF(T31>100,"EERM","Okay")) -> Okay | O31: =IF(G31>E31,"TRUE","FALSE") -> TRUE | P31: =G31>=Comm_Date -> TRUE | Q31: =$G31>=$F31 -> TRUE | R31: =$F31>$E31 -> TRUE | S31: =YEARFRAC(E31,F31,3) -> 39.964384 | T31: =ROUNDDOWN(YEARFRAC($E31,Analysis_Date,3),0) -> 50 | U31: =ROUNDDOWN(YEARFRAC($E31,$G31,3),0) -> 43 | V31: =YEARFRAC($G31,Analysis_Date,3) -> 7.4821918 | W31: =MAX(ROUNDDOWN(NRA-T31,0),0) -> 10 | X31: =L31*W31 -> 2536337.7 | Y31: =IF($D31=$C$1,VLOOKUP($T31,Mortality_Table,3,FALSE),VLOOKUP($T31,Mortality_Table,2,FALSE)) -> 0.00376 | Z31: =IF($D31=$C$1,VLOOKUP($T31,Male_Annuity_Tables,MATCH($W31+2,'Mortality Tables'!$DS$1:$HT$1,0),FALSE),VLOOKUP($T31,Fe_Annuity_Tables,MATCH($W31+2,'Mortality Tables'!$M$1:$DN$1,0),FALSE)) -> 0.43239791 | AB31: =IFERROR(IF($W31>=AB$3,($H31*(1+Ann_Salary_Growth_Rate)^AB$3),""),0) -> 2109606.6 | AC31: =IFERROR(IF($W31>=AC$3,($H31*(1+Ann_Salary_Growth_Rate)^AC$3),""),0) -> 2217091.1 | AD31: =IFERROR(IF($W31>=AD$3,($H31*(1+Ann_Salary_Growth_Rate)^AD$3),""),0) -> 2330051.9 | AE31: =IFERROR(IF($W31>=AE$3,($H31*(1+Ann_Salary_Growth_Rate)^AE$3),""),0) -> 2448768 | AF31: =IFERROR(IF($W31>=AF$3,($H31*(1+Ann_Salary_Growth_Rate)^AF$3),""),0) -> 2573532.7 | AG31: =IFERROR(IF($W31>=AG$3,($H31*(1+Ann_Salary_Growth_Rate)^AG$3),""),0) -> 2704654.2 | AH31: =IFERROR(IF($W31>=AH$3,($H31*(1+Ann_Salary_Growth_Rate)^AH$3),""),0) -> 2842456.4 | AI31: =IFERROR(IF($W31>=AI$3,($H31*(1+Ann_Salary_Growth_Rate)^AI$3),""),0) -> 2987279.5 | ... BQ31: =IFERROR(IF($W31>=BQ$3,($H31*(1+Ann_Salary_Growth_Rate)^BQ$3),""),0) | BS31: =IFERROR(($L31+AB31*Contr_Rate)*(1+Inv_Return)*IF($D31=$C$1,VLOOKUP($T31,Male_Annuity_Tables,MATCH($BS$3+3,'Mortality Tables'!$N$1:$DN$1,0),FALSE),VLOOKUP($T31,Fe_Annuity_Tables,MATCH(BS$3+3,'Mortality Tables'!$N$1:$DN$1,0),FALSE)),"") -> 816837.69 | BT31: =IFERROR(($BS31+AC31*Contr_Rate)*(1+Inv_Return)*IF($D31=$C$1,VLOOKUP($T31,Male_Annuity_Tables,MATCH($BS$3+3,'Mortality Tables'!$N$1:$DN$1,0),FALSE),VLOOKUP($T31,Fe_Annuity_Tables,MATCH(BT$3+3,'Mortality Tables'!$N$1:$DN$1,0),FALSE)),"") -> 1223960.2 | BU31: =IFERROR((BT31+AD31*Contr_Rate)*(1+Inv_Return)*IF($D31=$C$1,VLOOKUP($T31,Male_Annuity_Tables,MATCH($BS$3+3,'Mortality Tables'!$N$1:$DN$1,0),FALSE),VLOOKUP($T31,Fe_Annuity_Tables,MATCH(BU$3+3,'Mortality Tables'!$N$1:$DN$1,0),FALSE)),"") -> 1423127 | BV31: =IFERROR((BU31+AE31*Contr_Rate)*(1+Inv_Return)*IF($D31=$C$1,VLOOKUP($T31,Male_Annuity_Tables,MATCH($BS$3+3,'Mortality Tables'!$N$1:$DN$1,0),FALSE),VLOOKUP($T31,Fe_Annuity_Tables,MATCH(BV$3+3,'Mortality Tables'!$N$1:$DN$1,0),FALSE)),"") -> 1430409 | BW31: =IFERROR((BV31+AF31*Contr_Rate)*(1+Inv_Return)*IF($D31=$C$1,VLOOKUP($T31,Male_Annuity_Tables,MATCH($BS$3+3,'Mortality Tables'!$N$1:$DN$1,0),FALSE),VLOOKUP($T31,Fe_Annuity_Tables,MATCH(BW$3+3,'Mortality Tables'!$N$1:$DN$1,0),FALSE)),"") -> 1307342.4 | BX31: =IFERROR((BW31+AG31*Contr_Rate)*(1+Inv_Return)*IF($D31=$C$1,VLOOKUP($T31,Male_Annuity_Tables,MATCH($BS$3+3,'Mortality Tables'!$N$1:$DN$1,0),FALSE),VLOOKUP($T31,Fe_Annuity_Tables,MATCH(BX$3+3,'Mortality Tables'!$N$1:$DN$1,0),FALSE)),"") -> 1188152.7 | BY31: =IFERROR((BX31+AH31*Contr_Rate)*(1+Inv_Return)*IF($D31=$C$1,VLOOKUP($T31,Male_Annuity_Tables,MATCH($BS$3+3,'Mortality Tables'!$N$1:$DN$1,0),FALSE),VLOOKUP($T31,Fe_Annuity_Tables,MATCH(BY$3+3,'Mortality Tables'!$N$1:$DN$1,0),FALSE)),"") -> 1080747.8 | BZ31: =IFERROR((BY31+AI31*Contr_Rate)*(1+Inv_Return)*IF($D31=$C$1,VLOOKUP($T31,Male_Annuity_Tables,MATCH($BS$3+3,'Mortality Tables'!$N$1:$DN$1,0),FALSE),VLOOKUP($T31,Fe_Annuity_Tables,MATCH(BZ$3+3,'Mortality Tables'!$N$1:$DN$1,0),FALSE)),"") -> 988040.77 | CA31: =IFERROR((BZ31+AJ31*Contr_Rate)*(1+Inv_Return)*IF($D31=$C$1,VLOOKUP($T31,Male_Annuity_Tables,MATCH($BS$3+3,'Mortality Tables'!$N$1:$DN$1,0),FALSE),VLOOKUP($T31,Fe_Annuity_Tables,MATCH(CA$3+3,'Mortality Tables'!$N$1:$DN$1,0),FALSE)),"") -> 909768.05 | CB31: =IFERROR((CA31+AK31*Contr_Rate)*(1+Inv_Return)*IF($D31=$C$1,VLOOKUP($T31,Male_Annuity_Tables,MATCH($BS$3+3,'Mortality Tables'!$N$1:$DN$1,0),FALSE),VLOOKUP($T31,Fe_Annuity_Tables,MATCH(CB$3+3,'Mortality Tables'!$N$1:$DN$1,0),FALSE)),"") -> 844089.4 | ... DH31: =IFERROR((DG31+BQ31*Contr_Rate)*(1+Inv_Return)*IF($D31=$C$1,VLOOKUP($T31,Male_Annuity_Tables,MATCH($BS$3+3,'Mortality Tables'!$N$1:$DN$1,0),FALSE),VLOOKUP($T31,Fe_Annuity_Tables,MATCH(DH$3+3,'Mortality Tables'!$N$1:$DN$1,0),FALSE)),"") | DJ31: =MAX(BS31:DH31) -> 1430409 | DK31: =IF($D31="FEMALE",Fe_Annuity_Factor,Male_Annuity_Factor) -> 8.8017766 | DL31: =(DJ31*Annuity_Ratio)/DK31 -> 108884.16 | DM31: =MAX($AB31:$BQ31) -> 3299438 | DN31: =IFERROR((DL31/DM31),"") -> 0.03300082 | DP31: =IFERROR(IF($D31=$C$1,VLOOKUP($T31+DP$3-1,Male_Annuity_Tables,2,FALSE),VLOOKUP($T31,Fe_Annuity_Tables,2,FALSE))*BS31,"") -> 84447.948 | DQ31: =IFERROR(IF($D31=$C$1,VLOOKUP($T31+DQ$3-1,Male_Annuity_Tables,2,FALSE),VLOOKUP($T31,Fe_Annuity_Tables,2,FALSE))*BT31,"") -> 126537.91 | DR31: =IFERROR(IF($D31=$C$1,VLOOKUP($T31+DR$3-1,Male_Annuity_Tables,2,FALSE),VLOOKUP($T31,Fe_Annuity_Tables,2,FALSE))*BU31,"") -> 147128.56
A32: M0029 | B32: Jennifer Powers | C32: Exited | D32: Male | E32: 31106 | F32: 40418 | G32: 43634 | H32: 712794 | I32: 37799.92 | J32: 61593.01 | K32: 9917.11 | L32: 109310.04 | M32: =IF(COUNTIF($A$4:A204,A32)=1,0,1) -> 0 | N32: =IF(T32<=18,"WHAT!!!",IF(T32>100,"EERM","Okay")) -> Okay | O32: =IF(G32>E32,"TRUE","FALSE") -> TRUE | P32: =G32>=Comm_Date -> TRUE | Q32: =$G32>=$F32 -> TRUE | R32: =$F32>$E32 -> TRUE | S32: =YEARFRAC(E32,F32,3) -> 25.512329 | T32: =ROUNDDOWN(YEARFRAC($E32,Analysis_Date,3),0) -> 39 | U32: =ROUNDDOWN(YEARFRAC($E32,$G32,3),0) -> 34 | V32: =YEARFRAC($G32,Analysis_Date,3) -> 5.539726 | W32: =MAX(ROUNDDOWN(NRA-T32,0),0) -> 21 | X32: =L32*W32 -> 2295510.8 | Y32: =IF($D32=$C$1,VLOOKUP($T32,Mortality_Table,3,FALSE),VLOOKUP($T32,Mortality_Table,2,FALSE)) -> 0.00214 | Z32: =IF($D32=$C$1,VLOOKUP($T32,Male_Annuity_Tables,MATCH($W32+2,'Mortality Tables'!$DS$1:$HT$1,0),FALSE),VLOOKUP($T32,Fe_Annuity_Tables,MATCH($W32+2,'Mortality Tables'!$M$1:$DN$1,0),FALSE)) -> 0.063604625 | AB32: =IFERROR(IF($W32>=AB$3,($H32*(1+Ann_Salary_Growth_Rate)^AB$3),""),0) -> 749110.85 | AC32: =IFERROR(IF($W32>=AC$3,($H32*(1+Ann_Salary_Growth_Rate)^AC$3),""),0) -> 787278.05 | AD32: =IFERROR(IF($W32>=AD$3,($H32*(1+Ann_Salary_Growth_Rate)^AD$3),""),0) -> 827389.87 | AE32: =IFERROR(IF($W32>=AE$3,($H32*(1+Ann_Salary_Growth_Rate)^AE$3),""),0) -> 869545.38 | AF32: =IFERROR(IF($W32>=AF$3,($H32*(1+Ann_Salary_Growth_Rate)^AF$3),""),0) -> 913848.72 | AG32: =IFERROR(IF($W32>=AG$3,($H32*(1+Ann_Salary_Growth_Rate)^AG$3),""),0) -> 960409.31 | AH32: =IFERROR(IF($W32>=AH$3,($H32*(1+Ann_Salary_Growth_Rate)^AH$3),""),0) -> 1009342.2 | AI32: =IFERROR(IF($W32>=AI$3,($H32*(1+Ann_Salary_Growth_Rate)^AI$3),""),0) -> 1060768.2 | ... BQ32: =IFERROR(IF($W32>=BQ$3,($H32*(1+Ann_Salary_Growth_Rate)^BQ$3),""),0) | BS32: =IFERROR(($L32+AB32*Contr_Rate)*(1+Inv_Return)*IF($D32=$C$1,VLOOKUP($T32,Male_Annuity_Tables,MATCH($BS$3+3,'Mortality Tables'!$N$1:$DN$1,0),FALSE),VLOOKUP($T32,Fe_Annuity_Tables,MATCH(BS$3+3,'Mortality Tables'!$N$1:$DN$1,0),FALSE)),"") -> 274034.47 | BT32: =IFERROR(($BS32+AC32*Contr_Rate)*(1+Inv_Return)*IF($D32=$C$1,VLOOKUP($T32,Male_Annuity_Tables,MATCH($BS$3+3,'Mortality Tables'!$N$1:$DN$1,0),FALSE),VLOOKUP($T32,Fe_Annuity_Tables,MATCH(BT$3+3,'Mortality Tables'!$N$1:$DN$1,0),FALSE)),"") -> 418560.37 | BU32: =IFERROR((BT32+AD32*Contr_Rate)*(1+Inv_Return)*IF($D32=$C$1,VLOOKUP($T32,Male_Annuity_Tables,MATCH($BS$3+3,'Mortality Tables'!$N$1:$DN$1,0),FALSE),VLOOKUP($T32,Fe_Annuity_Tables,MATCH(BU$3+3,'Mortality Tables'!$N$1:$DN$1,0),FALSE)),"") -> 546994.87 | BV32: =IFERROR((BU32+AE32*Contr_Rate)*(1+Inv_Return)*IF($D32=$C$1,VLOOKUP($T32,Male_Annuity_Tables,MATCH($BS$3+3,'Mortality Tables'!$N$1:$DN$1,0),FALSE),VLOOKUP($T32,Fe_Annuity_Tables,MATCH(BV$3+3,'Mortality Tables'!$N$1:$DN$1,0),FALSE)),"") -> 662731.66 | BW32: =IFERROR((BV32+AF32*Contr_Rate)*(1+Inv_Return)*IF($D32=$C$1,VLOOKUP($T32,Male_Annuity_Tables,MATCH($BS$3+3,'Mortality Tables'!$N$1:$DN$1,0),FALSE),VLOOKUP($T32,Fe_Annuity_Tables,MATCH(BW$3+3,'Mortality Tables'!$N$1:$DN$1,0),FALSE)),"") -> 768580.4 | BX32: =IFERROR((BW32+AG32*Contr_Rate)*(1+Inv_Return)*IF($D32=$C$1,VLOOKUP($T32,Male_Annuity_Tables,MATCH($BS$3+3,'Mortality Tables'!$N$1:$DN$1,0),FALSE),VLOOKUP($T32,Fe_Annuity_Tables,MATCH(BX$3+3,'Mortality Tables'!$N$1:$DN$1,0),FALSE)),"") -> 866872.95 | BY32: =IFERROR((BX32+AH32*Contr_Rate)*(1+Inv_Return)*IF($D32=$C$1,VLOOKUP($T32,Male_Annuity_Tables,MATCH($BS$3+3,'Mortality Tables'!$N$1:$DN$1,0),FALSE),VLOOKUP($T32,Fe_Annuity_Tables,MATCH(BY$3+3,'Mortality Tables'!$N$1:$DN$1,0),FALSE)),"") -> 959550.55 | BZ32: =IFERROR((BY32+AI32*Contr_Rate)*(1+Inv_Return)*IF($D32=$C$1,VLOOKUP($T32,Male_Annuity_Tables,MATCH($BS$3+3,'Mortality Tables'!$N$1:$DN$1,0),FALSE),VLOOKUP($T32,Fe_Annuity_Tables,MATCH(BZ$3+3,'Mortality Tables'!$N$1:$DN$1,0),FALSE)),"") -> 1048235.5 | CA32: =IFERROR((BZ32+AJ32*Contr_Rate)*(1+Inv_Return)*IF($D32=$C$1,VLOOKUP($T32,Male_Annuity_Tables,MATCH($BS$3+3,'Mortality Tables'!$N$1:$DN$1,0),FALSE),VLOOKUP($T32,Fe_Annuity_Tables,MATCH(CA$3+3,'Mortality Tables'!$N$1:$DN$1,0),FALSE)),"") -> 1134289.8 | CB32: =IFERROR((CA32+AK32*Contr_Rate)*(1+Inv_Return)*IF($D32=$C$1,VLOOKUP($T32,Male_Annuity_Tables,MATCH($BS$3+3,'Mortality Tables'!$N$1:$DN$1,0),FALSE),VLOOKUP($T32,Fe_Annuity_Tables,MATCH(CB$3+3,'Mortality Tables'!$N$1:$DN$1,0),FALSE)),"") -> 1218863.8 | ... DH32: =IFERROR((DG32+BQ32*Contr_Rate)*(1+Inv_Return)*IF($D32=$C$1,VLOOKUP($T32,Male_Annuity_Tables,MATCH($BS$3+3,'Mortality Tables'!$N$1:$DN$1,0),FALSE),VLOOKUP($T32,Fe_Annuity_Tables,MATCH(DH$3+3,'Mortality Tables'!$N$1:$DN$1,0),FALSE)),"") | DJ32: =MAX(BS32:DH32) -> 2259310.9 | DK32: =IF($D32="FEMALE",Fe_Annuity_Factor,Male_Annuity_Factor) -> 8.0909278 | DL32: =(DJ32*Annuity_Ratio)/DK32 -> 187090.82 | DM32: =MAX($AB32:$BQ32) -> 2023891.3 | DN32: =IFERROR((DL32/DM32),"") -> 0.092441139 | DP32: =IFERROR(IF($D32=$C$1,VLOOKUP($T32+DP$3-1,Male_Annuity_Tables,2,FALSE),VLOOKUP($T32,Fe_Annuity_Tables,2,FALSE))*BS32,"") -> 55276.04 | DQ32: =IFERROR(IF($D32=$C$1,VLOOKUP($T32+DQ$3-1,Male_Annuity_Tables,2,FALSE),VLOOKUP($T32,Fe_Annuity_Tables,2,FALSE))*BT32,"") -> 63602.341 | DR32: =IFERROR(IF($D32=$C$1,VLOOKUP($T32+DR$3-1,Male_Annuity_Tables,2,FALSE),VLOOKUP($T32,Fe_Annuity_Tables,2,FALSE))*BU32,"") -> 83206.945
