Workbook

Sheet Intro
E15: CLIENT NAME
E16: Group Life Insurance Business
E17: LRC Analysis
G20: Start Date | H20: 44197
G21: Valuation Date | H21: 45657

Sheet GWP
A1: Paste GWP Summaries
C3: Summary of Gross Written Premium
C4: Class of Business | D4: 2021 | E4: 2022 | F4: 2023 | G4: 2024
C5: Group Life
C6: Group Credit
C7: Group Last Expense
C8: Total | D8: =SUM(D5:D7) -> 0 | E8: =SUM(E5:E7) -> 0 | F8: =SUM(F5:F7) -> 0 | G8: =SUM(G5:G7) -> 0

Sheet Premium Receivables
A1: Paste Premium Receivables Summaries
C3: Summary of Premium Receivables
C4: Class of Business | D4: 2021 | E4: 2022 | F4: 2023 | G4: 2024
C5: Group Life
C6: Group Credit
C7: Group Last Expense
C8: Total | D8: =SUM(D5:D7) -> 0 | E8: =SUM(E5:E7) -> 0 | F8: =SUM(F5:F7) -> 0 | G8: =SUM(G5:G7) -> 0

Sheet DAC
A1: Paste DAC Summaries
C3: Summary of Deferred Acquisition Costs
C4: Class of Business | D4: 2021 | E4: 2022 | F4: 2023 | G4: 2024
C5: Group Life
C6: Group Credit
C7: Group Last Expense
C8: Total | D8: =SUM(D5:D7) -> 0 | E8: =SUM(E5:E7) -> 0 | F8: =SUM(F5:F7) -> 0 | G8: =SUM(G5:G7) -> 0

Sheet UPR
A1: Paste UPR Data
C3: Summary of Unearned Premium Reserve
C4: Class of Business | D4: 2021 | E4: 2022 | F4: 2023 | G4: 2024
C5: Group Life
C6: Group Credit
C7: Group Last Expense
C8: Total | D8: =SUM(D5:D7) -> 0 | E8: =SUM(E5:E7) -> 0 | F8: =SUM(F5:F7) -> 0 | G8: =SUM(G5:G7) -> 0

Sheet LRC
A2: COMPUTE LRC AS AT :
A3: 1. 31 December 2021
A4: 2. 31 December 2022
A5: 3. 31 December 2023
A6: 4. 31 December 2024
B12: Client Name Summary of LRC as at 31 December 2021
B13: Class | C13: UPR | D13: DAC | E13: Premium Receivables as at 31 Dec 2021 | F13: Closing LRC
B14: Group Life | F14: =C14-D14-E14 -> 0
B15: Group Credit | F15: =C15-D15-E15 -> 0
B16: Group Last Expense | F16: =C16-D16-E16 -> 0
B17: Grand Total | C17: =SUM(C14:C15) -> 0 | D17: =SUM(D14:D15) -> 0 | E17: =SUM(E14:E15) -> 0 | F17: =SUM(F14:F15) -> 0
B21: Client Name Summary of LRC as at 31 December 2022
B22: Class | C22: Opening LRC | D22: GWP 2022 | E22: Premium Receivables as at 31 Dec 2021 | F22: Premium Receivables as at 31 Dec 2022 | G22: Premium Received for the year | H22: Earned Premium for the year | I22: Change in DAC | J22: Closing LRC
B23: Group Life | C23: =F14 -> 0 | D23: =GWP!E5 -> 0 | E23: =E14 -> 0 | F23: ='Premium Receivables'!E5 -> 0 | G23: =D23+E23-F23 -> 0 | H23: =GWP!E5-(UPR!E5-UPR!D5) -> 0 | I23: =DAC!E5-DAC!D5 -> 0 | J23: =C23+G23-H23-I23 -> 0
B24: Group Credit | C24: =F15 -> 0 | D24: =GWP!E6 -> 0 | E24: =E15 -> 0 | F24: ='Premium Receivables'!E6 -> 0 | G24: =D24+E24-F24 -> 0 | H24: =GWP!E6-(UPR!E6-UPR!D6) -> 0 | I24: =DAC!E6-DAC!D6 -> 0 | J24: =C24+G24-H24-I24 -> 0
B25: Group Last Expense | C25: =F16 -> 0 | D25: =GWP!E7 -> 0 | E25: =E16 -> 0 | F25: ='Premium Receivables'!E7 -> 0 | G25: =D25+E25-F25 -> 0 | H25: =GWP!E7-(UPR!E7-UPR!D7) -> 0 | I25: =DAC!E7-DAC!D7 -> 0 | J25: =C25+G25-H25-I25 -> 0
B26: Grand Total | C26: =SUM(C23:C24) -> 0 | D26: =SUM(D23:D25) -> 0 | E26: =SUM(E23:E25) -> 0 | F26: =SUM(F23:F25) -> 0 | G26: =SUM(G23:G24) -> 0 | H26: =SUM(H23:H24) -> 0 | I26: =SUM(I23:I24) -> 0 | J26: =SUM(J23:J24) -> 0
B29: Client Name Summary of LRC as at 31 December 2023
B30: Class | C30: Opening LRC | D30: GWP 2023 | E30: Premium Receivables as at 31 Dec 2022 | F30: Premium Receivables as at 31 Dec 2023 | G30: Premium Received for the year | H30: Earned Premium for the year | I30: Change in DAC | J30: Closing LRC
B31: Group Life | C31: =J23 -> 0 | D31: =GWP!F5 -> 0 | E31: =F23 -> 0 | F31: ='Premium Receivables'!F5 -> 0 | G31: =D31+E31-F31 -> 0 | H31: =GWP!F5-(UPR!F5-UPR!E5) -> 0 | I31: =DAC!F5-DAC!E5 -> 0 | J31: =C31+G31-H31-I31 -> 0
B32: Group Credit | C32: =J24 -> 0 | D32: =GWP!F6 -> 0 | E32: =F24 -> 0 | F32: ='Premium Receivables'!F6 -> 0 | G32: =D32+E32-F32 -> 0 | H32: =GWP!F6-(UPR!F6-UPR!E6) -> 0 | I32: =DAC!F6-DAC!E6 -> 0 | J32: =C32+G32-H32-I32 -> 0
B33: Group Last Expense | C33: =J25 -> 0 | D33: =GWP!F7 -> 0 | E33: =F25 -> 0 | F33: ='Premium Receivables'!F7 -> 0 | G33: =D33+E33-F33 -> 0 | H33: =GWP!F7-(UPR!F7-UPR!E7) -> 0 | I33: =DAC!F7-DAC!E7 -> 0 | J33: =C33+G33-H33-I33 -> 0
B34: Grand Total | C34: =SUM(C31:C32) -> 0 | D34: =SUM(D31:D33) -> 0 | E34: =SUM(E31:E33) -> 0 | F34: =SUM(F31:F33) -> 0 | G34: =SUM(G31:G32) -> 0 | H34: =SUM(H31:H32) -> 0 | I34: =SUM(I31:I32) -> 0 | J34: =SUM(J31:J32) -> 0
B37: Client Name Summary of LRC as at 31 December 2024
B38: Class | C38: Opening LRC | D38: GWP 2024 | E38: Premium Receivables as at 31 Dec 2023 | F38: Premium Receivables as at 31 Dec 2024 | G38: Premium Received for the year | H38: Earned Premium for the year | I38: Change in DAC | J38: Closing LRC
B39: Group Life | C39: =J31 -> 0 | D39: =GWP!G5 -> 0 | E39: =F31 -> 0 | F39: ='Premium Receivables'!G5 -> 0 | G39: =D39+E39-F39 -> 0 | H39: =GWP!G5-(UPR!G5-UPR!F5) -> 0 | I39: =DAC!G5-DAC!F5 -> 0 | J39: =C39+G39-H39-I39 -> 0
B40: Group Credit | C40: =J32 -> 0 | D40: =GWP!G6 -> 0 | E40: =F32 -> 0 | F40: ='Premium Receivables'!G6 -> 0 | G40: =D40+E40-F40 -> 0 | H40: =GWP!G6-(UPR!G6-UPR!F6) -> 0 | I40: =DAC!G6-DAC!F6 -> 0 | J40: =C40+G40-H40-I40 -> 0
B41: Group Last Expense | C41: =J33 -> 0 | D41: =GWP!G7 -> 0 | E41: =F33 -> 0 | F41: ='Premium Receivables'!G7 -> 0 | G41: =D41+E41-F41 -> 0 | H41: =GWP!G7-(UPR!G7-UPR!F7) -> 0 | I41: =DAC!G7-DAC!F7 -> 0 | J41: =C41+G41-H41-I41 -> 0
B42: Grand Total | C42: =SUM(C39:C40) -> 0 | D42: =SUM(D39:D41) -> 0 | E42: =SUM(E39:E41) -> 0 | F42: =SUM(F39:F41) -> 0 | G42: =SUM(G39:G40) -> 0 | H42: =SUM(H39:H40) -> 0 | I42: =SUM(I39:I40) -> 0 | J42: =SUM(J39:J40) -> 0
B47: Use Net figures/ retention rates to compute Net LRC
